Workbook

Sheet Company Cover
C2: ADANI ENERGY SOLUTIONS LTD.
C3: NSE/BSE Listed | Sector: Power | Industry: Power Transmission & Distribution | Part of Adani Group
B14: ABOUT THE COMPANY
B15: Adani Energy Solutions Ltd (AESL) is India's largest private power transmission company and part of the Adani Group. AESL operates across four segments: Power Transmission (~40%), Power Distribution (~50%), Smart Metering (~3%), and Trading/Others (~7%). The company serves 13 Mn+ consumers in Mumbai & Mundra SEZ and operates 36 transmission assets across 16 states with 27,949 ckm network. AESL's under-construction transmission pipeline stands at ~₹71,779 Cr with a smart metering pipeline of ₹29,519 Cr across 24.6 Mn meters. The company targets 30,000 ckm of transmission lines by 2030, backed by planned capex of ₹22,000 Cr (FY27) and ₹23,000 Cr (FY28).
B19: REGISTERED OFFICE
B21: Address: Shantigram, Near Vaishno Devi Circle, S.G. Highway, Khodiyar, Ahmedabad, Gujarat – 382421
B23: S.No. | C23: Name of Entity | D23: Type
B24: 1 | C24: Adani Energy Solutions Limited | D24: Holding Company
B25: 2 | C25: Adani Transmission Step-One Limited | D25: Wholly Owned Subsidiary
B26: 3 | C26: Adani Transmission Limited | D26: Wholly Owned Subsidiary
B27: 4 | C27: Adani Electricity Mumbai Limited | D27: Subsidiary
B28: 5 | C28: Adani Electricity Navi Mumbai Limited | D28: Subsidiary
B29: 6 | C29: Adani Electricity Services Limited | D29: Subsidiary
B30: 7 | C30: Adani Electricity Mulund Limited | D30: Subsidiary
B31: 8 | C31: Maharashtra Eastern Grid Power Transmission Company Limited | D31: Subsidiary
B32: 9 | C32: Kharghar Vikhroli Transmission Private Limited | D32: Subsidiary
B33: 10 | C33: Western Transmission (Maharashtra) Private Limited | D33: Subsidiary
B34: 11 | C34: Maru Transmission Service Company Limited | D34: Subsidiary
B35: 12 | C35: Fatehgarh Bhadla Transmission Limited | D35: Subsidiary
... B48: 25 | C48: Various Project SPVs acquired through TBCB bidding routes | D48: Subsidiaries

Sheet Promoters
B1: Shareholding Pattern
B2: Adani Energy Solutions Ltd
B3: Scrip Code : 539254 | C3: Quarter Ending : Mar-26
B4: Statement showing shareholding pattern of the Promoter and Promoter Group
B5: Category of shareholder | C5: Entity Type | D5: Nos. of shareholders | E5: No. of fully paid up equity shares held | F5: Total nos. shares held | G5: Shareholding as a % of total no. of shares (calculated as per SCRR, 1957)As a % of (A+B+C2) | H5: Number of Voting Rights held in each class of securities | J5: Total No. Of shares on fully diluted basis (including warrants, ESOP, Convertible Securities etc.) | K5: Shareholding , as a % assuming full conversion of convertible securities ( as a percentage of diluted share capital)As a % of (A+B+C2) | L5: Number of Shares pledged or otherwise encumbered | N5: Total Number of Shares encumbered | P5: Number of equity shares held in dematerialized form
H6: Class eg: X | I6: Total | L6: No.(a) | M6: As a % of total Shares held(b) | N6: No.(a) | O6: As a % of total Shares held(b)
B8: A9) Indian | D8: - | E8: - | F8: - | G8: 0 | H8: - | I8: 0 | J8: - | K8: 0 | L8: - | M8: 0 | N8: - | O8: 0 | P8: -
B9: Individuals/Hindu undivided Family | D9: 2 | E9: 2 | F9: 2 | G9: 0 | H9: 2 | I9: 0 | J9: 2 | K9: 0 | L9: - | M9: 0 | N9: - | O9: 0 | P9: 2
B10: Gautambhai Shantilal Adani | C10: Promoter | D10: 1 | E10: 1 | F10: 1 | G10: 0 | H10: 1 | I10: 0 | J10: 1 | K10: 0 | L10: - | M10: 0 | N10: - | O10: 0 | P10: 1
B11: Rajeshbhai Shantilal Adani | C11: Promoter | D11: 1 | E11: 1 | F11: 1 | G11: 0 | H11: 1 | I11: 0 | J11: 1 | K11: 0 | L11: - | M11: 0 | N11: - | O11: 0 | P11: 1
B12: Any Other (specify) | D12: 3 | E12: 717701985 | F12: 717701985 | G12: 59.74 | H12: 717701985 | I12: 59.74 | J12: 717701985 | K12: 59.74 | L12: 4700000 | M12: 0.65 | N12: 4700000 | O12: 0.65 | P12: 717701985
B13: Gautambhai Shantilal Adani and Rajeshbhai Shantilal Adani (on behalf of S.B. Adani Family Trust) | C13: Promoter Group | D13: 1 | E13: 601634660 | F13: 601634660 | G13: 50.08 | H13: 601634660 | I13: 50.08 | J13: 601634660 | K13: 50.08 | L13: - | M13: 0 | N13: - | O13: 0 | P13: 601634660
B14: Shri Gautam S. Adani/Smt.Priti G. Adani (on behalf of Gautam S. Adani Family Trust) | C14: Promoter Group | D14: - | E14: - | F14: - | G14: 0 | H14: - | I14: 0 | J14: - | K14: 0 | L14: - | M14: 0 | N14: - | O14: 0 | P14: -
B15: Adani Tradeline Private Limited | C15: Promoter Group | D15: 1 | E15: 97617325 | F15: 97617325 | G15: 8.13 | H15: 97617325 | I15: 8.13 | J15: 97617325 | K15: 8.13 | L15: 4700000 | M15: 4.81 | N15: 4700000 | O15: 4.81 | P15: 97617325
B16: Adani Infra (India) Limited | C16: Promoter Group | D16: 1 | E16: 18450000 | F16: 18450000 | G16: 1.54 | H16: 18450000 | I16: 1.54 | J16: 18450000 | K16: 1.54 | L16: - | M16: 0 | N16: - | O16: 0 | P16: 18450000
B17: Adani Properties Private Limited | C17: Promoter Group | D17: - | E17: - | F17: - | G17: 0 | H17: - | I17: 0 | J17: - | K17: 0 | L17: - | M17: 0 | N17: - | O17: 0 | P17: -
B18: Sub Total A1 | D18: 5 | E18: 717701987 | F18: 717701987 | G18: 59.74 | H18: 717701987 | I18: 59.74 | J18: 717701987 | K18: 59.74 | L18: 4700000 | M18: 0.65 | N18: 4700000 | O18: 0.65 | P18: 717701987
B19: A10) Foreign | D19: - | E19: - | F19: - | G19: 0 | H19: - | I19: 0 | J19: - | K19: 0 | L19: - | M19: 0 | N19: - | O19: 0 | P19: -
B20: Any Other (specify) | D20: 5 | E20: 155981400 | F20: 155981400 | G20: 12.98 | H20: 155981400 | I20: 12.98 | J20: 155981400 | K20: 12.98 | L20: - | M20: 0 | N20: - | O20: 0 | P20: 155981400
B21: Afro Asia Trade And Investments Limited | C21: Promoter Group | D21: 1 | E21: 30249700 | F21: 30249700 | G21: 2.52 | H21: 30249700 | I21: 2.52 | J21: 30249700 | K21: 2.52 | L21: - | M21: 0 | N21: - | O21: 0 | P21: 30249700
B22: Worldwide Emerging Market Holding Limited | C22: Promoter Group | D22: 1 | E22: 30249700 | F22: 30249700 | G22: 2.52 | H22: 30249700 | I22: 2.52 | J22: 30249700 | K22: 2.52 | L22: - | M22: 0 | N22: - | O22: 0 | P22: 30249700
B23: Flourishing Trade And Investment Limited | C23: Promoter Group | D23: 1 | E23: 3688000 | F23: 3688000 | G23: 0.31 | H23: 3688000 | I23: 0.31 | J23: 3688000 | K23: 0.31 | L23: - | M23: 0 | N23: - | O23: 0 | P23: 3688000
B24: Gelt Bery Trade and Investment Limited | C24: Promoter Group | D24: 1 | E24: 64760500 | F24: 64760500 | G24: 5.39 | H24: 64760500 | I24: 5.39 | J24: 64760500 | K24: 5.39 | L24: - | M24: 0 | N24: - | O24: 0 | P24: 64760500
B25: Fortitude Trade and Investment Limited | C25: Promoter Group | D25: - | E25: - | F25: - | G25: 0 | H25: - | I25: 0 | J25: - | K25: 0 | L25: - | M25: 0 | N25: - | O25: 0 | P25: -
B26: Emerging Market Investment DMCC | C26: Promoter Group | D26: 1 | E26: 27033500 | F26: 27033500 | G26: 2.25 | H26: 27033500 | I26: 2.25 | J26: 27033500 | K26: 2.25 | L26: - | M26: 0 | N26: - | O26: 0 | P26: 27033500
B27: Sub Total A2 | D27: 5 | E27: 155981400 | F27: 155981400 | G27: 12.98 | H27: 155981400 | I27: 12.98 | J27: 155981400 | K27: 12.98 | L27: - | M27: 0 | N27: - | O27: 0 | P27: 155981400
B28: A=A1+A2 | D28: 10 | E28: 873683387 | F28: 873683387 | G28: 72.73 | H28: 873683387 | I28: 72.73 | J28: 873683387 | K28: 72.73 | L28: 4700000 | M28: 0.54 | N28: 4700000 | O28: 0.54 | P28: 873683387

Sheet Public
B1: Shareholding Pattern Public Shareholder
B2: Adani Energy Solutions Ltd
B3: Scrip Code : 539254 | E3: Quarter Ending : Mar-26
B5: Statement showing shareholding pattern of the Public shareholder
B7: Category & Name of the Shareholders | C7: No. of shareholder | D7: No. of fully paid up equity shares held | E7: Total no. shares held | F7: Shareholding % calculated as per SCRR, 1957 As a % of (A+B+C2) | G7: No. of Voting Rights | H7: Total as a % of Total Voting right | I7: Total No. Of shares on fully diluted basis (including warrants, ESOP, Convertible Securities etc.) | J7: Shareholding , as a % assuming full conversion of convertible securities ( as a percentage of diluted share capital)As a % of (A+B+C2) | K7: No. of equity shares held in dematerialized form(Not Applicable) | L7: Sub-categorization of shares (XV)
L8: Shareholding (No. of shares) under
L9: SubCategory_I | M9: SubCategory_II | N9: SubCategory_III
B10: Institutions | C10: 0 | D10: 0 | E10: - | F10: 0 | G10: - | H10: 0 | I10: - | J10: 0 | K10: - | L10: - | M10: - | N10: -
B11: B2) Institutions (Domestic) | C11: 0 | D11: 0 | E11: - | F11: 0 | G11: - | H11: 0 | I11: - | J11: 0 | K11: - | L11: - | M11: - | N11: -
B12: Mutual Funds/ | C12: 33 | D12: 79195541 | E12: 79195541 | F12: 6.59 | G12: 79195541 | H12: 6.59 | I12: 79195541 | J12: 6.59 | K12: 79195541 | L12: - | M12: - | N12: -
B13: SBI Equity Hybrid Fund | C13: 1 | D13: 44073466 | E13: 44073466 | F13: 3.67 | G13: 44073466 | H13: 3.67 | I13: 44073466 | J13: 3.67 | K13: 44073466 | L13: - | M13: - | N13: -
B14: Venture Capital Funds | C14: 0 | D14: 0 | E14: - | F14: 0 | G14: - | H14: 0 | I14: - | J14: 0 | K14: - | L14: - | M14: - | N14: -
B15: Alternate Investment Funds | C15: 7 | D15: 897195 | E15: 897195 | F15: 0.07 | G15: 897195 | H15: 0.07 | I15: 897195 | J15: 0.07 | K15: 897195 | L15: - | M15: - | N15: -
B16: Banks | C16: 3 | D16: 387 | E16: 387 | F16: 0 | G16: 387 | H16: 0 | I16: 387 | J16: 0 | K16: 387 | L16: - | M16: - | N16: -
B17: Insurance Companies | C17: 6 | D17: 43049610 | E17: 43049610 | F17: 3.58 | G17: 43049610 | H17: 3.58 | I17: 43049610 | J17: 3.58 | K17: 43049610 | L17: - | M17: - | N17: -
B18: Life Insurance Corporation Of India | C18: 1 | D18: 41081207 | E18: 41081207 | F18: 3.42 | G18: 41081207 | H18: 3.42 | I18: 41081207 | J18: 3.42 | K18: 41081207 | L18: - | M18: - | N18: -
B19: Provident Funds/ Pension Funds | C19: 0 | D19: 0 | E19: - | F19: 0 | G19: - | H19: 0 | I19: - | J19: 0 | K19: - | L19: - | M19: - | N19: -
B20: Asset reconstruction companies | C20: 0 | D20: 0 | E20: - | F20: 0 | G20: - | H20: 0 | I20: - | J20: 0 | K20: - | L20: - | M20: - | N20: -
B21: Sovereign Wealth Funds | C21: 0 | D21: 0 | E21: - | F21: 0 | G21: - | H21: 0 | I21: - | J21: 0 | K21: - | L21: - | M21: - | N21: -
B22: NBFCs registered with RBI | C22: 4 | D22: 1709 | E22: 1709 | F22: 0 | G22: 1709 | H22: 0 | I22: 1709 | J22: 0 | K22: 1709 | L22: - | M22: - | N22: -
B23: Other Financial Institutions | C23: 0 | D23: 0 | E23: - | F23: 0 | G23: - | H23: 0 | I23: - | J23: 0 | K23: - | L23: - | M23: - | N23: -
B24: Any Other(Institutions (Domestic)) | C24: 0 | D24: 0 | E24: - | F24: 0 | G24: - | H24: 0 | I24: - | J24: 0 | K24: - | L24: - | M24: - | N24: -
B25: Sub Total B1 | C25: 53 | D25: 123144442 | E25: 123144442 | F25: 10.25 | G25: 123144442 | H25: 10.25 | I25: 123144442 | J25: 10.25 | K25: 123144442 | L25: - | M25: - | N25: -
B26: B17) Institutions (Foreign) | C26: 0 | D26: 0 | E26: - | F26: 0 | G26: - | H26: 0 | I26: - | J26: 0 | K26: - | L26: - | M26: - | N26: -
B27: Foreign Direct Investment | C27: 0 | D27: 0 | E27: - | F27: 0 | G27: - | H27: 0 | I27: - | J27: 0 | K27: - | L27: - | M27: - | N27: -
B28: Foreign Venture Capital Investors | C28: 0 | D28: 0 | E28: - | F28: 0 | G28: - | H28: 0 | I28: - | J28: 0 | K28: - | L28: - | M28: - | N28: -
B29: Sovereign Wealth Funds | C29: 0 | D29: 0 | E29: - | F29: 0 | G29: - | H29: 0 | I29: - | J29: 0 | K29: - | L29: - | M29: - | N29: -
B30: Foreign Portfolio Investors Category I | C30: 173 | D30: 130640837 | E30: 130640837 | F30: 10.88 | G30: 130640837 | H30: 10.88 | I30: 130640837 | J30: 10.88 | K30: 130640837 | L30: - | M30: - | N30: -
B31: Inq Holding Llc | C31: 1 | D31: 12868770 | E31: 12868770 | F31: 1.07 | G31: 12868770 | H31: 1.07 | I31: 12868770 | J31: 1.07 | K31: 12868770 | L31: - | M31: - | N31: -
B32: Gqg Partners Emerging Markets Equity Fund | C32: 1 | D32: 22886433 | E32: 22886433 | F32: 1.91 | G32: 22886433 | H32: 1.91 | I32: 22886433 | J32: 1.91 | K32: 22886433 | L32: - | M32: - | N32: -
B33: Goldman Sachs Trust Ii - Goldman Sachs Gqg Partners International Opportunities Fund | C33: 1 | D33: 35665659 | E33: 35665659 | F33: 2.97 | G33: 35665659 | H33: 2.97 | I33: 35665659 | J33: 2.97 | K33: 35665659 | L33: - | M33: - | N33: -
B34: Foreign Portfolio Investors Category II | C34: 18 | D34: 16249671 | E34: 16249671 | F34: 1.35 | G34: 16249671 | H34: 1.35 | I34: 16249671 | J34: 1.35 | K34: 16249671 | L34: - | M34: - | N34: -
B35: Overseas Depositories (holding DRs) (balancing figure) | C35: 0 | D35: 0 | E35: - | F35: 0 | G35: - | H35: 0 | I35: - | J35: 0 | K35: - | L35: - | M35: - | N35: -
B36: Any Other(Institutions (Foreign)) | C36: 0 | D36: 0 | E36: - | F36: 0 | G36: - | H36: 0 | I36: - | J36: 0 | K36: - | L36: - | M36: - | N36: -
B37: Sub Total B2 | C37: 191 | D37: 146890508 | E37: 146890508 | F37: 12.23 | G37: 146890508 | H37: 12.23 | I37: 146890508 | J37: 12.23 | K37: 146890508 | L37: - | M37: - | N37: -
B38: B29) Central Government/ State Government(s)/ President of India | C38: 0 | D38: 0 | E38: - | F38: 0 | G38: - | H38: 0 | I38: - | J38: 0 | K38: - | L38: - | M38: - | N38: -
B39: Central Government / President of India | C39: 0 | D39: 0 | E39: - | F39: 0 | G39: - | H39: 0 | I39: - | J39: 0 | K39: - | L39: - | M39: - | N39: -
B40: State Government / Governor | C40: 0 | D40: 0 | E40: - | F40: 0 | G40: - | H40: 0 | I40: - | J40: 0 | K40: - | L40: - | M40: - | N40: -
B41: Shareholding by Companies or Bodies Corporate where Central / State Government is a promoter | C41: 0 | D41: 0 | E41: - | F41: 0 | G41: - | H41: 0 | I41: - | J41: 0 | K41: - | L41: - | M41: - | N41: -
B42: Sub Total B3 | C42: 0 | D42: 0 | E42: - | F42: 0 | G42: - | H42: 0 | I42: - | J42: 0 | K42: - | L42: - | M42: - | N42: -
B43: B34) Non-Institutions | C43: 0 | D43: 0 | E43: - | F43: 0 | G43: - | H43: 0 | I43: - | J43: 0 | K43: - | L43: - | M43: - | N43: -
B44: Associate companies / Subsidiaries | C44: 0 | D44: 0 | E44: - | F44: 0 | G44: - | H44: 0 | I44: - | J44: 0 | K44: - | L44: - | M44: - | N44: -
B45: Directors and their relatives (excluding independent directors and nominee directors) | C45: 2 | D45: 106925 | E45: 106925 | F45: 0.01 | G45: 106925 | H45: 0.01 | I45: 106925 | J45: 0.01 | K45: 106925 | L45: - | M45: - | N45: -
B46: Key Managerial Personnel | C46: 2 | D46: 49 | E46: 49 | F46: 0 | G46: 49 | H46: 0 | I46: 49 | J46: 0 | K46: 49 | L46: - | M46: - | N46: -
B47: Relatives of promoters (other than 'immediate relatives' of promoters disclosed under 'Promoter and Promoter Group' category) | C47: 0 | D47: 0 | E47: - | F47: 0 | G47: - | H47: 0 | I47: - | J47: 0 | K47: - | L47: - | M47: - | N47: -
B48: Trusts where any person belonging to 'Promoter and Promoter Group' category is 'trustee', 'beneficiary', or 'author of the trust' | C48: 0 | D48: 0 | E48: - | F48: 0 | G48: - | H48: 0 | I48: - | J48: 0 | K48: - | L48: - | M48: - | N48: -
B49: Investor Education and Protection Fund (IEPF) | C49: 0 | D49: 0 | E49: - | F49: 0 | G49: - | H49: 0 | I49: - | J49: 0 | K49: - | L49: - | M49: - | N49: -
B50: Resident Individuals holding nominal share capital up to Rs. 2 lakhs | C50: 394692 | D50: 25377225 | E50: 25377225 | F50: 2.11 | G50: 25377225 | H50: 2.11 | I50: 25377225 | J50: 2.11 | K50: 25243814 | L50: - | M50: - | N50: -
B51: Resident Individuals holding nominal share capital in excess of Rs. 2 lakhs | C51: 95 | D51: 7270279 | E51: 7270279 | F51: 0.61 | G51: 7270279 | H51: 0.61 | I51: 7270279 | J51: 0.61 | K51: 7240279 | L51: - | M51: - | N51: -
B52: Non Resident Indians (NRIs) | C52: 4354 | D52: 1029489 | E52: 1029489 | F52: 0.09 | G52: 1029489 | H52: 0.09 | I52: 1029489 | J52: 0.09 | K52: 1029489 | L52: - | M52: - | N52: -
B53: Foreign Nationals | C53: 1 | D53: 10000 | E53: 10000 | F53: 0 | G53: 10000 | H53: 0 | I53: 10000 | J53: 0 | K53: 10000 | L53: - | M53: - | N53: -
B54: Foreign Companies | C54: 1 | D54: 15682600 | E54: 15682600 | F54: 1.31 | G54: 15682600 | H54: 1.31 | I54: 15682600 | J54: 1.31 | K54: 15682600 | L54: - | M54: - | N54: -
B55: Multi Ventures Limited | C55: 1 | D55: 15682600 | E55: 15682600 | F55: 1.31 | G55: 15682600 | H55: 1.31 | I55: 15682600 | J55: 1.31 | K55: 15682600 | L55: - | M55: - | N55: -
B56: Bodies Corporate | C56: 635 | D56: 5711688 | E56: 5711688 | F56: 0.48 | G56: 5711688 | H56: 0.48 | I56: 5711688 | J56: 0.48 | K56: 5711688 | L56: - | M56: - | N56: -
B57: Any Other (specify) | C57: 3589 | D57: 2376050 | E57: 2376050 | F57: 0.2 | G57: 2376050 | H57: 0.2 | I57: 2376050 | J57: 0.2 | K57: 2376050 | L57: - | M57: - | N57: -
B58: Any Other (specify) | C58: 3 | D58: 1336 | E58: 1336 | F58: 0 | G58: 1336 | H58: 0 | I58: 1336 | J58: 0 | K58: 1336 | L58: - | M58: - | N58: -
B59: Body Corporate - LLP | C59: 72 | D59: 408383 | E59: 408383 | F59: 0.03 | G59: 408383 | H59: 0.03 | I59: 408383 | J59: 0.03 | K59: 408383 | L59: - | M59: - | N59: -
B60: Any Other (specify) | C60: 3467 | D60: 1736635 | E60: 1736635 | F60: 0.14 | G60: 1736635 | H60: 0.14 | I60: 1736635 | J60: 0.14 | K60: 1736635 | L60: - | M60: - | N60: -
B61: Any Other (specify) | C61: 47 | D61: 229696 | E61: 229696 | F61: 0.02 | G61: 229696 | H61: 0.02 | I61: 229696 | J61: 0.02 | K61: 229696 | L61: - | M61: - | N61: -
... B63: B=B1+B2+B3+B4 | C63: 403615 | D63: 327599255 | E63: 327599255 | F63: 27.27 | G63: 327599255 | H63: 27.27 | I63: 327599255 | J63: 27.27 | K63: 327435844 | L63: - | M63: - | N63: -

Sheet Consolidated Balance Sheet
B1: Adani Energy Solutions
B2: Consolidated Balance Sheet
C3: 44621 | D3: 44986 | E3: 45352 | F3: 45717 | G3: Mar 26
C5: 12 mths | D5: 12 mths | E5: 12 mths | F5: 12 mths | G5: 12 mths
B7: EQUITIES AND LIABILITIES | I7: Changes %
B8: SHAREHOLDER'S FUNDS | I8: 44621 | J8: 44986 | K8: 45352 | L8: 45717 | M8: Mar 26
B9: Equity Share Capital | C9: 1099.81 | D9: 1115.49 | E9: 1115.49 | F9: 1201.28 | G9: 1201.28 | J9: =(D9-C9)/C9 -> 0.014257008 | K9: =(E9-D9)/D9 -> 0 | L9: =(F9-E9)/E9 -> 0.076907906 | M9: =(G9-F9)/F9 -> 0
B10: Total Share Capital | C10: 1099.81 | D10: 1115.49 | E10: 1115.49 | F10: 1201.28 | G10: 1201.28 | J10: =(D10-C10)/C10 -> 0.014257008 | K10: =(E10-D10)/D10 -> 0 | L10: =(F10-E10)/E10 -> 0.076907906 | M10: =(G10-F10)/F10 -> 0
B11: Reserves and Surplus | C11: 5757.36 | D11: 10546.95 | E11: 11526.06 | F11: 20866.92 | G11: 24226.26 | J11: =(D11-C11)/C11 -> 0.83190733 | K11: =(E11-D11)/D11 -> 0.092833473 | L11: =(F11-E11)/E11 -> 0.81041223 | M11: =(G11-F11)/F11 -> 0.16098878
B12: Total Reserves and Surplus | C12: 5757.36 | D12: 10546.95 | E12: 11526.06 | F12: 20866.92 | G12: 24226.26 | J12: =(D12-C12)/C12 -> 0.83190733 | K12: =(E12-D12)/D12 -> 0.092833473 | L12: =(F12-E12)/E12 -> 0.81041223 | M12: =(G12-F12)/F12 -> 0.16098878
B13: Total Shareholders Funds | C13: 6857.17 | D13: 11662.44 | E13: 12641.55 | F13: 22068.2 | G13: 25427.54 | J13: =(D13-C13)/C13 -> 0.70076577 | K13: =(E13-D13)/D13 -> 0.08395413 | L13: =(F13-E13)/E13 -> 0.74568783 | M13: =(G13-F13)/F13 -> 0.15222537
B14: Hybrid/Debt/Other Securities | C14: 3055.65 | D14: 0 | E14: 0 | F14: 0 | G14: 0 | J14: =(D14-C14)/C14 -> -1 | K14: 0 | L14: 0 | M14: 0
B15: Minority Interest | C15: 1093.68 | D15: 1097.55 | E15: 1061.58 | F15: 943.06 | G15: 1098.1 | J15: =(D15-C15)/C15 -> 0.0035385122 | K15: =(E15-D15)/D15 -> -0.032772994 | L15: =(F15-E15)/E15 -> -0.11164491 | M15: =(G15-F15)/F15 -> 0.16440099
B16: NON-CURRENT LIABILITIES
B17: Long Term Borrowings | C17: 27774.04 | D17: 31330.39 | E17: 33559.62 | F17: 36992.29 | G17: 45367.32 | J17: =(D17-C17)/C17 -> 0.12804583 | K17: =(E17-D17)/D17 -> 0.071152322 | L17: =(F17-E17)/E17 -> 0.10228572 | M17: =(G17-F17)/F17 -> 0.22639934
B18: Deferred Tax Liabilities [Net] | C18: 1414.46 | D18: 1540.1 | E18: 1652.78 | F18: 1753.76 | G18: 2490.14 | J18: =(D18-C18)/C18 -> 0.088825417 | K18: =(E18-D18)/D18 -> 0.07316408 | L18: =(F18-E18)/E18 -> 0.061097061 | M18: =(G18-F18)/F18 -> 0.41988642
B19: Other Long Term Liabilities | C19: 723.4 | D19: 756.25 | E19: 1016.37 | F19: 1632.82 | G19: 2202.98 | J19: =(D19-C19)/C19 -> 0.045410561 | K19: =(E19-D19)/D19 -> 0.34396033 | L19: =(F19-E19)/E19 -> 0.60652125 | M19: =(G19-F19)/F19 -> 0.3491873
B20: Long Term Provisions | C20: 617.47 | D20: 527.73 | E20: 630.23 | F20: 553.57 | G20: 680.99 | J20: =(D20-C20)/C20 -> -0.145335 | K20: =(E20-D20)/D20 -> 0.19422811 | L20: =(F20-E20)/E20 -> -0.12163813 | M20: =(G20-F20)/F20 -> 0.23017866
B21: Total Non-Current Liabilities | C21: 30529.37 | D21: 34154.47 | E21: 36859 | F21: 40932.44 | G21: 50741.43 | J21: =(D21-C21)/C21 -> 0.1187414 | K21: =(E21-D21)/D21 -> 0.079185243 | L21: =(F21-E21)/E21 -> 0.11051412 | M21: =(G21-F21)/F21 -> 0.23963854
B22: CURRENT LIABILITIES
B23: Short Term Borrowings | C23: 2040.54 | D23: 2868.45 | E23: 3449.25 | F23: 3213.79 | G23: 3531.13 | J23: =(D23-C23)/C23 -> 0.40573084 | K23: =(E23-D23)/D23 -> 0.20247869 | L23: =(F23-E23)/E23 -> -0.068264115 | M23: =(G23-F23)/F23 -> 0.098743228
B24: Trade Payables | C24: 1607.91 | D24: 1800.43 | E24: 1722.11 | F24: 2955.62 | G24: 4993.65 | J24: =(D24-C24)/C24 -> 0.11973307 | K24: =(E24-D24)/D24 -> -0.043500719 | L24: =(F24-E24)/E24 -> 0.71627829 | M24: =(G24-F24)/F24 -> 0.68954399
B25: Other Current Liabilities | C25: 2208.88 | D25: 2229.12 | E25: 2746.81 | F25: 3741.47 | G25: 6836.2 | J25: =(D25-C25)/C25 -> 0.0091630147 | K25: =(E25-D25)/D25 -> 0.23223963 | L25: =(F25-E25)/E25 -> 0.3621146 | M25: =(G25-F25)/F25 -> 0.82714281
B26: Short Term Provisions | C26: 70.91 | D26: 119.29 | E26: 98.51 | F26: 105.52 | G26: 206.87 | J26: =(D26-C26)/C26 -> 0.6822733 | K26: =(E26-D26)/D26 -> -0.17419733 | L26: =(F26-E26)/E26 -> 0.071160288 | M26: =(G26-F26)/F26 -> 0.96048143
B27: Total Current Liabilities | C27: 5928.24 | D27: 7017.29 | E27: 8016.68 | F27: 10016.4 | G27: 15567.85 | J27: =(D27-C27)/C27 -> 0.18370545 | K27: =(E27-D27)/D27 -> 0.14241823 | L27: =(F27-E27)/E27 -> 0.24944491 | M27: =(G27-F27)/F27 -> 0.55423605
B28: Total Capital And Liabilities | C28: 47464.11 | D28: 53931.75 | E28: 58578.81 | F28: 73960.1 | G28: 92834.92 | J28: =(D28-C28)/C28 -> 0.1362638 | K28: =(E28-D28)/D28 -> 0.08616557 | L28: =(F28-E28)/E28 -> 0.2625743 | M28: =(G28-F28)/F28 -> 0.25520274
B29: ASSETS
B30: NON-CURRENT ASSETS
B31: Tangible Assets | C31: 28578.02 | D31: 30947.5 | E31: 37219.85 | F31: 37845.22 | G31: 45060.12 | J31: =(D31-C31)/C31 -> 0.082912672 | K31: =(E31-D31)/D31 -> 0.20267711 | L31: =(F31-E31)/E31 -> 0.016802056 | M31: =(G31-F31)/F31 -> 0.19064231
B32: Intangible Assets | C32: 1095.46 | D32: 1099.35 | E32: 1101.6 | F32: 1111.24 | G32: 1145.53 | J32: =(D32-C32)/C32 -> 0.0035510197 | K32: =(E32-D32)/D32 -> 0.0020466639 | L32: =(F32-E32)/E32 -> 0.0087509078 | M32: =(G32-F32)/F32 -> 0.030857421
B33: Capital Work-In-Progress | C33: 5060.16 | D33: 6200.44 | E33: 3002.69 | F33: 5695.36 | G33: 2053.6 | J33: =(D33-C33)/C33 -> 0.22534465 | K33: =(E33-D33)/D33 -> -0.51572953 | L33: =(F33-E33)/E33 -> 0.89675258 | M33: =(G33-F33)/F33 -> -0.63942578
B34: Intangible Assets Under Development | C34: 0 | D34: 0 | E34: 0 | F34: 6.88 | G34: 0 | J34: 0 | K34: 0 | L34: 0 | M34: =(G34-F34)/F34 -> -1
B35: Fixed Assets | C35: 34733.64 | D35: 38247.29 | E35: 41324.14 | F35: 44658.7 | G35: 48259.25 | J35: =(D35-C35)/C35 -> 0.10115986 | K35: =(E35-D35)/D35 -> 0.080446222 | L35: =(F35-E35)/E35 -> 0.080692786 | M35: =(G35-F35)/F35 -> 0.080623708
B36: Non-Current Investments | C36: 264.17 | D36: 312.89 | E36: 323.79 | F36: 348.72 | G36: 407.29 | J36: =(D36-C36)/C36 -> 0.18442669 | K36: =(E36-D36)/D36 -> 0.034836524 | L36: =(F36-E36)/E36 -> 0.076994348 | M36: =(G36-F36)/F36 -> 0.1679571
B37: Deferred Tax Assets [Net] | C37: 0 | D37: 0 | E37: 40.43 | F37: 57.85 | G37: 78.17 | J37: 0 | K37: 0 | L37: =(F37-E37)/E37 -> 0.43086817 | M37: =(G37-F37)/F37 -> 0.35125324
B38: Long Term Loans And Advances | C38: 1128.54 | D38: 26.1 | E38: 22.51 | F38: 15.88 | G38: 10.58 | J38: =(D38-C38)/C38 -> -0.97687277 | K38: =(E38-D38)/D38 -> -0.13754789 | L38: =(F38-E38)/E38 -> -0.29453576 | M38: =(G38-F38)/F38 -> -0.33375315
B39: Other Non-Current Assets | C39: 5096.85 | D39: 5840.32 | E39: 6651.53 | F39: 11606.54 | G39: 23639.66 | J39: =(D39-C39)/C39 -> 0.14586853 | K39: =(E39-D39)/D39 -> 0.13889821 | L39: =(F39-E39)/E39 -> 0.74494289 | M39: =(G39-F39)/F39 -> 1.0367534
B40: Total Non-Current Assets | C40: 41821.49 | D40: 45024.89 | E40: 48960.69 | F40: 57285.98 | G40: 72993.24 | J40: =(D40-C40)/C40 -> 0.076596984 | K40: =(E40-D40)/D40 -> 0.087413873 | L40: =(F40-E40)/E40 -> 0.17004029 | M40: =(G40-F40)/F40 -> 0.2741903
B41: CURRENT ASSETS
B42: Current Investments | C42: 296.35 | D42: 1056.79 | E42: 442.69 | F42: 2289.69 | G42: 2236.32 | J42: =(D42-C42)/C42 -> 2.5660199 | K42: =(E42-D42)/D42 -> -0.58109937 | L42: =(F42-E42)/E42 -> 4.1722198 | M42: =(G42-F42)/F42 -> -0.023308832
B43: Inventories | C43: 250.11 | D43: 151.91 | E43: 255.28 | F43: 625.24 | G43: 669.45 | J43: =(D43-C43)/C43 -> -0.39262724 | K43: =(E43-D43)/D43 -> 0.6804687 | L43: =(F43-E43)/E43 -> 1.4492322 | M43: =(G43-F43)/F43 -> 0.070708848
B44: Trade Receivables | C44: 1070.84 | D44: 1437.59 | E44: 1564.95 | F44: 4217.86 | G44: 5733.75 | J44: =(D44-C44)/C44 -> 0.34248814 | K44: =(E44-D44)/D44 -> 0.088592714 | L44: =(F44-E44)/E44 -> 1.6952043 | M44: =(G44-F44)/F44 -> 0.35939789
B45: Cash And Cash Equivalents | C45: 1492.57 | D45: 1704.14 | E45: 2228.14 | F45: 3618.68 | G45: 3947.34 | J45: =(D45-C45)/C45 -> 0.1417488 | K45: =(E45-D45)/D45 -> 0.30748647 | L45: =(F45-E45)/E45 -> 0.62408107 | M45: =(G45-F45)/F45 -> 0.090823173
B46: Short Term Loans And Advances | C46: 7.81 | D46: 477.2 | E46: 407.78 | F46: 6.45 | G46: 5.77 | J46: =(D46-C46)/C46 -> 60.101152 | K46: =(E46-D46)/D46 -> -0.1454736 | L46: =(F46-E46)/E46 -> -0.98418265 | M46: =(G46-F46)/F46 -> -0.10542636
B47: OtherCurrentAssets | C47: 2524.94 | D47: 4079.23 | E47: 4719.28 | F47: 5916.2 | G47: 7249.05 | J47: =(D47-C47)/C47 -> 0.61557502 | K47: =(E47-D47)/D47 -> 0.15690461 | L47: =(F47-E47)/E47 -> 0.25362343 | M47: =(G47-F47)/F47 -> 0.22528819
B48: Total Current Assets | C48: 5642.62 | D48: 8906.86 | E48: 9618.12 | F48: 16674.12 | G48: 19841.68 | J48: =(D48-C48)/C48 -> 0.57849722 | K48: =(E48-D48)/D48 -> 0.079855303 | L48: =(F48-E48)/E48 -> 0.7336153 | M48: =(G48-F48)/F48 -> 0.18996865
B49: Total Assets | C49: 47464.11 | D49: 53931.75 | E49: 58578.81 | F49: 73960.1 | G49: 92834.92 | J49: =(D49-C49)/C49 -> 0.1362638 | K49: =(E49-D49)/D49 -> 0.08616557 | L49: =(F49-E49)/E49 -> 0.2625743 | M49: =(G49-F49)/F49 -> 0.25520274
B50: OTHER ADDITIONAL INFORMATION
B51: CONTINGENT LIABILITIES, COMMITMENTS
B52: Contingent Liabilities | C52: 3717.33 | D52: 7890.27 | E52: 9221.82 | F52: 14107.15 | G52: 40053.98 | J52: =(D52-C52)/C52 -> 1.1225638 | K52: =(E52-D52)/D52 -> 0.16875848 | L52: =(F52-E52)/E52 -> 0.52975768 | M52: =(G52-F52)/F52 -> 1.839268
B53: BONUS DETAILS
B54: NON-CURRENT INVESTMENTS
B55: Non-Current Investments Quoted Market Value | C55: 246.65 | D55: 290.6 | E55: 309.38 | F55: 341.61 | G55: 380.64 | J55: =(D55-C55)/C55 -> 0.17818772 | K55: =(E55-D55)/D55 -> 0.064624914 | L55: =(F55-E55)/E55 -> 0.10417609 | M55: =(G55-F55)/F55 -> 0.1142531
B56: Non-Current Investments Unquoted Book Value | C56: 0 | D56: 0 | E56: 0 | F56: 0.01 | G56: 0 | J56: 0 | K56: 0 | L56: 0 | M56: =(G56-F56)/F56 -> -1
B57: CURRENT INVESTMENTS
B58: Current Investments Quoted Market Value | C58: 0 | D58: 36.29 | E58: 50.81 | F58: 43.09 | G58: 0.12 | J58: 0 | K58: =(E58-D58)/D58 -> 0.40011022 | L58: =(F58-E58)/E58 -> -0.15193859 | M58: =(G58-F58)/F58 -> -0.99721513
B59: Current Investments Unquoted Book Value | C59: 260.53 | D59: 1020.43 | E59: 392.3 | F59: 2246.6 | G59: 2236.2 | J59: =(D59-C59)/C59 -> 2.9167466 | K59: =(E59-D59)/D59 -> -0.61555423 | L59: =(F59-E59)/E59 -> 4.7267397 | M59: =(G59-F59)/F59 -> -0.0046292175
B63: Source : Dion Global Solutions Limited

Sheet Consolidated Profit & Loss
B1: Adani Energy Solutions
B2: Consolidated Profit & Loss account
C3: 44621 | D3: 44986 | E3: 45352 | F3: 45717 | G3: Mar 26
C5: 12 mths | D5: 12 mths | E5: 12 mths | F5: 12 mths | G5: 12 mths
I6: Changes in %
B7: INCOME | I7: 44621 | J7: 44986 | K7: 45352 | L7: 45717 | M7: Mar 26
B8: Revenue From Operations [Gross] | C8: 10960.21 | D8: 12995.12 | E8: 16355.01 | F8: 23546.15 | G8: 27202.63 | J8: =(D8-C8)/C8 -> 0.18566341 | K8: =(E8-D8)/D8 -> 0.25855013 | L8: =(F8-E8)/E8 -> 0.43969035 | M8: =(G8-F8)/F8 -> 0.15528993
B9: Revenue From Operations [Net] | C9: 10960.21 | D9: 12995.12 | E9: 16355.01 | F9: 23546.15 | G9: 27202.63 | J9: =(D9-C9)/C9 -> 0.18566341 | K9: =(E9-D9)/D9 -> 0.25855013 | L9: =(F9-E9)/E9 -> 0.43969035 | M9: =(G9-F9)/F9 -> 0.15528993
B10: Other Operating Revenues | C10: 297.31 | D10: 297.6 | E10: 252.35 | F10: 220.94 | G10: 385.4 | J10: =(D10-C10)/C10 -> 0.00097541287 | K10: =(E10-D10)/D10 -> -0.15204973 | L10: =(F10-E10)/E10 -> -0.12446998 | M10: =(G10-F10)/F10 -> 0.74436499
B11: Total Operating Revenues | C11: 11257.52 | D11: 13292.72 | E11: 16607.36 | F11: 23767.09 | G11: 27588.03 | J11: =(D11-C11)/C11 -> 0.18078582 | K11: =(E11-D11)/D11 -> 0.24935754 | L11: =(F11-E11)/E11 -> 0.43111789 | M11: =(G11-F11)/F11 -> 0.160766
B12: Other Income | C12: 603.95 | D12: 547.74 | E12: 610.95 | F12: 679.46 | G12: 737.13 | J12: =(D12-C12)/C12 -> -0.093070618 | K12: =(E12-D12)/D12 -> 0.11540147 | L12: =(F12-E12)/E12 -> 0.11213684 | M12: =(G12-F12)/F12 -> 0.084876225
B13: Total Revenue | C13: 11861.47 | D13: 13840.46 | E13: 17218.31 | F13: 24446.55 | G13: 28325.16 | J13: =(D13-C13)/C13 -> 0.16684188 | K13: =(E13-D13)/D13 -> 0.24405619 | L13: =(F13-E13)/E13 -> 0.41979962 | M13: =(G13-F13)/F13 -> 0.15865674
B14: EXPENSES
B15: Purchase Of Stock-In Trade | C15: 821.23 | D15: 755.13 | E15: 1028.95 | F15: 1365.74 | G15: 1004.14 | J15: =(D15-C15)/C15 -> -0.080489023 | K15: =(E15-D15)/D15 -> 0.36261306 | L15: =(F15-E15)/E15 -> 0.32731425 | M15: =(G15-F15)/F15 -> -0.26476489
B16: Cost of Power Purchased | C16: 2778.88 | D16: 3839.98 | E16: 4340.3 | F16: 5584.14 | G16: 6347.88 | J16: =(D16-C16)/C16 -> 0.38184448 | K16: =(E16-D16)/D16 -> 0.13029235 | L16: =(F16-E16)/E16 -> 0.28657927 | M16: =(G16-F16)/F16 -> 0.13676949
B17: Cost Of Fuel | C17: 1065.99 | D17: 1384.18 | E17: 1119.09 | F17: 623.54 | G17: 0 | J17: =(D17-C17)/C17 -> 0.29849248 | K17: =(E17-D17)/D17 -> -0.19151411 | L17: =(F17-E17)/E17 -> -0.44281514 | M17: =(G17-F17)/F17 -> -1
B18: Operating And Direct Expenses | C18: 0 | D18: 0 | E18: 0 | F18: 0 | G18: 7135.35
B19: Employee Benefit Expenses | C19: 885.07 | D19: 986.65 | E19: 951.7 | F19: 1032.94 | G19: 1092.64 | J19: =(D19-C19)/C19 -> 0.11477058 | K19: =(E19-D19)/D19 -> -0.035422896 | L19: =(F19-E19)/E19 -> 0.085363035 | M19: =(G19-F19)/F19 -> 0.057796193
B20: Finance Costs | C20: 2364.95 | D20: 2781.47 | E20: 2766.51 | F20: 3259.16 | G20: 3632.9 | J20: =(D20-C20)/C20 -> 0.17612212 | K20: =(E20-D20)/D20 -> -0.005378451 | L20: =(F20-E20)/E20 -> 0.17807635 | M20: =(G20-F20)/F20 -> 0.11467372
B21: Depreciation And Amortisation Expenses | C21: 1427.15 | D21: 1607.74 | E21: 1776.08 | F21: 1905.95 | G21: 1978.23 | J21: =(D21-C21)/C21 -> 0.12653891 | K21: =(E21-D21)/D21 -> 0.10470598 | L21: =(F21-E21)/E21 -> 0.073121706 | M21: =(G21-F21)/F21 -> 0.037923345
B22: Other Expenses | C22: 1500.18 | D22: 1809.17 | E22: 2996.11 | F22: 6753.46 | G22: 2923.62 | J22: =(D22-C22)/C22 -> 0.20596862 | K22: =(E22-D22)/D22 -> 0.65606881 | L22: =(F22-E22)/E22 -> 1.2540761 | M22: =(G22-F22)/F22 -> -0.56709302
B23: Total Expenses | C23: 10843.45 | D23: 13164.32 | E23: 14978.74 | F23: 20524.93 | G23: 24114.76 | J23: =(D23-C23)/C23 -> 0.21403428 | K23: =(E23-D23)/D23 -> 0.13782862 | L23: =(F23-E23)/E23 -> 0.3702708 | M23: =(G23-F23)/F23 -> 0.17490096
B24: Profit/Loss Before Exceptional, ExtraOrdinary Items And Tax | C24: 1018.02 | D24: 676.14 | E24: 2239.57 | F24: 3921.62 | G24: 4210.4 | J24: =(D24-C24)/C24 -> -0.33582837 | K24: =(E24-D24)/D24 -> 2.3122874 | L24: =(F24-E24)/E24 -> 0.75105936 | M24: =(G24-F24)/F24 -> 0.073637935
B25: Exceptional Items | C25: 682.47 | D25: 1035.58 | E25: -460.01 | F25: -2846.77 | G25: -1095.56 | J25: =(D25-C25)/C25 -> 0.51740003 | K25: =(E25-D25)/D25 -> -1.4442052 | L25: =(F25-E25)/E25 -> 5.1884959 | M25: =(G25-F25)/F25 -> -0.61515683
B26: Profit/Loss Before Tax | C26: 1700.49 | D26: 1711.72 | E26: 1779.56 | F26: 1074.85 | G26: 3114.84 | J26: =(D26-C26)/C26 -> 0.0066039789 | K26: =(E26-D26)/D26 -> 0.03963265 | L26: =(F26-E26)/E26 -> -0.39600238 | M26: =(G26-F26)/F26 -> 1.8979299
B27: Tax Expenses-Continued Operations
B28: Current Tax | C28: 244.23 | D28: 260.94 | E28: 298.6 | F28: 195.04 | G28: 392.8 | J28: =(D28-C28)/C28 -> 0.068419113 | K28: =(E28-D28)/D28 -> 0.14432437 | L28: =(F28-E28)/E28 -> -0.34681849 | M28: =(G28-F28)/F28 -> 1.0139459
B29: Deferred Tax | C29: 191.83 | D29: 174.39 | E29: 281.53 | F29: -16.05 | G29: 378.91 | J29: =(D29-C29)/C29 -> -0.09091383 | K29: =(E29-D29)/D29 -> 0.61437009 | L29: =(F29-E29)/E29 -> -1.0570099 | M29: =(G29-F29)/F29 -> -24.6081
B30: Total Tax Expenses | C30: 436.06 | D30: 435.33 | E30: 580.13 | F30: 178.99 | G30: 771.71 | J30: =(D30-C30)/C30 -> -0.0016740815 | K30: =(E30-D30)/D30 -> 0.33262123 | L30: =(F30-E30)/E30 -> -0.69146571 | M30: =(G30-F30)/F30 -> 3.3114699
B31: Profit/Loss After Tax And Before ExtraOrdinary Items | C31: 1264.43 | D31: 1276.39 | E31: 1199.43 | F31: 895.86 | G31: 2343.13 | J31: =(D31-C31)/C31 -> 0.0094588075 | K31: =(E31-D31)/D31 -> -0.060295051 | L31: =(F31-E31)/E31 -> -0.25309522 | M31: =(G31-F31)/F31 -> 1.6155091
B32: Extraordinary Items | C32: -28.68 | D32: 4.21 | E32: -3.82 | F32: 25.83 | G32: 49.62 | J32: =(D32-C32)/C32 -> -1.1467922 | K32: =(E32-D32)/D32 -> -1.9073634 | L32: =(F32-E32)/E32 -> -7.7617801 | M32: =(G32-F32)/F32 -> 0.92102207
B33: Profit/Loss From Continuing Operations | C33: 1235.75 | D33: 1280.6 | E33: 1195.61 | F33: 921.69 | G33: 2392.75 | J33: =(D33-C33)/C33 -> 0.036293749 | K33: =(E33-D33)/D33 -> -0.066367328 | L33: =(F33-E33)/E33 -> -0.22910481 | M33: =(G33-F33)/F33 -> 1.5960464
B34: Profit/Loss For The Period | C34: 1235.75 | D34: 1280.6 | E34: 1195.61 | F34: 921.69 | G34: 2392.75 | J34: =(D34-C34)/C34 -> 0.036293749 | K34: =(E34-D34)/D34 -> -0.066367328 | L34: =(F34-E34)/E34 -> -0.22910481 | M34: =(G34-F34)/F34 -> 1.5960464
B35: Minority Interest | C35: -31.14 | D35: -24.27 | E35: -58.33 | F35: 138.28 | G35: -110.21 | J35: =(D35-C35)/C35 -> -0.22061657 | K35: =(E35-D35)/D35 -> 1.4033787 | L35: =(F35-E35)/E35 -> -3.3706498 | M35: =(G35-F35)/F35 -> -1.7970061
B36: Consolidated Profit/Loss After MI And Associates | C36: 1204.61 | D36: 1256.33 | E36: 1137.28 | F36: 1059.97 | G36: 2282.54 | J36: =(D36-C36)/C36 -> 0.042935058 | K36: =(E36-D36)/D36 -> -0.094760135 | L36: =(F36-E36)/E36 -> -0.067977983 | M36: =(G36-F36)/F36 -> 1.1534006
B37: OTHER ADDITIONAL INFORMATION
B38: EARNINGS PER SHARE
B39: Basic EPS (Rs.) | C39: 9 | D39: 11 | E39: 10 | F39: 9 | G39: 19 | J39: =(D39-C39)/C39 -> 0.22222222 | K39: =(E39-D39)/D39 -> -0.090909091 | L39: =(F39-E39)/E39 -> -0.1 | M39: =(G39-F39)/F39 -> 1.1111111
B40: Diluted EPS (Rs.) | C40: 5 | D40: 11 | E40: 10 | F40: 9 | G40: 19 | J40: =(D40-C40)/C40 -> 1.2 | K40: =(E40-D40)/D40 -> -0.090909091 | L40: =(F40-E40)/E40 -> -0.1 | M40: =(G40-F40)/F40 -> 1.1111111
B41: DIVIDEND AND DIVIDEND PERCENTAGE
B45: Source : Dion Global Solutions Limited

Sheet Consolidated Cash Flow
B1: Adani Energy Solutions
B2: Cash Flow
C3: Mar 26 | D3: 46082 | E3: 45717 | F3: 45717 | G3: 45352
C5: 12 mths | D5: 12 mths | E5: 12 mths | F5: 12 mths | G5: 12 mths
B7: Net Profit/Loss Before Extraordinary Items And Tax | C7: 631.36 | D7: 631.36 | E7: 626.6 | F7: 626.6 | G7: 659.34
B8: Net CashFlow From Operating Activities | C8: 441.92 | D8: 441.92 | E8: -955.19 | F8: -955.19 | G8: -209.49
B9: Net Cash Used In Investing Activities | C9: -3695.05 | D9: -3695.05 | E9: -9164.34 | F9: -9164.34 | G9: -2000.95
B10: Net Cash Used From Financing Activities | C10: 2827.78 | D10: 2827.78 | E10: 10587.48 | F10: 10587.48 | G10: 2210.16
B11: Net Inc/Dec In Cash And Cash Equivalents | C11: -425.35 | D11: -425.35 | E11: 467.95 | F11: 467.95 | G11: -0.28
B12: Cash And Cash Equivalents Begin of Year | C12: 470.31 | D12: 470.31 | E12: 2.36 | F12: 2.36 | G12: 2.64
B13: Cash And Cash Equivalents End Of Year | C13: 44.96 | D13: 44.96 | E13: 470.31 | F13: 470.31 | G13: 2.36

Sheet Peer Comps
B1: Company | C1: Business Overview
B2: Adani Energy Solutions Ltd | C2: Adani Energy Solutions Ltd is one of India's largest private-sector power transmission companies. The company develops, owns, and operates transmission networks across multiple states and is expanding rapidly in smart metering, distribution infrastructure, and energy transition projects. It plays a key role in strengthening India's power delivery ecosystem through transmission, distribution, and utility modernization solutions.
B3: Tata Power Company Ltd | C3: Tata Power Company Ltd is one of India's largest integrated power companies with operations spanning power generation, transmission, distribution, renewable energy, solar manufacturing, EV charging infrastructure, and energy services. The company serves residential, commercial, and industrial customers while actively expanding its clean energy and sustainability-focused businesses.
B4: Torrent Power Ltd | C4: Torrent Power Ltd is an integrated power utility engaged in electricity generation, transmission, distribution, and renewable energy development. The company operates distribution networks across several Indian cities and has a growing portfolio of gas-based, renewable, and conventional power assets serving industrial, commercial, and retail consumers.
B5: Power Grid Corporation of India | C5: Power Grid Corporation of India Ltd is India's largest electric power transmission company and a central transmission utility. The company owns and operates an extensive high-voltage transmission network across the country and plays a critical role in integrating renewable energy, ensuring grid stability, and facilitating interstate power transmission.
B6: CESC Limited | C6: CESC Ltd is an integrated power utility primarily engaged in electricity generation and distribution. The company supplies power to Kolkata and surrounding areas while also having investments in power generation, distribution utilities, retail electricity businesses, and emerging energy-related ventures

Sheet Stock Analysis
B2: STOCK ANALYSIS — ADANI ENERGY SOLUTIONS LTD.
B18: MARKET SNAPSHOT | E18: Recommendation:
B19: Shares Outstanding (Cr) | C19: 120.13 | E19: AVOID/HOLD – Adani Energy Solutions Ltd, despite operating in a structurally favourable space of power transmission, distribution, and smart metering infrastructure, currently trades at a significant premium to its intrinsic value, with our DCF-based fair value estimate of ₹543 standing nearly 64% below the current market price of ₹1,495. The company's WACC of 12.77% and projected 10-year revenue CAGR of apx13.5% with EBIT margins near 30% reflect a fundamentally sound and growing business, but these growth assumptions appear to already be priced in, and then some. On the price front, AESL has been the weakest performer among its peer set over the past five years, returning just +32.49% compared to Tata Power (+284.24%), Torrent Power (+222.02%), and Power Grid (+124.00%), having crashed over 60% in early 2023 amid group-level concerns and remaining range-bound since, with no relative-strength reversal yet visible. While the company's exposure to India's grid modernization capex cycle and potential optionality from newer verticals such as data centre power and smart metering could support a future re-rating, this remains a forward-looking, sentiment-driven case rather than one supported by current cash flow projections. Elevated valuation versus DCF fair value, persistent underperformance versus sector peers, and sensitivity of the investment case to cost-of-capital normalization for the Adani group remain key monitorables.
B20: Book Value per Share (₹) | C20: 211.7
B21: Gross Debt (₹ Cr) | C21: 48,898
B22: Net Debt (₹ Cr) | C22: 44,951
B23: Net Debt / EBITDA (x) | C23: 4.58x
B24: Debt / Equity (x) | C24: 1.92x
B25: Interest Coverage (x) | C25: 1.16x
B26: Return on Equity | C26: 9.5%
B27: Return on Assets | C27: 2.5%
B28: Basic EPS (₹) FY26 | C28: 19.0
B29: EPS CAGR (FY22-FY26) | C29: 20.5%
B30: Revenue CAGR (FY22-FY26) | C30: 25.5%
B31: PAT CAGR (FY22-FY26) | C31: 17.3%
B32: Dividend | C32: Nil

Sheet Ratio Analysis
B1: RATIO ANALYSIS
B3: Ratio | C3: 2022 | D3: 2023 | E3: 2024 | F3: 2025 | G3: 2026 | H3: 5Y Avg
B4: Income Statement Ratios
B5: Sales Growth | D5: ='Consolidated Profit & Loss'!D9/'Consolidated Profit & Loss'!C9-1 -> 0.18566341 | E5: ='Consolidated Profit & Loss'!E9/'Consolidated Profit & Loss'!D9-1 -> 0.25855013 | F5: ='Consolidated Profit & Loss'!F9/'Consolidated Profit & Loss'!E9-1 -> 0.43969035 | G5: ='Consolidated Profit & Loss'!G9/'Consolidated Profit & Loss'!F9-1 -> 0.15528993 | H5: =AVERAGE(D5,E5,F5,G5) -> 0.25979846
B6: EBITDA | C6: ='Consolidated Profit & Loss'!C24+'Consolidated Profit & Loss'!C20+'Consolidated Profit & Loss'!C21 -> 4810.12 | D6: ='Consolidated Profit & Loss'!D24+'Consolidated Profit & Loss'!D20+'Consolidated Profit & Loss'!D21 -> 5065.35 | E6: ='Consolidated Profit & Loss'!E24+'Consolidated Profit & Loss'!E20+'Consolidated Profit & Loss'!E21 -> 6782.16 | F6: ='Consolidated Profit & Loss'!F24+'Consolidated Profit & Loss'!F20+'Consolidated Profit & Loss'!F21 -> 9086.73 | G6: ='Consolidated Profit & Loss'!G24+'Consolidated Profit & Loss'!G20+'Consolidated Profit & Loss'!G21 -> 9821.53 | H6: =AVERAGE(C6,D6,E6,F6,G6) -> 7113.178
B7: EBITDA Margins | C7: =('Consolidated Profit & Loss'!C24+'Consolidated Profit & Loss'!C20+'Consolidated Profit & Loss'!C21)/'Consolidated Profit & Loss'!C9 -> 0.43887115 | D7: =('Consolidated Profit & Loss'!D24+'Consolidated Profit & Loss'!D20+'Consolidated Profit & Loss'!D21)/'Consolidated Profit & Loss'!D9 -> 0.38978863 | E7: =('Consolidated Profit & Loss'!E24+'Consolidated Profit & Loss'!E20+'Consolidated Profit & Loss'!E21)/'Consolidated Profit & Loss'!E9 -> 0.41468394 | F7: =('Consolidated Profit & Loss'!F24+'Consolidated Profit & Loss'!F20+'Consolidated Profit & Loss'!F21)/'Consolidated Profit & Loss'!F9 -> 0.3859115 | G7: =('Consolidated Profit & Loss'!G24+'Consolidated Profit & Loss'!G20+'Consolidated Profit & Loss'!G21)/'Consolidated Profit & Loss'!G9 -> 0.36105075 | H7: =AVERAGE(C7,D7,E7,F7,G7) -> 0.39806119
B8: EBIT | C8: ='Consolidated Profit & Loss'!C24+'Consolidated Profit & Loss'!C20 -> 3382.97 | D8: ='Consolidated Profit & Loss'!D24+'Consolidated Profit & Loss'!D20 -> 3457.61 | E8: ='Consolidated Profit & Loss'!E24+'Consolidated Profit & Loss'!E20 -> 5006.08 | F8: ='Consolidated Profit & Loss'!F24+'Consolidated Profit & Loss'!F20 -> 7180.78 | G8: ='Consolidated Profit & Loss'!G24+'Consolidated Profit & Loss'!G20 -> 7843.3 | H8: =AVERAGE(C8,D8,E8,F8,G8) -> 5374.148
B9: EBIT Margin | C9: =('Consolidated Profit & Loss'!C24+'Consolidated Profit & Loss'!C20)/'Consolidated Profit & Loss'!C9 -> 0.30865923 | D9: =('Consolidated Profit & Loss'!D24+'Consolidated Profit & Loss'!D20)/'Consolidated Profit & Loss'!D9 -> 0.26606988 | E9: =('Consolidated Profit & Loss'!E24+'Consolidated Profit & Loss'!E20)/'Consolidated Profit & Loss'!E9 -> 0.30608847 | F9: =('Consolidated Profit & Loss'!F24+'Consolidated Profit & Loss'!F20)/'Consolidated Profit & Loss'!F9 -> 0.3049662 | G9: =('Consolidated Profit & Loss'!G24+'Consolidated Profit & Loss'!G20)/'Consolidated Profit & Loss'!G9 -> 0.28832874 | H9: =AVERAGE(C9,D9,E9,F9,G9) -> 0.2948225
B10: Finance Costs | C10: ='Consolidated Profit & Loss'!C20 -> 2364.95 | D10: ='Consolidated Profit & Loss'!D20 -> 2781.47 | E10: ='Consolidated Profit & Loss'!E20 -> 2766.51 | F10: ='Consolidated Profit & Loss'!F20 -> 3259.16 | G10: ='Consolidated Profit & Loss'!G20 -> 3632.9 | H10: =AVERAGE(C10,D10,E10,F10,G10) -> 2960.998
B11: Finance Costs % Revenue | C11: ='Consolidated Profit & Loss'!C20/'Consolidated Profit & Loss'!C9 -> 0.21577598 | D11: ='Consolidated Profit & Loss'!D20/'Consolidated Profit & Loss'!D9 -> 0.21403958 | E11: ='Consolidated Profit & Loss'!E20/'Consolidated Profit & Loss'!E9 -> 0.16915367 | F11: ='Consolidated Profit & Loss'!F20/'Consolidated Profit & Loss'!F9 -> 0.13841583 | G11: ='Consolidated Profit & Loss'!G20/'Consolidated Profit & Loss'!G9 -> 0.13354959 | H11: =AVERAGE(C11,D11,E11,F11,G11) -> 0.17418693
B12: Depreciation | C12: ='Consolidated Profit & Loss'!C21 -> 1427.15 | D12: ='Consolidated Profit & Loss'!D21 -> 1607.74 | E12: ='Consolidated Profit & Loss'!E21 -> 1776.08 | F12: ='Consolidated Profit & Loss'!F21 -> 1905.95 | G12: ='Consolidated Profit & Loss'!G21 -> 1978.23 | H12: =AVERAGE(C12,D12,E12,F12,G12) -> 1739.03
B13: Depreciation % of Sales | C13: ='Consolidated Profit & Loss'!C21/'Consolidated Profit & Loss'!C9 -> 0.13021192 | D13: ='Consolidated Profit & Loss'!D21/'Consolidated Profit & Loss'!D9 -> 0.12371875 | E13: ='Consolidated Profit & Loss'!E21/'Consolidated Profit & Loss'!E9 -> 0.10859547 | F13: ='Consolidated Profit & Loss'!F21/'Consolidated Profit & Loss'!F9 -> 0.080945293 | G13: ='Consolidated Profit & Loss'!G21/'Consolidated Profit & Loss'!G9 -> 0.072722013 | H13: =AVERAGE(C13,D13,E13,F13,G13) -> 0.10323869
B14: PBT | C14: ='Consolidated Profit & Loss'!C24 -> 1018.02 | D14: ='Consolidated Profit & Loss'!D24 -> 676.14 | E14: ='Consolidated Profit & Loss'!E24 -> 2239.57 | F14: ='Consolidated Profit & Loss'!F24 -> 3921.62 | G14: ='Consolidated Profit & Loss'!G24 -> 4210.4 | H14: =AVERAGE(C14,D14,E14,F14,G14) -> 2413.15
B15: PBT Margin | C15: ='Consolidated Profit & Loss'!C24/'Consolidated Profit & Loss'!C9 -> 0.092883257 | D15: ='Consolidated Profit & Loss'!D24/'Consolidated Profit & Loss'!D9 -> 0.052030301 | E15: ='Consolidated Profit & Loss'!E24/'Consolidated Profit & Loss'!E9 -> 0.1369348 | F15: ='Consolidated Profit & Loss'!F24/'Consolidated Profit & Loss'!F9 -> 0.16655037 | G15: ='Consolidated Profit & Loss'!G24/'Consolidated Profit & Loss'!G9 -> 0.15477915 | H15: =AVERAGE(C15,D15,E15,F15,G15) -> 0.12063558
B16: Net Profit | C16: ='Consolidated Profit & Loss'!C36 -> 1204.61 | D16: ='Consolidated Profit & Loss'!D36 -> 1256.33 | E16: ='Consolidated Profit & Loss'!E36 -> 1137.28 | F16: ='Consolidated Profit & Loss'!F36 -> 1059.97 | G16: ='Consolidated Profit & Loss'!G36 -> 2282.54 | H16: =AVERAGE(C16,D16,E16,F16,G16) -> 1388.146
B17: Net Margins | C17: ='Consolidated Profit & Loss'!C36/'Consolidated Profit & Loss'!C9 -> 0.10990757 | D17: ='Consolidated Profit & Loss'!D36/'Consolidated Profit & Loss'!D9 -> 0.09667706 | E17: ='Consolidated Profit & Loss'!E36/'Consolidated Profit & Loss'!E9 -> 0.069537102 | F17: ='Consolidated Profit & Loss'!F36/'Consolidated Profit & Loss'!F9 -> 0.045016701 | G17: ='Consolidated Profit & Loss'!G36/'Consolidated Profit & Loss'!G9 -> 0.083908799 | H17: =AVERAGE(C17,D17,E17,F17,G17) -> 0.081009446
B18: Earnings Per Share | C18: ='Consolidated Profit & Loss'!C39 -> 9 | D18: ='Consolidated Profit & Loss'!D39 -> 11 | E18: ='Consolidated Profit & Loss'!E39 -> 10 | F18: ='Consolidated Profit & Loss'!F39 -> 9 | G18: ='Consolidated Profit & Loss'!G39 -> 19 | H18: =AVERAGE(C18,D18,E18,F18,G18) -> 11.6
B19: EPS Growth % | D19: ='Consolidated Profit & Loss'!D39/'Consolidated Profit & Loss'!C39-1 -> 0.22222222 | E19: ='Consolidated Profit & Loss'!E39/'Consolidated Profit & Loss'!D39-1 -> -0.090909091 | F19: ='Consolidated Profit & Loss'!F39/'Consolidated Profit & Loss'!E39-1 -> -0.1 | G19: ='Consolidated Profit & Loss'!G39/'Consolidated Profit & Loss'!F39-1 -> 1.1111111 | H19: =AVERAGE(D19,E19,F19,G19) -> 0.28560606
B21: Balance Statement Ratios
B22: Total Shareholders Funds | C22: ='Consolidated Balance Sheet'!C13 -> 6857.17 | D22: ='Consolidated Balance Sheet'!D13 -> 11662.44 | E22: ='Consolidated Balance Sheet'!E13 -> 12641.55 | F22: ='Consolidated Balance Sheet'!F13 -> 22068.2 | G22: ='Consolidated Balance Sheet'!G13 -> 25427.54 | H22: =AVERAGE(C22,D22,E22,F22,G22) -> 15731.38
B23: Total Equity incl. Minority Interest | C23: ='Consolidated Balance Sheet'!C13+'Consolidated Balance Sheet'!C15 -> 7950.85 | D23: ='Consolidated Balance Sheet'!D13+'Consolidated Balance Sheet'!D15 -> 12759.99 | E23: ='Consolidated Balance Sheet'!E13+'Consolidated Balance Sheet'!E15 -> 13703.13 | F23: ='Consolidated Balance Sheet'!F13+'Consolidated Balance Sheet'!F15 -> 23011.26 | G23: ='Consolidated Balance Sheet'!G13+'Consolidated Balance Sheet'!G15 -> 26525.64 | H23: =AVERAGE(C23,D23,E23,F23,G23) -> 16790.174
B24: Long Term Borrowings | C24: ='Consolidated Balance Sheet'!C17 -> 27774.04 | D24: ='Consolidated Balance Sheet'!D17 -> 31330.39 | E24: ='Consolidated Balance Sheet'!E17 -> 33559.62 | F24: ='Consolidated Balance Sheet'!F17 -> 36992.29 | G24: ='Consolidated Balance Sheet'!G17 -> 45367.32 | H24: =AVERAGE(C24,D24,E24,F24,G24) -> 35004.732
B25: Short Term Borrowings | C25: ='Consolidated Balance Sheet'!C23 -> 2040.54 | D25: ='Consolidated Balance Sheet'!D23 -> 2868.45 | E25: ='Consolidated Balance Sheet'!E23 -> 3449.25 | F25: ='Consolidated Balance Sheet'!F23 -> 3213.79 | G25: ='Consolidated Balance Sheet'!G23 -> 3531.13 | H25: =AVERAGE(C25,D25,E25,F25,G25) -> 3020.632
B26: Gross Debt | C26: ='Consolidated Balance Sheet'!C17+'Consolidated Balance Sheet'!C23 -> 29814.58 | D26: ='Consolidated Balance Sheet'!D17+'Consolidated Balance Sheet'!D23 -> 34198.84 | E26: ='Consolidated Balance Sheet'!E17+'Consolidated Balance Sheet'!E23 -> 37008.87 | F26: ='Consolidated Balance Sheet'!F17+'Consolidated Balance Sheet'!F23 -> 40206.08 | G26: ='Consolidated Balance Sheet'!G17+'Consolidated Balance Sheet'!G23 -> 48898.45 | H26: =AVERAGE(C26,D26,E26,F26,G26) -> 38025.364
B27: Cash & Equivalents | C27: ='Consolidated Balance Sheet'!C45 -> 1492.57 | D27: ='Consolidated Balance Sheet'!D45 -> 1704.14 | E27: ='Consolidated Balance Sheet'!E45 -> 2228.14 | F27: ='Consolidated Balance Sheet'!F45 -> 3618.68 | G27: ='Consolidated Balance Sheet'!G45 -> 3947.34 | H27: =AVERAGE(C27,D27,E27,F27,G27) -> 2598.174
B28: Net Debt | C28: ='Consolidated Balance Sheet'!C17+'Consolidated Balance Sheet'!C23-'Consolidated Balance Sheet'!C45 -> 28322.01 | D28: ='Consolidated Balance Sheet'!D17+'Consolidated Balance Sheet'!D23-'Consolidated Balance Sheet'!D45 -> 32494.7 | E28: ='Consolidated Balance Sheet'!E17+'Consolidated Balance Sheet'!E23-'Consolidated Balance Sheet'!E45 -> 34780.73 | F28: ='Consolidated Balance Sheet'!F17+'Consolidated Balance Sheet'!F23-'Consolidated Balance Sheet'!F45 -> 36587.4 | G28: ='Consolidated Balance Sheet'!G17+'Consolidated Balance Sheet'!G23-'Consolidated Balance Sheet'!G45 -> 44951.11 | H28: =AVERAGE(C28,D28,E28,F28,G28) -> 35427.19
B29: Total Assets | C29: ='Consolidated Balance Sheet'!C49 -> 47464.11 | D29: ='Consolidated Balance Sheet'!D49 -> 53931.75 | E29: ='Consolidated Balance Sheet'!E49 -> 58578.81 | F29: ='Consolidated Balance Sheet'!F49 -> 73960.1 | G29: ='Consolidated Balance Sheet'!G49 -> 92834.92 | H29: =AVERAGE(C29,D29,E29,F29,G29) -> 65353.938
B30: Fixed Assets | C30: ='Consolidated Balance Sheet'!C35 -> 34733.64 | D30: ='Consolidated Balance Sheet'!D35 -> 38247.29 | E30: ='Consolidated Balance Sheet'!E35 -> 41324.14 | F30: ='Consolidated Balance Sheet'!F35 -> 44658.7 | G30: ='Consolidated Balance Sheet'!G35 -> 48259.25 | H30: =AVERAGE(C30,D30,E30,F30,G30) -> 41444.604
B32: Return Ratios
B33: RoE: PAT / Equity (%) | C33: ='Consolidated Profit & Loss'!C36/('Consolidated Balance Sheet'!C13+'Consolidated Balance Sheet'!C15) -> 0.15150707 | D33: ='Consolidated Profit & Loss'!D36/('Consolidated Balance Sheet'!D13+'Consolidated Balance Sheet'!D15) -> 0.098458541 | E33: ='Consolidated Profit & Loss'!E36/('Consolidated Balance Sheet'!E13+'Consolidated Balance Sheet'!E15) -> 0.082994177 | F33: ='Consolidated Profit & Loss'!F36/('Consolidated Balance Sheet'!F13+'Consolidated Balance Sheet'!F15) -> 0.046063101 | G33: ='Consolidated Profit & Loss'!G36/('Consolidated Balance Sheet'!G13+'Consolidated Balance Sheet'!G15) -> 0.086050327 | H33: =AVERAGE(C33,D33,E33,F33,G33) -> 0.093014644
B34: RoA: PAT / Total Assets (%) | C34: ='Consolidated Profit & Loss'!C36/'Consolidated Balance Sheet'!C49 -> 0.025379387 | D34: ='Consolidated Profit & Loss'!D36/'Consolidated Balance Sheet'!D49 -> 0.023294812 | E34: ='Consolidated Profit & Loss'!E36/'Consolidated Balance Sheet'!E49 -> 0.019414529 | F34: ='Consolidated Profit & Loss'!F36/'Consolidated Balance Sheet'!F49 -> 0.014331646 | G34: ='Consolidated Profit & Loss'!G36/'Consolidated Balance Sheet'!G49 -> 0.024587084 | H34: =AVERAGE(C34,D34,E34,F34,G34) -> 0.021401492
B35: RoCE: EBIT / Capital Employed (%) | C35: =('Consolidated Profit & Loss'!C24+'Consolidated Profit & Loss'!C20)/('Consolidated Balance Sheet'!C49-'Consolidated Balance Sheet'!C27) -> 0.081446952 | D35: =('Consolidated Profit & Loss'!D24+'Consolidated Profit & Loss'!D20)/('Consolidated Balance Sheet'!D49-'Consolidated Balance Sheet'!D27) -> 0.073700305 | E35: =('Consolidated Profit & Loss'!E24+'Consolidated Profit & Loss'!E20)/('Consolidated Balance Sheet'!E49-'Consolidated Balance Sheet'!E27) -> 0.099008487 | F35: =('Consolidated Profit & Loss'!F24+'Consolidated Profit & Loss'!F20)/('Consolidated Balance Sheet'!F49-'Consolidated Balance Sheet'!F27) -> 0.11229848 | G35: =('Consolidated Profit & Loss'!G24+'Consolidated Profit & Loss'!G20)/('Consolidated Balance Sheet'!G49-'Consolidated Balance Sheet'!G27) -> 0.10150896 | H35: =AVERAGE(C35,D35,E35,F35,G35) -> 0.093592636
B37: Leverage & Coverage Ratios
B38: Gross Debt / Equity (x) | C38: =('Consolidated Balance Sheet'!C17+'Consolidated Balance Sheet'!C23)/('Consolidated Balance Sheet'!C13+'Consolidated Balance Sheet'!C15) -> 3.7498607 | D38: =('Consolidated Balance Sheet'!D17+'Consolidated Balance Sheet'!D23)/('Consolidated Balance Sheet'!D13+'Consolidated Balance Sheet'!D15) -> 2.680162 | E38: =('Consolidated Balance Sheet'!E17+'Consolidated Balance Sheet'!E23)/('Consolidated Balance Sheet'!E13+'Consolidated Balance Sheet'!E15) -> 2.7007603 | F38: =('Consolidated Balance Sheet'!F17+'Consolidated Balance Sheet'!F23)/('Consolidated Balance Sheet'!F13+'Consolidated Balance Sheet'!F15) -> 1.747235 | G38: =('Consolidated Balance Sheet'!G17+'Consolidated Balance Sheet'!G23)/('Consolidated Balance Sheet'!G13+'Consolidated Balance Sheet'!G15) -> 1.8434409 | H38: =AVERAGE(C38,D38,E38,F38,G38) -> 2.5442918
B39: Net Debt / Equity (x) | C39: =('Consolidated Balance Sheet'!C17+'Consolidated Balance Sheet'!C23-'Consolidated Balance Sheet'!C45)/('Consolidated Balance Sheet'!C13+'Consolidated Balance Sheet'!C15) -> 3.5621361 | D39: =('Consolidated Balance Sheet'!D17+'Consolidated Balance Sheet'!D23-'Consolidated Balance Sheet'!D45)/('Consolidated Balance Sheet'!D13+'Consolidated Balance Sheet'!D15) -> 2.5466086 | E39: =('Consolidated Balance Sheet'!E17+'Consolidated Balance Sheet'!E23-'Consolidated Balance Sheet'!E45)/('Consolidated Balance Sheet'!E13+'Consolidated Balance Sheet'!E15) -> 2.5381595 | F39: =('Consolidated Balance Sheet'!F17+'Consolidated Balance Sheet'!F23-'Consolidated Balance Sheet'!F45)/('Consolidated Balance Sheet'!F13+'Consolidated Balance Sheet'!F15) -> 1.5899781 | G39: =('Consolidated Balance Sheet'!G17+'Consolidated Balance Sheet'!G23-'Consolidated Balance Sheet'!G45)/('Consolidated Balance Sheet'!G13+'Consolidated Balance Sheet'!G15) -> 1.6946287 | H39: =AVERAGE(C39,D39,E39,F39,G39) -> 2.3863022
B40: Net Debt / EBITDA (x) | C40: =('Consolidated Balance Sheet'!C17+'Consolidated Balance Sheet'!C23-'Consolidated Balance Sheet'!C45)/('Consolidated Profit & Loss'!C24+'Consolidated Profit & Loss'!C20+'Consolidated Profit & Loss'!C21) -> 5.8880049 | D40: =('Consolidated Balance Sheet'!D17+'Consolidated Balance Sheet'!D23-'Consolidated Balance Sheet'!D45)/('Consolidated Profit & Loss'!D24+'Consolidated Profit & Loss'!D20+'Consolidated Profit & Loss'!D21) -> 6.4150947 | E40: =('Consolidated Balance Sheet'!E17+'Consolidated Balance Sheet'!E23-'Consolidated Balance Sheet'!E45)/('Consolidated Profit & Loss'!E24+'Consolidated Profit & Loss'!E20+'Consolidated Profit & Loss'!E21) -> 5.1282674 | F40: =('Consolidated Balance Sheet'!F17+'Consolidated Balance Sheet'!F23-'Consolidated Balance Sheet'!F45)/('Consolidated Profit & Loss'!F24+'Consolidated Profit & Loss'!F20+'Consolidated Profit & Loss'!F21) -> 4.026465 | G40: =('Consolidated Balance Sheet'!G17+'Consolidated Balance Sheet'!G23-'Consolidated Balance Sheet'!G45)/('Consolidated Profit & Loss'!G24+'Consolidated Profit & Loss'!G20+'Consolidated Profit & Loss'!G21) -> 4.576793 | H40: =AVERAGE(C40,D40,E40,F40,G40) -> 5.206925
B41: Interest Coverage: EBIT / Finance (x) | C41: =('Consolidated Profit & Loss'!C24+'Consolidated Profit & Loss'!C20)/'Consolidated Profit & Loss'!C20 -> 1.4304615 | D41: =('Consolidated Profit & Loss'!D24+'Consolidated Profit & Loss'!D20)/'Consolidated Profit & Loss'!D20 -> 1.2430873 | E41: =('Consolidated Profit & Loss'!E24+'Consolidated Profit & Loss'!E20)/'Consolidated Profit & Loss'!E20 -> 1.809529 | F41: =('Consolidated Profit & Loss'!F24+'Consolidated Profit & Loss'!F20)/'Consolidated Profit & Loss'!F20 -> 2.203261 | G41: =('Consolidated Profit & Loss'!G24+'Consolidated Profit & Loss'!G20)/'Consolidated Profit & Loss'!G20 -> 2.1589639 | H41: =AVERAGE(C41,D41,E41,F41,G41) -> 1.7690605
B42: Gross Debt / Total Assets (%) | C42: =('Consolidated Balance Sheet'!C17+'Consolidated Balance Sheet'!C23)/'Consolidated Balance Sheet'!C49 -> 0.62814999 | D42: =('Consolidated Balance Sheet'!D17+'Consolidated Balance Sheet'!D23)/'Consolidated Balance Sheet'!D49 -> 0.6341133 | E42: =('Consolidated Balance Sheet'!E17+'Consolidated Balance Sheet'!E23)/'Consolidated Balance Sheet'!E49 -> 0.63177914 | F42: =('Consolidated Balance Sheet'!F17+'Consolidated Balance Sheet'!F23)/'Consolidated Balance Sheet'!F49 -> 0.54361852 | G42: =('Consolidated Balance Sheet'!G17+'Consolidated Balance Sheet'!G23)/'Consolidated Balance Sheet'!G49 -> 0.52672475 | H42: =AVERAGE(C42,D42,E42,F42,G42) -> 0.59287714
B44: Asset & Efficiency Ratios
B45: Asset Turnover: Revenue / Total Assets (x) | C45: ='Consolidated Profit & Loss'!C9/'Consolidated Balance Sheet'!C49 -> 0.23091574 | D45: ='Consolidated Profit & Loss'!D9/'Consolidated Balance Sheet'!D49 -> 0.24095491 | E45: ='Consolidated Profit & Loss'!E9/'Consolidated Balance Sheet'!E49 -> 0.27919669 | F45: ='Consolidated Profit & Loss'!F9/'Consolidated Balance Sheet'!F49 -> 0.31836287 | G45: ='Consolidated Profit & Loss'!G9/'Consolidated Balance Sheet'!G49 -> 0.29302153 | H45: =AVERAGE(C45,D45,E45,F45,G45) -> 0.27249035
B46: Fixed Asset Turnover (x) | C46: ='Consolidated Profit & Loss'!C9/'Consolidated Balance Sheet'!C35 -> 0.31555028 | D46: ='Consolidated Profit & Loss'!D9/'Consolidated Balance Sheet'!D35 -> 0.33976577 | E46: ='Consolidated Profit & Loss'!E9/'Consolidated Balance Sheet'!E35 -> 0.39577375 | F46: ='Consolidated Profit & Loss'!F9/'Consolidated Balance Sheet'!F35 -> 0.52724665 | G46: ='Consolidated Profit & Loss'!G9/'Consolidated Balance Sheet'!G35 -> 0.56367702 | H46: =AVERAGE(C46,D46,E46,F46,G46) -> 0.4284027
B48: Growth Ratios
B49: Revenue Growth YoY (%) | D49: ='Consolidated Profit & Loss'!D9/'Consolidated Profit & Loss'!C9-1 -> 0.18566341 | E49: ='Consolidated Profit & Loss'!E9/'Consolidated Profit & Loss'!D9-1 -> 0.25855013 | F49: ='Consolidated Profit & Loss'!F9/'Consolidated Profit & Loss'!E9-1 -> 0.43969035 | G49: ='Consolidated Profit & Loss'!G9/'Consolidated Profit & Loss'!F9-1 -> 0.15528993 | H49: =AVERAGE(D49,E49,F49,G49) -> 0.25979846
B50: EBITDA Growth YoY (%) | D50: =('Consolidated Profit & Loss'!D24+'Consolidated Profit & Loss'!D20+'Consolidated Profit & Loss'!D21)/('Consolidated Profit & Loss'!C24+'Consolidated Profit & Loss'!C20+'Consolidated Profit & Loss'!C21)-1 -> 0.053061046 | E50: =('Consolidated Profit & Loss'!E24+'Consolidated Profit & Loss'!E20+'Consolidated Profit & Loss'!E21)/('Consolidated Profit & Loss'!D24+'Consolidated Profit & Loss'!D20+'Consolidated Profit & Loss'!D21)-1 -> 0.33893216 | F50: =('Consolidated Profit & Loss'!F24+'Consolidated Profit & Loss'!F20+'Consolidated Profit & Loss'!F21)/('Consolidated Profit & Loss'!E24+'Consolidated Profit & Loss'!E20+'Consolidated Profit & Loss'!E21)-1 -> 0.33979883 | G50: =('Consolidated Profit & Loss'!G24+'Consolidated Profit & Loss'!G20+'Consolidated Profit & Loss'!G21)/('Consolidated Profit & Loss'!F24+'Consolidated Profit & Loss'!F20+'Consolidated Profit & Loss'!F21)-1 -> 0.080865174 | H50: =AVERAGE(D50,E50,F50,G50) -> 0.2031643
B51: PAT Growth YoY (%) | D51: ='Consolidated Profit & Loss'!D36/'Consolidated Profit & Loss'!C36-1 -> 0.042935058 | E51: ='Consolidated Profit & Loss'!E36/'Consolidated Profit & Loss'!D36-1 -> -0.094760135 | F51: ='Consolidated Profit & Loss'!F36/'Consolidated Profit & Loss'!E36-1 -> -0.067977983 | G51: ='Consolidated Profit & Loss'!G36/'Consolidated Profit & Loss'!F36-1 -> 1.1534006 | H51: =AVERAGE(D51,E51,F51,G51) -> 0.25839938
B53: Per Share Data
B54: Basic EPS (₹) | C54: ='Consolidated Profit & Loss'!C39 -> 9 | D54: ='Consolidated Profit & Loss'!D39 -> 11 | E54: ='Consolidated Profit & Loss'!E39 -> 10 | F54: ='Consolidated Profit & Loss'!F39 -> 9 | G54: ='Consolidated Profit & Loss'!G39 -> 19 | H54: =AVERAGE(C54,D54,E54,F54,G54) -> 11.6
B55: Book Value per Share (₹) | C55: =IF('Consolidated Profit & Loss'!C39<>0,'Consolidated Balance Sheet'!C13/('Consolidated Profit & Loss'!C36/'Consolidated Profit & Loss'!C39),0) -> 51.231959 | D55: =IF('Consolidated Profit & Loss'!D39<>0,'Consolidated Balance Sheet'!D13/('Consolidated Profit & Loss'!D36/'Consolidated Profit & Loss'!D39),0) -> 102.11237 | E55: =IF('Consolidated Profit & Loss'!E39<>0,'Consolidated Balance Sheet'!E13/('Consolidated Profit & Loss'!E36/'Consolidated Profit & Loss'!E39),0) -> 111.156 | F55: =IF('Consolidated Profit & Loss'!F39<>0,'Consolidated Balance Sheet'!F13/('Consolidated Profit & Loss'!F36/'Consolidated Profit & Loss'!F39),0) -> 187.37681 | G55: =IF('Consolidated Profit & Loss'!G39<>0,'Consolidated Balance Sheet'!G13/('Consolidated Profit & Loss'!G36/'Consolidated Profit & Loss'!G39),0) -> 211.66037 | H55: =AVERAGE(C55,D55,E55,F55,G55) -> 132.7075
B56: Net Debt per Share (₹) | C56: =IF('Consolidated Profit & Loss'!C39<>0,('Consolidated Balance Sheet'!C17+'Consolidated Balance Sheet'!C23-'Consolidated Balance Sheet'!C45)/('Consolidated Profit & Loss'!C36/'Consolidated Profit & Loss'!C39),0) -> 211.60217 | D56: =IF('Consolidated Profit & Loss'!D39<>0,('Consolidated Balance Sheet'!D17+'Consolidated Balance Sheet'!D23-'Consolidated Balance Sheet'!D45)/('Consolidated Profit & Loss'!D36/'Consolidated Profit & Loss'!D39),0) -> 284.51259 | E56: =IF('Consolidated Profit & Loss'!E39<>0,('Consolidated Balance Sheet'!E17+'Consolidated Balance Sheet'!E23-'Consolidated Balance Sheet'!E45)/('Consolidated Profit & Loss'!E36/'Consolidated Profit & Loss'!E39),0) -> 305.82381 | F56: =IF('Consolidated Profit & Loss'!F39<>0,('Consolidated Balance Sheet'!F17+'Consolidated Balance Sheet'!F23-'Consolidated Balance Sheet'!F45)/('Consolidated Profit & Loss'!F36/'Consolidated Profit & Loss'!F39),0) -> 310.65653 | G56: =IF('Consolidated Profit & Loss'!G39<>0,('Consolidated Balance Sheet'!G17+'Consolidated Balance Sheet'!G23-'Consolidated Balance Sheet'!G45)/('Consolidated Profit & Loss'!G36/'Consolidated Profit & Loss'!G39),0) -> 374.17574 | H56: =AVERAGE(C56,D56,E56,F56,G56) -> 297.35417

Sheet Assumption
B1: Adani Energy Solutions Ltd.
B3: Particulars | C3: 44621 | D3: 44986 | E3: 45352 | F3: 45717 | G3: Mar-26
B4: Revenue from operations | C4: ='Consolidated Profit & Loss'!C11 -> 11257.52 | D4: ='Consolidated Profit & Loss'!D11 -> 13292.72 | E4: ='Consolidated Profit & Loss'!E11 -> 16607.36 | F4: ='Consolidated Profit & Loss'!F11 -> 23767.09 | G4: ='Consolidated Profit & Loss'!G11 -> 27588.03 | I4: Median of Revenue Growth
B5: Revenue growth in % | D5: =(D4/C4)-1 -> 0.18078582 | E5: =(E4/D4)-1 -> 0.24935754 | F5: =(F4/E4)-1 -> 0.43111789 | G5: =(G4/F4)-1 -> 0.160766 | I5: =MEDIAN(D5:G5) -> 0.21507168
B6: Less: Cost of Power Purchased | C6: ='Consolidated Profit & Loss'!C16 -> 2778.88 | D6: ='Consolidated Profit & Loss'!D16 -> 3839.98 | E6: ='Consolidated Profit & Loss'!E16 -> 4340.3 | F6: ='Consolidated Profit & Loss'!F16 -> 5584.14 | G6: ='Consolidated Profit & Loss'!G16 -> 6347.88
B7: Less: Employee Benefit Expenses | C7: ='Consolidated Profit & Loss'!C19 -> 885.07 | D7: ='Consolidated Profit & Loss'!D19 -> 986.65 | E7: ='Consolidated Profit & Loss'!E19 -> 951.7 | F7: ='Consolidated Profit & Loss'!F19 -> 1032.94 | G7: ='Consolidated Profit & Loss'!G19 -> 1092.64
B8: Less: Cost Of Fuel | C8: ='Consolidated Profit & Loss'!C17 -> 1065.99 | D8: ='Consolidated Profit & Loss'!D17 -> 1384.18 | E8: ='Consolidated Profit & Loss'!E17 -> 1119.09 | F8: ='Consolidated Profit & Loss'!F17 -> 623.54 | G8: ='Consolidated Profit & Loss'!G17 -> 0
B9: Less: Other Expenses | C9: ='Consolidated Profit & Loss'!C22 -> 1500.18 | D9: ='Consolidated Profit & Loss'!D22 -> 1809.17 | E9: ='Consolidated Profit & Loss'!E22 -> 2996.11 | F9: ='Consolidated Profit & Loss'!F22 -> 6753.46 | G9: ='Consolidated Profit & Loss'!G22 -> 2923.62
B10: Less: Purchase Of Stock-In Trade | C10: ='Consolidated Profit & Loss'!C15 -> 821.23 | D10: ='Consolidated Profit & Loss'!D15 -> 755.13 | E10: ='Consolidated Profit & Loss'!E15 -> 1028.95 | F10: ='Consolidated Profit & Loss'!F15 -> 1365.74 | G10: ='Consolidated Profit & Loss'!G15 -> 1004.14
B11: Total Expenses | C11: =C6+C7+C8+C9+C10 -> 7051.35 | D11: =D6+D7+D8+D9+D10 -> 8775.11 | E11: =E6+E7+E8+E9+E10 -> 10436.15 | F11: =F6+F7+F8+F9+F10 -> 15359.82 | G11: =G6+G7+G8+G9+G10 -> 11368.28
B12: EBITDA | C12: =C4-C11 -> 4206.17 | D12: =D4-D11 -> 4517.61 | E12: =E4-E11 -> 6171.21 | F12: =F4-F11 -> 8407.27 | G12: =G4-G11 -> 16219.75
B13: Less: Depreciation And Amortization | C13: ='Consolidated Profit & Loss'!C21 -> 1427.15 | D13: ='Consolidated Profit & Loss'!D21 -> 1607.74 | E13: ='Consolidated Profit & Loss'!E21 -> 1776.08 | F13: ='Consolidated Profit & Loss'!F21 -> 1905.95 | G13: ='Consolidated Profit & Loss'!G21 -> 1978.23
B14: EBIT | C14: =C12-C13 -> 2779.02 | D14: =D12-D13 -> 2909.87 | E14: =E12-E13 -> 4395.13 | F14: =F12-F13 -> 6501.32 | G14: =G12-G13 -> 14241.52
B15: ADD: Other Income / Non-Operating Income | C15: ='Consolidated Profit & Loss'!C12 -> 603.95 | D15: ='Consolidated Profit & Loss'!D12 -> 547.74 | E15: ='Consolidated Profit & Loss'!E12 -> 610.95 | F15: ='Consolidated Profit & Loss'!F12 -> 679.46 | G15: ='Consolidated Profit & Loss'!G12 -> 737.13
B16: Less: Finance Costs / Interest Expenses | C16: ='Consolidated Profit & Loss'!C20 -> 2364.95 | D16: ='Consolidated Profit & Loss'!D20 -> 2781.47 | E16: ='Consolidated Profit & Loss'!E20 -> 2766.51 | F16: ='Consolidated Profit & Loss'!F20 -> 3259.16 | G16: ='Consolidated Profit & Loss'!G20 -> 3632.9
B17: PBT | C17: =C14+C15-C16 -> 1018.02 | D17: =D14+D15-D16 -> 676.14 | E17: =E14+E15-E16 -> 2239.57 | F17: =F14+F15-F16 -> 3921.62 | G17: =G14+G15-G16 -> 11345.75
B18: Less: Total Tax Expenses | C18: ='Consolidated Profit & Loss'!C30 -> 436.06 | D18: ='Consolidated Profit & Loss'!D30 -> 435.33 | E18: ='Consolidated Profit & Loss'!E30 -> 580.13 | F18: ='Consolidated Profit & Loss'!F30 -> 178.99 | G18: ='Consolidated Profit & Loss'!G30 -> 771.71
B19: Tax Rate | C19: =C18/C17 -> 0.42834129 | D19: =D18/D17 -> 0.64384595 | E19: =E18/E17 -> 0.25903633 | F19: =F18/F17 -> 0.045641852 | G19: =G18/G17 -> 0.06801754
B20: Less: Minority Interest | C20: =-'Consolidated Profit & Loss'!C35 -> 31.14 | D20: =-'Consolidated Profit & Loss'!D35 -> 24.27 | E20: =-'Consolidated Profit & Loss'!E35 -> 58.33 | F20: =-'Consolidated Profit & Loss'!F35 -> -138.28 | G20: =-'Consolidated Profit & Loss'!G35 -> 110.21
B21: Net Profit - PAT | C21: =C17-C18-C20 -> 550.82 | D21: =D17-D18-D20 -> 216.54 | E21: =E17-E18-E20 -> 1601.11 | F21: =F17-F18-F20 -> 3880.91 | G21: =G17-G18-G20 -> 10463.83
B23: Historical Growth
B24: Average Growth | C24: =AVERAGE(D5:G5) -> 0.25550681
B25: CAGR | C25: =(G4/C4)^(1/4)-1 -> 0.25117913 | D25: =_xlfn.RRI(4,C4,G4) -> 0.25117913 | E25: RRI
B27: Margins
B28: EBITDA | C28: =C12/C4 -> 0.37363203 | D28: =D12/D4 -> 0.33985595 | E28: =E12/E4 -> 0.37159488 | F28: =F12/F4 -> 0.35373577 | G28: =G12/G4 -> 0.58792708
B29: EBIT | C29: =C14/C4 -> 0.24685899 | D29: =D14/D4 -> 0.21890704 | E29: =E14/E4 -> 0.26464953 | F29: =F14/F4 -> 0.27354295 | G29: =G14/G4 -> 0.51622098
B30: EBT | C30: =C17/C4 -> 0.090430219 | D30: =D17/D4 -> 0.050865436 | E30: =E17/E4 -> 0.13485406 | F30: =F17/F4 -> 0.16500211 | G30: =G17/G4 -> 0.41125626
B31: Net Profit | C31: =C21/C4 -> 0.048929071 | D31: =D21/D4 -> 0.01629012 | E31: =E21/E4 -> 0.096409664 | F31: =F21/F4 -> 0.16328924 | G31: =G21/G4 -> 0.37928877
B33: Tax Rate
B34: Effective tax rate | C34: =C18/C17 -> 0.42834129 | D34: =D18/D17 -> 0.64384595 | E34: =E18/E17 -> 0.25903633 | F34: =F18/F17 -> 0.045641852 | G34: =G18/G17 -> 0.06801754
B35: Marginal Tax rate | C35: 0.25 | D35: 0.25 | E35: 0.25 | F35: 0.25 | G35: 0.25
B37: Return On Capital
B38: EBIT*(1-T) | C38: =C14*(1-C35) -> 2084.265 | D38: =D14*(1-D35) -> 2182.4025 | E38: =E14*(1-E35) -> 3296.3475 | F38: =F14*(1-F35) -> 4875.99 | G38: =G14*(1-G35) -> 10681.14
B39: Book Equity | C39: ='Consolidated Balance Sheet'!C13 -> 6857.17 | D39: ='Consolidated Balance Sheet'!D13 -> 11662.44 | E39: ='Consolidated Balance Sheet'!E13 -> 12641.55 | F39: ='Consolidated Balance Sheet'!F13 -> 22068.2 | G39: ='Consolidated Balance Sheet'!G13 -> 25427.54
B40: Book Debt | C40: ='Consolidated Balance Sheet'!C17+'Consolidated Balance Sheet'!C23 -> 29814.58 | D40: ='Consolidated Balance Sheet'!D17+'Consolidated Balance Sheet'!D23 -> 34198.84 | E40: ='Consolidated Balance Sheet'!E17+'Consolidated Balance Sheet'!E23 -> 37008.87 | F40: ='Consolidated Balance Sheet'!F17+'Consolidated Balance Sheet'!F23 -> 40206.08 | G40: ='Consolidated Balance Sheet'!G17+'Consolidated Balance Sheet'!G23 -> 48898.45
B41: Cash and Cash Equivalents | C41: ='Consolidated Balance Sheet'!C45 -> 1492.57 | D41: ='Consolidated Balance Sheet'!D45 -> 1704.14 | E41: ='Consolidated Balance Sheet'!E45 -> 2228.14 | F41: ='Consolidated Balance Sheet'!F45 -> 3618.68 | G41: ='Consolidated Balance Sheet'!G45 -> 3947.34
B42: Capital Employed | C42: =C39+C40+C41 -> 38164.32 | D42: =D39+D40+D41 -> 47565.42 | E42: =E39+E40+E41 -> 51878.56 | F42: =F39+F40+F41 -> 65892.96 | G42: =G39+G40+G41 -> 78273.33
B44: Pre-Tax Return on Capital | C44: =C14/C42 -> 0.072817228 | D44: =D14/D42 -> 0.061176165 | E44: =E14/E42 -> 0.084719584 | F44: =F14/F42 -> 0.098664865 | G44: =G14/G42 -> 0.18194601
B45: Post Tax Return on Capital | C45: =C38/C42 -> 0.054612921 | D45: =D38/D42 -> 0.045882124 | E45: =E38/E42 -> 0.063539688 | F45: =F38/F42 -> 0.073998649 | G45: =G38/G42 -> 0.13645951
B47: Growth In EBIT | C47: ='Fixed Assets Schedule'!C29*Assumption!G45 -> 0.030537193

Sheet Historical FS
B1: Historical Financial Statement
B3: Years | C3: 2022 | D3: 2023 | E3: 2024 | F3: 2025 | G3: 2026
B4: Income statement
B5: Revenue from Operations | C5: ='Consolidated Profit & Loss'!C9 -> 10960.21 | D5: ='Consolidated Profit & Loss'!D9 -> 12995.12 | E5: ='Consolidated Profit & Loss'!E9 -> 16355.01 | F5: ='Consolidated Profit & Loss'!F9 -> 23546.15 | G5: ='Consolidated Profit & Loss'!G9 -> 27202.63
B6: Revenue Growth | D6: ='Consolidated Profit & Loss'!D9/'Consolidated Profit & Loss'!C9-1 -> 0.18566341 | E6: ='Consolidated Profit & Loss'!E9/'Consolidated Profit & Loss'!D9-1 -> 0.25855013 | F6: ='Consolidated Profit & Loss'!F9/'Consolidated Profit & Loss'!E9-1 -> 0.43969035 | G6: ='Consolidated Profit & Loss'!G9/'Consolidated Profit & Loss'!F9-1 -> 0.15528993
B8: Total Operating Expenses (ex Finance & Depr) | C8: ='Consolidated Profit & Loss'!C23-'Consolidated Profit & Loss'!C20-'Consolidated Profit & Loss'!C21 -> 7051.35 | D8: ='Consolidated Profit & Loss'!D23-'Consolidated Profit & Loss'!D20-'Consolidated Profit & Loss'!D21 -> 8775.11 | E8: ='Consolidated Profit & Loss'!E23-'Consolidated Profit & Loss'!E20-'Consolidated Profit & Loss'!E21 -> 10436.15 | F8: ='Consolidated Profit & Loss'!F23-'Consolidated Profit & Loss'!F20-'Consolidated Profit & Loss'!F21 -> 15359.82 | G8: ='Consolidated Profit & Loss'!G23-'Consolidated Profit & Loss'!G20-'Consolidated Profit & Loss'!G21 -> 18503.63
B9: Opex % Revenue | C9: =('Consolidated Profit & Loss'!C23-'Consolidated Profit & Loss'!C20-'Consolidated Profit & Loss'!C21)/'Consolidated Profit & Loss'!C9 -> 0.64335902 | D9: =('Consolidated Profit & Loss'!D23-'Consolidated Profit & Loss'!D20-'Consolidated Profit & Loss'!D21)/'Consolidated Profit & Loss'!D9 -> 0.67526194 | E9: =('Consolidated Profit & Loss'!E23-'Consolidated Profit & Loss'!E20-'Consolidated Profit & Loss'!E21)/'Consolidated Profit & Loss'!E9 -> 0.63810111 | F9: =('Consolidated Profit & Loss'!F23-'Consolidated Profit & Loss'!F20-'Consolidated Profit & Loss'!F21)/'Consolidated Profit & Loss'!F9 -> 0.6523283 | G9: =('Consolidated Profit & Loss'!G23-'Consolidated Profit & Loss'!G20-'Consolidated Profit & Loss'!G21)/'Consolidated Profit & Loss'!G9 -> 0.68021474
B11: EBITDA | C11: ='Consolidated Profit & Loss'!C24+'Consolidated Profit & Loss'!C20+'Consolidated Profit & Loss'!C21 -> 4810.12 | D11: ='Consolidated Profit & Loss'!D24+'Consolidated Profit & Loss'!D20+'Consolidated Profit & Loss'!D21 -> 5065.35 | E11: ='Consolidated Profit & Loss'!E24+'Consolidated Profit & Loss'!E20+'Consolidated Profit & Loss'!E21 -> 6782.16 | F11: ='Consolidated Profit & Loss'!F24+'Consolidated Profit & Loss'!F20+'Consolidated Profit & Loss'!F21 -> 9086.73 | G11: ='Consolidated Profit & Loss'!G24+'Consolidated Profit & Loss'!G20+'Consolidated Profit & Loss'!G21 -> 9821.53
B12: EBITDA Margins | C12: =('Consolidated Profit & Loss'!C24+'Consolidated Profit & Loss'!C20+'Consolidated Profit & Loss'!C21)/'Consolidated Profit & Loss'!C9 -> 0.43887115 | D12: =('Consolidated Profit & Loss'!D24+'Consolidated Profit & Loss'!D20+'Consolidated Profit & Loss'!D21)/'Consolidated Profit & Loss'!D9 -> 0.38978863 | E12: =('Consolidated Profit & Loss'!E24+'Consolidated Profit & Loss'!E20+'Consolidated Profit & Loss'!E21)/'Consolidated Profit & Loss'!E9 -> 0.41468394 | F12: =('Consolidated Profit & Loss'!F24+'Consolidated Profit & Loss'!F20+'Consolidated Profit & Loss'!F21)/'Consolidated Profit & Loss'!F9 -> 0.3859115 | G12: =('Consolidated Profit & Loss'!G24+'Consolidated Profit & Loss'!G20+'Consolidated Profit & Loss'!G21)/'Consolidated Profit & Loss'!G9 -> 0.36105075
B14: Depreciation & Amortisation | C14: ='Consolidated Profit & Loss'!C21 -> 1427.15 | D14: ='Consolidated Profit & Loss'!D21 -> 1607.74 | E14: ='Consolidated Profit & Loss'!E21 -> 1776.08 | F14: ='Consolidated Profit & Loss'!F21 -> 1905.95 | G14: ='Consolidated Profit & Loss'!G21 -> 1978.23
B15: Depreciation % of Sales | C15: ='Consolidated Profit & Loss'!C21/'Consolidated Profit & Loss'!C9 -> 0.13021192 | D15: ='Consolidated Profit & Loss'!D21/'Consolidated Profit & Loss'!D9 -> 0.12371875 | E15: ='Consolidated Profit & Loss'!E21/'Consolidated Profit & Loss'!E9 -> 0.10859547 | F15: ='Consolidated Profit & Loss'!F21/'Consolidated Profit & Loss'!F9 -> 0.080945293 | G15: ='Consolidated Profit & Loss'!G21/'Consolidated Profit & Loss'!G9 -> 0.072722013
B17: EBIT | C17: ='Consolidated Profit & Loss'!C24+'Consolidated Profit & Loss'!C20 -> 3382.97 | D17: ='Consolidated Profit & Loss'!D24+'Consolidated Profit & Loss'!D20 -> 3457.61 | E17: ='Consolidated Profit & Loss'!E24+'Consolidated Profit & Loss'!E20 -> 5006.08 | F17: ='Consolidated Profit & Loss'!F24+'Consolidated Profit & Loss'!F20 -> 7180.78 | G17: ='Consolidated Profit & Loss'!G24+'Consolidated Profit & Loss'!G20 -> 7843.3
B18: EBIT Margin | C18: =('Consolidated Profit & Loss'!C24+'Consolidated Profit & Loss'!C20)/'Consolidated Profit & Loss'!C9 -> 0.30865923 | D18: =('Consolidated Profit & Loss'!D24+'Consolidated Profit & Loss'!D20)/'Consolidated Profit & Loss'!D9 -> 0.26606988 | E18: =('Consolidated Profit & Loss'!E24+'Consolidated Profit & Loss'!E20)/'Consolidated Profit & Loss'!E9 -> 0.30608847 | F18: =('Consolidated Profit & Loss'!F24+'Consolidated Profit & Loss'!F20)/'Consolidated Profit & Loss'!F9 -> 0.3049662 | G18: =('Consolidated Profit & Loss'!G24+'Consolidated Profit & Loss'!G20)/'Consolidated Profit & Loss'!G9 -> 0.28832874
B20: Finance Costs | C20: ='Consolidated Profit & Loss'!C20 -> 2364.95 | D20: ='Consolidated Profit & Loss'!D20 -> 2781.47 | E20: ='Consolidated Profit & Loss'!E20 -> 2766.51 | F20: ='Consolidated Profit & Loss'!F20 -> 3259.16 | G20: ='Consolidated Profit & Loss'!G20 -> 3632.9
B21: Finance Costs % of Sales | C21: ='Consolidated Profit & Loss'!C20/'Consolidated Profit & Loss'!C9 -> 0.21577598 | D21: ='Consolidated Profit & Loss'!D20/'Consolidated Profit & Loss'!D9 -> 0.21403958 | E21: ='Consolidated Profit & Loss'!E20/'Consolidated Profit & Loss'!E9 -> 0.16915367 | F21: ='Consolidated Profit & Loss'!F20/'Consolidated Profit & Loss'!F9 -> 0.13841583 | G21: ='Consolidated Profit & Loss'!G20/'Consolidated Profit & Loss'!G9 -> 0.13354959
B23: Other Income | C23: ='Consolidated Profit & Loss'!C12 -> 603.95 | D23: ='Consolidated Profit & Loss'!D12 -> 547.74 | E23: ='Consolidated Profit & Loss'!E12 -> 610.95 | F23: ='Consolidated Profit & Loss'!F12 -> 679.46 | G23: ='Consolidated Profit & Loss'!G12 -> 737.13
B25: Profit Before Tax | C25: ='Consolidated Profit & Loss'!C24 -> 1018.02 | D25: ='Consolidated Profit & Loss'!D24 -> 676.14 | E25: ='Consolidated Profit & Loss'!E24 -> 2239.57 | F25: ='Consolidated Profit & Loss'!F24 -> 3921.62 | G25: ='Consolidated Profit & Loss'!G24 -> 4210.4
B26: PBT % Sales | C26: ='Consolidated Profit & Loss'!C24/'Consolidated Profit & Loss'!C9 -> 0.092883257 | D26: ='Consolidated Profit & Loss'!D24/'Consolidated Profit & Loss'!D9 -> 0.052030301 | E26: ='Consolidated Profit & Loss'!E24/'Consolidated Profit & Loss'!E9 -> 0.1369348 | F26: ='Consolidated Profit & Loss'!F24/'Consolidated Profit & Loss'!F9 -> 0.16655037 | G26: ='Consolidated Profit & Loss'!G24/'Consolidated Profit & Loss'!G9 -> 0.15477915
B28: Total Tax Expenses | C28: ='Consolidated Profit & Loss'!C30 -> 436.06 | D28: ='Consolidated Profit & Loss'!D30 -> 435.33 | E28: ='Consolidated Profit & Loss'!E30 -> 580.13 | F28: ='Consolidated Profit & Loss'!F30 -> 178.99 | G28: ='Consolidated Profit & Loss'!G30 -> 771.71
B29: Effective Tax Rate | C29: ='Consolidated Profit & Loss'!C30/'Consolidated Profit & Loss'!C26 -> 0.25643197 | D29: ='Consolidated Profit & Loss'!D30/'Consolidated Profit & Loss'!D26 -> 0.25432314 | E29: ='Consolidated Profit & Loss'!E30/'Consolidated Profit & Loss'!E26 -> 0.32599631 | F29: ='Consolidated Profit & Loss'!F30/'Consolidated Profit & Loss'!F26 -> 0.16652556 | G29: ='Consolidated Profit & Loss'!G30/'Consolidated Profit & Loss'!G26 -> 0.24775269
B31: Net Profit | C31: ='Consolidated Profit & Loss'!C36 -> 1204.61 | D31: ='Consolidated Profit & Loss'!D36 -> 1256.33 | E31: ='Consolidated Profit & Loss'!E36 -> 1137.28 | F31: ='Consolidated Profit & Loss'!F36 -> 1059.97 | G31: ='Consolidated Profit & Loss'!G36 -> 2282.54
B32: Net Margins | C32: ='Consolidated Profit & Loss'!C36/'Consolidated Profit & Loss'!C9 -> 0.10990757 | D32: ='Consolidated Profit & Loss'!D36/'Consolidated Profit & Loss'!D9 -> 0.09667706 | E32: ='Consolidated Profit & Loss'!E36/'Consolidated Profit & Loss'!E9 -> 0.069537102 | F32: ='Consolidated Profit & Loss'!F36/'Consolidated Profit & Loss'!F9 -> 0.045016701 | G32: ='Consolidated Profit & Loss'!G36/'Consolidated Profit & Loss'!G9 -> 0.083908799
B34: Basic EPS (₹) | C34: ='Consolidated Profit & Loss'!C39 -> 9 | D34: ='Consolidated Profit & Loss'!D39 -> 11 | E34: ='Consolidated Profit & Loss'!E39 -> 10 | F34: ='Consolidated Profit & Loss'!F39 -> 9 | G34: ='Consolidated Profit & Loss'!G39 -> 19
B35: EPS Growth % | D35: ='Consolidated Profit & Loss'!D39/'Consolidated Profit & Loss'!C39-1 -> 0.22222222 | E35: ='Consolidated Profit & Loss'!E39/'Consolidated Profit & Loss'!D39-1 -> -0.090909091 | F35: ='Consolidated Profit & Loss'!F39/'Consolidated Profit & Loss'!E39-1 -> -0.1 | G35: ='Consolidated Profit & Loss'!G39/'Consolidated Profit & Loss'!F39-1 -> 1.1111111
B38: Balance statement | C38: 2022 | D38: 2023 | E38: 2024 | F38: 2025 | G38: 2026
B39: Equity Share Capital | C39: ='Consolidated Balance Sheet'!C9 -> 1099.81 | D39: ='Consolidated Balance Sheet'!D9 -> 1115.49 | E39: ='Consolidated Balance Sheet'!E9 -> 1115.49 | F39: ='Consolidated Balance Sheet'!F9 -> 1201.28 | G39: ='Consolidated Balance Sheet'!G9 -> 1201.28
B40: Reserves & Surplus | C40: ='Consolidated Balance Sheet'!C11 -> 5757.36 | D40: ='Consolidated Balance Sheet'!D11 -> 10546.95 | E40: ='Consolidated Balance Sheet'!E11 -> 11526.06 | F40: ='Consolidated Balance Sheet'!F11 -> 20866.92 | G40: ='Consolidated Balance Sheet'!G11 -> 24226.26
B41: Total Shareholders Funds | C41: ='Consolidated Balance Sheet'!C13 -> 6857.17 | D41: ='Consolidated Balance Sheet'!D13 -> 11662.44 | E41: ='Consolidated Balance Sheet'!E13 -> 12641.55 | F41: ='Consolidated Balance Sheet'!F13 -> 22068.2 | G41: ='Consolidated Balance Sheet'!G13 -> 25427.54
B42: Minority Interest | C42: ='Consolidated Balance Sheet'!C15 -> 1093.68 | D42: ='Consolidated Balance Sheet'!D15 -> 1097.55 | E42: ='Consolidated Balance Sheet'!E15 -> 1061.58 | F42: ='Consolidated Balance Sheet'!F15 -> 943.06 | G42: ='Consolidated Balance Sheet'!G15 -> 1098.1
B43: Long Term Borrowings | C43: ='Consolidated Balance Sheet'!C17 -> 27774.04 | D43: ='Consolidated Balance Sheet'!D17 -> 31330.39 | E43: ='Consolidated Balance Sheet'!E17 -> 33559.62 | F43: ='Consolidated Balance Sheet'!F17 -> 36992.29 | G43: ='Consolidated Balance Sheet'!G17 -> 45367.32
B44: Short Term Borrowings | C44: ='Consolidated Balance Sheet'!C23 -> 2040.54 | D44: ='Consolidated Balance Sheet'!D23 -> 2868.45 | E44: ='Consolidated Balance Sheet'!E23 -> 3449.25 | F44: ='Consolidated Balance Sheet'!F23 -> 3213.79 | G44: ='Consolidated Balance Sheet'!G23 -> 3531.13
B45: Total Borrowings | C45: ='Consolidated Balance Sheet'!C17+'Consolidated Balance Sheet'!C23 -> 29814.58 | D45: ='Consolidated Balance Sheet'!D17+'Consolidated Balance Sheet'!D23 -> 34198.84 | E45: ='Consolidated Balance Sheet'!E17+'Consolidated Balance Sheet'!E23 -> 37008.87 | F45: ='Consolidated Balance Sheet'!F17+'Consolidated Balance Sheet'!F23 -> 40206.08 | G45: ='Consolidated Balance Sheet'!G17+'Consolidated Balance Sheet'!G23 -> 48898.45
B46: Other Liabilities | C46: ='Consolidated Balance Sheet'!C18+'Consolidated Balance Sheet'!C19+'Consolidated Balance Sheet'!C20 -> 2755.33 | D46: ='Consolidated Balance Sheet'!D18+'Consolidated Balance Sheet'!D19+'Consolidated Balance Sheet'!D20 -> 2824.08 | E46: ='Consolidated Balance Sheet'!E18+'Consolidated Balance Sheet'!E19+'Consolidated Balance Sheet'!E20 -> 3299.38 | F46: ='Consolidated Balance Sheet'!F18+'Consolidated Balance Sheet'!F19+'Consolidated Balance Sheet'!F20 -> 3940.15 | G46: ='Consolidated Balance Sheet'!G18+'Consolidated Balance Sheet'!G19+'Consolidated Balance Sheet'!G20 -> 5374.11
B47: Total Current Liabilities | C47: ='Consolidated Balance Sheet'!C27 -> 5928.24 | D47: ='Consolidated Balance Sheet'!D27 -> 7017.29 | E47: ='Consolidated Balance Sheet'!E27 -> 8016.68 | F47: ='Consolidated Balance Sheet'!F27 -> 10016.4 | G47: ='Consolidated Balance Sheet'!G27 -> 15567.85
B48: Total Liabilities | C48: ='Consolidated Balance Sheet'!C21+'Consolidated Balance Sheet'!C27 -> 36457.61 | D48: ='Consolidated Balance Sheet'!D21+'Consolidated Balance Sheet'!D27 -> 41171.76 | E48: ='Consolidated Balance Sheet'!E21+'Consolidated Balance Sheet'!E27 -> 44875.68 | F48: ='Consolidated Balance Sheet'!F21+'Consolidated Balance Sheet'!F27 -> 50948.84 | G48: ='Consolidated Balance Sheet'!G21+'Consolidated Balance Sheet'!G27 -> 66309.28
B50: Fixed Assets (Net Block) | C50: ='Consolidated Balance Sheet'!C35 -> 34733.64 | D50: ='Consolidated Balance Sheet'!D35 -> 38247.29 | E50: ='Consolidated Balance Sheet'!E35 -> 41324.14 | F50: ='Consolidated Balance Sheet'!F35 -> 44658.7 | G50: ='Consolidated Balance Sheet'!G35 -> 48259.25
B51: Capital Work in Progress | C51: ='Consolidated Balance Sheet'!C33 -> 5060.16 | D51: ='Consolidated Balance Sheet'!D33 -> 6200.44 | E51: ='Consolidated Balance Sheet'!E33 -> 3002.69 | F51: ='Consolidated Balance Sheet'!F33 -> 5695.36 | G51: ='Consolidated Balance Sheet'!G33 -> 2053.6
B52: Non-Current Investments | C52: ='Consolidated Balance Sheet'!C36 -> 264.17 | D52: ='Consolidated Balance Sheet'!D36 -> 312.89 | E52: ='Consolidated Balance Sheet'!E36 -> 323.79 | F52: ='Consolidated Balance Sheet'!F36 -> 348.72 | G52: ='Consolidated Balance Sheet'!G36 -> 407.29
B53: Other Non-Current Assets | C53: ='Consolidated Balance Sheet'!C39 -> 5096.85 | D53: ='Consolidated Balance Sheet'!D39 -> 5840.32 | E53: ='Consolidated Balance Sheet'!E39 -> 6651.53 | F53: ='Consolidated Balance Sheet'!F39 -> 11606.54 | G53: ='Consolidated Balance Sheet'!G39 -> 23639.66
B54: Total Non Current Assets | C54: ='Consolidated Balance Sheet'!C40 -> 41821.49 | D54: ='Consolidated Balance Sheet'!D40 -> 45024.89 | E54: ='Consolidated Balance Sheet'!E40 -> 48960.69 | F54: ='Consolidated Balance Sheet'!F40 -> 57285.98 | G54: ='Consolidated Balance Sheet'!G40 -> 72993.24
B56: Trade Receivables | C56: ='Consolidated Balance Sheet'!C44 -> 1070.84 | D56: ='Consolidated Balance Sheet'!D44 -> 1437.59 | E56: ='Consolidated Balance Sheet'!E44 -> 1564.95 | F56: ='Consolidated Balance Sheet'!F44 -> 4217.86 | G56: ='Consolidated Balance Sheet'!G44 -> 5733.75
B57: Inventories | C57: ='Consolidated Balance Sheet'!C43 -> 250.11 | D57: ='Consolidated Balance Sheet'!D43 -> 151.91 | E57: ='Consolidated Balance Sheet'!E43 -> 255.28 | F57: ='Consolidated Balance Sheet'!F43 -> 625.24 | G57: ='Consolidated Balance Sheet'!G43 -> 669.45
B58: Cash & Bank | C58: ='Consolidated Balance Sheet'!C45 -> 1492.57 | D58: ='Consolidated Balance Sheet'!D45 -> 1704.14 | E58: ='Consolidated Balance Sheet'!E45 -> 2228.14 | F58: ='Consolidated Balance Sheet'!F45 -> 3618.68 | G58: ='Consolidated Balance Sheet'!G45 -> 3947.34
B59: Total Current Assets | C59: ='Consolidated Balance Sheet'!C48 -> 5642.62 | D59: ='Consolidated Balance Sheet'!D48 -> 8906.86 | E59: ='Consolidated Balance Sheet'!E48 -> 9618.12 | F59: ='Consolidated Balance Sheet'!F48 -> 16674.12 | G59: ='Consolidated Balance Sheet'!G48 -> 19841.68
B61: Total Assets | C61: ='Consolidated Balance Sheet'!C49 -> 47464.11 | D61: ='Consolidated Balance Sheet'!D49 -> 53931.75 | E61: ='Consolidated Balance Sheet'!E49 -> 58578.81 | F61: ='Consolidated Balance Sheet'!F49 -> 73960.1 | G61: ='Consolidated Balance Sheet'!G49 -> 92834.92

Sheet Fixed Assets Schedule
B1: Fixed Assets Schedule
B3: Particular | C3: 2022 | D3: 2023 | E3: 2024 | F3: 2025 | G3: 2026
B4: GROSS BLOCK
B5: Opening Gross Block | D5: ='Consolidated Balance Sheet'!C31 -> 28578.02 | E5: ='Consolidated Balance Sheet'!D31 -> 30947.5 | F5: ='Consolidated Balance Sheet'!E31 -> 37219.85 | G5: ='Consolidated Balance Sheet'!F31 -> 37845.22
B6: Add: Capital Expenditure (Gross) | D6: =('Consolidated Balance Sheet'!D31-'Consolidated Balance Sheet'!C31)+'Consolidated Profit & Loss'!D21 -> 3977.22 | E6: =('Consolidated Balance Sheet'!E31-'Consolidated Balance Sheet'!D31)+'Consolidated Profit & Loss'!E21 -> 8048.43 | F6: =('Consolidated Balance Sheet'!F31-'Consolidated Balance Sheet'!E31)+'Consolidated Profit & Loss'!F21 -> 2531.32 | G6: =('Consolidated Balance Sheet'!G31-'Consolidated Balance Sheet'!F31)+'Consolidated Profit & Loss'!G21 -> 9193.13
B7: Closing Gross Block | C7: ='Consolidated Balance Sheet'!C31 -> 28578.02 | D7: ='Consolidated Balance Sheet'!D31 -> 30947.5 | E7: ='Consolidated Balance Sheet'!E31 -> 37219.85 | F7: ='Consolidated Balance Sheet'!F31 -> 37845.22 | G7: ='Consolidated Balance Sheet'!G31 -> 45060.12
B9: ACCUMULATED DEPRECIATION
B10: Depreciation for the Year | C10: ='Consolidated Profit & Loss'!C21 -> 1427.15 | D10: ='Consolidated Profit & Loss'!D21 -> 1607.74 | E10: ='Consolidated Profit & Loss'!E21 -> 1776.08 | F10: ='Consolidated Profit & Loss'!F21 -> 1905.95 | G10: ='Consolidated Profit & Loss'!G21 -> 1978.23
B11: Accumulated Depreciation | D11: =SUM('Consolidated Profit & Loss'!C21:D21) -> 3034.89 | E11: =SUM('Consolidated Profit & Loss'!C21:E21) -> 4810.97 | F11: =SUM('Consolidated Profit & Loss'!C21:F21) -> 6716.92 | G11: =SUM('Consolidated Profit & Loss'!C21:G21) -> 8695.15
B13: NET BLOCK
B14: Net Fixed Assets (Tangible) | C14: ='Consolidated Balance Sheet'!C31 -> 28578.02 | D14: ='Consolidated Balance Sheet'!D31 -> 30947.5 | E14: ='Consolidated Balance Sheet'!E31 -> 37219.85 | F14: ='Consolidated Balance Sheet'!F31 -> 37845.22 | G14: ='Consolidated Balance Sheet'!G31 -> 45060.12
B15: Capital Work In Progress | C15: ='Consolidated Balance Sheet'!C33 -> 5060.16 | D15: ='Consolidated Balance Sheet'!D33 -> 6200.44 | E15: ='Consolidated Balance Sheet'!E33 -> 3002.69 | F15: ='Consolidated Balance Sheet'!F33 -> 5695.36 | G15: ='Consolidated Balance Sheet'!G33 -> 2053.6
B16: Intangible Assets | C16: ='Consolidated Balance Sheet'!C32 -> 1095.46 | D16: ='Consolidated Balance Sheet'!D32 -> 1099.35 | E16: ='Consolidated Balance Sheet'!E32 -> 1101.6 | F16: ='Consolidated Balance Sheet'!F32 -> 1111.24 | G16: ='Consolidated Balance Sheet'!G32 -> 1145.53
B17: Total Net Block | C17: ='Consolidated Balance Sheet'!C35 -> 34733.64 | D17: ='Consolidated Balance Sheet'!D35 -> 38247.29 | E17: ='Consolidated Balance Sheet'!E35 -> 41324.14 | F17: ='Consolidated Balance Sheet'!F35 -> 44658.7 | G17: ='Consolidated Balance Sheet'!G35 -> 48259.25
B19: CAPEX ANALYSIS
B20: Gross Capex | D20: =D6 -> 3977.22 | E20: =E6 -> 8048.43 | F20: =F6 -> 2531.32 | G20: =G6 -> 9193.13
B21: Less: Depreciation | C21: ='Consolidated Profit & Loss'!C21 -> 1427.15 | D21: ='Consolidated Profit & Loss'!D21 -> 1607.74 | E21: ='Consolidated Profit & Loss'!E21 -> 1776.08 | F21: ='Consolidated Profit & Loss'!F21 -> 1905.95 | G21: ='Consolidated Profit & Loss'!G21 -> 1978.23
B22: Net Capital Expenditure | D22: =D20-D21 -> 2369.48 | E22: =E20-E21 -> 6272.35 | F22: =F20-F21 -> 625.37 | G22: =G20-G21 -> 7214.9
B23: Gross Capex / Sales % | D23: =D20/'Consolidated Profit & Loss'!D9 -> 0.30605489 | E23: =E20/'Consolidated Profit & Loss'!E9 -> 0.49210792 | F23: =F20/'Consolidated Profit & Loss'!F9 -> 0.10750462 | G23: =G20/'Consolidated Profit & Loss'!G9 -> 0.33795004
B24: Net Capex / Sales % | D24: =D22/'Consolidated Profit & Loss'!D9 -> 0.18233614 | E24: =E22/'Consolidated Profit & Loss'!E9 -> 0.38351245 | F24: =F22/'Consolidated Profit & Loss'!F9 -> 0.026559331 | G24: =G22/'Consolidated Profit & Loss'!G9 -> 0.26522803
B25: Depreciation / Gross Block % | C25: ='Consolidated Profit & Loss'!C21/'Consolidated Balance Sheet'!C31 -> 0.049938729 | D25: ='Consolidated Profit & Loss'!D21/'Consolidated Balance Sheet'!D31 -> 0.051950561 | E25: ='Consolidated Profit & Loss'!E21/'Consolidated Balance Sheet'!E31 -> 0.047718623 | F25: ='Consolidated Profit & Loss'!F21/'Consolidated Balance Sheet'!F31 -> 0.05036171 | G25: ='Consolidated Profit & Loss'!G21/'Consolidated Balance Sheet'!G31 -> 0.043902014
B27: Median Gross Capex / Sales % | C27: =MEDIAN(D23:G23) -> 0.32200247
B28: Average Gross Capex / Sales % | C28: =AVERAGE(D23:G23) -> 0.31090437
B29: Median Net Capex / Sales % | C29: =MEDIAN(D24:G24) -> 0.22378208
B30: Average Net Capex / Sales % | C30: =AVERAGE(D24:G24) -> 0.21440899

Sheet Working Capital Changes
B1: Change In Working Capital
B3: Particular | C3: 2022 | D3: 2023 | E3: 2024 | F3: 2025 | G3: 2026
B4: Inventories | C4: ='Consolidated Balance Sheet'!C43 -> 250.11 | D4: ='Consolidated Balance Sheet'!D43 -> 151.91 | E4: ='Consolidated Balance Sheet'!E43 -> 255.28 | F4: ='Consolidated Balance Sheet'!F43 -> 625.24 | G4: ='Consolidated Balance Sheet'!G43 -> 669.45
B5: Trade Receivables | C5: ='Consolidated Balance Sheet'!C44 -> 1070.84 | D5: ='Consolidated Balance Sheet'!D44 -> 1437.59 | E5: ='Consolidated Balance Sheet'!E44 -> 1564.95 | F5: ='Consolidated Balance Sheet'!F44 -> 4217.86 | G5: ='Consolidated Balance Sheet'!G44 -> 5733.75
B6: Other Current Assets | C6: ='Consolidated Balance Sheet'!C47 -> 2524.94 | D6: ='Consolidated Balance Sheet'!D47 -> 4079.23 | E6: ='Consolidated Balance Sheet'!E47 -> 4719.28 | F6: ='Consolidated Balance Sheet'!F47 -> 5916.2 | G6: ='Consolidated Balance Sheet'!G47 -> 7249.05
B7: Total Current Assets | C7: ='Consolidated Balance Sheet'!C43+'Consolidated Balance Sheet'!C44+'Consolidated Balance Sheet'!C47 -> 3845.89 | D7: ='Consolidated Balance Sheet'!D43+'Consolidated Balance Sheet'!D44+'Consolidated Balance Sheet'!D47 -> 5668.73 | E7: ='Consolidated Balance Sheet'!E43+'Consolidated Balance Sheet'!E44+'Consolidated Balance Sheet'!E47 -> 6539.51 | F7: ='Consolidated Balance Sheet'!F43+'Consolidated Balance Sheet'!F44+'Consolidated Balance Sheet'!F47 -> 10759.3 | G7: ='Consolidated Balance Sheet'!G43+'Consolidated Balance Sheet'!G44+'Consolidated Balance Sheet'!G47 -> 13652.25
B9: Trade Payables | C9: ='Consolidated Balance Sheet'!C24 -> 1607.91 | D9: ='Consolidated Balance Sheet'!D24 -> 1800.43 | E9: ='Consolidated Balance Sheet'!E24 -> 1722.11 | F9: ='Consolidated Balance Sheet'!F24 -> 2955.62 | G9: ='Consolidated Balance Sheet'!G24 -> 4993.65
B10: Other Current Liabilities | C10: ='Consolidated Balance Sheet'!C25 -> 2208.88 | D10: ='Consolidated Balance Sheet'!D25 -> 2229.12 | E10: ='Consolidated Balance Sheet'!E25 -> 2746.81 | F10: ='Consolidated Balance Sheet'!F25 -> 3741.47 | G10: ='Consolidated Balance Sheet'!G25 -> 6836.2
B11: Short Term Provisions | C11: ='Consolidated Balance Sheet'!C26 -> 70.91 | D11: ='Consolidated Balance Sheet'!D26 -> 119.29 | E11: ='Consolidated Balance Sheet'!E26 -> 98.51 | F11: ='Consolidated Balance Sheet'!F26 -> 105.52 | G11: ='Consolidated Balance Sheet'!G26 -> 206.87
B12: Total Current Liabilities | C12: ='Consolidated Balance Sheet'!C24+'Consolidated Balance Sheet'!C25+'Consolidated Balance Sheet'!C26 -> 3887.7 | D12: ='Consolidated Balance Sheet'!D24+'Consolidated Balance Sheet'!D25+'Consolidated Balance Sheet'!D26 -> 4148.84 | E12: ='Consolidated Balance Sheet'!E24+'Consolidated Balance Sheet'!E25+'Consolidated Balance Sheet'!E26 -> 4567.43 | F12: ='Consolidated Balance Sheet'!F24+'Consolidated Balance Sheet'!F25+'Consolidated Balance Sheet'!F26 -> 6802.61 | G12: ='Consolidated Balance Sheet'!G24+'Consolidated Balance Sheet'!G25+'Consolidated Balance Sheet'!G26 -> 12036.72
B14: Net Working Capital (NWC) | C14: =(C7-C12) -> -41.81 | D14: =(D7-D12) -> 1519.89 | E14: =(E7-E12) -> 1972.08 | F14: =(F7-F12) -> 3956.69 | G14: =(G7-G12) -> 1615.53
B15: Change in Working Capital | D15: =D14-C14 -> 1561.7 | E15: =E14-D14 -> 452.19 | F15: =F14-E14 -> 1984.61 | G15: =G14-F14 -> -2341.16
B16: Change in WC / Sales % | D16: =D15/'Consolidated Profit & Loss'!D9 -> 0.12017588 | E16: =E15/'Consolidated Profit & Loss'!E9 -> 0.027648409 | F16: =F15/'Consolidated Profit & Loss'!F9 -> 0.084285966 | G16: =G15/'Consolidated Profit & Loss'!G9 -> -0.086063737
B17: Median Change in WC / Sales % | D17: =MEDIAN(D16:G16) -> 0.055967187
B18: Average Change in WC / Sales % | D18: =AVERAGE(D16:G16) -> 0.03651163
B19: Debtor Days | C19: ='Consolidated Balance Sheet'!C44/'Consolidated Profit & Loss'!C9*365 -> 35.661415 | D19: ='Consolidated Balance Sheet'!D44/'Consolidated Profit & Loss'!D9*365 -> 40.378261 | E19: ='Consolidated Balance Sheet'!E44/'Consolidated Profit & Loss'!E9*365 -> 34.925491 | F19: ='Consolidated Balance Sheet'!F44/'Consolidated Profit & Loss'!F9*365 -> 65.383041 | G19: ='Consolidated Balance Sheet'!G44/'Consolidated Profit & Loss'!G9*365 -> 76.934427
B20: Inventory Days | C20: ='Consolidated Balance Sheet'!C43/'Consolidated Profit & Loss'!C9*365 -> 8.3292337 | D20: ='Consolidated Balance Sheet'!D43/'Consolidated Profit & Loss'!D9*365 -> 4.2667671 | E20: ='Consolidated Balance Sheet'!E43/'Consolidated Profit & Loss'!E9*365 -> 5.6971656 | F20: ='Consolidated Balance Sheet'!F43/'Consolidated Profit & Loss'!F9*365 -> 9.6921408 | G20: ='Consolidated Balance Sheet'!G43/'Consolidated Profit & Loss'!G9*365 -> 8.9825598
B21: Creditor Days | C21: ='Consolidated Balance Sheet'!C24/'Consolidated Profit & Loss'!C9*365 -> 53.547072 | D21: ='Consolidated Balance Sheet'!D24/'Consolidated Profit & Loss'!D9*365 -> 50.569518 | E21: ='Consolidated Balance Sheet'!E24/'Consolidated Profit & Loss'!E9*365 -> 38.432881 | F21: ='Consolidated Balance Sheet'!F24/'Consolidated Profit & Loss'!F9*365 -> 45.816463 | G21: ='Consolidated Balance Sheet'!G24/'Consolidated Profit & Loss'!G9*365 -> 67.003898
B22: Cash Conversion Cycle | C22: =C19+C20-C21 -> -9.5564227 | D22: =D19+D20-D21 -> -5.9244893 | E22: =E19+E20-E21 -> 2.1897755 | F22: =F19+F20-F21 -> 29.25872 | G22: =G19+G20-G21 -> 18.913089
B24: Median change WC / Sales % | D24: =MEDIAN(D16:G16) -> 0.055967187
B25: Average change WC / Sales % | D25: =AVERAGE(D16:G16) -> 0.03651163

Sheet FCFF
B1: FCFF
B3: Particulars | C3: 2022 | D3: 2023 | E3: 2024 | F3: 2025 | G3: 2026
B4: EBIT | C4: ='Consolidated Profit & Loss'!C24+'Consolidated Profit & Loss'!C20 -> 3382.97 | D4: ='Consolidated Profit & Loss'!D24+'Consolidated Profit & Loss'!D20 -> 3457.61 | E4: ='Consolidated Profit & Loss'!E24+'Consolidated Profit & Loss'!E20 -> 5006.08 | F4: ='Consolidated Profit & Loss'!F24+'Consolidated Profit & Loss'!F20 -> 7180.78 | G4: ='Consolidated Profit & Loss'!G24+'Consolidated Profit & Loss'!G20 -> 7843.3
B5: Less: Tax on EBIT | C5: =C4*('Consolidated Profit & Loss'!C30/'Consolidated Profit & Loss'!C26) -> 867.50166 | D5: =D4*('Consolidated Profit & Loss'!D30/'Consolidated Profit & Loss'!D26) -> 879.35022 | E5: =E4*('Consolidated Profit & Loss'!E30/'Consolidated Profit & Loss'!E26) -> 1631.9636 | F5: =F4*('Consolidated Profit & Loss'!F30/'Consolidated Profit & Loss'!F26) -> 1195.7834 | G5: =G4*('Consolidated Profit & Loss'!G30/'Consolidated Profit & Loss'!G26) -> 1943.1987
B6: NOPAT | C6: =C4-C5 -> 2515.4683 | D6: =D4-D5 -> 2578.2598 | E6: =E4-E5 -> 3374.1164 | F6: =F4-F5 -> 5984.9966 | G6: =G4-G5 -> 5900.1013
B7: Add: Depreciation & Amortisation | C7: ='Consolidated Profit & Loss'!C21 -> 1427.15 | D7: ='Consolidated Profit & Loss'!D21 -> 1607.74 | E7: ='Consolidated Profit & Loss'!E21 -> 1776.08 | F7: ='Consolidated Profit & Loss'!F21 -> 1905.95 | G7: ='Consolidated Profit & Loss'!G21 -> 1978.23
B8: Less: Net Capital Expenditure | D8: ='Fixed Assets Schedule'!D22 -> 2369.48 | E8: ='Fixed Assets Schedule'!E22 -> 6272.35 | F8: ='Fixed Assets Schedule'!F22 -> 625.37 | G8: ='Fixed Assets Schedule'!G22 -> 7214.9
B9: Less: Change in Working Capital | D9: ='Working Capital Changes'!D15 -> 1561.7 | E9: ='Working Capital Changes'!E15 -> 452.19 | F9: ='Working Capital Changes'!F15 -> 1984.61 | G9: ='Working Capital Changes'!G15 -> -2341.16
B10: Total Reinvestment | D10: =D8+D9 -> 3931.18 | E10: =E8+E9 -> 6724.54 | F10: =F8+F9 -> 2609.98 | G10: =G8+G9 -> 4873.74
B11: Free Cash Flow to Firm (FCFF) | C11: =C6+C7-C10 -> 3942.6183 | D11: =D6+D7-D10 -> 254.81978 | E11: =E6+E7-E10 -> -1574.3436 | F11: =F6+F7-F10 -> 5280.9666 | G11: =G6+G7-G10 -> 3004.5913
B13: Reinvestment Rate % | D13: =D10/D6 -> 1.5247416 | E13: =E10/E6 -> 1.9929781 | F13: =F10/F6 -> 0.43608713 | G13: =G10/G6 -> 0.82604344
B14: FCFF / NOPAT % | D14: =D11/D6 -> 0.09883402 | E14: =E11/E6 -> -0.46659435 | F14: =F11/F6 -> 0.88236752 | G14: =G11/G6 -> 0.50924402
B15: FCFF / Revenue % | C15: =C11/'Consolidated Profit & Loss'!C9 -> 0.35972106 | D15: =D11/'Consolidated Profit & Loss'!D9 -> 0.019608882 | E15: =E11/'Consolidated Profit & Loss'!E9 -> -0.096260634 | F15: =F11/'Consolidated Profit & Loss'!F9 -> 0.22428153 | G15: =G11/'Consolidated Profit & Loss'!G9 -> 0.11045224
B17: Median Reinvestment Rate | D17: =MEDIAN(D13:G13) -> 1.1753925
B18: Average Reinvestment Rate | D18: =AVERAGE(D13:G13) -> 1.1949626

Sheet Beta Calculation
B1: Date | C1: Nifty 50 Daily Returns | D1: ADANIENSOL.NS Daily Returns
B2: 44565 | C2: 1.02 | D2: 1.38
B3: 44566 | C3: 0.67 | D3: 0.35 | F3: Beta | G3: =G26 -> 1.3824346
B4: 44567 | C4: -1 | D4: -0.06 | F4: Beta by Coveriance | G4: =_xlfn.COVARIANCE.S(C2:C1093,D2:D1093) -> 1.0635786
B5: 44568 | C5: 0.38 | D5: 0.91 | F5: Beta by Slope | G5: =SLOPE(D2:D1093,C2:C1093) -> 1.3824346
B6: 44571 | C6: 1.07 | D6: 2.46 | F6: Adjusted Beta
B7: 44572 | C7: 0.29 | D7: 2.62
B8: 44573 | C8: 0.87 | D8: 3.26
B9: 44574 | C9: 0.25 | D9: 4.74 | F9: SUMMARY OUTPUT
B10: 44575 | C10: -0.01 | D10: 0.04
B11: 44578 | C11: 0.29 | D11: -0.89 | F11: Regression Statistics
B12: 44579 | C12: -1.07 | D12: 1.2 | F12: Multiple R | G12: 0.37121058
B13: 44580 | C13: -0.96 | D13: 0.81 | F13: R Square | G13: 0.13779729
B14: 44581 | C14: -1.01 | D14: -0.17 | F14: Adjusted R Square | G14: 0.13700628
B15: 44582 | C15: -0.79 | D15: 1.33 | F15: Standard Error | G15: 3.034524
B16: 44585 | C16: -2.66 | D16: -1.5 | F16: Observations | G16: 1092
B17: 44586 | C17: 0.75 | D17: -2.13
B18: 44588 | C18: -0.97 | D18: 0.85 | F18: ANOVA
B19: 44589 | C19: -0.05 | D19: -1.12 | G19: df | H19: SS | I19: MS | J19: F | K19: Significance F
B20: 44592 | C20: 1.39 | D20: -0.8 | F20: Regression | G20: 1 | H20: 1604.1278 | I20: 1604.1278 | J20: 174.20387 | K20: 5.2259588e-37
B21: 44593 | C21: 1.37 | D21: 0.81 | F21: Residual | G21: 1090 | H21: 10037.086 | I21: 9.2083358
B22: 44594 | C22: 1.16 | D22: 1.46 | F22: Total | G22: 1091 | H22: 11641.214
B23: 44595 | C23: -1.24 | D23: -0.49
B24: 44596 | C24: -0.25 | D24: 1.34 | G24: Coefficients | H24: Standard Error | I24: t Stat | J24: P-value | K24: Lower 95% | L24: Upper 95% | M24: Lower 95.0% | N24: Upper 95.0%
B25: 44599 | C25: -1.73 | D25: -0.23 | F25: Intercept | G25: 0.0021789391 | H25: 0.091881866 | I25: 0.023714572 | J25: 0.98108462 | K25: -0.1781064 | L25: 0.18246428 | M25: -0.1781064 | N25: 0.18246428
B26: 44600 | C26: 0.31 | D26: -2.97 | F26: X Variable 1 | G26: 1.3824346 | H26: 0.10474076 | I26: 13.198631 | J26: 5.2259588e-37 | K26: 1.1769183 | L26: 1.5879509 | M26: 1.1769183 | N26: 1.5879509
B27: 44601 | C27: 1.14 | D27: -0.67
B28: 44602 | C28: 0.81 | D28: 4.15
B29: 44603 | C29: -1.31 | D29: -1
B30: 44606 | C30: -3.06 | D30: -5
B31: 44607 | C31: 3.03 | D31: 0.61
B32: 44608 | C32: -0.17 | D32: 0.29
B33: 44609 | C33: -0.1 | D33: 4.57
B34: 44610 | C34: -0.16 | D34: -3.11
B35: 44613 | C35: -0.4 | D35: -3.18
B36: 44614 | C36: -0.67 | D36: 3.86
B37: 44615 | C37: -0.17 | D37: 4.62
B38: 44616 | C38: -4.78 | D38: -4.99
... B1093: 46184 | C1093: 0.35 | D1093: -2.21

Sheet Wacc
B1: WACC Calculation
B3: Cost Of Capital
B4: As On Date: | C4: Jun-26
B6: Cost of equity using CAPM:
B7: Risk-free rate | C7: 0.0685
B8: India default spread | C8: 0.0187
B9: Beta | C9: 1.05
B10: Equity Risk Premium (Damodaran India, total) | C10: 0.075
B11: Equity Risk Premium | C11: =C10 -> 0.075
B12: Cost of equity = Rf + (Beta x ERP) | C12: =C7+(C9*C11) -> 0.14725
B15: Cost of debt:
B16: Pre-Tax Cost of Debt | C16: =C17/C18 -> 0.074294788
B17: Finance Cost | C17: ='Consolidated Profit & Loss'!G20 -> 3632.9
B18: Total Debt | C18: ='Consolidated Balance Sheet'!G17+'Consolidated Balance Sheet'!G23 -> 48898.45
B20: Marginal tax rate % | C20: ='Consolidated Profit & Loss'!G30/'Consolidated Profit & Loss'!G26 -> 0.24775269
B21: Post-Tax Cost of Debt | C21: =C16*(1-C20) -> 0.055888055
B23: WACC Calculation :
B24: Equity Share Capital | C24: ='Consolidated Balance Sheet'!G9 -> 1201.28
B25: Face Value | C25: 10
B26: Shares Outstanding | C26: =C24/C25 -> 120.128
B29: Share Price (as on date) | C29: 1490
B30: Market Value of Equity | C30: =C29*C26 -> 178990.72
B32: Capital Structure Weights
B33: Total Capital | C33: =C18+C30 -> 227889.17
B35: Weight of Debt (Wd) | C35: =C18/C33 -> 0.21457119
B36: Weight of Equity (We) | C36: =C30/C33 -> 0.78542881
B38: WACC | C38: =(C36*C12)+(C35*C21) -> 0.12764636

Sheet Cost of Capital
B2: Weighted Average Cost of Capital
B3: All Figures are in INR Cr.
B4: Peer Comp
B5: Name of the company | D5: Country | E5: Total Equity | F5: Total Debt | G5: Tax Rate | H5: Debt/ Equity | I5: Debt/ Capital | J5: Levered/ beta | K5: Unlevered/ beta
B7: Adani Energy Solutions | D7: India | E7: ='Relative Valuation'!E6 -> 179591.36 | F7: ='Relative Valuation'!F6 -> 48898.45 | G7: 0.25 | H7: =F7/E7 -> 0.27227618 | I7: =F7/(F7+E7) -> 0.21400714 | J7: ='Beta Calculation'!G26 -> 1.3824346 | K7: =J7/(1+(1-G7)*H7) -> 1.148004
B8: Tata Power | D8: India | E8: ='Relative Valuation'!E7 -> 131697.9 | F8: ='Relative Valuation'!F7 -> 35000 | G8: 0.25 | H8: =F8/E8 -> 0.26575974 | I8: =F8/(F8+E8) -> 0.20996065 | J8: 1.56 | K8: =J8/(1+(1-G8)*H8) -> 1.3007373
B9: Torrent Power | D9: India | E9: ='Relative Valuation'!E8 -> 65721.6 | F9: ='Relative Valuation'!F8 -> 14000 | G9: 0.25 | H9: =F9/E9 -> 0.21301977 | I9: =F9/(F9+E9) -> 0.17561113 | J9: 0.9 | K9: =J9/(1+(1-G9)*H9) -> 0.7760194
B10: Power Grid Corp | D10: India | E10: ='Relative Valuation'!E9 -> 269988.3 | F10: ='Relative Valuation'!F9 -> 95000 | G10: 0.25 | H10: =F10/E10 -> 0.3518671 | I10: =F10/(F10+E10) -> 0.26028232 | J10: 0.85 | K10: =J10/(1+(1-G10)*H10) -> 0.67252139
B11: CESC Ltd | D11: India | E11: ='Relative Valuation'!E10 -> 24166.35 | F11: ='Relative Valuation'!F10 -> 8000 | G11: 0.25 | H11: =F11/E11 -> 0.33103882 | I11: =F11/(F11+E11) -> 0.24870711 | J11: 1.1 | K11: =J11/(1+(1-G11)*H11) -> 0.88121317
F13: Average | G13: =AVERAGE(G7:G11) -> 0.25 | H13: =AVERAGE(H7:H11) -> 0.28679232 | I13: =AVERAGE(I7:I11) -> 0.22171367 | J13: =AVERAGE(J7:J11) -> 1.1584869 | K13: =AVERAGE(K7:K11) -> 0.95569905
F14: Median | G14: =MEDIAN(G7:G11) -> 0.25 | H14: =MEDIAN(H7:H11) -> 0.27227618 | I14: =MEDIAN(I7:I11) -> 0.21400714 | J14: =MEDIAN(J7:J11) -> 1.1 | K14: =MEDIAN(K7:K11) -> 0.88121317
B17: Cost of Debt | G17: Cost of Equity
B19: Pre-tax Cost of Debt | C19: ='Consolidated Profit & Loss'!G20/F7 -> 0.074294788 | G19: Risk Free Rate | K19: =Wacc!C7 -> 0.0685
B20: Tax Rate | C20: =G14 -> 0.25 | G20: Equity Risk Premium | K20: =Wacc!C11 -> 0.075
B21: After Tax Cost of Debt | C21: =C19*(1-C20) -> 0.055721091 | G21: Levered Beta | K21: =K30 -> 1.0694893
G22: Cost of Equity | K22: =K19+(K20*K21) -> 0.1487117
B25: Capital Structure | G25: Levered Beta
D27: Current | E27: Target | G27: Comps Median Unlevered Beta | K27: =K14 -> 0.88121317
B28: Total Debt | C28: =F7 -> 48898.45 | D28: =C28/$C$30 -> 0.21400714 | E28: =I13 -> 0.22171367 | G28: Target Debt/ Equity | K28: =E32 -> 0.28487417
B29: Market Capitalization | C29: =E7 -> 179591.36 | D29: =C29/$C$30 -> 0.78599286 | E29: =E30-E28 -> 0.77828633 | G29: Tax Rate | K29: 0.25
B30: Total Capital | C30: =SUM(C28:C29) -> 228489.81 | D30: =C30/$C$30 -> 1 | E30: =D30 -> 1 | G30: Levered Beta | K30: =K27*(1+(1-K29)*K28) -> 1.0694893
B32: Debt/ Equity | D32: =D28/D29 -> 0.27227618 | E32: =E28/E29 -> 0.28487417
G33: Weighted Average Cost of Capital
G35: Cost of Equity | K35: =K22 -> 0.1487117
G36: Equity Weight | K36: =E29 -> 0.77828633
G38: Cost of Debt | K38: =C21 -> 0.055721091
G39: Debt Weight | K39: =E28 -> 0.22171367
G41: WACC | K41: =(K35*K36)+(K38*K39) -> 0.12809441

Sheet Peer Comp.
B1: Peer comparison
B2: S.No. | C2: Name | D2: CMP Rs. | E2: No. Eq. Shares Cr. | F2: Debt Rs.Cr. | G2: EV Rs.Cr. | H2: NP 12M Rs.Cr. | I2: EPS 12M Rs. | J2: Sales Rs.Cr. | K2: EBIDT Ann Rs.Cr. | L2: Cash Rs.Cr.
B3: 1 | C3: Adani Energy Solutions | D3: 1495 | E3: 120.128 | F3: 48898.45 | G3: 224542.47 | H3: ='Historical FS'!G31 -> 2282.54 | I3: 19.01 | J3: 27203 | K3: 9821 | L3: 3947.34
B4: 2 | C4: Tata Power | D4: 412.2 | E4: 319.5 | F4: 35000 | G4: 166712 | H4: 4800 | I4: 15.02 | J4: 60000 | K4: 12500 | L4: 13644
B5: 3 | C5: Torrent Power | D5: 1304 | E5: 50.4 | F5: 14000 | G5: 79714 | H5: 2800 | I5: 55.56 | J5: 22000 | K5: 6800 | L5: 831
B6: 4 | C6: Power Grid Corp | D6: 279 | E6: 967.7 | F6: 95000 | G6: 365000 | H6: 16000 | I6: 16.53 | J6: 47000 | K6: 35000 | L6: 8920
B7: 5 | C7: CESC Ltd | D7: 182.25 | E7: 132.6 | F7: 8000 | G7: 32159 | H7: 1600 | I7: 12.07 | J7: 17500 | K7: 4200 | L7: 0

Sheet Relative Valuation
B1: Relative Valuation
B3: Comparable Company Valuation
B4: Company Name | C4: Market Data | J4: Financials | O4: Valuation
C5: No. of shares | D5: Share Price | E5: Equity value | F5: Debt | G5: cash | H5: Enterprises value | J5: Revenue | K5: EBITDA | L5: Net Profit | M5: EPS | O5: EV/Revenue | P5: EV/EBITDA | Q5: P/E Ratio
B6: Adani Energy Solutions | C6: ='Peer Comp.'!E3 -> 120.128 | D6: ='Peer Comp.'!D3 -> 1495 | E6: =C6*D6 -> 179591.36 | F6: ='Peer Comp.'!F3 -> 48898.45 | G6: ='Peer Comp.'!L3 -> 3947.34 | H6: =E6+F6-G6 -> 224542.47 | J6: ='Peer Comp.'!J3 -> 27203 | K6: ='Peer Comp.'!K3 -> 9821 | L6: ='Peer Comp.'!H3 -> 2282.54 | M6: ='Peer Comp.'!I3 -> 19.01 | O6: =H6/J6 -> 8.2543275 | P6: =H6/K6 -> 22.863504 | Q6: =D6/M6 -> 78.64282
B7: Tata Power | C7: ='Peer Comp.'!E4 -> 319.5 | D7: ='Peer Comp.'!D4 -> 412.2 | E7: =C7*D7 -> 131697.9 | F7: ='Peer Comp.'!F4 -> 35000 | G7: ='Peer Comp.'!L4 -> 13644 | H7: =E7+F7-G7 -> 153053.9 | J7: ='Peer Comp.'!J4 -> 60000 | K7: ='Peer Comp.'!K4 -> 12500 | L7: ='Peer Comp.'!H4 -> 4800 | M7: ='Peer Comp.'!I4 -> 15.02 | O7: =H7/J7 -> 2.5508983 | P7: =H7/K7 -> 12.244312 | Q7: =D7/M7 -> 27.443409
B8: Torrent Power | C8: ='Peer Comp.'!E5 -> 50.4 | D8: ='Peer Comp.'!D5 -> 1304 | E8: =C8*D8 -> 65721.6 | F8: ='Peer Comp.'!F5 -> 14000 | G8: ='Peer Comp.'!L5 -> 831 | H8: =E8+F8-G8 -> 78890.6 | J8: ='Peer Comp.'!J5 -> 22000 | K8: ='Peer Comp.'!K5 -> 6800 | L8: ='Peer Comp.'!H5 -> 2800 | M8: ='Peer Comp.'!I5 -> 55.56 | O8: =H8/J8 -> 3.5859364 | P8: =H8/K8 -> 11.601559 | Q8: =D8/M8 -> 23.470122
B9: Power Grid Corp | C9: ='Peer Comp.'!E6 -> 967.7 | D9: ='Peer Comp.'!D6 -> 279 | E9: =C9*D9 -> 269988.3 | F9: ='Peer Comp.'!F6 -> 95000 | G9: ='Peer Comp.'!L6 -> 8920 | H9: =E9+F9-G9 -> 356068.3 | J9: ='Peer Comp.'!J6 -> 47000 | K9: ='Peer Comp.'!K6 -> 35000 | L9: ='Peer Comp.'!H6 -> 16000 | M9: ='Peer Comp.'!I6 -> 16.53 | O9: =H9/J9 -> 7.5759213 | P9: =H9/K9 -> 10.17338 | Q9: =D9/M9 -> 16.878403
B10: CESC Ltd | C10: ='Peer Comp.'!E7 -> 132.6 | D10: ='Peer Comp.'!D7 -> 182.25 | E10: =C10*D10 -> 24166.35 | F10: ='Peer Comp.'!F7 -> 8000 | G10: ='Peer Comp.'!L7 -> 0 | H10: =E10+F10-G10 -> 32166.35 | J10: ='Peer Comp.'!J7 -> 17500 | K10: ='Peer Comp.'!K7 -> 4200 | L10: ='Peer Comp.'!H7 -> 1600 | M10: ='Peer Comp.'!I7 -> 12.07 | O10: =H10/J10 -> 1.8380771 | P10: =H10/K10 -> 7.6586548 | Q10: =D10/M10 -> 15.09942
B12: M&M Industry Comparable comps | C12: EV/Revenue | D12: EV/EBITDA | E12: P/E Ratio | K12: Average | M12: =IFERROR(AVERAGE(O7:O10),0) -> 3.8877083 | N12: =IFERROR(AVERAGE(P7:P10),0) -> 10.419476 | O12: =IFERROR(AVERAGE(Q7:Q10),0) -> 20.722839
C13: Overvalued | D13: Overvalued | E13: Overvalued | K13: median | M13: =IFERROR(MEDIAN(O7:O10),0) -> 3.0684173 | N13: =IFERROR(MEDIAN(P7:P10),0) -> 10.887469 | O13: =IFERROR(MEDIAN(Q7:Q10),0) -> 20.174263
B14: Implied Enterprise Value / Equity Value (P/E) | C14: =$M$13*J6 -> 83470.157 | D14: =$N$13*K6 -> 106925.84 | E14: =O13*L6 -> 46048.561
B15: Net Debt | C15: =F6-G6 -> 44951.11 | D15: =C15 -> 44951.11 | E15: 0 | K15: Max | M15: =IFERROR(MAX(O7:O10),0) -> 7.5759213 | N15: =IFERROR(MAX(P7:P10),0) -> 12.244312 | O15: =IFERROR(MAX(Q7:Q10),0) -> 27.443409
B16: Implied Market Value | C16: =C14-C15 -> 38519.047 | D16: =D14-D15 -> 61974.727 | E16: =E14-E15 -> 46048.561 | K16: 75th Percentile | M16: =IFERROR(QUARTILE(O7:O10,3),0) -> 4.5834326 | N16: =IFERROR(QUARTILE(P7:P10,3),0) -> 11.762247 | O16: =IFERROR(QUARTILE(Q7:Q10,3),0) -> 24.463444
B17: Share Outstanding | C17: =C6 -> 120.128 | D17: =C17 -> 120.128 | E17: =D17 -> 120.128
B18: Implied Value per Share | C18: =C16/C17 -> 320.65003 | D18: =D16/D17 -> 515.90576 | E18: =E16/E17 -> 383.32913 | K18: 25th Percentile | M18: =IFERROR(QUARTILE(O7:O10,1),0) -> 2.372693 | N18: =IFERROR(QUARTILE(P7:P10,1),0) -> 9.5446987 | O18: =IFERROR(QUARTILE(Q7:Q10,1),0) -> 16.433657
K19: Min. | M19: =IFERROR(MIN(O7:O10),0) -> 1.8380771 | N19: =IFERROR(MIN(P7:P10),0) -> 7.6586548 | O19: =IFERROR(MIN(Q7:Q10),0) -> 15.09942

Sheet Growth rate analysis
B2: GROWTH RATE ANALYSIS
B4: Year | C4: Revenue | D4: %Change | E4: No. of years | F4: Logarithmic Regression | G4: Geomean
B5: 2022 | C5: ='Historical FS'!C5 -> 10960.21 | E5: 1 | F5: =LN(C5) -> 9.3020267
B6: 2023 | C6: ='Historical FS'!D5 -> 12995.12 | D6: =C6/C5-1 -> 0.18566341 | E6: 2 | F6: =LN(C6) -> 9.4723292 | G6: =C6/C5 -> 1.1856634
B7: 2024 | C7: ='Historical FS'!E5 -> 16355.01 | D7: =C7/C6-1 -> 0.25855013 | E7: 3 | F7: =LN(C7) -> 9.7022896 | G7: =C7/C6 -> 1.2585501
B8: 2025 | C8: ='Historical FS'!F5 -> 23546.15 | D8: =C8/C7-1 -> 0.43969035 | E8: 4 | F8: =LN(C8) -> 10.066718 | G8: =C8/C7 -> 1.4396903
B9: 2026 | C9: ='Historical FS'!G5 -> 27202.63 | D9: =C9/C8-1 -> 0.15528993 | E9: 5 | F9: =LN(C9) -> 10.211069 | G9: =C9/C8 -> 1.1552899
B11: Approaches to calculate 'g' | C11: values
B12: Arthmetic Method | C12: =AVERAGE(D6:D9) -> 0.25979846
B13: CAGR Method | C13: =(C9/C5)^(1/(E9-E5))-1 -> 0.25515686
B14: Log Regression | C14: =EXP(SLOPE(F5:F9,E5:E9))-1 -> 0.27283575
B15: Geometric Mean | C15: =GEOMEAN(G6:G9)-1 -> 0.25515686
B17: For FCFF Growth:
B18: Retention Ratio: | C18: 1- D/P Ratio
B19: Return on Equity: | C19: PAT/Equity
B20: Dividend Payout Ratio: | C20: DPS/EPS
B21: Earnings Per Share | C21: ='Consolidated Profit & Loss'!G39 -> 19
B22: D/P Ratio | C22: 0
B23: Retention Ratio: | C23: =1-C22 -> 1
B24: RoE (Return on Equity) - 5yr Avg | C24: =AVERAGE('Ratio Analysis'!C33:G33) -> 0.093014644
B25: g' ( Growth Rate) | C25: =C23*C24 -> 0.093014644

Sheet Growth Scenerio
B1: Growth Scenarios
B4: Scenario 1: High Growth
B5: INR Cr. | C5: LTM | D5: Y1E | E5: Y2E | F5: Y3E | G5: Y4E | H5: Y5E | I5: Y6E | J5: Y7E | K5: Y8E | L5: Y9E | M5: Y10E | N5: Average Revenue Growth | O5: =Assumption!I5 -> 0.21507168
B6: Sales | C6: ='Consolidated Profit & Loss'!G11 -> 27588.03 | D6: =C6*(1+D7) -> 33521.434 | E6: =D6*(1+E7) -> 40185.024 | F6: =E6*(1+F7) -> 47518.799 | G6: =F6*(1+G7) -> 55417.11 | H6: =G6*(1+H7) -> 63725.726 | I6: =H6*(1+I7) -> 72242.221 | J6: =I6*(1+J7) -> 80720.368 | K6: =J6*(1+K7) -> 88878.895 | ... M6: =L6*(1+M7) -> 103018.96 | N6: Risk Free Rate | O6: =Wacc!C7 -> 0.0685
B7: Sales Growth % | D7: =O5 -> 0.21507168 | E7: =D7-$O$8 -> 0.19878594 | F7: =E7-$O$8 -> 0.1825002 | G7: =F7-$O$8 -> 0.16621445 | H7: =G7-$O$8 -> 0.14992871 | I7: =H7-$O$8 -> 0.13364297 | J7: =I7-$O$8 -> 0.11735723 | K7: =J7-$O$8 -> 0.10107148 | L7: =K7-$O$8 -> 0.084785742 | M7: =L7-$O$8 -> 0.0685 | O7: =O5-O6 -> 0.14657168
N8: Growth Per Year | O8: =O7/9 -> 0.016285742
B9: Scenario 2: Average Growth
B10: INR Cr. | C10: LTM | D10: Y1E | E10: Y2E | F10: Y3E | G10: Y4E | H10: Y5E | I10: Y6E | J10: Y7E | K10: Y8E | L10: Y9E | M10: Y10E | N10: Average Revenue Growth | O10: =Assumption!C24 -> 0.25550681
B11: Sales | C11: =C6 -> 27588.03 | D11: =C11*(1+D12) -> 34636.96 | E11: =D11*(1+E12) -> 42767.234 | F11: =E11*(1+F12) -> 51917.272 | G11: =F11*(1+G12) -> 61946.194 | H11: =G11*(1+H12) -> 72625.265 | I11: =H11*(1+I12) -> 83636.282 | J11: =I11*(1+J12) -> 94578.885 | K11: =J11*(1+K12) -> 104987.96 | ... M11: =L11*(1+M12) -> 122194.87 | N11: Risk Free Rate | O11: =Wacc!C7 -> 0.0685
B12: Sales Growth % | D12: =O10 -> 0.25550681 | E12: =D12-$O$13 -> 0.23472828 | F12: =E12-$O$13 -> 0.21394974 | G12: =F12-$O$13 -> 0.19317121 | H12: =G12-$O$13 -> 0.17239267 | I12: =H12-$O$13 -> 0.15161414 | J12: =I12-$O$13 -> 0.1308356 | K12: =J12-$O$13 -> 0.11005707 | L12: =K12-$O$13 -> 0.089278535 | M12: =L12-$O$13 -> 0.0685 | O12: =O10-O11 -> 0.18700681
N13: Growth Per Year | O13: =O12/9 -> 0.020778535
B14: Scenario 3: EBIT Growth
B15: INR Cr. | C15: LTM | D15: Y1E | E15: Y2E | F15: Y3E | G15: Y4E | H15: Y5E | I15: Y6E | J15: Y7E | K15: Y8E | L15: Y9E | M15: Y10E | N15: Average Revenue Growth | O15: =Assumption!C47 -> 0.030537193
B16: Sales | C16: =C11 -> 27588.03 | D16: =C16*(1+D17) -> 28430.491 | E16: =D16*(1+E17) -> 29178.756 | F16: =E16*(1+F17) -> 29823.636 | G16: =F16*(1+G17) -> 30356.97 | H16: =G16*(1+H17) -> 30771.793 | I16: =H16*(1+I17) -> 31062.486 | J16: =I16*(1+J17) -> 31224.901 | K16: =J16*(1+K17) -> 31256.456 | ... M16: =L16*(1+M17) -> 30924.846 | N16: Risk Free Rate | O16: =Wacc!C7 -> 0.0685
B17: Sales Growth % | D17: =O15 -> 0.030537193 | E17: =D17-(-$O$18) -> 0.026319103 | F17: =E17-(-$O$18) -> 0.022101014 | G17: =F17-(-$O$18) -> 0.017882924 | H17: =G17-(-$O$18) -> 0.013664834 | I17: =H17-(-$O$18) -> 0.0094467445 | J17: =I17-(-$O$18) -> 0.0052286549 | K17: =J17-(-$O$18) -> 0.0010105652 | L17: =K17-(-$O$18) -> -0.0032075245 | M17: =L17-(-$O$18) -> -0.0074256142 | O17: =O15-O16 -> -0.037962807
N18: Growth Per Year | O18: =O17/9 -> -0.0042180897
B19: Live Scenario | C19: 2
B20: INR Cr. | C20: LTM | D20: Y1E | E20: Y2E | F20: Y3E | G20: Y4E | H20: Y5E | I20: Y6E | J20: Y7E | K20: Y8E | L20: Y9E | M20: Y10E
B21: Sales | C21: =C6 -> 27588.03 | D21: =C21*(1+D22) -> 34636.96 | E21: =D21*(1+E22) -> 42767.234 | F21: =E21*(1+F22) -> 51917.272 | G21: =F21*(1+G22) -> 61946.194 | H21: =G21*(1+H22) -> 72625.265 | I21: =H21*(1+I22) -> 83636.282 | J21: =I21*(1+J22) -> 94578.885 | K21: =J21*(1+K22) -> 104987.96 | ... M21: =L21*(1+M22) -> 122194.87
B22: Sales Growth % | D22: =CHOOSE($C$19,D7,D12,D17) -> 0.25550681 | E22: =CHOOSE($C$19,E7,E12,E17) -> 0.23472828 | F22: =CHOOSE($C$19,F7,F12,F17) -> 0.21394974 | G22: =CHOOSE($C$19,G7,G12,G17) -> 0.19317121 | H22: =CHOOSE($C$19,H7,H12,H17) -> 0.17239267 | I22: =CHOOSE($C$19,I7,I12,I17) -> 0.15161414 | J22: =CHOOSE($C$19,J7,J12,J17) -> 0.1308356 | K22: =CHOOSE($C$19,K7,K12,K17) -> 0.11005707 | ... M22: =CHOOSE($C$19,M7,M12,M17) -> 0.0685
O23: >Median of Revenue Growth
O24: Less : Risk Free Rate
O25: >Risk/ Range of 9years
O26: : Per Year Risk

Sheet DCF Valuation
B1: DCF Valuation
D3: 1 | E3: 2 | F3: 3 | G3: 4 | H3: 5 | I3: 6 | J3: 7 | K3: 8 | L3: 9 | M3: 10
B4: INR Cr | C4: LTM | D4: Y1E | E4: Y2E | F4: Y3E | G4: Y4E | H4: Y5E | I4: Y6E | J4: Y7E | K4: Y8E | L4: Y9E | M4: Y10E | O4: Terminal Year | Q4: Terminal growth rate % | R4: ='Growth rate analysis'!C25 -> 0.093014644
B5: Sales | C5: ='Growth Scenerio'!C21 -> 27588.03 | D5: ='Growth Scenerio'!D21 -> 34636.96 | E5: ='Growth Scenerio'!E21 -> 42767.234 | F5: ='Growth Scenerio'!F21 -> 51917.272 | G5: ='Growth Scenerio'!G21 -> 61946.194 | H5: ='Growth Scenerio'!H21 -> 72625.265 | I5: ='Growth Scenerio'!I21 -> 83636.282 | J5: ='Growth Scenerio'!J21 -> 94578.885 | ... M5: ='Growth Scenerio'!M21 -> 122194.87 | N5: Terminal Year Revenue | O5: =M5*(1+R4) -> 133560.78 | Q5: Cost of Capital % | R5: =Wacc!C38 -> 0.12764636
B6: Sales Growth | D6: ='Growth Scenerio'!D22 -> 0.25550681 | E6: ='Growth Scenerio'!E22 -> 0.23472828 | F6: ='Growth Scenerio'!F22 -> 0.21394974 | G6: ='Growth Scenerio'!G22 -> 0.19317121 | H6: ='Growth Scenerio'!H22 -> 0.17239267 | I6: ='Growth Scenerio'!I22 -> 0.15161414 | J6: ='Growth Scenerio'!J22 -> 0.1308356 | K6: ='Growth Scenerio'!K22 -> 0.11005707 | ... M6: ='Growth Scenerio'!M22 -> 0.0685 | N6: projected sales/revenue | O6: =R4 -> 0.093014644 | Q6: Terminal reinvestment rate % | R6: =R4*R5 -> 0.011872981
B7: EBIT | D7: =D8*D5 -> 10530.879 | E7: =E8*E5 -> 13002.774 | F7: =F8*F5 -> 15784.715 | G7: =G8*G5 -> 18833.867 | H7: =H8*H5 -> 22080.688 | I7: =I8*I5 -> 25428.432 | J7: =J8*J5 -> 28755.376 | K7: =K8*K5 -> 31920.109 | ... M7: =M8*M5 -> 37151.627 | N7: EBIT | O7: =O8*O5 -> 40607.272
B8: EBIT Margin % | D8: =AVERAGE(Assumption!$C$29:$G$29) -> 0.3040359 | E8: =AVERAGE(Assumption!$C$29:$G$29) -> 0.3040359 | F8: =AVERAGE(Assumption!$C$29:$G$29) -> 0.3040359 | G8: =AVERAGE(Assumption!$C$29:$G$29) -> 0.3040359 | H8: =AVERAGE(Assumption!$C$29:$G$29) -> 0.3040359 | I8: =AVERAGE(Assumption!$C$29:$G$29) -> 0.3040359 | J8: =AVERAGE(Assumption!$C$29:$G$29) -> 0.3040359 | K8: =AVERAGE(Assumption!$C$29:$G$29) -> 0.3040359 | ... M8: =AVERAGE(Assumption!$C$29:$G$29) -> 0.3040359 | N8: EBIT Margin | O8: =M8 -> 0.3040359 | Q8: Enterprise value = Equity Value + Minority interest
B9: Less: Tax on EBIT | D9: =D7*Assumption!C35 -> 2632.7198 | E9: =E7*Assumption!D35 -> 3250.6936 | F9: =F7*Assumption!E35 -> 3946.1786 | G9: =G7*Assumption!$G$35 -> 4708.4667 | H9: =H7*Assumption!$G$35 -> 5520.1719 | I9: =I7*Assumption!$G$35 -> 6357.108 | J9: =J7*Assumption!$G$35 -> 7188.8441 | K9: =K7*Assumption!$G$35 -> 7980.0272 | L9: =L7*Assumption!$G$35 -> 8692.4723 | M9: =M7*Assumption!$G$35 -> 9287.9067 | N9: Tax on EBIT | O9: =25%*O7 -> 10151.818
B10: EBIT(1-T) | D10: =D7-D9 -> 7898.1594 | E10: =E7-E9 -> 9752.0807 | F10: =F7-F9 -> 11838.536 | G10: =G7-G9 -> 14125.4 | H10: =H7-H9 -> 16560.516 | I10: =I7-I9 -> 19071.324 | J10: =J7-J9 -> 21566.532 | K10: =K7-K9 -> 23940.082 | ... M10: =M7-M9 -> 27863.72 | N10: EBIT(1-T) | O10: =O7-O9 -> 30455.454
B11: Less: Net Capital Expenditure | D11: =D5*'Fixed Assets Schedule'!$C$29 -> 7751.131 | E11: =E5*'Fixed Assets Schedule'!$C$29 -> 9570.5407 | F11: =F5*'Fixed Assets Schedule'!$C$29 -> 11618.155 | G11: =G5*'Fixed Assets Schedule'!$C$29 -> 13862.449 | H11: =H5*'Fixed Assets Schedule'!$C$29 -> 16252.233 | I11: =I5*'Fixed Assets Schedule'!$C$29 -> 18716.301 | J11: =J5*'Fixed Assets Schedule'!$C$29 -> 21165.06 | K11: =K5*'Fixed Assets Schedule'!$C$29 -> 23494.425 | ... M11: =M5*'Fixed Assets Schedule'!$C$29 -> 27345.022
B12: Non Cash Working Capital | C12: ='Working Capital Changes'!G14 -> 1615.53 | D12: =D5*'Working Capital Changes'!$D$17 -> 1938.5332 | E12: =E5*'Working Capital Changes'!$D$17 -> 2393.5618 | F12: =F5*'Working Capital Changes'!$D$17 -> 2905.6637 | G12: =G5*'Working Capital Changes'!$D$17 -> 3466.9543 | H12: =H5*'Working Capital Changes'!$D$17 -> 4064.6318 | I12: =I5*'Working Capital Changes'!$D$17 -> 4680.8874 | J12: =J5*'Working Capital Changes'!$D$17 -> 5293.3142 | K12: =K5*'Working Capital Changes'!$D$17 -> 5875.8808 | ... M12: =M5*'Working Capital Changes'!$D$17 -> 6838.9031
B13: Less: Change in Working Capital | D13: =D12-C12 -> 323.00321 | E13: =E12-D12 -> 455.02856 | F13: =F12-E12 -> 512.10193 | G13: =G12-F12 -> 561.29057 | H13: =H12-G12 -> 597.67752 | I13: =I12-H12 -> 616.25565 | J13: =J12-I12 -> 612.42674 | K13: =K12-J12 -> 582.56665 | ... M13: =M12-L12 -> 438.43225
B14: Reinvestment | D14: =D11+D13 -> 8074.1343 | E14: =E11+E13 -> 10025.569 | F14: =F11+F13 -> 12130.257 | G14: =G11+G13 -> 14423.739 | H14: =H11+H13 -> 16849.911 | I14: =I11+I13 -> 19332.557 | J14: =J11+J13 -> 21777.487 | K14: =K11+K13 -> 24076.991 | ... M14: =M11+M13 -> 27783.455 | O14: =O10*O16 -> 361.59702
B15: Free Cash Flow To Firm (FCFF) | D15: =D10-D14 -> -175.97487 | E15: =E10-E14 -> -273.48852 | F15: =F10-F14 -> -291.72144 | G15: =G10-G14 -> -298.33891 | H15: =H10-H14 -> -289.39492 | I15: =I10-I14 -> -261.23305 | J15: =J10-J14 -> -210.95455 | K15: =K10-K14 -> -136.9096 | ... M15: =M10-M14 -> 80.265358 | O15: =O10-O14 -> 30093.857
B16: Implied Reinvestment rate % | D16: =D14/D10 -> 1.0222805 | E16: =E14/E10 -> 1.0280441 | F16: =F14/F10 -> 1.0246417 | G16: =G14/G10 -> 1.0211207 | H16: =H14/H10 -> 1.017475 | I16: =I14/I10 -> 1.0136977 | J16: =J14/J10 -> 1.0097816 | K16: =K14/K10 -> 1.0057188 | ... M16: =M14/M10 -> 0.99711936 | O16: =R6 -> 0.011872981
B18: Terminal Value | C18: =O15/(R5-R4) -> 868968.14
B20: Present Value Interest Factor(PVIF) | D20: =1/(1+$R$5)^1 -> 0.88680285 | E20: =1/(1+$R$5)^2 -> 0.78641929 | F20: =1/(1+$R$5)^3 -> 0.69739886 | G20: =1/(1+$R$5)^4 -> 0.6184553 | H20: =1/(1+$R$5)^5 -> 0.54844792 | I20: =1/(1+$R$5)^6 -> 0.48636517 | J20: =1/(1+$R$5)^7 -> 0.43131002 | K20: =1/(1+$R$5)^8 -> 0.38248695 | L20: =1/(1+$R$5)^9 -> 0.33919052 | M20: =1/(1+$R$5)^10 -> 0.30079512
B22: Present value of FCFF | C22: =SUM(D22:M22) -> -1177.3471 | D22: =D15*D20 -> -156.05502 | E22: =E15*E20 -> -215.07665 | F22: =F15*F20 -> -203.4462 | G22: =G15*G20 -> -184.50928 | H22: =H15*H20 -> -158.71804 | I22: =I15*I20 -> -127.05466 | J22: =J15*J20 -> -90.986809 | K22: =K15*K20 -> -52.366137 | ... M22: =M15*M20 -> 24.143428
B23: Present value of Terminal value | C23: =C18*M20 -> 261381.37
I24: Sensitivity: Intrinsic Value per Share
B25: Value of operating assets | C25: =C22+C23 -> 260204.03 | I25: =C32 -> 1782.7219 | J25: 0.1076 | K25: 0.1176 | L25: 0.1276 | M25: 0.1376
B26: Add: Cash | C26: ='Consolidated Balance Sheet'!G45 -> 3947.34 | I26: 0.03 | J26: 1050 | K26: 880 | L26: 740 | M26: 630
B27: Less: Debt | C27: ='Consolidated Balance Sheet'!G17+'Consolidated Balance Sheet'!G23 -> 48898.45 | I27: 0.04 | J27: 1340 | K27: 1100 | L27: 920 | M27: 770
B28: Less: Minority Interest | C28: ='Consolidated Balance Sheet'!G15 -> 1098.1 | I28: 0.05 | J28: 1780 | K28: 1500 | L28: 1783 | M28: 960
B29: Equity Value | C29: =C25+C26-C27-C28 -> 214154.82 | I29: 0.06 | J29: 2500 | K29: 2000 | L29: 1600 | M29: 1250
I30: 0.07 | J30: 3900 | K30: 2900 | L30: 2200 | M30: 1650
B31: No. of Shares outstanding (Cr) | C31: =Wacc!C26 -> 120.128
B32: Intrinsic value per share | C32: =C29/C31 -> 1782.7219 | E32: Current Market Price (CMP) | F32: =Wacc!C29 -> 1490
E33: Upside / (Downside) to Intrinsic Value | F33: =C32/F32-1 -> 0.19645765
