Workbook

Sheet Company Overview
A1: ASIAN PAINTS LIMITED
B6: COMPANY OVERVIEW
B7: ABOUT THE COMPANY | L7: Source
B8: Asian Paints Limited (NSE: ASIANPAINT | BSE: 500820) is India's largest paint company and one of the leading players in the decorative and industrial coatings space across Asia, the Middle East and Africa. Originally set up in 1942 in a garage in Mumbai by four friends - Champaklal Choksey, Chimanlal Choksi, Suryakant Dani and Arvind Vakil - the company has grown into a multi-brand group with operations spanning 15+ countries and 27 manufacturing facilities, serving customers in more than 60 countries. Beyond its core decorative and industrial paints business, Asian Paints has steadily expanded into the home decor and improvement space, covering waterproofing, adhesives, wall coverings, modular kitchens, bath fittings and interior design services. The company commands a market share of over 50% in the organised Indian decorative paints segment and continues to invest in backward integration through a large multi-year capex programme aimed at securing raw material supply and improving cost efficiency.
B9: REGISTERED OFFICE
B10: Address | C10: 6A & 6B, Shantinagar, Santacruz (East), Mumbai - 400055, Maharashtra, India
B12: S.No | C12: Name of Entity | D12: Type | F12: Country / Region of Operation | G12: Primary Business | H12: Remarks
B13: 1 | C13: Berger International Limited (Asian Paints Berger) | D13: Subsidiary | F13: UAE, Bahrain, Oman, Qatar | G13: Decorative & industrial paints | H13: Middle East operations
B14: 2 | C14: SCIB Paints S.A.E. | D14: Subsidiary | F14: Egypt | G14: Decorative & industrial paints | H14: Africa operations
B15: 3 | C15: Taubmans Paints (Fiji) Limited | D15: Subsidiary | F15: Fiji, Samoa | G15: Decorative paints | H15: South Pacific operations
B16: 4 | C16: Apco Coatings (Fiji) Limited | D16: Subsidiary | F16: Fiji, Solomon Islands, Vanuatu | G16: Protective & marine coatings | H16: South Pacific operations
B17: 5 | C17: Asian Paints (Causeway) Limited | D17: Subsidiary | F17: Sri Lanka | G17: Decorative paints | H17: Asia operations
B18: 6 | C18: Kadisco Asian Paints Industries S.C. | D18: Associate | F18: Ethiopia | G18: Decorative, industrial & automotive paints, adhesives | H18: Africa operations
B19: 7 | C19: Asian Paints (Nepal) Private Limited | D19: Subsidiary | F19: Nepal | G19: Decorative paints | H19: Asia operations
B20: 8 | C20: Asian Paints International Pte. Limited | D20: Subsidiary | F20: Singapore | G20: Holding company | H20: Holding entity for international subsidiaries
B21: 9 | C21: PPG Asian Paints Private Limited | D21: Joint Venture (50:50 with PPG Inc.) | F21: India | G21: Automotive coatings | H21: JV with PPG Industries Inc.
B22: 10 | C22: Asian PPG Industrial Coatings Private Limited | D22: Joint Venture (50:50 with PPG Inc.) | F22: India | G22: Protective, powder & industrial coatings | H22: JV with PPG Industries Inc.
B23: 11 | C23: Sleek International Private Limited | D23: Subsidiary | F23: India | G23: Modular kitchens | H23: Home decor segment
B24: 12 | C24: Weatherseal Fenestration Private Limited | D24: Subsidiary | F24: India | G24: uPVC windows & doors | H24: Home improvement segment
... B26: 14 | C26: Maxbhumi Developers Limited | D26: Subsidiary | F26: India | G26: Real estate | H26: Support entity

Sheet Promoters
B1: Shareholding Pattern
B3: Asian Paints Ltd
B4: Scrip Code : 500820 | C4: Quarter Ending : Mar-26
B5: Statement showing shareholding pattern of the Promoter and Promoter Group
B6: Category of shareholder | C6: Entity Type | D6: Nos. of shareholders | E6: No. of fully paid up equity shares held | F6: Total nos. shares held | G6: Shareholding as a % of total no. of shares (calculated as per SCRR, 1957)As a % of (A+B+C2) | H6: Number of Voting Rights held in each class of securities | J6: Total No. Of shares on fully diluted basis (including warrants, ESOP, Convertible Securities etc.) | K6: Shareholding , as a % assuming full conversion of convertible securities ( as a percentage of diluted share capital)As a % of (A+B+C2) | L6: Number of Shares pledged or otherwise encumbered | N6: Total Number of Shares encumbered | P6: Number of equity shares held in dematerialized form
H7: Class eg: X | I7: Total | L7: No.(a) | M7: As a % of total Shares held(b) | N7: No.(a) | O7: As a % of total Shares held(b)
B9: A1) Indian | D9: - | E9: - | F9: - | G9: 0 | H9: - | I9: 0 | J9: - | K9: 0 | L9: - | M9: 0 | N9: - | O9: 0 | P9: -
B10: Individuals/Hindu undivided Family | D10: 52 | E10: 95399647 | F10: 95399647 | G10: 9.95 | H10: 95399647 | I10: 9.95 | J10: 95399647 | K10: 9.95 | L10: 2685727 | M10: 2.82 | N10: 2685727 | O10: 2.82 | P10: 95399647
B11: Dipika Amar Vakil | C11: Promoter Group | D11: 1 | E11: 12761340 | F11: 12761340 | G11: 1.33 | H11: 12761340 | I11: 1.33 | J11: 12761340 | K11: 1.33 | L11: - | M11: 0 | N11: - | O11: 0 | P11: 12761340
B12: Late Abhay Arvind Vakil | C12: Promoter | D12: 1 | E12: 12418060 | F12: 12418060 | G12: 1.29 | H12: 12418060 | I12: 1.29 | J12: 12418060 | K12: 1.29 | L12: - | M12: 0 | N12: - | O12: 0 | P12: 12418060
B13: Vivek Abhay Vakil | C13: Promoter | D13: 1 | E13: 6812369 | F13: 6812369 | G13: 0.71 | H13: 6812369 | I13: 0.71 | J13: 6812369 | K13: 0.71 | L13: - | M13: 0 | N13: - | O13: 0 | P13: 6812369
B14: Bhairavi Abhay Vakil | C14: Promoter | D14: 1 | E14: 6064322 | F14: 6064322 | G14: 0.63 | H14: 6064322 | I14: 0.63 | J14: 6064322 | K14: 0.63 | L14: - | M14: 0 | N14: - | O14: 0 | P14: 6064322
B15: Nehal Abhay Vakil | C15: Promoter | D15: 1 | E15: 5738489 | F15: 5738489 | G15: 0.6 | H15: 5738489 | I15: 0.6 | J15: 5738489 | K15: 0.6 | L15: - | M15: 0 | N15: - | O15: 0 | P15: 5738489
B16: Prafullika Shailesh Choksi | C16: Promoter Group | D16: 1 | E16: 3874480 | F16: 3874480 | G16: 0.4 | H16: 3874480 | I16: 0.4 | J16: 3874480 | K16: 0.4 | L16: - | M16: 0 | N16: - | O16: 0 | P16: 3874480
B17: Satyen Ashwin Gandhi | C17: Promoter Group | D17: 1 | E17: 3725954 | F17: 3725954 | G17: 0.39 | H17: 3725954 | I17: 0.39 | J17: 3725954 | K17: 0.39 | L17: 1391500 | M17: 37.35 | N17: 1391500 | O17: 37.35 | P17: 3725954
B18: Hiren Ashwin Gandhi | C18: Promoter Group | D18: 1 | E18: 3706265 | F18: 3706265 | G18: 0.39 | H18: 3706265 | I18: 0.39 | J18: 3706265 | K18: 0.39 | L18: 1294227 | M18: 34.92 | N18: 1294227 | O18: 34.92 | P18: 3706265
B19: Vishal Shailesh Choksi | C19: Promoter Group | D19: 1 | E19: 3380865 | F19: 3380865 | G19: 0.35 | H19: 3380865 | I19: 0.35 | J19: 3380865 | K19: 0.35 | L19: - | M19: 0 | N19: - | O19: 0 | P19: 3380865
B20: Hasit A Dani | C20: Promoter Group | D20: 1 | E20: 3150800 | F20: 3150800 | G20: 0.33 | H20: 3150800 | I20: 0.33 | J20: 3150800 | K20: 0.33 | L20: - | M20: 0 | N20: - | O20: 0 | P20: 3150800
B21: VAKIL HUF (VARUN AMAR VAKIL) | C21: Promoter Group | D21: 1 | E21: 3103290 | F21: 3103290 | G21: 0.32 | H21: 3103290 | I21: 0.32 | J21: 3103290 | K21: 0.32 | L21: - | M21: 0 | N21: - | O21: 0 | P21: 3103290
B22: Amrita Amar Vakil | C22: Promoter Group | D22: 1 | E22: 2566680 | F22: 2566680 | G22: 0.27 | H22: 2566680 | I22: 0.27 | J22: 2566680 | K22: 0.27 | L22: - | M22: 0 | N22: - | O22: 0 | P22: 2566680
B23: Jigish Shailesh Choksi | C23: Promoter Group | D23: 1 | E23: 2424825 | F23: 2424825 | G23: 0.25 | H23: 2424825 | I23: 0.25 | J23: 2424825 | K23: 0.25 | L23: - | M23: 0 | N23: - | O23: 0 | P23: 2424825
B24: Manish Mahendra Choksi | C24: Promoter | D24: 1 | E24: 2381040 | F24: 2381040 | G24: 0.25 | H24: 2381040 | I24: 0.25 | J24: 2381040 | K24: 0.25 | L24: - | M24: 0 | N24: - | O24: 0 | P24: 2381040
B25: Varun Amar Vakil | C25: Promoter Group | D25: 1 | E25: 2230590 | F25: 2230590 | G25: 0.23 | H25: 2230590 | I25: 0.23 | J25: 2230590 | K25: 0.23 | L25: - | M25: 0 | N25: - | O25: 0 | P25: 2230590
B26: AMAR ARVIND VAKIL HUF (VARUN AMAR VAKIL) | C26: Promoter Group | D26: 1 | E26: 2112190 | F26: 2112190 | G26: 0.22 | H26: 2112190 | I26: 0.22 | J26: 2112190 | K26: 0.22 | L26: - | M26: 0 | N26: - | O26: 0 | P26: 2112190
B27: ABHAY ARVIND VAKIL HUF (VIVEK ABHAY VAKIL) | C27: Promoter Group | D27: 1 | E27: 2076820 | F27: 2076820 | G27: 0.22 | H27: 2076820 | I27: 0.22 | J27: 2076820 | K27: 0.22 | L27: - | M27: 0 | N27: - | O27: 0 | P27: 2076820
B28: Rupal Anant Bhat | C28: Promoter Group | D28: 1 | E28: 1923770 | F28: 1923770 | G28: 0.2 | H28: 1923770 | I28: 0.2 | J28: 1923770 | K28: 0.2 | L28: - | M28: 0 | N28: - | O28: 0 | P28: 1923770
B29: SHAILESH CHIMANLAL CHOKSI HUF (JIGISH SHAILESH CHOKSI) | C29: Promoter Group | D29: 1 | E29: 1749690 | F29: 1749690 | G29: 0.18 | H29: 1749690 | I29: 0.18 | J29: 1749690 | K29: 0.18 | L29: - | M29: 0 | N29: - | O29: 0 | P29: 1749690
B30: Mahendra Chimanlal Choksi | C30: Promoter Group | D30: 1 | E30: 1656380 | F30: 1656380 | G30: 0.17 | H30: 1656380 | I30: 0.17 | J30: 1656380 | K30: 0.17 | L30: - | M30: 0 | N30: - | O30: 0 | P30: 1656380
... B62: ASHISH ASHWIN CHOKSI HUF (ASHISH ASHWIN CHOKSI) | C62: Promoter Group | D62: 1 | E62: 5620 | F62: 5620 | G62: 0 | H62: 5620 | I62: 0 | J62: 5620 | K62: 0 | L62: - | M62: 0 | N62: - | O62: 0 | P62: 5620
B63: ASHWIN SURYAKANT DANI HUF (ASHWIN SURYAKANT DANI) | C63: Promoter Group | D63: - | E63: - | F63: - | G63: 0 | H63: - | I63: 0 | J63: - | K63: 0 | L63: - | M63: 0 | N63: - | O63: 0 | P63: -
B64: Anant Raghuvir Bhat | C64: Promoter Group | D64: - | E64: - | F64: - | G64: 0 | H64: - | I64: 0 | J64: - | K64: 0 | L64: - | M64: 0 | N64: - | O64: 0 | P64: -
B65: Arhaan Anant Bhat | C65: Promoter Group | D65: - | E65: - | F65: - | G65: 0 | H65: - | I65: 0 | J65: - | K65: 0 | L65: - | M65: 0 | N65: - | O65: 0 | P65: -
B66: Rehaan Anant Bhat (Minor) | C66: Promoter Group | D66: - | E66: - | F66: - | G66: 0 | H66: - | I66: 0 | J66: - | K66: 0 | L66: - | M66: 0 | N66: - | O66: 0 | P66: -
B67: Priyanka Jigish Choksi | C67: Promoter Group | D67: - | E67: - | F67: - | G67: 0 | H67: - | I67: 0 | J67: - | K67: 0 | L67: - | M67: 0 | N67: - | O67: 0 | P67: -
B68: Aryan Jigish Choksi N/G Jigish Shailesh Choksi (Minor) | C68: Promoter Group | D68: - | E68: - | F68: - | G68: 0 | H68: - | I68: 0 | J68: - | K68: 0 | L68: - | M68: 0 | N68: - | O68: 0 | P68: -
B69: Gayatri Subhash Gujarathi | C69: Promoter Group | D69: - | E69: - | F69: - | G69: 0 | H69: - | I69: 0 | J69: - | K69: 0 | L69: - | M69: 0 | N69: - | O69: 0 | P69: -
B70: Amreen Sethi (Minor) | C70: Promoter Group | D70: - | E70: - | F70: - | G70: 0 | H70: - | I70: 0 | J70: - | K70: 0 | L70: - | M70: 0 | N70: - | O70: 0 | P70: -
B71: Any Other (specify) | D71: 28 | E71: 404283583 | F71: 404283583 | G71: 42.15 | H71: 404283583 | I71: 42.15 | J71: 404283583 | K71: 42.15 | L71: 47057000 | M71: 11.64 | N71: 47057000 | O71: 11.64 | P71: 404283583
B72: Sattva Holding and Trading Private Limited | C72: Promoter Group | D72: 1 | E72: 54789183 | F72: 54789183 | G72: 5.71 | H72: 54789183 | I72: 5.71 | J72: 54789183 | K72: 5.71 | L72: 6251000 | M72: 11.41 | N72: 6251000 | O72: 11.41 | P72: 54789183
B73: Smiti Holding and Trading Company Private Limited | C73: Promoter Group | D73: 1 | E73: 51442638 | F73: 51442638 | G73: 5.36 | H73: 51442638 | I73: 5.36 | J73: 51442638 | K73: 5.36 | L73: 38306000 | M73: 74.46 | N73: 38306000 | O73: 74.46 | P73: 51442638
B74: Geetanjali Trading and Investments Private Limited | C74: Promoter Group | D74: 1 | E74: 45706140 | F74: 45706140 | G74: 4.77 | H74: 45706140 | I74: 4.77 | J74: 45706140 | K74: 4.77 | L74: 2500000 | M74: 5.47 | N74: 2500000 | O74: 5.47 | P74: 45706140
B75: Elcid Investments Limited | C75: Promoter Group | D75: 1 | E75: 28313860 | F75: 28313860 | G75: 2.95 | H75: 28313860 | I75: 2.95 | J75: 28313860 | K75: 2.95 | L75: - | M75: 0 | N75: - | O75: 0 | P75: 28313860
B76: Shubhit Holdings Private Limited | C76: Promoter Group | D76: 1 | E76: 23150730 | F76: 23150730 | G76: 2.41 | H76: 23150730 | I76: 2.41 | J76: 23150730 | K76: 2.41 | L76: - | M76: 0 | N76: - | O76: 0 | P76: 23150730
B77: Sudhanva Investments and Trading Company Private Limited | C77: Promoter Group | D77: 1 | E77: 19001760 | F77: 19001760 | G77: 1.98 | H77: 19001760 | I77: 1.98 | J77: 19001760 | K77: 1.98 | L77: - | M77: 0 | N77: - | O77: 0 | P77: 19001760
B78: Rupen Investment & Industries Private Limited | C78: Promoter Group | D78: 1 | E78: 18849825 | F78: 18849825 | G78: 1.97 | H78: 18849825 | I78: 1.97 | J78: 18849825 | K78: 1.97 | L78: - | M78: 0 | N78: - | O78: 0 | P78: 18849825
B79: Satyadharma Investments and Trading Company Private Ltd. | C79: Promoter Group | D79: 1 | E79: 18334280 | F79: 18334280 | G79: 1.91 | H79: 18334280 | I79: 1.91 | J79: 18334280 | K79: 1.91 | L79: - | M79: 0 | N79: - | O79: 0 | P79: 18334280
B80: Castle Investment & Industries Private Limited | C80: Promoter Group | D80: 1 | E80: 15457470 | F80: 15457470 | G80: 1.61 | H80: 15457470 | I80: 1.61 | J80: 15457470 | K80: 1.61 | L80: - | M80: 0 | N80: - | O80: 0 | P80: 15457470
B81: Lyon Investment & Industries Private Limited | C81: Promoter Group | D81: 1 | E81: 14342060 | F81: 14342060 | G81: 1.5 | H81: 14342060 | I81: 1.5 | J81: 14342060 | K81: 1.5 | L81: - | M81: 0 | N81: - | O81: 0 | P81: 14342060
B82: Jaldhar Investments and Trading Company Private Limited | C82: Promoter Group | D82: 1 | E82: 12428250 | F82: 12428250 | G82: 1.3 | H82: 12428250 | I82: 1.3 | J82: 12428250 | K82: 1.3 | L82: - | M82: 0 | N82: - | O82: 0 | P82: 12428250
B83: Tru Trading and Investments Pvt Limited | C83: Promoter Group | D83: 1 | E83: 12176500 | F83: 12176500 | G83: 1.27 | H83: 12176500 | I83: 1.27 | J83: 12176500 | K83: 1.27 | L83: - | M83: 0 | N83: - | O83: 0 | P83: 12176500
B84: Nehal Trading and Investments Private Limited | C84: Promoter Group | D84: 1 | E84: 11102530 | F84: 11102530 | G84: 1.16 | H84: 11102530 | I84: 1.16 | J84: 11102530 | K84: 1.16 | L84: - | M84: 0 | N84: - | O84: 0 | P84: 11102530
B85: Asteroids Trading and Investments Private Limited | C85: Promoter Group | D85: 1 | E85: 10818530 | F85: 10818530 | G85: 1.13 | H85: 10818530 | I85: 1.13 | J85: 10818530 | K85: 1.13 | L85: - | M85: 0 | N85: - | O85: 0 | P85: 10818530
B86: Jalaj Trading & Investment Company Private Limited | C86: Promoter Group | D86: 1 | E86: 10776697 | F86: 10776697 | G86: 1.12 | H86: 10776697 | I86: 1.12 | J86: 10776697 | K86: 1.12 | L86: - | M86: 0 | N86: - | O86: 0 | P86: 10776697
... B98: Dani Finlease Private Limited | C98: Promoter Group | D98: 1 | E98: 10930 | F98: 10930 | G98: 0 | H98: 10930 | I98: 0 | J98: 10930 | K98: 0 | L98: - | M98: 0 | N98: - | O98: 0 | P98: 10930
B99: S C Dani Research Foundation Private Limited | C99: Promoter Group | D99: - | E99: - | F99: - | G99: 0 | H99: - | I99: 0 | J99: - | K99: 0 | L99: - | M99: 0 | N99: - | O99: 0 | P99: -
B100: Haish Holding and Trading Company Private Limited | C100: Promoter Group | D100: - | E100: - | F100: - | G100: 0 | H100: - | I100: 0 | J100: - | K100: 0 | L100: - | M100: 0 | N100: - | O100: 0 | P100: -
B101: Avinash Holding and Trading Company Private Limited | C101: Promoter Group | D101: - | E101: - | F101: - | G101: 0 | H101: - | I101: 0 | J101: - | K101: 0 | L101: - | M101: 0 | N101: - | O101: 0 | P101: -
B102: Canes Venatici Trading Private Limited | C102: Promoter Group | D102: - | E102: - | F102: - | G102: 0 | H102: - | I102: 0 | J102: - | K102: 0 | L102: - | M102: 0 | N102: - | O102: 0 | P102: -
B103: Hydra Trading Private Limited | C103: Promoter Group | D103: - | E103: - | F103: - | G103: 0 | H103: - | I103: 0 | J103: - | K103: 0 | L103: - | M103: 0 | N103: - | O103: 0 | P103: -
B104: Hitech Specialities Solutions Private Limited | C104: Promoter Group | D104: - | E104: - | F104: - | G104: 0 | H104: - | I104: 0 | J104: - | K104: 0 | L104: - | M104: 0 | N104: - | O104: 0 | P104: -
B105: Rituh Holding and Trading Company Private Limited | C105: Promoter Group | D105: - | E105: - | F105: - | G105: 0 | H105: - | I105: 0 | J105: - | K105: 0 | L105: - | M105: 0 | N105: - | O105: 0 | P105: -
B106: Hitech Corporation Limited | C106: Promoter Group | D106: - | E106: - | F106: - | G106: 0 | H106: - | I106: 0 | J106: - | K106: 0 | L106: - | M106: 0 | N106: - | O106: 0 | P106: -
B107: Homevilla Yoga Private Limited | C107: Promoter Group | D107: - | E107: - | F107: - | G107: 0 | H107: - | I107: 0 | J107: - | K107: 0 | L107: - | M107: 0 | N107: - | O107: 0 | P107: -
B108: Riash Renewable Materials Private Limited | C108: Promoter Group | D108: - | E108: - | F108: - | G108: 0 | H108: - | I108: 0 | J108: - | K108: 0 | L108: - | M108: 0 | N108: - | O108: 0 | P108: -
B109: Stack Pack Limited | C109: Promoter Group | D109: - | E109: - | F109: - | G109: 0 | H109: - | I109: 0 | J109: - | K109: 0 | L109: - | M109: 0 | N109: - | O109: 0 | P109: -
B110: Dipika Chemicals Private Limited | C110: Promoter Group | D110: - | E110: - | F110: - | G110: 0 | H110: - | I110: 0 | J110: - | K110: 0 | L110: - | M110: 0 | N110: - | O110: 0 | P110: -
... B112: Mefree LLP | C112: Promoter Group | D112: - | E112: - | F112: - | G112: 0 | H112: - | I112: 0 | J112: - | K112: 0 | L112: - | M112: 0 | N112: - | O112: 0 | P112: -
B113: ACC AP TRUST (Urvashi Ashwin Choksi, Ashish Ashwin Choksi, Rupen Ashwin Choksi) | C113: Promoter Group | D113: 1 | E113: 785700 | F113: 785700 | G113: 0.08 | H113: 785700 | I113: 0.08 | J113: 785700 | K113: 0.08 | L113: - | M113: 0 | N113: - | O113: 0 | P113: 785700
B114: DANI FOUNDATION (Jalaj Dani, Vita Dani, Mudit Dani, Smiti Dani) | C114: Promoter Group | D114: - | E114: - | F114: - | G114: 0 | H114: - | I114: 0 | J114: - | K114: 0 | L114: - | M114: 0 | N114: - | O114: 0 | P114: -
B115: PARAM-ARTH CHARITABLE TRUST (Hasit Dani, Shubhlakshmi Dani, Priyadarshini Kanodia) | C115: Promoter Group | D115: - | E115: - | F115: - | G115: 0 | H115: - | I115: 0 | J115: - | K115: 0 | L115: - | M115: 0 | N115: - | O115: 0 | P115: -
B116: ASHIYANA TRUST (Ina Ashwin Dani - Managing Trustee, Percy Jal Dajee - Trustee) | C116: Promoter Group | D116: - | E116: - | F116: - | G116: 0 | H116: - | I116: 0 | J116: - | K116: 0 | L116: - | M116: 0 | N116: - | O116: 0 | P116: -
B117: CRONUS TRUST (Jalaj Dani, Vita Dani) | C117: Promoter Group | D117: - | E117: - | F117: - | G117: 0 | H117: - | I117: 0 | J117: - | K117: 0 | L117: - | M117: 0 | N117: - | O117: 0 | P117: -
B118: ISHWARA TRUST (Hasit Dani, Shubhlakshmi Dani) | C118: Promoter Group | D118: - | E118: - | F118: - | G118: 0 | H118: - | I118: 0 | J118: - | K118: 0 | L118: - | M118: 0 | N118: - | O118: 0 | P118: -
B119: NARADIYA TRUST (Malav Ashwin Dani - Managing Trustee, Ina Ashwin Dani) | C119: Promoter Group | D119: - | E119: - | F119: - | G119: 0 | H119: - | I119: 0 | J119: - | K119: 0 | L119: - | M119: 0 | N119: - | O119: 0 | P119: -
B120: RIG Trust (Jalaj Dani, Vita Dani) | C120: Promoter Group | D120: - | E120: - | F120: - | G120: 0 | H120: - | I120: 0 | J120: - | K120: 0 | L120: - | M120: 0 | N120: - | O120: 0 | P120: -
B121: INAASHWIN TRUST (Ina Dani and Malav Dani-Managing Trustees,Viraf Mehta,Gautam Doshi,Vaishali Sharma) | C121: Promoter Group | D121: - | E121: - | F121: - | G121: 0 | H121: - | I121: 0 | J121: - | K121: 0 | L121: - | M121: 0 | N121: - | O121: 0 | P121: -
B122: Advaita Charitable Trust (Malav Ashwin Dani, Ina Ashwin Dani, Percy Jal Dajee) | C122: Promoter Group | D122: - | E122: - | F122: - | G122: 0 | H122: - | I122: 0 | J122: - | K122: 0 | L122: - | M122: 0 | N122: - | O122: 0 | P122: -
B123: Sab Ka Mangal Ho Foundation (Ina Ashwin Dani, Malav Ashwin Dani, Percy Dajee, Mehernosh Mehta) | C123: Promoter Group | D123: - | E123: - | F123: - | G123: 0 | H123: - | I123: 0 | J123: - | K123: 0 | L123: - | M123: 0 | N123: - | O123: 0 | P123: -
B124: Dani Charitable Foundation (Ina Ashwin Dani, Jalaj Dani, Malav Ashwin Dani, Hasit Dani) | C124: Promoter Group | D124: - | E124: - | F124: - | G124: 0 | H124: - | I124: 0 | J124: - | K124: 0 | L124: - | M124: 0 | N124: - | O124: 0 | P124: -
B125: Homevilla Charitable Trust (Ina Ashwin Dani, Mahendra Sheth, Percy Jal Dajee, Homi Daruwalla) | C125: Promoter Group | D125: - | E125: - | F125: - | G125: 0 | H125: - | I125: 0 | J125: - | K125: 0 | L125: - | M125: 0 | N125: - | O125: 0 | P125: -
B126: Ashwin Ina Charitable Trust (Ina Ashwin Dani, Malav Ashwin Dani, Percy Jal Dajee) | C126: Promoter Group | D126: - | E126: - | F126: - | G126: 0 | H126: - | I126: 0 | J126: - | K126: 0 | L126: - | M126: 0 | N126: - | O126: 0 | P126: -
B127: Sub Total A1 | D127: 80 | E127: 499683230 | F127: 499683230 | G127: 52.09 | H127: 499683230 | I127: 52.09 | J127: 499683230 | K127: 52.09 | L127: 49742727 | M127: 9.95 | N127: 49742727 | O127: 9.95 | P127: 499683230
B128: A2) Foreign | D128: - | E128: - | F128: - | G128: 0 | H128: - | I128: 0 | J128: - | K128: 0 | L128: - | M128: 0 | N128: - | O128: 0 | P128: -
B129: Individuals (NonResident Individuals/ Foreign Individuals) | D129: 2 | E129: 5101968 | F129: 5101968 | G129: 0.53 | H129: 5101968 | I129: 0.53 | J129: 5101968 | K129: 0.53 | L129: - | M129: 0 | N129: - | O129: 0 | P129: 5101968
B130: Malav A Dani | C130: Promoter Group | D130: 1 | E130: 3650176 | F130: 3650176 | G130: 0.38 | H130: 3650176 | I130: 0.38 | J130: 3650176 | K130: 0.38 | L130: - | M130: 0 | N130: - | O130: 0 | P130: 3650176
B131: Ina Ashwin Dani | C131: Promoter | D131: 1 | E131: 1451792 | F131: 1451792 | G131: 0.15 | H131: 1451792 | I131: 0.15 | J131: 1451792 | K131: 0.15 | L131: - | M131: 0 | N131: - | O131: 0 | P131: 1451792
B132: Sub Total A2 | D132: 2 | E132: 5101968 | F132: 5101968 | G132: 0.53 | H132: 5101968 | I132: 0.53 | J132: 5101968 | K132: 0.53 | L132: - | M132: 0 | N132: - | O132: 0 | P132: 5101968
B133: A=A1+A2 | D133: 82 | E133: 504785198 | F133: 504785198 | G133: 52.63 | H133: 504785198 | I133: 52.63 | J133: 504785198 | K133: 52.63 | L133: 49742727 | M133: 9.85 | N133: 49742727 | O133: 9.85 | P133: 504785198

Sheet Public
B1: Shareholding Pattern Public Shareholder
B3: Asian Paints Ltd
B4: Scrip Code : 500820 | E4: Quarter Ending : Mar-26
B6: Statement showing shareholding pattern of the Public shareholder
B8: Category & Name of the Shareholders | C8: No. of shareholder | D8: No. of fully paid up equity shares held | E8: Total no. shares held | F8: Shareholding % calculated as per SCRR, 1957 As a % of (A+B+C2) | G8: No. of Voting Rights | H8: Total as a % of Total Voting right | I8: Total No. Of shares on fully diluted basis (including warrants, ESOP, Convertible Securities etc.) | J8: Shareholding , as a % assuming full conversion of convertible securities ( as a percentage of diluted share capital)As a % of (A+B+C2) | K8: No. of equity shares held in dematerialized form(Not Applicable) | L8: Sub-categorization of shares (XV)
L9: Shareholding (No. of shares) under
L10: SubCategory_I | M10: SubCategory_II | N10: SubCategory_III
B11: Institutions | C11: 0 | D11: 0 | E11: - | F11: 0 | G11: - | H11: 0 | I11: - | J11: 0 | K11: - | L11: - | M11: - | N11: -
B12: B2) Institutions (Domestic) | C12: 0 | D12: 0 | E12: - | F12: 0 | G12: - | H12: 0 | I12: - | J12: 0 | K12: - | L12: - | M12: - | N12: -
B13: Mutual Funds/ | C13: 40 | D13: 109551686 | E13: 109551686 | F13: 11.42 | G13: 109551686 | H13: 11.42 | I13: 109551686 | J13: 11.42 | K13: 109551686 | L13: - | M13: - | N13: -
B14: UTI Mutual Fund | C14: 1 | D14: 11131106 | E14: 11131106 | F14: 1.16 | G14: 11131106 | H14: 1.16 | I14: 11131106 | J14: 1.16 | K14: 11131106 | L14: - | M14: - | N14: -
B15: ICICI Prudential Mutual Fund | C15: 1 | D15: 21582801 | E15: 21582801 | F15: 2.25 | G15: 21582801 | H15: 2.25 | I15: 21582801 | J15: 2.25 | K15: 21582801 | L15: - | M15: - | N15: -
B16: SBI Mutual Fund | C16: 1 | D16: 49885007 | E16: 49885007 | F16: 5.2 | G16: 49885007 | H16: 5.2 | I16: 49885007 | J16: 5.2 | K16: 49885007 | L16: - | M16: - | N16: -
B17: Venture Capital Funds | C17: 0 | D17: 0 | E17: - | F17: 0 | G17: - | H17: 0 | I17: - | J17: 0 | K17: - | L17: - | M17: - | N17: -
B18: Alternate Investment Funds | C18: 22 | D18: 4159909 | E18: 4159909 | F18: 0.43 | G18: 4159909 | H18: 0.43 | I18: 4159909 | J18: 0.43 | K18: 4159909 | L18: - | M18: - | N18: -
B19: Banks | C19: 9 | D19: 276596 | E19: 276596 | F19: 0.03 | G19: 276596 | H19: 0.03 | I19: 276596 | J19: 0.03 | K19: 272996 | L19: - | M19: - | N19: -
B20: Insurance Companies | C20: 32 | D20: 90823469 | E20: 90823469 | F20: 9.47 | G20: 90823469 | H20: 9.47 | I20: 90823469 | J20: 9.47 | K20: 90822469 | L20: - | M20: - | N20: -
B21: Life Insurance Corporation of India | C21: 1 | D21: 77822006 | E21: 77822006 | F21: 8.11 | G21: 77822006 | H21: 8.11 | I21: 77822006 | J21: 8.11 | K21: 77821006 | L21: - | M21: - | N21: -
B22: Provident Funds/ Pension Funds | C22: 1 | D22: 3732220 | E22: 3732220 | F22: 0.39 | G22: 3732220 | H22: 0.39 | I22: 3732220 | J22: 0.39 | K22: 3732220 | L22: - | M22: - | N22: -
B23: Asset reconstruction companies | C23: 0 | D23: 0 | E23: - | F23: 0 | G23: - | H23: 0 | I23: - | J23: 0 | K23: - | L23: - | M23: - | N23: -
B24: Sovereign Wealth Funds | C24: 2 | D24: 650782 | E24: 650782 | F24: 0.07 | G24: 650782 | H24: 0.07 | I24: 650782 | J24: 0.07 | K24: 650782 | L24: - | M24: - | N24: -
B25: NBFCs registered with RBI | C25: 8 | D25: 5298 | E25: 5298 | F25: 0 | G25: 5298 | H25: 0 | I25: 5298 | J25: 0 | K25: 5298 | L25: - | M25: - | N25: -
B26: Other Financial Institutions | C26: 2 | D26: 3630 | E26: 3630 | F26: 0 | G26: 3630 | H26: 0 | I26: 3630 | J26: 0 | K26: 240 | L26: - | M26: - | N26: -
B27: Any Other(Institutions (Domestic)) | C27: 0 | D27: 0 | E27: - | F27: 0 | G27: - | H27: 0 | I27: - | J27: 0 | K27: - | L27: - | M27: - | N27: -
B28: Sub Total B1 | C28: 116 | D28: 209203590 | E28: 209203590 | F28: 21.81 | G28: 209203590 | H28: 21.81 | I28: 209203590 | J28: 21.81 | K28: 209195600 | L28: - | M28: - | N28: -
B29: B19) Institutions (Foreign) | C29: 0 | D29: 0 | E29: - | F29: 0 | G29: - | H29: 0 | I29: - | J29: 0 | K29: - | L29: - | M29: - | N29: -
B30: Foreign Direct Investment | C30: 0 | D30: 0 | E30: - | F30: 0 | G30: - | H30: 0 | I30: - | J30: 0 | K30: - | L30: - | M30: - | N30: -
B31: Foreign Venture Capital Investors | C31: 0 | D31: 0 | E31: - | F31: 0 | G31: - | H31: 0 | I31: - | J31: 0 | K31: - | L31: - | M31: - | N31: -
B32: Sovereign Wealth Funds | C32: 0 | D32: 0 | E32: - | F32: 0 | G32: - | H32: 0 | I32: - | J32: 0 | K32: - | L32: - | M32: - | N32: -
B33: Foreign Portfolio Investors Category I | C33: 811 | D33: 113436518 | E33: 113436518 | F33: 11.83 | G33: 113436518 | H33: 11.83 | I33: 113436518 | J33: 11.83 | K33: 113436518 | L33: - | M33: - | N33: -
B34: Foreign Portfolio Investors Category II | C34: 39 | D34: 2712554 | E34: 2712554 | F34: 0.28 | G34: 2712554 | H34: 0.28 | I34: 2712554 | J34: 0.28 | K34: 2712554 | L34: - | M34: - | N34: -
B35: Overseas Depositories (holding DRs) (balancing figure) | C35: 0 | D35: 0 | E35: - | F35: 0 | G35: - | H35: 0 | I35: - | J35: 0 | K35: - | L35: - | M35: - | N35: -
B36: Any Other(Institutions (Foreign)) | C36: 0 | D36: 0 | E36: - | F36: 0 | G36: - | H36: 0 | I36: - | J36: 0 | K36: - | L36: - | M36: - | N36: -
B37: Sub Total B2 | C37: 850 | D37: 116149072 | E37: 116149072 | F37: 12.11 | G37: 116149072 | H37: 12.11 | I37: 116149072 | J37: 12.11 | K37: 116149072 | L37: - | M37: - | N37: -
B38: B28) Central Government/ State Government(s)/ President of India | C38: 0 | D38: 0 | E38: - | F38: 0 | G38: - | H38: 0 | I38: - | J38: 0 | K38: - | L38: - | M38: - | N38: -
B39: Central Government / President of India | C39: 3 | D39: 15420 | E39: 15420 | F39: 0 | G39: 15420 | H39: 0 | I39: 15420 | J39: 0 | K39: 15420 | L39: - | M39: - | N39: -
B40: State Government / Governor | C40: 1 | D40: 3 | E40: 3 | F40: 0 | G40: 3 | H40: 0 | I40: 3 | J40: 0 | K40: 3 | L40: - | M40: - | N40: -
B41: Shareholding by Companies or Bodies Corporate where Central / State Government is a promoter | C41: 0 | D41: 0 | E41: - | F41: 0 | G41: - | H41: 0 | I41: - | J41: 0 | K41: - | L41: - | M41: - | N41: -
B42: Sub Total B3 | C42: 4 | D42: 15423 | E42: 15423 | F42: 0 | G42: 15423 | H42: 0 | I42: 15423 | J42: 0 | K42: 15423 | L42: - | M42: - | N42: -
B43: B33) Non-Institutions | C43: 0 | D43: 0 | E43: - | F43: 0 | G43: - | H43: 0 | I43: - | J43: 0 | K43: - | L43: - | M43: - | N43: -
B44: Associate companies / Subsidiaries | C44: 0 | D44: 0 | E44: - | F44: 0 | G44: - | H44: 0 | I44: - | J44: 0 | K44: - | L44: - | M44: - | N44: -
B45: Directors and their relatives (excluding independent directors and nominee directors) | C45: 2 | D45: 38140 | E45: 38140 | F45: 0 | G45: 38140 | H45: 0 | I45: 38140 | J45: 0 | K45: 38140 | L45: - | M45: - | N45: -
B46: Key Managerial Personnel | C46: 1 | D46: 1415 | E46: 1415 | F46: 0 | G46: 1415 | H46: 0 | I46: 1415 | J46: 0 | K46: 1415 | L46: - | M46: - | N46: -
B47: Relatives of promoters (other than 'immediate relatives' of promoters disclosed under 'Promoter and Promoter Group' category) | C47: 0 | D47: 0 | E47: - | F47: 0 | G47: - | H47: 0 | I47: - | J47: 0 | K47: - | L47: - | M47: - | N47: -
B48: Trusts where any person belonging to 'Promoter and Promoter Group' category is 'trustee', 'beneficiary', or 'author of the trust' | C48: 0 | D48: 0 | E48: - | F48: 0 | G48: - | H48: 0 | I48: - | J48: 0 | K48: - | L48: - | M48: - | N48: -
B49: Investor Education and Protection Fund (IEPF) | C49: 1 | D49: 2191478 | E49: 2191478 | F49: 0.23 | G49: 2191478 | H49: 0.23 | I49: 2191478 | J49: 0.23 | K49: 2191478 | L49: - | M49: - | N49: -
B50: Resident Individuals holding nominal share capital up to Rs. 2 lakhs | C50: 964158 | D50: 103196983 | E50: 103196983 | F50: 10.76 | G50: 103196983 | H50: 10.76 | I50: 103196983 | J50: 10.76 | K50: 101025049 | L50: - | M50: - | N50: -
B51: Resident Individuals holding nominal share capital in excess of Rs. 2 lakhs | C51: 13 | D51: 5088891 | E51: 5088891 | F51: 0.53 | G51: 5088891 | H51: 0.53 | I51: 5088891 | J51: 0.53 | K51: 5088891 | L51: - | M51: - | N51: -
B52: Non Resident Indians (NRIs) | C52: 24692 | D52: 11237717 | E52: 11237717 | F52: 1.17 | G52: 11237717 | H52: 1.17 | I52: 11237717 | J52: 1.17 | K52: 10984317 | L52: - | M52: - | N52: -
B53: Foreign Nationals | C53: 6 | D53: 1620 | E53: 1620 | F53: 0 | G53: 1620 | H53: 0 | I53: 1620 | J53: 0 | K53: 1620 | L53: - | M53: - | N53: -
B54: Foreign Companies | C54: 1 | D54: 25 | E54: 25 | F54: 0 | G54: 25 | H54: 0 | I54: 25 | J54: 0 | K54: 25 | L54: - | M54: - | N54: -
B55: Bodies Corporate | C55: 1973 | D55: 3854733 | E55: 3854733 | F55: 0.4 | G55: 3854733 | H55: 0.4 | I55: 3854733 | J55: 0.4 | K55: 3815263 | L55: - | M55: - | N55: -
B56: Any Other (specify) | C56: 9899 | D56: 2880010 | E56: 2880010 | F56: 0.3 | G56: 2880010 | H56: 0.3 | I56: 2880010 | J56: 0.3 | K56: 2878810 | L56: - | M56: - | N56: -
B57: Trusts | C57: 52 | D57: 170447 | E57: 170447 | F57: 0.02 | G57: 170447 | H57: 0.02 | I57: 170447 | J57: 0.02 | K57: 170447 | L57: - | M57: - | N57: -
B58: Unclaimed or Suspense or Escrow Account | C58: 1 | D58: 6840 | E58: 6840 | F58: 0 | G58: 6840 | H58: 0 | I58: 6840 | J58: 0 | K58: 6840 | L58: - | M58: - | N58: -
B59: LLP | C59: 214 | D59: 473322 | E59: 473322 | F59: 0.05 | G59: 473322 | H59: 0.05 | I59: 473322 | J59: 0.05 | K59: 473322 | L59: - | M59: - | N59: -
B60: HUF | C60: 9561 | D60: 2065320 | E60: 2065320 | F60: 0.22 | G60: 2065320 | H60: 0.22 | I60: 2065320 | J60: 0.22 | K60: 2064120 | L60: - | M60: - | N60: -
... B64: B=B1+B2+B3+B4 | C64: 1001716 | D64: 453859097 | E64: 453859097 | F64: 47.32 | G64: 453859097 | H64: 47.32 | I64: 453859097 | J64: 47.32 | K64: 451385103 | L64: - | M64: - | N64: -

Sheet Balance Sheet
B1: Asian Paints
B2: Consolidated Balance Sheet
C3: Mar 26 | D3: 45717 | E3: 45352 | F3: 44986 | G3: 44621
C5: 12 mths | D5: 12 mths | E5: 12 mths | F5: 12 mths | G5: 12 mths
B7: EQUITIES AND LIABILITIES
B8: SHAREHOLDER'S FUNDS | I8: Changes in %
B9: Equity Share Capital | C9: 95.92 | D9: 95.92 | E9: 95.92 | F9: 95.92 | G9: 95.92 | I9: =D9/C9-1 -> 0 | J9: =E9/D9-1 -> 0 | K9: =F9/E9-1 -> 0 | L9: =G9/F9-1 -> 0
B10: Total Share Capital | C10: 95.92 | D10: 95.92 | E10: 95.92 | F10: 95.92 | G10: 95.92 | I10: =D10/C10-1 -> 0 | J10: =E10/D10-1 -> 0 | K10: =F10/E10-1 -> 0 | L10: =G10/F10-1 -> 0
B11: Reserves and Surplus | C11: 21275.67 | D11: 19303.89 | E11: 18632.38 | F11: 15896.31 | G11: 13715.64 | I11: =D11/C11-1 -> -0.092677692 | J11: =E11/D11-1 -> -0.034786253 | K11: =F11/E11-1 -> -0.1468449 | L11: =G11/F11-1 -> -0.13718089
B12: Total Reserves and Surplus | C12: 21275.67 | D12: 19303.89 | E12: 18632.38 | F12: 15896.31 | G12: 13715.64 | I12: =D12/C12-1 -> -0.092677692 | J12: =E12/D12-1 -> -0.034786253 | K12: =F12/E12-1 -> -0.1468449 | L12: =G12/F12-1 -> -0.13718089
B13: Total Shareholders Funds | C13: 21371.59 | D13: 19399.81 | E13: 18728.3 | F13: 15992.23 | G13: 13811.56 | I13: =D13/C13-1 -> -0.092261736 | J13: =E13/D13-1 -> -0.034614257 | K13: =F13/E13-1 -> -0.14609281 | L13: =G13/F13-1 -> -0.13635809
B14: Minority Interest | C14: 643.39 | D14: 659.24 | E14: 695.38 | F14: 453.66 | G14: 387.53 | I14: =D14/C14-1 -> 0.024635136 | J14: =E14/D14-1 -> 0.054820703 | K14: =F14/E14-1 -> -0.3476085 | L14: =G14/F14-1 -> -0.14576996
B15: NON-CURRENT LIABILITIES
B16: Long Term Borrowings | C16: 1247.17 | D16: 259.62 | E16: 54.38 | F16: 76.15 | G16: 44.54 | I16: =D16/C16-1 -> -0.79183271 | J16: =E16/D16-1 -> -0.79054002 | K16: =F16/E16-1 -> 0.400331 | L16: =G16/F16-1 -> -0.41510177
B17: Deferred Tax Liabilities [Net] | C17: 403.26 | D17: 404.91 | E17: 352.17 | F17: 334.84 | G17: 348.85 | I17: =D17/C17-1 -> 0.004091653 | J17: =E17/D17-1 -> -0.13025117 | K17: =F17/E17-1 -> -0.049209189 | L17: =G17/F17-1 -> 0.041840879
B18: Other Long Term Liabilities | C18: 1458.25 | D18: 1248.78 | E18: 1370.34 | F18: 814.49 | G18: 602.66 | I18: =D18/C18-1 -> -0.14364478 | J18: =E18/D18-1 -> 0.097343007 | K18: =F18/E18-1 -> -0.40562926 | L18: =G18/F18-1 -> -0.26007686
B19: Long Term Provisions | C19: 273.8 | D19: 257.78 | E19: 222.56 | F19: 230.7 | G19: 218.32 | I19: =D19/C19-1 -> -0.058509861 | J19: =E19/D19-1 -> -0.13662813 | K19: =F19/E19-1 -> 0.036574407 | L19: =G19/F19-1 -> -0.053662765
B20: Total Non-Current Liabilities | C20: 3382.48 | D20: 2171.09 | E20: 1999.45 | F20: 1456.18 | G20: 1214.37 | I20: =D20/C20-1 -> -0.35813663 | J20: =E20/D20-1 -> -0.079057064 | K20: =F20/E20-1 -> -0.27170972 | L20: =G20/F20-1 -> -0.16605777
B21: CURRENT LIABILITIES
B22: Short Term Borrowings | C22: 1046.09 | D22: 604.13 | E22: 1052.76 | F22: 896.06 | G22: 731.12 | I22: =D22/C22-1 -> -0.42248755 | J22: =E22/D22-1 -> 0.74260507 | K22: =F22/E22-1 -> -0.14884684 | L22: =G22/F22-1 -> -0.1840725
B23: Trade Payables | C23: 3863.04 | D23: 3848 | E23: 3831.34 | F23: 3635.44 | G23: 4164.3 | I23: =D23/C23-1 -> -0.0038933068 | J23: =E23/D23-1 -> -0.0043295218 | K23: =F23/E23-1 -> -0.051130936 | L23: =G23/F23-1 -> 0.14547345
B24: Other Current Liabilities | C24: 4011.32 | D24: 3621.95 | E24: 3554.38 | F24: 3290.22 | G24: 2605.87 | I24: =D24/C24-1 -> -0.097067798 | J24: =E24/D24-1 -> -0.018655697 | K24: =F24/E24-1 -> -0.074319572 | L24: =G24/F24-1 -> -0.20799521
B25: Short Term Provisions | C25: 216.58 | D25: 67.15 | E25: 62.48 | F25: 74.21 | G25: 69.7 | I25: =D25/C25-1 -> -0.6899529 | J25: =E25/D25-1 -> -0.069545793 | K25: =F25/E25-1 -> 0.18774008 | L25: =G25/F25-1 -> -0.060773481
B26: Total Current Liabilities | C26: 9137.03 | D26: 8141.23 | E26: 8500.96 | F26: 7895.93 | G26: 7570.99 | I26: =D26/C26-1 -> -0.10898509 | J26: =E26/D26-1 -> 0.044186198 | K26: =F26/E26-1 -> -0.071171962 | L26: =G26/F26-1 -> -0.041152847
B27: Total Capital And Liabilities | C27: 34534.49 | D27: 30371.37 | E27: 29924.09 | F27: 25798 | G27: 22984.45 | I27: =D27/C27-1 -> -0.12054963 | J27: =E27/D27-1 -> -0.014727027 | K27: =F27/E27-1 -> -0.13788523 | L27: =G27/F27-1 -> -0.10906078
B28: ASSETS
B29: NON-CURRENT ASSETS
B30: Tangible Assets | C30: 9165 | D30: 8631.34 | E30: 6302.47 | F30: 5354.57 | G30: 5090.21 | I30: =D30/C30-1 -> -0.058228041 | J30: =E30/D30-1 -> -0.26981558 | K30: =F30/E30-1 -> -0.15040135 | L30: =G30/F30-1 -> -0.049370911
B31: Intangible Assets | C31: 256.2 | D31: 369.18 | E31: 424.96 | F31: 187.41 | G31: 185.99 | I31: =D31/C31-1 -> 0.44098361 | J31: =E31/D31-1 -> 0.15109161 | K31: =F31/E31-1 -> -0.55899379 | L31: =G31/F31-1 -> -0.0075769703
B32: Capital Work-In-Progress | C32: 1848.67 | D32: 1254.49 | E32: 2698.37 | F32: 1019.59 | G32: 426.43 | I32: =D32/C32-1 -> -0.32140945 | J32: =E32/D32-1 -> 1.1509697 | K32: =F32/E32-1 -> -0.62214596 | L32: =G32/F32-1 -> -0.58176326
B33: Fixed Assets | C33: 11269.87 | D33: 10255.01 | E33: 9425.8 | F33: 6561.57 | G33: 5702.63 | I33: =D33/C33-1 -> -0.090050728 | J33: =E33/D33-1 -> -0.080859014 | K33: =F33/E33-1 -> -0.30387129 | L33: =G33/F33-1 -> -0.13090465
B34: Non-Current Investments | C34: 775.91 | D34: 1479.79 | E34: 1384.51 | F34: 1564.71 | G34: 1066.83 | I34: =D34/C34-1 -> 0.90716707 | J34: =E34/D34-1 -> -0.064387514 | K34: =F34/E34-1 -> 0.13015435 | L34: =G34/F34-1 -> -0.31819315
B35: Deferred Tax Assets [Net] | C35: 15.74 | D35: 16.12 | E35: 23.32 | F35: 18.67 | G35: 26.02 | I35: =D35/C35-1 -> 0.024142313 | J35: =E35/D35-1 -> 0.44665012 | K35: =F35/E35-1 -> -0.19939966 | L35: =G35/F35-1 -> 0.3936797
B36: Long Term Loans And Advances | C36: 1.57 | D36: 0 | E36: 0 | F36: 0 | G36: 0 | I36: =D36/C36-1 -> -1 | J36: 0 | K36: 0 | L36: 0
B37: Other Non-Current Assets | C37: 2067.68 | D37: 1409.19 | E37: 1134.21 | F37: 889.41 | G37: 793.78 | I37: =D37/C37-1 -> -0.31846804 | J37: =E37/D37-1 -> -0.19513337 | K37: =F37/E37-1 -> -0.21583305 | L37: =G37/F37-1 -> -0.10752072
B38: Total Non-Current Assets | C38: 14349.85 | D38: 13379.69 | E38: 12387.03 | F38: 9262.84 | G38: 7832.12 | I38: =D38/C38-1 -> -0.067607675 | J38: =E38/D38-1 -> -0.074191555 | K38: =F38/E38-1 -> -0.25221461 | L38: =G38/F38-1 -> -0.15445803
B39: CURRENT ASSETS
B40: Current Investments | C40: 6285.83 | D40: 3244.96 | E40: 3203.41 | F40: 2697 | G40: 2180.7 | I40: =D40/C40-1 -> -0.48376587 | J40: =E40/D40-1 -> -0.012804472 | K40: =F40/E40-1 -> -0.15808467 | L40: =G40/F40-1 -> -0.19143493
B41: Inventories | C41: 5743.69 | D41: 6719.27 | E41: 5923.41 | F41: 6210.64 | G41: 6152.98 | I41: =D41/C41-1 -> 0.16985248 | J41: =E41/D41-1 -> -0.11844441 | K41: =F41/E41-1 -> 0.04849065 | L41: =G41/F41-1 -> -0.0092840673
B42: Trade Receivables | C42: 4461.8 | D42: 4313.65 | E42: 4889.05 | F42: 4636.94 | G42: 3871.44 | I42: =D42/C42-1 -> -0.033204088 | J42: =E42/D42-1 -> 0.13339052 | K42: =F42/E42-1 -> -0.051566255 | L42: =G42/F42-1 -> -0.16508732
B43: Cash And Cash Equivalents | C43: 1073.68 | D43: 781.98 | E43: 1084.01 | F43: 843.82 | G43: 864.33 | I43: =D43/C43-1 -> -0.27168244 | J43: =E43/D43-1 -> 0.3862375 | K43: =F43/E43-1 -> -0.22157545 | L43: =G43/F43-1 -> 0.024306132
B44: Short Term Loans And Advances | C44: 0.46 | D44: 0 | E44: 0 | F44: 0 | G44: 0 | I44: =D44/C44-1 -> -1 | J44: 0 | K44: 0 | L44: 0
B45: OtherCurrentAssets | C45: 2619.18 | D45: 1931.82 | E45: 2437.18 | F45: 2146.76 | G45: 2082.88 | I45: =D45/C45-1 -> -0.26243328 | J45: =E45/D45-1 -> 0.26159787 | K45: =F45/E45-1 -> -0.11916231 | L45: =G45/F45-1 -> -0.02975647
B46: Total Current Assets | C46: 20184.64 | D46: 16991.68 | E46: 17537.06 | F46: 16535.16 | G46: 15152.33 | I46: =D46/C46-1 -> -0.15818761 | J46: =E46/D46-1 -> 0.032096885 | K46: =F46/E46-1 -> -0.057130443 | L46: =G46/F46-1 -> -0.083629672
B47: Total Assets | C47: 34534.49 | D47: 30371.37 | E47: 29924.09 | F47: 25798 | G47: 22984.45 | I47: =D47/C47-1 -> -0.12054963 | J47: =E47/D47-1 -> -0.014727027 | K47: =F47/E47-1 -> -0.13788523 | L47: =G47/F47-1 -> -0.10906078
B48: OTHER ADDITIONAL INFORMATION
B49: CONTINGENT LIABILITIES, COMMITMENTS
B50: Contingent Liabilities | C50: 0 | D50: 2424.09 | E50: 2845.22 | F50: 2679.89 | G50: 1651.73 | I50: 0 | J50: =E50/D50-1 -> 0.17372705 | K50: =F50/E50-1 -> -0.058107985 | L50: =G50/F50-1 -> -0.38365754
B51: BONUS DETAILS
B52: Bonus Equity Share Capital | C52: 0 | D52: 93.99 | E52: 93.99 | F52: 93.99 | G52: 93.99 | I52: 0 | J52: =E52/D52-1 -> 0 | K52: =F52/E52-1 -> 0 | L52: =G52/F52-1 -> 0
B53: NON-CURRENT INVESTMENTS
B54: Non-Current Investments Quoted Market Value | C54: 0 | D54: 867.39 | E54: 796.11 | F54: 778.74 | G54: 0 | I54: 0 | J54: =E54/D54-1 -> -0.082177567 | K54: =F54/E54-1 -> -0.021818593 | L54: =G54/F54-1 -> -1
B55: Non-Current Investments Unquoted Book Value | C55: 0 | D55: 4.4 | E55: 2 | F55: 4.24 | G55: 517.21 | I55: 0 | J55: =E55/D55-1 -> -0.54545455 | K55: =F55/E55-1 -> 1.12 | L55: =G55/F55-1 -> 120.98349
B56: CURRENT INVESTMENTS
B57: Current Investments Quoted Market Value | C57: 0 | D57: 3244.27 | E57: 3203.41 | F57: 2647.03 | G57: 2180.34 | I57: 0 | J57: =E57/D57-1 -> -0.012594513 | K57: =F57/E57-1 -> -0.17368367 | L57: =G57/F57-1 -> -0.17630703
B58: Current Investments Unquoted Book Value | C58: 0 | D58: 0.71 | E58: 0 | F58: 49.97 | G58: 0.36 | I58: 0 | J58: =E58/D58-1 -> -1 | K58: 0 | L58: =G58/F58-1 -> -0.99279568

Sheet Profit & Loss
B1: Asian Paints
B2: Consolidated Profit & Loss account
C3: Mar 26 | D3: 45717 | E3: 45352 | F3: 44986 | G3: 44621
C5: 12 mths | D5: 12 mths | E5: 12 mths | F5: 12 mths | G5: 12 mths
B7: INCOME | I7: Chnages in %
B8: Revenue From Operations [Gross] | C8: 35516.37 | D8: 33797.36 | E8: 35382.12 | F8: 34367.83 | G8: 28923.48 | I8: =D8/C8-1 -> -0.048400498 | J8: =E8/D8-1 -> 0.046890053 | K8: =F8/E8-1 -> -0.028666739 | L8: =G8/F8-1 -> -0.15841413
B9: Revenue From Operations [Net] | C9: 35516.37 | D9: 33797.36 | E9: 35382.12 | F9: 34367.83 | G9: 28923.48 | I9: =D9/C9-1 -> -0.048400498 | J9: =E9/D9-1 -> 0.046890053 | K9: =F9/E9-1 -> -0.028666739 | L9: =G9/F9-1 -> -0.15841413
B10: Other Operating Revenues | C10: 67.17 | D10: 108.26 | E10: 112.61 | F10: 120.76 | G10: 177.8 | I10: =D10/C10-1 -> 0.61173143 | J10: =E10/D10-1 -> 0.040181046 | K10: =F10/E10-1 -> 0.072373679 | L10: =G10/F10-1 -> 0.47234184
B11: Total Operating Revenues | C11: 35583.54 | D11: 33905.62 | E11: 35494.73 | F11: 34488.59 | G11: 29101.28 | I11: =D11/C11-1 -> -0.047154387 | J11: =E11/D11-1 -> 0.046868631 | K11: =F11/E11-1 -> -0.02834618 | L11: =G11/F11-1 -> -0.15620557
B12: Other Income | C12: 723.8 | D12: 572.61 | E12: 687.96 | F12: 386.48 | G12: 380.01 | I12: =D12/C12-1 -> -0.20888367 | J12: =E12/D12-1 -> 0.20144601 | K12: =F12/E12-1 -> -0.43822315 | L12: =G12/F12-1 -> -0.01674084
B13: Total Revenue | C13: 36307.34 | D13: 34478.23 | E13: 36182.69 | F13: 34875.07 | G13: 29481.29 | I13: =D13/C13-1 -> -0.050378519 | J13: =E13/D13-1 -> 0.049435832 | K13: =F13/E13-1 -> -0.03613938 | L13: =G13/F13-1 -> -0.15466005
B14: EXPENSES
B15: Cost Of Materials Consumed | C15: 15384.05 | D15: 15793.92 | E15: 15868.21 | F15: 17330.58 | G15: 16254.59 | I15: =D15/C15-1 -> 0.026642529 | J15: =E15/D15-1 -> 0.0047037088 | K15: =F15/E15-1 -> 0.092157212 | L15: =G15/F15-1 -> -0.062086208
B16: Purchase Of Stock-In Trade | C16: 4014.05 | D16: 3926.86 | E16: 3858.2 | F16: 4135.65 | G16: 3371.13 | I16: =D16/C16-1 -> -0.021721204 | J16: =E16/D16-1 -> -0.017484708 | K16: =F16/E16-1 -> 0.071911772 | L16: =G16/F16-1 -> -0.1848609
B17: Changes In Inventories Of FG,WIP And Stock-In Trade | C17: 603.68 | D17: -205 | E17: 363.8 | F17: -309.73 | G17: -1324.97 | I17: =D17/C17-1 -> -1.3395839 | J17: =E17/D17-1 -> -2.7746341 | K17: =F17/E17-1 -> -1.8513744 | L17: =G17/F17-1 -> 3.2778226
B18: Employee Benefit Expenses | C18: 2799.59 | D18: 2597.23 | E18: 2326.18 | F18: 2028.07 | G18: 1786.67 | I18: =D18/C18-1 -> -0.072282013 | J18: =E18/D18-1 -> -0.10436118 | K18: =F18/E18-1 -> -0.12815431 | L18: =G18/F18-1 -> -0.11902942
B19: Finance Costs | C19: 195.41 | D19: 227.02 | E19: 205.17 | F19: 144.45 | G19: 95.41 | I19: =D19/C19-1 -> 0.16176245 | J19: =E19/D19-1 -> -0.096247027 | K19: =F19/E19-1 -> -0.2959497 | L19: =G19/F19-1 -> -0.33949463
B20: Depreciation And Amortisation Expenses | C20: 1228.85 | D20: 1026.34 | E20: 853 | F20: 858.02 | G20: 816.36 | I20: =D20/C20-1 -> -0.16479635 | J20: =E20/D20-1 -> -0.1688914 | K20: =F20/E20-1 -> 0.0058851114 | L20: =G20/F20-1 -> -0.048553647
B21: Other Expenses | C21: 6086.25 | D21: 5786.4 | E21: 5493.36 | F21: 5044.18 | G21: 4210.25 | I21: =D21/C21-1 -> -0.04926679 | J21: =E21/D21-1 -> -0.050642887 | K21: =F21/E21-1 -> -0.081767807 | L21: =G21/F21-1 -> -0.16532519
B22: Total Expenses | C22: 30311.88 | D22: 29152.77 | E22: 28967.92 | F22: 29231.22 | G22: 25209.44 | I22: =D22/C22-1 -> -0.038239463 | J22: =E22/D22-1 -> -0.0063407354 | K22: =F22/E22-1 -> 0.0090893651 | L22: =G22/F22-1 -> -0.13758509
B23: Profit/Loss Before Exceptional, ExtraOrdinary Items And Tax | C23: 5995.46 | D23: 5325.46 | E23: 7214.77 | F23: 5643.85 | G23: 4271.85 | I23: =D23/C23-1 -> -0.11175123 | J23: =E23/D23-1 -> 0.35476935 | K23: =F23/E23-1 -> -0.21773667 | L23: =G23/F23-1 -> -0.24309647
B24: Exceptional Items | C24: -157.61 | D24: -363.1 | E24: 0 | F24: -48.87 | G24: -115.7 | I24: =D24/C24-1 -> 1.3037878 | J24: =E24/D24-1 -> -1 | K24: 0 | L24: =G24/F24-1 -> 1.3675056
B25: Profit/Loss Before Tax | C25: 5837.85 | D25: 4962.36 | E25: 7214.77 | F25: 5594.98 | G25: 4156.15 | I25: =D25/C25-1 -> -0.14996788 | J25: =E25/D25-1 -> 0.45389895 | K25: =F25/E25-1 -> -0.22451028 | L25: =G25/F25-1 -> -0.25716446
B26: Tax Expenses-Continued Operations
B27: Current Tax | C27: 1608.75 | D27: 1388.98 | E27: 1836 | F27: 1504.14 | G27: 1161.53 | I27: =D27/C27-1 -> -0.13660917 | J27: =E27/D27-1 -> 0.32183329 | K27: =F27/E27-1 -> -0.18075163 | L27: =G27/F27-1 -> -0.227778
B28: Deferred Tax | C28: 0 | D28: 17.77 | E28: 5.43 | F28: -17.28 | G28: -61.44 | I28: 0 | J28: =E28/D28-1 -> -0.69442881 | K28: =F28/E28-1 -> -4.1823204 | L28: =G28/F28-1 -> 2.5555556
B29: Tax For Earlier Years | C29: 0 | D29: -13.39 | E29: -51.35 | F29: 6.64 | G29: 2.82 | I29: 0 | J29: =E29/D29-1 -> 2.8349515 | K29: =F29/E29-1 -> -1.1293087 | L29: =G29/F29-1 -> -0.5753012
B30: Total Tax Expenses | C30: 1608.75 | D30: 1393.36 | E30: 1790.08 | F30: 1493.5 | G30: 1102.91 | I30: =D30/C30-1 -> -0.13388656 | J30: =E30/D30-1 -> 0.28472182 | K30: =F30/E30-1 -> -0.16567975 | L30: =G30/F30-1 -> -0.26152662
B31: Profit/Loss After Tax And Before ExtraOrdinary Items | C31: 4229.1 | D31: 3569 | E31: 5424.69 | F31: 4101.48 | G31: 3053.24 | I31: =D31/C31-1 -> -0.15608522 | J31: =E31/D31-1 -> 0.51994676 | K31: =F31/E31-1 -> -0.24392362 | L31: =G31/F31-1 -> -0.25557604
B32: Profit/Loss From Continuing Operations | C32: 4229.1 | D32: 3569 | E32: 5424.69 | F32: 4101.48 | G32: 3053.24 | I32: =D32/C32-1 -> -0.15608522 | J32: =E32/D32-1 -> 0.51994676 | K32: =F32/E32-1 -> -0.24392362 | L32: =G32/F32-1 -> -0.25557604
B33: Profit/Loss For The Period | C33: 4229.1 | D33: 3569 | E33: 5424.69 | F33: 4101.48 | G33: 3053.24 | I33: =D33/C33-1 -> -0.15608522 | J33: =E33/D33-1 -> 0.51994676 | K33: =F33/E33-1 -> -0.24392362 | L33: =G33/F33-1 -> -0.25557604
B34: Minority Interest | C34: -69.34 | D34: -42.48 | E34: -97.46 | F34: -88.88 | G34: -54.24 | I34: =D34/C34-1 -> -0.3873666 | J34: =E34/D34-1 -> 1.2942561 | K34: =F34/E34-1 -> -0.088036117 | L34: =G34/F34-1 -> -0.38973897
B35: Share Of Profit/Loss Of Associates | C35: 165.59 | D35: 140.71 | E35: 133 | F35: 93.85 | G35: 31.57 | I35: =D35/C35-1 -> -0.15025062 | J35: =E35/D35-1 -> -0.054793547 | K35: =F35/E35-1 -> -0.2943609 | L35: =G35/F35-1 -> -0.66361215
B36: Consolidated Profit/Loss After MI And Associates | C36: 4325.35 | D36: 3667.23 | E36: 5460.23 | F36: 4106.45 | G36: 3030.57 | I36: =D36/C36-1 -> -0.15215416 | J36: =E36/D36-1 -> 0.48892488 | K36: =F36/E36-1 -> -0.24793461 | L36: =G36/F36-1 -> -0.26199759
B37: OTHER ADDITIONAL INFORMATION
B38: EARNINGS PER SHARE
B39: Basic EPS (Rs.) | C39: 45 | D39: 38 | E39: 57 | F39: 43 | G39: 32 | I39: =D39/C39-1 -> -0.15555556 | J39: =E39/D39-1 -> 0.5 | K39: =F39/E39-1 -> -0.24561404 | L39: =G39/F39-1 -> -0.25581395
B40: Diluted EPS (Rs.) | C40: 45 | D40: 38 | E40: 57 | F40: 43 | G40: 32 | I40: =D40/C40-1 -> -0.15555556 | J40: =E40/D40-1 -> 0.5 | K40: =F40/E40-1 -> -0.24561404 | L40: =G40/F40-1 -> -0.25581395
B41: DIVIDEND AND DIVIDEND PERCENTAGE
B42: Equity Share Dividend | C42: 0 | D42: 3107.91 | E42: 2532.38 | F42: 1908.86 | G42: 1740.95 | I42: 0 | J42: =E42/D42-1 -> -0.18518233 | K42: =F42/E42-1 -> -0.24621897 | L42: =G42/F42-1 -> -0.087963497

Sheet Cash Flow
B1: Asian Paints
B2: Consolidated Cash Flow
C3: Mar '26 | D3: Mar '25 | E3: Mar '24 | F3: Mar '23 | G3: Mar '22
C5: 12 mths | D5: 12 mths | E5: 12 mths | F5: 12 mths | G5: 12 mths
I6: Change in %
B7: Net Profit Before Tax | C7: 5837.85 | D7: 5103.07 | E7: 7347.77 | F7: 5688.83 | G7: 4187.72 | I7: =D7/C7-1 -> -0.12586483 | J7: =E7/D7-1 -> 0.43987247 | K7: =F7/E7-1 -> -0.22577462 | L7: =G7/F7-1 -> -0.26386972
B8: Net Cash From Operating Activities | C8: 7088.18 | D8: 4423.96 | E8: 6103.6 | F8: 4193.43 | G8: 986.49 | I8: =D8/C8-1 -> -0.37586799 | J8: =E8/D8-1 -> 0.37966889 | K8: =F8/E8-1 -> -0.31295793 | L8: =G8/F8-1 -> -0.76475344
B9: Net Cash (used in)/from | C9: -1334.07 | D9: -874.12 | E9: -2517.63 | F9: -1274.64 | G9: -321.69 | I9: =D9/C9-1 -> -0.34477201 | J9: =E9/D9-1 -> 1.8801881 | K9: =F9/E9-1 -> -0.49371433 | L9: =G9/F9-1 -> -0.74762286
B10: Investing Activities
B11: Net Cash (used in)/from Financing Activities | C11: -2376.51 | D11: -3752.58 | E11: -2982.5 | F11: -2140.05 | G11: -1807.61 | I11: =D11/C11-1 -> 0.57902975 | J11: =E11/D11-1 -> -0.20521348 | K11: =F11/E11-1 -> -0.28246438 | L11: =G11/F11-1 -> -0.15534216
B12: Net (decrease)/increase In Cash and Cash Equivalents | C12: 3383.44 | D12: -269.53 | E12: 572.62 | F12: 771.04 | G12: -1137.87 | I12: =D12/C12-1 -> -1.0796615 | J12: =E12/D12-1 -> -3.124513 | K12: =F12/E12-1 -> 0.34651252 | L12: =G12/F12-1 -> -2.47576
B13: Opening Cash & Cash Equivalents | C13: 3357.42 | D13: 3626.95 | E13: 3054.33 | F13: 2283.29 | G13: 3421.16 | I13: =D13/C13-1 -> 0.080278905 | J13: =E13/D13-1 -> -0.15787921 | K13: =F13/E13-1 -> -0.25244162 | L13: =G13/F13-1 -> 0.49834668
B14: Closing Cash & Cash Equivalents | C14: 6740.86 | D14: 3357.42 | E14: 3626.95 | F14: 3054.33 | G14: 2283.29 | I14: =D14/C14-1 -> -0.50193002 | J14: =E14/D14-1 -> 0.080278905 | K14: =F14/E14-1 -> -0.15787921 | L14: =G14/F14-1 -> -0.25244162

Sheet Stock Analysis
B18: Recommendation - Asian Paints Ltd: | I18: Financial Year | J18: Revenue | K18: PAT | L18: Revenue Change | M18: PAT Change
B19: "HOLD" Asian Paints Ltd remains India's dominant decorative paint franchise with 52% market share, but FY25 marks a structural inflection point driven by intensifying competition from Grasim's Birla Opus, muted urban demand, and raw-material-led margin compression. FY25 standalone revenue declined 4.5% YoY to ₹33,906 Cr, while net profit fell 34% YoY to ₹3,569 Cr OPM contracted from 21.7% to 17.1%, the sharpest single-year margin compression in over a decade. The chart reflects this reset: the stock has corrected 22% from its 52-week high, partially de-rating from 70x P/E toward 55x still elevated relative to peers (Berger at 58x, Kansai at 31x) and not yet at levels that price in the market share risk fully. Birla Opus captured ~6-10% market share in FY25 alone, with Asian Paints losing ~7 percentage points (59% → 52%); Morgan Stanley flags a further 209bps loss through FY28. Long-term moat remains intact: 70,000+ dealer touchpoints, brand equity built over 75+ years, low leverage (D/E < 0.1x), consistent 65%+ dividend payout ratio, and ROCE of 27.2% well above cost of capital. A recovery in urban housing demand, raw material cost tailwinds (crude-linked inputs), and new capacity from Vizag and Mysuru plants could support earnings revival in FY27. BUY trigger: price dip to ₹2,100-2,200 or visible PAT recovery of 20%+ in H1 FY26 results. | I19: 2024-25 | J19: 33906 | K19: 3569 | L19: =(J19-J20)/J20 -> -0.044766869 | M19: =(K19-K20)/K20 -> -0.346337
I20: 2023-24 | J20: 35495 | K20: 5460 | L20: =(J20-J21)/J21 -> 0.02916872 | M20: =(K20-K21)/K21 -> 0.32976132
I21: 2022-23 | J21: 34489 | K21: 4106 | L21: =(J21-J22)/J22 -> 0.192442 | M21: =(K21-K22)/K22 -> 0.0012192148
I22: 2021-22 | J22: 28923 | K22: 4101 | L22: =(J22-J23)/J23 -> 0.33212049 | M22: =(K22-K23)/K23 -> 0.29043424
I23: 2020-21 | J23: 21712 | K23: 3178 | L23: =IFERROR(J23/J24,0) -> 0 | M23: =IFERROR(K23/K24,0) -> 0

Sheet Historical Analysis
B1: Historical Financial Statement
B3: Years | C3: 2022 | D3: 2023 | E3: 2024 | F3: 2025 | G3: 2026
B4: Income statement
B5: Revenue from Operations | C5: ='Profit & Loss'!G9 -> 28923.48 | D5: ='Profit & Loss'!F9 -> 34367.83 | E5: ='Profit & Loss'!E9 -> 35382.12 | F5: ='Profit & Loss'!D9 -> 33797.36 | G5: ='Profit & Loss'!C9 -> 35516.37
B6: Revenue Growth | D6: ='Profit & Loss'!F9/'Profit & Loss'!G9-1 -> 0.18823288 | E6: ='Profit & Loss'!E9/'Profit & Loss'!F9-1 -> 0.029512774 | F6: ='Profit & Loss'!D9/'Profit & Loss'!E9-1 -> -0.044789854 | G6: ='Profit & Loss'!C9/'Profit & Loss'!D9-1 -> 0.050862257
B8: Total Operating Expenses (ex Finance & Depr) | C8: ='Profit & Loss'!G22-'Profit & Loss'!G19-'Profit & Loss'!G20 -> 24297.67 | D8: ='Profit & Loss'!F22-'Profit & Loss'!F19-'Profit & Loss'!F20 -> 28228.75 | E8: ='Profit & Loss'!E22-'Profit & Loss'!E19-'Profit & Loss'!E20 -> 27909.75 | F8: ='Profit & Loss'!D22-'Profit & Loss'!D19-'Profit & Loss'!D20 -> 27899.41 | G8: ='Profit & Loss'!C22-'Profit & Loss'!C19-'Profit & Loss'!C20 -> 28887.62
B9: Opex % Revenue | C9: =('Profit & Loss'!G22-'Profit & Loss'!G19-'Profit & Loss'!G20)/'Profit & Loss'!G9 -> 0.84006731 | D9: =('Profit & Loss'!F22-'Profit & Loss'!F19-'Profit & Loss'!F20)/'Profit & Loss'!F9 -> 0.82137132 | E9: =('Profit & Loss'!E22-'Profit & Loss'!E19-'Profit & Loss'!E20)/'Profit & Loss'!E9 -> 0.78880943 | F9: =('Profit & Loss'!D22-'Profit & Loss'!D19-'Profit & Loss'!D20)/'Profit & Loss'!D9 -> 0.82549081 | G9: =('Profit & Loss'!C22-'Profit & Loss'!C19-'Profit & Loss'!C20)/'Profit & Loss'!C9 -> 0.81336071
B11: EBITDA | C11: =C5-C8 -> 4625.81 | D11: =D5-D8 -> 6139.08 | E11: =E5-E8 -> 7472.37 | F11: =F5-F8 -> 5897.95 | G11: =G5-G8 -> 6628.75
B12: EBITDA Margins | C12: =('Profit & Loss'!G23+'Profit & Loss'!G19+'Profit & Loss'!G20)/'Profit & Loss'!G9 -> 0.17921841 | D12: =('Profit & Loss'!F23+'Profit & Loss'!F19+'Profit & Loss'!F20)/'Profit & Loss'!F9 -> 0.19338783 | E12: =('Profit & Loss'!E23+'Profit & Loss'!E19+'Profit & Loss'!E20)/'Profit & Loss'!E9 -> 0.23381697 | F12: =('Profit & Loss'!D23+'Profit & Loss'!D19+'Profit & Loss'!D20)/'Profit & Loss'!D9 -> 0.19465485 | G12: =('Profit & Loss'!C23+'Profit & Loss'!C19+'Profit & Loss'!C20)/'Profit & Loss'!C9 -> 0.20890986
B14: Depreciation & Amortisation | C14: ='Profit & Loss'!G20 -> 816.36 | D14: ='Profit & Loss'!F20 -> 858.02 | E14: ='Profit & Loss'!E20 -> 853 | F14: ='Profit & Loss'!D20 -> 1026.34 | G14: ='Profit & Loss'!C20 -> 1228.85
B15: Depreciation % of Sales | C15: ='Profit & Loss'!G20/'Profit & Loss'!G9 -> 0.028224819 | D15: ='Profit & Loss'!F20/'Profit & Loss'!F9 -> 0.024965789 | E15: ='Profit & Loss'!E20/'Profit & Loss'!E9 -> 0.024108222 | F15: ='Profit & Loss'!D20/'Profit & Loss'!D9 -> 0.030367461 | G15: ='Profit & Loss'!C20/'Profit & Loss'!C9 -> 0.034599538
B17: EBIT | C17: =C11-C14 -> 3809.45 | D17: =D11-D14 -> 5281.06 | E17: =E11-E14 -> 6619.37 | F17: =F11-F14 -> 4871.61 | G17: =G11-G14 -> 5399.9
B18: EBIT Margin | C18: =('Profit & Loss'!G23+'Profit & Loss'!G19)/'Profit & Loss'!G9 -> 0.15099359 | D18: =('Profit & Loss'!F23+'Profit & Loss'!F19)/'Profit & Loss'!F9 -> 0.16842204 | E18: =('Profit & Loss'!E23+'Profit & Loss'!E19)/'Profit & Loss'!E9 -> 0.20970875 | F18: =('Profit & Loss'!D23+'Profit & Loss'!D19)/'Profit & Loss'!D9 -> 0.16428739 | G18: =('Profit & Loss'!C23+'Profit & Loss'!C19)/'Profit & Loss'!C9 -> 0.17431033
B20: Finance Costs | C20: ='Profit & Loss'!G19 -> 95.41 | D20: ='Profit & Loss'!F19 -> 144.45 | E20: ='Profit & Loss'!E19 -> 205.17 | F20: ='Profit & Loss'!D19 -> 227.02 | G20: ='Profit & Loss'!C19 -> 195.41
B21: Finance Costs % of Sales | C21: ='Profit & Loss'!G19/'Profit & Loss'!G9 -> 0.003298704 | D21: ='Profit & Loss'!F19/'Profit & Loss'!F9 -> 0.0042030585 | E21: ='Profit & Loss'!E19/'Profit & Loss'!E9 -> 0.0057986915 | F21: ='Profit & Loss'!D19/'Profit & Loss'!D9 -> 0.0067170927 | G21: ='Profit & Loss'!C19/'Profit & Loss'!C9 -> 0.0055019699
B23: Other Income | C23: ='Profit & Loss'!G12 -> 380.01 | D23: ='Profit & Loss'!F12 -> 386.48 | E23: ='Profit & Loss'!E12 -> 687.96 | F23: ='Profit & Loss'!D12 -> 572.61 | G23: ='Profit & Loss'!C12 -> 723.8
B25: Profit Before Tax | C25: ='Profit & Loss'!G23 -> 4271.85 | D25: ='Profit & Loss'!F23 -> 5643.85 | E25: ='Profit & Loss'!E23 -> 7214.77 | F25: ='Profit & Loss'!D23 -> 5325.46 | G25: ='Profit & Loss'!C23 -> 5995.46
B26: PBT % Sales | C26: ='Profit & Loss'!G23/'Profit & Loss'!G9 -> 0.14769488 | D26: ='Profit & Loss'!F23/'Profit & Loss'!F9 -> 0.16421898 | E26: ='Profit & Loss'!E23/'Profit & Loss'!E9 -> 0.20391005 | F26: ='Profit & Loss'!D23/'Profit & Loss'!D9 -> 0.1575703 | G26: ='Profit & Loss'!C23/'Profit & Loss'!C9 -> 0.16880836
B28: Total Tax Expenses | C28: ='Profit & Loss'!G30 -> 1102.91 | D28: ='Profit & Loss'!F30 -> 1493.5 | E28: ='Profit & Loss'!E30 -> 1790.08 | F28: ='Profit & Loss'!D30 -> 1393.36 | G28: ='Profit & Loss'!C30 -> 1608.75
B29: Effective Tax Rate | C29: ='Profit & Loss'!G30/'Profit & Loss'!G25 -> 0.26536819 | D29: ='Profit & Loss'!F30/'Profit & Loss'!F25 -> 0.26693572 | E29: ='Profit & Loss'!E30/'Profit & Loss'!E25 -> 0.24811325 | F29: ='Profit & Loss'!D30/'Profit & Loss'!D25 -> 0.28078576 | G29: ='Profit & Loss'!C30/'Profit & Loss'!C25 -> 0.27557234
B31: Net Profit | C31: ='Profit & Loss'!G36 -> 3030.57 | D31: ='Profit & Loss'!F36 -> 4106.45 | E31: ='Profit & Loss'!E36 -> 5460.23 | F31: ='Profit & Loss'!D36 -> 3667.23 | G31: ='Profit & Loss'!C36 -> 4325.35
B32: Net Margins | C32: ='Profit & Loss'!G36/'Profit & Loss'!G9 -> 0.10477889 | D32: ='Profit & Loss'!F36/'Profit & Loss'!F9 -> 0.11948529 | E32: ='Profit & Loss'!E36/'Profit & Loss'!E9 -> 0.15432173 | F32: ='Profit & Loss'!D36/'Profit & Loss'!D9 -> 0.1085064 | G32: ='Profit & Loss'!C36/'Profit & Loss'!C9 -> 0.12178469
B34: Basic EPS (₹) | C34: ='Profit & Loss'!G39 -> 32 | D34: ='Profit & Loss'!F39 -> 43 | E34: ='Profit & Loss'!E39 -> 57 | F34: ='Profit & Loss'!D39 -> 38 | G34: ='Profit & Loss'!C39 -> 45
B35: EPS Growth % | D35: ='Profit & Loss'!F39/'Profit & Loss'!G39-1 -> 0.34375 | E35: ='Profit & Loss'!E39/'Profit & Loss'!F39-1 -> 0.3255814 | F35: ='Profit & Loss'!D39/'Profit & Loss'!E39-1 -> -0.33333333 | G35: ='Profit & Loss'!C39/'Profit & Loss'!D39-1 -> 0.18421053
B38: Balance Sheet | C38: 2022 | D38: 2023 | E38: 2024 | F38: 2025 | G38: 2026
B39: Equity Share Capital | C39: ='Balance Sheet'!G9 -> 95.92 | D39: ='Balance Sheet'!F9 -> 95.92 | E39: ='Balance Sheet'!E9 -> 95.92 | F39: ='Balance Sheet'!D9 -> 95.92 | G39: ='Balance Sheet'!C9 -> 95.92
B40: Reserves & Surplus | C40: ='Balance Sheet'!G11 -> 13715.64 | D40: ='Balance Sheet'!F11 -> 15896.31 | E40: ='Balance Sheet'!E11 -> 18632.38 | F40: ='Balance Sheet'!D11 -> 19303.89 | G40: ='Balance Sheet'!C11 -> 21275.67
B41: Total Shareholders Funds | C41: ='Balance Sheet'!G13 -> 13811.56 | D41: ='Balance Sheet'!F13 -> 15992.23 | E41: ='Balance Sheet'!E13 -> 18728.3 | F41: ='Balance Sheet'!D13 -> 19399.81 | G41: ='Balance Sheet'!C13 -> 21371.59
B42: Minority Interest | C42: ='Balance Sheet'!G14 -> 387.53 | D42: ='Balance Sheet'!F14 -> 453.66 | E42: ='Balance Sheet'!E14 -> 695.38 | F42: ='Balance Sheet'!D14 -> 659.24 | G42: ='Balance Sheet'!C14 -> 643.39
B43: Long Term Borrowings | C43: ='Balance Sheet'!G16 -> 44.54 | D43: ='Balance Sheet'!F16 -> 76.15 | E43: ='Balance Sheet'!E16 -> 54.38 | F43: ='Balance Sheet'!D16 -> 259.62 | G43: ='Balance Sheet'!C16 -> 1247.17
B44: Short Term Borrowings | C44: ='Balance Sheet'!G22 -> 731.12 | D44: ='Balance Sheet'!F22 -> 896.06 | E44: ='Balance Sheet'!E22 -> 1052.76 | F44: ='Balance Sheet'!D22 -> 604.13 | G44: ='Balance Sheet'!C22 -> 1046.09
B45: Total Borrowings | C45: ='Balance Sheet'!G16+'Balance Sheet'!G22 -> 775.66 | D45: ='Balance Sheet'!F16+'Balance Sheet'!F22 -> 972.21 | E45: ='Balance Sheet'!E16+'Balance Sheet'!E22 -> 1107.14 | F45: ='Balance Sheet'!D16+'Balance Sheet'!D22 -> 863.75 | G45: ='Balance Sheet'!C16+'Balance Sheet'!C22 -> 2293.26
B46: Other Liabilities | C46: ='Balance Sheet'!G17+'Balance Sheet'!G18+'Balance Sheet'!G19 -> 1169.83 | D46: ='Balance Sheet'!F17+'Balance Sheet'!F18+'Balance Sheet'!F19 -> 1380.03 | E46: ='Balance Sheet'!E17+'Balance Sheet'!E18+'Balance Sheet'!E19 -> 1945.07 | F46: ='Balance Sheet'!D17+'Balance Sheet'!D18+'Balance Sheet'!D19 -> 1911.47 | G46: ='Balance Sheet'!C17+'Balance Sheet'!C18+'Balance Sheet'!C19 -> 2135.31
B47: Total Current Liabilities | C47: ='Balance Sheet'!G26 -> 7570.99 | D47: ='Balance Sheet'!F26 -> 7895.93 | E47: ='Balance Sheet'!E26 -> 8500.96 | F47: ='Balance Sheet'!D26 -> 8141.23 | G47: ='Balance Sheet'!C26 -> 9137.03
B48: Total Liabilities | C48: ='Balance Sheet'!G20+'Balance Sheet'!G26 -> 8785.36 | D48: ='Balance Sheet'!F20+'Balance Sheet'!F26 -> 9352.11 | E48: ='Balance Sheet'!E20+'Balance Sheet'!E26 -> 10500.41 | F48: ='Balance Sheet'!D20+'Balance Sheet'!D26 -> 10312.32 | G48: ='Balance Sheet'!C20+'Balance Sheet'!C26 -> 12519.51
B50: Fixed Assets (Net Block) | C50: ='Balance Sheet'!G33 -> 5702.63 | D50: ='Balance Sheet'!F33 -> 6561.57 | E50: ='Balance Sheet'!E33 -> 9425.8 | F50: ='Balance Sheet'!D33 -> 10255.01 | G50: ='Balance Sheet'!C33 -> 11269.87
B51: Capital Work in Progress | C51: ='Balance Sheet'!G32 -> 426.43 | D51: ='Balance Sheet'!F32 -> 1019.59 | E51: ='Balance Sheet'!E32 -> 2698.37 | F51: ='Balance Sheet'!D32 -> 1254.49 | G51: ='Balance Sheet'!C32 -> 1848.67
B52: Non-Current Investments | C52: ='Balance Sheet'!G34 -> 1066.83 | D52: ='Balance Sheet'!F34 -> 1564.71 | E52: ='Balance Sheet'!E34 -> 1384.51 | F52: ='Balance Sheet'!D34 -> 1479.79 | G52: ='Balance Sheet'!C34 -> 775.91
B53: Other Non-Current Assets | C53: ='Balance Sheet'!G37 -> 793.78 | D53: ='Balance Sheet'!F37 -> 889.41 | E53: ='Balance Sheet'!E37 -> 1134.21 | F53: ='Balance Sheet'!D37 -> 1409.19 | G53: ='Balance Sheet'!C37 -> 2067.68
B54: Total Non Current Assets | C54: ='Balance Sheet'!G38 -> 7832.12 | D54: ='Balance Sheet'!F38 -> 9262.84 | E54: ='Balance Sheet'!E38 -> 12387.03 | F54: ='Balance Sheet'!D38 -> 13379.69 | G54: ='Balance Sheet'!C38 -> 14349.85
B56: Trade Receivables | C56: ='Balance Sheet'!G42 -> 3871.44 | D56: ='Balance Sheet'!F42 -> 4636.94 | E56: ='Balance Sheet'!E42 -> 4889.05 | F56: ='Balance Sheet'!D42 -> 4313.65 | G56: ='Balance Sheet'!C42 -> 4461.8
B57: Inventories | C57: ='Balance Sheet'!G41 -> 6152.98 | D57: ='Balance Sheet'!F41 -> 6210.64 | E57: ='Balance Sheet'!E41 -> 5923.41 | F57: ='Balance Sheet'!D41 -> 6719.27 | G57: ='Balance Sheet'!C41 -> 5743.69
B58: Cash & Bank | C58: ='Balance Sheet'!G43 -> 864.33 | D58: ='Balance Sheet'!F43 -> 843.82 | E58: ='Balance Sheet'!E43 -> 1084.01 | F58: ='Balance Sheet'!D43 -> 781.98 | G58: ='Balance Sheet'!C43 -> 1073.68
B59: Total Current Assets | C59: ='Balance Sheet'!G46 -> 15152.33 | D59: ='Balance Sheet'!F46 -> 16535.16 | E59: ='Balance Sheet'!E46 -> 17537.06 | F59: ='Balance Sheet'!D46 -> 16991.68 | G59: ='Balance Sheet'!C46 -> 20184.64
B61: Total Assets | C61: ='Balance Sheet'!G47 -> 22984.45 | D61: ='Balance Sheet'!F47 -> 25798 | E61: ='Balance Sheet'!E47 -> 29924.09 | F61: ='Balance Sheet'!D47 -> 30371.37 | G61: ='Balance Sheet'!C47 -> 34534.49

Sheet Ratio Analysis
B1: RATIO ANALYSIS
B3: Ratio | C3: 2022 | D3: 2023 | E3: 2024 | F3: 2025 | G3: 2026 | H3: 5Y Avg
B4: Income Statement Ratios
B5: Sales Growth | D5: ='Profit & Loss'!F9/'Profit & Loss'!G9-1 -> 0.18823288 | E5: ='Profit & Loss'!E9/'Profit & Loss'!F9-1 -> 0.029512774 | F5: ='Profit & Loss'!D9/'Profit & Loss'!E9-1 -> -0.044789854 | G5: ='Profit & Loss'!C9/'Profit & Loss'!D9-1 -> 0.050862257 | H5: =AVERAGE(D5,E5,F5,G5) -> 0.055954515
B6: EBITDA | C6: ='Profit & Loss'!G23+'Profit & Loss'!G19+'Profit & Loss'!G20 -> 5183.62 | D6: ='Profit & Loss'!F23+'Profit & Loss'!F19+'Profit & Loss'!F20 -> 6646.32 | E6: ='Profit & Loss'!E23+'Profit & Loss'!E19+'Profit & Loss'!E20 -> 8272.94 | F6: ='Profit & Loss'!D23+'Profit & Loss'!D19+'Profit & Loss'!D20 -> 6578.82 | G6: ='Profit & Loss'!C23+'Profit & Loss'!C19+'Profit & Loss'!C20 -> 7419.72 | H6: =AVERAGE(C6,D6,E6,F6,G6) -> 6820.284
B7: EBITDA Margins | C7: =('Profit & Loss'!G23+'Profit & Loss'!G19+'Profit & Loss'!G20)/'Profit & Loss'!G9 -> 0.17921841 | D7: =('Profit & Loss'!F23+'Profit & Loss'!F19+'Profit & Loss'!F20)/'Profit & Loss'!F9 -> 0.19338783 | E7: =('Profit & Loss'!E23+'Profit & Loss'!E19+'Profit & Loss'!E20)/'Profit & Loss'!E9 -> 0.23381697 | F7: =('Profit & Loss'!D23+'Profit & Loss'!D19+'Profit & Loss'!D20)/'Profit & Loss'!D9 -> 0.19465485 | G7: =('Profit & Loss'!C23+'Profit & Loss'!C19+'Profit & Loss'!C20)/'Profit & Loss'!C9 -> 0.20890986 | H7: =AVERAGE(C7,D7,E7,F7,G7) -> 0.20199758
B8: EBIT | C8: ='Profit & Loss'!G23+'Profit & Loss'!G19 -> 4367.26 | D8: ='Profit & Loss'!F23+'Profit & Loss'!F19 -> 5788.3 | E8: ='Profit & Loss'!E23+'Profit & Loss'!E19 -> 7419.94 | F8: ='Profit & Loss'!D23+'Profit & Loss'!D19 -> 5552.48 | G8: ='Profit & Loss'!C23+'Profit & Loss'!C19 -> 6190.87 | H8: =AVERAGE(C8,D8,E8,F8,G8) -> 5863.77
B9: EBIT Margin | C9: =('Profit & Loss'!G23+'Profit & Loss'!G19)/'Profit & Loss'!G9 -> 0.15099359 | D9: =('Profit & Loss'!F23+'Profit & Loss'!F19)/'Profit & Loss'!F9 -> 0.16842204 | E9: =('Profit & Loss'!E23+'Profit & Loss'!E19)/'Profit & Loss'!E9 -> 0.20970875 | F9: =('Profit & Loss'!D23+'Profit & Loss'!D19)/'Profit & Loss'!D9 -> 0.16428739 | G9: =('Profit & Loss'!C23+'Profit & Loss'!C19)/'Profit & Loss'!C9 -> 0.17431033 | H9: =AVERAGE(C9,D9,E9,F9,G9) -> 0.17354442
B10: Finance Costs | C10: ='Profit & Loss'!G19 -> 95.41 | D10: ='Profit & Loss'!F19 -> 144.45 | E10: ='Profit & Loss'!E19 -> 205.17 | F10: ='Profit & Loss'!D19 -> 227.02 | G10: ='Profit & Loss'!C19 -> 195.41 | H10: =AVERAGE(C10,D10,E10,F10,G10) -> 173.492
B11: Finance Costs % Revenue | C11: ='Profit & Loss'!G19/'Profit & Loss'!G9 -> 0.003298704 | D11: ='Profit & Loss'!F19/'Profit & Loss'!F9 -> 0.0042030585 | E11: ='Profit & Loss'!E19/'Profit & Loss'!E9 -> 0.0057986915 | F11: ='Profit & Loss'!D19/'Profit & Loss'!D9 -> 0.0067170927 | G11: ='Profit & Loss'!C19/'Profit & Loss'!C9 -> 0.0055019699 | H11: =AVERAGE(C11,D11,E11,F11,G11) -> 0.0051039033
B12: Depreciation | C12: ='Profit & Loss'!G20 -> 816.36 | D12: ='Profit & Loss'!F20 -> 858.02 | E12: ='Profit & Loss'!E20 -> 853 | F12: ='Profit & Loss'!D20 -> 1026.34 | G12: ='Profit & Loss'!C20 -> 1228.85 | H12: =AVERAGE(C12,D12,E12,F12,G12) -> 956.514
B13: Depreciation % of Sales | C13: ='Profit & Loss'!G20/'Profit & Loss'!G9 -> 0.028224819 | D13: ='Profit & Loss'!F20/'Profit & Loss'!F9 -> 0.024965789 | E13: ='Profit & Loss'!E20/'Profit & Loss'!E9 -> 0.024108222 | F13: ='Profit & Loss'!D20/'Profit & Loss'!D9 -> 0.030367461 | G13: ='Profit & Loss'!C20/'Profit & Loss'!C9 -> 0.034599538 | H13: =AVERAGE(C13,D13,E13,F13,G13) -> 0.028453166
B14: PBT | C14: ='Profit & Loss'!G23 -> 4271.85 | D14: ='Profit & Loss'!F23 -> 5643.85 | E14: ='Profit & Loss'!E23 -> 7214.77 | F14: ='Profit & Loss'!D23 -> 5325.46 | G14: ='Profit & Loss'!C23 -> 5995.46 | H14: =AVERAGE(C14,D14,E14,F14,G14) -> 5690.278
B15: PBT Margin | C15: ='Profit & Loss'!G23/'Profit & Loss'!G9 -> 0.14769488 | D15: ='Profit & Loss'!F23/'Profit & Loss'!F9 -> 0.16421898 | E15: ='Profit & Loss'!E23/'Profit & Loss'!E9 -> 0.20391005 | F15: ='Profit & Loss'!D23/'Profit & Loss'!D9 -> 0.1575703 | G15: ='Profit & Loss'!C23/'Profit & Loss'!C9 -> 0.16880836 | H15: =AVERAGE(C15,D15,E15,F15,G15) -> 0.16844051
B16: Net Profit | C16: ='Profit & Loss'!G36 -> 3030.57 | D16: ='Profit & Loss'!F36 -> 4106.45 | E16: ='Profit & Loss'!E36 -> 5460.23 | F16: ='Profit & Loss'!D36 -> 3667.23 | G16: ='Profit & Loss'!C36 -> 4325.35 | H16: =AVERAGE(C16,D16,E16,F16,G16) -> 4117.966
B17: Net Margins | C17: ='Profit & Loss'!G36/'Profit & Loss'!G9 -> 0.10477889 | D17: ='Profit & Loss'!F36/'Profit & Loss'!F9 -> 0.11948529 | E17: ='Profit & Loss'!E36/'Profit & Loss'!E9 -> 0.15432173 | F17: ='Profit & Loss'!D36/'Profit & Loss'!D9 -> 0.1085064 | G17: ='Profit & Loss'!C36/'Profit & Loss'!C9 -> 0.12178469 | H17: =AVERAGE(C17,D17,E17,F17,G17) -> 0.1217754
B18: Earnings Per Share | C18: ='Profit & Loss'!G39 -> 32 | D18: ='Profit & Loss'!F39 -> 43 | E18: ='Profit & Loss'!E39 -> 57 | F18: ='Profit & Loss'!D39 -> 38 | G18: ='Profit & Loss'!C39 -> 45 | H18: =AVERAGE(C18,D18,E18,F18,G18) -> 43
B19: EPS Growth % | D19: ='Profit & Loss'!F39/'Profit & Loss'!G39-1 -> 0.34375 | E19: ='Profit & Loss'!E39/'Profit & Loss'!F39-1 -> 0.3255814 | F19: ='Profit & Loss'!D39/'Profit & Loss'!E39-1 -> -0.33333333 | G19: ='Profit & Loss'!C39/'Profit & Loss'!D39-1 -> 0.18421053 | H19: =AVERAGE(D19,E19,F19,G19) -> 0.13005215
B21: Balance Statement Ratios
B22: Total Shareholders Funds | C22: ='Balance Sheet'!G13 -> 13811.56 | D22: ='Balance Sheet'!F13 -> 15992.23 | E22: ='Balance Sheet'!E13 -> 18728.3 | F22: ='Balance Sheet'!D13 -> 19399.81 | G22: ='Balance Sheet'!C13 -> 21371.59 | H22: =AVERAGE(C22,D22,E22,F22,G22) -> 17860.698
B23: Total Equity incl. Minority Interest | C23: ='Balance Sheet'!G13+'Balance Sheet'!G14 -> 14199.09 | D23: ='Balance Sheet'!F13+'Balance Sheet'!F14 -> 16445.89 | E23: ='Balance Sheet'!E13+'Balance Sheet'!E14 -> 19423.68 | F23: ='Balance Sheet'!D13+'Balance Sheet'!D14 -> 20059.05 | G23: ='Balance Sheet'!C13+'Balance Sheet'!C14 -> 22014.98 | H23: =AVERAGE(C23,D23,E23,F23,G23) -> 18428.538
B24: Long Term Borrowings | C24: ='Balance Sheet'!G16 -> 44.54 | D24: ='Balance Sheet'!F16 -> 76.15 | E24: ='Balance Sheet'!E16 -> 54.38 | F24: ='Balance Sheet'!D16 -> 259.62 | G24: ='Balance Sheet'!C16 -> 1247.17 | H24: =AVERAGE(C24,D24,E24,F24,G24) -> 336.372
B25: Short Term Borrowings | C25: ='Balance Sheet'!G22 -> 731.12 | D25: ='Balance Sheet'!F22 -> 896.06 | E25: ='Balance Sheet'!E22 -> 1052.76 | F25: ='Balance Sheet'!D22 -> 604.13 | G25: ='Balance Sheet'!C22 -> 1046.09 | H25: =AVERAGE(C25,D25,E25,F25,G25) -> 866.032
B26: Gross Debt | C26: ='Balance Sheet'!G16+'Balance Sheet'!G22 -> 775.66 | D26: ='Balance Sheet'!F16+'Balance Sheet'!F22 -> 972.21 | E26: ='Balance Sheet'!E16+'Balance Sheet'!E22 -> 1107.14 | F26: ='Balance Sheet'!D16+'Balance Sheet'!D22 -> 863.75 | G26: ='Balance Sheet'!C16+'Balance Sheet'!C22 -> 2293.26 | H26: =AVERAGE(C26,D26,E26,F26,G26) -> 1202.404
B27: Cash & Equivalents | C27: ='Balance Sheet'!G43 -> 864.33 | D27: ='Balance Sheet'!F43 -> 843.82 | E27: ='Balance Sheet'!E43 -> 1084.01 | F27: ='Balance Sheet'!D43 -> 781.98 | G27: ='Balance Sheet'!C43 -> 1073.68 | H27: =AVERAGE(C27,D27,E27,F27,G27) -> 929.564
B28: Net Debt | C28: ='Balance Sheet'!G16+'Balance Sheet'!G22-'Balance Sheet'!G43 -> -88.67 | D28: ='Balance Sheet'!F16+'Balance Sheet'!F22-'Balance Sheet'!F43 -> 128.39 | E28: ='Balance Sheet'!E16+'Balance Sheet'!E22-'Balance Sheet'!E43 -> 23.13 | F28: ='Balance Sheet'!D16+'Balance Sheet'!D22-'Balance Sheet'!D43 -> 81.77 | G28: ='Balance Sheet'!C16+'Balance Sheet'!C22-'Balance Sheet'!C43 -> 1219.58 | H28: =AVERAGE(C28,D28,E28,F28,G28) -> 272.84
B29: Total Assets | C29: ='Balance Sheet'!G47 -> 22984.45 | D29: ='Balance Sheet'!F47 -> 25798 | E29: ='Balance Sheet'!E47 -> 29924.09 | F29: ='Balance Sheet'!D47 -> 30371.37 | G29: ='Balance Sheet'!C47 -> 34534.49 | H29: =AVERAGE(C29,D29,E29,F29,G29) -> 28722.48
B30: Fixed Assets | C30: ='Balance Sheet'!G33 -> 5702.63 | D30: ='Balance Sheet'!F33 -> 6561.57 | E30: ='Balance Sheet'!E33 -> 9425.8 | F30: ='Balance Sheet'!D33 -> 10255.01 | G30: ='Balance Sheet'!C33 -> 11269.87 | H30: =AVERAGE(C30,D30,E30,F30,G30) -> 8642.976
B32: Return Ratios
B33: RoE: PAT / Equity (%) | C33: ='Profit & Loss'!G36/('Balance Sheet'!G13+'Balance Sheet'!G14) -> 0.2134341 | D33: ='Profit & Loss'!F36/('Balance Sheet'!F13+'Balance Sheet'!F14) -> 0.2496946 | E33: ='Profit & Loss'!E36/('Balance Sheet'!E13+'Balance Sheet'!E14) -> 0.28111202 | F33: ='Profit & Loss'!D36/('Balance Sheet'!D13+'Balance Sheet'!D14) -> 0.18282172 | G33: ='Profit & Loss'!C36/('Balance Sheet'!C13+'Balance Sheet'!C14) -> 0.19647304 | H33: =AVERAGE(C33,D33,E33,F33,G33) -> 0.2247071
B34: RoA: PAT / Total Assets (%) | C34: ='Profit & Loss'!G36/'Balance Sheet'!G47 -> 0.13185306 | D34: ='Profit & Loss'!F36/'Balance Sheet'!F47 -> 0.15917707 | E34: ='Profit & Loss'!E36/'Balance Sheet'!E47 -> 0.18246938 | F34: ='Profit & Loss'!D36/'Balance Sheet'!D47 -> 0.12074628 | G34: ='Profit & Loss'!C36/'Balance Sheet'!C47 -> 0.12524725 | H34: =AVERAGE(C34,D34,E34,F34,G34) -> 0.14389861
B35: RoCE: EBIT / Capital Employed (%) | C35: =('Profit & Loss'!G23+'Profit & Loss'!G19)/('Balance Sheet'!G47-'Balance Sheet'!G26) -> 0.28334066 | D35: =('Profit & Loss'!F23+'Profit & Loss'!F19)/('Balance Sheet'!F47-'Balance Sheet'!F26) -> 0.32333132 | E35: =('Profit & Loss'!E23+'Profit & Loss'!E19)/('Balance Sheet'!E47-'Balance Sheet'!E26) -> 0.34635182 | F35: =('Profit & Loss'!D23+'Profit & Loss'!D19)/('Balance Sheet'!D47-'Balance Sheet'!D26) -> 0.24977261 | G35: =('Profit & Loss'!C23+'Profit & Loss'!C19)/('Balance Sheet'!C47-'Balance Sheet'!C26) -> 0.24375942 | H35: =AVERAGE(C35,D35,E35,F35,G35) -> 0.28931117
B37: Leverage & Coverage Ratios
B38: Gross Debt / Equity (x) | C38: =('Balance Sheet'!G16+'Balance Sheet'!G22)/('Balance Sheet'!G13+'Balance Sheet'!G14) -> 0.054627444 | D38: =('Balance Sheet'!F16+'Balance Sheet'!F22)/('Balance Sheet'!F13+'Balance Sheet'!F14) -> 0.059115682 | E38: =('Balance Sheet'!E16+'Balance Sheet'!E22)/('Balance Sheet'!E13+'Balance Sheet'!E14) -> 0.056999498 | F38: =('Balance Sheet'!D16+'Balance Sheet'!D22)/('Balance Sheet'!D13+'Balance Sheet'!D14) -> 0.043060364 | G38: =('Balance Sheet'!C16+'Balance Sheet'!C22)/('Balance Sheet'!C13+'Balance Sheet'!C14) -> 0.10416816 | H38: =AVERAGE(C38,D38,E38,F38,G38) -> 0.06359423
B39: Net Debt / Equity (x) | C39: =('Balance Sheet'!G16+'Balance Sheet'!G22-'Balance Sheet'!G43)/('Balance Sheet'!G13+'Balance Sheet'!G14) -> -0.0062447664 | D39: =('Balance Sheet'!F16+'Balance Sheet'!F22-'Balance Sheet'!F43)/('Balance Sheet'!F13+'Balance Sheet'!F14) -> 0.0078068137 | E39: =('Balance Sheet'!E16+'Balance Sheet'!E22-'Balance Sheet'!E43)/('Balance Sheet'!E13+'Balance Sheet'!E14) -> 0.0011908145 | F39: =('Balance Sheet'!D16+'Balance Sheet'!D22-'Balance Sheet'!D43)/('Balance Sheet'!D13+'Balance Sheet'!D14) -> 0.0040764642 | G39: =('Balance Sheet'!C16+'Balance Sheet'!C22-'Balance Sheet'!C43)/('Balance Sheet'!C13+'Balance Sheet'!C14) -> 0.055397734 | H39: =AVERAGE(C39,D39,E39,F39,G39) -> 0.012445412
B40: Net Debt / EBITDA (x) | C40: =('Balance Sheet'!G16+'Balance Sheet'!G22-'Balance Sheet'!G43)/('Profit & Loss'!G23+'Profit & Loss'!G19+'Profit & Loss'!G20) -> -0.017105806 | D40: =('Balance Sheet'!F16+'Balance Sheet'!F22-'Balance Sheet'!F43)/('Profit & Loss'!F23+'Profit & Loss'!F19+'Profit & Loss'!F20) -> 0.019317457 | E40: =('Balance Sheet'!E16+'Balance Sheet'!E22-'Balance Sheet'!E43)/('Profit & Loss'!E23+'Profit & Loss'!E19+'Profit & Loss'!E20) -> 0.0027958622 | F40: =('Balance Sheet'!D16+'Balance Sheet'!D22-'Balance Sheet'!D43)/('Profit & Loss'!D23+'Profit & Loss'!D19+'Profit & Loss'!D20) -> 0.012429281 | G40: =('Balance Sheet'!C16+'Balance Sheet'!C22-'Balance Sheet'!C43)/('Profit & Loss'!C23+'Profit & Loss'!C19+'Profit & Loss'!C20) -> 0.16437008 | H40: =AVERAGE(C40,D40,E40,F40,G40) -> 0.036361375
B41: Interest Coverage: EBIT / Finance (x) | C41: =('Profit & Loss'!G23+'Profit & Loss'!G19)/'Profit & Loss'!G19 -> 45.773609 | D41: =('Profit & Loss'!F23+'Profit & Loss'!F19)/'Profit & Loss'!F19 -> 40.071305 | E41: =('Profit & Loss'!E23+'Profit & Loss'!E19)/'Profit & Loss'!E19 -> 36.164839 | F41: =('Profit & Loss'!D23+'Profit & Loss'!D19)/'Profit & Loss'!D19 -> 24.458109 | G41: =('Profit & Loss'!C23+'Profit & Loss'!C19)/'Profit & Loss'!C19 -> 31.681439 | H41: =AVERAGE(C41,D41,E41,F41,G41) -> 35.62986
B42: Gross Debt / Total Assets (%) | C42: =('Balance Sheet'!G16+'Balance Sheet'!G22)/'Balance Sheet'!G47 -> 0.033747164 | D42: =('Balance Sheet'!F16+'Balance Sheet'!F22)/'Balance Sheet'!F47 -> 0.037685479 | E42: =('Balance Sheet'!E16+'Balance Sheet'!E22)/'Balance Sheet'!E47 -> 0.036998285 | F42: =('Balance Sheet'!D16+'Balance Sheet'!D22)/'Balance Sheet'!D47 -> 0.028439613 | G42: =('Balance Sheet'!C16+'Balance Sheet'!C22)/'Balance Sheet'!C47 -> 0.066404919 | H42: =AVERAGE(C42,D42,E42,F42,G42) -> 0.040655092
B44: Asset & Efficiency Ratios
B45: Asset Turnover: Revenue / Total Assets (x) | C45: ='Profit & Loss'!G9/'Balance Sheet'!G47 -> 1.2583934 | D45: ='Profit & Loss'!F9/'Balance Sheet'!F47 -> 1.3321897 | E45: ='Profit & Loss'!E9/'Balance Sheet'!E47 -> 1.1823959 | F45: ='Profit & Loss'!D9/'Balance Sheet'!D47 -> 1.1128033 | G45: ='Profit & Loss'!C9/'Balance Sheet'!C47 -> 1.0284319 | H45: =AVERAGE(C45,D45,E45,F45,G45) -> 1.1828428
B46: Fixed Asset Turnover (x) | C46: ='Profit & Loss'!G9/'Balance Sheet'!G33 -> 5.0719545 | D46: ='Profit & Loss'!F9/'Balance Sheet'!F33 -> 5.2377449 | E46: ='Profit & Loss'!E9/'Balance Sheet'!E33 -> 3.7537525 | F46: ='Profit & Loss'!D9/'Balance Sheet'!D33 -> 3.2956925 | G46: ='Profit & Loss'!C9/'Balance Sheet'!C33 -> 3.1514445 | H46: =AVERAGE(C46,D46,E46,F46,G46) -> 4.1021178
B48: Growth Ratios
B49: Revenue Growth YoY (%) | D49: ='Profit & Loss'!F9/'Profit & Loss'!G9-1 -> 0.18823288 | E49: ='Profit & Loss'!E9/'Profit & Loss'!F9-1 -> 0.029512774 | F49: ='Profit & Loss'!D9/'Profit & Loss'!E9-1 -> -0.044789854 | G49: ='Profit & Loss'!C9/'Profit & Loss'!D9-1 -> 0.050862257 | H49: =AVERAGE(D49,E49,F49,G49) -> 0.055954515
B50: EBITDA Growth YoY (%) | D50: =('Profit & Loss'!F23+'Profit & Loss'!F19+'Profit & Loss'!F20)/('Profit & Loss'!G23+'Profit & Loss'!G19+'Profit & Loss'!G20)-1 -> 0.28217732 | E50: =('Profit & Loss'!E23+'Profit & Loss'!E19+'Profit & Loss'!E20)/('Profit & Loss'!F23+'Profit & Loss'!F19+'Profit & Loss'!F20)-1 -> 0.24473995 | F50: =('Profit & Loss'!D23+'Profit & Loss'!D19+'Profit & Loss'!D20)/('Profit & Loss'!E23+'Profit & Loss'!E19+'Profit & Loss'!E20)-1 -> -0.20477847 | G50: =('Profit & Loss'!C23+'Profit & Loss'!C19+'Profit & Loss'!C20)/('Profit & Loss'!D23+'Profit & Loss'!D19+'Profit & Loss'!D20)-1 -> 0.12781927 | H50: =AVERAGE(D50,E50,F50,G50) -> 0.11248952
B51: PAT Growth YoY (%) | D51: ='Profit & Loss'!F36/'Profit & Loss'!G36-1 -> 0.35500912 | E51: ='Profit & Loss'!E36/'Profit & Loss'!F36-1 -> 0.32967161 | F51: ='Profit & Loss'!D36/'Profit & Loss'!E36-1 -> -0.32837445 | G51: ='Profit & Loss'!C36/'Profit & Loss'!D36-1 -> 0.1794597 | H51: =AVERAGE(D51,E51,F51,G51) -> 0.1339415
B53: Per Share Data
B54: Basic EPS (₹) | C54: ='Profit & Loss'!G39 -> 32 | D54: ='Profit & Loss'!F39 -> 43 | E54: ='Profit & Loss'!E39 -> 57 | F54: ='Profit & Loss'!D39 -> 38 | G54: ='Profit & Loss'!C39 -> 45 | H54: =AVERAGE(C54,D54,E54,F54,G54) -> 43
B55: Book Value per Share (₹) | C55: =IF('Profit & Loss'!G39<>0,'Balance Sheet'!G13/('Profit & Loss'!G36/'Profit & Loss'!G39),0) -> 145.83723 | D55: =IF('Profit & Loss'!F39<>0,'Balance Sheet'!F13/('Profit & Loss'!F36/'Profit & Loss'!F39),0) -> 167.45994 | E55: =IF('Profit & Loss'!E39<>0,'Balance Sheet'!E13/('Profit & Loss'!E36/'Profit & Loss'!E39),0) -> 195.50698 | F55: =IF('Profit & Loss'!D39<>0,'Balance Sheet'!D13/('Profit & Loss'!D36/'Profit & Loss'!D39),0) -> 201.02169 | G55: =IF('Profit & Loss'!C39<>0,'Balance Sheet'!C13/('Profit & Loss'!C36/'Profit & Loss'!C39),0) -> 222.34537 | H55: =AVERAGE(C55,D55,E55,F55,G55) -> 186.43424
B56: Net Debt per Share (₹) | C56: =IF('Profit & Loss'!G39<>0,('Balance Sheet'!G16+'Balance Sheet'!G22-'Balance Sheet'!G43)/('Profit & Loss'!G36/'Profit & Loss'!G39),0) -> -0.93627271 | D56: =IF('Profit & Loss'!F39<>0,('Balance Sheet'!F16+'Balance Sheet'!F22-'Balance Sheet'!F43)/('Profit & Loss'!F36/'Profit & Loss'!F39),0) -> 1.3444143 | E56: =IF('Profit & Loss'!E39<>0,('Balance Sheet'!E16+'Balance Sheet'!E22-'Balance Sheet'!E43)/('Profit & Loss'!E36/'Profit & Loss'!E39),0) -> 0.24145686 | F56: =IF('Profit & Loss'!D39<>0,('Balance Sheet'!D16+'Balance Sheet'!D22-'Balance Sheet'!D43)/('Profit & Loss'!D36/'Profit & Loss'!D39),0) -> 0.84730437 | G56: =IF('Profit & Loss'!C39<>0,('Balance Sheet'!C16+'Balance Sheet'!C22-'Balance Sheet'!C43)/('Profit & Loss'!C36/'Profit & Loss'!C39),0) -> 12.688245 | H56: =AVERAGE(C56,D56,E56,F56,G56) -> 2.8370295

Sheet Fixed Assets Schedule
B1: Fixed Assets Schedule
B3: Particular | C3: 2022 | D3: 2023 | E3: 2024 | F3: 2025 | G3: 2026
B4: Beginning balance | D4: =C8 -> 5702.63 | E4: =D8 -> 6561.57 | F4: =E8 -> 9425.8 | G4: =F8 -> 10255.01
B5: Add: Net Purchases | D5: ='Balance Sheet'!F33-'Balance Sheet'!G33+'Profit & Loss'!F20 -> 1716.96 | E5: ='Balance Sheet'!E33-'Balance Sheet'!F33+'Profit & Loss'!E20 -> 3717.23 | F5: ='Balance Sheet'!D33-'Balance Sheet'!E33+'Profit & Loss'!D20 -> 1855.55 | G5: ='Balance Sheet'!C33-'Balance Sheet'!D33+'Profit & Loss'!C20 -> 2243.71
B6: Total Fixed Assets | C6: =C7+C8 -> 6518.99 | D6: =D4+D5 -> 7419.59 | E6: =E4+E5 -> 10278.8 | F6: =F4+F5 -> 11281.35 | G6: =G4+G5 -> 12498.72
B7: Less: Depreciation | C7: ='Profit & Loss'!G20 -> 816.36 | D7: ='Profit & Loss'!F20 -> 858.02 | E7: ='Profit & Loss'!E20 -> 853 | F7: ='Profit & Loss'!D20 -> 1026.34 | G7: ='Profit & Loss'!C20 -> 1228.85
B8: Closing Balance(Fixed Asests ) | C8: ='Balance Sheet'!G33 -> 5702.63 | D8: =D4+D5-D7 -> 6561.57 | E8: =E4+E5-E7 -> 9425.8 | F8: =F4+F5-F7 -> 10255.01 | G8: =G4+G5-G7 -> 11269.87
B10: Net Capital expenditure | D10: =D5-D7 -> 858.94 | E10: =E5-E7 -> 2864.23 | F10: =F5-F7 -> 829.21 | G10: =G5-G7 -> 1014.86
B11: Net Capex / Sales % | D11: =D10/'Profit & Loss'!F9 -> 0.024992558 | E11: =E10/'Profit & Loss'!E9 -> 0.080951339 | F11: =F10/'Profit & Loss'!D9 -> 0.024534757 | G11: =G10/'Profit & Loss'!C9 -> 0.028574429
B13: Median Capex / Sales % | D13: =MEDIAN(D11:G11) -> 0.026783494
B14: Average Capex / Sales % | D14: =AVERAGE(D11:G11) -> 0.039763271

Sheet Working Capital Changes
B1: Change In Working Capital
B3: Particular | C3: 2022 | D3: 2023 | E3: 2024 | F3: 2025 | G3: 2026
B4: Inventory | C4: ='Balance Sheet'!G41 -> 6152.98 | D4: ='Balance Sheet'!F41 -> 6210.64 | E4: ='Balance Sheet'!E41 -> 5923.41 | F4: ='Balance Sheet'!D41 -> 6719.27 | G4: ='Balance Sheet'!C41 -> 5743.69
B5: Trade Receivables | C5: ='Balance Sheet'!G42 -> 3871.44 | D5: ='Balance Sheet'!F42 -> 4636.94 | E5: ='Balance Sheet'!E42 -> 4889.05 | F5: ='Balance Sheet'!D42 -> 4313.65 | G5: ='Balance Sheet'!C42 -> 4461.8
B6: Trade Payable | C6: ='Balance Sheet'!G23 -> 4164.3 | D6: ='Balance Sheet'!F23 -> 3635.44 | E6: ='Balance Sheet'!E23 -> 3831.34 | F6: ='Balance Sheet'!D23 -> 3848 | G6: ='Balance Sheet'!C23 -> 3863.04
B7: Non Cash working Capital | C7: =C4+C5-C6 -> 5860.12 | D7: =D4+D5-D6 -> 7212.14 | E7: =E4+E5-E6 -> 6981.12 | F7: =F4+F5-F6 -> 7184.92 | G7: =G4+G5-G6 -> 6342.45
B8: Change in Working Capital | D8: =D7-C7 -> 1352.02 | E8: =E7-D7 -> -231.02 | F8: =F7-E7 -> 203.8 | G8: =G7-F7 -> -842.47
B9: Change in Working Capital / Sales percentage | D9: =D8/'Profit & Loss'!F9 -> 0.039339696 | E9: =E8/'Profit & Loss'!E9 -> -0.0065292865 | F9: =F8/'Profit & Loss'!D9 -> 0.0060300568 | G9: =G8/'Profit & Loss'!C9 -> -0.023720611
B11: Median Change in Working Capital / Sales percentage | D11: =MEDIAN(D9:G9) -> -0.00024961488
B12: Average Change in Working Capital / Sales percentage | D12: =AVERAGE(D9:G9) -> 0.0037799639

Sheet Assumption
B1: Asian Paints Ltd.
B3: Particulars | C3: 44621 | D3: 44986 | E3: 45352 | F3: 45717 | G3: Mar-26
B4: Revenue from operations | C4: ='Profit & Loss'!G11 -> 29101.28 | D4: ='Profit & Loss'!F11 -> 34488.59 | E4: ='Profit & Loss'!E11 -> 35494.73 | F4: ='Profit & Loss'!D11 -> 33905.62 | G4: ='Profit & Loss'!C11 -> 35583.54 | I4: Median of Revenue Growth
B5: Revenue growth in % | D5: =(D4/C4)-1 -> 0.18512278 | E5: =(E4/D4)-1 -> 0.029173127 | F5: =(F4/E4)-1 -> -0.044770308 | G5: =(G4/F4)-1 -> 0.049487961 | I5: =MEDIAN(D5:G5) -> 0.039330544
B6: Less: Cost Of Materials Consumed | C6: ='Profit & Loss'!G15 -> 16254.59 | D6: ='Profit & Loss'!F15 -> 17330.58 | E6: ='Profit & Loss'!E15 -> 15868.21 | F6: ='Profit & Loss'!D15 -> 15793.92 | G6: ='Profit & Loss'!C15 -> 15384.05
B7: Less: Employee Benefit Expenses | C7: ='Profit & Loss'!G18 -> 1786.67 | D7: ='Profit & Loss'!F18 -> 2028.07 | E7: ='Profit & Loss'!E18 -> 2326.18 | F7: ='Profit & Loss'!D18 -> 2597.23 | G7: ='Profit & Loss'!C18 -> 2799.59
B8: Less: Changes In Inventories | C8: ='Profit & Loss'!G17 -> -1324.97 | D8: ='Profit & Loss'!F17 -> -309.73 | E8: ='Profit & Loss'!E17 -> 363.8 | F8: ='Profit & Loss'!D17 -> -205 | G8: ='Profit & Loss'!C17 -> 603.68
B9: Less: Other Expenses | C9: ='Profit & Loss'!G21 -> 4210.25 | D9: ='Profit & Loss'!F21 -> 5044.18 | E9: ='Profit & Loss'!E21 -> 5493.36 | F9: ='Profit & Loss'!D21 -> 5786.4 | G9: ='Profit & Loss'!C21 -> 6086.25
B10: Less: Purchase Of Stock-In Trade | C10: ='Profit & Loss'!G16 -> 3371.13 | D10: ='Profit & Loss'!F16 -> 4135.65 | E10: ='Profit & Loss'!E16 -> 3858.2 | F10: ='Profit & Loss'!D16 -> 3926.86 | G10: ='Profit & Loss'!C16 -> 4014.05
B11: Total Expenses | C11: =C6+C7+C8+C9+C10 -> 24297.67 | D11: =D6+D7+D8+D9+D10 -> 28228.75 | E11: =E6+E7+E8+E9+E10 -> 27909.75 | F11: =F6+F7+F8+F9+F10 -> 27899.41 | G11: =G6+G7+G8+G9+G10 -> 28887.62
B12: EBITDA | C12: =C4-C11 -> 4803.61 | D12: =D4-D11 -> 6259.84 | E12: =E4-E11 -> 7584.98 | F12: =F4-F11 -> 6006.21 | G12: =G4-G11 -> 6695.92
B13: Less: Depreciation And Amortization | C13: ='Profit & Loss'!G20 -> 816.36 | D13: ='Profit & Loss'!F20 -> 858.02 | E13: ='Profit & Loss'!E20 -> 853 | F13: ='Profit & Loss'!D20 -> 1026.34 | G13: ='Profit & Loss'!C20 -> 1228.85
B14: EBIT | C14: =C12-C13 -> 3987.25 | D14: =D12-D13 -> 5401.82 | E14: =E12-E13 -> 6731.98 | F14: =F12-F13 -> 4979.87 | G14: =G12-G13 -> 5467.07
B15: ADD: Other Income / Non-Operating Income | C15: ='Profit & Loss'!G12 -> 380.01 | D15: ='Profit & Loss'!F12 -> 386.48 | E15: ='Profit & Loss'!E12 -> 687.96 | F15: ='Profit & Loss'!D12 -> 572.61 | G15: ='Profit & Loss'!C12 -> 723.8
B16: Less: Finance Costs / Interest Expenses | C16: ='Profit & Loss'!G19 -> 95.41 | D16: ='Profit & Loss'!F19 -> 144.45 | E16: ='Profit & Loss'!E19 -> 205.17 | F16: ='Profit & Loss'!D19 -> 227.02 | G16: ='Profit & Loss'!C19 -> 195.41
B17: PBT | C17: =C14+C15-C16 -> 4271.85 | D17: =D14+D15-D16 -> 5643.85 | E17: =E14+E15-E16 -> 7214.77 | F17: =F14+F15-F16 -> 5325.46 | G17: =G14+G15-G16 -> 5995.46
B18: Less: Total Tax Expenses | C18: ='Profit & Loss'!G30 -> 1102.91 | D18: ='Profit & Loss'!F30 -> 1493.5 | E18: ='Profit & Loss'!E30 -> 1790.08 | F18: ='Profit & Loss'!D30 -> 1393.36 | G18: ='Profit & Loss'!C30 -> 1608.75
B19: Tax Rate | C19: =C18/C17 -> 0.25818088 | D19: =D18/D17 -> 0.26462433 | E19: =E18/E17 -> 0.24811325 | F19: =F18/F17 -> 0.26164125 | G19: =G18/G17 -> 0.26832803
B20: Less: Minority Interest | C20: =-'Profit & Loss'!G34 -> 54.24 | D20: =-'Profit & Loss'!F34 -> 88.88 | E20: =-'Profit & Loss'!E34 -> 97.46 | F20: =-'Profit & Loss'!D34 -> 42.48 | G20: =-'Profit & Loss'!C34 -> 69.34
B21: Net Profit - PAT | C21: =C17-C18-C20 -> 3114.7 | D21: =D17-D18-D20 -> 4061.47 | E21: =E17-E18-E20 -> 5327.23 | F21: =F17-F18-F20 -> 3889.62 | G21: =G17-G18-G20 -> 4317.37
B23: Historical Growth
B24: Average Growth | C24: =AVERAGE(D5:G5) -> 0.054753391
B25: CAGR | C25: =(G4/C4)^(1/4)-1 -> 0.051560502 | D25: =_xlfn.RRI(4,C4,G4) -> 0.051560502 | E25: RRI
B27: Margins
B28: EBITDA | C28: =C12/C4 -> 0.16506525 | D28: =D12/D4 -> 0.18150467 | E28: =E12/E4 -> 0.21369313 | F28: =F12/F4 -> 0.17714497 | G28: =G12/G4 -> 0.18817464
B29: EBIT | C29: =C14/C4 -> 0.13701287 | D29: =D14/D4 -> 0.15662629 | E29: =E14/E4 -> 0.18966139 | F29: =F14/F4 -> 0.14687447 | G29: =G14/G4 -> 0.15364042
B30: EBT | C30: =C17/C4 -> 0.14679251 | D30: =D17/D4 -> 0.16364398 | E30: =E17/E4 -> 0.20326313 | F30: =F17/F4 -> 0.15706718 | G30: =G17/G4 -> 0.1684897
B31: Net Profit | C31: =C21/C4 -> 0.10702966 | D31: =D21/D4 -> 0.11776272 | E31: =E21/E4 -> 0.1500851 | F31: =F21/F4 -> 0.11471903 | G31: =G21/G4 -> 0.12133054
B33: Tax Rate
B34: Effective tax rate | C34: =C18/C17 -> 0.25818088 | D34: =D18/D17 -> 0.26462433 | E34: =E18/E17 -> 0.24811325 | F34: =F18/F17 -> 0.26164125 | G34: =G18/G17 -> 0.26832803
B35: Marginal Tax rate | C35: 0.25 | D35: 0.25 | E35: 0.25 | F35: 0.25 | G35: 0.25
B37: Return On Capital
B38: EBIT*(1-T) | C38: =C14*(1-C35) -> 2990.4375 | D38: =D14*(1-D35) -> 4051.365 | E38: =E14*(1-E35) -> 5048.985 | F38: =F14*(1-F35) -> 3734.9025 | G38: =G14*(1-G35) -> 4100.3025
B39: Book Equity | C39: ='Balance Sheet'!G13 -> 13811.56 | D39: ='Balance Sheet'!F13 -> 15992.23 | E39: ='Balance Sheet'!E13 -> 18728.3 | F39: ='Balance Sheet'!D13 -> 19399.81 | G39: ='Balance Sheet'!C13 -> 21371.59
B40: Book Debt | C40: ='Balance Sheet'!G16+'Balance Sheet'!G22 -> 775.66 | D40: ='Balance Sheet'!F16+'Balance Sheet'!F22 -> 972.21 | E40: ='Balance Sheet'!E16+'Balance Sheet'!E22 -> 1107.14 | F40: ='Balance Sheet'!D16+'Balance Sheet'!D22 -> 863.75 | G40: ='Balance Sheet'!C16+'Balance Sheet'!C22 -> 2293.26
B41: Cash and Cash Equivalents | C41: ='Balance Sheet'!G43 -> 864.33 | D41: ='Balance Sheet'!F43 -> 843.82 | E41: ='Balance Sheet'!E43 -> 1084.01 | F41: ='Balance Sheet'!D43 -> 781.98 | G41: ='Balance Sheet'!C43 -> 1073.68
B42: Capital Employed | C42: =C39+C40+C41 -> 15451.55 | D42: =D39+D40+D41 -> 17808.26 | E42: =E39+E40+E41 -> 20919.45 | F42: =F39+F40+F41 -> 21045.54 | G42: =G39+G40+G41 -> 24738.53
B44: Pre-Tax Return on Capital | C44: =C14/C42 -> 0.25804855 | D44: =D14/D42 -> 0.30333227 | E44: =E14/E42 -> 0.32180483 | F44: =F14/F42 -> 0.23662353 | G44: =G14/G42 -> 0.22099413
B45: Post Tax Return on Capital | C45: =C38/C42 -> 0.19353641 | D45: =D38/D42 -> 0.22749921 | E45: =E38/E42 -> 0.24135362 | F45: =F38/F42 -> 0.17746765 | G45: =G38/G42 -> 0.1657456
B47: Growth In EBIT | C47: ='Fixed Assets Schedule'!D13*Assumption!G45 -> 0.0044392463

Sheet FCFF
B1: FCFF
B3: Particulars | C3: 2022 | D3: 2023 | E3: 2024 | F3: 2025 | G3: 2026
B4: EBIT | C4: ='Profit & Loss'!G23+'Profit & Loss'!G19 -> 4367.26 | D4: ='Profit & Loss'!F23+'Profit & Loss'!F19 -> 5788.3 | E4: ='Profit & Loss'!E23+'Profit & Loss'!E19 -> 7419.94 | F4: ='Profit & Loss'!D23+'Profit & Loss'!D19 -> 5552.48 | G4: ='Profit & Loss'!C23+'Profit & Loss'!C19 -> 6190.87
B5: Less: Tax on EBIT | C5: =C4*('Profit & Loss'!G30/'Profit & Loss'!G25) -> 1158.9319 | D5: =D4*('Profit & Loss'!F30/'Profit & Loss'!F25) -> 1545.104 | E5: =E4*('Profit & Loss'!E30/'Profit & Loss'!E25) -> 1840.9854 | F5: =F4*('Profit & Loss'!D30/'Profit & Loss'!D25) -> 1559.0573 | G5: =G4*('Profit & Loss'!C30/'Profit & Loss'!C25) -> 1706.0325
B6: EBIT*(1-tax) | C6: =C4-C5 -> 3208.3281 | D6: =D4-D5 -> 4243.196 | E6: =E4-E5 -> 5578.9546 | F6: =F4-F5 -> 3993.4227 | G6: =G4-G5 -> 4484.8375
B7: Less: Net capital expenditure | D7: ='Fixed Assets Schedule'!D10 -> 858.94 | E7: ='Fixed Assets Schedule'!E10 -> 2864.23 | F7: ='Fixed Assets Schedule'!F10 -> 829.21 | G7: ='Fixed Assets Schedule'!G10 -> 1014.86
B8: Less: Change in WC | D8: ='Working Capital Changes'!D8 -> 1352.02 | E8: ='Working Capital Changes'!E8 -> -231.02 | F8: ='Working Capital Changes'!F8 -> 203.8 | G8: ='Working Capital Changes'!G8 -> -842.47
B9: Reinvestment | D9: =SUM(D7:D8) -> 2210.96 | E9: =SUM(E7:E8) -> 2633.21 | F9: =SUM(F7:F8) -> 1033.01 | G9: =SUM(G7:G8) -> 172.39
B10: Free Cah Flow to Firm (FCFF) | C10: =C6 -> 3208.3281 | D10: =D6-D9 -> 2032.236 | E10: =E6-E9 -> 2945.7446 | F10: =F6-F9 -> 2960.4127 | G10: =G6-G9 -> 4312.4475
B12: Reinvestment Rate % | D12: =D9/D6 -> 0.52106007 | E12: =E9/E6 -> 0.47198986 | F12: =F9/F6 -> 0.25867785 | G12: =G9/G6 -> 0.038438405
B13: Medium Reinvestment Rate | C13: =MEDIAN(D12:G12) -> 0.36533385
B14: Average Reinvestment Rate | C14: =AVERAGE(D12:G12) -> 0.32254155

Sheet WACC
B1: WACC Calculation
B2: Cost Of Capital
B3: As On Date: | C3: June 2026
B5: Cost of equity using CAPM:
B6: Risk-free rate | C6: 0.0685
B7: India Default Spread | C7: 0.0187
B8: Beta | C8: 0.98
B9: Equity Risk Premium (ERP) | C9: 0.075
B10: Cost of equity | C10: =C6+C8*C9 -> 0.142
B12: Cost of debt:
B13: Finance Cost (₹ Cr.) | C13: ='Profit & Loss'!C19 -> 195.41
B14: Total Debt (₹ Cr.) | C14: ='Balance Sheet'!C16+'Balance Sheet'!C22 -> 2293.26
B15: Pre-Tax Cost of Debt | C15: =C13/C14 -> 0.085210574
B16: Marginal Tax Rate % | C16: =Assumption!G35 -> 0.25
B17: Post-Tax Cost of Debt | C17: =C15*(1-C16) -> 0.06390793
B19: WACC Calculation :
B20: Equity Share Capital (₹ Cr.) | C20: ='Balance Sheet'!C9 -> 95.92
B21: Face Value (₹) | C21: 1
B22: Shares Outstanding (Cr.) | C22: =C20/C21 -> 95.92
B23: Share Price (₹, as on date) | C23: 2747
B24: Market Value of Equity (₹ Cr.) | C24: =C22*C23 -> 263492.24
B26: Capital Structure Weights
B27: Total Capital (Equity + Debt) (₹ Cr.) | C27: =C24+C14 -> 265785.5
B28: Weight of Debt (Wd) | C28: =C14/C27 -> 0.0086282359
B29: Weight of Equity (We) | C29: =C24/C27 -> 0.99137176
B31: WACC
B32: WACC | C32: =(C29*C10)+(C28*C17) -> 0.1413262

Sheet COC
B2: Weighted Average Cost of Capital
B3: All Figures are in INR unless stated otherwise
B5: Peer Comp | N5: Peer Comp
N6: S.No. | O6: Name | P6: CMP Rs. | Q6: Mar Cap Rs.Cr. | R6: Debt Rs.Cr. | S6: Debt / Eq
H7: Debt/ | I7: Debt/ | J7: Levered/ | K7: Unlevered/ | N7: 1 | O7: Asian Paints | P7: 2747.4 | Q7: 263530 | R7: 3928.93 | S7: 0.18
B8: Name of the company | E8: Country | F8: Total Equity | G8: Total Debt | H8: Tax Rate 1 | I8: Equity | J8: Capital | K8: beta 2 | N8: 2 | O8: Berger Paints | P8: 515.15 | Q8: 60066.63 | R8: 635.13 | S8: 0.09
N9: 3 | O9: Kansai Nerolac | P9: 216.5 | Q9: 17508.67 | R9: 302.73 | S9: 0.05
B10: Asian Paints | D10: India | E10: =Q7 -> 263530 | F10: =R7 -> 3928.93 | G10: 0.25 | H10: =F10/E10 -> 0.014908853 | I10: =F10/(F10+E10) -> 0.014689844 | J10: 0.98 | K10: =J10/(1+(1-G10)*H10) -> 0.96916317 | N10: 4 | O10: JSW Dulux | P10: 3168.4 | Q10: 14428.99 | R10: 79.1 | S10: 0.03
B11: Berger Paints | D11: India | E11: =Q8 -> 60066.63 | F11: =R8 -> 635.13 | G11: 0.25 | H11: =F11/E11 -> 0.010573758 | I11: =F11/(F11+E11) -> 0.010463123 | J11: 0.85 | K11: =J11/(1+(1-G11)*H11) -> 0.84331227 | N11: 5 | O11: Indigo Paints | P11: 995.2 | Q11: 4744.68 | R11: 18.37 | S11: 0.02
B12: Kansai Nerolac | D12: India | E12: =Q9 -> 17508.67 | F12: =R9 -> 302.73 | G12: 0.25 | H12: =F12/E12 -> 0.017290291 | I12: =F12/(F12+E12) -> 0.016996418 | J12: 0.72 | K12: =J12/(1+(1-G12)*H12) -> 0.71078277
B13: JSW Dulux | D13: India | E13: =Q10 -> 14428.99 | F13: =R10 -> 79.1 | G13: 0.25 | H13: =F13/E13 -> 0.0054820192 | I13: =F13/(F13+E13) -> 0.0054521305 | J13: 0.65 | K13: =J13/(1+(1-G13)*H13) -> 0.64733846
B14: Indigo Paints | D14: India | E14: =Q11 -> 4744.68 | F14: =R11 -> 18.37 | G14: 0.25 | H14: =F14/E14 -> 0.0038717047 | I14: =F14/(F14+E14) -> 0.0038567724 | J14: 1.1 | K14: =J14/(1+(1-G14)*H14) -> 1.0968151
F16: Average | G16: =AVERAGE(G10:G14) -> 0.25 | H16: =AVERAGE(H10:H14) -> 0.010425325 | I16: =AVERAGE(I10:I14) -> 0.010291658 | J16: =AVERAGE(J10:J14) -> 0.86 | K16: =AVERAGE(K10:K14) -> 0.85348235
F17: Median | G17: =MEDIAN(G10:G14) -> 0.25 | H17: =MEDIAN(H10:H14) -> 0.010573758 | I17: =MEDIAN(I10:I14) -> 0.010463123 | J17: =MEDIAN(J10:J14) -> 0.85 | K17: =MEDIAN(K10:K14) -> 0.84331227
B20: Cost of Debt | G20: Cost of Equity
B22: Pre-tax Cost of Debt | E22: =WACC!C15 -> 0.085210574 | G22: Risk Free Rate | K22: =WACC!C6 -> 0.0685
B23: Tax Rate | E23: =G17 -> 0.25 | G23: Equity Risk Premium | K23: =WACC!C9 -> 0.075
B24: After Tax Cost of Debt | E24: =E22*(1-E23) -> 0.06390793 | G24: Levered Beta | K24: =K33 -> 0.84988926
G25: Cost of Equity | K25: =K22+(K23*K24) -> 0.13224169
B28: Capital Structure | G28: Levered Beta
D30: Current | E30: Target | G30: Comps Median Unlevered Beta | K30: =K17 -> 0.84331227
B31: Total Debt | C31: =WACC!C14 -> 2293.26 | D31: =C31/$C$33 -> 0.0086282359 | E31: =I16 -> 0.010291658 | G31: Target Debt / Equity | K31: =E35 -> 0.010398677
B32: Market Capitalisation | C32: =WACC!C24 -> 263492.24 | D32: =C32/$C$33 -> 0.99137176 | E32: =E33-E31 -> 0.98970834 | G32: Tax Rate | K32: 0.25
B33: Total Capital | C33: =SUM(C31:C32) -> 265785.5 | D33: =C33/$C$33 -> 1 | E33: =D33 -> 1 | G33: Levered Beta | K33: =K30*(1+(1-K32)*K31) -> 0.84988926
B35: Debt / Equity | D35: =D31/D32 -> 0.0087033303 | E35: =E31/E32 -> 0.010398677
G36: Weighted Average Cost of Capital
G38: Cost of Equity | K38: =K25 -> 0.13224169
G39: Equity Weight | K39: =E32 -> 0.98970834
G41: Cost of Debt | K41: =E24 -> 0.06390793
G42: Debt Weight | K42: =E31 -> 0.010291658
G44: WACC | K44: =(K38*K39)+(K41*K42) -> 0.13153843

Sheet Relative Valuation
B1: Relative Valuation
B3: Comparable Company Valuation
B4: Company Name | C4: Market Data | J4: Financials (FY26, ₹ Cr.) | O4: Valuation Multiples
C5: No. of Shares (Cr.) | D5: Share Price (₹) | E5: Equity Value (₹ Cr.) | F5: Debt (₹ Cr.) | G5: Cash (₹ Cr.) | H5: Enterprise Value (₹ Cr.) | J5: Revenue (₹ Cr.) | K5: EBITDA (₹ Cr.) | L5: Net Profit (₹ Cr.) | M5: EPS (₹) | O5: EV/Revenue | P5: EV/EBITDA | Q5: P/E Ratio
B6: Asian Paints | C6: ='Balance Sheet'!C9/WACC!C21 -> 95.92 | D6: =WACC!C23 -> 2747 | E6: =C6*D6 -> 263492.24 | F6: ='Balance Sheet'!C16+'Balance Sheet'!C22 -> 2293.26 | G6: ='Balance Sheet'!C43 -> 1073.68 | H6: =E6+F6-G6 -> 264711.82 | J6: ='Profit & Loss'!C11 -> 35583.54 | K6: ='Profit & Loss'!C23+'Profit & Loss'!C20+'Profit & Loss'!C19 -> 7419.72 | L6: ='Profit & Loss'!C31 -> 4229.1 | M6: ='Profit & Loss'!C40 -> 45 | O6: =H6/J6 -> 7.4391648 | P6: =H6/K6 -> 35.676794 | Q6: =D6/M6 -> 61.044444
B7: Berger Paints | C7: 116.6 | D7: 515.15 | E7: =C7*D7 -> 60066.49 | F7: 635.13 | G7: 210 | H7: =E7+F7-G7 -> 60491.62 | J7: 9200 | K7: 1105 | L7: 632 | M7: 9.66 | O7: =H7/J7 -> 6.5751761 | P7: =H7/K7 -> 54.743548 | Q7: =D7/M7 -> 53.328157
B8: Kansai Nerolac | C8: 80.87 | D8: 216.5 | E8: =C8*D8 -> 17508.355 | F8: 302.73 | G8: 180 | H8: =E8+F8-G8 -> 17631.085 | J8: 7800 | K8: 860 | L8: 599 | M8: 7.29 | O8: =H8/J8 -> 2.2603955 | P8: =H8/K8 -> 20.501262 | Q8: =D8/M8 -> 29.698217
B9: JSW Dulux | C9: 4.56 | D9: 3168.4 | E9: =C9*D9 -> 14447.904 | F9: 79.1 | G9: 95 | H9: =E9+F9-G9 -> 14432.004 | J9: 4200 | K9: 462 | L9: 195 | M9: 433.42 | O9: =H9/J9 -> 3.4361914 | P9: =H9/K9 -> 31.238104 | Q9: =D9/M9 -> 7.3102303
B10: Indigo Paints | C10: 4.77 | D10: 995.2 | E10: =C10*D10 -> 4747.104 | F10: 18.37 | G10: 45 | H10: =E10+F10-G10 -> 4720.474 | J10: 1500 | K10: 165 | L10: 144 | M10: 30.5 | O10: =H10/J10 -> 3.1469827 | P10: =H10/K10 -> 28.608933 | Q10: =D10/M10 -> 32.629508
B12: M&M Industry Comparable Comps | M12: Average | O12: =AVERAGE(O6:O10) -> 4.5715821 | P12: =AVERAGE(P6:P10) -> 34.153728 | Q12: =AVERAGE(Q6:Q10) -> 36.802111
E13: EV/Revenue | F13: EV/EBITDA | G13: P/E | M13: Median | O13: =MEDIAN(O6:O10) -> 3.4361914 | P13: =MEDIAN(P6:P10) -> 31.238104 | Q13: =MEDIAN(Q6:Q10) -> 32.629508
B14: Implied Enterprise Value | E14: =O13*J6 -> 122271.86 | F14: =P13*K6 -> 231777.98 | G14: =Q13*M6*C6 -> 140842.01
B15: Net Debt | E15: ='Balance Sheet'!C16+'Balance Sheet'!C22-'Balance Sheet'!C43 -> 1219.58 | F15: ='Balance Sheet'!C16+'Balance Sheet'!C22-'Balance Sheet'!C43 -> 1219.58 | G15: ='Balance Sheet'!C16+'Balance Sheet'!C22-'Balance Sheet'!C43 -> 1219.58 | M15: Max | O15: =MAX(O6:O10) -> 7.4391648 | P15: =MAX(P6:P10) -> 54.743548 | Q15: =MAX(Q6:Q10) -> 61.044444
B16: Implied Market Value | E16: =E14-E15 -> 121052.28 | F16: =F14-F15 -> 230558.4 | G16: =G14-G15 -> 139622.43 | M16: 75th Percentile | O16: =PERCENTILE(O6:O10,0.75) -> 6.5751761 | P16: =PERCENTILE(P6:P10,0.75) -> 35.676794 | Q16: =PERCENTILE(Q6:Q10,0.75) -> 53.328157
B17: Share Outstanding (Cr.) | E17: ='Balance Sheet'!C9/WACC!C21 -> 95.92 | F17: ='Balance Sheet'!C9/WACC!C21 -> 95.92 | G17: ='Balance Sheet'!C9/WACC!C21 -> 95.92
B18: Implied Value per Share (₹) | E18: =E16/E17 -> 1262.0129 | F18: =F16/F17 -> 2403.6531 | G18: =G16/G17 -> 1455.6133 | M18: 25th Percentile | O18: =PERCENTILE(O6:O10,0.25) -> 3.1469827 | P18: =PERCENTILE(P6:P10,0.25) -> 28.608933 | Q18: =PERCENTILE(Q6:Q10,0.25) -> 29.698217
M19: Min | O19: =MIN(O6:O10) -> 2.2603955 | P19: =MIN(P6:P10) -> 20.501262 | Q19: =MIN(Q6:Q10) -> 7.3102303

Sheet Peer Comps.
B1: Asian Paints Ltd - Peer Comparison
B3: Company | C3: Business Overview | M3: Trend-Chart of 5Yr
B4: Asian Paints Ltd | C4: Asian Paints Ltd is India's largest paint and décor company commanding ~52% of the domestic decorative paints market. It operates across interior/exterior paints, waterproofing, industrial coatings, adhesives, and home décor with presence in 15+ countries. The company is a Nifty 50 constituent and a benchmark for consumer staples in India.
B5: Berger Paints India Ltd | C5: Berger Paints India Ltd is the second-largest paint company in India, engaged in decorative and industrial coatings. Known for consistent volume growth and expanding premium product offerings, Berger has steadily gained distribution reach and reported resilient performance in FY25 despite muted urban demand and competitive intensity.
B6: Kansai Nerolac Paints Ltd | C6: Kansai Nerolac Paints Ltd is India's largest industrial paint company and third-largest decorative paints player, a subsidiary of Japan's Kansai Paint Co. Ltd. The company operates across decorative, automotive, and industrial coatings segments from six manufacturing plants across India.
B7: Indigo Paints Ltd | C7: Indigo Paints Ltd is a fast-growing mid-tier decorative paint company known for its differentiated product portfolio in cement paints, tile coatings, and wood coatings. With a unique distribution strategy focusing on Tier 2/3 towns and strong brand recall via advertising, it has carved a niche in the competitive paints market.
B9: Attribute | C9: Asian Paints | D9: Berger Paints | E9: Kansai Nerolac | F9: Indigo Paints | H9: Metric | I9: Asian Paints | J9: Berger Paints | K9: Kansai Nerolac
B10: LTP (₹) | C10: 2450 | D10: 555 | E10: 258 | F10: 995 | H10: Debtor Days (FY25) | I10: 35 | J10: 28 | K10: 32
B11: Sales (₹ Cr.) | C11: 33906 | D11: 11545 | E11: 7823 | F11: 1620 | H11: Inventory Days (FY25) | I11: 55 | J11: 45 | K11: 58
B12: Net Profit 12M (₹ Cr.) | C12: 3569 | D12: 1180 | E12: 1109 | F12: 86.4 | H12: Days Payable (FY25) | I12: 78 | J12: 65 | K12: 72
B13: Debt (₹ Cr.) | C13: 1125 | D13: 300 | E13: 100 | F13: 18.37 | H13: Cash Conversion Cycle (FY25) | I13: 12 | J13: 8 | K13: 18
B14: Cash (₹ Cr.) | C14: 1200 | D14: 852 | E14: 800 | F14: 55 | H14: Working Capital Days (FY25) | I14: 15 | J14: 12 | K14: 22
B15: OPM % | C15: 0.171 | D15: 0.158 | E15: 0.138 | F15: 0.136 | H15: ROCE % (FY25) | I15: 0.272 | J15: 0.251 | K15: 0.234
B16: P/E Ratio | C16: Premium Valuation | D16: 58 | E16: 31.15 | F16: 54
B17: ROCE % | C17: 0.272 | D17: 0.251 | E17: 0.234 | F17: 0.192
B18: ROE % | C18: Strong | D18: 0.22 | E18: 0.173 | F18: 0.151
B19: EV/EBITDA | C19: Premium | D19: 34.86 | E19: 22 | F19: 28.5
B20: EPS (₹) | C20: Strong | D20: 12.3 | E20: 8.4 | F20: 18.1

Sheet Growth Scenerio
B1: Growth Scenarios
B4: Scenario 1: High Growth
B5: INR Cr. | C5: LTM | D5: Y1E | E5: Y2E | F5: Y3E | G5: Y4E | H5: Y5E | I5: Y6E | J5: Y7E | K5: Y8E | L5: Y9E | M5: Y10E | N5: Average Revenue Growth | O5: =Assumption!I5 -> 0.039330544
B6: Sales | C6: ='Profit & Loss'!C11 -> 35583.54 | D6: =C6*(1+D7) -> 36983.06 | E6: =D6*(1+E7) -> 38534.55 | F6: =E6*(1+F7) -> 40252.12 | G6: =F6*(1+G7) -> 42151.739 | H6: =G6*(1+H7) -> 44251.479 | I6: =H6*(1+I7) -> 46571.792 | J6: =I6*(1+J7) -> 49135.825 | K6: =J6*(1+K7) -> 51969.799 | ... M6: =L6*(1+M7) -> 58570.428 | N6: Risk Free Rate | O6: ='DCF Valuation'!$R$4 -> 0.062917987
B7: Sales Growth % | D7: =O5 -> 0.039330544 | E7: =D7-$O$8 -> 0.041951371 | F7: =E7-$O$8 -> 0.044572198 | G7: =F7-$O$8 -> 0.047193025 | H7: =G7-$O$8 -> 0.049813852 | I7: =H7-$O$8 -> 0.052434679 | J7: =I7-$O$8 -> 0.055055506 | K7: =J7-$O$8 -> 0.057676333 | L7: =K7-$O$8 -> 0.06029716 | M7: =L7-$O$8 -> 0.062917987 | O7: =O5-O6 -> -0.023587443
N8: Growth Per Year | O8: =O7/9 -> -0.002620827
B9: Scenario 2: Average Growth
B10: INR Cr. | C10: LTM | D10: Y1E | E10: Y2E | F10: Y3E | G10: Y4E | H10: Y5E | I10: Y6E | J10: Y7E | K10: Y8E | L10: Y9E | M10: Y10E | N10: Average Revenue Growth | O10: =Assumption!C24 -> 0.054753391
B11: Sales | C11: =C6 -> 35583.54 | D11: =C11*(1+D12) -> 37531.859 | E11: =D11*(1+E12) -> 39620.904 | F11: =E11*(1+F12) -> 41862.169 | G11: =F11*(1+G12) -> 44268.194 | H11: =G11*(1+H12) -> 46852.664 | I11: =H11*(1+I12) -> 49630.525 | J11: =I11*(1+J12) -> 52618.107 | K11: =J11*(1+K12) -> 55833.264 | ... M11: =L11*(1+M12) -> 63026.286 | N11: Risk Free Rate | O11: ='DCF Valuation'!$R$4 -> 0.062917987
B12: Sales Growth % | D12: =O10 -> 0.054753391 | E12: =D12-$O$13 -> 0.055660568 | F12: =E12-$O$13 -> 0.056567746 | G12: =F12-$O$13 -> 0.057474923 | H12: =G12-$O$13 -> 0.0583821 | I12: =H12-$O$13 -> 0.059289278 | J12: =I12-$O$13 -> 0.060196455 | K12: =J12-$O$13 -> 0.061103633 | L12: =K12-$O$13 -> 0.06201081 | M12: =L12-$O$13 -> 0.062917987 | O12: =O10-O11 -> -0.0081645961
N13: Growth Per Year | O13: =O12/9 -> -0.00090717735
B14: Scenario 3: EBIT Growth
B15: INR Cr. | C15: LTM | D15: Y1E | E15: Y2E | F15: Y3E | G15: Y4E | H15: Y5E | I15: Y6E | J15: Y7E | K15: Y8E | L15: Y9E | M15: Y10E | N15: Average Revenue Growth | O15: =Assumption!C47 -> 0.0044392463
B16: Sales | C16: =C11 -> 35583.54 | D16: =C16*(1+D17) -> 35741.504 | E16: =D16*(1+E17) -> 35667.934 | F16: =E16*(1+F17) -> 35362.758 | G16: =F16*(1+G17) -> 34830.419 | H16: =G16*(1+H17) -> 34079.778 | I16: =H16*(1+I17) -> 33123.876 | J16: =I16*(1+J17) -> 31979.56 | K16: =J16*(1+K17) -> 30666.984 | ... M16: =L16*(1+M17) -> 27630.578 | N16: Risk Free Rate | O16: ='DCF Valuation'!$R$4 -> 0.062917987
B17: Sales Growth % | D17: =O15 -> 0.0044392463 | E17: =D17-(-O18) -> -0.0020583916 | F17: =E17-(-P18) -> -0.0085560295 | G17: =F17-(-Q18) -> -0.015053667 | H17: =G17-(-R18) -> -0.021551305 | I17: =H17-(-S18) -> -0.028048943 | J17: =I17-(-T18) -> -0.034546581 | K17: =J17-(-U18) -> -0.041044219 | L17: =K17-(-V18) -> -0.047541857 | M17: =L17-(-W18) -> -0.054039495 | O17: =O15-O16 -> -0.058478741
N18: Growth Per Year | O18: =O17/9 -> -0.0064976379 | P18: =O17/9 -> -0.0064976379 | Q18: =O17/9 -> -0.0064976379 | R18: =O17/9 -> -0.0064976379 | S18: =O17/9 -> -0.0064976379 | T18: =O17/9 -> -0.0064976379 | U18: =O17/9 -> -0.0064976379 | V18: =O17/9 -> -0.0064976379 | W18: =O17/9 -> -0.0064976379
B19: Live Scenario | C19: 2
B20: INR Cr. | C20: LTM | D20: Y1E | E20: Y2E | F20: Y3E | G20: Y4E | H20: Y5E | I20: Y6E | J20: Y7E | K20: Y8E | L20: Y9E | M20: Y10E
B21: Sales | C21: =C6 -> 35583.54 | D21: =C21*(1+D22) -> 37531.859 | E21: =D21*(1+E22) -> 39620.904 | F21: =E21*(1+F22) -> 41862.169 | G21: =F21*(1+G22) -> 44268.194 | H21: =G21*(1+H22) -> 46852.664 | I21: =H21*(1+I22) -> 49630.525 | J21: =I21*(1+J22) -> 52618.107 | K21: =J21*(1+K22) -> 55833.264 | ... M21: =L21*(1+M22) -> 63026.286
B22: Sales Growth % | D22: =CHOOSE($C$19,D7,D12,D17) -> 0.054753391 | E22: =CHOOSE($C$19,E7,E12,E17) -> 0.055660568 | F22: =CHOOSE($C$19,F7,F12,F17) -> 0.056567746 | G22: =CHOOSE($C$19,G7,G12,G17) -> 0.057474923 | H22: =CHOOSE($C$19,H7,H12,H17) -> 0.0583821 | I22: =CHOOSE($C$19,I7,I12,I17) -> 0.059289278 | J22: =CHOOSE($C$19,J7,J12,J17) -> 0.060196455 | K22: =CHOOSE($C$19,K7,K12,K17) -> 0.061103633 | ... M22: =CHOOSE($C$19,M7,M12,M17) -> 0.062917987

Sheet Growth Rate Analysis
B2: GROWTH RATE ANALYSIS
B3: Year | C3: Revenue | D3: %Change | E3: No. of years | F3: Logarithmic Regression | G3: Geomean | R3: ='Growth Rate Analysis'!C24 -> 0.062917987
B4: 2022 | C4: ='Historical Analysis'!C5 -> 28923.48 | E4: 1 | F4: =LN(C4) -> 10.272409
B5: 2023 | C5: ='Historical Analysis'!D5 -> 34367.83 | D5: =C5/C4-1 -> 0.18823288 | E5: 2 | F5: =LN(C5) -> 10.444876 | G5: =C5/C4 -> 1.1882329
B6: 2024 | C6: ='Historical Analysis'!E5 -> 35382.12 | D6: =C6/C5-1 -> 0.029512774 | E6: 3 | F6: =LN(C6) -> 10.473962 | G6: =C6/C5 -> 1.0295128
B7: 2025 | C7: ='Historical Analysis'!F5 -> 33797.36 | D7: =C7/C6-1 -> -0.044789854 | E7: 4 | F7: =LN(C7) -> 10.428138 | G7: =C7/C6 -> 0.95521015
B8: 2026 | C8: ='Historical Analysis'!G5 -> 35516.37 | D8: =C8/C7-1 -> 0.050862257 | E8: 5 | F8: =LN(C8) -> 10.477749 | G8: =C8/C7 -> 1.0508623
B10: Approaches to calculate 'g' | C10: values
B11: Arthmetic Method | C11: =AVERAGE(D5:D8) -> 0.055954515
B12: CAGR Method | C12: =(C8/C4)^(1/(E8-E4))-1 -> 0.052675479
B13: Log Regression | C13: =EXP(SLOPE(F4:F8,E4:E8))-1 -> 0.040180414
B14: Geometric Mean | C14: =GEOMEAN(G5:G8)-1 -> 0.052675479
B16: For FCFF Growth:
B17: Retention Ratio: | C17: 1- D/P Ratio
B18: Return on Equity: | C18: PAT/Equity
B19: Dividend Payout Ratio: | C19: DPS/EPS
B20: Earnings Per Share | C20: ='Profit & Loss'!C39 -> 45
B21: D/P Ratio | C21: 0.72
B22: Retention Ratio: | C22: =1-C21 -> 0.28
B23: RoE (Return on Equity) - 5yr Avg | C23: =AVERAGE('Ratio Analysis'!C33,'Ratio Analysis'!D33,'Ratio Analysis'!E33,'Ratio Analysis'!F33,'Ratio Analysis'!G33) -> 0.2247071
B24: g' ( Growth Rate) | C24: =C22*C23 -> 0.062917987

Sheet DCF Valuation
B1: DCF Valuation
D3: 1 | E3: 2 | F3: 3 | G3: 4 | H3: 5 | I3: 6 | J3: 7 | K3: 8 | L3: 9 | M3: 10
B4: INR Cr | C4: LTM | D4: Y1E | E4: Y2E | F4: Y3E | G4: Y4E | H4: Y5E | I4: Y6E | J4: Y7E | K4: Y8E | L4: Y9E | M4: Y10E | N4: Terminal Year | O4: Terminal Year | Q4: Terminal growth rate % | R4: ='Growth Rate Analysis'!C24 -> 0.062917987
B5: Sales | C5: ='Growth Scenerio'!C21 -> 35583.54 | D5: ='Growth Scenerio'!D21 -> 37531.859 | E5: ='Growth Scenerio'!E21 -> 39620.904 | F5: ='Growth Scenerio'!F21 -> 41862.169 | G5: ='Growth Scenerio'!G21 -> 44268.194 | H5: ='Growth Scenerio'!H21 -> 46852.664 | I5: ='Growth Scenerio'!I21 -> 49630.525 | J5: ='Growth Scenerio'!J21 -> 52618.107 | ... M5: ='Growth Scenerio'!M21 -> 63026.286 | N5: Terminal Year Revenue | O5: =M5*(1+R4) -> 66991.773 | Q5: Cost of Capital % | R5: =COC!K44 -> 0.13153843
B6: Sales Growth | D6: ='Growth Scenerio'!D22 -> 0.054753391 | E6: ='Growth Scenerio'!E22 -> 0.055660568 | F6: ='Growth Scenerio'!F22 -> 0.056567746 | G6: ='Growth Scenerio'!G22 -> 0.057474923 | H6: ='Growth Scenerio'!H22 -> 0.0583821 | I6: ='Growth Scenerio'!I22 -> 0.059289278 | J6: ='Growth Scenerio'!J22 -> 0.060196455 | K6: ='Growth Scenerio'!K22 -> 0.061103633 | ... M6: ='Growth Scenerio'!M22 -> 0.062917987 | N6: projected sales/revenue | O6: =R4 -> 0.062917987 | Q6: Terminal reinvestment rate % | R6: =R4*R5 -> 0.0082761331
B7: EBIT | D7: =D8*D5 -> 5883.6103 | E7: =E8*E5 -> 6211.0954 | F7: =F8*F5 -> 6562.443 | G7: =G8*G5 -> 6939.6189 | H7: =H8*H5 -> 7344.7685 | I7: =I8*I5 -> 7780.2345 | J7: =J8*J5 -> 8248.577 | K7: =K8*K5 -> 8752.595 | ... M7: =M8*M5 -> 9880.1953 | N7: EBIT | O7: =O8*O5 -> 10501.837
B8: EBIT Margin % | D8: =AVERAGE(Assumption!$C$29:$G$29) -> 0.15676309 | E8: =AVERAGE(Assumption!$C$29:$G$29) -> 0.15676309 | F8: =AVERAGE(Assumption!$C$29:$G$29) -> 0.15676309 | G8: =AVERAGE(Assumption!$C$29:$G$29) -> 0.15676309 | H8: =AVERAGE(Assumption!$C$29:$G$29) -> 0.15676309 | I8: =AVERAGE(Assumption!$C$29:$G$29) -> 0.15676309 | J8: =AVERAGE(Assumption!$C$29:$G$29) -> 0.15676309 | K8: =AVERAGE(Assumption!$C$29:$G$29) -> 0.15676309 | ... M8: =AVERAGE(Assumption!$C$29:$G$29) -> 0.15676309 | N8: EBIT Margin | O8: =M8 -> 0.15676309
B9: Less: Tax on EBIT | D9: =D7*Assumption!C$34 -> 1519.0357 | E9: =E7*Assumption!D$34 -> 1643.6069 | F9: =F7*Assumption!E$34 -> 1628.229 | G9: =G7*Assumption!F$34 -> 1815.6906 | H9: =H7*Assumption!$G$34 -> 1970.8073 | I9: =I7*Assumption!$G$34 -> 2087.655 | J9: =J7*Assumption!$G$34 -> 2213.3245 | K9: =K7*Assumption!$G$34 -> 2348.5666 | L9: =L7*Assumption!$G$34 -> 2494.2031 | M9: =M7*Assumption!$G$34 -> 2651.1334 | N9: Tax on EBIT | O9: =25%*O7 -> 2625.4593
B10: EBIT(1-T) | D10: =D7-D9 -> 4364.5746 | E10: =E7-E9 -> 4567.4884 | F10: =F7-F9 -> 4934.214 | G10: =G7-G9 -> 5123.9284 | H10: =H7-H9 -> 5373.9612 | I10: =I7-I9 -> 5692.5795 | J10: =J7-J9 -> 6035.2526 | K10: =K7-K9 -> 6404.0284 | ... M10: =M7-M9 -> 7229.0619 | N10: EBIT(1-T) | O10: =O7-O9 -> 7876.378
B11: Less: Net Capital Expenditure | D11: =D5*'Fixed Assets Schedule'!$D$13 -> 1005.2343 | E11: =E5*'Fixed Assets Schedule'!$D$13 -> 1061.1862 | F11: =F5*'Fixed Assets Schedule'!$D$13 -> 1121.2152 | G11: =G5*'Fixed Assets Schedule'!$D$13 -> 1185.6569 | H11: =H5*'Fixed Assets Schedule'!$D$13 -> 1254.878 | I11: =I5*'Fixed Assets Schedule'!$D$13 -> 1329.2789 | J11: =J5*'Fixed Assets Schedule'!$D$13 -> 1409.2967 | K11: =K5*'Fixed Assets Schedule'!$D$13 -> 1495.4099 | ... M11: =M5*'Fixed Assets Schedule'!$D$13 -> 1688.0641
B12: Non Cash Working Capital | C12: ='Working Capital Changes'!G7 -> 6342.45 | D12: =C12+D5*'Working Capital Changes'!$D$12 -> 6484.3191 | E12: =D12+E5*'Working Capital Changes'!$D$12 -> 6634.0847 | F12: =E12+F5*'Working Capital Changes'!$D$12 -> 6792.3222 | G12: =F12+G5*'Working Capital Changes'!$D$12 -> 6959.6543 | H12: =G12+H5*'Working Capital Changes'!$D$12 -> 7136.7557 | I12: =H12+I5*'Working Capital Changes'!$D$12 -> 7324.3573 | J12: =I12+J5*'Working Capital Changes'!$D$12 -> 7523.2518 | K12: =J12+K5*'Working Capital Changes'!$D$12 -> 7734.2996 | ... M12: =L12+M5*'Working Capital Changes'!$D$12 -> 8196.6716
B13: Less: Change in Working Capital | D13: =D12-C12 -> 141.86907 | E13: =E12-D12 -> 149.76559 | F13: =F12-E12 -> 158.23749 | G13: =G12-F12 -> 167.33218 | H13: =H12-G12 -> 177.10138 | I13: =I12-H12 -> 187.60159 | J13: =J12-I12 -> 198.89454 | K13: =K12-J12 -> 211.04772 | ... M13: =M12-L12 -> 238.23708
B14: Reinvestment | D14: =D11+D13 -> 1147.1034 | E14: =E11+E13 -> 1210.9518 | F14: =F11+F13 -> 1279.4526 | G14: =G11+G13 -> 1352.9891 | H14: =H11+H13 -> 1431.9794 | I14: =I11+I13 -> 1516.8805 | J14: =J11+J13 -> 1608.1913 | K14: =K11+K13 -> 1706.4576 | ... M14: =M11+M13 -> 1926.3012 | O14: =O10*O16 -> 65.185952
B15: Free Cash Flow To Firm (FCFF) | D15: =D10-D14 -> 3217.4712 | E15: =E10-E14 -> 3356.5366 | F15: =F10-F14 -> 3654.7614 | G15: =G10-G14 -> 3770.9393 | H15: =H10-H14 -> 3941.9818 | I15: =I10-I14 -> 4175.699 | J15: =J10-J14 -> 4427.0613 | K15: =K10-K14 -> 4697.5708 | ... M15: =M10-M14 -> 5302.7607 | O15: =O10-O14 -> 7811.192
B16: Implied Reinvestment rate % | D16: =D14/D10 -> 0.26282135 | E16: =E14/E10 -> 0.26512422 | F16: =F14/F10 -> 0.25930222 | G16: =G14/G10 -> 0.26405308 | H16: =H14/H10 -> 0.26646628 | I16: =I14/I10 -> 0.26646628 | J16: =J14/J10 -> 0.26646628 | K16: =K14/K10 -> 0.26646628 | ... M16: =M14/M10 -> 0.26646628 | O16: =R6 -> 0.0082761331
B18: Terminal Value | M18: =O15/(R5-R4) -> 113831.86
B20: Present Value Interest Factor (PVIF) | D20: =1/(1+$R$5)^1 -> 0.88375258 | E20: =1/(1+$R$5)^2 -> 0.78101862 | F20: =1/(1+$R$5)^3 -> 0.69022721 | G20: =1/(1+$R$5)^4 -> 0.60999008 | H20: =1/(1+$R$5)^5 -> 0.5390803 | I20: =1/(1+$R$5)^6 -> 0.47641361 | J20: =1/(1+$R$5)^7 -> 0.42103175 | K20: =1/(1+$R$5)^8 -> 0.3720879 | L20: =1/(1+$R$5)^9 -> 0.32883364 | M20: =1/(1+$R$5)^10 -> 0.29060757
B22: Present value of FCFF | C22: =SUM(D22:M22) -> 21195.595 | D22: =D15*D20 -> 2843.4485 | E22: =E15*E20 -> 2621.5176 | F22: =F15*F20 -> 2522.6157 | G22: =G15*G20 -> 2300.2356 | H22: =H15*H20 -> 2125.0447 | I22: =I15*I20 -> 1989.3598 | J22: =J15*J20 -> 1863.9334 | K22: =K15*K20 -> 1747.9092 | ... M22: =M15*M20 -> 1541.0224
B23: Present value of Terminal value | M23: =M18*M20 -> 33080.399
I24: Sensitivity: Intrinsic Value per Share
B25: Value of operating assets | C25: =C22+M23 -> 54275.995 | I25: =C32 -> 546.42436 | J25: =R5-0.02 -> 0.11153843 | K25: =R5-0.01 -> 0.12153843 | L25: =R5 -> 0.13153843 | M25: =R5+0.01 -> 0.14153843
B26: Add: Cash | C26: ='Balance Sheet'!C43 -> 1073.68 | I26: =R4-0.01 -> 0.052917987 | J26: =(D15*(1/(1+J25)^1)+E15*(1/(1+J25)^2)+F15*(1/(1+J25)^3)+G15*(1/(1+J25)^4)+H15*(1/(1+J25)^5)+I15*(1/(1+J25)^6)+J15*(1/(1+J25)^7)+K15*(1/(1+J25)^8)+L15*(1/(1+J25)^9)+M15*(1/(1+J25)^10)+(O15/(J25-I26))*(1/(1+J25)^10)+C26-C27-C28)/C31 -> 704.71266 | K26: =(D15*(1/(1+K25)^1)+E15*(1/(1+K25)^2)+F15*(1/(1+K25)^3)+G15*(1/(1+K25)^4)+H15*(1/(1+K25)^5)+I15*(1/(1+K25)^6)+J15*(1/(1+K25)^7)+K15*(1/(1+K25)^8)+L15*(1/(1+K25)^9)+M15*(1/(1+K25)^10)+(O15/(K25-I26))*(1/(1+K25)^10)+C26-C27-C28)/C31 -> 588.40922 | L26: =(D15*(1/(1+L25)^1)+E15*(1/(1+L25)^2)+F15*(1/(1+L25)^3)+G15*(1/(1+L25)^4)+H15*(1/(1+L25)^5)+I15*(1/(1+L25)^6)+J15*(1/(1+L25)^7)+K15*(1/(1+L25)^8)+L15*(1/(1+L25)^9)+M15*(1/(1+L25)^10)+(O15/(L25-I26))*(1/(1+L25)^10)+C26-C27-C28)/C31 -> 502.55856 | M26: =(D15*(1/(1+M25)^1)+E15*(1/(1+M25)^2)+F15*(1/(1+M25)^3)+G15*(1/(1+M25)^4)+H15*(1/(1+M25)^5)+I15*(1/(1+M25)^6)+J15*(1/(1+M25)^7)+K15*(1/(1+M25)^8)+L15*(1/(1+M25)^9)+M15*(1/(1+M25)^10)+(O15/(M25-I26))*(1/(1+M25)^10)+C26-C27-C28)/C31 -> 436.7747
B27: Less: Debt | C27: ='Balance Sheet'!C16+'Balance Sheet'!C22 -> 2293.26 | I27: =R4 -> 0.062917987 | J27: =(D15*(1/(1+J25)^1)+E15*(1/(1+J25)^2)+F15*(1/(1+J25)^3)+G15*(1/(1+J25)^4)+H15*(1/(1+J25)^5)+I15*(1/(1+J25)^6)+J15*(1/(1+J25)^7)+K15*(1/(1+J25)^8)+L15*(1/(1+J25)^9)+M15*(1/(1+J25)^10)+(O15/(J25-I27))*(1/(1+J25)^10)+C26-C27-C28)/C31 -> 803.95463 | K27: =(D15*(1/(1+K25)^1)+E15*(1/(1+K25)^2)+F15*(1/(1+K25)^3)+G15*(1/(1+K25)^4)+H15*(1/(1+K25)^5)+I15*(1/(1+K25)^6)+J15*(1/(1+K25)^7)+K15*(1/(1+K25)^8)+L15*(1/(1+K25)^9)+M15*(1/(1+K25)^10)+(O15/(K25-I27))*(1/(1+K25)^10)+C26-C27-C28)/C31 -> 652.70226 | L27: =(D15*(1/(1+L25)^1)+E15*(1/(1+L25)^2)+F15*(1/(1+L25)^3)+G15*(1/(1+L25)^4)+H15*(1/(1+L25)^5)+I15*(1/(1+L25)^6)+J15*(1/(1+L25)^7)+K15*(1/(1+L25)^8)+L15*(1/(1+L25)^9)+M15*(1/(1+L25)^10)+(O15/(L25-I27))*(1/(1+L25)^10)+C26-C27-C28)/C31 -> 546.42436 | M27: =(D15*(1/(1+M25)^1)+E15*(1/(1+M25)^2)+F15*(1/(1+M25)^3)+G15*(1/(1+M25)^4)+H15*(1/(1+M25)^5)+I15*(1/(1+M25)^6)+J15*(1/(1+M25)^7)+K15*(1/(1+M25)^8)+L15*(1/(1+M25)^9)+M15*(1/(1+M25)^10)+(O15/(M25-I27))*(1/(1+M25)^10)+C26-C27-C28)/C31 -> 467.87993
B28: Less: Minority Interest | C28: ='Balance Sheet'!C14 -> 643.39 | I28: =R4+0.01 -> 0.072917987 | J28: =(D15*(1/(1+J25)^1)+E15*(1/(1+J25)^2)+F15*(1/(1+J25)^3)+G15*(1/(1+J25)^4)+H15*(1/(1+J25)^5)+I15*(1/(1+J25)^6)+J15*(1/(1+J25)^7)+K15*(1/(1+J25)^8)+L15*(1/(1+J25)^9)+M15*(1/(1+J25)^10)+(O15/(J25-I28))*(1/(1+J25)^10)+C26-C27-C28)/C31 -> 954.5901 | K28: =(D15*(1/(1+K25)^1)+E15*(1/(1+K25)^2)+F15*(1/(1+K25)^3)+G15*(1/(1+K25)^4)+H15*(1/(1+K25)^5)+I15*(1/(1+K25)^6)+J15*(1/(1+K25)^7)+K15*(1/(1+K25)^8)+L15*(1/(1+K25)^9)+M15*(1/(1+K25)^10)+(O15/(K25-I28))*(1/(1+K25)^10)+C26-C27-C28)/C31 -> 743.44222 | L28: =(D15*(1/(1+L25)^1)+E15*(1/(1+L25)^2)+F15*(1/(1+L25)^3)+G15*(1/(1+L25)^4)+H15*(1/(1+L25)^5)+I15*(1/(1+L25)^6)+J15*(1/(1+L25)^7)+K15*(1/(1+L25)^8)+L15*(1/(1+L25)^9)+M15*(1/(1+L25)^10)+(O15/(L25-I28))*(1/(1+L25)^10)+C26-C27-C28)/C31 -> 605.25621 | M28: =(D15*(1/(1+M25)^1)+E15*(1/(1+M25)^2)+F15*(1/(1+M25)^3)+G15*(1/(1+M25)^4)+H15*(1/(1+M25)^5)+I15*(1/(1+M25)^6)+J15*(1/(1+M25)^7)+K15*(1/(1+M25)^8)+L15*(1/(1+M25)^9)+M15*(1/(1+M25)^10)+(O15/(M25-I28))*(1/(1+M25)^10)+C26-C27-C28)/C31 -> 508.05104
B29: Equity Value | C29: =C25+C26-C27-C28 -> 52413.025 | I29: =R4+0.02 -> 0.082917987 | J29: =(D15*(1/(1+J25)^1)+E15*(1/(1+J25)^2)+F15*(1/(1+J25)^3)+G15*(1/(1+J25)^4)+H15*(1/(1+J25)^5)+I15*(1/(1+J25)^6)+J15*(1/(1+J25)^7)+K15*(1/(1+J25)^8)+L15*(1/(1+J25)^9)+M15*(1/(1+J25)^10)+(O15/(J25-I29))*(1/(1+J25)^10)+C26-C27-C28)/C31 -> 1210.4898 | K29: =(D15*(1/(1+K25)^1)+E15*(1/(1+K25)^2)+F15*(1/(1+K25)^3)+G15*(1/(1+K25)^4)+H15*(1/(1+K25)^5)+I15*(1/(1+K25)^6)+J15*(1/(1+K25)^7)+K15*(1/(1+K25)^8)+L15*(1/(1+K25)^9)+M15*(1/(1+K25)^10)+(O15/(K25-I29))*(1/(1+K25)^10)+C26-C27-C28)/C31 -> 881.17283 | L29: =(D15*(1/(1+L25)^1)+E15*(1/(1+L25)^2)+F15*(1/(1+L25)^3)+G15*(1/(1+L25)^4)+H15*(1/(1+L25)^5)+I15*(1/(1+L25)^6)+J15*(1/(1+L25)^7)+K15*(1/(1+L25)^8)+L15*(1/(1+L25)^9)+M15*(1/(1+L25)^10)+(O15/(L25-I29))*(1/(1+L25)^10)+C26-C27-C28)/C31 -> 688.28852 | M29: =(D15*(1/(1+M25)^1)+E15*(1/(1+M25)^2)+F15*(1/(1+M25)^3)+G15*(1/(1+M25)^4)+H15*(1/(1+M25)^5)+I15*(1/(1+M25)^6)+J15*(1/(1+M25)^7)+K15*(1/(1+M25)^8)+L15*(1/(1+M25)^9)+M15*(1/(1+M25)^10)+(O15/(M25-I29))*(1/(1+M25)^10)+C26-C27-C28)/C31 -> 561.92764
I30: =R4+0.03 -> 0.092917987 | J30: =(D15*(1/(1+J25)^1)+E15*(1/(1+J25)^2)+F15*(1/(1+J25)^3)+G15*(1/(1+J25)^4)+H15*(1/(1+J25)^5)+I15*(1/(1+J25)^6)+J15*(1/(1+J25)^7)+K15*(1/(1+J25)^8)+L15*(1/(1+J25)^9)+M15*(1/(1+J25)^10)+(O15/(J25-I30))*(1/(1+J25)^10)+C26-C27-C28)/C31 -> 1741.2485 | K30: =(D15*(1/(1+K25)^1)+E15*(1/(1+K25)^2)+F15*(1/(1+K25)^3)+G15*(1/(1+K25)^4)+H15*(1/(1+K25)^5)+I15*(1/(1+K25)^6)+J15*(1/(1+K25)^7)+K15*(1/(1+K25)^8)+L15*(1/(1+K25)^9)+M15*(1/(1+K25)^10)+(O15/(K25-I30))*(1/(1+K25)^10)+C26-C27-C28)/C31 -> 1115.1498 | L30: =(D15*(1/(1+L25)^1)+E15*(1/(1+L25)^2)+F15*(1/(1+L25)^3)+G15*(1/(1+L25)^4)+H15*(1/(1+L25)^5)+I15*(1/(1+L25)^6)+J15*(1/(1+L25)^7)+K15*(1/(1+L25)^8)+L15*(1/(1+L25)^9)+M15*(1/(1+L25)^10)+(O15/(L25-I30))*(1/(1+L25)^10)+C26-C27-C28)/C31 -> 814.31998 | M30: =(D15*(1/(1+M25)^1)+E15*(1/(1+M25)^2)+F15*(1/(1+M25)^3)+G15*(1/(1+M25)^4)+H15*(1/(1+M25)^5)+I15*(1/(1+M25)^6)+J15*(1/(1+M25)^7)+K15*(1/(1+M25)^8)+L15*(1/(1+M25)^9)+M15*(1/(1+M25)^10)+(O15/(M25-I30))*(1/(1+M25)^10)+C26-C27-C28)/C31 -> 637.96637
B31: No. of Shares outstanding (Cr) | C31: =WACC!C22 -> 95.92
B32: Intrinsic value per share | C32: =C29/C31 -> 546.42436 | F32: Current CMP - ₹2,747
