Workbook
Name UPDATE: 'Data Sheet'!$E$1

Sheet Company Overview
B1: DABUR INDIA LIMITED
B2: Sector : FMCG | Industry : Household & Personal Products
B3: Section | C3: Points for Equity Research
B4: Company Name | C4: Dabur India Ltd
B5: Industry | C5: FMCG / Consumer Defensive
B6: Founded | C6: 1884
B7: Business Type | C7: Ayurvedic & Natural Healthcare Company
B8: Presence | C8: 120+ Countries
B9: Core Segments | C9: Hair Care, Oral Care, Healthcare, Foods & Beverages, Home Care
B10: Key Brands | C10: Dabur Amla, Real, Dabur Red, Hajmola, Chyawanprash, Odonil
B11: Business Strength | C11: Strong Brand Value + Wide Distribution Network
B12: Competitive Advantage | C12: Ayurveda positioning, consumer trust, repeat purchases
B13: Revenue Drivers | C13: Rural expansion, premiumisation, wellness products, e-commerce
B14: Future Growth Focus | C14: Health & Wellness, Functional Beverages, Premium Products
B15: Management Strategy | C15: Double-digit CAGR target till FY28
B16: FY25 Revenue | C16: ₹12,563 Cr
B17: FY25 Operating Profit | C17: ₹2,317 Cr
B18: FY25 PAT | C18: ₹1,768 Cr
B19: International Business Growth | C19: 0.172
B20: ESG Highlights | C20: 61% renewable energy usage, 87% recyclable packaging
B21: Key Positives | C21: Stable cash flows, strong margins, defensive business model
B22: Risks | C22: Competition, inflation, changing consumer demand
B23: Valuation Methods | C23: DCF, Relative Valuation, FCFF
B24: Why Premium Valuation? | C24: Predictable earnings and strong brand loyalty
B25: Analyst View | C25: Stable long-term FMCG company with consistent growth potential
B27: Address | C27: Dabur Registered Office:8/3, Asaf Ali Road, New Delhi – 110002

Sheet Promoters
B2: Statement showing shareholding pattern of the Promoter and Promoter Group
B3: Category of shareholder | C3: Shareholding as a % of total no. of shares (calculated as per SCRR, 1957)As a % of (A+B+C2) | D3: Number of Voting Rights held in each class of securities
D4: Class eg: X | E4: Total
B6: A1) Indian | C6: 0 | D6: - | E6: 0
B7: Individuals/Hindu undivided Family | C7: 0.09 | D7: 1570625 | E7: 0.09
B8: ASHOK CHAND BURMAN & BROS (ANAND CHAND BURMAN) (HUF) | C8: 0 | D8: 30000 | E8: 0
B9: GYAN CHAND BURMAN & OTHERS (AMIT BURMAN) (HUF) | C9: 0 | D9: 30000 | E9: 0
B10: PRADIP BURMAN & ORS (PRADIP BURMAN) (HUF) | C10: 0 | D10: 30000 | E10: 0
B11: VIVEK CHAND BURMAN | C11: 0 | D11: 15000 | E11: 0
B12: GAURI TANDON | C12: 0.04 | D12: 677995 | E12: 0.04
B13: PRADIP BURMAN | C13: 0.03 | D13: 597630 | E13: 0.03
B14: SHIVANI BURMAN | C14: 0 | D14: 30000 | E14: 0
B15: ASHA BURMAN | C15: 0.01 | D15: 154000 | E15: 0.01
B16: EISHANA BURMAN | C16: 0 | D16: 6000 | E16: 0
B17: AMIT BURMAN | C17: 0 | D17: - | E17: 0
B18: ADITYA BURMAN | C18: 0 | D18: - | E18: 0
B19: ARIANA BURMAN | C19: 0 | D19: - | E19: 0
B20: DIVYA BURMAN | C20: 0 | D20: - | E20: 0
B21: ADHIRAJ BURMAN | C21: 0 | D21: - | E21: 0
B22: DIYA BURMAN | C22: 0 | D22: - | E22: 0
B23: SANDEEP TANDON | C23: 0 | D23: - | E23: 0
B24: ARMAAN TANDON | C24: 0 | D24: - | E24: 0
B25: POOJA BURMAN | C25: 0 | D25: - | E25: 0
B26: SUMATI RAVI RAHEJA | C26: 0 | D26: - | E26: 0
B27: RAMAN SOOD | C27: 0 | D27: - | E27: 0
B28: UMESH TALWAR | C28: 0 | D28: - | E28: 0
... B31: SIDHARTH BURMAN HUF | C31: 0 | D31: - | E31: 0
B32: Any Other (specify) | C32: 66.09 | D32: 1172228360 | E32: 66.09
B33: VIC ENTERPRISES PVT LTD | C33: 12.28 | D33: 217794000 | E33: 12.28
B34: RATNA COMMERCIAL ENTERPRISES PRIVATE LIMITED | C34: 8.99 | D34: 159405604 | E34: 8.99
B35: CHOWDRY ASSOCIATES | C35: 11.79 | D35: 209083800 | E35: 11.79
B36: SAHIWAL INVESTMENT AND TRADING COMPANY | C36: 0 | D36: 15000 | E36: 0
B37: BURMANS FINVEST PRIVATE LIMITED | C37: 2.99 | D37: 53012986 | E37: 2.99
B38: MILKY INVESTMENT AND TRADING COMPANY | C38: 5.98 | D38: 106147503 | E38: 5.98
B39: GYAN ENTERPRISES PVT LTD | C39: 10.9 | D39: 193379980 | E39: 10.9
B40: WINDY INVESTMENTS PRIVATE LIMITED | C40: 1 | D40: 17670995 | E40: 1
B41: M.B. FINMART PRIVATE LIMITED | C41: 1.49 | D41: 26506492 | E41: 1.49
B42: PURAN ASSOCIATES PRIVATE LIMITED | C42: 10.67 | D42: 189212000 | E42: 10.67
B43: BURMAN BROTHERS, PARTNERSHIP FIRM | C43: 0 | D43: - | E43: 0
B44: ASIA PACIFIC HEALTHCARE ADVISORS LLP | C44: 0 | D44: - | E44: 0
B45: DABUR INVESTMENT CORPORATION | C45: 0 | D45: - | E45: 0
B46: WESTERN ENTERPRISES | C46: 0 | D46: - | E46: 0
B47: EASTERN ENTERPRISES | C47: 0 | D47: - | E47: 0
B48: DABUR INVEST CORP | C48: 0 | D48: - | E48: 0
B49: A.CEE ENTERPRISES | C49: 0 | D49: - | E49: 0
B50: AVIVA LIFE INSURANCE COMPANY INDIA LIMITED | C50: 0 | D50: - | E50: 0
B51: ONCQUEST LABORATORIES LTD. | C51: 0 | D51: - | E51: 0
B52: MOONLIGHT RANCH PVT. LTD. | C52: 0 | D52: - | E52: 0
B53: VANSH HOLDINGS PVT. LTD. | C53: 0 | D53: - | E53: 0
B54: KBC INDIA PVT. LTD. | C54: 0 | D54: - | E54: 0
... B138: Rabia Spinner Private Limited | C138: 0 | D138: - | E138: 0
B139: Sub Total A1 | C139: 66.18 | D139: 1173798985 | E139: 66.18
B140: A2) Foreign | C140: 0 | D140: - | E140: 0
B141: Individuals (NonResident Individuals/ Foreign Individuals) | C141: 0.07 | D141: 1206000 | E141: 0.07
B142: MONICA BURMAN | C142: 0 | D142: 15000 | E142: 0
B143: MINNIE BURMAN | C143: 0 | D143: 30000 | E143: 0
B144: ANAND CHAND BURMAN | C144: 0.04 | D144: 660000 | E144: 0.04
B145: MOHIT BURMAN | C145: 0 | D145: 80000 | E145: 0
B146: CHETAN BURMAN | C146: 0 | D146: 21000 | E146: 0
B147: SAKET BURMAN | C147: 0.02 | D147: 300000 | E147: 0.02
B148: INDIRA BURMAN | C148: 0.01 | D148: 100000 | E148: 0.01
B149: ANISHA BURMAN | C149: 0 | D149: - | E149: 0
B150: GAURAV BURMAN | C150: 0 | D150: - | E150: 0
B151: ISHAAAN TANDON | C151: 0 | D151: - | E151: 0
B152: KAMRAN BURMAN | C152: 0 | D152: - | E152: 0
B153: DEVIKA BURMAN | C153: 0 | D153: - | E153: 0
B154: MEERA BURMAN | C154: 0 | D154: - | E154: 0
B155: Victoria Burman | C155: 0 | D155: - | E155: 0
B156: Maya Rose Burman | C156: 0 | D156: - | E156: 0
B157: Sophia Indira Burman | C157: 0 | D157: - | E157: 0
B158: Any Other (specify) | C158: 0 | D158: - | E158: 0
B159: GREATER HIMALAYAN HONEY TRADING LLC | C159: 0 | D159: - | E159: 0
B160: BBIFO HOLDINGS LIMITED | C160: 0 | D160: - | E160: 0
... B165: Lite Bite Foods Inc. Ltd | C165: 0 | D165: - | E165: 0
B166: Sub Total A2 | C166: 0.07 | D166: 1206000 | E166: 0.07
B167: A=A1+A2 | C167: 66.25 | D167: 1175004985 | E167: 66.25

Sheet Public
B2: Statement showing shareholding pattern of the Public shareholder
B4: Category & Name of the Shareholders | C4: No. of shareholder | D4: No. of fully paid up equity shares held | E4: Total no. shares held | F4: Shareholding % calculated as per SCRR, 1957 As a % of (A+B+C2) | G4: No. of Voting Rights | H4: Total as a % of Total Voting right | I4: Total No. Of shares on fully diluted basis (including warrants, ESOP, Convertible Securities etc.) | J4: Shareholding , as a % assuming full conversion of convertible securities ( as a percentage of diluted share capital)As a % of (A+B+C2) | K4: No. of equity shares held in dematerialized form(Not Applicable)
B7: Institutions | C7: 0 | D7: 0 | E7: - | F7: 0 | G7: - | H7: 0 | I7: - | J7: 0 | K7: -
B8: B2) Institutions (Domestic) | C8: 0 | D8: 0 | E8: - | F8: 0 | G8: - | H8: 0 | I8: - | J8: 0 | K8: -
B9: Mutual Funds/ | C9: 35 | D9: 125909430 | E9: 125909430 | F9: 7.1 | G9: 125909430 | H9: 7.1 | I9: 125909430 | J9: 7.09 | K9: 125909430
B10: SBI LARGE & MIDCAP FUND | C10: 1 | D10: 30784597 | E10: 30784597 | F10: 1.74 | G10: 30784597 | H10: 1.74 | I10: 30784597 | J10: 1.73 | K10: 30784597
B11: HDFC TRUSTEE COMPANY LTD. A/C HDFC LARGE CAP FUND | C11: 1 | D11: 45904492 | E11: 45904492 | F11: 2.59 | G11: 45904492 | H11: 2.59 | I11: 45904492 | J11: 2.58 | K11: 45904492
B12: Venture Capital Funds | C12: 0 | D12: 0 | E12: - | F12: 0 | G12: - | H12: 0 | I12: - | J12: 0 | K12: -
B13: Alternate Investment Funds | C13: 4 | D13: 259605 | E13: 259605 | F13: 0.01 | G13: 259605 | H13: 0.01 | I13: 259605 | J13: 0.01 | K13: 259605
B14: Banks | C14: 3 | D14: 974315 | E14: 974315 | F14: 0.05 | G14: 974315 | H14: 0.05 | I14: 974315 | J14: 0.05 | K14: 974315
B15: Insurance Companies | C15: 28 | D15: 177720958 | E15: 177720958 | F15: 10.02 | G15: 177720958 | H15: 10.02 | I15: 177720958 | J15: 10 | K15: 177720958
B16: LIFE INSURANCE CORPORATION OF INDIA - ULIF00320091 | C16: 1 | D16: 151981918 | E16: 151981918 | F16: 8.57 | G16: 151981918 | H16: 8.57 | I16: 151981918 | J16: 8.55 | K16: 151981918
B17: Provident Funds/ Pension Funds | C17: 1 | D17: 22462399 | E17: 22462399 | F17: 1.27 | G17: 22462399 | H17: 1.27 | I17: 22462399 | J17: 1.26 | K17: 22462399
B18: NPS TRUST- A/C LIC PENSION FUND SCHEME E - TIER I | C18: 1 | D18: 22462399 | E18: 22462399 | F18: 1.27 | G18: 22462399 | H18: 1.27 | I18: 22462399 | J18: 1.26 | K18: 22462399
B19: Asset reconstruction companies | C19: 0 | D19: 0 | E19: - | F19: 0 | G19: - | H19: 0 | I19: - | J19: 0 | K19: -
B20: Sovereign Wealth Funds | C20: 2 | D20: 1812410 | E20: 1812410 | F20: 0.1 | G20: 1812410 | H20: 0.1 | I20: 1812410 | J20: 0.1 | K20: 1812410
B21: NBFCs registered with RBI | C21: 8 | D21: 128500 | E21: 128500 | F21: 0.01 | G21: 128500 | H21: 0.01 | I21: 128500 | J21: 0.01 | K21: 128500
B22: Other Financial Institutions | C22: 0 | D22: 0 | E22: - | F22: 0 | G22: - | H22: 0 | I22: - | J22: 0 | K22: -
B23: Any Other(Institutions (Domestic)) | C23: 0 | D23: 0 | E23: - | F23: 0 | G23: - | H23: 0 | I23: - | J23: 0 | K23: -
B24: Sub Total B1 | C24: 81 | D24: 329267617 | E24: 329267617 | F24: 18.56 | G24: 329267617 | H24: 18.56 | I24: 329267617 | J24: 18.53 | K24: 329267617
B25: B19) Institutions (Foreign) | C25: 0 | D25: 0 | E25: - | F25: 0 | G25: - | H25: 0 | I25: - | J25: 0 | K25: -
B26: Foreign Direct Investment | C26: 0 | D26: 0 | E26: - | F26: 0 | G26: - | H26: 0 | I26: - | J26: 0 | K26: -
B27: Foreign Venture Capital Investors | C27: 0 | D27: 0 | E27: - | F27: 0 | G27: - | H27: 0 | I27: - | J27: 0 | K27: -
B28: Sovereign Wealth Funds | C28: 0 | D28: 0 | E28: - | F28: 0 | G28: - | H28: 0 | I28: - | J28: 0 | K28: -
B29: Foreign Portfolio Investors Category I | C29: 623 | D29: 172140677 | E29: 172140677 | F29: 9.71 | G29: 172140677 | H29: 9.71 | I29: 172140677 | J29: 9.69 | K29: 172140677
B30: Foreign Portfolio Investors Category II | C30: 32 | D30: 4798098 | E30: 4798098 | F30: 0.27 | G30: 4798098 | H30: 0.27 | I30: 4798098 | J30: 0.27 | K30: 4798098
B31: Overseas Depositories (holding DRs) (balancing figure) | C31: 1 | D31: 6000 | E31: 6000 | F31: 0 | G31: 6000 | H31: 0 | I31: 6000 | J31: 0 | K31: -
B32: Any Other(Institutions (Foreign)) | C32: 1 | D32: 6000 | E32: 6000 | F32: 0 | G32: 6000 | H32: 0 | I32: 6000 | J32: 0 | K32: 6000
B33: FOREIGN BANK | C33: 1 | D33: 6000 | E33: 6000 | F33: 0 | G33: 6000 | H33: 0 | I33: 6000 | J33: 0 | K33: 6000
B34: Sub Total B2 | C34: 657 | D34: 176950775 | E34: 176950775 | F34: 9.98 | G34: 176950775 | H34: 9.98 | I34: 176950775 | J34: 9.96 | K34: 176944775
B35: B29) Central Government/ State Government(s)/ President of India | C35: 0 | D35: 0 | E35: - | F35: 0 | G35: - | H35: 0 | I35: - | J35: 0 | K35: -
B36: Central Government / President of India | C36: 0 | D36: 0 | E36: - | F36: 0 | G36: - | H36: 0 | I36: - | J36: 0 | K36: -
B37: State Government / Governor | C37: 0 | D37: 0 | E37: - | F37: 0 | G37: - | H37: 0 | I37: - | J37: 0 | K37: -
B38: Shareholding by Companies or Bodies Corporate where Central / State Government is a promoter | C38: 1 | D38: 238 | E38: 238 | F38: 0 | G38: 238 | H38: 0 | I38: 238 | J38: 0 | K38: 238
B39: Sub Total B3 | C39: 1 | D39: 238 | E39: 238 | F39: 0 | G39: 238 | H39: 0 | I39: 238 | J39: 0 | K39: 238
B40: B34) Non-Institutions | C40: 0 | D40: 0 | E40: - | F40: 0 | G40: - | H40: 0 | I40: - | J40: 0 | K40: -
B41: Associate companies / Subsidiaries | C41: 0 | D41: 0 | E41: - | F41: 0 | G41: - | H41: 0 | I41: - | J41: 0 | K41: -
B42: Directors and their relatives (excluding independent directors and nominee directors) | C42: 3 | D42: 4784865 | E42: 4784865 | F42: 0.27 | G42: 4784865 | H42: 0.27 | I42: 6819315 | J42: 0.38 | K42: 4784865
B43: Key Managerial Personnel | C43: 3 | D43: 375082 | E43: 375082 | F43: 0.02 | G43: 375082 | H43: 0.02 | I43: 445282 | J43: 0.03 | K43: 375082
B44: Relatives of promoters (other than 'immediate relatives' of promoters disclosed under 'Promoter and Promoter Group' category) | C44: 0 | D44: 0 | E44: - | F44: 0 | G44: - | H44: 0 | I44: - | J44: 0 | K44: -
B45: Trusts where any person belonging to 'Promoter and Promoter Group' category is 'trustee', 'beneficiary', or 'author of the trust' | C45: 0 | D45: 0 | E45: - | F45: 0 | G45: - | H45: 0 | I45: - | J45: 0 | K45: -
B46: Investor Education and Protection Fund (IEPF) | C46: 1 | D46: 2964326 | E46: 2964326 | F46: 0.17 | G46: 2964326 | H46: 0.17 | I46: 2964326 | J46: 0.17 | K46: 2964326
B47: Resident Individuals holding nominal share capital up to Rs. 2 lakhs | C47: 453934 | D47: 64638915 | E47: 64638915 | F47: 3.64 | G47: 64638915 | H47: 3.64 | I47: 65823100 | J47: 3.7 | K47: 63466139
B48: Resident Individuals holding nominal share capital in excess of Rs. 2 lakhs | C48: 14 | D48: 8569664 | E48: 8569664 | F48: 0.48 | G48: 8569664 | H48: 0.48 | I48: 8569664 | J48: 0.48 | K48: 8569664
B49: Non Resident Indians (NRIs) | C49: 10084 | D49: 4836932 | E49: 4836932 | F49: 0.27 | G49: 4836932 | H49: 0.27 | I49: 4836932 | J49: 0.27 | K49: 4523432
B50: Foreign Nationals | C50: 2 | D50: 1919 | E50: 1919 | F50: 0 | G50: 1919 | H50: 0 | I50: 1919 | J50: 0 | K50: 1919
B51: Foreign Companies | C51: 1 | D51: 78000 | E51: 78000 | F51: 0 | G51: 78000 | H51: 0 | I51: 78000 | J51: 0 | K51: 78000
B52: Bodies Corporate | C52: 928 | D52: 4421223 | E52: 4421223 | F52: 0.25 | G52: 4421223 | H52: 0.25 | I52: 4421223 | J52: 0.25 | K52: 4418223
B53: Any Other (specify) | C53: 3889 | D53: 1795631 | E53: 1795631 | F53: 0.1 | G53: 1795631 | H53: 0.1 | I53: 1795631 | J53: 0.1 | K53: 1795631
B54: HUF | C54: 3871 | D54: 1685665 | E54: 1685665 | F54: 0.1 | G54: 1685665 | H54: 0.1 | I54: 1685665 | J54: 0.09 | K54: 1685665
B55: Clearing Members | C55: 3 | D55: 735 | E55: 735 | F55: 0 | G55: 735 | H55: 0 | I55: 735 | J55: 0 | K55: 735
B56: Trusts | C56: 15 | D56: 109231 | E56: 109231 | F56: 0.01 | G56: 109231 | H56: 0.01 | I56: 109231 | J56: 0.01 | K56: 109231
B57: Sub Total B4 | C57: 468859 | D57: 92466557 | E57: 92466557 | F57: 5.21 | G57: 92466557 | H57: 5.21 | I57: 95755392 | J57: 5.39 | K57: 90977281
B58: B=B1+B2+B3+B4 | C58: 469598 | D58: 598685187 | E58: 598685187 | F58: 33.75 | G58: 598685187 | H58: 33.75 | I58: 601974022 | J58: 33.88 | K58: 597189911

Sheet Balance Sheet
A1: ='Profit & Loss'!A1 -> DABUR INDIA LTD
A3: Narration | B3: ='Data Sheet'!B53 -> 42825 | C3: ='Data Sheet'!C53 -> 43190 | D3: ='Data Sheet'!D53 -> 43555 | E3: ='Data Sheet'!E53 -> 43921 | F3: ='Data Sheet'!F53 -> 44286 | G3: ='Data Sheet'!G53 -> 44651 | H3: ='Data Sheet'!H53 -> 45016 | I3: ='Data Sheet'!I53 -> 45382 | ... K3: ='Data Sheet'!K53 -> 46112
A4: Equity Share Capital | B4: ='Data Sheet'!B54 -> 176.15 | C4: ='Data Sheet'!C54 -> 176.15 | D4: ='Data Sheet'!D54 -> 176.63 | E4: ='Data Sheet'!E54 -> 176.71 | F4: ='Data Sheet'!F54 -> 176.74 | G4: ='Data Sheet'!G54 -> 176.79 | H4: ='Data Sheet'!H54 -> 177.18 | I4: ='Data Sheet'!I54 -> 177.2 | ... K4: ='Data Sheet'!K54 -> 177.37
A5: Reserves | B5: ='Data Sheet'!B55 -> 4671.24 | C5: ='Data Sheet'!C55 -> 5530.37 | D5: ='Data Sheet'!D55 -> 5455.05 | E5: ='Data Sheet'!E55 -> 6429.04 | F5: ='Data Sheet'!F55 -> 7486.79 | G5: ='Data Sheet'!G55 -> 8204.51 | H5: ='Data Sheet'!H55 -> 8796.08 | I5: ='Data Sheet'!I55 -> 9689.1 | ... K5: ='Data Sheet'!K55 -> 11242.15
A6: Borrowings | B6: ='Data Sheet'!B56 -> 975 | C6: ='Data Sheet'!C56 -> 937.59 | D6: ='Data Sheet'!D56 -> 699.37 | E6: ='Data Sheet'!E56 -> 521.99 | F6: ='Data Sheet'!F56 -> 509.06 | G6: ='Data Sheet'!G56 -> 1030.1 | H6: ='Data Sheet'!H56 -> 1173.79 | I6: ='Data Sheet'!I56 -> 1365.09 | ... K6: ='Data Sheet'!K56 -> 1287.32 | L6: Long+Short | M6: =16+1047 -> 1063
A7: Other Liabilities | B7: ='Data Sheet'!B57 -> 1909.85 | C7: ='Data Sheet'!C57 -> 2057.52 | D7: ='Data Sheet'!D57 -> 2105.59 | E7: ='Data Sheet'!E57 -> 2208.84 | F7: ='Data Sheet'!F57 -> 2660.63 | G7: ='Data Sheet'!G57 -> 2872.46 | H7: ='Data Sheet'!H57 -> 3505.23 | I7: ='Data Sheet'!I57 -> 3884.97 | ... K7: ='Data Sheet'!K57 -> 4773.07
A8: Total | B8: ='Data Sheet'!B58 -> 7732.24 | C8: ='Data Sheet'!C58 -> 8701.63 | D8: ='Data Sheet'!D58 -> 8436.64 | E8: ='Data Sheet'!E58 -> 9336.58 | F8: ='Data Sheet'!F58 -> 10833.22 | G8: ='Data Sheet'!G58 -> 12283.86 | H8: ='Data Sheet'!H58 -> 13652.28 | I8: ='Data Sheet'!I58 -> 15116.36 | ... K8: ='Data Sheet'!K58 -> 17479.91
A10: Net Block | B10: ='Data Sheet'!B59 -> 1958.4 | C10: ='Data Sheet'!C59 -> 2028.11 | D10: ='Data Sheet'!D59 -> 1969.06 | E10: ='Data Sheet'!E59 -> 2252.68 | F10: ='Data Sheet'!F59 -> 2242.92 | G10: ='Data Sheet'!G59 -> 2307.9 | H10: ='Data Sheet'!H59 -> 3578.65 | I10: ='Data Sheet'!I59 -> 3815 | ... K10: ='Data Sheet'!K59 -> 3938.92 | M10: Other Liabilities - | N10: 2019 | O10: 1956 | P10: 1910 | Q10: 2058 | R10: 2106 | S10: 2209 | T10: 2661 | U10: 2872 | V10: 3505 | W10: 3885 | X10: 4479 | Y10: 4773
A11: Capital Work in Progress | B11: ='Data Sheet'!B60 -> 42.1 | C11: ='Data Sheet'!C60 -> 41.51 | D11: ='Data Sheet'!D60 -> 63.76 | E11: ='Data Sheet'!E60 -> 146.57 | F11: ='Data Sheet'!F60 -> 147.3 | G11: ='Data Sheet'!G60 -> 167.5 | H11: ='Data Sheet'!H60 -> 175.13 | I11: ='Data Sheet'!I60 -> 232.23 | ... K11: ='Data Sheet'!K60 -> 137.48 | M11: Non controlling int | N11: 18 | O11: 22 | P11: 25 | Q11: 27 | R11: 31 | S11: 36 | T11: 37 | U11: 41 | V11: 468 | W11: 437 | X11: 410 | Y11: 383
A12: Investments | B12: ='Data Sheet'!B61 -> 3240.16 | C12: ='Data Sheet'!C61 -> 3805.17 | D12: ='Data Sheet'!D61 -> 3358.76 | E12: ='Data Sheet'!E61 -> 2800.26 | F12: ='Data Sheet'!F61 -> 4159.63 | G12: ='Data Sheet'!G61 -> 6219.62 | H12: ='Data Sheet'!H61 -> 6265.26 | I12: ='Data Sheet'!I61 -> 6932.69 | ... K12: ='Data Sheet'!K61 -> 8947.26 | M12: Trade Payables | N12: 1096 | O12: 1330 | P12: 1310 | Q12: 1410 | R12: 1455 | S12: 1482 | T12: 1915 | U12: 2018 | V12: 2187 | W12: 2422 | X12: 2825 | Y12: 2954
A13: Other Assets | B13: ='Data Sheet'!B62 -> 2491.58 | C13: ='Data Sheet'!C62 -> 2826.84 | D13: ='Data Sheet'!D62 -> 3045.06 | E13: ='Data Sheet'!E62 -> 4137.07 | F13: ='Data Sheet'!F62 -> 4283.37 | G13: ='Data Sheet'!G62 -> 3588.84 | H13: ='Data Sheet'!H62 -> 3633.24 | I13: ='Data Sheet'!I62 -> 4136.44 | ... K13: ='Data Sheet'!K62 -> 4456.25 | M13: Advance from Customers | N13: 42 | O13: 35 | P13: 18 | Q13: 25 | R13: 28 | S13: 30 | T13: 43 | U13: 37 | V13: 9 | W13: 33 | X13: 28
A14: Total | B14: ='Data Sheet'!B63 -> 7732.24 | C14: ='Data Sheet'!C63 -> 8701.63 | D14: ='Data Sheet'!D63 -> 8436.64 | E14: ='Data Sheet'!E63 -> 9336.58 | F14: ='Data Sheet'!F63 -> 10833.22 | G14: ='Data Sheet'!G63 -> 12283.86 | H14: ='Data Sheet'!H63 -> 13652.28 | I14: ='Data Sheet'!I63 -> 15116.36 | ... K14: ='Data Sheet'!K63 -> 17479.91 | M14: Other liability items | N14: 863 | O14: 569 | P14: 557 | Q14: 596 | R14: 591 | S14: 660 | T14: 666 | U14: 777 | V14: 842 | W14: 994 | X14: 1216 | Y14: 1436
A16: Working Capital | B16: =B13-B7 -> 581.73 | C16: =C13-C7 -> 769.32 | D16: =D13-D7 -> 939.47 | E16: =E13-E7 -> 1928.23 | F16: =F13-F7 -> 1622.74 | G16: =G13-G7 -> 716.38 | H16: =H13-H7 -> 128.01 | I16: =I13-I7 -> 251.47 | ... K16: =K13-K7 -> -316.82
A17: Debtors | B17: ='Data Sheet'!B64 -> 650.42 | C17: ='Data Sheet'!C64 -> 706.08 | D17: ='Data Sheet'!D64 -> 833.56 | E17: ='Data Sheet'!E64 -> 813.89 | F17: ='Data Sheet'!F64 -> 561.58 | G17: ='Data Sheet'!G64 -> 646.15 | H17: ='Data Sheet'!H64 -> 848.75 | I17: ='Data Sheet'!I64 -> 898.72 | ... K17: ='Data Sheet'!K64 -> 715.41
A18: Inventory | B18: ='Data Sheet'!B65 -> 1106.71 | C18: ='Data Sheet'!C65 -> 1256.18 | D18: ='Data Sheet'!D65 -> 1300.53 | E18: ='Data Sheet'!E65 -> 1379.57 | F18: ='Data Sheet'!F65 -> 1734.28 | G18: ='Data Sheet'!G65 -> 1911.37 | H18: ='Data Sheet'!H65 -> 2024.2 | I18: ='Data Sheet'!I65 -> 1946.97 | ... K18: ='Data Sheet'!K65 -> 2321.63
A20: Debtor Days | B20: =IF('Profit & Loss'!B4>0,'Balance Sheet'!B17/('Profit & Loss'!B4/365),0) -> 31.181519 | C20: =IF('Profit & Loss'!C4>0,'Balance Sheet'!C17/('Profit & Loss'!C4/365),0) -> 33.375318 | D20: =IF('Profit & Loss'!D4>0,'Balance Sheet'!D17/('Profit & Loss'!D4/365),0) -> 35.731034 | E20: =IF('Profit & Loss'!E4>0,'Balance Sheet'!E17/('Profit & Loss'!E4/365),0) -> 34.206352 | F20: =IF('Profit & Loss'!F4>0,'Balance Sheet'!F17/('Profit & Loss'!F4/365),0) -> 21.437377 | G20: =IF('Profit & Loss'!G4>0,'Balance Sheet'!G17/('Profit & Loss'!G4/365),0) -> 21.659627 | H20: =IF('Profit & Loss'!H4>0,'Balance Sheet'!H17/('Profit & Loss'!H4/365),0) -> 26.868752 | I20: =IF('Profit & Loss'!I4>0,'Balance Sheet'!I17/('Profit & Loss'!I4/365),0) -> 26.445706 | ... K20: =IF('Profit & Loss'!K4>0,'Balance Sheet'!K17/('Profit & Loss'!K4/365),0) -> 19.793312
A21: Inventory Turnover | B21: =IF('Balance Sheet'!B18>0,'Profit & Loss'!B4/'Balance Sheet'!B18,0) -> 6.8794806 | C21: =IF('Balance Sheet'!C18>0,'Profit & Loss'!C4/'Balance Sheet'!C18,0) -> 6.1470888 | D21: =IF('Balance Sheet'!D18>0,'Profit & Loss'!D4/'Balance Sheet'!D18,0) -> 6.547323 | E21: =IF('Balance Sheet'!E18>0,'Profit & Loss'!E4/'Balance Sheet'!E18,0) -> 6.2951789 | F21: =IF('Balance Sheet'!F18>0,'Profit & Loss'!F4/'Balance Sheet'!F18,0) -> 5.5133254 | G21: =IF('Balance Sheet'!G18>0,'Profit & Loss'!G4/'Balance Sheet'!G18,0) -> 5.6967934 | H21: =IF('Balance Sheet'!H18>0,'Profit & Loss'!H4/'Balance Sheet'!H18,0) -> 5.6960231 | I21: =IF('Balance Sheet'!I18>0,'Profit & Loss'!I4/'Balance Sheet'!I18,0) -> 6.3709302 | ... K21: =IF('Balance Sheet'!K18>0,'Profit & Loss'!K4/'Balance Sheet'!K18,0) -> 5.6824602
A23: Return on Equity | B23: =IF(SUM('Balance Sheet'!B4:B5)>0,'Profit & Loss'!B12/SUM('Balance Sheet'!B4:B5),"") -> 0.26342836 | C23: =IF(SUM('Balance Sheet'!C4:C5)>0,'Profit & Loss'!C12/SUM('Balance Sheet'!C4:C5),"") -> 0.2373408 | D23: =IF(SUM('Balance Sheet'!D4:D5)>0,'Profit & Loss'!D12/SUM('Balance Sheet'!D4:D5),"") -> 0.25611008 | E23: =IF(SUM('Balance Sheet'!E4:E5)>0,'Profit & Loss'!E12/SUM('Balance Sheet'!E4:E5),"") -> 0.21874276 | F23: =IF(SUM('Balance Sheet'!F4:F5)>0,'Profit & Loss'!F12/SUM('Balance Sheet'!F4:F5),"") -> 0.22095562 | G23: =IF(SUM('Balance Sheet'!G4:G5)>0,'Profit & Loss'!G12/SUM('Balance Sheet'!G4:G5),"") -> 0.20751196 | H23: =IF(SUM('Balance Sheet'!H4:H5)>0,'Profit & Loss'!H12/SUM('Balance Sheet'!H4:H5),"") -> 0.19024858 | I23: =IF(SUM('Balance Sheet'!I4:I5)>0,'Profit & Loss'!I12/SUM('Balance Sheet'!I4:I5),"") -> 0.18676505 | ... K23: =IF(SUM('Balance Sheet'!K4:K5)>0,'Profit & Loss'!K12/SUM('Balance Sheet'!K4:K5),"") -> 0.16594655
A24: Return on Capital Emp | C24: =IF((B4+B5+B6+C4+C5+C6)>0,('Profit & Loss'!C10+'Profit & Loss'!C9)*2/(B4+B5+B6+C4+C5+C6),"") -> 0.28013316 | D24: =IF((C4+C5+C6+D4+D5+D6)>0,('Profit & Loss'!D10+'Profit & Loss'!D9)*2/(C4+C5+C6+D4+D5+D6),"") -> 0.27505634 | E24: =IF((D4+D5+D6+E4+E5+E6)>0,('Profit & Loss'!E10+'Profit & Loss'!E9)*2/(D4+D5+D6+E4+E5+E6),"") -> 0.26409209 | F24: =IF((E4+E5+E6+F4+F5+F6)>0,('Profit & Loss'!F10+'Profit & Loss'!F9)*2/(E4+E5+E6+F4+F5+F6),"") -> 0.27278235 | G24: =IF((F4+F5+F6+G4+G5+G6)>0,('Profit & Loss'!G10+'Profit & Loss'!G9)*2/(F4+F5+F6+G4+G5+G6),"") -> 0.26242963 | H24: =IF((G4+G5+G6+H4+H5+H6)>0,('Profit & Loss'!H10+'Profit & Loss'!H9)*2/(G4+G5+G6+H4+H5+H6),"") -> 0.23487751 | I24: =IF((H4+H5+H6+I4+I5+I6)>0,('Profit & Loss'!I10+'Profit & Loss'!I9)*2/(H4+H5+H6+I4+I5+I6),"") -> 0.23228262 | J24: =IF((I4+I5+I6+J4+J5+J6)>0,('Profit & Loss'!J10+'Profit & Loss'!J9)*2/(I4+I5+I6+J4+J5+J6),"") -> 0.21071644 | K24: =IF((J4+J5+J6+K4+K5+K6)>0,('Profit & Loss'!K10+'Profit & Loss'!K9)*2/(J4+J5+J6+K4+K5+K6),"") -> 0.20981605

Sheet Profit & Loss
A1: ='Data Sheet'!B1 -> DABUR INDIA LTD
A3: Narration | B3: ='Data Sheet'!B13 -> 42825 | C3: ='Data Sheet'!C13 -> 43190 | D3: ='Data Sheet'!D13 -> 43555 | E3: ='Data Sheet'!E13 -> 43921 | F3: ='Data Sheet'!F13 -> 44286 | G3: ='Data Sheet'!G13 -> 44651 | H3: ='Data Sheet'!H13 -> 45016 | I3: ='Data Sheet'!I13 -> 45382 | ... K3: ='Data Sheet'!K13 -> 46112 | L3: Trailing | M3: Best Case | N3: Worst Case
A4: Sales | B4: ='Data Sheet'!B14 -> 7613.59 | C4: ='Data Sheet'!C14 -> 7721.85 | D4: ='Data Sheet'!D14 -> 8514.99 | E4: ='Data Sheet'!E14 -> 8684.64 | F4: ='Data Sheet'!F14 -> 9561.65 | G4: ='Data Sheet'!G14 -> 10888.68 | H4: ='Data Sheet'!H14 -> 11529.89 | I4: ='Data Sheet'!I14 -> 12404.01 | ... K4: ='Data Sheet'!K14 -> 13192.57 | L4: =SUM(Quarters!H4:K4) -> 13192.57 | M4: =$K4+M23*K4 -> 13853.59 | N4: =$K4+N23*L4 -> 13798.466
A5: Expenses | B5: =SUM('Data Sheet'!B15,'Data Sheet'!B17:B21, -1*'Data Sheet'!B16) -> 6101.98 | C5: =SUM('Data Sheet'!C15,'Data Sheet'!C17:C21, -1*'Data Sheet'!C16) -> 6104.41 | D5: =SUM('Data Sheet'!D15,'Data Sheet'!D17:D21, -1*'Data Sheet'!D16) -> 6775.43 | E5: =SUM('Data Sheet'!E15,'Data Sheet'!E17:E21, -1*'Data Sheet'!E16) -> 6892.3 | F5: =SUM('Data Sheet'!F15,'Data Sheet'!F17:F21, -1*'Data Sheet'!F16) -> 7559.98 | G5: =SUM('Data Sheet'!G15,'Data Sheet'!G17:G21, -1*'Data Sheet'!G16) -> 8636.67 | H5: =SUM('Data Sheet'!H15,'Data Sheet'!H17:H21, -1*'Data Sheet'!H16) -> 9367.4 | I5: =SUM('Data Sheet'!I15,'Data Sheet'!I17:I21, -1*'Data Sheet'!I16) -> 10004.29 | ... K5: =SUM('Data Sheet'!K15,'Data Sheet'!K17:K21, -1*'Data Sheet'!K16) -> 10742.53 | L5: =SUM(Quarters!H5:K5) -> 10742.53 | M5: =M4-M6 -> 11251.99 | N5: =N4-N6 -> 11235.903
A6: Operating Profit | B6: =B4-B5 -> 1511.61 | C6: =C4-C5 -> 1617.44 | D6: =D4-D5 -> 1739.56 | E6: =E4-E5 -> 1792.34 | F6: =F4-F5 -> 2001.67 | G6: =G4-G5 -> 2252.01 | H6: =H4-H5 -> 2162.49 | I6: =I4-I5 -> 2399.72 | ... K6: =K4-K5 -> 2450.04 | L6: =SUM(Quarters!H6:K6) -> 2450.04 | M6: =M4*M24 -> 2601.6004 | N6: =N4*N24 -> 2562.5632
A7: Other Income | B7: ='Data Sheet'!B22 -> 295.93 | C7: ='Data Sheet'!C22 -> 290.88 | D7: ='Data Sheet'!D22 -> 221.79 | E7: ='Data Sheet'!E22 -> 205.29 | F7: ='Data Sheet'!F22 -> 325.29 | G7: ='Data Sheet'!G22 -> 308.16 | H7: ='Data Sheet'!H22 -> 445.39 | I7: ='Data Sheet'!I22 -> 482.41 | ... K7: ='Data Sheet'!K22 -> 584.72 | L7: =SUM(Quarters!H7:K7) -> 584.72 | M7: 0 | N7: 0
A8: Depreciation | B8: ='Data Sheet'!B23 -> 142.86 | C8: ='Data Sheet'!C23 -> 162.18 | D8: ='Data Sheet'!D23 -> 176.9 | E8: ='Data Sheet'!E23 -> 220.45 | F8: ='Data Sheet'!F23 -> 240.13 | G8: ='Data Sheet'!G23 -> 252.89 | H8: ='Data Sheet'!H23 -> 310.96 | I8: ='Data Sheet'!I23 -> 399.21 | ... K8: ='Data Sheet'!K23 -> 468.93 | L8: =SUM(Quarters!H8:K8) -> 468.93 | M8: =+$L8 -> 468.93 | N8: =+$L8 -> 468.93
A9: Interest | B9: ='Data Sheet'!B24 -> 54.03 | C9: ='Data Sheet'!C24 -> 53.05 | D9: ='Data Sheet'!D24 -> 59.58 | E9: ='Data Sheet'!E24 -> 49.54 | F9: ='Data Sheet'!F24 -> 30.81 | G9: ='Data Sheet'!G24 -> 38.6 | H9: ='Data Sheet'!H24 -> 78.24 | I9: ='Data Sheet'!I24 -> 124.18 | ... K9: ='Data Sheet'!K24 -> 145.4 | L9: =SUM(Quarters!H9:K9) -> 145.4 | M9: =+$L9 -> 145.4 | N9: =+$L9 -> 145.4
A10: Profit before tax | B10: ='Data Sheet'!B25 -> 1610.65 | C10: ='Data Sheet'!C25 -> 1693.09 | D10: ='Data Sheet'!D25 -> 1724.87 | E10: ='Data Sheet'!E25 -> 1727.64 | F10: ='Data Sheet'!F25 -> 2056.02 | G10: ='Data Sheet'!G25 -> 2268.68 | H10: ='Data Sheet'!H25 -> 2218.68 | I10: ='Data Sheet'!I25 -> 2358.74 | ... K10: ='Data Sheet'!K25 -> 2420.43 | L10: =SUM(Quarters!H10:K10) -> 2420.43 | M10: =M6+M7-SUM(M8:M9) -> 1987.2704 | N10: =N6+N7-SUM(N8:N9) -> 1948.2332
A11: Tax | B11: ='Data Sheet'!B26 -> 330.34 | C11: ='Data Sheet'!C26 -> 335.35 | D11: ='Data Sheet'!D26 -> 278.62 | E11: ='Data Sheet'!E26 -> 279.72 | F11: ='Data Sheet'!F26 -> 361.07 | G11: ='Data Sheet'!G26 -> 526.38 | H11: ='Data Sheet'!H26 -> 517.35 | I11: ='Data Sheet'!I26 -> 547.43 | ... K11: ='Data Sheet'!K26 -> 551.74 | L11: =SUM(Quarters!H11:K11) -> 551.74 | M11: =IF($L10>0,$L11/$L10,0) -> 0.22795123 | N11: =IF($L10>0,$L11/$L10,0) -> 0.22795123
A12: Net profit | B12: ='Data Sheet'!B27 -> 1276.94 | C12: ='Data Sheet'!C27 -> 1354.39 | D12: ='Data Sheet'!D27 -> 1442.33 | E12: ='Data Sheet'!E27 -> 1444.96 | F12: ='Data Sheet'!F27 -> 1693.3 | G12: ='Data Sheet'!G27 -> 1739.22 | H12: ='Data Sheet'!H27 -> 1707.15 | I12: ='Data Sheet'!I27 -> 1842.68 | ... K12: ='Data Sheet'!K27 -> 1895.03 | L12: =SUM(Quarters!H12:K12) -> 1895.03 | M12: =M10-M11*M10 -> 1534.2697 | N12: =N10-N11*N10 -> 1504.1311
A13: EPS | B13: =IF('Data Sheet'!B90>0,B12/'Data Sheet'!B90,0) -> 7.2491626 | C13: =IF('Data Sheet'!C90>0,C12/'Data Sheet'!C90,0) -> 7.6888447 | D13: =IF('Data Sheet'!D90>0,D12/'Data Sheet'!D90,0) -> 8.1658269 | E13: =IF('Data Sheet'!E90>0,E12/'Data Sheet'!E90,0) -> 8.1770132 | F13: =IF('Data Sheet'!F90>0,F12/'Data Sheet'!F90,0) -> 9.5807401 | G13: =IF('Data Sheet'!G90>0,G12/'Data Sheet'!G90,0) -> 9.8377736 | H13: =IF('Data Sheet'!H90>0,H12/'Data Sheet'!H90,0) -> 9.6351168 | I13: =IF('Data Sheet'!I90>0,I12/'Data Sheet'!I90,0) -> 10.398871 | ... K13: =IF('Data Sheet'!K90>0,K12/'Data Sheet'!K90,0) -> 10.68405 | L13: =IF('Data Sheet'!$B6>0,'Profit & Loss'!L12/'Data Sheet'!$B6,0) -> 10.68411 | M13: =IF('Data Sheet'!$B6>0,'Profit & Loss'!M12/'Data Sheet'!$B6,0) -> 8.6501564 | N13: =IF('Data Sheet'!$B6>0,'Profit & Loss'!N12/'Data Sheet'!$B6,0) -> 8.4802359
A14: Price to earning | B14: =IF(B15>0,B15/B13,"") -> 38.259591 | C14: =IF(C15>0,C15/C13,"") -> 42.711228 | D14: =IF(D15>0,D15/D13,"") -> 50.062291 | E14: =IF(E15>0,E15/E13,"") -> 55.038434 | F14: =IF(F15>0,F15/F13,"") -> 56.415266 | G14: =IF(G15>0,G15/G13,"") -> 54.504202 | H14: =IF(H15>0,H15/H13,"") -> 56.553544 | I14: =IF(I15>0,I15/I13,"") -> 50.308344 | ... K14: =IF(K15>0,K15/K13,"") -> 38.417079 | L14: =IF(L13>0,L15/L13,0) -> 41.561722 | M14: =M25 -> 45.26774 | N14: =N25 -> 41.561722
A15: Price | B15: ='Data Sheet'!B87 -> 277.35 | C15: ='Data Sheet'!C87 -> 328.4 | D15: ='Data Sheet'!D87 -> 408.8 | E15: ='Data Sheet'!E87 -> 450.05 | F15: ='Data Sheet'!F87 -> 540.5 | G15: ='Data Sheet'!G87 -> 536.2 | H15: ='Data Sheet'!H87 -> 544.9 | I15: ='Data Sheet'!I87 -> 523.15 | ... K15: ='Data Sheet'!K87 -> 410.45 | L15: ='Data Sheet'!B8 -> 444.05 | M15: =M13*M14 -> 391.57303 | N15: =N13*N14 -> 352.45321
A17: RATIOS:
A18: Dividend Payout | B18: =IF('Data Sheet'!B27>0, 'Data Sheet'!B28/'Data Sheet'!B27, 0) -> 0.31038263 | C18: =IF('Data Sheet'!C27>0, 'Data Sheet'!C28/'Data Sheet'!C27, 0) -> 0.81286779 | D18: =IF('Data Sheet'!D27>0, 'Data Sheet'!D28/'Data Sheet'!D27, 0) -> 0.33676759 | E18: =IF('Data Sheet'!E27>0, 'Data Sheet'!E28/'Data Sheet'!E27, 0) -> 0.36688213 | F18: =IF('Data Sheet'!F27>0, 'Data Sheet'!F28/'Data Sheet'!F27, 0) -> 0.49578929 | G18: =IF('Data Sheet'!G27>0, 'Data Sheet'!G28/'Data Sheet'!G27, 0) -> 0.52857603 | H18: =IF('Data Sheet'!H27>0, 'Data Sheet'!H28/'Data Sheet'!H27, 0) -> 0.53969481 | I18: =IF('Data Sheet'!I27>0, 'Data Sheet'!I28/'Data Sheet'!I27, 0) -> 0.52890355 | ... K18: =IF('Data Sheet'!K27>0, 'Data Sheet'!K28/'Data Sheet'!K27, 0) -> 0.77217775
A19: OPM | B19: =IF(B6>0,B6/B4,0) -> 0.19854103 | C19: =IF(C6>0,C6/C4,0) -> 0.20946276 | D19: =IF(D6>0,D6/D4,0) -> 0.20429384 | E19: =IF(E6>0,E6/E4,0) -> 0.20638046 | F19: =IF(F6>0,F6/F4,0) -> 0.20934358 | G19: =IF(G6>0,G6/G4,0) -> 0.20682121 | H19: =IF(H6>0,H6/H4,0) -> 0.18755513 | I19: =IF(I6>0,I6/I4,0) -> 0.19346324 | ... L19: =IF(L6>0,L6/L4,0) -> 0.18571363
G22: TRENDS: | H22: 10 YEARS | I22: 7 YEARS | J22: 5 YEARS | K22: 3 YEARS | L22: RECENT | M22: BEST | N22: WORST
G23: Sales Growth | H23: =IF(B4=0,"",POWER($K4/B4,1/9)-1) -> 0.06298383 | I23: =IF(D4=0,"",POWER($K4/D4,1/7)-1) -> 0.064543982 | J23: =IF(F4=0,"",POWER($K4/F4,1/5)-1) -> 0.066496201 | K23: =IF(H4=0,"",POWER($K4/H4, 1/3)-1) -> 0.045927097 | L23: =IF(ISERROR(MAX(IF(J4=0,"",(K4-J4)/J4),IF(K4=0,"",(L4-K4)/K4))),"",MAX(IF(J4=0,"",(K4-J4)/J4),IF(K4=0,"",(L4-K4)/K4))) -> 0.050105507 | M23: =MAX(K23:L23) -> 0.050105507 | N23: =MIN(H23:L23) -> 0.045927097
G24: OPM | H24: =IF(SUM(B4:$K$4)=0,"",SUMPRODUCT(B19:$K$19,B4:$K$4)/SUM(B4:$K$4)) -> 0.19715829 | I24: =IF(SUM(E4:$K$4)=0,"",SUMPRODUCT(E19:$K$19,E4:$K$4)/SUM(E4:$K$4)) -> 0.19504855 | J24: =IF(SUM(G4:$K$4)=0,"",SUMPRODUCT(G19:$K$19,G4:$K$4)/SUM(G4:$K$4)) -> 0.19116765 | K24: =IF(SUM(I4:$K$4)=0, "", SUMPRODUCT(I19:$K$19,I4:$K$4)/SUM(I4:$K$4)) -> 0.1877925 | L24: =L19 -> 0.18571363 | M24: =MAX(K24:L24) -> 0.1877925 | N24: =MIN(H24:L24) -> 0.18571363
G25: Price to Earning | H25: =IF(ISERROR(AVERAGEIF(B14:$L14,">0")),"",AVERAGEIF(B14:$L14,">0")) -> 48.601411 | I25: =IF(ISERROR(AVERAGEIF(E14:$L14,">0")),"",AVERAGEIF(E14:$L14,">0")) -> 50.447801 | J25: =IF(ISERROR(AVERAGEIF(G14:$L14,">0")),"",AVERAGEIF(G14:$L14,">0")) -> 48.688118 | K25: =IF(ISERROR(AVERAGEIF(I14:$L14,">0")),"",AVERAGEIF(I14:$L14,">0")) -> 45.26774 | L25: =L14 -> 41.561722 | M25: =MAX(K25:L25) -> 45.26774 | N25: =MIN(H25:L25) -> 41.561722

Sheet Quarters
A1: ='Profit & Loss'!A1 -> DABUR INDIA LTD
A3: Narration | B3: ='Data Sheet'!B38 -> 45291 | C3: ='Data Sheet'!C38 -> 45382 | D3: ='Data Sheet'!D38 -> 45473 | E3: ='Data Sheet'!E38 -> 45565 | F3: ='Data Sheet'!F38 -> 45657 | G3: ='Data Sheet'!G38 -> 45747 | H3: ='Data Sheet'!H38 -> 45838 | I3: ='Data Sheet'!I38 -> 45930 | ... K3: ='Data Sheet'!K38 -> 46112
A4: Sales | B4: ='Data Sheet'!B39 -> 3255.06 | C4: ='Data Sheet'!C39 -> 2814.64 | D4: ='Data Sheet'!D39 -> 3349.11 | E4: ='Data Sheet'!E39 -> 3028.59 | F4: ='Data Sheet'!F39 -> 3355.25 | G4: ='Data Sheet'!G39 -> 2830.14 | H4: ='Data Sheet'!H39 -> 3404.58 | I4: ='Data Sheet'!I39 -> 3191.32 | ... K4: ='Data Sheet'!K39 -> 3038.02
A5: Expenses | B5: ='Data Sheet'!B40 -> 2587.64 | C5: ='Data Sheet'!C40 -> 2348.23 | D5: ='Data Sheet'!D40 -> 2694.28 | E5: ='Data Sheet'!E40 -> 2476.04 | F5: ='Data Sheet'!F40 -> 2673.36 | G5: ='Data Sheet'!G40 -> 2403.27 | H5: ='Data Sheet'!H40 -> 2737.16 | I5: ='Data Sheet'!I40 -> 2603.35 | ... K5: ='Data Sheet'!K40 -> 2577.2
A6: Operating Profit | B6: ='Data Sheet'!B47 -> 667.42 | C6: ='Data Sheet'!C47 -> 466.41 | D6: ='Data Sheet'!D47 -> 654.83 | E6: ='Data Sheet'!E47 -> 552.55 | F6: ='Data Sheet'!F47 -> 681.89 | G6: ='Data Sheet'!G47 -> 426.87 | H6: ='Data Sheet'!H47 -> 667.42 | I6: ='Data Sheet'!I47 -> 587.97 | ... K6: ='Data Sheet'!K47 -> 460.82
A7: Other Income | B7: ='Data Sheet'!B41 -> 127.37 | C7: ='Data Sheet'!C41 -> 128.85 | D7: ='Data Sheet'!D41 -> 129.4 | E7: ='Data Sheet'!E41 -> 151.76 | F7: ='Data Sheet'!F41 -> 128.53 | G7: ='Data Sheet'!G41 -> 141.16 | H7: ='Data Sheet'!H41 -> 143.97 | I7: ='Data Sheet'!I41 -> 140.13 | ... K7: ='Data Sheet'!K41 -> 175.03
A8: Depreciation | B8: ='Data Sheet'!B42 -> 96.89 | C8: ='Data Sheet'!C42 -> 107.36 | D8: ='Data Sheet'!D42 -> 109.12 | E8: ='Data Sheet'!E42 -> 110.97 | F8: ='Data Sheet'!F42 -> 108.64 | G8: ='Data Sheet'!G42 -> 116.87 | H8: ='Data Sheet'!H42 -> 114.14 | I8: ='Data Sheet'!I42 -> 115.4 | ... K8: ='Data Sheet'!K42 -> 122.2
A9: Interest | B9: ='Data Sheet'!B43 -> 36.49 | C9: ='Data Sheet'!C43 -> 35.24 | D9: ='Data Sheet'!D43 -> 32.66 | E9: ='Data Sheet'!E43 -> 47.39 | F9: ='Data Sheet'!F43 -> 44.2 | G9: ='Data Sheet'!G43 -> 39.25 | H9: ='Data Sheet'!H43 -> 34.63 | I9: ='Data Sheet'!I43 -> 39.68 | ... K9: ='Data Sheet'!K43 -> 39.97
A10: Profit before tax | B10: ='Data Sheet'!B44 -> 661.41 | C10: ='Data Sheet'!C44 -> 452.66 | D10: ='Data Sheet'!D44 -> 642.45 | E10: ='Data Sheet'!E44 -> 545.95 | F10: ='Data Sheet'!F44 -> 657.58 | G10: ='Data Sheet'!G44 -> 411.91 | H10: ='Data Sheet'!H44 -> 662.62 | I10: ='Data Sheet'!I44 -> 573.02 | ... K10: ='Data Sheet'!K44 -> 473.68
A11: Tax | B11: ='Data Sheet'!B45 -> 154.97 | C11: ='Data Sheet'!C45 -> 111.44 | D11: ='Data Sheet'!D45 -> 148.1 | E11: ='Data Sheet'!E45 -> 128.43 | F11: ='Data Sheet'!F45 -> 141.76 | G11: ='Data Sheet'!G45 -> 99.18 | H11: ='Data Sheet'!H45 -> 154.33 | I11: ='Data Sheet'!I45 -> 128.23 | ... K11: ='Data Sheet'!K45 -> 111.68
A12: Net profit | B12: ='Data Sheet'!B46 -> 514.22 | C12: ='Data Sheet'!C46 -> 349.53 | D12: ='Data Sheet'!D46 -> 500.12 | E12: ='Data Sheet'!E46 -> 425 | F12: ='Data Sheet'!F46 -> 522.38 | G12: ='Data Sheet'!G46 -> 320.13 | H12: ='Data Sheet'!H46 -> 513.91 | I12: ='Data Sheet'!I46 -> 452.55 | ... K12: ='Data Sheet'!K46 -> 368.6
A14: OPM | B14: =IF(B4>0,B6/B4,"") -> 0.20504077 | C14: =IF(C4>0,C6/C4,"") -> 0.16570858 | D14: =IF(D4>0,D6/D4,"") -> 0.19552359 | E14: =IF(E4>0,E6/E4,"") -> 0.18244464 | F14: =IF(F4>0,F6/F4,"") -> 0.20323076 | G14: =IF(G4>0,G6/G4,"") -> 0.15082999 | H14: =IF(H4>0,H6/H4,"") -> 0.19603593 | I14: =IF(I4>0,I6/I4,"") -> 0.18424038 | ... K14: =IF(K4>0,K6/K4,"") -> 0.15168432

Sheet Cash Flow
A1: ='Balance Sheet'!A1 -> DABUR INDIA LTD
A3: Narration | B3: ='Data Sheet'!B78 -> 42825 | C3: ='Data Sheet'!C78 -> 43190 | D3: ='Data Sheet'!D78 -> 43555 | E3: ='Data Sheet'!E78 -> 43921 | F3: ='Data Sheet'!F78 -> 44286 | G3: ='Data Sheet'!G78 -> 44651 | H3: ='Data Sheet'!H78 -> 45016 | I3: ='Data Sheet'!I78 -> 45382 | ... K3: ='Data Sheet'!K78 -> 46112
A4: Cash from Operating Activity | B4: ='Data Sheet'!B79 -> 1226.94 | C4: ='Data Sheet'!C79 -> 1091.5 | D4: ='Data Sheet'!D79 -> 1499.13 | E4: ='Data Sheet'!E79 -> 1613.62 | F4: ='Data Sheet'!F79 -> 2114.67 | G4: ='Data Sheet'!G79 -> 1802.33 | H4: ='Data Sheet'!H79 -> 1488.43 | I4: ='Data Sheet'!I79 -> 2013.47 | ... K4: ='Data Sheet'!K79 -> 2578.62
A5: Cash from Investing Activity | B5: ='Data Sheet'!B80 -> -807.07 | C5: ='Data Sheet'!C80 -> -540.93 | D5: ='Data Sheet'!D80 -> 337.58 | E5: ='Data Sheet'!E80 -> -516.63 | F5: ='Data Sheet'!F80 -> -1404.22 | G5: ='Data Sheet'!G80 -> -1273.45 | H5: ='Data Sheet'!H80 -> -582.79 | I5: ='Data Sheet'!I80 -> -971.04 | ... K5: ='Data Sheet'!K80 -> -1285.22
A6: Cash from Financing Activity | B6: ='Data Sheet'!B81 -> -338.97 | C6: ='Data Sheet'!C81 -> -577.11 | D6: ='Data Sheet'!D81 -> -1888.2 | E6: ='Data Sheet'!E81 -> -1042.97 | F6: ='Data Sheet'!F81 -> -613.41 | G6: ='Data Sheet'!G81 -> -490.49 | H6: ='Data Sheet'!H81 -> -1035.24 | I6: ='Data Sheet'!I81 -> -1161.18 | ... K6: ='Data Sheet'!K81 -> -1235.73
A7: Net Cash Flow | B7: ='Data Sheet'!B82 -> 80.9 | C7: ='Data Sheet'!C82 -> -26.54 | D7: ='Data Sheet'!D82 -> -51.49 | E7: ='Data Sheet'!E82 -> 54.02 | F7: ='Data Sheet'!F82 -> 97.04 | G7: ='Data Sheet'!G82 -> 38.39 | H7: ='Data Sheet'!H82 -> -129.6 | I7: ='Data Sheet'!I82 -> -118.75 | ... K7: ='Data Sheet'!K82 -> 57.67

Sheet Stock Analysis
R3: Recommendation
R4: Investor Type
R5: Existing Shareholder | S5: HOLD
R6: Long-Term Investor | S6: ACCUMULATE
R7: Value Investor | S7: WAIT FOR DIPS
R8: Short-Term Trader | S8: NEUTRAL
A20: Stock Analysis:
A21: Despite the recent underperformance across the FMCG sector, Dabur India continues to demonstrate resilient fundamentals supported by strong brands, healthy cash generation, and a debt-free balance sheet. The correction seen across peers such as Godrej Consumer, Colgate-Palmolive, and Gillette suggests that sector-wide valuation compression rather than company-specific weakness has driven stock performance. While near-term growth remains moderate, improving rural demand and Dabur's strong market position provide a foundation for long-term value creation. Therefore, I maintain a HOLD recommendation, with accumulation advised on meaningful price corrections.

Sheet Ratio Analysis
B1: Ratio Analysis
B3: Years | C3: 2022 | D3: 2023 | E3: 2024 | F3: 2025 | G3: 2026
B4: Growth Rates
B5: Sales Growth | D5: =IFERROR(HistoricalFS!D5/HistoricalFS!C5-1,0) -> 0.058887762 | E5: =IFERROR(HistoricalFS!E5/HistoricalFS!D5-1,0) -> 0.075813386 | F5: =IFERROR(HistoricalFS!F5/HistoricalFS!E5-1,0) -> 0.012824885 | G5: =IFERROR(HistoricalFS!G5/HistoricalFS!F5-1,0) -> 0.050105507
B6: EBITDA Growth | D6: =IFERROR(HistoricalFS!D17/HistoricalFS!C17-1,0) -> -0.11365111 | E6: =IFERROR(HistoricalFS!E17/HistoricalFS!D17-1,0) -> 0.26084476 | F6: =IFERROR(HistoricalFS!F17/HistoricalFS!E17-1,0) -> -0.11830463 | G6: =IFERROR(HistoricalFS!G17/HistoricalFS!F17-1,0) -> 0.037845005
B7: EBIT Growth | D7: =IFERROR(HistoricalFS!D23/HistoricalFS!C23-1,0) -> -0.15745048 | E7: =IFERROR(HistoricalFS!E23/HistoricalFS!D23-1,0) -> 0.25657056 | F7: =IFERROR(HistoricalFS!F23/HistoricalFS!E23-1,0) -> -0.16291859 | G7: =IFERROR(HistoricalFS!G23/HistoricalFS!F23-1,0) -> 0.034163754
B8: Net Profit Growth | D8: =IFERROR(HistoricalFS!D37/HistoricalFS!C37-1,0) -> -0.11908764 | E8: =IFERROR(HistoricalFS!E37/HistoricalFS!D37-1,0) -> 0.25626583 | F8: =IFERROR(HistoricalFS!F37/HistoricalFS!E37-1,0) -> -0.14822361 | G8: =IFERROR(HistoricalFS!G37/HistoricalFS!F37-1,0) -> 0.047908647
B9: Dividend Growth | D9: =IFERROR(HistoricalFS!D45/HistoricalFS!C45-1,0) -> 2.1659673e-06 | E9: =IFERROR(HistoricalFS!E45/HistoricalFS!D45-1,0) -> 0.057687716 | F9: =IFERROR(HistoricalFS!F45/HistoricalFS!E45-1,0) -> 0.45454545 | G9: =IFERROR(HistoricalFS!G45/HistoricalFS!F45-1,0) -> 0.031248238
B11: Margins
B12: Gross Margin | C12: =IFERROR(HistoricalFS!C12,0) -> 0.45535731 | D12: =IFERROR(HistoricalFS!D12,0) -> 0.41167522 | E12: =IFERROR(HistoricalFS!E12,0) -> 0.46179743 | F12: =IFERROR(HistoricalFS!F12,0) -> 0.44411447 | G12: =IFERROR(HistoricalFS!G12,0) -> 0.47028289
B13: EBITDA Margin | C13: =IFERROR(HistoricalFS!C18,0) -> 0.20525077 | D13: =IFERROR(HistoricalFS!D18,0) -> 0.1718065 | E13: =IFERROR(HistoricalFS!E18,0) -> 0.20135585 | F13: =IFERROR(HistoricalFS!F18,0) -> 0.17528649 | G13: =IFERROR(HistoricalFS!G18,0) -> 0.17323994
B14: EBIT Margin | C14: =IFERROR(HistoricalFS!C24,0) -> 0.18202574 | D14: =IFERROR(HistoricalFS!D24,0) -> 0.14483659 | E14: =IFERROR(HistoricalFS!E24,0) -> 0.1691719 | F14: =IFERROR(HistoricalFS!F24,0) -> 0.13981751 | G14: =IFERROR(HistoricalFS!G24,0) -> 0.13769493
B15: EBT Margin | C15: =IFERROR(HistoricalFS!C32,0) -> 0.20678172 | D15: =IFERROR(HistoricalFS!D32,0) -> 0.17667992 | E15: =IFERROR(HistoricalFS!E32,0) -> 0.19805208 | F15: =IFERROR(HistoricalFS!F32,0) -> 0.17063398 | G15: =IFERROR(HistoricalFS!G32,0) -> 0.17099549
B16: Net Profit Margin | C16: =IFERROR(HistoricalFS!C38,0) -> 0.15843977 | D16: =IFERROR(HistoricalFS!D38,0) -> 0.13180958 | E16: =IFERROR(HistoricalFS!E38,0) -> 0.15391877 | F16: =IFERROR(HistoricalFS!F38,0) -> 0.12944427 | G16: =IFERROR(HistoricalFS!G38,0) -> 0.12917347
B18: Expense Ratios
B19: Sales Expenses | C19: =IFERROR(HistoricalFS!C15,0) -> 0.25010653 | D19: =IFERROR(HistoricalFS!D15,0) -> 0.23986872 | E19: =IFERROR(HistoricalFS!E15,0) -> 0.26044158 | F19: =IFERROR(HistoricalFS!F15,0) -> 0.26882797 | G19: =IFERROR(HistoricalFS!G15,0) -> 0.29704296
B20: Depreciation | C20: =IFERROR(HistoricalFS!C21,0) -> 0.023225037 | D20: =IFERROR(HistoricalFS!D21,0) -> 0.026969902 | E20: =IFERROR(HistoricalFS!E21,0) -> 0.032183947 | F20: =IFERROR(HistoricalFS!F21,0) -> 0.035468981 | G20: =IFERROR(HistoricalFS!G21,0) -> 0.035545008
B21: Operating Income | C21: =IFERROR(HistoricalFS!C24,0) -> 0.18202574 | D21: =IFERROR(HistoricalFS!D24,0) -> 0.14483659 | E21: =IFERROR(HistoricalFS!E24,0) -> 0.1691719 | F21: =IFERROR(HistoricalFS!F24,0) -> 0.13981751 | G21: =IFERROR(HistoricalFS!G24,0) -> 0.13769493
B23: Returns
B24: Return on Capital Employed | C24: =IFERROR(HistoricalFS!C23/SUM(HistoricalFS!C51+HistoricalFS!C53+HistoricalFS!C52),0) -> 0.21059779 | D24: =IFERROR(HistoricalFS!D23/SUM(HistoricalFS!D51+HistoricalFS!D53+HistoricalFS!D52),0) -> 0.16457493 | E24: =IFERROR(HistoricalFS!E23/SUM(HistoricalFS!E51+HistoricalFS!E53+HistoricalFS!E52),0) -> 0.1868344 | F24: =IFERROR(HistoricalFS!F23/SUM(HistoricalFS!F51+HistoricalFS!F53+HistoricalFS!F52),0) -> 0.14947928 | G24: =IFERROR(HistoricalFS!G23/SUM(HistoricalFS!G51+HistoricalFS!G53+HistoricalFS!G52),0) -> 0.14295844
B25: Retained Earnings | C25: =HistoricalFS!C48 -> 0.46712845 | D25: =HistoricalFS!D48 -> 0.39375555 | E25: =HistoricalFS!E48 -> 0.48952708 | F25: =HistoricalFS!F48 -> 0.12813764 | G25: =HistoricalFS!G48 -> 0.14132138
B26: Return on Equity | C26: =IFERROR(HistoricalFS!C37/(HistoricalFS!C51+HistoricalFS!C52),0) -> 0.20583919 | D26: =IFERROR(HistoricalFS!D37/(HistoricalFS!D51+HistoricalFS!D52),0) -> 0.16936431 | E26: =IFERROR(HistoricalFS!E37/(HistoricalFS!E51+HistoricalFS!E52),0) -> 0.1935082 | F26: =IFERROR(HistoricalFS!F37/(HistoricalFS!F51+HistoricalFS!F52),0) -> 0.15056631 | G26: =IFERROR(HistoricalFS!G37/(HistoricalFS!G51+HistoricalFS!G52),0) -> 0.14922956
B27: Self Sustained Growth Rate | C27: =IFERROR(C25*C26,0) -> 0.096153341 | D27: =IFERROR(D25*D26,0) -> 0.066688138 | E27: =IFERROR(E25*E26,0) -> 0.094727507 | F27: =IFERROR(F25*F26,0) -> 0.019293212 | G27: =IFERROR(G25*G26,0) -> 0.021089328
B28: Interest Coverage Ratio | C28: =IFERROR(HistoricalFS!C23/HistoricalFS!C26,0) -> 51.347668 | D28: =IFERROR(HistoricalFS!D23/HistoricalFS!D26,0) -> 21.343942 | E28: =IFERROR(HistoricalFS!E23/HistoricalFS!E26,0) -> 16.898132 | F28: =IFERROR(HistoricalFS!F23/HistoricalFS!F26,0) -> 10.743364 | G28: =IFERROR(HistoricalFS!G23/HistoricalFS!G26,0) -> 12.493466
B30: Efficiency Ratios
B31: Debtor Turnover Ratio | C31: =IFERROR(HistoricalFS!C5/HistoricalFS!C63,0) -> 16.851629 | D31: =IFERROR(HistoricalFS!D5/HistoricalFS!D63,0) -> 13.584554 | E31: =IFERROR(HistoricalFS!E5/HistoricalFS!E63,0) -> 13.801863 | F31: =IFERROR(HistoricalFS!F5/HistoricalFS!F63,0) -> 14.139662 | G31: =IFERROR(HistoricalFS!G5/HistoricalFS!G63,0) -> 18.440573
B32: Creditor Turnover Ratio | C32: =IFERROR(HistoricalFS!C5/HistoricalFS!C54,0) -> 3.790716 | D32: =IFERROR(HistoricalFS!D5/HistoricalFS!D54,0) -> 3.2893391 | E32: =IFERROR(HistoricalFS!E5/HistoricalFS!E54,0) -> 3.19282 | F32: =IFERROR(HistoricalFS!F5/HistoricalFS!F54,0) -> 2.8050814 | G32: =IFERROR(HistoricalFS!G5/HistoricalFS!G54,0) -> 2.763959
B33: Inventory Turnover | C33: =IFERROR(HistoricalFS!C5/HistoricalFS!C64,0) -> 5.6967934 | D33: =IFERROR(HistoricalFS!D5/HistoricalFS!D64,0) -> 5.6960231 | E33: =IFERROR(HistoricalFS!E5/HistoricalFS!E64,0) -> 6.3709302 | F33: =IFERROR(HistoricalFS!F5/HistoricalFS!F64,0) -> 5.4619518 | G33: =IFERROR(HistoricalFS!G5/HistoricalFS!G64,0) -> 5.6824602
B34: Fixed Asset Turnover | C34: =IFERROR(HistoricalFS!C5/HistoricalFS!C57,0) -> 4.7180034 | D34: =IFERROR(HistoricalFS!D5/HistoricalFS!D57,0) -> 3.2218546 | E34: =IFERROR(HistoricalFS!E5/HistoricalFS!E57,0) -> 3.2513788 | F34: =IFERROR(HistoricalFS!F5/HistoricalFS!F57,0) -> 3.1488888 | G34: =IFERROR(HistoricalFS!G5/HistoricalFS!G57,0) -> 3.3492861
B35: Capital Turnover Ratio | C35: =IFERROR(HistoricalFS!C5/SUM(HistoricalFS!C51+HistoricalFS!C52),0) -> 1.2991636 | D35: =IFERROR(HistoricalFS!D5/SUM(HistoricalFS!D51+HistoricalFS!D52),0) -> 1.2849165 | E35: =IFERROR(HistoricalFS!E5/SUM(HistoricalFS!E51+HistoricalFS!E52),0) -> 1.2572099 | F35: =IFERROR(HistoricalFS!F5/SUM(HistoricalFS!F51+HistoricalFS!F52),0) -> 1.1631748 | G35: =IFERROR(HistoricalFS!G5/SUM(HistoricalFS!G51+HistoricalFS!G52),0) -> 1.1552648
B37: Working Capital Days
B38: Debtors Days | C38: =IFERROR(365/C31,0) -> 21.659627 | D38: =IFERROR(365/D31,0) -> 26.868752 | E38: =IFERROR(365/E31,0) -> 26.445706 | F38: =IFERROR(365/F31,0) -> 25.813912 | G38: =IFERROR(365/G31,0) -> 19.793312
B39: Payable Days | C39: =IFERROR(365/C32,0) -> 96.287879 | D39: =IFERROR(365/D32,0) -> 110.96454 | E39: =IFERROR(365/E32,0) -> 114.319 | F39: =IFERROR(365/F32,0) -> 130.121 | G39: =IFERROR(365/G32,0) -> 132.05695
B40: Inventory Days | C40: =IFERROR(365/C33,0) -> 64.071132 | D40: =IFERROR(365/D33,0) -> 64.079796 | E40: =IFERROR(365/E33,0) -> 57.291477 | F40: =IFERROR(365/F33,0) -> 66.825928 | G40: =IFERROR(365/G33,0) -> 64.232742
B41: Cash Conversion Cycle | C41: =SUM(C38+C40-C39) -> -10.55712 | D41: =SUM(D38+D40-D39) -> -20.015993 | E41: =SUM(E38+E40-E39) -> -30.58182 | F41: =SUM(F38+F40-F39) -> -37.481161 | G41: =SUM(G38+G40-G39) -> -48.030895
B43: Cash Flow Quality
B44: CFO / Sales | C44: =IFERROR(HistoricalFS!C74/HistoricalFS!C5,0) -> 0.16552328 | D44: =IFERROR(HistoricalFS!D74/HistoricalFS!D5,0) -> 0.12909317 | E44: =IFERROR(HistoricalFS!E74/HistoricalFS!E5,0) -> 0.16232412 | F44: =IFERROR(HistoricalFS!F74/HistoricalFS!F5,0) -> 0.15814183 | G44: =IFERROR(HistoricalFS!G74/HistoricalFS!G5,0) -> 0.19546002
B45: CFO / Total Assets | C45: =IFERROR(HistoricalFS!C74/HistoricalFS!C68,0) -> 0.14672342 | D45: =IFERROR(HistoricalFS!D74/HistoricalFS!D68,0) -> 0.10902428 | E45: =IFERROR(HistoricalFS!E74/HistoricalFS!E68,0) -> 0.13319807 | F45: =IFERROR(HistoricalFS!F74/HistoricalFS!F68,0) -> 0.12241409 | G45: =IFERROR(HistoricalFS!G74/HistoricalFS!G68,0) -> 0.14751907
B46: CFO / Total Debt | C46: =IFERROR(HistoricalFS!C74/HistoricalFS!C53,0) -> 1.7496651 | D46: =IFERROR(HistoricalFS!D74/HistoricalFS!D53,0) -> 1.2680548 | E46: =IFERROR(HistoricalFS!E74/HistoricalFS!E53,0) -> 1.4749723 | F46: =IFERROR(HistoricalFS!F74/HistoricalFS!F53,0) -> 2.0905016 | G46: =IFERROR(HistoricalFS!G74/HistoricalFS!G53,0) -> 2.0030917

Sheet Data Sheet
A1: COMPANY NAME | B1: DABUR INDIA LTD
A2: LATEST VERSION | B2: 2.1 | E2: PLEASE DO NOT MAKE ANY CHANGES TO THIS SHEET
A3: CURRENT VERSION | B3: 2.1
A5: META
A6: Number of shares | B6: =IF(B9>0, B9/B8, 0) -> 177.36901
A7: Face Value | B7: 1
A8: Current Price | B8: 444.05
A9: Market Capitalization | B9: 78760.71
A12: PROFIT & LOSS
A13: Report Date | B13: 42825 | C13: 43190 | D13: 43555 | E13: 43921 | F13: 44286 | G13: 44651 | H13: 45016 | I13: 45382 | J13: 45747 | K13: 46112
A14: Sales | B14: 7613.59 | C14: 7721.85 | D14: 8514.99 | E14: 8684.64 | F14: 9561.65 | G14: 10888.68 | H14: 11529.89 | I14: 12404.01 | J14: 12563.09 | K14: 13192.57
A15: Raw Material Cost | B15: 2659.55 | C15: 2775.35 | D15: 3067.95 | E15: 3138.49 | F15: 3764.3 | G15: 4136.7 | H15: 4762.03 | I15: 4714.88 | J15: 4843.98 | K15: 6906.05
A16: Change in Inventory | B16: 23.02 | C16: 65.93 | D16: -12.64 | E16: 65.04 | F16: 207.2 | G16: 8.55 | H16: 90.79 | I16: -48.95 | J16: 57.1 | K16: 82.28
A17: Power and Fuel | B17: 87.48 | C17: 93.91 | D17: 105.26 | E17: 107.12 | F17: 104.01 | G17: 128.66 | H17: 150.59 | I17: 153.44 | J17: 155.95
A18: Other Mfr. Exp | B18: 1247.42 | C18: 1219 | D18: 1327.63 | E18: 1387.98 | F18: 1347.34 | G18: 1656.53 | H18: 1779.91 | I18: 1856.5 | J18: 1926.61
A19: Employee Cost | B19: 790.3 | C19: 793.36 | D19: 938.55 | E19: 949.16 | F19: 1034.9 | G19: 1081.39 | H19: 1138.43 | I19: 1241.06 | J19: 1292.36 | K19: 1375.64
A20: Selling and admin | B20: 1161.4 | C20: 1135.38 | D20: 1183.56 | E20: 1224.59 | F20: 1388.27 | G20: 1480.71 | H20: 1426.95 | I20: 1827.33 | J20: 1896.92 | K20: 888.06
A21: Other Expenses | B21: 178.85 | C21: 153.34 | D21: 139.84 | E21: 150 | F21: 128.36 | G21: 161.23 | H21: 200.28 | I21: 162.13 | J21: 188.03 | K21: 1655.06
A22: Other Income | B22: 295.93 | C22: 290.88 | D22: 221.79 | E22: 205.29 | F22: 325.29 | G22: 308.16 | H22: 445.39 | I22: 482.41 | J22: 550.65 | K22: 584.72
A23: Depreciation | B23: 142.86 | C23: 162.18 | D23: 176.9 | E23: 220.45 | F23: 240.13 | G23: 252.89 | H23: 310.96 | I23: 399.21 | J23: 445.6 | K23: 468.93
A24: Interest | B24: 54.03 | C24: 53.05 | D24: 59.58 | E24: 49.54 | F24: 30.81 | G24: 38.6 | H24: 78.24 | I24: 124.18 | J24: 163.5 | K24: 145.4
A25: Profit before tax | B25: 1610.65 | C25: 1693.09 | D25: 1724.87 | E25: 1727.64 | F25: 2056.02 | G25: 2268.68 | H25: 2218.68 | I25: 2358.74 | J25: 2257.89 | K25: 2420.43
A26: Tax | B26: 330.34 | C26: 335.35 | D26: 278.62 | E26: 279.72 | F26: 361.07 | G26: 526.38 | H26: 517.35 | I26: 547.43 | J26: 517.47 | K26: 551.74
A27: Net profit | B27: 1276.94 | C27: 1354.39 | D27: 1442.33 | E27: 1444.96 | F27: 1693.3 | G27: 1739.22 | H27: 1707.15 | I27: 1842.68 | J27: 1767.63 | K27: 1895.03
A28: Dividend Amount | B28: 396.34 | C28: 1100.94 | D28: 485.73 | E28: 530.13 | F28: 839.52 | G28: 919.31 | H28: 921.34 | I28: 974.6 | J28: 1417.84 | K28: 1463.3
A37: Quarters
A38: Report Date | B38: 45291 | C38: 45382 | D38: 45473 | E38: 45565 | F38: 45657 | G38: 45747 | H38: 45838 | I38: 45930 | J38: 46022 | K38: 46112
A39: Sales | B39: 3255.06 | C39: 2814.64 | D39: 3349.11 | E39: 3028.59 | F39: 3355.25 | G39: 2830.14 | H39: 3404.58 | I39: 3191.32 | J39: 3558.65 | K39: 3038.02
A40: Expenses | B40: 2587.64 | C40: 2348.23 | D40: 2694.28 | E40: 2476.04 | F40: 2673.36 | G40: 2403.27 | H40: 2737.16 | I40: 2603.35 | J40: 2824.82 | K40: 2577.2
A41: Other Income | B41: 127.37 | C41: 128.85 | D41: 129.4 | E41: 151.76 | F41: 128.53 | G41: 141.16 | H41: 143.97 | I41: 140.13 | J41: 125.59 | K41: 175.03
A42: Depreciation | B42: 96.89 | C42: 107.36 | D42: 109.12 | E42: 110.97 | F42: 108.64 | G42: 116.87 | H42: 114.14 | I42: 115.4 | J42: 117.19 | K42: 122.2
A43: Interest | B43: 36.49 | C43: 35.24 | D43: 32.66 | E43: 47.39 | F43: 44.2 | G43: 39.25 | H43: 34.63 | I43: 39.68 | J43: 31.12 | K43: 39.97
A44: Profit before tax | B44: 661.41 | C44: 452.66 | D44: 642.45 | E44: 545.95 | F44: 657.58 | G44: 411.91 | H44: 662.62 | I44: 573.02 | J44: 711.11 | K44: 473.68
A45: Tax | B45: 154.97 | C45: 111.44 | D45: 148.1 | E45: 128.43 | F45: 141.76 | G45: 99.18 | H45: 154.33 | I45: 128.23 | J45: 157.5 | K45: 111.68
A46: Net profit | B46: 514.22 | C46: 349.53 | D46: 500.12 | E46: 425 | F46: 522.38 | G46: 320.13 | H46: 513.91 | I46: 452.55 | J46: 559.97 | K46: 368.6 | M46: Year | N46: Interest Expense | O46: Opening Debt | P46: Closing Debt | Q46: Average Debt | R46: Cost of Debt
A47: Operating Profit | B47: 667.42 | C47: 466.41 | D47: 654.83 | E47: 552.55 | F47: 681.89 | G47: 426.87 | H47: 667.42 | I47: 587.97 | J47: 733.83 | K47: 460.82 | M47: 2022 | N47: 38.6 | O47: 0 | P47: 1030.1 | Q47: 1030.1 | R47: 0.0375
M48: 2023 | N48: 78.2 | O48: 1030.1 | P48: 1173.8 | Q48: 1101.95 | R48: 0.071
M49: 2024 | N49: 124.2 | O49: 1173.8 | P49: 1365.1 | Q49: 1269.45 | R49: 0.0978
M50: 2025 | N50: 163.5 | O50: 1365.1 | P50: 950.4 | Q50: 1157.75 | R50: 0.1412
M51: 2026 | N51: 145.4 | O51: 950.4 | P51: 1287.3 | Q51: 1118.85 | R51: 0.1299
A52: BALANCE SHEET
A53: Report Date | B53: 42825 | C53: 43190 | D53: 43555 | E53: 43921 | F53: 44286 | G53: 44651 | H53: 45016 | I53: 45382 | J53: 45747 | K53: 46112
A54: Equity Share Capital | B54: 176.15 | C54: 176.15 | D54: 176.63 | E54: 176.71 | F54: 176.74 | G54: 176.79 | H54: 177.18 | I54: 177.2 | J54: 177.23 | K54: 177.37 | M54: Extra Info :
A55: Reserves | B55: 4671.24 | C55: 5530.37 | D55: 5455.05 | E55: 6429.04 | F55: 7486.79 | G55: 8204.51 | H55: 8796.08 | I55: 9689.1 | J55: 10623.46 | K55: 11242.15 | M55: 2021 | N55: =R47 -> 0.0375
A56: Borrowings | B56: 975 | C56: 937.59 | D56: 699.37 | E56: 521.99 | F56: 509.06 | G56: 1030.1 | H56: 1173.79 | I56: 1365.09 | J56: 950.37 | K56: 1287.32 | M56: 2023 | N56: =R48 -> 0.071
A57: Other Liabilities | B57: 1909.85 | C57: 2057.52 | D57: 2105.59 | E57: 2208.84 | F57: 2660.63 | G57: 2872.46 | H57: 3505.23 | I57: 3884.97 | J57: 4478.69 | K57: 4773.07 | M57: 2024 | N57: =R49 -> 0.0978
A58: Total | B58: 7732.24 | C58: 8701.63 | D58: 8436.64 | E58: 9336.58 | F58: 10833.22 | G58: 12283.86 | H58: 13652.28 | I58: 15116.36 | J58: 16229.75 | K58: 17479.91 | M58: 2025 | N58: =R50 -> 0.1412
A59: Net Block | B59: 1958.4 | C59: 2028.11 | D59: 1969.06 | E59: 2252.68 | F59: 2242.92 | G59: 2307.9 | H59: 3578.65 | I59: 3815 | J59: 3989.69 | K59: 3938.92 | M59: 2026 | N59: =R51 -> 0.1299
A60: Capital Work in Progress | B60: 42.1 | C60: 41.51 | D60: 63.76 | E60: 146.57 | F60: 147.3 | G60: 167.5 | H60: 175.13 | I60: 232.23 | J60: 168.99 | K60: 137.48 | M60: Average | N60: =AVERAGE(N55:N59) -> 0.09548
A61: Investments | B61: 3240.16 | C61: 3805.17 | D61: 3358.76 | E61: 2800.26 | F61: 4159.63 | G61: 6219.62 | H61: 6265.26 | I61: 6932.69 | J61: 7467.86 | K61: 8947.26 | M61: Median | N61: =MEDIAN(N55:N59) -> 0.0978
A62: Other Assets | B62: 2491.58 | C62: 2826.84 | D62: 3045.06 | E62: 4137.07 | F62: 4283.37 | G62: 3588.84 | H62: 3633.24 | I62: 4136.44 | J62: 4603.21 | K62: 4456.25
A63: Total | B63: 7732.24 | C63: 8701.63 | D63: 8436.64 | E63: 9336.58 | F63: 10833.22 | G63: 12283.86 | H63: 13652.28 | I63: 15116.36 | J63: 16229.75 | K63: 17479.91
A64: Receivables | B64: 650.42 | C64: 706.08 | D64: 833.56 | E64: 813.89 | F64: 561.58 | G64: 646.15 | H64: 848.75 | I64: 898.72 | J64: 888.5 | K64: 715.41
A65: Inventory | B65: 1106.71 | C65: 1256.18 | D65: 1300.53 | E65: 1379.57 | F65: 1734.28 | G65: 1911.37 | H65: 2024.2 | I65: 1946.97 | J65: 2300.11 | K65: 2321.63
A66: Cash & Bank | B66: 304.81 | C66: 306.06 | D66: 328.16 | E66: 811.37 | F66: 1329.03 | G66: 570.14 | H66: 325.92 | I66: 666.36 | J66: 578.01 | K66: 562.07
A67: No. of Equity Shares | B67: 1761520510 | C67: 1761520510 | D67: 1766291141 | E67: 1767063892 | F67: 1767425349 | G67: 1767856483 | H67: 1767856483 | I67: 1772039162 | J67: 1772318252
A68: New Bonus Shares
A69: Face value | B69: 1 | C69: 1 | D69: 1 | E69: 1 | F69: 1 | G69: 1 | H69: 1 | I69: 1 | J69: 1 | K69: 1
A77: CASH FLOW:
A78: Report Date | B78: 42825 | C78: 43190 | D78: 43555 | E78: 43921 | F78: 44286 | G78: 44651 | H78: 45016 | I78: 45382 | J78: 45747 | K78: 46112
A79: Cash from Operating Activity | B79: 1226.94 | C79: 1091.5 | D79: 1499.13 | E79: 1613.62 | F79: 2114.67 | G79: 1802.33 | H79: 1488.43 | I79: 2013.47 | J79: 1986.75 | K79: 2578.62
A80: Cash from Investing Activity | B80: -807.07 | C80: -540.93 | D80: 337.58 | E80: -516.63 | F80: -1404.22 | G80: -1273.45 | H80: -582.79 | I80: -971.04 | J80: -448.26 | K80: -1285.22
A81: Cash from Financing Activity | B81: -338.97 | C81: -577.11 | D81: -1888.2 | E81: -1042.97 | F81: -613.41 | G81: -490.49 | H81: -1035.24 | I81: -1161.18 | J81: -1405.34 | K81: -1235.73
A82: Net Cash Flow | B82: 80.9 | C82: -26.54 | D82: -51.49 | E82: 54.02 | F82: 97.04 | G82: 38.39 | H82: -129.6 | I82: -118.75 | J82: 133.15 | K82: 57.67
A87: PRICE: | B87: 277.35 | C87: 328.4 | D87: 408.8 | E87: 450.05 | F87: 540.5 | G87: 536.2 | H87: 544.9 | I87: 523.15 | J87: 506.5 | K87: 410.45
A89: DERIVED:
A90: Adjusted Equity Shares in Cr | B90: 176.15 | C90: 176.15 | D90: 176.63 | E90: 176.71 | F90: 176.74 | G90: 176.79 | H90: 177.18 | I90: 177.2 | J90: 177.23 | K90: 177.37

Sheet Peer Comps
A1: RELATIVE VALUATION
A4: S.No. | B4: Company | C4: CMP | D4: Mkt Cap | E4: Revenue | F4: EBITDA | G4: PAT | H4: EPS | I4: P/E | J4: EV/EBITDA | K4: EV/Sales | L4: P/BV | M4: EBITDA Margin % | N4: Rev Growth | O4: ROE FY26 %
A5: 1 | B5: Godrej Consumer | C5: 1028 | D5: 105138 | E5: 14763 | F5: 3100 | G5: 2047 | H5: 20.12 | I5: 51.1 | J5: 34.8 | K5: 7.27 | L5: 10.2 | M5: 0.21 | N5: 0.082 | O5: 0.224
A6: 2 | B6: Colgate-Palmolive | C6: 2157 | D6: 58665 | E6: 5827 | F6: 1688 | G6: 1241 | H6: 45.65 | I6: 47.3 | J6: 34.9 | K6: 10.15 | L6: 25.6 | M6: 0.29 | N6: 0.091 | O6: 0.741
A7: 3 | B7: P&G Hygiene | C7: 9585 | D7: 31114 | E7: 4219 | F7: 935 | G7: 752 | H7: 231.85 | I7: 41.3 | J7: 33.5 | K7: 7.53 | L7: 9.1 | M7: 0.212 | N7: 0.087 | O7: 0.263
A8: 4 | B8: Gillette India | C8: 7784 | D8: 25366 | E8: 3106 | F8: 743 | G8: 583 | H8: 179 | I8: 43.5 | J8: 34.3 | K8: 8.32 | L8: 9.7 | M8: 0.239 | N8: 0.095 | O8: 0.304
A9: 5 | B9: Dabur India | C9: 451.05 | D9: 80002 | E9: 13193 | F9: 2285 | G9: 1704 | H9: 9.61 | I9: 46.9 | J9: 35.3 | K9: 6.09 | L9: 7.15 | M9: 0.173 | N9: 0.047 | O9: 0.166
B11: Mean | C11: =AVERAGE(C5:C9) -> 4201.01 | D11: =AVERAGE(D5:D9) -> 60057 | E11: =AVERAGE(E5:E9) -> 8221.6 | F11: =AVERAGE(F5:F9) -> 1750.2 | G11: =AVERAGE(G5:G9) -> 1265.4 | H11: =MEDIAN(H5:H9) -> 45.65 | I11: =AVERAGE(I5:I9) -> 46.02 | J11: =AVERAGE(J5:J9) -> 34.56 | K11: =AVERAGE(K5:K9) -> 7.872 | L11: =AVERAGE(L5:L9) -> 12.35 | M11: =AVERAGE(M5:M9) -> 0.2248 | N11: =AVERAGE(N5:N9) -> 0.0804 | O11: =AVERAGE(O5:O9) -> 0.3396
B12: Median | C12: =MEDIAN(C5:C9) -> 2157 | D12: =MEDIAN(D5:D9) -> 58665 | E12: =MEDIAN(E5:E9) -> 5827 | F12: =MEDIAN(F5:F9) -> 1688 | G12: =MEDIAN(G5:G9) -> 1241 | H12: =MEDIAN(H5:H9) -> 45.65 | I12: =MEDIAN(I5:I9) -> 46.9 | J12: =MEDIAN(J5:J9) -> 34.8 | ... O12: =MEDIAN(O5:O9) -> 0.263
B13: Min | C13: =MIN(C5:C9) -> 451.05 | D13: =MIN(D5:D9) -> 25366 | E13: =MIN(E5:E9) -> 3106 | F13: =MIN(F5:F9) -> 743 | G13: =MIN(G5:G9) -> 583 | H13: =MIN(H5:H9) -> 9.61 | I13: =MIN(I5:I9) -> 41.3 | J13: =MIN(J5:J9) -> 33.5 | ... O13: =MIN(O5:O9) -> 0.166
B14: Max | C14: =MAX(C5:C9) -> 9585 | D14: =MAX(D5:D9) -> 105138 | E14: =MAX(E5:E9) -> 14763 | F14: =MAX(F5:F9) -> 3100 | G14: =MAX(G5:G9) -> 2047 | H14: =MAX(H5:H9) -> 231.85 | I14: =MAX(I5:I9) -> 51.1 | J14: =MAX(J5:J9) -> 35.3 | ... O14: =MAX(O5:O9) -> 0.741
A17: IMPLIED PRICE FOR DABUR INDIA
C18: Multiple Used | D18: Dabur Metric | E18: Implied Price (₹) | F18: Current CMP (₹) | G18: Premium/ (Discount) | H18: Weight | I18: Wtd Price
B19: P/E Multiple | C19: =I12 -> 46.9 | D19: 9.608 | E19: =I12*9.608 -> 450.6152 | F19: 451.05 | G19: =E19/F19-1 -> -0.00096397295 | H19: 0.35 | I19: =E19*H19 -> 157.71532
B20: EV/EBITDA Multiple | C20: =J12 -> 34.8 | D20: 2285.48 | E20: =(J12*2285.48+562.07-1287.32)/177.37 -> 444.32234 | F20: 451.05 | G20: =E20/F20-1 -> -0.014915546 | H20: 0.35 | I20: =E20*H20 -> 155.51282
B21: EV/Sales Multiple | C21: =K12 -> 7.53 | D21: 13192.57 | E21: =(K12*13192.57+562.07-1287.32)/177.37 -> 555.98355 | F21: 451.05 | G21: =E21/F21-1 -> 0.23264283 | H21: 0.15 | I21: =E21*H21 -> 83.397532
B22: P/Book Value | C22: =L12 -> 9.7 | D22: 64.382477 | E22: =L12*64.3825 -> 624.51025 | F22: 451.05 | G22: =E22/F22-1 -> 0.38456989 | H22: 0.15 | I22: =E22*H22 -> 93.676537
A24: Weighted Target Price | E24: =SUM(I19+I20+I21+I22) -> 490.30221 | F24: 451.05 | G24: =E24/F24-1 -> 0.087024077

Sheet Fixed Asset Schedule
B2: Fixed Asset Schedule
B3: Particulars | C3: 2022 | D3: 2023 | E3: 2024 | F3: 2025 | G3: 2026
B4: Opening Balance | D4: =C8 -> 2307.9 | E4: =D8 -> 3578.65 | F4: =E8 -> 3815 | G4: =F8 -> 3989.69
B5: Add: Gross Additions (Capex) | D5: =D8-C8+D7 -> 1581.71 | E5: =E8-D8+E7 -> 635.56 | F5: =F8-E8+F7 -> 620.29 | G5: =G8-F8+G7 -> 418.16
B6: Fixed Assets Before Depreciation | C6: =HistoricalFS!C57 -> 2307.9 | D6: =D4+D5 -> 3889.61 | E6: =E4+E5 -> 4214.21 | F6: =F4+F5 -> 4435.29 | G6: =G4+G5 -> 4407.85
B7: Less: Depreciation | C7: =HistoricalFS!C20 -> 252.89 | D7: =HistoricalFS!D20 -> 310.96 | E7: =HistoricalFS!E20 -> 399.21 | F7: =HistoricalFS!F20 -> 445.6 | G7: =HistoricalFS!G20 -> 468.93
B8: Closing Balance Net Block | C8: =HistoricalFS!C57 -> 2307.9 | D8: =HistoricalFS!D57 -> 3578.65 | E8: =HistoricalFS!E57 -> 3815 | F8: =HistoricalFS!F57 -> 3989.69 | G8: =HistoricalFS!G57 -> 3938.92
B10: Net Capital Expenditure | D10: =D5-D7 -> 1270.75 | E10: =E5-E7 -> 236.35 | F10: =F5-F7 -> 174.69 | G10: =G5-G7 -> -50.77
B11: Net Capex / Sales % | D11: =D10/HistoricalFS!D5 -> 0.11021354 | E11: =E10/HistoricalFS!E5 -> 0.019054322 | F11: =F10/HistoricalFS!F5 -> 0.013905019 | G11: =G10/HistoricalFS!G5 -> -0.0038483783
B13: Median Net Capex / Sales % | C13: =MEDIAN(D11:G11) -> 0.01647967
B14: Average Net Capex / Sales % | C14: =AVERAGE(D11:G11) -> 0.034831126

Sheet Changes in Working Capital
B2: Changes in Working Capital
B3: Particulars | C3: FY 2022 | D3: FY 2023 | E3: FY 2024 | F3: FY 2025 | G3: FY 2026
B4: Inventories | C4: =HistoricalFS!C64 -> 1911.37 | D4: =HistoricalFS!D64 -> 2024.2 | E4: =HistoricalFS!E64 -> 1946.97 | F4: =HistoricalFS!F64 -> 2300.11 | G4: =HistoricalFS!G64 -> 2321.63
B5: Receivables | C5: =HistoricalFS!C63 -> 646.15 | D5: =HistoricalFS!D63 -> 848.75 | E5: =HistoricalFS!E63 -> 898.72 | F5: =HistoricalFS!F63 -> 888.5 | G5: =HistoricalFS!G63 -> 715.41
B6: Payables | C6: ='Balance Sheet'!U12 -> 2018 | D6: ='Balance Sheet'!V12 -> 2187 | E6: ='Balance Sheet'!W12 -> 2422 | F6: ='Balance Sheet'!X12 -> 2825 | G6: ='Balance Sheet'!Y12 -> 2954
B7: Non-Cash Working Capital | C7: =C4+C5-C6 -> 539.52 | D7: =D4+D5-D6 -> 685.95 | E7: =E4+E5-E6 -> 423.69 | F7: =F4+F5-F6 -> 363.61 | G7: =G4+G5-G6 -> 83.04
B9: Change in Working Capital | D9: =D7-C7 -> 146.43 | E9: =E7-D7 -> -262.26 | F9: =F7-E7 -> -60.08 | G9: =G7-F7 -> -280.57
B10: Change in WC / % of Sales | D10: =D9/HistoricalFS!D5 -> 0.012700034 | E10: =E9/HistoricalFS!E5 -> -0.021143163 | F10: =F9/HistoricalFS!F5 -> -0.004782263 | G10: =G9/HistoricalFS!G5 -> -0.021267274
B12: Median Change in WC / % of Sales | C12: =MEDIAN(D10:G10) -> -0.012962713
B13: Average Change in WC / % of Sales | C13: =AVERAGE(D10:G10) -> -0.0086231663

Sheet Beta Calculation
B1: Beta Calculation
B3: Date | C3: Nifty 50 | D3: DABUR.NS
B4: 44565 | C4: 1.02 | D4: -1.22
B5: 44566 | C5: 0.67 | D5: 1.47
B6: 44567 | C6: -1 | D6: 0.01 | F6: Beta | G6: =G26 -> 0.60376438
B7: 44568 | C7: 0.38 | D7: 0.85
B8: 44571 | C8: 1.07 | D8: 0.27
B9: 44572 | C9: 0.29 | D9: -0.26 | F9: SUMMARY OUTPUT
B10: 44573 | C10: 0.87 | D10: -0.86
B11: 44574 | C11: 0.25 | D11: -0.31 | F11: Regression Statistics
B12: 44575 | C12: -0.01 | D12: -0.84 | F12: Multiple R | G12: 0.3859228
B13: 44578 | C13: 0.29 | D13: -1.08 | F13: R Square | G13: 0.1489364
B14: 44579 | C14: -1.07 | D14: -1 | F14: Adjusted R Square | G14: 0.14814692
B15: 44580 | C15: -0.96 | D15: 0.82 | F15: Standard Error | G15: 1.2684881
B16: 44581 | C16: -1.01 | D16: -1.53 | F16: Observations | G16: 1080
B17: 44582 | C17: -0.79 | D17: -1.48
B18: 44585 | C18: -2.66 | D18: -0.99 | F18: ANOVA
B19: 44586 | C19: 0.75 | D19: -0.6 | G19: df | H19: SS | I19: MS | J19: F | K19: Significance F
B20: 44588 | C20: -0.97 | D20: -2.53 | F20: Regression | G20: 1 | H20: 303.5501 | I20: 303.5501 | J20: 188.65035 | K20: 1.1124659e-39
B21: 44589 | C21: -0.05 | D21: 0.93 | F21: Residual | G21: 1078 | H21: 1734.5688 | I21: 1.609062
B22: 44592 | C22: 1.39 | D22: 0.52 | F22: Total | G22: 1079 | H22: 2038.1189
B23: 44593 | C23: 1.37 | D23: 1.81
B24: 44594 | C24: 1.16 | D24: 2.01 | G24: Coefficients | H24: Standard Error | I24: t Stat | J24: P-value | K24: Lower 95% | L24: Upper 95% | M24: Lower 95.0% | N24: Upper 95.0%
B25: 44595 | C25: -1.24 | D25: -0.18 | F25: Intercept | G25: -0.030587584 | H25: 0.038623896 | I25: -0.7919342 | J25: 0.42857327 | K25: -0.10637412 | L25: 0.045198951 | M25: -0.10637412 | N25: 0.045198951
B26: 44596 | C26: -0.25 | D26: 2.26 | F26: X Variable 1 | G26: 0.60376438 | H26: 0.043958076 | I26: 13.735005 | J26: 1.1124659e-39 | K26: 0.51751129 | L26: 0.69001746 | M26: 0.51751129 | N26: 0.69001746
B27: 44599 | C27: -1.73 | D27: -0.4
B28: 44600 | C28: 0.31 | D28: -0.79
B29: 44601 | C29: 1.14 | D29: 1.47
B30: 44602 | C30: 0.81 | D30: -1.03
B31: 44603 | C31: -1.31 | D31: -0.66
B32: 44606 | C32: -3.06 | D32: -1.38
B33: 44607 | C33: 3.03 | D33: 1.69
B34: 44608 | C34: -0.17 | D34: -0.11
B35: 44609 | C35: -0.1 | D35: -1.33
B36: 44610 | C36: -0.16 | D36: -1.19
B37: 44613 | C37: -0.4 | D37: 1.06
B38: 44614 | C38: -0.67 | D38: -0.64
... B1083: 46164 | C1083: 0.27 | D1083: 0.94
H1087: 46037

Sheet Rm
B1: Total Market Return
B3: Year | C3: Annual
B4: 2000 | C4: -0.1465 | E4: Average return | F4: =AVERAGE(C4:C29) -> 0.15121154 | G4: Market Return
B5: 2001 | C5: -0.1618 | E5: Dividend yield | F5: 0.013 | G5: Dividend Yield
B6: 2002 | C6: 0.0325 | E6: Total market return | F6: =SUM(F4:F5) -> 0.16421154
B7: 2003 | C7: 0.719
B8: 2004 | C8: 0.1068
B9: 2005 | C9: 0.3634
B10: 2006 | C10: 0.3983
B11: 2007 | C11: 0.5477
B12: 2008 | C12: -0.5179
B13: 2009 | C13: 0.7576
B14: 2010 | C14: 0.1795
B15: 2011 | C15: -0.2462
B16: 2012 | C16: 0.277
B17: 2013 | C17: 0.0676
B18: 2014 | C18: 0.3139
... B29: 2025 | C29: 0.1051

Sheet WACC
B1: Weighted average cost of capital
B3: All Figures are in INR unless stated otherwise
B5: Peer Comp | N5: S.No. | O5: Name | P5: CMP Rs. | Q5: Mar Cap Rs.Cr. | R5: Debt Rs.Cr. | S5: Debt / Eq | T5: Beta
N6: 1 | O6: Godrej Consumer | P6: 1027.5 | Q6: 105138.38 | R6: 4415.81 | S6: 0.35 | T6: 0.62872046
H7: Debt/ | I7: Debt/ | J7: Levered/ | K7: Unlevered/ | N7: 2 | O7: Dabur India | P7: 451.05 | Q7: 80002.3 | R7: 1287.32 | S7: 0.11 | T7: =J10 -> 0.60376438
B8: Name of the company | D8: Country | E8: Total Equity | F8: Total Debt | G8: Tax Rate 1 | H8: Equity | I8: Capital | J8: beta 2 | K8: beta 3 | N8: 3 | O8: Colgate-Palmoliv | P8: 2156.9 | Q8: 58664.58 | R8: 47.41 | S8: 0.03 | T8: 0.014084006
N9: 4 | O9: P & G Hygiene | P9: 9585 | Q9: 31113.62 | R9: 2.06 | S9: 0 | T9: 0.851
B10: Dabur India | D10: India | E10: =Q7 -> 80002.3 | F10: =R7 -> 1287.32 | G10: 0.25 | H10: =S7 -> 0.11 | I10: =F10/(F10+E10) -> 0.015836216 | J10: ='Beta Calculation'!G6 -> 0.60376438 | K10: =J10/(1+(1-G10)*H10) -> 0.55775 | N10: 5 | O10: Gillette India | P10: 7783.5 | Q10: 25366.43 | R10: 0.05 | S10: 0 | T10: 0.42959689
B11: Godrej Consumer | D11: India | E11: =Q6 -> 105138.38 | F11: =R6 -> 4415.81 | G11: 0.25 | H11: =S6 -> 0.35 | I11: =F11/(F11+E11) -> 0.040307085 | J11: =T6 -> 0.62872046 | K11: =J11/(1+(1-G11)*H11) -> 0.4979964
B12: Colgate-Palmoliv | D12: India | E12: =Q8 -> 58664.58 | F12: =R8 -> 47.41 | G12: 0.25 | H12: =S8 -> 0.03 | I12: =F12/(F12+E12) -> 0.00080750116 | J12: =T8 -> 0.014084006 | K12: =J12/(1+(1-G12)*H12) -> 0.013774089
B13: P & G Hygiene | D13: India | E13: =Q9 -> 31113.62 | F13: =R9 -> 2.06 | G13: 0.25 | H13: =S9 -> 0 | I13: =F13/(F13+E13) -> 6.6204563e-05 | J13: =T9 -> 0.851 | K13: =J13/(1+(1-G13)*H13) -> 0.851
B14: Gillette India | D14: India | E14: =Q10 -> 25366.43 | F14: =R10 -> 0.05 | G14: 0.25 | H14: =S10 -> 0 | I14: =F14/(F14+E14) -> 1.9711052e-06 | J14: =T10 -> 0.42959689 | K14: =J14/(1+(1-G14)*H14) -> 0.42959689
F16: Average | G16: =AVERAGE(G10:G14) -> 0.25 | H16: =AVERAGE(H10:H14) -> 0.098 | I16: =AVERAGE(I10:I14) -> 0.011403796 | J16: =AVERAGE(J10:J14) -> 0.50543315 | K16: =AVERAGE(K10:K14) -> 0.47002348
F17: Median | G17: =MEDIAN(G10:G14) -> 0.25 | H17: =MEDIAN(H10:H14) -> 0.03 | I17: =MEDIAN(I10:I14) -> 0.00080750116 | J17: =MEDIAN(J10:J14) -> 0.60376438 | K17: =MEDIAN(K10:K14) -> 0.4979964
B20: Cost of Debt | G20: Cost of Equity
B22: Pre-tax Cost of Debt | E22: ='Profit & Loss'!K9/'Balance Sheet'!K6 -> 0.11294783 | G22: Risk Free Rate | K22: 0.0709
B23: Tax Rate | E23: =G17 -> 0.25 | G23: Equity Risk Premium | K23: 0.07
B24: After Tax Cost of Debt | E24: =E22*(1-E23) -> 0.084710872 | G24: Levered Beta 4 | K24: =K33 -> 0.50230482
G25: Cost of Equity | K25: =K22+(K23*K24) -> 0.10606134
B28: Capital Structure | G28: Levered Beta
D30: Current | E30: Target | G30: Comps Median Unlevered Beta | K30: =K17 -> 0.4979964
B31: Total Debt | C31: =F10 -> 1287.32 | D31: =C31/C33 -> 0.015836216 | E31: =I16 -> 0.011403796 | G31: Target Debt/ Equity | K31: =E35 -> 0.011535342
B32: Market Captailizatation | C32: =E10 -> 80002.3 | D32: =C32/C33 -> 0.98416378 | E32: =E33-E31 -> 0.9885962 | G32: Tax Rate | K32: 0.25
B33: Total Capital | C33: =SUM(C31:C32) -> 81289.62 | D33: =SUM(D31:D32) -> 1 | E33: =D33 -> 1 | G33: Levered Beta | K33: =K30*(1+(1-K32)*K31) -> 0.50230482
B35: Debt/equity | D35: =D31/D32 -> 0.016091037 | E35: =E31/E32 -> 0.011535342
G36: Weighted Average Cost of Capital
G38: Cost of Equity | K38: =K25 -> 0.10606134
G39: Equity Weight | K39: =E32 -> 0.9885962
G41: Cost of Debt | K41: =E24 -> 0.084710872
G42: Debt Weight | K42: =E31 -> 0.011403796
G44: WACC | K44: =(K38*K39)+(K41*K42) -> 0.10581786

Sheet FCFF
B1: FCFF Analysis - DABUR INDIA LTD
B2: Free Cash Flow to Firm
B3: Particulars | C3: 2022 | D3: 2023 | E3: 2024 | F3: 2025 | G3: 2026
B4: EBIT (INR Cr.)
B5: EBIT | C5: =HistoricalFS!C23 -> 1982.02 | D5: =HistoricalFS!D23 -> 1669.95 | E5: =HistoricalFS!E23 -> 2098.41 | F5: =HistoricalFS!F23 -> 1756.54 | G5: =HistoricalFS!G23 -> 1816.55
B6: Less: Tax on EBIT (25%) | C6: =C5*25% -> 495.505 | D6: =D5*25% -> 417.4875 | E6: =E5*25% -> 524.6025 | F6: =F5*25% -> 439.135 | G6: =G5*25% -> 454.1375
B7: EBIT × (1 - Tax Rate) | C7: =C5-C6 -> 1486.515 | D7: =D5-D6 -> 1252.4625 | E7: =E5-E6 -> 1573.8075 | F7: =F5-F6 -> 1317.405 | G7: =G5-G6 -> 1362.4125
B9: Reinvestment
B10: Less: Net Capital Expenditure | D10: ='Fixed Asset Schedule'!D10 -> 1270.75 | E10: ='Fixed Asset Schedule'!E10 -> 236.35 | F10: ='Fixed Asset Schedule'!F10 -> 174.69 | G10: ='Fixed Asset Schedule'!G10 -> -50.77
B11: Less: Change in Working Capital | D11: ='Changes in Working Capital'!D9 -> 146.43 | E11: ='Changes in Working Capital'!E9 -> -262.26 | F11: ='Changes in Working Capital'!F9 -> -60.08 | G11: ='Changes in Working Capital'!G9 -> -280.57
B12: Total Reinvestment | D12: =D10+D11 -> 1417.18 | E12: =E10+E11 -> -25.91 | F12: =F10+F11 -> 114.61 | G12: =G10+G11 -> -331.34
B14: Free Cash Flow to Firm (FCFF)
B15: FCFF (INR Cr.) | D15: =D7-D12 -> -164.7175 | E15: =E7-E12 -> 1599.7175 | F15: =F7-F12 -> 1202.795 | G15: =G7-G12 -> 1693.7525
B17: Reinvestment Metrics
B18: Reinvestment Rate % | D18: =D12/D7 -> 1.1315149 | E18: =E12/E7 -> -0.016463259 | F18: =F12/F7 -> 0.086996785 | G18: =G12/G7 -> -0.24320094
B20: Summary Statistics
B21: Median Reinvestment Rate | C21: =MEDIAN(D18:G18) -> 0.035266763 | D21: Avg of NOPAT | E21: =AVERAGE(C7:G7) -> 1398.5205
B22: Average Reinvestment Rate | C22: =AVERAGE(C18:G18) -> 0.23971188 | D22: Avg of Reinvestment | E22: =AVERAGE(C12:G12) -> 293.635
D24: Reinvestment rate | E24: =E22/E21 -> 0.20996117

Sheet Assumptions
B1: ="Assumptions: "&'Data Sheet'!B1 -> Assumptions: DABUR INDIA LTD
B3: Margins | C3: 2022 | D3: 2023 | E3: 2024 | F3: 2025 | G3: 2026 | I3: Median Of Revenue Growth
B4: EBITDA | C4: =HistoricalFS!C18 -> 0.20525077 | D4: =HistoricalFS!D18 -> 0.1718065 | E4: =HistoricalFS!E18 -> 0.20135585 | F4: =HistoricalFS!F18 -> 0.17528649 | G4: =HistoricalFS!G18 -> 0.17323994 | I4: =MEDIAN(HistoricalFS!D6:G6) -> 0.054496635
B5: EBIT | C5: =HistoricalFS!C24 -> 0.18202574 | D5: =HistoricalFS!D24 -> 0.14483659 | E5: =HistoricalFS!E24 -> 0.1691719 | F5: =HistoricalFS!F24 -> 0.13981751 | G5: =HistoricalFS!G24 -> 0.13769493
B6: EBT | C6: =HistoricalFS!C32 -> 0.20678172 | D6: =HistoricalFS!D32 -> 0.17667992 | E6: =HistoricalFS!E32 -> 0.19805208 | F6: =HistoricalFS!F32 -> 0.17063398 | G6: =HistoricalFS!G32 -> 0.17099549
B7: Net Profit | C7: =HistoricalFS!C38 -> 0.15843977 | D7: =HistoricalFS!D38 -> 0.13180958 | E7: =HistoricalFS!E38 -> 0.15391877 | F7: =HistoricalFS!F38 -> 0.12944427 | G7: =HistoricalFS!G38 -> 0.12917347
B9: Historical Growth | C9: 2022 | D9: 2023 | E9: 2024 | F9: 2025 | G9: 2026
B10: Average Sales Growth | C10: =AVERAGE(HistoricalFS!D6:G6) -> 0.049407885
B11: CAGR % | C11: =(HistoricalFS!G5/HistoricalFS!C5)^(1/4)-1 -> 0.049152315 | D11: =_xlfn.RRI(4,HistoricalFS!C5,HistoricalFS!G5) -> 0.049152315 | E11: (RRI Formula)
B13: Tax Rate | C13: 2022 | D13: 2023 | E13: 2024 | F13: 2025 | G13: 2026
B14: Effective Tax Rate | C14: =HistoricalFS!C35 -> 0.2337825 | D14: =HistoricalFS!D35 -> 0.25396397 | E14: =HistoricalFS!E35 -> 0.22283688 | F14: =HistoricalFS!F35 -> 0.24139218 | G14: =HistoricalFS!G35 -> 0.2445797 | H14: =AVERAGE(C14:G14) -> 0.23931105
B15: Marginal Tax Rate | C15: 0.25
B17: Return On Capital Employed | C17: 2022 | D17: 2023 | E17: 2024 | F17: 2025 | G17: 2026
B18: EBIT*(1-T) | C18: =HistoricalFS!C23*(1-Assumptions!$C$15) -> 1486.515 | D18: =HistoricalFS!D23*(1-Assumptions!$C$15) -> 1252.4625 | E18: =HistoricalFS!E23*(1-Assumptions!$C$15) -> 1573.8075 | F18: =HistoricalFS!F23*(1-Assumptions!$C$15) -> 1317.405 | G18: =HistoricalFS!G23*(1-Assumptions!$C$15) -> 1362.4125
B19: Book Equity | C19: =HistoricalFS!C51+HistoricalFS!C52 -> 8381.3 | D19: =HistoricalFS!D51+HistoricalFS!D52 -> 8973.26 | E19: =HistoricalFS!E51+HistoricalFS!E52 -> 9866.3 | F19: =HistoricalFS!F51+HistoricalFS!F52 -> 10800.69 | G19: =HistoricalFS!G51+HistoricalFS!G52 -> 11419.52
B20: Book Debt | C20: =HistoricalFS!C53 -> 1030.1 | D20: =HistoricalFS!D53 -> 1173.79 | E20: =HistoricalFS!E53 -> 1365.09 | F20: =HistoricalFS!F53 -> 950.37 | G20: =HistoricalFS!G53 -> 1287.32
B21: Cash and Equivalents | C21: =HistoricalFS!C65 -> 570.14 | D21: =HistoricalFS!D65 -> 325.92 | E21: =HistoricalFS!E65 -> 666.36 | F21: =HistoricalFS!F65 -> 578.01 | G21: =HistoricalFS!G65 -> 562.07
B22: Capital Employed | C22: =C19+C20 -> 9411.4 | D22: =D19+D20 -> 10147.05 | E22: =E19+E20 -> 11231.39 | F22: =F19+F20 -> 11751.06 | G22: =G19+G20 -> 12706.84
B24: Pre/Post Tax Return on Capital Employed | C24: 2022 | D24: 2023 | E24: 2024 | F24: 2025 | G24: 2026
B25: Pre Tax ROCE | C25: =HistoricalFS!C23/Assumptions!C22 -> 0.21059779 | D25: =HistoricalFS!D23/Assumptions!D22 -> 0.16457493 | E25: =HistoricalFS!E23/Assumptions!E22 -> 0.1868344 | F25: =HistoricalFS!F23/Assumptions!F22 -> 0.14947928 | G25: =HistoricalFS!G23/Assumptions!G22 -> 0.14295844
B26: Post Tax ROCE | C26: =C18/C22 -> 0.15794834 | D26: =D18/D22 -> 0.12343119 | E26: =E18/E22 -> 0.1401258 | F26: =F18/F22 -> 0.11210946 | G26: =G18/G22 -> 0.10721883
B28: Growth in EBIT (Reinvestment-based) | C28: =AVERAGE(C26:G26)*FCFF!E24 -> 0.026910035

Sheet HistoricalFS
B1: ="Historical Financial Statement - "&'Data Sheet'!B1 -> Historical Financial Statement - DABUR INDIA LTD
B3: Years | C3: 2022 | D3: 2023 | E3: 2024 | F3: 2025 | G3: 2026
B4: Income statement
B5: Sales | C5: ='Data Sheet'!G14 -> 10888.68 | D5: ='Data Sheet'!H14 -> 11529.89 | E5: ='Data Sheet'!I14 -> 12404.01 | F5: ='Data Sheet'!J14 -> 12563.09 | G5: ='Data Sheet'!K14 -> 13192.57
B6: Sales Growth | D6: =D5/C5-1 -> 0.058887762 | E6: =E5/D5-1 -> 0.075813386 | F6: =F5/E5-1 -> 0.012824885 | G6: =G5/F5-1 -> 0.050105507 | H6: Average Growth | I6: =AVERAGE(D6:G6) -> 0.049407885
B8: COGS | C8: =SUM('Data Sheet'!G15:G18) -> 5930.44 | D8: =SUM('Data Sheet'!H15:H18) -> 6783.32 | E8: =SUM('Data Sheet'!I15:I18) -> 6675.87 | F8: =SUM('Data Sheet'!J15:J18) -> 6983.64 | G8: =SUM('Data Sheet'!K15:K18) -> 6988.33
B9: COGS % Sales | C9: =C8/C5 -> 0.54464269 | D9: =D8/D5 -> 0.58832478 | E9: =E8/E5 -> 0.53820257 | F9: =F8/F5 -> 0.55588553 | G9: =G8/G5 -> 0.52971711
B11: Gross Profit | C11: =C5-C8 -> 4958.24 | D11: =D5-D8 -> 4746.57 | E11: =E5-E8 -> 5728.14 | F11: =F5-F8 -> 5579.45 | G11: =G5-G8 -> 6204.24
B12: Gross Margins | C12: =C11/C5 -> 0.45535731 | D12: =D11/D5 -> 0.41167522 | E12: =E11/E5 -> 0.46179743 | F12: =F11/F5 -> 0.44411447 | G12: =G11/G5 -> 0.47028289
B14: Selling & General Expense | C14: =SUM('Data Sheet'!G19:G21) -> 2723.33 | D14: =SUM('Data Sheet'!H19:H21) -> 2765.66 | E14: =SUM('Data Sheet'!I19:I21) -> 3230.52 | F14: =SUM('Data Sheet'!J19:J21) -> 3377.31 | G14: =SUM('Data Sheet'!K19:K21) -> 3918.76
B15: S&G Exp % Sales | C15: =C14/C5 -> 0.25010653 | D15: =D14/D5 -> 0.23986872 | E15: =E14/E5 -> 0.26044158 | F15: =F14/F5 -> 0.26882797 | G15: =G14/G5 -> 0.29704296
B17: EBITDA | C17: =C11-C14 -> 2234.91 | D17: =D11-D14 -> 1980.91 | E17: =E11-E14 -> 2497.62 | F17: =F11-F14 -> 2202.14 | G17: =G11-G14 -> 2285.48
B18: EBITDA Margins | C18: =C17/C5 -> 0.20525077 | D18: =D17/D5 -> 0.1718065 | E18: =E17/E5 -> 0.20135585 | F18: =F17/F5 -> 0.17528649 | G18: =G17/G5 -> 0.17323994
B20: Depreciation | C20: =IFERROR('Data Sheet'!G23,0) -> 252.89 | D20: =IFERROR('Data Sheet'!H23,0) -> 310.96 | E20: =IFERROR('Data Sheet'!I23,0) -> 399.21 | F20: =IFERROR('Data Sheet'!J23,0) -> 445.6 | G20: =IFERROR('Data Sheet'!K23,0) -> 468.93
B21: Depreciation % of Sales | C21: =C20/C5 -> 0.023225037 | D21: =D20/D5 -> 0.026969902 | E21: =E20/E5 -> 0.032183947 | F21: =F20/F5 -> 0.035468981 | G21: =G20/G5 -> 0.035545008
B23: EBIT | C23: =IFERROR(C17-C20,0) -> 1982.02 | D23: =IFERROR(D17-D20,0) -> 1669.95 | E23: =IFERROR(E17-E20,0) -> 2098.41 | F23: =IFERROR(F17-F20,0) -> 1756.54 | G23: =IFERROR(G17-G20,0) -> 1816.55
B24: EBIT Margin | C24: =C23/C5 -> 0.18202574 | D24: =D23/D5 -> 0.14483659 | E24: =E23/E5 -> 0.1691719 | F24: =F23/F5 -> 0.13981751 | G24: =G23/G5 -> 0.13769493 | H24: =AVERAGE(C24:G24) -> 0.15470934
B26: Interest | C26: =IFERROR('Data Sheet'!G24,0) -> 38.6 | D26: =IFERROR('Data Sheet'!H24,0) -> 78.24 | E26: =IFERROR('Data Sheet'!I24,0) -> 124.18 | F26: =IFERROR('Data Sheet'!J24,0) -> 163.5 | G26: =IFERROR('Data Sheet'!K24,0) -> 145.4
B27: Interest % of Sales | C27: =C26/C5 -> 0.003544966 | D27: =D26/D5 -> 0.006785841 | E27: =E26/E5 -> 0.010011279 | F27: =F26/F5 -> 0.013014314 | G27: =G26/G5 -> 0.011021355
B29: Other Income | C29: =IFERROR('Data Sheet'!G22,0) -> 308.16 | D29: =IFERROR('Data Sheet'!H22,0) -> 445.39 | E29: =IFERROR('Data Sheet'!I22,0) -> 482.41 | F29: =IFERROR('Data Sheet'!J22,0) -> 550.65 | G29: =IFERROR('Data Sheet'!K22,0) -> 584.72
B31: Earnings Before Tax | C31: =IFERROR(C23-C26+C29,0) -> 2251.58 | D31: =IFERROR(D23-D26+D29,0) -> 2037.1 | E31: =IFERROR(E23-E26+E29,0) -> 2456.64 | F31: =IFERROR(F23-F26+F29,0) -> 2143.69 | G31: =IFERROR(G23-G26+G29,0) -> 2255.87
B32: EBT % Sales | C32: =C31/C5 -> 0.20678172 | D32: =D31/D5 -> 0.17667992 | E32: =E31/E5 -> 0.19805208 | F32: =F31/F5 -> 0.17063398 | G32: =G31/G5 -> 0.17099549
B34: Tax | C34: =IFERROR('Data Sheet'!G26,0) -> 526.38 | D34: =IFERROR('Data Sheet'!H26,0) -> 517.35 | E34: =IFERROR('Data Sheet'!I26,0) -> 547.43 | F34: =IFERROR('Data Sheet'!J26,0) -> 517.47 | G34: =IFERROR('Data Sheet'!K26,0) -> 551.74
B35: Effective Tax Rate | C35: =C34/C31 -> 0.2337825 | D35: =D34/D31 -> 0.25396397 | E35: =E34/E31 -> 0.22283688 | F35: =F34/F31 -> 0.24139218 | G35: =G34/G31 -> 0.2445797
B37: Net Profit | C37: =IFERROR(C31-C34,0) -> 1725.2 | D37: =IFERROR(D31-D34,0) -> 1519.75 | E37: =IFERROR(E31-E34,0) -> 1909.21 | F37: =IFERROR(F31-F34,0) -> 1626.22 | G37: =IFERROR(G31-G34,0) -> 1704.13
B38: Net Margins | C38: =C37/C5 -> 0.15843977 | D38: =D37/D5 -> 0.13180958 | E38: =E37/E5 -> 0.15391877 | F38: =F37/F5 -> 0.12944427 | G38: =G37/G5 -> 0.12917347
B40: No. of Equity Shares (Cr) | C40: =IFERROR('Data Sheet'!G90,0) -> 176.79 | D40: =IFERROR('Data Sheet'!H90,0) -> 177.18 | E40: =IFERROR('Data Sheet'!I90,0) -> 177.2 | F40: =IFERROR('Data Sheet'!J90,0) -> 177.23 | G40: =IFERROR('Data Sheet'!K90,0) -> 177.37
B42: Earnings Per Share | C42: =IFERROR(C37/C40,0) -> 9.7584705 | D42: =IFERROR(D37/D40,0) -> 8.5774354 | E42: =IFERROR(E37/E40,0) -> 10.774323 | F42: =IFERROR(F37/F40,0) -> 9.1757603 | G42: =IFERROR(G37/G40,0) -> 9.6077691
B43: EPS Growth % | C43: - | D43: =IFERROR(D42/C42-1,0) -> -0.12102666 | E43: =IFERROR(E42/D42-1,0) -> 0.25612404 | F43: =IFERROR(F42/E42-1,0) -> -0.14836779 | G43: =IFERROR(G42/F42-1,0) -> 0.047081522
B45: Dividend per Share | C45: =IFERROR('Data Sheet'!G28/HistoricalFS!C40,0) -> 5.2000113 | D45: =IFERROR('Data Sheet'!H28/HistoricalFS!D40,0) -> 5.2000226 | E45: =IFERROR('Data Sheet'!I28/HistoricalFS!E40,0) -> 5.5 | F45: =IFERROR('Data Sheet'!J28/HistoricalFS!F40,0) -> 8 | G45: =IFERROR('Data Sheet'!K28/HistoricalFS!G40,0) -> 8.2499859
B46: Dividend Payout Ratio | C46: =IFERROR(C45/C42,0) -> 0.53287155 | D46: =IFERROR(D45/D42,0) -> 0.60624445 | E46: =IFERROR(E45/E42,0) -> 0.51047292 | F46: =IFERROR(F45/F42,0) -> 0.87186236 | G46: =IFERROR(G45/G42,0) -> 0.85867862
B48: Retained Earnings | C48: =IFERROR(IF(C42>C45,1-C46,0),0) -> 0.46712845 | D48: =IFERROR(IF(D42>D45,1-D46,0),0) -> 0.39375555 | E48: =IFERROR(IF(E42>E45,1-E46,0),0) -> 0.48952708 | F48: =IFERROR(IF(F42>F45,1-F46,0),0) -> 0.12813764 | G48: =IFERROR(IF(G42>G45,1-G46,0),0) -> 0.14132138
B50: Balance Statement | C50: =C3 -> 2022 | D50: =D3 -> 2023 | E50: =E3 -> 2024 | F50: =F3 -> 2025 | G50: =G3 -> 2026
B51: Equity Share Capital | C51: =IFERROR('Data Sheet'!G54,0) -> 176.79 | D51: =IFERROR('Data Sheet'!H54,0) -> 177.18 | E51: =IFERROR('Data Sheet'!I54,0) -> 177.2 | F51: =IFERROR('Data Sheet'!J54,0) -> 177.23 | G51: =IFERROR('Data Sheet'!K54,0) -> 177.37
B52: Reserves | C52: =IFERROR('Data Sheet'!G55,0) -> 8204.51 | D52: =IFERROR('Data Sheet'!H55,0) -> 8796.08 | E52: =IFERROR('Data Sheet'!I55,0) -> 9689.1 | F52: =IFERROR('Data Sheet'!J55,0) -> 10623.46 | G52: =IFERROR('Data Sheet'!K55,0) -> 11242.15
B53: Borrowings | C53: =IFERROR('Data Sheet'!G56,0) -> 1030.1 | D53: =IFERROR('Data Sheet'!H56,0) -> 1173.79 | E53: =IFERROR('Data Sheet'!I56,0) -> 1365.09 | F53: =IFERROR('Data Sheet'!J56,0) -> 950.37 | G53: =IFERROR('Data Sheet'!K56,0) -> 1287.32
B54: Other Liabilities | C54: =IFERROR('Data Sheet'!G57,0) -> 2872.46 | D54: =IFERROR('Data Sheet'!H57,0) -> 3505.23 | E54: =IFERROR('Data Sheet'!I57,0) -> 3884.97 | F54: =IFERROR('Data Sheet'!J57,0) -> 4478.69 | G54: =IFERROR('Data Sheet'!K57,0) -> 4773.07
B55: Total Liabilities | C55: =IFERROR('Data Sheet'!G58,0) -> 12283.86 | D55: =IFERROR('Data Sheet'!H58,0) -> 13652.28 | E55: =IFERROR('Data Sheet'!I58,0) -> 15116.36 | F55: =IFERROR('Data Sheet'!J58,0) -> 16229.75 | G55: =IFERROR('Data Sheet'!K58,0) -> 17479.91
B57: Fixed Assets Net Block | C57: =IFERROR('Data Sheet'!G59,0) -> 2307.9 | D57: =IFERROR('Data Sheet'!H59,0) -> 3578.65 | E57: =IFERROR('Data Sheet'!I59,0) -> 3815 | F57: =IFERROR('Data Sheet'!J59,0) -> 3989.69 | G57: =IFERROR('Data Sheet'!K59,0) -> 3938.92
B58: Capital Work in Progress | C58: =IFERROR('Data Sheet'!G60,0) -> 167.5 | D58: =IFERROR('Data Sheet'!H60,0) -> 175.13 | E58: =IFERROR('Data Sheet'!I60,0) -> 232.23 | F58: =IFERROR('Data Sheet'!J60,0) -> 168.99 | G58: =IFERROR('Data Sheet'!K60,0) -> 137.48
B59: Investments | C59: =IFERROR('Data Sheet'!G61,0) -> 6219.62 | D59: =IFERROR('Data Sheet'!H61,0) -> 6265.26 | E59: =IFERROR('Data Sheet'!I61,0) -> 6932.69 | F59: =IFERROR('Data Sheet'!J61,0) -> 7467.86 | G59: =IFERROR('Data Sheet'!K61,0) -> 8947.26
B60: Other Assets | C60: =IFERROR('Data Sheet'!G62-SUM('Data Sheet'!G64:G66),0) -> 461.18 | D60: =IFERROR('Data Sheet'!H62-SUM('Data Sheet'!H64:H66),0) -> 434.37 | E60: =IFERROR('Data Sheet'!I62-SUM('Data Sheet'!I64:I66),0) -> 624.39 | F60: =IFERROR('Data Sheet'!J62-SUM('Data Sheet'!J64:J66),0) -> 836.59 | G60: =IFERROR('Data Sheet'!K62-SUM('Data Sheet'!K64:K66),0) -> 857.14
B61: Total Non Current Assets | C61: =SUM(C57:C60) -> 9156.2 | D61: =SUM(D57:D60) -> 10453.41 | E61: =SUM(E57:E60) -> 11604.31 | F61: =SUM(F57:F60) -> 12463.13 | G61: =SUM(G57:G60) -> 13880.8
B63: Receivables | C63: =IFERROR('Data Sheet'!G64,0) -> 646.15 | D63: =IFERROR('Data Sheet'!H64,0) -> 848.75 | E63: =IFERROR('Data Sheet'!I64,0) -> 898.72 | F63: =IFERROR('Data Sheet'!J64,0) -> 888.5 | G63: =IFERROR('Data Sheet'!K64,0) -> 715.41
B64: Inventory | C64: =IFERROR('Data Sheet'!G65,0) -> 1911.37 | D64: =IFERROR('Data Sheet'!H65,0) -> 2024.2 | E64: =IFERROR('Data Sheet'!I65,0) -> 1946.97 | F64: =IFERROR('Data Sheet'!J65,0) -> 2300.11 | G64: =IFERROR('Data Sheet'!K65,0) -> 2321.63
B65: Cash & Bank | C65: =IFERROR('Data Sheet'!G66,0) -> 570.14 | D65: =IFERROR('Data Sheet'!H66,0) -> 325.92 | E65: =IFERROR('Data Sheet'!I66,0) -> 666.36 | F65: =IFERROR('Data Sheet'!J66,0) -> 578.01 | G65: =IFERROR('Data Sheet'!K66,0) -> 562.07
B66: Total Current Assets | C66: =IFERROR(SUM(C63:C65),0) -> 3127.66 | D66: =IFERROR(SUM(D63:D65),0) -> 3198.87 | E66: =IFERROR(SUM(E63:E65),0) -> 3512.05 | F66: =IFERROR(SUM(F63:F65),0) -> 3766.62 | G66: =IFERROR(SUM(G63:G65),0) -> 3599.11
B68: Total Assets | C68: =IFERROR(SUM(C61+C66),0) -> 12283.86 | D68: =IFERROR(SUM(D61+D66),0) -> 13652.28 | E68: =IFERROR(SUM(E61+E66),0) -> 15116.36 | F68: =IFERROR(SUM(F61+F66),0) -> 16229.75 | G68: =IFERROR(SUM(G61+G66),0) -> 17479.91
B70: Check (Assets=Liabilities) | C70: =C68=C55 -> TRUE | D70: =D68=D55 -> TRUE | E70: =E68=E55 -> TRUE | F70: =F68=F55 -> TRUE | G70: =G68=G55 -> TRUE
B72: Cash Flow Statement | C72: =C3 -> 2022 | D72: =D3 -> 2023 | E72: =E3 -> 2024 | F72: =F3 -> 2025 | G72: =G3 -> 2026
B73: Operating Activities
B74: Cash from Operating Activities | C74: =IFERROR('Data Sheet'!G79,0) -> 1802.33 | D74: =IFERROR('Data Sheet'!H79,0) -> 1488.43 | E74: =IFERROR('Data Sheet'!I79,0) -> 2013.47 | F74: =IFERROR('Data Sheet'!J79,0) -> 1986.75 | G74: =IFERROR('Data Sheet'!K79,0) -> 2578.62
B75: Cash from Investing Activities | C75: =IFERROR('Data Sheet'!G80,0) -> -1273.45 | D75: =IFERROR('Data Sheet'!H80,0) -> -582.79 | E75: =IFERROR('Data Sheet'!I80,0) -> -971.04 | F75: =IFERROR('Data Sheet'!J80,0) -> -448.26 | G75: =IFERROR('Data Sheet'!K80,0) -> -1285.22
B76: Cash from Financing Activities | C76: =IFERROR('Data Sheet'!G81,0) -> -490.49 | D76: =IFERROR('Data Sheet'!H81,0) -> -1035.24 | E76: =IFERROR('Data Sheet'!I81,0) -> -1161.18 | F76: =IFERROR('Data Sheet'!J81,0) -> -1405.34 | G76: =IFERROR('Data Sheet'!K81,0) -> -1235.73
B78: Net Cash Flow | C78: =IFERROR(SUM(C74:C76),0) -> 38.39 | D78: =IFERROR(SUM(D74:D76),0) -> -129.6 | E78: =IFERROR(SUM(E74:E76),0) -> -118.75 | F78: =IFERROR(SUM(F74:F76),0) -> 133.15 | G78: =IFERROR(SUM(G74:G76),0) -> 57.67

Sheet Forecasting
B1: Forecasting - DABUR INDIA LTD
A3: # | B3: Sales Forecasting | G3: EBITDA Forecasting | L3: EPS Forecasting
B4: Year Weight | C4: Year | D4: Sales (INR Cr.) | E4: Sales Growth | G4: Year Weight | H4: Year | I4: EBITDA (INR Cr.) | J4: EBITDA Growth | L4: Year Weight | M4: Year | N4: EPS (INR) | O4: EPS Growth
B5: 1 | C5: 2022 | D5: =HistoricalFS!C5 -> 10888.68 | G5: 1 | H5: 2022 | I5: =IFERROR(HistoricalFS!C17,0) -> 2234.91 | L5: 1 | M5: 2022 | N5: =IFERROR(HistoricalFS!C42,0) -> 9.7584705
B6: 2 | C6: 2023 | D6: =HistoricalFS!D5 -> 11529.89 | E6: =(D6/D5)-1 -> 0.058887762 | G6: 2 | H6: 2023 | I6: =IFERROR(HistoricalFS!D17,0) -> 1980.91 | J6: =(I6/I5)-1 -> -0.11365111 | L6: 2 | M6: 2023 | N6: =IFERROR(HistoricalFS!D42,0) -> 8.5774354 | O6: =IFERROR(N6/N5-1,0) -> -0.12102666
B7: 3 | C7: 2024 | D7: =HistoricalFS!E5 -> 12404.01 | E7: =(D7/D6)-1 -> 0.075813386 | G7: 3 | H7: 2024 | I7: =IFERROR(HistoricalFS!E17,0) -> 2497.62 | J7: =(I7/I6)-1 -> 0.26084476 | L7: 3 | M7: 2024 | N7: =IFERROR(HistoricalFS!E42,0) -> 10.774323 | O7: =IFERROR(N7/N6-1,0) -> 0.25612404
B8: 4 | C8: 2025 | D8: =HistoricalFS!F5 -> 12563.09 | E8: =(D8/D7)-1 -> 0.012824885 | G8: 4 | H8: 2025 | I8: =IFERROR(HistoricalFS!F17,0) -> 2202.14 | J8: =(I8/I7)-1 -> -0.11830463 | L8: 4 | M8: 2025 | N8: =IFERROR(HistoricalFS!F42,0) -> 9.1757603 | O8: =IFERROR(N8/N7-1,0) -> -0.14836779
B9: 5 | C9: 2026 | D9: =HistoricalFS!G5 -> 13192.57 | E9: =(D9/D8)-1 -> 0.050105507 | G9: 5 | H9: 2026 | I9: =IFERROR(HistoricalFS!G17,0) -> 2285.48 | J9: =(I9/I8)-1 -> 0.037845005 | L9: 5 | M9: 2026 | N9: =IFERROR(HistoricalFS!G42,0) -> 9.6077691 | O9: =IFERROR(N9/N8-1,0) -> 0.047081522
B10: 6 | C10: 2027 | D10: =FORECAST(B10,$D$5:$D$9,$B$5:$B$9) -> 13807.942 | E10: =(D10/D9)-1 -> 0.046645347 | G10: 6 | H10: 2027 | I10: =FORECAST(G10,$I$5:$I$9,$G$5:$G$9) -> 2336.923 | J10: =(I10/I9)-1 -> 0.02250862 | L10: 6 | M10: 2027 | N10: =FORECAST(L10,$N$5:$N$9,$L$5:$L$9) -> 9.6678282 | O10: =IFERROR(N10/N9-1,0) -> 0.0062511039
B11: 7 | C11: 2028 | D11: =FORECAST(B11,$D$5:$D$9,$B$5:$B$9) -> 14372.04 | E11: =(D11/D10)-1 -> 0.040853155 | G11: 7 | H11: 2028 | I11: =FORECAST(G11,$I$5:$I$9,$G$5:$G$9) -> 2369.16 | J11: =(I11/I10)-1 -> 0.013794635 | L11: 7 | M11: 2028 | N11: =FORECAST(L11,$N$5:$N$9,$L$5:$L$9) -> 9.6975204 | O11: =IFERROR(N11/N10-1,0) -> 0.0030712386
B12: 8 | C12: 2029 | D12: =FORECAST(B12,$D$5:$D$9,$B$5:$B$9) -> 14936.138 | E12: =(D12/D11)-1 -> 0.039249682 | G12: 8 | H12: 2029 | I12: =FORECAST(G12,$I$5:$I$9,$G$5:$G$9) -> 2401.397 | J12: =(I12/I11)-1 -> 0.013606932 | L12: 8 | M12: 2029 | N12: =FORECAST(L12,$N$5:$N$9,$L$5:$L$9) -> 9.7272126 | O12: =IFERROR(N12/N11-1,0) -> 0.003061835
B13: 9 | C13: 2030 | D13: =FORECAST(B13,$D$5:$D$9,$B$5:$B$9) -> 15500.236 | E13: =(D13/D12)-1 -> 0.037767326 | G13: 9 | H13: 2030 | I13: =FORECAST(G13,$I$5:$I$9,$G$5:$G$9) -> 2433.634 | J13: =(I13/I12)-1 -> 0.013424269 | L13: 9 | M13: 2030 | N13: =FORECAST(L13,$N$5:$N$9,$L$5:$L$9) -> 9.7569049 | O13: =IFERROR(N13/N12-1,0) -> 0.0030524888
B14: 10 | C14: 2031 | D14: =FORECAST(B14,$D$5:$D$9,$B$5:$B$9) -> 16064.334 | E14: =(D14/D13)-1 -> 0.036392865 | G14: 10 | H14: 2031 | I14: =FORECAST(G14,$I$5:$I$9,$G$5:$G$9) -> 2465.871 | J14: =(I14/I13)-1 -> 0.013246445 | L14: 10 | M14: 2031 | N14: =FORECAST(L14,$N$5:$N$9,$L$5:$L$9) -> 9.7865971 | O14: =IFERROR(N14/N13-1,0) -> 0.0030431994
A16: #

Sheet Growth Scenarios
B3: Growth Scenarios
B4: INR Cr. | C4: LTM (2026) | D4: Y1E | E4: Y2E | F4: Y3E | G4: Y4E | H4: Y5E | I4: Y6E | J4: Y7E | K4: Y8E | L4: Y9E | M4: Y10E
B5: Scenario 1: High Growth
B6: Sales | C6: =HistoricalFS!G5 -> 13192.57 | D6: =C6*(1+D7) -> 13911.521 | E6: =D6*(1+E7) -> 14647.244 | F6: =E6*(1+F7) -> 15398.284 | G6: =F6*(1+G7) -> 16163.031 | H6: =G6*(1+H7) -> 16939.724 | I6: =H6*(1+I7) -> 17726.455 | J6: =I6*(1+J7) -> 18521.171 | K6: =J6*(1+K7) -> 19321.683 | ... M6: =L6*(1+M7) -> 20930.699 | O6: Median Revenue Growth | P6: =Assumptions!I4 -> 0.054496635
B7: Sales Growth % | D7: =Assumptions!I4 -> 0.054496635 | E7: =D7-($P$9) -> 0.052885898 | F7: =E7-($P$9) -> 0.05127516 | G7: =F7-($P$9) -> 0.049664423 | H7: =G7-($P$9) -> 0.048053686 | I7: =H7-($P$9) -> 0.046442949 | J7: =I7-($P$9) -> 0.044832212 | K7: =J7-($P$9) -> 0.043221474 | L7: =K7-($P$9) -> 0.041610737 | M7: =L7-($P$9) -> 0.04 | O7: Risk Free Rate | P7: 0.04
B8: Scenario 2: Average Growth | P8: =P6-P7 -> 0.014496635
B9: Sales | C9: =IFERROR(HistoricalFS!G5,0) -> 13192.57 | D9: =C9*(1+D10) -> 13844.387 | E9: =D9*(1+E10) -> 14513.937 | F9: =E9*(1+F10) -> 15200.697 | G9: =F9*(1+G10) -> 15904.062 | H9: =G9*(1+H10) -> 16623.349 | I9: =H9*(1+I10) -> 17357.79 | J9: =I9*(1+J10) -> 18106.535 | K9: =J9*(1+K10) -> 18868.65 | ... M9: =L9*(1+M10) -> 20428.845 | O9: Growth Per Year | P9: =P8/9 -> 0.0016107372
B10: Sales Growth % | D10: =Assumptions!C10 -> 0.049407885 | E10: =D10-($P$14) -> 0.048362565 | F10: =E10-($P$14) -> 0.047317244 | G10: =F10-($P$14) -> 0.046271923 | H10: =G10-($P$14) -> 0.045226603 | I10: =H10-($P$14) -> 0.044181282 | J10: =I10-($P$14) -> 0.043135962 | K10: =J10-($P$14) -> 0.042090641 | L10: =K10-($P$14) -> 0.041045321 | M10: =L10-($P$14) -> 0.04
B11: Scenario 3: EBIT-based Growth | O11: Average Revenue Growth | P11: =Assumptions!C10 -> 0.049407885
B12: Sales | C12: =IFERROR(HistoricalFS!G5,0) -> 13192.57 | D12: =C12*(1+D13) -> 13547.583 | E12: =D12*(1+E13) -> 13892.444 | F12: =E12*(1+F13) -> 14225.879 | G12: =F12*(1+G13) -> 14546.626 | H12: =G12*(1+H13) -> 14853.447 | I12: =H12*(1+I13) -> 15145.137 | J12: =I12*(1+J13) -> 15420.527 | K12: =J12*(1+K13) -> 15678.496 | ... M12: =L12*(1+M13) -> 16137.965 | O12: Risk Free Rate | P12: =P7 -> 0.04
B13: Sales Growth % | D13: =P16 -> 0.026910035 | E13: =D13-(-$P$19) -> 0.025455595 | F13: =E13-(-$P$19) -> 0.024001154 | G13: =F13-(-$P$19) -> 0.022546714 | H13: =G13-(-$P$19) -> 0.021092273 | I13: =H13-(-$P$19) -> 0.019637833 | J13: =I13-(-$P$19) -> 0.018183392 | K13: =J13-(-$P$19) -> 0.016728952 | L13: =K13-(-$P$19) -> 0.015274511 | M13: =L13-(-$P$19) -> 0.013820071 | P13: =P11-P12 -> 0.0094078851
O14: Growth Per Year | P14: =P13/9 -> 0.0010453206
B15: Live Scenario | C15: 1
B16: INR Cr. | C16: LTM | D16: Y1E | E16: Y2E | F16: Y3E | G16: Y4W | H16: Y5E | I16: Y6E | J16: Y7E | K16: Y8E | L16: Y9E | M16: Y10E | O16: Growth In EBIT | P16: =Assumptions!C28 -> 0.026910035
B17: Sales | C17: =C6 -> 13192.57 | D17: =C17*(1+D18) -> 13911.521 | E17: =D17*(1+E18) -> 14647.244 | F17: =E17*(1+F18) -> 15398.284 | G17: =F17*(1+G18) -> 16163.031 | H17: =G17*(1+H18) -> 16939.724 | I17: =H17*(1+I18) -> 17726.455 | J17: =I17*(1+J18) -> 18521.171 | K17: =J17*(1+K18) -> 19321.683 | ... M17: =L17*(1+M18) -> 20930.699 | O17: Risk Free Rate | P17: =P12 -> 0.04
B18: Sales Growth % | D18: =CHOOSE($C$15,D7,D10,D13) -> 0.054496635 | E18: =CHOOSE($C$15,E7,E10,E13) -> 0.052885898 | F18: =CHOOSE($C$15,F7,F10,F13) -> 0.05127516 | G18: =CHOOSE($C$15,G7,G10,G13) -> 0.049664423 | H18: =CHOOSE($C$15,H7,H10,H13) -> 0.048053686 | I18: =CHOOSE($C$15,I7,I10,I13) -> 0.046442949 | J18: =CHOOSE($C$15,J7,J10,J13) -> 0.044832212 | K18: =CHOOSE($C$15,K7,K10,K13) -> 0.043221474 | ... M18: =CHOOSE($C$15,M7,M10,M13) -> 0.04 | P18: =P16-P17 -> -0.013089965
O19: Growth Per Year | P19: =P18/9 -> -0.0014544405

Sheet DDM Valuation
B1: GORDON GROWTH MODEL (DDM)
B3: Historical Dividend Per Share (DPS)
B4: Particulars | C4: FY22 | D4: FY23 | E4: FY24 | F4: FY25 | G4: FY26
B5: Shares Outstanding (Cr) | C5: =HistoricalFS!C40 -> 176.79 | D5: =HistoricalFS!D40 -> 177.18 | E5: =HistoricalFS!E40 -> 177.2 | F5: =HistoricalFS!F40 -> 177.23 | G5: =HistoricalFS!G40 -> 177.37
B6: Dividend Per Share | C6: =HistoricalFS!C45 -> 5.2000113 | D6: =HistoricalFS!D45 -> 5.2000226 | E6: =HistoricalFS!E45 -> 5.5 | F6: =HistoricalFS!F45 -> 8 | G6: =HistoricalFS!G45 -> 8.2499859
B7: Earnings Per Share | C7: =HistoricalFS!C42 -> 9.7584705 | D7: =HistoricalFS!D42 -> 8.5774354 | E7: =HistoricalFS!E42 -> 10.774323 | F7: =HistoricalFS!F42 -> 9.1757603 | G7: =HistoricalFS!G42 -> 9.6077691
B8: Dividend Payout Ratio | C8: =HistoricalFS!C46 -> 0.53287155 | D8: =HistoricalFS!D46 -> 0.60624445 | E8: =HistoricalFS!E46 -> 0.51047292 | F8: =HistoricalFS!F46 -> 0.87186236 | G8: =HistoricalFS!G46 -> 0.85867862
B10: Dividend Growth Rate (g) | C10: 2022 | D10: 2023 | E10: 2024 | F10: 2025 | G10: 2026
B11: YoY DPS Growth % | D11: =(D6-C6)/C6 -> 2.1659673e-06 | E11: =(E6-D6)/D6 -> 0.057687716 | F11: =(F6-E6)/E6 -> 0.45454545 | G11: =(G6-F6)/F6 -> 0.031248238
B12: CAGR of DPS | C12: =(G6/C6)^(1/4)-1 -> 0.12230844
B13: Average YoY DPS Growth | C13: =AVERAGE(D11:G11) -> 0.13587089
B14: Revenue CAGR | C14: =Assumptions!C11 -> 0.049152315
B15: Sustainable Growth g | C15: =HistoricalFS!G37/(HistoricalFS!G51+HistoricalFS!G52)*AVERAGE(HistoricalFS!C48:G48) -> 0.048346502
B16: Dividend Growth Rate | C16: =C15 -> 0.048346502
B17: Cost of Equity
B18: Risk-Free Rate | C18: =WACC!K22 -> 0.0709
B19: Equity Risk Premium | C19: =WACC!K23 -> 0.07
B20: Levered Beta | C20: =WACC!K24 -> 0.50230482
B21: Cost of Equity | C21: =WACC!K25 -> 0.10606134
B23: Cost of Equity (Ke) | C23: =C21 -> 0.10606134
B24: Growth Rate | C24: 0.067
B25: Ke − g | C25: =C21-C16 -> 0.057714835
B27: Expected Next Year Dividend
B28: D0 Latest DPS | C28: =HistoricalFS!G45 -> 8.2499859
B29: D1 Expected next year DPS | C29: =C28*(1+C16) -> 8.6488439
B31: Intrinsic Value per Share
B32: Intrinsic Value per Share | C32: =C29/(C21-C16) -> 149.85478
B33: Current Market Price | C33: 451.05

Sheet DCF Valuation
A1: DABUR INDIA LTD - DCF
C2: 1 | D2: 2 | E2: 3 | F2: 4 | G2: 5 | H2: 6 | I2: 7 | J2: 8 | K2: 9 | L2: 10
A3: INR Cr. | B3: FY2026 | C3: Y1E (FY27) | D3: Y2E (FY28) | E3: Y3E (FY29) | F3: Y4E (FY30) | G3: Y5E (FY31) | H3: Y6E (FY32) | I3: Y7E (FY33) | J3: Y8E (FY34) | K3: Y9E (FY35) | L3: Y10E (FY36) | N3: Terminal Year | P3: KEY ASSUMPTIONS | Q3: Value
A4: REVENUE FORECAST | P4: WACC (Cost of Capital) | Q4: =WACC!K44 -> 0.10581786
A5: Sales (INR Cr.) | B5: ='Growth Scenarios'!C17 -> 13192.57 | C5: ='Growth Scenarios'!D17 -> 13911.521 | D5: ='Growth Scenarios'!E17 -> 14647.244 | E5: ='Growth Scenarios'!F17 -> 15398.284 | F5: ='Growth Scenarios'!G17 -> 16163.031 | G5: ='Growth Scenarios'!H17 -> 16939.724 | H5: ='Growth Scenarios'!I17 -> 17726.455 | I5: ='Growth Scenarios'!J17 -> 18521.171 | ... L5: ='Growth Scenarios'!M17 -> 20930.699 | N5: =L5*(1+Q5) -> 22333.056 | P5: Terminal Growth Rate (g = Rf) | Q5: 0.067
A6: Sales Growth % | C6: ='Growth Scenarios'!D18 -> 0.054496635 | D6: ='Growth Scenarios'!E18 -> 0.052885898 | E6: ='Growth Scenarios'!F18 -> 0.05127516 | F6: ='Growth Scenarios'!G18 -> 0.049664423 | G6: ='Growth Scenarios'!H18 -> 0.048053686 | H6: ='Growth Scenarios'!I18 -> 0.046442949 | I6: ='Growth Scenarios'!J18 -> 0.044832212 | J6: ='Growth Scenarios'!K18 -> 0.043221474 | ... L6: ='Growth Scenarios'!M18 -> 0.04 | N6: =Q5 -> 0.067 | P6: Risk-Free Rate (Rf) | Q6: =WACC!K22 -> 0.0709
A7: EBIT & TAX SHIELD | P7: Terminal reinvestment rate % | Q7: =Q4*Q5 -> 0.0070897967
A8: EBIT Margin % (Median Historical) | C8: =AVERAGE(HistoricalFS!$C$18:$G$18) -> 0.18538791 | D8: =AVERAGE(HistoricalFS!$C$18:$G$18) -> 0.18538791 | E8: =AVERAGE(HistoricalFS!$C$18:$G$18) -> 0.18538791 | F8: =AVERAGE(HistoricalFS!$C$18:$G$18) -> 0.18538791 | G8: =AVERAGE(HistoricalFS!$C$18:$G$18) -> 0.18538791 | H8: =AVERAGE(HistoricalFS!$C$18:$G$18) -> 0.18538791 | I8: =AVERAGE(HistoricalFS!$C$18:$G$18) -> 0.18538791 | J8: =AVERAGE(HistoricalFS!$C$18:$G$18) -> 0.18538791 | ... L8: =AVERAGE(HistoricalFS!$C$18:$G$18) -> 0.18538791 | N8: =L8 -> 0.18538791
A9: EBIT | C9: =C5*C8 -> 2579.0278 | D9: =D5*D8 -> 2715.4219 | E9: =E5*E8 -> 2854.6556 | F9: =F5*F8 -> 2996.4305 | G9: =G5*G8 -> 3140.42 | H9: =H5*H8 -> 3286.2704 | I9: =I5*I8 -> 3433.6011 | J9: =J5*J8 -> 3582.0064 | ... L9: =L5*L8 -> 3880.2986 | N9: =N5*N8 -> 4140.2786
A10: Less: Tax on EBIT (25%) | C10: ='DCF Valuation'!C9*Assumptions!$C$15 -> 644.75694 | D10: ='DCF Valuation'!D9*Assumptions!$C$15 -> 678.85549 | E10: ='DCF Valuation'!E9*Assumptions!$C$15 -> 713.66391 | F10: ='DCF Valuation'!F9*Assumptions!$C$15 -> 749.10762 | G10: ='DCF Valuation'!G9*Assumptions!$C$15 -> 785.105 | H10: ='DCF Valuation'!H9*Assumptions!$C$15 -> 821.56759 | I10: ='DCF Valuation'!I9*Assumptions!$C$15 -> 858.40028 | J10: ='DCF Valuation'!J9*Assumptions!$C$15 -> 895.50161 | ... L10: ='DCF Valuation'!L9*Assumptions!$C$15 -> 970.07466 | N10: =25%*N9 -> 1035.0697
A11: EBIT × (1 − Tax Rate) | C11: =C9-C10 -> 1934.2708 | D11: =D9-D10 -> 2036.5665 | E11: =E9-E10 -> 2140.9917 | F11: =F9-F10 -> 2247.3229 | G11: =G9-G10 -> 2355.315 | H11: =H9-H10 -> 2464.7028 | I11: =I9-I10 -> 2575.2009 | J11: =J9-J10 -> 2686.5048 | ... L11: =L9-L10 -> 2910.224 | N11: =N9-N10 -> 3105.209
A12: REINVESTMENT
A13: Less: Net Capital Expenditure | C13: =C5*FCFF!$C$21 -> 490.61431 | D13: =D5*FCFF!$C$21 -> 516.56089 | E13: =E5*FCFF!$C$21 -> 543.04763 | F13: =F5*FCFF!$C$21 -> 570.01777 | G13: =G5*FCFF!$C$21 -> 597.40923 | H13: =H5*FCFF!$C$21 -> 625.15468 | I13: =I5*FCFF!$C$21 -> 653.18174 | J13: =J5*FCFF!$C$21 -> 681.41322 | ... L13: =L5*FCFF!$C$21 -> 738.15802
A14: Non-Cash Working Capital | B14: ='[1]Changes in Working Capital'!G7 -> 83.04 | C14: =C5*'Changes in Working Capital'!$C$12 -> -180.33105 | D14: =D5*'Changes in Working Capital'!$C$12 -> -189.86802 | E14: =E5*'Changes in Working Capital'!$C$12 -> -199.60353 | F14: =F5*'Changes in Working Capital'!$C$12 -> -209.51672 | G14: =G5*'Changes in Working Capital'!$C$12 -> -219.58477 | H14: =H5*'Changes in Working Capital'!$C$12 -> -229.78294 | I14: =I5*'Changes in Working Capital'!$C$12 -> -240.08462 | J14: =J5*'Changes in Working Capital'!$C$12 -> -250.46143 | ... L14: =L5*'Changes in Working Capital'!$C$12 -> -271.31864
A15: Less: Change in Working Capital | C15: =C14-B14 -> -263.37105 | D15: =D14-C14 -> -9.5369693 | E15: =E14-D14 -> -9.735513 | F15: =F14-E14 -> -9.9131941 | G15: =G14-F14 -> -10.068051 | H15: =H14-G14 -> -10.198164 | I15: =I14-H14 -> -10.301677 | J15: =J14-I14 -> -10.376811 | ... L15: =L14-K14 -> -10.435332
A16: Total Reinvestment | C16: =IFERROR(C13+C15,0) -> 227.24326 | D16: =IFERROR(D13+D15,0) -> 507.02392 | E16: =IFERROR(E13+E15,0) -> 533.31211 | F16: =IFERROR(F13+F15,0) -> 560.10458 | G16: =IFERROR(G13+G15,0) -> 587.34118 | H16: =IFERROR(H13+H15,0) -> 614.95651 | I16: =IFERROR(I13+I15,0) -> 642.88007 | J16: =IFERROR(J13+J15,0) -> 671.03641 | ... L16: =IFERROR(L13+L15,0) -> 727.72269 | N16: =N11*N19 -> 22.0153
A17: FREE CASH FLOW TO FIRM (FCFF)
A18: FCFF (INR Cr.) | C18: =C11-C16 -> 1707.0276 | D18: =D11-D16 -> 1529.5425 | E18: =E11-E16 -> 1607.6796 | F18: =F11-F16 -> 1687.2183 | G18: =G11-G16 -> 1767.9738 | H18: =H11-H16 -> 1849.7463 | I18: =I11-I16 -> 1932.3208 | J18: =J11-J16 -> 2015.4684 | ... L18: =L11-L16 -> 2182.5013 | N18: =N11-N16 -> 3083.1937
A19: Reinvestment Rate % | C19: =C16/C11 -> 0.11748265 | D19: =D16/D11 -> 0.24896016 | E19: =E16/E11 -> 0.24909583 | F19: =F16/F11 -> 0.24923192 | G19: =G16/G11 -> 0.24936842 | H19: =H16/H11 -> 0.24950534 | I19: =I16/I11 -> 0.24964269 | J19: =J16/J11 -> 0.24978046 | ... L19: =L16/L11 -> 0.25005728 | N19: =Q7 -> 0.0070897967
A21: TERMINAL VALUE & PRESENT VALUES
A22: Terminal Value : | L22: =N18/(Q4-Q5) -> 79427.191
A23: Present Value Interest Factor (PVIF) | C23: =1/(1+$Q$4)^C2 -> 0.90430806 | D23: =1/(1+$Q$4)^D2 -> 0.81777306 | E23: =1/(1+$Q$4)^E2 -> 0.73951877 | F23: =1/(1+$Q$4)^F2 -> 0.66875278 | G23: =1/(1+$Q$4)^G2 -> 0.60475852 | H23: =1/(1+$Q$4)^H2 -> 0.546888 | I23: =1/(1+$Q$4)^I2 -> 0.49455523 | J23: =1/(1+$Q$4)^J2 -> 0.44723028 | ... L23: =1/(1+$Q$4)^L2 -> 0.36573287
A24: PV of FCFF (Sum of Y1-Y10) | B24: =IFERROR(SUMPRODUCT(C18:L18,C23:L23),0) -> 10696.656
A25: PV of Terminal Value | B25: =IFERROR(L22*L23,0) -> 29049.135
A27: ENTERPRISE VALUE → EQUITY VALUE → INTRINSIC VALUE
A28: Enterprise Value | B28: =IFERROR(B24+B25,0) -> 39745.79
A29: Add: Cash & Equivalents (FY2026) | B29: =HistoricalFS!G65 -> 562.07
A30: Less: Total Debt / Borrowings (FY2026) | B30: ='Balance Sheet'!K6 -> 1287.32
A31: Less: Minority Interest | B31: 26
A32: Equity Value (INR Cr.) | B32: =B28+B29-B30-B31 -> 38994.54
A33: Shares Outstanding (Cr) | B33: ='Data Sheet'!B6 -> 177.36901
A34: INTRINSIC VALUE PER SHARE (INR) | B34: =B32/B33 -> 219.84979
P36: Sensitivity Analysis
