Workbook

Sheet About
A1: INDIAN OIL CORPORATION LIMITED
B6: COMPANY OVERVIEW
B7: ABOUT THE COMPANY | L7: Source
B8: Indian Oil Corporation Limited (NSE: IOC | BSE: 530965), commonly known as IndianOil, is India's largest oil refining and fuel marketing company and a Maharatna public sector enterprise functioning under the Ministry of Petroleum and Natural Gas. Formed in 1959 through the merger of Indian Refineries Limited and the original Indian Oil Company, the group today spans the entire hydrocarbon value chain - exploration and production, refining, pipeline transportation, marketing, petrochemicals and natural gas. IndianOil operates 11 refineries (including those of subsidiary Chennai Petroleum Corporation) with a combined capacity of over 80 million tonnes a year, moves crude and finished products through a cross-country pipeline network exceeding 20,000 km, and serves customers through more than 40,000 retail outlets - the largest fuel retail network in the country. Its portfolio includes well-known brands such as Indane LPG, SERVO lubricants and XtraPremium/XtraMile fuels. Majority owned by the Government of India (around 51.5%), the company is now steadily directing capital toward the energy transition - green hydrogen, biofuels, sustainable aviation fuel, EV charging infrastructure and renewable power - alongside its core refining and marketing businesses.
B9: REGISTERED OFFICE
B10: Address | C10: Indian Oil Bhavan, G-9, Ali Yavar Jung Marg, Bandra (East), Mumbai - 400051, Maharashtra, India
B12: S.No | C12: Name of Entity | D12: Type | F12: Country / Region of Operation | G12: Primary Business | H12: Remarks
B13: 1 | C13: Chennai Petroleum Corporation Limited (CPCL) | D13: Subsidiary | F13: India | G13: Refining & petrochemicals | H13: ~51.9% IOCL stake; principal refining subsidiary
B14: 2 | C14: Lanka IOC PLC | D14: Subsidiary | F14: Sri Lanka | G14: Refining, marketing & retail | H14: ~75.1% IOCL stake; international downstream arm
B15: 3 | C15: IOC Middle East FZE | D15: Subsidiary | F15: UAE | G15: Crude & product trading | H15: Wholly owned trading and marketing hub
B16: 4 | C16: IndianOil (Mauritius) Ltd. | D16: Subsidiary | F16: Mauritius | G16: Investment holding | H16: Wholly owned holding entity for overseas ventures
B17: 5 | C17: IOC Sweden AB | D17: Subsidiary | F17: Sweden | G17: Investment holding | H17: Wholly owned European holding company
B18: 6 | C18: IOCL Singapore Pte. Limited | D18: Subsidiary | F18: Singapore | G18: Trading & shipping | H18: Wholly owned trading and chartering hub
B19: 7 | C19: IOCL (USA) Inc. | D19: Subsidiary | F19: USA | G19: International trading | H19: Wholly owned North America trading arm
B20: 8 | C20: Indian Oil Tanking Limited | D20: Joint Venture | F20: India | G20: Petroleum storage & terminalling | H20: ~49.4% JV with Oiltanking GmbH, Germany
B21: 9 | C21: Indian Oil Petronas Private Limited | D21: Joint Venture | F21: India | G21: LPG bottling & auto LPG | H21: ~50% JV with Petronas, Malaysia
B22: 10 | C22: Indian Oil Skytanking Private Limited | D22: Joint Venture | F22: India | G22: Aviation fuel storage & handling | H22: ~50% JV serving major Indian airports
B23: 11 | C23: Lubrizol India Private Limited | D23: Joint Venture | F23: India | G23: Lubricant additives | H23: ~26% JV with The Lubrizol Corporation, USA
B24: 12 | C24: NPCIL - IndianOil Nuclear Energy Corporation Ltd. | D24: Joint Venture | F24: India | G24: Nuclear power generation | H24: ~26% JV with NPCIL; diversification into nuclear energy
... B26: 14 | C26: Indian Oil NTPC Green Energy Private Limited | D26: Joint Venture | F26: India | G26: Renewable energy | H26: ~50% JV with NTPC for solar & wind projects

Sheet Promoters
B1: Shareholding Pattern
B3: Indian Oil Corporation Ltd
B4: Scrip Code : 530965 | C4: Quarter Ending : Mar-26
B5: Statement showing shareholding pattern of the Promoter and Promoter Group
B6: Category of shareholder | C6: Entity Type | D6: Nos. of shareholders | E6: No. of fully paid up equity shares held | F6: Total nos. shares held | G6: Shareholding as a % of total no. of shares (calculated as per SCRR, 1957)As a % of (A+B+C2) | H6: Number of Voting Rights held in each class of securities | J6: Total No. Of shares on fully diluted basis (including warrants, ESOP, Convertible Securities etc.) | K6: Shareholding , as a % assuming full conversion of convertible securities ( as a percentage of diluted share capital)As a % of (A+B+C2) | L6: Number of equity shares held in dematerialized form
H7: Class eg: X | I7: Total
B9: A7) Indian | D9: - | E9: - | F9: - | G9: 0 | H9: - | I9: 0 | J9: - | K9: 0 | L9: -
B10: Central Government/ State Government(s) | D10: 1 | E10: 7272199767 | F10: 7272199767 | G10: 51.5 | H10: 7272199767 | I10: 51.5 | J10: 7272199767 | K10: 51.5 | L10: 7272199767
B11: President of India | C11: Promoter | D11: 1 | E11: 7272199767 | F11: 7272199767 | G11: 51.5 | H11: 7272199767 | I11: 51.5 | J11: 7272199767 | K11: 51.5 | L11: 7272199767
B12: Sub Total A1 | D12: 1 | E12: 7272199767 | F12: 7272199767 | G12: 51.5 | H12: 7272199767 | I12: 51.5 | J12: 7272199767 | K12: 51.5 | L12: 7272199767
B13: A8) Foreign | D13: - | E13: - | F13: - | G13: 0 | H13: - | I13: 0 | J13: - | K13: 0 | L13: -
B14: A=A1+A2 | D14: 1 | E14: 7272199767 | F14: 7272199767 | G14: 51.5 | H14: 7272199767 | I14: 51.5 | J14: 7272199767 | K14: 51.5 | L14: 7272199767

Sheet Public
B1: Shareholding Pattern Public Shareholder
B3: Indian Oil Corporation Ltd
B4: Scrip Code : 530965 | E4: Quarter Ending : Mar-26
B6: Statement showing shareholding pattern of the Public shareholder
B8: Category & Name of the Shareholders | C8: No. of shareholder | D8: No. of fully paid up equity shares held | E8: Total no. shares held | F8: Shareholding % calculated as per SCRR, 1957 As a % of (A+B+C2) | G8: No. of Voting Rights | H8: Total as a % of Total Voting right | I8: Total No. Of shares on fully diluted basis (including warrants, ESOP, Convertible Securities etc.) | J8: Shareholding , as a % assuming full conversion of convertible securities ( as a percentage of diluted share capital)As a % of (A+B+C2) | K8: No. of equity shares held in dematerialized form(Not Applicable) | L8: Sub-categorization of shares (XV)
L9: Shareholding (No. of shares) under
L10: SubCategory_I | M10: SubCategory_II | N10: SubCategory_III
B11: Institutions | C11: 0 | D11: 0 | E11: - | F11: 0 | G11: - | H11: 0 | I11: - | J11: 0 | K11: - | L11: - | M11: - | N11: -
B12: B2) Institutions (Domestic) | C12: 0 | D12: 0 | E12: - | F12: 0 | G12: - | H12: 0 | I12: - | J12: 0 | K12: - | L12: - | M12: - | N12: -
B13: Mutual Funds/ | C13: 34 | D13: 355639743 | E13: 355639743 | F13: 2.52 | G13: 355639743 | H13: 2.52 | I13: 355639743 | J13: 2.52 | K13: 355639683 | L13: - | M13: - | N13: -
B14: Venture Capital Funds | C14: 0 | D14: 0 | E14: - | F14: 0 | G14: - | H14: 0 | I14: - | J14: 0 | K14: - | L14: - | M14: - | N14: -
B15: Alternate Investment Funds | C15: 7 | D15: 564435 | E15: 564435 | F15: 0 | G15: 564435 | H15: 0 | I15: 564435 | J15: 0 | K15: 564435 | L15: - | M15: - | N15: -
B16: Banks | C16: 21 | D16: 81338 | E16: 81338 | F16: 0 | G16: 81338 | H16: 0 | I16: 81338 | J16: 0 | K16: 25171 | L16: - | M16: - | N16: -
B17: Insurance Companies | C17: 22 | D17: 929160203 | E17: 929160203 | F17: 6.58 | G17: 929160203 | H17: 6.58 | I17: 929160203 | J17: 6.58 | K17: 929159703 | L17: - | M17: - | N17: -
B18: LIFE INSURANCE CORPORATION OF INDIA | C18: 1 | D18: 853418670 | E18: 853418670 | F18: 6.04 | G18: 853418670 | H18: 6.04 | I18: 853418670 | J18: 6.04 | K18: 853418170 | L18: - | M18: - | N18: -
B19: Provident Funds/ Pension Funds | C19: 0 | D19: 0 | E19: - | F19: 0 | G19: - | H19: 0 | I19: - | J19: 0 | K19: - | L19: - | M19: - | N19: -
B20: Asset reconstruction companies | C20: 0 | D20: 0 | E20: - | F20: 0 | G20: - | H20: 0 | I20: - | J20: 0 | K20: - | L20: - | M20: - | N20: -
B21: Sovereign Wealth Funds | C21: 2 | D21: 14670520 | E21: 14670520 | F21: 0.1 | G21: 14670520 | H21: 0.1 | I21: 14670520 | J21: 0.1 | K21: 14670520 | L21: - | M21: - | N21: -
B22: NBFCs registered with RBI | C22: 14 | D22: 96399 | E22: 96399 | F22: 0 | G22: 96399 | H22: 0 | I22: 96399 | J22: 0 | K22: 96399 | L22: - | M22: - | N22: -
B23: Other Financial Institutions | C23: 0 | D23: 0 | E23: - | F23: 0 | G23: - | H23: 0 | I23: - | J23: 0 | K23: - | L23: - | M23: - | N23: -
B24: Sub Total B1 | C24: 100 | D24: 1300212638 | E24: 1300212638 | F24: 9.21 | G24: 1300212638 | H24: 9.21 | I24: 1300212638 | J24: 9.21 | K24: 1300155911 | L24: - | M24: - | N24: -
B25: B15) Institutions (Foreign) | C25: 0 | D25: 0 | E25: - | F25: 0 | G25: - | H25: 0 | I25: - | J25: 0 | K25: - | L25: - | M25: - | N25: -
B26: Foreign Direct Investment | C26: 0 | D26: 0 | E26: - | F26: 0 | G26: - | H26: 0 | I26: - | J26: 0 | K26: - | L26: - | M26: - | N26: -
B27: Foreign Venture Capital Investors | C27: 0 | D27: 0 | E27: - | F27: 0 | G27: - | H27: 0 | I27: - | J27: 0 | K27: - | L27: - | M27: - | N27: -
B28: Sovereign Wealth Funds | C28: 0 | D28: 0 | E28: - | F28: 0 | G28: - | H28: 0 | I28: - | J28: 0 | K28: - | L28: - | M28: - | N28: -
B29: Foreign Portfolio Investors Category I | C29: 751 | D29: 1332327749 | E29: 1332327749 | F29: 9.43 | G29: 1332327749 | H29: 9.43 | I29: 1332327749 | J29: 9.43 | K29: 1332327749 | L29: - | M29: - | N29: -
B30: Foreign Portfolio Investors Category II | C30: 49 | D30: 58141121 | E30: 58141121 | F30: 0.41 | G30: 58141121 | H30: 0.41 | I30: 58141121 | J30: 0.41 | K30: 58141121 | L30: - | M30: - | N30: -
B31: Overseas Depositories (holding DRs) (balancing figure) | C31: 0 | D31: 0 | E31: - | F31: 0 | G31: - | H31: 0 | I31: - | J31: 0 | K31: - | L31: - | M31: - | N31: -
B32: Sub Total B2 | C32: 800 | D32: 1390468870 | E32: 1390468870 | F32: 9.85 | G32: 1390468870 | H32: 9.85 | I32: 1390468870 | J32: 9.85 | K32: 1390468870 | L32: - | M32: - | N32: -
B33: B23) Central Government/ State Government(s)/ President of India | C33: 0 | D33: 0 | E33: - | F33: 0 | G33: - | H33: 0 | I33: - | J33: 0 | K33: - | L33: - | M33: - | N33: -
B34: State Government / Governor | C34: 1 | D34: 16200000 | E34: 16200000 | F34: 0.11 | G34: 16200000 | H34: 0.11 | I34: 16200000 | J34: 0.11 | K34: 16200000 | L34: - | M34: - | N34: -

Sheet Balance Sheet
B1: Indian Oil Corporation
B2: Consolidated Balance Sheet
C3: Mar 26 | D3: 45717 | E3: 45352 | F3: 44986 | G3: 44621
C5: 12 mths | D5: 12 mths | E5: 12 mths | F5: 12 mths | G5: 12 mths
B7: EQUITIES AND LIABILITIES
B8: SHAREHOLDER'S FUNDS
B9: Equity Share Capital | C9: 13771.56 | D9: 13771.56 | E9: 13771.56 | F9: 13771.56 | G9: 9181.04
B10: Total Share Capital | C10: 13771.56 | D10: 13771.56 | E10: 13771.56 | F10: 13771.56 | G10: 9181.04
B11: Reserves and Surplus | C11: 205745.99 | D11: 172715.76 | E11: 169644.71 | F11: 125948.68 | G11: 124354.14
B12: Total Reserves and Surplus | C12: 205745.99 | D12: 172715.76 | E12: 169644.71 | F12: 125948.68 | G12: 124354.14
B13: Total Shareholders Funds | C13: 219517.55 | D13: 186487.32 | E13: 183416.27 | F13: 139720.24 | G13: 133535.18
B14: Minority Interest | C14: 6029.56 | D14: 4537.34 | E14: 4746.71 | F14: 3494.1 | G14: 1591.47
B15: NON-CURRENT LIABILITIES
B16: Long Term Borrowings | C16: 63652.1 | D16: 51755.75 | E16: 46792.9 | F16: 63312.94 | G16: 55944.54
B17: Deferred Tax Liabilities [Net] | C17: 21615.85 | D17: 20664.96 | E17: 18960.7 | F17: 16800.42 | G17: 15354.37
B18: Other Long Term Liabilities | C18: 5492.46 | D18: 11400.64 | E18: 10626.67 | F18: 10379.62 | G18: 10458
B19: Long Term Provisions | C19: 1441.64 | D19: 1406.63 | E19: 1414.82 | F19: 1396.44 | G19: 1586.59
B20: Total Non-Current Liabilities | C20: 92202.05 | D20: 85227.98 | E20: 77795.09 | F20: 91889.42 | G20: 83343.5
B21: CURRENT LIABILITIES
B22: Short Term Borrowings | C22: 68170.29 | D22: 90804.15 | E22: 76660.67 | F22: 76801.88 | G22: 67605.56
B23: Trade Payables | C23: 57368.69 | D23: 60534.94 | E23: 59454.1 | F23: 54734.1 | G23: 49045.91
B24: Other Current Liabilities | C24: 75160.71 | D24: 69262.58 | E24: 69660.9 | F24: 64966.07 | G24: 65754.64
B25: Short Term Provisions | C25: 10506.11 | D25: 10012.74 | E25: 10628.26 | F25: 10156.28 | G25: 9748.59
B26: Total Current Liabilities | C26: 211205.8 | D26: 230614.41 | E26: 216403.93 | F26: 206658.33 | G26: 192154.7
B27: Total Capital And Liabilities | C27: 528954.96 | D27: 506867.05 | E27: 482362 | F27: 441762.09 | G27: 410624.85
B28: ASSETS
B29: NON-CURRENT ASSETS
B30: Tangible Assets | C30: 207625.53 | D30: 197162.03 | E30: 192159.52 | F30: 176532.05 | G30: 157194.98
B31: Intangible Assets | C31: 4095.37 | D31: 3979.1 | E31: 3837.23 | F31: 3514.48 | G31: 3318.33
B32: Capital Work-In-Progress | C32: 82896.79 | D32: 73740.41 | E32: 57316.86 | F32: 47550.08 | G32: 44049.82
B33: Intangible Assets Under Development | C33: 0 | D33: 4180.87 | E33: 3715.56 | F33: 3583.39 | G33: 3419.45
B34: Fixed Assets | C34: 294617.69 | D34: 279062.41 | E34: 257029.17 | F34: 231180 | G34: 207982.58
B35: Non-Current Investments | C35: 66160.99 | D35: 56849.59 | E35: 55162.04 | F35: 41753.92 | G35: 44338.76
B36: Deferred Tax Assets [Net] | C36: 1364.02 | D36: 0 | E36: 0 | F36: 0 | G36: 0
B37: Long Term Loans And Advances | C37: 3357.31 | D37: 3223.44 | E37: 2586.98 | F37: 2285.11 | G37: 2292.96
B38: Other Non-Current Assets | C38: 6643.14 | D38: 10087.42 | E38: 9134.5 | F38: 7676.53 | G38: 9148.82
B39: Total Non-Current Assets | C39: 372144.19 | D39: 349223.9 | E39: 323913.73 | F39: 282896.6 | G39: 263764.16
B40: CURRENT ASSETS
B41: Current Investments | C41: 7136.54 | D41: 10368.91 | E41: 10379.86 | F41: 10436.54 | G41: 8013.2
B42: Inventories | C42: 117132.72 | D42: 113878.49 | E42: 121375.83 | F42: 121107.58 | G42: 111736.51
B43: Trade Receivables | C43: 14634.83 | D43: 18550.96 | E43: 13831.45 | F43: 16271.21 | G43: 18700.42
B44: Cash And Cash Equivalents | C44: 4414.66 | D44: 3304.94 | E44: 3158.79 | F44: 2096.64 | G44: 1820.14
B45: Short Term Loans And Advances | C45: 698.58 | D45: 628.76 | E45: 492.94 | F45: 379.73 | G45: 450.92
B46: OtherCurrentAssets | C46: 12793.44 | D46: 10911.09 | E46: 9209.4 | F46: 8573.79 | G46: 6139.5
B47: Total Current Assets | C47: 156810.77 | D47: 157643.15 | E47: 158448.27 | F47: 158865.49 | G47: 146860.69
B48: Total Assets | C48: 528954.96 | D48: 506867.05 | E48: 482362 | F48: 441762.09 | G48: 410624.85
B49: OTHER ADDITIONAL INFORMATION
B50: CONTINGENT LIABILITIES, COMMITMENTS
B51: Contingent Liabilities | C51: 0 | D51: 64066.62 | E51: 77963.87 | F51: 18483.75 | G51: 69357.88
B52: BONUS DETAILS
B53: Bonus Equity Share Capital | C53: 0 | D53: 9037.98 | E53: 9037.98 | F53: 9037.98 | G53: 9037.98
B54: NON-CURRENT INVESTMENTS
B55: Non-Current Investments Quoted Market Value | C55: 0 | D55: 35969.01 | E55: 37901.25 | F55: 33570.1 | G55: 34445.57
B56: Non-Current Investments Unquoted Book Value | C56: 0 | D56: 23895.22 | E56: 20039.6 | F56: 21003.23 | G56: 19830.69
B57: CURRENT INVESTMENTS
B58: Current Investments Quoted Market Value | C58: 0 | D58: 9516.68 | E58: 9530.9 | F58: 0 | G58: 0
B59: Current Investments Unquoted Book Value | C59: 0 | D59: 852.23 | E59: 848.96 | F59: 0 | G59: 0
B63: Source : Dion Global Solutions Limited

Sheet Profit & Loss
B1: Indian Oil Corporation
B2: Consolidated Profit & Loss account
C3: Mar 26 | D3: 45717 | E3: 45352 | F3: 44986 | G3: 44621
C5: 12 mths | D5: 12 mths | E5: 12 mths | F5: 12 mths | G5: 12 mths
B7: INCOME
B8: Revenue From Operations [Gross] | C8: 901452.7 | D8: 854952.77 | E8: 876951.19 | F8: 947418.92 | G8: 732879.32
B9: Less: Excise/Sevice Tax/Other Levies | C9: 117037.27 | D9: 101256.92 | E9: 104883.6 | F9: 109654.03 | G9: 147395.1
B10: Revenue From Operations [Net] | C10: 784415.43 | D10: 753695.85 | E10: 772067.59 | F10: 837764.89 | G10: 585484.22
B11: Other Operating Revenues | C11: 0 | D11: 4409.96 | E11: 4284.26 | F11: 3991.02 | G11: 3851.52
B12: Total Operating Revenues | C12: 784415.43 | D12: 758105.81 | E12: 776351.85 | F12: 841755.91 | G12: 589335.74
B13: Other Income | C13: 4162.99 | D13: 3513.73 | E13: 3842.85 | F13: 4198.92 | G13: 3082.22
B14: Total Revenue | C14: 788578.42 | D14: 761619.54 | E14: 780194.7 | F14: 845954.83 | G14: 592417.96
B15: EXPENSES
B16: Cost Of Materials Consumed | C16: 433584.37 | D16: 449812.63 | E16: 446251.39 | F16: 503757.28 | G16: 330672.38
B17: Purchase Of Stock-In Trade | C17: 193977.16 | D17: 207762.62 | E17: 191316.43 | F17: 250207.42 | G17: 169991.5
B18: Changes In Inventories Of FG,WIP And Stock-In Trade | C18: 5562.28 | D18: -789.75 | E18: 1231.34 | F18: -6329.71 | G18: -13710.98
B19: Employee Benefit Expenses | C19: 11434.58 | D19: 10879.86 | E19: 11670.94 | F19: 9359.14 | G19: 11582.92
B20: Finance Costs | C20: 8307.88 | D20: 9261.93 | E20: 7825.65 | F20: 7541.36 | G20: 5423.26
B21: Provsions and Contingencies | C21: 1129.99 | D21: 173.27 | E21: 274.47 | F21: 683.33 | G21: -272.23
B22: Depreciation And Amortisation Expenses | C22: 18420.24 | D22: 16777.34 | E22: 15866.11 | F22: 13181.05 | G22: 12347.58
B23: Other Expenses | C23: 61665.4 | D23: 54276.64 | E23: 50016.51 | F23: 53379.46 | G23: 43330.47
B24: Total Expenses | C24: 734081.9 | D24: 748154.54 | E24: 724452.84 | F24: 831779.33 | G24: 559364.9
B25: Profit/Loss Before Exceptional, ExtraOrdinary Items And Tax | C25: 54496.52 | D25: 13465 | E25: 55741.86 | F25: 14175.5 | G25: 33053.06
B26: Exceptional Items | C26: 0 | D26: 1838.02 | E26: 0 | F26: 0 | G26: 0
B27: Profit/Loss Before Tax | C27: 54496.52 | D27: 15303.02 | E27: 55741.86 | F27: 14175.5 | G27: 33053.06
B28: Tax Expenses-Continued Operations
B29: Current Tax | C29: 13794.76 | D29: 1700.08 | E29: 12895.91 | F29: 1922.46 | G29: 7234.66
B30: Deferred Tax | C30: 0 | D30: 1574.54 | E30: 1230.73 | F30: 1410.97 | G30: 1327.36
B31: Total Tax Expenses | C31: 13794.76 | D31: 3274.62 | E31: 14126.64 | F31: 3333.43 | G31: 8562.02
B32: Profit/Loss After Tax And Before ExtraOrdinary Items | C32: 40701.76 | D32: 12028.4 | E32: 41615.22 | F32: 10842.07 | G32: 24491.04
B33: Profit/Loss From Continuing Operations | C33: 40701.76 | D33: 12028.4 | E33: 41615.22 | F33: 10842.07 | G33: 24491.04
B34: Profit/Loss For The Period | C34: 40701.76 | D34: 12028.4 | E34: 41615.22 | F34: 10842.07 | G34: 24491.04
B35: Minority Interest | C35: -1581.06 | D35: -190.99 | E35: -1431.46 | F35: -1912.14 | G35: -624.37
B36: Share Of Profit/Loss Of Associates | C36: 2975.56 | D36: 1760.43 | E36: 1545.93 | F36: 862.19 | G36: 1235.56
B37: Consolidated Profit/Loss After MI And Associates | C37: 42096.26 | D37: 13597.84 | E37: 41729.69 | F37: 9792.12 | G37: 25102.23
B38: OTHER ADDITIONAL INFORMATION
B39: EARNINGS PER SHARE
B40: Basic EPS (Rs.) | C40: 31 | D40: 10 | E40: 30 | F40: 7 | G40: 27
B41: Diluted EPS (Rs.) | C41: 31 | D41: 10 | E41: 30 | F41: 7 | G41: 27
B42: DIVIDEND AND DIVIDEND PERCENTAGE
B43: Equity Share Dividend | C43: 0 | D43: 9640.28 | E43: 11017.62 | F43: 3305.36 | G43: 9640.8

Sheet Cash Flow
B1: Indian Oil Corporation
B2: Cash Flow
C3: Mar 26 | D3: 45717 | E3: 45717 | F3: 45352 | G3: 45352
C5: 12 mths | D5: 12 mths | E5: 12 mths | F5: 12 mths | G5: 12 mths
B7: Net Profit/Loss Before Extraordinary Items And Tax | C7: 48784.41 | D7: 15882.34 | E7: 15882.34 | F7: 52344.21 | G7: 52344.21
B8: Net CashFlow From Operating Activities | C8: 71398.57 | D8: 33170.46 | E8: 33170.46 | F8: 68096.6 | G8: 68096.6
B9: Net Cash Used In Investing Activities | C9: -17661.78 | D9: -29261.29 | E9: -29261.29 | F9: -29701.62 | G9: -29701.62
B10: Net Cash Used From Financing Activities | C10: -53718.55 | D10: -4110.28 | E10: -4110.28 | F10: -38294.02 | G10: -38294.02
B11: Net Inc/Dec In Cash And Cash Equivalents | C11: 18.24 | D11: -201.11 | E11: -201.11 | F11: 100.96 | G11: 100.96
B12: Cash And Cash Equivalents Begin of Year | C12: 263.17 | D12: 464.28 | E12: 464.28 | F12: 363.32 | G12: 363.32
B13: Cash And Cash Equivalents End Of Year | C13: 281.41 | D13: 263.17 | E13: 263.17 | F13: 464.28 | G13: 464.28
B17: Source : Dion Global Solutions Limited

Sheet Stock Analysis
B18: Recommendation - Indian Oil Corporation Ltd: | I18: Financial Year | J18: Revenue | K18: PAT | L18: Revenue Change | M18: PAT Change
B19: "HOLD" Indian Oil Corporation remains India's largest refining and fuel-marketing PSU, but earnings have swung sharply over the past two years on volatile crude prices and government-controlled LPG pricing. FY25 consolidated PAT (after minority interest and associates) fell around 67% YoY to ₹13,598 Cr on inventory losses and marketing under-recoveries, even as revenue held broadly flat at ₹7.58 lakh Cr. The trailing-twelve-month print (Mar'26) shows a sharp recovery to ₹42,096 Cr PAT, helped by softer crude, improved refining margins, and the Government's ₹30,000 Cr compensation for past LPG under-recoveries. The chart reflects this volatility well: the stock rallied sharply through 2024, gave back most of those gains into early 2025, then staged another strong run-up through early 2026 to a 52-week high of ₹188.96, before correcting about 24% to the current ₹143.89 - still roughly 11% above its 52-week low of ₹130.22. At this level, IOC trades at a TTM P/E of approximately 4.8-5.6x and a P/B of about 1.1x - inexpensive on an absolute basis, but broadly in line with how the market has historically priced cyclical, regulation-sensitive OMC earnings rather than signalling a clear valuation gap. | I19: TTM (Mar'26) | J19: ='Profit & Loss'!C12 -> 784415.43 | K19: ='Profit & Loss'!C37 -> 42096.26 | L19: =(J19-J20)/J20 -> 0.034704417 | M19: =(K19-K20)/K20 -> 2.0958049
I20: 2024-25 | J20: ='Profit & Loss'!D12 -> 758105.81 | K20: ='Profit & Loss'!D37 -> 13597.84 | L20: =(J20-J21)/J21 -> -0.023502282 | M20: =(K20-K21)/K21 -> -0.67414472
I21: 2023-24 | J21: ='Profit & Loss'!E12 -> 776351.85 | K21: ='Profit & Loss'!E37 -> 41729.69 | L21: =(J21-J22)/J22 -> -0.077699555 | M21: =(K21-K22)/K22 -> 3.2615583
I22: 2022-23 | J22: ='Profit & Loss'!F12 -> 841755.91 | K22: ='Profit & Loss'!F37 -> 9792.12 | L22: =(J22-J23)/J23 -> 0.42831302 | M22: =(K22-K23)/K23 -> -0.60991035
I23: 2021-22 | J23: ='Profit & Loss'!G12 -> 589335.74 | K23: ='Profit & Loss'!G37 -> 25102.23 | L23: =IFERROR(J23/J24,0) -> 0 | M23: =IFERROR(K23/K24,0) -> 0

Sheet Historical FS
B1: Indian Oil Corporation Limited
B2: Historical Financial Statement | C2: in Rs. Cr.
B3: Years | C3: 2022 | D3: 2023 | E3: 2024 | F3: 2025 | G3: 2026
B4: Income Statement
B5: Revenue from Operations (Net) | C5: 585484.22 | D5: 837764.89 | E5: 772067.59 | F5: 753695.85 | G5: 784415.43
B6: Revenue Growth % | D6: =(D5-C5)/C5 -> 0.43089235 | E6: =(E5-D5)/D5 -> -0.078419734 | F6: =(F5-E5)/E5 -> -0.023795507 | G6: =(G5-F5)/F5 -> 0.04075859
B8: Less: Excise/Service Tax/Other Levies | C8: 147395.1 | D8: 109654.03 | E8: 104883.6 | F8: 101256.92 | G8: 117037.27
B9: Revenue from Operations (Gross) | C9: 732879.32 | D9: 947418.92 | E9: 876951.19 | F9: 854952.77 | G9: 901452.7
B10: Other Operating Revenue | C10: 3851.52 | D10: 3991.02 | E10: 4284.26 | F10: 4409.96 | G10: 0
B11: Other Income | C11: 3082.22 | D11: 4198.92 | E11: 3842.85 | F11: 3513.73 | G11: 4162.99
B12: Total Revenue | C12: =C8+C11 -> 150477.32 | D12: =D8+D11 -> 113852.95 | E12: =E8+E11 -> 108726.45 | F12: =F8+F11 -> 104770.65 | G12: =G8+G11 -> 121200.26
B14: EXPENSES
B15: Cost of Materials Consumed | C15: 330672.38 | D15: 503757.28 | E15: 446251.39 | F15: 449812.63 | G15: 433584.37
B16: Purchase of Stock-in-Trade | C16: 169991.5 | D16: 250207.42 | E16: 191316.43 | F16: 207762.62 | G16: 193977.16
B17: Changes in Inventories of FG/WIP/SIT | C17: -13710.98 | D17: -6329.71 | E17: 1231.34 | F17: -789.75 | G17: 5562.28
B18: Employee Benefit Expenses | C18: 11582.92 | D18: 9359.14 | E18: 11670.94 | F18: 10879.86 | G18: 11434.58
B19: Finance Costs | C19: 5423.26 | D19: 7541.36 | E19: 7825.65 | F19: 9261.93 | G19: 8307.88
B20: Provisions & Contingencies | C20: -272.23 | D20: 683.33 | E20: 274.47 | F20: 173.27 | G20: 1129.99
B21: Depreciation & Amortisation Expenses | C21: 12347.58 | D21: 13181.05 | E21: 15866.11 | F21: 16777.34 | G21: 18420.24
B22: Other Expenses | C22: 43330.47 | D22: 53379.46 | E22: 50016.51 | F22: 54276.64 | G22: 61665.4
B23: Total Expenses | C23: =SUM(C15:C22) -> 559364.9 | D23: =SUM(D15:D22) -> 831779.33 | E23: =SUM(E15:E22) -> 724452.84 | F23: =SUM(F15:F22) -> 748154.54 | G23: =SUM(G15:G22) -> 734081.9
B25: EBITDA | C25: =C5+C8-C23+C18+C21 -> 197444.92 | D25: =D5+D8-D23+D18+D21 -> 138179.78 | E25: =E5+E8-E23+E18+E21 -> 180035.4 | F25: =F5+F8-F23+F18+F21 -> 134455.43 | G25: =G5+G8-G23+G18+G21 -> 197225.62
B26: EBITDA Margins | C26: =C25/C5 -> 0.33723355 | D26: =D25/D5 -> 0.16493861 | E26: =E25/E5 -> 0.23318606 | F26: =F25/F5 -> 0.17839481 | G26: =G25/G5 -> 0.25143006
B28: Depreciation & Amortisation | C28: 12347.58 | D28: 13181.05 | E28: 15866.11 | F28: 16777.34 | G28: 18420.24
B29: Depreciation % of Sales | C29: =C28/C5 -> 0.021089518 | D29: =D28/D5 -> 0.015733591 | E29: =E28/E5 -> 0.020550157 | F29: =F28/F5 -> 0.022260093 | G29: =G28/G5 -> 0.023482761
B31: EBIT | C31: =C25-C28 -> 185097.34 | D31: =D25-D28 -> 124998.73 | E31: =E25-E28 -> 164169.29 | F31: =F25-F28 -> 117678.09 | G31: =G25-G28 -> 178805.38
B32: EBIT Margin | C32: =C31/C5 -> 0.31614403 | D32: =D31/D5 -> 0.14920502 | E32: =E31/E5 -> 0.2126359 | F32: =F31/F5 -> 0.15613472 | G32: =G31/G5 -> 0.2279473
B34: Finance Costs | C34: 5423.26 | D34: 7541.36 | E34: 7825.65 | F34: 9261.93 | G34: 8307.88
B35: Finance Costs % of Sales | C35: =C34/C5 -> 0.0092628628 | D35: =D34/D5 -> 0.0090017618 | E35: =E34/E5 -> 0.010135965 | F35: =F34/F5 -> 0.012288684 | G35: =G34/G5 -> 0.010591174
B37: Profit Before Tax | C37: 33053.06 | D37: 14175.5 | E37: 55741.86 | F37: 15303.02 | G37: 54496.52
B38: PBT % Sales | C38: =C37/C5 -> 0.056454229 | D38: =D37/D5 -> 0.016920618 | E38: =E37/E5 -> 0.072198161 | F38: =F37/F5 -> 0.020303973 | G38: =G37/G5 -> 0.069474054
B40: Total Tax Expenses | C40: 8562.02 | D40: 3333.43 | E40: 14126.64 | F40: 3274.62 | G40: 13794.76
B41: Effective Tax Rate | C41: =C40/C37 -> 0.25903865 | D41: =D40/D37 -> 0.23515432 | E41: =E40/E37 -> 0.25342965 | F41: =F40/F37 -> 0.21398521 | G41: =G40/G37 -> 0.25313103
B43: Net Profit (after MI & Associates) | C43: 25102.23 | D43: 9792.12 | E43: 41729.69 | F43: 13597.84 | G43: 42096.26
B44: Net Profit Margins | C44: =C43/C5 -> 0.042874307 | D44: =D43/D5 -> 0.011688387 | E44: =E43/E5 -> 0.05404927 | F44: =F43/F5 -> 0.018041548 | G44: =G43/G5 -> 0.053665772
B46: Basic EPS (₹) | C46: 27 | D46: 7 | E46: 30 | F46: 10 | G46: 31
B47: EPS Growth % | D47: =(D46-C46)/C46 -> -0.74074074 | E47: =(E46-D46)/D46 -> 3.2857143 | F47: =(F46-E46)/E46 -> -0.66666667 | G47: =(G46-F46)/F46 -> 2.1
B50: Balance Sheet
B51: Years | C51: 2022 | D51: 2023 | E51: 2024 | F51: 2025 | G51: 2026
B52: EQUITY & LIABILITIES
B53: Equity Share Capital | C53: 9181.04 | D53: 13771.56 | E53: 13771.56 | F53: 13771.56 | G53: 13771.56
B54: Reserves & Surplus | C54: 124354.14 | D54: 125948.68 | E54: 169644.71 | F54: 172715.76 | G54: 205745.99
B55: Total Shareholders Funds | C55: =C53+C54 -> 133535.18 | D55: =D53+D54 -> 139720.24 | E55: =E53+E54 -> 183416.27 | F55: =F53+F54 -> 186487.32 | G55: =G53+G54 -> 219517.55
B56: Minority Interest | C56: 1591.47 | D56: 3494.1 | E56: 4746.71 | F56: 4537.34 | G56: 6029.56
B57: Long Term Borrowings | C57: 55944.54 | D57: 63312.94 | E57: 46792.9 | F57: 51755.75 | G57: 63652.1
B58: Short Term Borrowings | C58: 67605.56 | D58: 76801.88 | E58: 76660.67 | F58: 90804.15 | G58: 68170.29
B59: Total Borrowings | C59: =C57+C58 -> 123550.1 | D59: =D57+D58 -> 140114.82 | E59: =E57+E58 -> 123453.57 | F59: =F57+F58 -> 142559.9 | G59: =G57+G58 -> 131822.39
B60: Trade Payables | C60: 49045.91 | D60: 54734.1 | E60: 59454.1 | F60: 60534.94 | G60: 57368.69
B61: Other Current Liabilities | C61: 65754.64 | D61: 64966.07 | E61: 69660.9 | F61: 69262.58 | G61: 75160.71
B62: Short Term Provisions | C62: 9748.59 | D62: 10156.28 | E62: 10628.26 | F62: 10012.74 | G62: 10506.11
B63: Total Current Liabilities | C63: =SUM(C60:C62) -> 124549.14 | D63: =SUM(D60:D62) -> 129856.45 | E63: =SUM(E60:E62) -> 139743.26 | F63: =SUM(F60:F62) -> 139810.26 | G63: =SUM(G60:G62) -> 143035.51
B64: Deferred Tax Liabilities [Net] | C64: 15354.37 | D64: 16800.42 | E64: 18960.7 | F64: 20664.96 | G64: 21615.85
B65: Other Long Term Liabilities | C65: 10458 | D65: 10379.62 | E65: 10626.67 | F65: 11400.64 | G65: 5492.46
B66: Long Term Provisions | C66: 1586.59 | D66: 1396.44 | E66: 1414.82 | F66: 1406.63 | G66: 1441.64
B68: ASSETS
B69: Tangible Assets (Net Block) | C69: 157194.98 | D69: 176532.05 | E69: 192159.52 | F69: 197162.03 | G69: 207625.53
B70: Intangible Assets | C70: 3318.33 | D70: 3514.48 | E70: 3837.23 | F70: 3979.1 | G70: 4095.37
B71: Capital Work-in-Progress | C71: 44049.82 | D71: 47550.08 | E71: 57316.86 | F71: 73740.41 | G71: 82896.79
B72: Fixed Assets (Net Block) | C72: =SUM(C69:C71) -> 204563.13 | D72: =SUM(D69:D71) -> 227596.61 | E72: =SUM(E69:E71) -> 253313.61 | F72: =SUM(F69:F71) -> 274881.54 | G72: =SUM(G69:G71) -> 294617.69
B73: Non-Current Investments | C73: 44338.76 | D73: 41753.92 | E73: 55162.04 | F73: 56849.59 | G73: 66160.99
B74: Deferred Tax Assets [Net] | C74: 0 | D74: 0 | E74: 0 | F74: 0 | G74: 1364.02
B75: Long Term Loans & Advances | C75: 2292.96 | D75: 2285.11 | E75: 2586.98 | F75: 3223.44 | G75: 3357.31
B76: Other Non-Current Assets | C76: 9148.82 | D76: 7676.53 | E76: 9134.5 | F76: 10087.42 | G76: 6643.14
B77: Total Non-Current Assets | C77: =C72+C73+C74+C75+C76 -> 260343.67 | D77: =D72+D73+D74+D75+D76 -> 279312.17 | E77: =E72+E73+E74+E75+E76 -> 320197.13 | F77: =F72+F73+F74+F75+F76 -> 345041.99 | G77: =G72+G73+G74+G75+G76 -> 372143.15
B79: Current Investments | C79: 8013.2 | D79: 10436.54 | E79: 10379.86 | F79: 10368.91 | G79: 7136.54
B80: Inventories | C80: 111736.51 | D80: 121107.58 | E80: 121375.83 | F80: 113878.49 | G80: 117132.72
B81: Trade Receivables | C81: 18700.42 | D81: 16271.21 | E81: 13831.45 | F81: 18550.96 | G81: 14634.83
B82: Cash & Cash Equivalents | C82: 1820.14 | D82: 2096.64 | E82: 3158.79 | F82: 3304.94 | G82: 4414.66
B83: Short Term Loans & Advances | C83: 450.92 | D83: 379.73 | E83: 492.94 | F83: 628.76 | G83: 698.58
B84: Other Current Assets | C84: 6139.5 | D84: 8573.79 | E84: 9209.4 | F84: 10911.09 | G84: 12793.44
B85: Total Current Assets | C85: =SUM(C79:C84) -> 146860.69 | D85: =SUM(D79:D84) -> 158865.49 | E85: =SUM(E79:E84) -> 158448.27 | F85: =SUM(F79:F84) -> 157643.15 | G85: =SUM(G79:G84) -> 156810.77
B86: Total Assets | C86: =C77+C84 -> 266483.17 | D86: =D77+D84 -> 287885.96 | E86: =E77+E84 -> 329406.53 | F86: =F77+F84 -> 355953.08 | G86: =G77+G84 -> 384936.59
B89: Cash Flow Statement
B90: Years | C90: 2022 | D90: 2023 | E90: 2024 | F90: 2025 | G90: 2026
B91: Net Cash from Operating Activities | E91: 68096.6 | F91: 33170.46 | G91: 71398.57
B92: Net Cash used in Investing Activities | E92: -29701.62 | F92: -29261.29 | G92: -17661.78
B93: Net Cash from Financing Activities | E93: -38294.02 | F93: -4110.28 | G93: -53718.55
B94: Net Inc/(Dec) in Cash & Equivalents | E94: =SUM(E91:E93) -> 100.96 | F94: =SUM(F91:F93) -> -201.11 | G94: =SUM(G91:G93) -> 18.24
B95: Opening Cash & Cash Equivalents | E95: 363.32 | F95: 464.28 | G95: 263.17
B96: Closing Cash & Cash Equivalents | E96: 464.28 | F96: 263.17 | G96: 281.41

Sheet Working Capital Changes
B1: Indian Oil Corporation Limited – Working Capital Analysis
B2: Change in Working Capital | C2: in Rs. Cr.
B3: Particulars | C3: 2022 | D3: 2023 | E3: 2024 | F3: 2025 | G3: 2026
B4: CURRENT ASSETS (Operating)
B5: Inventories | C5: 111736.51 | D5: 121107.58 | E5: 121375.83 | F5: 113878.49 | G5: 117132.72
B6: Trade Receivables | C6: 18700.42 | D6: 16271.21 | E6: 13831.45 | F6: 18550.96 | G6: 14634.83
B7: Short Term Loans & Advances | C7: 450.92 | D7: 379.73 | E7: 492.94 | F7: 628.76 | G7: 698.58
B8: Other Current Assets | C8: 6139.5 | D8: 8573.79 | E8: 9209.4 | F8: 10911.09 | G8: 12793.44
B9: Total Operating Current Assets (A) | C9: =C5+C6+C7+C8 -> 137027.35 | D9: =D5+D6+D7+D8 -> 146332.31 | E9: =E5+E6+E7+E8 -> 144909.62 | F9: =F5+F6+F7+F8 -> 143969.3 | G9: =G5+G6+G7+G8 -> 145259.57
B11: CURRENT LIABILITIES (Operating)
B12: Trade Payables | C12: 49045.91 | D12: 54734.1 | E12: 59454.1 | F12: 60534.94 | G12: 57368.69
B13: Other Current Liabilities | C13: 65754.64 | D13: 64966.07 | E13: 69660.9 | F13: 69262.58 | G13: 75160.71
B14: Short Term Provisions | C14: 9748.59 | D14: 10156.28 | E14: 10628.26 | F14: 10012.74 | G14: 10506.11
B15: Total Operating Current Liabilities (B) | C15: =C12+C13+C14 -> 124549.14 | D15: =D12+D13+D14 -> 129856.45 | E15: =E12+E13+E14 -> 139743.26 | F15: =F12+F13+F14 -> 139810.26 | G15: =G12+G13+G14 -> 143035.51
B17: Non-Cash Working Capital (A − B) | C17: =C9-C15 -> 12478.21 | D17: =D9-D15 -> 16475.86 | E17: =E9-E15 -> 5166.36 | F17: =F9-F15 -> 4159.04 | G17: =G9-G15 -> 2224.06
B19: Change in Working Capital (YoY) | D19: =D17-C17 -> 3997.65 | E19: =E17-D17 -> -11309.5 | F19: =F17-E17 -> -1007.32 | G19: =G17-F17 -> -1934.98
B20: Change in Working Capital / Sales % | D20: =D19/837764.89 -> 0.0047718042 | E20: =E19/772067.59 -> -0.014648329 | F20: =F19/753695.85 -> -0.0013365073 | G20: =G19/784415.43 -> -0.0024667796
B21: Median Change in WC / Sales % | D21: =MEDIAN(D20:G20) -> -0.0019016435
B22: Average Change in WC / Sales % | D22: =AVERAGE(D20:G20) -> -0.0034199529
B24: WORKING CAPITAL EFFICIENCY RATIOS
B25: Inventory Days | C25: =C5/585484.22*365 -> 69.658284 | D25: =D5/837764.89*365 -> 52.764525 | E25: =E5/772067.59*365 -> 57.381217 | F25: =F5/753695.85*365 -> 55.149101 | G25: =G5/784415.43*365 -> 54.503572
B26: Debtor Days (Receivable Days) | C26: =C6/585484.22*365 -> 11.658134 | D26: =D6/837764.89*365 -> 7.0890911 | E26: =E6/772067.59*365 -> 6.5389084 | F26: =F6/753695.85*365 -> 8.9838632 | G26: =G6/784415.43*365 -> 6.809801
B27: Creditor Days (Payable Days) | C27: =C12/585484.22*365 -> 30.575986 | D27: =D12/837764.89*365 -> 23.846722 | E27: =E12/772067.59*365 -> 28.107314 | F27: =F12/753695.85*365 -> 29.315875 | G27: =G12/784415.43*365 -> 26.694493
B28: Cash Conversion Cycle (days) | C28: =C25+C26-C27 -> 50.740432 | D28: =D25+D26-D27 -> 36.006894 | E28: =E25+E26-E27 -> 35.812811 | F28: =F25+F26-F27 -> 34.81709 | G28: =G25+G26-G27 -> 34.61888

Sheet Fixed Assets Schedule
B1: Indian Oil Corporation Limited – Fixed Assets Schedule
B2: Fixed Assets Schedule | C2: in Rs. Cr.
B3: Particulars | C3: 2022 | D3: 2023 | E3: 2024 | F3: 2025 | G3: 2026
B4: Beginning Balance (Net Fixed Assets) | D4: 207982.58 | E4: 231180 | F4: 257029.17 | G4: 279062.41
B5: Add: Gross Capital Expenditure (Purchases) | D5: 36378.47 | E5: 41715.28 | F5: 38810.58 | G5: 33975.52
B6: Gross Fixed Assets (Before Depreciation) | C6: 220330.16 | D6: =D4+D5 -> 244361.05 | E6: =E4+E5 -> 272895.28 | F6: =F4+F5 -> 295839.75 | G6: =G4+G5 -> 313037.93
B7: Less: Depreciation & Amortisation | C7: 12347.58 | D7: 13181.05 | E7: 15866.11 | F7: 16777.34 | G7: 18420.24
B8: Closing Balance (Net Fixed Assets) | C8: =C6-C7 -> 207982.58 | D8: =D6-D7 -> 231180 | E8: =E6-E7 -> 257029.17 | F8: =F6-F7 -> 279062.41 | G8: =G6-G7 -> 294617.69
B10: Net Capital Expenditure (Closing − Opening) | D10: =D8-D4 -> 23197.42 | E10: =E8-E4 -> 25849.17 | F10: =F8-F4 -> 22033.24 | G10: =G8-G4 -> 15555.28
B11: Net Capex / Sales % | D11: =D10/837764.89 -> 0.027689654 | E11: =E10/772067.59 -> 0.03348045 | F11: =F10/753695.85 -> 0.029233596 | G11: =G10/784415.43 -> 0.019830411
B12: Median Net Capex / Sales % | D12: =MEDIAN(D11:G11) -> 0.028461625
B13: Average Net Capex / Sales % | D13: =AVERAGE(D11:G11) -> 0.027558528
B15: Gross Capex / Sales % | D15: =D5/837764.89 -> 0.043423245 | E15: =E5/772067.59 -> 0.054030606 | F15: =F5/753695.85 -> 0.051493689 | G15: =G5/784415.43 -> 0.043313171
B16: Median Gross Capex / Sales % | D16: =MEDIAN(D15:G15) -> 0.047458467
B17: Average Gross Capex / Sales % | D17: =AVERAGE(D15:G15) -> 0.048065178
B19: Depreciation % of Sales | C19: =C7/585484.22 -> 0.021089518 | D19: =D7/837764.89 -> 0.015733591 | E19: =E7/772067.59 -> 0.020550157 | F19: =F7/753695.85 -> 0.022260093 | G19: =G7/784415.43 -> 0.023482761
B20: Median Depreciation / Sales % | C20: =MEDIAN(C19:G19) -> 0.021089518
B21: Average Depreciation / Sales % | C21: =AVERAGE(C19:G19) -> 0.020623224

Sheet FCFF
B1: Indian Oil Corporation Limited – FCFF Build
B2: Free Cash Flow to Firm (FCFF) | C2: in Rs. Cr.
B3: Particulars | C3: 2022 | D3: 2023 | E3: 2024 | F3: 2025 | G3: 2026
B4: EBIT | C4: ='Historical FS'!C31 -> 185097.34 | D4: ='Historical FS'!D31 -> 124998.73 | E4: ='Historical FS'!E31 -> 164169.29 | F4: ='Historical FS'!F31 -> 117678.09 | G4: ='Historical FS'!G31 -> 178805.38
B5: Effective Tax Rate | C5: ='Historical FS'!C41 -> 0.25903865 | D5: ='Historical FS'!D41 -> 0.23515432 | E5: ='Historical FS'!E41 -> 0.25342965 | F5: ='Historical FS'!F41 -> 0.21398521 | G5: ='Historical FS'!G41 -> 0.25313103
B6: Less: Tax on EBIT | C6: =C4*C5 -> 47947.365 | D6: =D4*D5 -> 29393.991 | E6: =E4*E5 -> 41605.365 | F6: =F4*F5 -> 25181.371 | G6: =G4*G5 -> 45261.189
B8: EBIT × (1 − t) [NOPAT] | C8: =C4-C6 -> 137149.98 | D8: =D4-D6 -> 95604.739 | E8: =E4-E6 -> 122563.92 | F8: =F4-F6 -> 92496.719 | G8: =G4-G6 -> 133544.19
B10: REINVESTMENT
B11: Less: Net Capital Expenditure | D11: ='Fixed Assets Schedule'!D10 -> 23197.42 | E11: ='Fixed Assets Schedule'!E10 -> 25849.17 | F11: ='Fixed Assets Schedule'!F10 -> 22033.24 | G11: ='Fixed Assets Schedule'!G10 -> 15555.28
B12: Less: Change in Working Capital | D12: ='Working Capital Changes'!D19 -> 3997.65 | E12: ='Working Capital Changes'!E19 -> -11309.5 | F12: ='Working Capital Changes'!F19 -> -1007.32 | G12: ='Working Capital Changes'!G19 -> -1934.98
B13: Total Reinvestment | D13: =D11+D12 -> 27195.07 | E13: =E11+E12 -> 14539.67 | F13: =F11+F12 -> 21025.92 | G13: =G11+G12 -> 13620.3
B15: Free Cash Flow to Firm | C15: =C8 -> 137149.98 | D15: =D8-D13 -> 68409.669 | E15: =E8-E13 -> 108024.25 | F15: =F8-F13 -> 71470.799 | G15: =G8-G13 -> 119923.89
B17: REINVESTMENT RATE & EFFICIENCY METRICS
B18: Reinvestment Rate (Reinvestment / NOPAT) | D18: =IF(D8<>0,D13/D8,0) -> 0.28445316 | E18: =IF(E8<>0,E13/E8,0) -> 0.11862928 | F18: =IF(F8<>0,F13/F8,0) -> 0.22731531 | G18: =IF(G8<>0,G13/G8,0) -> 0.10199096
B19: Median Reinvestment Rate | D19: =MEDIAN(D18:G18) -> 0.17297229
B20: Average Reinvestment Rate | D20: =AVERAGE(D18:G18) -> 0.18309718
B22: FCFF / Net Revenue % | C22: =C15/('Historical FS'!C5) -> 0.23425051 | D22: =D15/('Historical FS'!D5) -> 0.08165736 | E22: =E15/('Historical FS'!E5) -> 0.13991554 | F22: =F15/('Historical FS'!F5) -> 0.094827109 | G22: =G15/('Historical FS'!G5) -> 0.15288314
B23: NOPAT Margin (NOPAT / Net Revenue) | C23: =C8/('Historical FS'!C5) -> 0.23425051 | D23: =D8/('Historical FS'!D5) -> 0.11411882 | E23: =E8/('Historical FS'!E5) -> 0.15874766 | F23: =F8/('Historical FS'!F5) -> 0.1227242 | G23: =G8/('Historical FS'!G5) -> 0.17024677
B25: FCFF Growth (YoY) | E25: =IF(D15<>0,(E15-D15)/D15,0) -> 0.57907874 | F25: =IF(E15<>0,(F15-E15)/E15,0) -> -0.33838193 | G25: =IF(F15<>0,(G15-F15)/F15,0) -> 0.6779425

Sheet WACC
B1: WACC Calculation
B2: Cost Of Capital
B3: As On Date: | C3: June 2026
B5: Cost of Equity using CAPM:
B6: Risk-free rate | C6: 0.0685
B7: India Default Spread | C7: 0.0187
B8: Beta (Regression - IOC vs Nifty 50) | C8: =SLOPE(Beta!D2:D1101,Beta!C2:C1101) -> 1.0089971
B9: Equity Risk Premium (ERP) | C9: 0.075
B10: Cost of Equity (Ke) | C10: =C6+C8*C9 -> 0.14417478
B12: Cost of Debt:
B13: Finance Cost (₹ Cr.) | C13: ='Profit & Loss'!C20 -> 8307.88
B14: Long Term Borrowings (₹ Cr.) | C14: ='Balance Sheet'!C16 -> 63652.1
B15: Short Term Borrowings (₹ Cr.) | C15: ='Balance Sheet'!C22 -> 68170.29
B16: Total Debt (₹ Cr.) | C16: =C14+C15 -> 131822.39
B17: Pre-Tax Cost of Debt (Kd) | C17: =C13/C16 -> 0.063023285
B18: Marginal Tax Rate % | C18: 0.25
B19: Post-Tax Cost of Debt | C19: =C17*(1-C18) -> 0.047267463
B21: WACC Calculation:
B22: Equity Share Capital (₹ Cr.) | C22: ='Balance Sheet'!C9 -> 13771.56
B23: Face Value (₹) | C23: 10
B24: Shares Outstanding (Cr.) | C24: =C22/C23 -> 1377.156
B25: Share Price (₹, as on date) | C25: 147
B26: Market Value of Equity (₹ Cr.) | C26: =C24*C25 -> 202441.93
B28: Capital Structure Weights
B29: Total Capital (Equity + Debt) (₹ Cr.) | C29: =C26+C16 -> 334264.32
B30: Weight of Debt (Wd) | C30: =C16/C29 -> 0.39436572
B31: Weight of Equity (We) | C31: =C26/C29 -> 0.60563428
B33: WACC
B34: WACC | C34: =(C31*C10)+(C30*C19) -> 0.10595786

Sheet Assumption
B1: Indian Oil Corporation
B3: Particulars | C3: 2022 | D3: 2023 | E3: 2024 | F3: 2025 | G3: 2026 | I3: Metric | J3: Value
B4: A. Income Statement Build-up
B5: Revenue from Operations (Net) | C5: ='Profit & Loss'!G10 -> 585484.22 | D5: ='Profit & Loss'!F10 -> 837764.89 | E5: ='Profit & Loss'!E10 -> 772067.59 | F5: ='Profit & Loss'!D10 -> 753695.85 | G5: ='Profit & Loss'!C10 -> 784415.43
B6: Revenue Growth % | D6: =(Assumption!D5/Assumption!C5)-1 -> 0.43089235 | E6: =(Assumption!E5/Assumption!D5)-1 -> -0.078419734 | F6: =(Assumption!F5/Assumption!E5)-1 -> -0.023795507 | G6: =(Assumption!G5/Assumption!F5)-1 -> 0.04075859 | I6: Median Revenue Growth | J6: =MEDIAN(D6:G6) -> 0.0084815412
B7: Less: Cost of Materials Consumed | C7: ='Profit & Loss'!G16 -> 330672.38 | D7: ='Profit & Loss'!F16 -> 503757.28 | E7: ='Profit & Loss'!E16 -> 446251.39 | F7: ='Profit & Loss'!D16 -> 449812.63 | G7: ='Profit & Loss'!C16 -> 433584.37
B8: Less: Purchase of Stock-in-Trade | C8: ='Profit & Loss'!G17 -> 169991.5 | D8: ='Profit & Loss'!F17 -> 250207.42 | E8: ='Profit & Loss'!E17 -> 191316.43 | F8: ='Profit & Loss'!D17 -> 207762.62 | G8: ='Profit & Loss'!C17 -> 193977.16
B9: Less: Changes in Inventories | C9: ='Profit & Loss'!G18 -> -13710.98 | D9: ='Profit & Loss'!F18 -> -6329.71 | E9: ='Profit & Loss'!E18 -> 1231.34 | F9: ='Profit & Loss'!D18 -> -789.75 | G9: ='Profit & Loss'!C18 -> 5562.28
B10: Less: Employee Benefit Expenses | C10: ='Profit & Loss'!G19 -> 11582.92 | D10: ='Profit & Loss'!F19 -> 9359.14 | E10: ='Profit & Loss'!E19 -> 11670.94 | F10: ='Profit & Loss'!D19 -> 10879.86 | G10: ='Profit & Loss'!C19 -> 11434.58
B11: Less: Other Expenses | C11: ='Profit & Loss'!G23 -> 43330.47 | D11: ='Profit & Loss'!F23 -> 53379.46 | E11: ='Profit & Loss'!E23 -> 50016.51 | F11: ='Profit & Loss'!D23 -> 54276.64 | G11: ='Profit & Loss'!C23 -> 61665.4
B12: Total Operating Expenses | C12: =Assumption!C7+Assumption!C8+Assumption!C9+Assumption!C10+Assumption!C11 -> 541866.29 | D12: =Assumption!D7+Assumption!D8+Assumption!D9+Assumption!D10+Assumption!D11 -> 810373.59 | E12: =Assumption!E7+Assumption!E8+Assumption!E9+Assumption!E10+Assumption!E11 -> 700486.61 | F12: =Assumption!F7+Assumption!F8+Assumption!F9+Assumption!F10+Assumption!F11 -> 721942 | G12: =Assumption!G7+Assumption!G8+Assumption!G9+Assumption!G10+Assumption!G11 -> 706223.79
B13: EBITDA | C13: =Assumption!C5-Assumption!C12 -> 43617.93 | D13: =Assumption!D5-Assumption!D12 -> 27391.3 | E13: =Assumption!E5-Assumption!E12 -> 71580.98 | F13: =Assumption!F5-Assumption!F12 -> 31753.85 | G13: =Assumption!G5-Assumption!G12 -> 78191.64 | I13: Median EBITDA Margin | J13: =MEDIAN(C14:G14) -> 0.074498899
B14: EBITDA Margin % | C14: =Assumption!C13/Assumption!C5 -> 0.074498899 | D14: =Assumption!D13/Assumption!D5 -> 0.032695689 | E14: =Assumption!E13/Assumption!E5 -> 0.092713359 | F14: =Assumption!F13/Assumption!F5 -> 0.042130854 | G14: =Assumption!G13/Assumption!G5 -> 0.099681415
B15: Less: Depreciation & Amortisation | C15: ='Profit & Loss'!G22 -> 12347.58 | D15: ='Profit & Loss'!F22 -> 13181.05 | E15: ='Profit & Loss'!E22 -> 15866.11 | F15: ='Profit & Loss'!D22 -> 16777.34 | G15: ='Profit & Loss'!C22 -> 18420.24
B16: EBIT | C16: =Assumption!C13-Assumption!C15 -> 31270.35 | D16: =Assumption!D13-Assumption!D15 -> 14210.25 | E16: =Assumption!E13-Assumption!E15 -> 55714.87 | F16: =Assumption!F13-Assumption!F15 -> 14976.51 | G16: =Assumption!G13-Assumption!G15 -> 59771.4 | I16: Median EBIT Margin | J16: =MEDIAN(C17:G17) -> 0.053409381
B17: EBIT Margin % | C17: =Assumption!C16/Assumption!C5 -> 0.053409381 | D17: =Assumption!D16/Assumption!D5 -> 0.016962098 | E17: =Assumption!E16/Assumption!E5 -> 0.072163203 | F17: =Assumption!F16/Assumption!F5 -> 0.019870761 | G17: =Assumption!G16/Assumption!G5 -> 0.076198654
B18: Add: Other Income | C18: ='Profit & Loss'!G13 -> 3082.22 | D18: ='Profit & Loss'!F13 -> 4198.92 | E18: ='Profit & Loss'!E13 -> 3842.85 | F18: ='Profit & Loss'!D13 -> 3513.73 | G18: ='Profit & Loss'!C13 -> 4162.99
B19: Less: Finance Costs | C19: ='Profit & Loss'!G20 -> 5423.26 | D19: ='Profit & Loss'!F20 -> 7541.36 | E19: ='Profit & Loss'!E20 -> 7825.65 | F19: ='Profit & Loss'!D20 -> 9261.93 | G19: ='Profit & Loss'!C20 -> 8307.88
B20: PBT | C20: =Assumption!C16+Assumption!C18-Assumption!C19 -> 28929.31 | D20: =Assumption!D16+Assumption!D18-Assumption!D19 -> 10867.81 | E20: =Assumption!E16+Assumption!E18-Assumption!E19 -> 51732.07 | F20: =Assumption!F16+Assumption!F18-Assumption!F19 -> 9228.31 | G20: =Assumption!G16+Assumption!G18-Assumption!G19 -> 55626.51
B21: Less: Total Tax Expenses | C21: ='Profit & Loss'!G31 -> 8562.02 | D21: ='Profit & Loss'!F31 -> 3333.43 | E21: ='Profit & Loss'!E31 -> 14126.64 | F21: ='Profit & Loss'!D31 -> 3274.62 | G21: ='Profit & Loss'!C31 -> 13794.76
B22: Effective Tax Rate | C22: =Assumption!C21/Assumption!C20 -> 0.29596351 | D22: =Assumption!D21/Assumption!D20 -> 0.30672509 | E22: =Assumption!E21/Assumption!E20 -> 0.27307316 | F22: =Assumption!F21/Assumption!F20 -> 0.35484504 | G22: =Assumption!G21/Assumption!G20 -> 0.24798895
B23: Less: Minority Interest | C23: =-'Profit & Loss'!G35 -> 624.37 | D23: =-'Profit & Loss'!F35 -> 1912.14 | E23: =-'Profit & Loss'!E35 -> 1431.46 | F23: =-'Profit & Loss'!D35 -> 190.99 | G23: =-'Profit & Loss'!C35 -> 1581.06
B24: Net Profit - PAT | C24: =Assumption!C20-Assumption!C21-Assumption!C23 -> 19742.92 | D24: =Assumption!D20-Assumption!D21-Assumption!D23 -> 5622.24 | E24: =Assumption!E20-Assumption!E21-Assumption!E23 -> 36173.97 | F24: =Assumption!F20-Assumption!F21-Assumption!F23 -> 5762.7 | G24: =Assumption!G20-Assumption!G21-Assumption!G23 -> 40250.69 | I24: Median PAT Margin | J24: =MEDIAN(C25:G25) -> 0.03372067
B25: Net Profit Margin % | C25: =Assumption!C24/Assumption!C5 -> 0.03372067 | D25: =Assumption!D24/Assumption!D5 -> 0.0067109998 | E25: =Assumption!E24/Assumption!E5 -> 0.046853372 | F25: =Assumption!F24/Assumption!F5 -> 0.0076459224 | G25: =Assumption!G24/Assumption!G5 -> 0.051312976
B27: B. Historical Growth Analysis
B28: Average Revenue Growth (FY22-26) | C28: =AVERAGE(D6:G6) -> 0.092358924
B29: CAGR Revenue (FY22-26) | C29: =(G5/C5)^(1/4)-1 -> 0.075864886
B30: Median Revenue Growth (FY22-26) | C30: =MEDIAN(D6:G6) -> 0.0084815412
B32: C. Margin Analysis
B33: EBITDA Margin % | C33: =Assumption!C14 -> 0.074498899 | D33: =Assumption!D14 -> 0.032695689 | E33: =Assumption!E14 -> 0.092713359 | F33: =Assumption!F14 -> 0.042130854 | G33: =Assumption!G14 -> 0.099681415 | I33: Median EBITDA % | J33: =MEDIAN(C33:G33) -> 0.074498899
B34: EBIT Margin % | C34: =Assumption!C17 -> 0.053409381 | D34: =Assumption!D17 -> 0.016962098 | E34: =Assumption!E17 -> 0.072163203 | F34: =Assumption!F17 -> 0.019870761 | G34: =Assumption!G17 -> 0.076198654 | I34: Median EBIT % | J34: =MEDIAN(C34:G34) -> 0.053409381
B35: EBT Margin % | C35: =Assumption!C20/Assumption!C5 -> 0.049410913 | D35: =Assumption!D20/Assumption!D5 -> 0.012972387 | E35: =Assumption!E20/Assumption!E5 -> 0.067004587 | F35: =Assumption!F20/Assumption!F5 -> 0.012244077 | G35: =Assumption!G20/Assumption!G5 -> 0.070914605 | I35: Median EBT % | J35: =MEDIAN(C35:G35) -> 0.049410913
B36: Net Profit Margin % | C36: =Assumption!C25 -> 0.03372067 | D36: =Assumption!D25 -> 0.0067109998 | E36: =Assumption!E25 -> 0.046853372 | F36: =Assumption!F25 -> 0.0076459224 | G36: =Assumption!G25 -> 0.051312976 | I36: Median PAT % | J36: =MEDIAN(C36:G36) -> 0.03372067
B38: D. Tax Rate
B39: Effective Tax Rate | C39: =Assumption!C22 -> 0.29596351 | D39: =Assumption!D22 -> 0.30672509 | E39: =Assumption!E22 -> 0.27307316 | F39: =Assumption!F22 -> 0.35484504 | G39: =Assumption!G22 -> 0.24798895 | I39: Median Eff. Tax Rate | J39: =MEDIAN(C39:G39) -> 0.29596351
B40: Marginal Tax Rate (Standard) | C40: 0.25 | D40: 0.25 | E40: 0.25 | F40: 0.25 | G40: 0.25
B42: E. Return on Capital
B43: EBIT × (1 - Tax Rate) | C43: =Assumption!C16*(1-Assumption!C40) -> 23452.762 | D43: =Assumption!D16*(1-Assumption!D40) -> 10657.687 | E43: =Assumption!E16*(1-Assumption!E40) -> 41786.152 | F43: =Assumption!F16*(1-Assumption!F40) -> 11232.382 | G43: =Assumption!G16*(1-Assumption!G40) -> 44828.55
B44: Book Equity (Shareholders Funds) | C44: ='Balance Sheet'!G13 -> 133535.18 | D44: ='Balance Sheet'!F13 -> 139720.24 | E44: ='Balance Sheet'!E13 -> 183416.27 | F44: ='Balance Sheet'!D13 -> 186487.32 | G44: ='Balance Sheet'!C13 -> 219517.55
B45: Total Debt (LT + ST Borrowings) | C45: ='Balance Sheet'!G16+'Balance Sheet'!G22 -> 123550.1 | D45: ='Balance Sheet'!F16+'Balance Sheet'!F22 -> 140114.82 | E45: ='Balance Sheet'!E16+'Balance Sheet'!E22 -> 123453.57 | F45: ='Balance Sheet'!D16+'Balance Sheet'!D22 -> 142559.9 | G45: ='Balance Sheet'!C16+'Balance Sheet'!C22 -> 131822.39
B46: Cash & Cash Equivalents | C46: ='Balance Sheet'!G44 -> 1820.14 | D46: ='Balance Sheet'!F44 -> 2096.64 | E46: ='Balance Sheet'!E44 -> 3158.79 | F46: ='Balance Sheet'!D44 -> 3304.94 | G46: ='Balance Sheet'!C44 -> 4414.66
B47: Capital Employed (Equity + Debt + Cash) | C47: =Assumption!C44+Assumption!C45+Assumption!C46 -> 258905.42 | D47: =Assumption!D44+Assumption!D45+Assumption!D46 -> 281931.7 | E47: =Assumption!E44+Assumption!E45+Assumption!E46 -> 310028.63 | F47: =Assumption!F44+Assumption!F45+Assumption!F46 -> 332352.16 | G47: =Assumption!G44+Assumption!G45+Assumption!G46 -> 355754.6
B48: Pre-Tax Return on Capital (ROCE) | C48: =Assumption!C16/Assumption!C47 -> 0.12077905 | D48: =Assumption!D16/Assumption!D47 -> 0.050403165 | E48: =Assumption!E16/Assumption!E47 -> 0.17970879 | F48: =Assumption!F16/Assumption!F47 -> 0.045062171 | G48: =Assumption!G16/Assumption!G47 -> 0.16801301
B49: Post-Tax Return on Capital (ROCE) | C49: =Assumption!C43/Assumption!C47 -> 0.090584286 | D49: =Assumption!D43/Assumption!D47 -> 0.037802374 | E49: =Assumption!E43/Assumption!E47 -> 0.13478159 | F49: =Assumption!F43/Assumption!F47 -> 0.033796629 | G49: =Assumption!G43/Assumption!G47 -> 0.12600976 | I49: 5-Yr Avg Post-Tax ROCE | J49: =AVERAGE(C49:G49) -> 0.084594927
B50: Return on Equity (ROE) | C50: =Assumption!C24/Assumption!C44 -> 0.14784808 | D50: =Assumption!D24/Assumption!D44 -> 0.040239267 | E50: =Assumption!E24/Assumption!E44 -> 0.19722334 | F50: =Assumption!F24/Assumption!F44 -> 0.030901297 | G50: =Assumption!G24/Assumption!G44 -> 0.18335978 | I50: 5-Yr Avg ROE | J50: =AVERAGE(C50:G50) -> 0.11991435
B52: F. FCFF Driver: Implied Growth Rate
B53: Retention Ratio (1 - DPS/EPS) | C53: =IF('Profit & Loss'!G40=0,0,1-('Profit & Loss'!G43/('Balance Sheet'!G9/10)/'Profit & Loss'!G40)) -> 0.61108255 | D53: =IF('Profit & Loss'!F40=0,0,1-('Profit & Loss'!F43/('Balance Sheet'!F9/10)/'Profit & Loss'!F40)) -> 0.6571236 | E53: =IF('Profit & Loss'!E40=0,0,1-('Profit & Loss'!E43/('Balance Sheet'!E9/10)/'Profit & Loss'!E40)) -> 0.73332433 | F53: =IF('Profit & Loss'!D40=0,0,1-('Profit & Loss'!D43/('Balance Sheet'!D9/10)/'Profit & Loss'!D40)) -> 0.29998635 | G53: =IF('Profit & Loss'!C40=0,0,1-('Profit & Loss'!C43/('Balance Sheet'!C9/10)/'Profit & Loss'!C40)) -> 1
B54: Implied Growth Rate (Retention × Post-Tax ROCE) | C54: =Assumption!C53*Assumption!C49 -> 0.055354476 | D54: =Assumption!D53*Assumption!D49 -> 0.024840832 | E54: =Assumption!E53*Assumption!E49 -> 0.098838621 | F54: =Assumption!F53*Assumption!F49 -> 0.010138527 | G54: =Assumption!G53*Assumption!G49 -> 0.12600976 | I54: 5-Yr Avg Implied Growth | J54: =AVERAGE(C54:G54) -> 0.063036442
B56: G. Cost of Capital
B57: Cost of Equity (Ke) | G57: =WACC!C10 -> 0.14417478
B58: Post-Tax Cost of Debt (Kd) | G58: =WACC!C19 -> 0.047267463
B59: Weight of Equity (We) | G59: =WACC!C31 -> 0.60563428
B60: Weight of Debt (Wd) | G60: =WACC!C30 -> 0.39436572
B61: WACC | G61: =WACC!C34 -> 0.10595786

Sheet Beta
B1: Date | C1: Nifty 50 Daily Returns | D1: IOC.NS Daily Returns
B2: 44565 | C2: 1.02 | D2: 0.97
B3: 44566 | C3: 0.67 | D3: 2.81
B4: 44567 | C4: -1 | D4: 0
B5: 44568 | C5: 0.38 | D5: 1.07 | F5: Beta | G5: =G26 -> 1.0080673
B6: 44571 | C6: 1.07 | D6: 1.01
B7: 44572 | C7: 0.29 | D7: -0.92
B8: 44573 | C8: 0.87 | D8: 0.46
B9: 44574 | C9: 0.25 | D9: 1.68 | F9: SUMMARY OUTPUT
B10: 44575 | C10: -0.01 | D10: 1.77
B11: 44578 | C11: 0.29 | D11: 0.36 | F11: Regression Statistics
B12: 44579 | C12: -1.07 | D12: 0.16 | F12: Multiple R | G12: 0.50335145
B13: 44580 | C13: -0.96 | D13: 0.93 | F13: R Square | G13: 0.25336269
B14: 44581 | C14: -1.01 | D14: 0.32 | F14: Adjusted R Square | G14: 0.25268331
B15: 44582 | C15: -0.79 | D15: -3.03 | F15: Standard Error | G15: 1.5184329
B16: 44585 | C16: -2.66 | D16: -1.11 | F16: Observations | G16: 1101
B17: 44586 | C17: 0.75 | D17: 0.91
B18: 44588 | C18: -0.97 | D18: 1.03 | F18: ANOVA
B19: 44589 | C19: -0.05 | D19: 1.14 | G19: df | H19: SS | I19: MS | J19: F | K19: Significance F
B20: 44592 | C20: 1.39 | D20: 0.89 | F20: Regression | G20: 1 | H20: 859.84832 | I20: 859.84832 | J20: 372.93286 | K20: 8.9555307e-72
B21: 44593 | C21: 1.37 | D21: -2.76 | F21: Residual | G21: 1099 | H21: 2533.8966 | I21: 2.3056384
B22: 44594 | C22: 1.16 | D22: 2.22 | F22: Total | G22: 1100 | H22: 3393.7449
B23: 44595 | C23: -1.24 | D23: 0.16
B24: 44596 | C24: -0.25 | D24: -0.4 | G24: Coefficients | H24: Standard Error | I24: t Stat | J24: P-value | K24: Lower 95% | L24: Upper 95% | M24: Lower 95.0% | N24: Upper 95.0%
B25: 44599 | C25: -1.73 | D25: -1.01 | F25: Intercept | G25: 0.067918738 | H25: 0.045791566 | I25: 1.483215 | J25: 0.138304 | K25: -0.021930033 | L25: 0.15776751 | M25: -0.021930033 | N25: 0.15776751
B26: 44600 | C26: 0.31 | D26: -1.26 | F26: X Variable 1 | G26: 1.0080673 | H26: 0.052200446 | I26: 19.31147 | J26: 8.9555307e-72 | K26: 0.90564353 | L26: 1.1104911 | M26: 0.90564353 | N26: 1.1104911
B27: 44601 | C27: 1.14 | D27: 3.15
B28: 44602 | C28: 0.81 | D28: -0.91
B29: 44603 | C29: -1.31 | D29: 1.75
B30: 44606 | C30: -3.06 | D30: -4.51
B31: 44607 | C31: 3.03 | D31: 1.89
B32: 44608 | C32: -0.17 | D32: 2.32
B33: 44609 | C33: -0.1 | D33: -0.08
B34: 44610 | C34: -0.16 | D34: -0.21
B35: 44613 | C35: -0.4 | D35: -1.61
B36: 44614 | C36: -0.67 | D36: -1.76
B37: 44615 | C37: -0.17 | D37: 0.04
B38: 44616 | C38: -4.78 | D38: -6.1
... B1102: 46196 | C1102: -0.95 | D1102: -0.09

Sheet Ratio Analysis
B1: RATIO ANALYSIS
B3: Ratio | C3: 2022 | D3: 2023 | E3: 2024 | F3: 2025 | G3: 2026 | H3: 5Y Avg
B4: 1. Income Statement Ratios
B5: Revenue from Operations (Net) (₹ Cr.) | C5: ='Profit & Loss'!G10 -> 585484.22 | D5: ='Profit & Loss'!F10 -> 837764.89 | E5: ='Profit & Loss'!E10 -> 772067.59 | F5: ='Profit & Loss'!D10 -> 753695.85 | G5: ='Profit & Loss'!C10 -> 784415.43 | H5: =AVERAGE(C5:G5) -> 746685.6
B6: Revenue Growth YoY (%) | D6: ='Profit & Loss'!F10/'Profit & Loss'!G10-1 -> 0.43089235 | E6: ='Profit & Loss'!E10/'Profit & Loss'!F10-1 -> -0.078419734 | F6: ='Profit & Loss'!D10/'Profit & Loss'!E10-1 -> -0.023795507 | G6: ='Profit & Loss'!C10/'Profit & Loss'!D10-1 -> 0.04075859 | H6: =AVERAGE(D6:G6) -> 0.092358924
B7: EBITDA (₹ Cr.) | C7: ='Profit & Loss'!G12-('Profit & Loss'!G16+'Profit & Loss'!G17+'Profit & Loss'!G18+'Profit & Loss'!G19+'Profit & Loss'!G23) -> 47469.45 | D7: ='Profit & Loss'!F12-('Profit & Loss'!F16+'Profit & Loss'!F17+'Profit & Loss'!F18+'Profit & Loss'!F19+'Profit & Loss'!F23) -> 31382.32 | E7: ='Profit & Loss'!E12-('Profit & Loss'!E16+'Profit & Loss'!E17+'Profit & Loss'!E18+'Profit & Loss'!E19+'Profit & Loss'!E23) -> 75865.24 | F7: ='Profit & Loss'!D12-('Profit & Loss'!D16+'Profit & Loss'!D17+'Profit & Loss'!D18+'Profit & Loss'!D19+'Profit & Loss'!D23) -> 36163.81 | G7: ='Profit & Loss'!C12-('Profit & Loss'!C16+'Profit & Loss'!C17+'Profit & Loss'!C18+'Profit & Loss'!C19+'Profit & Loss'!C23) -> 78191.64 | H7: =AVERAGE(C7:G7) -> 53814.492
B8: EBITDA Margin (%) | C8: =('Profit & Loss'!G12-('Profit & Loss'!G16+'Profit & Loss'!G17+'Profit & Loss'!G18+'Profit & Loss'!G19+'Profit & Loss'!G23))/'Profit & Loss'!G12 -> 0.08054738 | D8: =('Profit & Loss'!F12-('Profit & Loss'!F16+'Profit & Loss'!F17+'Profit & Loss'!F18+'Profit & Loss'!F19+'Profit & Loss'!F23))/'Profit & Loss'!F12 -> 0.037281972 | E8: =('Profit & Loss'!E12-('Profit & Loss'!E16+'Profit & Loss'!E17+'Profit & Loss'!E18+'Profit & Loss'!E19+'Profit & Loss'!E23))/'Profit & Loss'!E12 -> 0.097720177 | F8: =('Profit & Loss'!D12-('Profit & Loss'!D16+'Profit & Loss'!D17+'Profit & Loss'!D18+'Profit & Loss'!D19+'Profit & Loss'!D23))/'Profit & Loss'!D12 -> 0.047702853 | G8: =('Profit & Loss'!C12-('Profit & Loss'!C16+'Profit & Loss'!C17+'Profit & Loss'!C18+'Profit & Loss'!C19+'Profit & Loss'!C23))/'Profit & Loss'!C12 -> 0.099681415 | H8: =AVERAGE(C8:G8) -> 0.072586759
B9: EBITDA Growth YoY (%) | D9: =('Profit & Loss'!F12-('Profit & Loss'!F16+'Profit & Loss'!F17+'Profit & Loss'!F18+'Profit & Loss'!F19+'Profit & Loss'!F23))/('Profit & Loss'!G12-('Profit & Loss'!G16+'Profit & Loss'!G17+'Profit & Loss'!G18+'Profit & Loss'!G19+'Profit & Loss'!G23))-1 -> -0.33889438 | E9: =('Profit & Loss'!E12-('Profit & Loss'!E16+'Profit & Loss'!E17+'Profit & Loss'!E18+'Profit & Loss'!E19+'Profit & Loss'!E23))/('Profit & Loss'!F12-('Profit & Loss'!F16+'Profit & Loss'!F17+'Profit & Loss'!F18+'Profit & Loss'!F19+'Profit & Loss'!F23))-1 -> 1.4174516 | F9: =('Profit & Loss'!D12-('Profit & Loss'!D16+'Profit & Loss'!D17+'Profit & Loss'!D18+'Profit & Loss'!D19+'Profit & Loss'!D23))/('Profit & Loss'!E12-('Profit & Loss'!E16+'Profit & Loss'!E17+'Profit & Loss'!E18+'Profit & Loss'!E19+'Profit & Loss'!E23))-1 -> -0.52331516 | G9: =('Profit & Loss'!C12-('Profit & Loss'!C16+'Profit & Loss'!C17+'Profit & Loss'!C18+'Profit & Loss'!C19+'Profit & Loss'!C23))/('Profit & Loss'!D12-('Profit & Loss'!D16+'Profit & Loss'!D17+'Profit & Loss'!D18+'Profit & Loss'!D19+'Profit & Loss'!D23))-1 -> 1.1621516 | H9: =AVERAGE(D9:G9) -> 0.42934842
B10: EBIT (₹ Cr.) | C10: =('Profit & Loss'!G12-('Profit & Loss'!G16+'Profit & Loss'!G17+'Profit & Loss'!G18+'Profit & Loss'!G19+'Profit & Loss'!G23))-'Profit & Loss'!G22 -> 35121.87 | D10: =('Profit & Loss'!F12-('Profit & Loss'!F16+'Profit & Loss'!F17+'Profit & Loss'!F18+'Profit & Loss'!F19+'Profit & Loss'!F23))-'Profit & Loss'!F22 -> 18201.27 | E10: =('Profit & Loss'!E12-('Profit & Loss'!E16+'Profit & Loss'!E17+'Profit & Loss'!E18+'Profit & Loss'!E19+'Profit & Loss'!E23))-'Profit & Loss'!E22 -> 59999.13 | F10: =('Profit & Loss'!D12-('Profit & Loss'!D16+'Profit & Loss'!D17+'Profit & Loss'!D18+'Profit & Loss'!D19+'Profit & Loss'!D23))-'Profit & Loss'!D22 -> 19386.47 | G10: =('Profit & Loss'!C12-('Profit & Loss'!C16+'Profit & Loss'!C17+'Profit & Loss'!C18+'Profit & Loss'!C19+'Profit & Loss'!C23))-'Profit & Loss'!C22 -> 59771.4 | H10: =AVERAGE(C10:G10) -> 38496.028
B11: EBIT Margin (%) | C11: =(('Profit & Loss'!G12-('Profit & Loss'!G16+'Profit & Loss'!G17+'Profit & Loss'!G18+'Profit & Loss'!G19+'Profit & Loss'!G23))-'Profit & Loss'!G22)/'Profit & Loss'!G12 -> 0.05959569 | D11: =(('Profit & Loss'!F12-('Profit & Loss'!F16+'Profit & Loss'!F17+'Profit & Loss'!F18+'Profit & Loss'!F19+'Profit & Loss'!F23))-'Profit & Loss'!F22)/'Profit & Loss'!F12 -> 0.021622979 | E11: =(('Profit & Loss'!E12-('Profit & Loss'!E16+'Profit & Loss'!E17+'Profit & Loss'!E18+'Profit & Loss'!E19+'Profit & Loss'!E23))-'Profit & Loss'!E22)/'Profit & Loss'!E12 -> 0.077283425 | F11: =(('Profit & Loss'!D12-('Profit & Loss'!D16+'Profit & Loss'!D17+'Profit & Loss'!D18+'Profit & Loss'!D19+'Profit & Loss'!D23))-'Profit & Loss'!D22)/'Profit & Loss'!D12 -> 0.025572248 | G11: =(('Profit & Loss'!C12-('Profit & Loss'!C16+'Profit & Loss'!C17+'Profit & Loss'!C18+'Profit & Loss'!C19+'Profit & Loss'!C23))-'Profit & Loss'!C22)/'Profit & Loss'!C12 -> 0.076198654 | H11: =AVERAGE(C11:G11) -> 0.052054599
B12: Finance Costs (₹ Cr.) | C12: ='Profit & Loss'!G20 -> 5423.26 | D12: ='Profit & Loss'!F20 -> 7541.36 | E12: ='Profit & Loss'!E20 -> 7825.65 | F12: ='Profit & Loss'!D20 -> 9261.93 | G12: ='Profit & Loss'!C20 -> 8307.88 | H12: =AVERAGE(C12:G12) -> 7672.016
B13: Finance Costs % Revenue | C13: ='Profit & Loss'!G20/'Profit & Loss'!G12 -> 0.0092023267 | D13: ='Profit & Loss'!F20/'Profit & Loss'!F12 -> 0.0089590817 | E13: ='Profit & Loss'!E20/'Profit & Loss'!E12 -> 0.01008003 | F13: ='Profit & Loss'!D20/'Profit & Loss'!D12 -> 0.0122172 | G13: ='Profit & Loss'!C20/'Profit & Loss'!C12 -> 0.010591174 | H13: =AVERAGE(C13:G13) -> 0.010209962
B14: Depreciation & Amortisation (₹ Cr.) | C14: ='Profit & Loss'!G22 -> 12347.58 | D14: ='Profit & Loss'!F22 -> 13181.05 | E14: ='Profit & Loss'!E22 -> 15866.11 | F14: ='Profit & Loss'!D22 -> 16777.34 | G14: ='Profit & Loss'!C22 -> 18420.24 | H14: =AVERAGE(C14:G14) -> 15318.464
B15: Depreciation % of Revenue | C15: ='Profit & Loss'!G22/'Profit & Loss'!G12 -> 0.02095169 | D15: ='Profit & Loss'!F22/'Profit & Loss'!F12 -> 0.015658993 | E15: ='Profit & Loss'!E22/'Profit & Loss'!E12 -> 0.020436752 | F15: ='Profit & Loss'!D22/'Profit & Loss'!D12 -> 0.022130605 | G15: ='Profit & Loss'!C22/'Profit & Loss'!C12 -> 0.023482761 | H15: =AVERAGE(C15:G15) -> 0.02053216
B16: PBT (₹ Cr.) | C16: ='Profit & Loss'!G27 -> 33053.06 | D16: ='Profit & Loss'!F27 -> 14175.5 | E16: ='Profit & Loss'!E27 -> 55741.86 | F16: ='Profit & Loss'!D27 -> 15303.02 | G16: ='Profit & Loss'!C27 -> 54496.52 | H16: =AVERAGE(C16:G16) -> 34553.992
B17: PBT Margin (%) | C17: ='Profit & Loss'!G27/'Profit & Loss'!G12 -> 0.05608528 | D17: ='Profit & Loss'!F27/'Profit & Loss'!F12 -> 0.016840393 | E17: ='Profit & Loss'!E27/'Profit & Loss'!E12 -> 0.071799739 | F17: ='Profit & Loss'!D27/'Profit & Loss'!D12 -> 0.020185863 | G17: ='Profit & Loss'!C27/'Profit & Loss'!C12 -> 0.069474054 | H17: =AVERAGE(C17:G17) -> 0.046877066
B18: Net Profit (Consolidated PAT) (₹ Cr.) | C18: ='Profit & Loss'!G37 -> 25102.23 | D18: ='Profit & Loss'!F37 -> 9792.12 | E18: ='Profit & Loss'!E37 -> 41729.69 | F18: ='Profit & Loss'!D37 -> 13597.84 | G18: ='Profit & Loss'!C37 -> 42096.26 | H18: =AVERAGE(C18:G18) -> 26463.628
B19: Net Profit Margin (%) | C19: ='Profit & Loss'!G37/'Profit & Loss'!G12 -> 0.042594108 | D19: ='Profit & Loss'!F37/'Profit & Loss'!F12 -> 0.011632969 | E19: ='Profit & Loss'!E37/'Profit & Loss'!E12 -> 0.053751002 | F19: ='Profit & Loss'!D37/'Profit & Loss'!D12 -> 0.017936599 | G19: ='Profit & Loss'!C37/'Profit & Loss'!C12 -> 0.053665772 | H19: =AVERAGE(C19:G19) -> 0.03591609
B20: PAT Growth YoY (%) | D20: ='Profit & Loss'!F37/'Profit & Loss'!G37-1 -> -0.60991035 | E20: ='Profit & Loss'!E37/'Profit & Loss'!F37-1 -> 3.2615583 | F20: ='Profit & Loss'!D37/'Profit & Loss'!E37-1 -> -0.67414472 | G20: ='Profit & Loss'!C37/'Profit & Loss'!D37-1 -> 2.0958049 | H20: =AVERAGE(D20:G20) -> 1.018327
B21: Basic EPS (₹) | C21: ='Profit & Loss'!G40 -> 27 | D21: ='Profit & Loss'!F40 -> 7 | E21: ='Profit & Loss'!E40 -> 30 | F21: ='Profit & Loss'!D40 -> 10 | G21: ='Profit & Loss'!C40 -> 31 | H21: =AVERAGE(C21:G21) -> 21
B22: EPS Growth YoY (%) | D22: ='Profit & Loss'!F40/'Profit & Loss'!G40-1 -> -0.74074074 | E22: ='Profit & Loss'!E40/'Profit & Loss'!F40-1 -> 3.2857143 | F22: ='Profit & Loss'!D40/'Profit & Loss'!E40-1 -> -0.66666667 | G22: ='Profit & Loss'!C40/'Profit & Loss'!D40-1 -> 2.1 | H22: =AVERAGE(D22:G22) -> 0.99457672
B24: 2. Balance Sheet Ratios
B25: Total Shareholders Funds (₹ Cr.) | C25: ='Balance Sheet'!G13 -> 133535.18 | D25: ='Balance Sheet'!F13 -> 139720.24 | E25: ='Balance Sheet'!E13 -> 183416.27 | F25: ='Balance Sheet'!D13 -> 186487.32 | G25: ='Balance Sheet'!C13 -> 219517.55 | H25: =AVERAGE(C25:G25) -> 172535.31
B26: Total Equity incl. Minority Interest (₹ Cr.) | C26: ='Balance Sheet'!G13+'Balance Sheet'!G14 -> 135126.65 | D26: ='Balance Sheet'!F13+'Balance Sheet'!F14 -> 143214.34 | E26: ='Balance Sheet'!E13+'Balance Sheet'!E14 -> 188162.98 | F26: ='Balance Sheet'!D13+'Balance Sheet'!D14 -> 191024.66 | G26: ='Balance Sheet'!C13+'Balance Sheet'!C14 -> 225547.11 | H26: =AVERAGE(C26:G26) -> 176615.15
B27: Long Term Borrowings (₹ Cr.) | C27: ='Balance Sheet'!G16 -> 55944.54 | D27: ='Balance Sheet'!F16 -> 63312.94 | E27: ='Balance Sheet'!E16 -> 46792.9 | F27: ='Balance Sheet'!D16 -> 51755.75 | G27: ='Balance Sheet'!C16 -> 63652.1 | H27: =AVERAGE(C27:G27) -> 56291.646
B28: Short Term Borrowings (₹ Cr.) | C28: ='Balance Sheet'!G22 -> 67605.56 | D28: ='Balance Sheet'!F22 -> 76801.88 | E28: ='Balance Sheet'!E22 -> 76660.67 | F28: ='Balance Sheet'!D22 -> 90804.15 | G28: ='Balance Sheet'!C22 -> 68170.29 | H28: =AVERAGE(C28:G28) -> 76008.51
B29: Gross Debt (₹ Cr.) | C29: ='Balance Sheet'!G16+'Balance Sheet'!G22 -> 123550.1 | D29: ='Balance Sheet'!F16+'Balance Sheet'!F22 -> 140114.82 | E29: ='Balance Sheet'!E16+'Balance Sheet'!E22 -> 123453.57 | F29: ='Balance Sheet'!D16+'Balance Sheet'!D22 -> 142559.9 | G29: ='Balance Sheet'!C16+'Balance Sheet'!C22 -> 131822.39 | H29: =AVERAGE(C29:G29) -> 132300.16
B30: Cash & Cash Equivalents (₹ Cr.) | C30: ='Balance Sheet'!G44 -> 1820.14 | D30: ='Balance Sheet'!F44 -> 2096.64 | E30: ='Balance Sheet'!E44 -> 3158.79 | F30: ='Balance Sheet'!D44 -> 3304.94 | G30: ='Balance Sheet'!C44 -> 4414.66 | H30: =AVERAGE(C30:G30) -> 2959.034
B31: Net Debt (₹ Cr.) | C31: ='Balance Sheet'!G16+'Balance Sheet'!G22-'Balance Sheet'!G44 -> 121729.96 | D31: ='Balance Sheet'!F16+'Balance Sheet'!F22-'Balance Sheet'!F44 -> 138018.18 | E31: ='Balance Sheet'!E16+'Balance Sheet'!E22-'Balance Sheet'!E44 -> 120294.78 | F31: ='Balance Sheet'!D16+'Balance Sheet'!D22-'Balance Sheet'!D44 -> 139254.96 | G31: ='Balance Sheet'!C16+'Balance Sheet'!C22-'Balance Sheet'!C44 -> 127407.73 | H31: =AVERAGE(C31:G31) -> 129341.12
B32: Inventories (₹ Cr.) | C32: ='Balance Sheet'!G42 -> 111736.51 | D32: ='Balance Sheet'!F42 -> 121107.58 | E32: ='Balance Sheet'!E42 -> 121375.83 | F32: ='Balance Sheet'!D42 -> 113878.49 | G32: ='Balance Sheet'!C42 -> 117132.72 | H32: =AVERAGE(C32:G32) -> 117046.23
B33: Trade Receivables (₹ Cr.) | C33: ='Balance Sheet'!G43 -> 18700.42 | D33: ='Balance Sheet'!F43 -> 16271.21 | E33: ='Balance Sheet'!E43 -> 13831.45 | F33: ='Balance Sheet'!D43 -> 18550.96 | G33: ='Balance Sheet'!C43 -> 14634.83 | H33: =AVERAGE(C33:G33) -> 16397.774
B34: Trade Payables (₹ Cr.) | C34: ='Balance Sheet'!G23 -> 49045.91 | D34: ='Balance Sheet'!F23 -> 54734.1 | E34: ='Balance Sheet'!E23 -> 59454.1 | F34: ='Balance Sheet'!D23 -> 60534.94 | G34: ='Balance Sheet'!C23 -> 57368.69 | H34: =AVERAGE(C34:G34) -> 56227.548
B35: Total Assets (₹ Cr.) | C35: ='Balance Sheet'!G48 -> 410624.85 | D35: ='Balance Sheet'!F48 -> 441762.09 | E35: ='Balance Sheet'!E48 -> 482362 | F35: ='Balance Sheet'!D48 -> 506867.05 | G35: ='Balance Sheet'!C48 -> 528954.96 | H35: =AVERAGE(C35:G35) -> 474114.19
B36: Fixed Assets (Net Block) (₹ Cr.) | C36: ='Balance Sheet'!G34 -> 207982.58 | D36: ='Balance Sheet'!F34 -> 231180 | E36: ='Balance Sheet'!E34 -> 257029.17 | F36: ='Balance Sheet'!D34 -> 279062.41 | G36: ='Balance Sheet'!C34 -> 294617.69 | H36: =AVERAGE(C36:G36) -> 253974.37
B38: 3. Return Ratios
B39: RoE: PAT / Shareholders Funds (%) | C39: ='Profit & Loss'!G37/'Balance Sheet'!G13 -> 0.18798215 | D39: ='Profit & Loss'!F37/'Balance Sheet'!F13 -> 0.070083762 | E39: ='Profit & Loss'!E37/'Balance Sheet'!E13 -> 0.22751357 | F39: ='Profit & Loss'!D37/'Balance Sheet'!D13 -> 0.072915628 | G39: ='Profit & Loss'!C37/'Balance Sheet'!C13 -> 0.19176717 | H39: =AVERAGE(C39:G39) -> 0.15005246
B40: RoA: PAT / Total Assets (%) | C40: ='Profit & Loss'!G37/'Balance Sheet'!G48 -> 0.061131785 | D40: ='Profit & Loss'!F37/'Balance Sheet'!F48 -> 0.022166049 | E40: ='Profit & Loss'!E37/'Balance Sheet'!E48 -> 0.086511147 | F40: ='Profit & Loss'!D37/'Balance Sheet'!D48 -> 0.026827232 | G40: ='Profit & Loss'!C37/'Balance Sheet'!C48 -> 0.079583827 | H40: =AVERAGE(C40:G40) -> 0.055244008
B41: RoCE: EBIT / Capital Employed (%) | C41: =(('Profit & Loss'!G12-('Profit & Loss'!G16+'Profit & Loss'!G17+'Profit & Loss'!G18+'Profit & Loss'!G19+'Profit & Loss'!G23))-'Profit & Loss'!G22)/('Balance Sheet'!G48-'Balance Sheet'!G26) -> 0.16076279 | D41: =(('Profit & Loss'!F12-('Profit & Loss'!F16+'Profit & Loss'!F17+'Profit & Loss'!F18+'Profit & Loss'!F19+'Profit & Loss'!F23))-'Profit & Loss'!F22)/('Balance Sheet'!F48-'Balance Sheet'!F26) -> 0.07741803 | E41: =(('Profit & Loss'!E12-('Profit & Loss'!E16+'Profit & Loss'!E17+'Profit & Loss'!E18+'Profit & Loss'!E19+'Profit & Loss'!E23))-'Profit & Loss'!E22)/('Balance Sheet'!E48-'Balance Sheet'!E26) -> 0.2255962 | F41: =(('Profit & Loss'!D12-('Profit & Loss'!D16+'Profit & Loss'!D17+'Profit & Loss'!D18+'Profit & Loss'!D19+'Profit & Loss'!D23))-'Profit & Loss'!D22)/('Balance Sheet'!D48-'Balance Sheet'!D26) -> 0.070176596 | G41: =(('Profit & Loss'!C12-('Profit & Loss'!C16+'Profit & Loss'!C17+'Profit & Loss'!C18+'Profit & Loss'!C19+'Profit & Loss'!C23))-'Profit & Loss'!C22)/('Balance Sheet'!C48-'Balance Sheet'!C26) -> 0.18810876 | H41: =AVERAGE(C41:G41) -> 0.14441247
B43: 4. Leverage & Coverage Ratios
B44: Gross Debt / Equity (x) | C44: =('Balance Sheet'!G16+'Balance Sheet'!G22)/('Balance Sheet'!G13+'Balance Sheet'!G14) -> 0.91432815 | D44: =('Balance Sheet'!F16+'Balance Sheet'!F22)/('Balance Sheet'!F13+'Balance Sheet'!F14) -> 0.97835747 | E44: =('Balance Sheet'!E16+'Balance Sheet'!E22)/('Balance Sheet'!E13+'Balance Sheet'!E14) -> 0.65609914 | F44: =('Balance Sheet'!D16+'Balance Sheet'!D22)/('Balance Sheet'!D13+'Balance Sheet'!D14) -> 0.74629056 | G44: =('Balance Sheet'!C16+'Balance Sheet'!C22)/('Balance Sheet'!C13+'Balance Sheet'!C14) -> 0.58445613 | H44: =AVERAGE(C44:G44) -> 0.77590629
B45: Net Debt / Equity (x) | C45: =('Balance Sheet'!G16+'Balance Sheet'!G22-'Balance Sheet'!G44)/('Balance Sheet'!G13+'Balance Sheet'!G14) -> 0.90085827 | D45: =('Balance Sheet'!F16+'Balance Sheet'!F22-'Balance Sheet'!F44)/('Balance Sheet'!F13+'Balance Sheet'!F14) -> 0.9637176 | E45: =('Balance Sheet'!E16+'Balance Sheet'!E22-'Balance Sheet'!E44)/('Balance Sheet'!E13+'Balance Sheet'!E14) -> 0.63931162 | F45: =('Balance Sheet'!D16+'Balance Sheet'!D22-'Balance Sheet'!D44)/('Balance Sheet'!D13+'Balance Sheet'!D14) -> 0.72898944 | G45: =('Balance Sheet'!C16+'Balance Sheet'!C22-'Balance Sheet'!C44)/('Balance Sheet'!C13+'Balance Sheet'!C14) -> 0.56488301 | H45: =AVERAGE(C45:G45) -> 0.75955199
B46: Net Debt / EBITDA (x) | C46: =('Balance Sheet'!G16+'Balance Sheet'!G22-'Balance Sheet'!G44)/('Profit & Loss'!G12-('Profit & Loss'!G16+'Profit & Loss'!G17+'Profit & Loss'!G18+'Profit & Loss'!G19+'Profit & Loss'!G23)) -> 2.5643853 | D46: =('Balance Sheet'!F16+'Balance Sheet'!F22-'Balance Sheet'!F44)/('Profit & Loss'!F12-('Profit & Loss'!F16+'Profit & Loss'!F17+'Profit & Loss'!F18+'Profit & Loss'!F19+'Profit & Loss'!F23)) -> 4.3979597 | E46: =('Balance Sheet'!E16+'Balance Sheet'!E22-'Balance Sheet'!E44)/('Profit & Loss'!E12-('Profit & Loss'!E16+'Profit & Loss'!E17+'Profit & Loss'!E18+'Profit & Loss'!E19+'Profit & Loss'!E23)) -> 1.5856376 | F46: =('Balance Sheet'!D16+'Balance Sheet'!D22-'Balance Sheet'!D44)/('Profit & Loss'!D12-('Profit & Loss'!D16+'Profit & Loss'!D17+'Profit & Loss'!D18+'Profit & Loss'!D19+'Profit & Loss'!D23)) -> 3.8506717 | G46: =('Balance Sheet'!C16+'Balance Sheet'!C22-'Balance Sheet'!C44)/('Profit & Loss'!C12-('Profit & Loss'!C16+'Profit & Loss'!C17+'Profit & Loss'!C18+'Profit & Loss'!C19+'Profit & Loss'!C23)) -> 1.6294291 | H46: =AVERAGE(C46:G46) -> 2.8056167
B47: Interest Coverage: EBIT / Finance Costs (x) | C47: =(('Profit & Loss'!G12-('Profit & Loss'!G16+'Profit & Loss'!G17+'Profit & Loss'!G18+'Profit & Loss'!G19+'Profit & Loss'!G23))-'Profit & Loss'!G22)/'Profit & Loss'!G20 -> 6.4761546 | D47: =(('Profit & Loss'!F12-('Profit & Loss'!F16+'Profit & Loss'!F17+'Profit & Loss'!F18+'Profit & Loss'!F19+'Profit & Loss'!F23))-'Profit & Loss'!F22)/'Profit & Loss'!F20 -> 2.4135262 | E47: =(('Profit & Loss'!E12-('Profit & Loss'!E16+'Profit & Loss'!E17+'Profit & Loss'!E18+'Profit & Loss'!E19+'Profit & Loss'!E23))-'Profit & Loss'!E22)/'Profit & Loss'!E20 -> 7.6669836 | F47: =(('Profit & Loss'!D12-('Profit & Loss'!D16+'Profit & Loss'!D17+'Profit & Loss'!D18+'Profit & Loss'!D19+'Profit & Loss'!D23))-'Profit & Loss'!D22)/'Profit & Loss'!D20 -> 2.093135 | G47: =(('Profit & Loss'!C12-('Profit & Loss'!C16+'Profit & Loss'!C17+'Profit & Loss'!C18+'Profit & Loss'!C19+'Profit & Loss'!C23))-'Profit & Loss'!C22)/'Profit & Loss'!C20 -> 7.194543 | H47: =AVERAGE(C47:G47) -> 5.1688685
B48: Gross Debt / Total Assets (%) | C48: =('Balance Sheet'!G16+'Balance Sheet'!G22)/'Balance Sheet'!G48 -> 0.30088315 | D48: =('Balance Sheet'!F16+'Balance Sheet'!F22)/'Balance Sheet'!F48 -> 0.31717258 | E48: =('Balance Sheet'!E16+'Balance Sheet'!E22)/'Balance Sheet'!E48 -> 0.25593552 | F48: =('Balance Sheet'!D16+'Balance Sheet'!D22)/'Balance Sheet'!D48 -> 0.28125699 | G48: =('Balance Sheet'!C16+'Balance Sheet'!C22)/'Balance Sheet'!C48 -> 0.24921288 | H48: =AVERAGE(C48:G48) -> 0.28089222
B50: 5. Asset & Efficiency / Working Capital Ratios
B51: Asset Turnover: Revenue / Total Assets (x) | C51: ='Profit & Loss'!G12/'Balance Sheet'!G48 -> 1.4352169 | D51: ='Profit & Loss'!F12/'Balance Sheet'!F48 -> 1.9054508 | E51: ='Profit & Loss'!E12/'Balance Sheet'!E48 -> 1.6094797 | F51: ='Profit & Loss'!D12/'Balance Sheet'!D48 -> 1.4956699 | G51: ='Profit & Loss'!C12/'Balance Sheet'!C48 -> 1.4829532 | H51: =AVERAGE(C51:G51) -> 1.5857541
B52: Fixed Asset Turnover (x) | C52: ='Profit & Loss'!G12/'Balance Sheet'!G34 -> 2.8335822 | D52: ='Profit & Loss'!F12/'Balance Sheet'!F34 -> 3.6411277 | E52: ='Profit & Loss'!E12/'Balance Sheet'!E34 -> 3.0204815 | F52: ='Profit & Loss'!D12/'Balance Sheet'!D34 -> 2.7166174 | G52: ='Profit & Loss'!C12/'Balance Sheet'!C34 -> 2.6624858 | H52: =AVERAGE(C52:G52) -> 2.9748589
B53: Debtor Days (days) | C53: ='Balance Sheet'!G43/'Profit & Loss'!G12*365 -> 11.581944 | D53: ='Balance Sheet'!F43/'Profit & Loss'!F12*365 -> 7.0554796 | E53: ='Balance Sheet'!E43/'Profit & Loss'!E12*365 -> 6.5028238 | F53: ='Balance Sheet'!D43/'Profit & Loss'!D12*365 -> 8.9316034 | G53: ='Balance Sheet'!C43/'Profit & Loss'!C12*365 -> 6.809801 | H53: =AVERAGE(C53:G53) -> 8.1763303
B54: Inventory Days (days) | C54: ='Balance Sheet'!G42/('Profit & Loss'!G16+'Profit & Loss'!G17+'Profit & Loss'!G18)*365 -> 83.753123 | D54: ='Balance Sheet'!F42/('Profit & Loss'!F16+'Profit & Loss'!F17+'Profit & Loss'!F18)*365 -> 59.125465 | E54: ='Balance Sheet'!E42/('Profit & Loss'!E16+'Profit & Loss'!E17+'Profit & Loss'!E18)*365 -> 69.35228 | F54: ='Balance Sheet'!D42/('Profit & Loss'!D16+'Profit & Loss'!D17+'Profit & Loss'!D18)*365 -> 63.28649 | G54: ='Balance Sheet'!C42/('Profit & Loss'!C16+'Profit & Loss'!C17+'Profit & Loss'!C18)*365 -> 67.527776 | H54: =AVERAGE(C54:G54) -> 68.609027
B55: Creditor / Payable Days (days) | C55: ='Balance Sheet'!G23/('Profit & Loss'!G16+'Profit & Loss'!G17+'Profit & Loss'!G18)*365 -> 36.76281 | D55: ='Balance Sheet'!F23/('Profit & Loss'!F16+'Profit & Loss'!F17+'Profit & Loss'!F18)*365 -> 26.721524 | E55: ='Balance Sheet'!E23/('Profit & Loss'!E16+'Profit & Loss'!E17+'Profit & Loss'!E18)*365 -> 33.971157 | F55: ='Balance Sheet'!D23/('Profit & Loss'!D16+'Profit & Loss'!D17+'Profit & Loss'!D18)*365 -> 33.641506 | G55: ='Balance Sheet'!C23/('Profit & Loss'!C16+'Profit & Loss'!C17+'Profit & Loss'!C18)*365 -> 33.073423 | H55: =AVERAGE(C55:G55) -> 32.834084
B56: Cash Conversion Cycle (days) | C56: =C53+C54-C55 -> 58.572256 | D56: =D53+D54-D55 -> 39.459421 | E56: =E53+E54-E55 -> 41.883946 | F56: =F53+F54-F55 -> 38.576588 | G56: =G53+G54-G55 -> 41.264154 | H56: =AVERAGE(C56:G56) -> 43.951273
B58: 6. Growth Ratios (YoY)
B59: Revenue Growth YoY (%) | D59: ='Profit & Loss'!F12/'Profit & Loss'!G12-1 -> 0.42831302 | E59: ='Profit & Loss'!E12/'Profit & Loss'!F12-1 -> -0.077699555 | F59: ='Profit & Loss'!D12/'Profit & Loss'!E12-1 -> -0.023502282 | G59: ='Profit & Loss'!C12/'Profit & Loss'!D12-1 -> 0.034704417 | H59: =AVERAGE(D59:G59) -> 0.0904539
B60: EBITDA Growth YoY (%) | D60: =('Profit & Loss'!F12-('Profit & Loss'!F16+'Profit & Loss'!F17+'Profit & Loss'!F18+'Profit & Loss'!F19+'Profit & Loss'!F23))/('Profit & Loss'!G12-('Profit & Loss'!G16+'Profit & Loss'!G17+'Profit & Loss'!G18+'Profit & Loss'!G19+'Profit & Loss'!G23))-1 -> -0.33889438 | E60: =('Profit & Loss'!E12-('Profit & Loss'!E16+'Profit & Loss'!E17+'Profit & Loss'!E18+'Profit & Loss'!E19+'Profit & Loss'!E23))/('Profit & Loss'!F12-('Profit & Loss'!F16+'Profit & Loss'!F17+'Profit & Loss'!F18+'Profit & Loss'!F19+'Profit & Loss'!F23))-1 -> 1.4174516 | F60: =('Profit & Loss'!D12-('Profit & Loss'!D16+'Profit & Loss'!D17+'Profit & Loss'!D18+'Profit & Loss'!D19+'Profit & Loss'!D23))/('Profit & Loss'!E12-('Profit & Loss'!E16+'Profit & Loss'!E17+'Profit & Loss'!E18+'Profit & Loss'!E19+'Profit & Loss'!E23))-1 -> -0.52331516 | G60: =('Profit & Loss'!C12-('Profit & Loss'!C16+'Profit & Loss'!C17+'Profit & Loss'!C18+'Profit & Loss'!C19+'Profit & Loss'!C23))/('Profit & Loss'!D12-('Profit & Loss'!D16+'Profit & Loss'!D17+'Profit & Loss'!D18+'Profit & Loss'!D19+'Profit & Loss'!D23))-1 -> 1.1621516 | H60: =AVERAGE(D60:G60) -> 0.42934842
B61: PAT Growth YoY (%) | D61: ='Profit & Loss'!F37/'Profit & Loss'!G37-1 -> -0.60991035 | E61: ='Profit & Loss'!E37/'Profit & Loss'!F37-1 -> 3.2615583 | F61: ='Profit & Loss'!D37/'Profit & Loss'!E37-1 -> -0.67414472 | G61: ='Profit & Loss'!C37/'Profit & Loss'!D37-1 -> 2.0958049 | H61: =AVERAGE(D61:G61) -> 1.018327
B62: EPS Growth YoY (%) | D62: ='Profit & Loss'!F40/'Profit & Loss'!G40-1 -> -0.74074074 | E62: ='Profit & Loss'!E40/'Profit & Loss'!F40-1 -> 3.2857143 | F62: ='Profit & Loss'!D40/'Profit & Loss'!E40-1 -> -0.66666667 | G62: ='Profit & Loss'!C40/'Profit & Loss'!D40-1 -> 2.1 | H62: =AVERAGE(D62:G62) -> 0.99457672
B64: 7. Per Share Data
B65: Basic EPS (₹) | C65: ='Profit & Loss'!G40 -> 27 | D65: ='Profit & Loss'!F40 -> 7 | E65: ='Profit & Loss'!E40 -> 30 | F65: ='Profit & Loss'!D40 -> 10 | G65: ='Profit & Loss'!C40 -> 31 | H65: =AVERAGE(C65:G65) -> 21
B66: Diluted EPS (₹) | C66: ='Profit & Loss'!G41 -> 27 | D66: ='Profit & Loss'!F41 -> 7 | E66: ='Profit & Loss'!E41 -> 30 | F66: ='Profit & Loss'!D41 -> 10 | G66: ='Profit & Loss'!C41 -> 31 | H66: =AVERAGE(C66:G66) -> 21
B67: Book Value per Share (₹) | C67: =IF('Profit & Loss'!G40<>0,'Balance Sheet'!G13/('Balance Sheet'!G9/10),0) -> 145.44668 | D67: =IF('Profit & Loss'!F40<>0,'Balance Sheet'!F13/('Balance Sheet'!F9/10),0) -> 101.45564 | E67: =IF('Profit & Loss'!E40<>0,'Balance Sheet'!E13/('Balance Sheet'!E9/10),0) -> 133.18482 | F67: =IF('Profit & Loss'!D40<>0,'Balance Sheet'!D13/('Balance Sheet'!D9/10),0) -> 135.41481 | G67: =IF('Profit & Loss'!C40<>0,'Balance Sheet'!C13/('Balance Sheet'!C9/10),0) -> 159.39919 | H67: =AVERAGE(C67:G67) -> 134.98023
B68: Net Debt per Share (₹) | C68: =IF('Profit & Loss'!G40<>0,('Balance Sheet'!G16+'Balance Sheet'!G22-'Balance Sheet'!G44)/('Balance Sheet'!G9/10),0) -> 132.58842 | D68: =IF('Profit & Loss'!F40<>0,('Balance Sheet'!F16+'Balance Sheet'!F22-'Balance Sheet'!F44)/('Balance Sheet'!F9/10),0) -> 100.21971 | E68: =IF('Profit & Loss'!E40<>0,('Balance Sheet'!E16+'Balance Sheet'!E22-'Balance Sheet'!E44)/('Balance Sheet'!E9/10),0) -> 87.350148 | F68: =IF('Profit & Loss'!D40<>0,('Balance Sheet'!D16+'Balance Sheet'!D22-'Balance Sheet'!D44)/('Balance Sheet'!D9/10),0) -> 101.11778 | G68: =IF('Profit & Loss'!C40<>0,('Balance Sheet'!C16+'Balance Sheet'!C22-'Balance Sheet'!C44)/('Balance Sheet'!C9/10),0) -> 92.515104 | H68: =AVERAGE(C68:G68) -> 102.75823
B69: Dividend per Share (₹) | C69: =IF('Balance Sheet'!G9>0,'Profit & Loss'!G43/('Balance Sheet'!G9/10),0) -> 10.500771 | D69: =IF('Balance Sheet'!F9>0,'Profit & Loss'!F43/('Balance Sheet'!F9/10),0) -> 2.4001348 | E69: =IF('Balance Sheet'!E9>0,'Profit & Loss'!E43/('Balance Sheet'!E9/10),0) -> 8.0002701 | F69: =IF('Balance Sheet'!D9>0,'Profit & Loss'!D43/('Balance Sheet'!D9/10),0) -> 7.0001365 | G69: =IF('Balance Sheet'!C9>0,'Profit & Loss'!C43/('Balance Sheet'!C9/10),0) -> 0 | H69: =AVERAGE(C69:G69) -> 5.5802625
B70: Dividend Payout Ratio (%) | C70: =IF('Profit & Loss'!G43>0,'Profit & Loss'!G43/'Profit & Loss'!G37,0) -> 0.3840615 | D70: =IF('Profit & Loss'!F43>0,'Profit & Loss'!F43/'Profit & Loss'!F37,0) -> 0.33755305 | E70: =IF('Profit & Loss'!E43>0,'Profit & Loss'!E43/'Profit & Loss'!E37,0) -> 0.26402353 | F70: =IF('Profit & Loss'!D43>0,'Profit & Loss'!D43/'Profit & Loss'!D37,0) -> 0.70895672 | G70: =IF('Profit & Loss'!C43>0,'Profit & Loss'!C43/'Profit & Loss'!C37,0) -> 0 | H70: =AVERAGE(C70:G70) -> 0.33891896

Sheet Relative Valuation
B1: Relative Valuation
B3: Comparable Company Valuation
B4: Company Name | D4: Market Data | K4: Financials (FY26, ₹ Cr.) | P4: Valuation Multiples
B5: Company Name | D5: No. of Shares (Cr.) | E5: Share Price (₹) | F5: Equity Value (₹ Cr.) | G5: Debt (₹ Cr.) | H5: Cash (₹ Cr.) | I5: Enterprise Value (₹ Cr.) | K5: Revenue (₹ Cr.) | L5: EBITDA (₹ Cr.) | M5: Net Profit (₹ Cr.) | N5: EPS (₹) | P5: EV/Revenue | Q5: EV/EBITDA | R5: P/E Ratio
B6: Indian Oil Corp. | D6: ='Balance Sheet'!C9/WACC!C23 -> 1377.156 | E6: =WACC!C25 -> 147 | F6: =D6*E6 -> 202441.93 | G6: ='Balance Sheet'!C16+'Balance Sheet'!C22 -> 131822.39 | H6: ='Balance Sheet'!C44 -> 4414.66 | I6: =F6+G6-H6 -> 329849.66 | K6: ='Profit & Loss'!C12 -> 784415.43 | L6: ='Profit & Loss'!C25+'Profit & Loss'!C20+'Profit & Loss'!C22 -> 81224.64 | M6: ='Profit & Loss'!C37 -> 42096.26 | N6: ='Profit & Loss'!C40 -> 31 | P6: =I6/K6 -> 0.42050379 | Q6: =I6/L6 -> 4.0609557 | R6: =E6/N6 -> 4.7419355
B7: BPCL | D7: 216.22 | E7: 309.75 | F7: =D7*E7 -> 66974.145 | G7: 54424.42 | H7: 8000 | I7: =F7+G7-H7 -> 113398.57 | K7: 466045 | L7: 18500 | M7: 6960 | N7: 32.19 | P7: =I7/K7 -> 0.24332106 | Q7: =I7/L7 -> 6.1296522 | R7: =E7/N7 -> 9.6225536
B8: HPCL | D8: 213.67 | E8: 409.25 | F8: =D8*E8 -> 87444.447 | G8: 55964.43 | H8: 4500 | I8: =F8+G8-H8 -> 138908.88 | K8: 471200 | L8: 21800 | M8: 8200 | N8: 38.38 | P8: =I8/K8 -> 0.29479813 | Q8: =I8/L8 -> 6.3719669 | R8: =E8/N8 -> 10.663106
B9: MRPL | D9: 175.19 | E9: 153.93 | F9: =D9*E9 -> 26966.997 | G9: 15341.02 | H9: 600 | I9: =F9+G9-H9 -> 41708.017 | K9: 90200 | L9: 6800 | M9: 2050 | N9: 11.7 | P9: =I9/K9 -> 0.46239486 | Q9: =I9/L9 -> 6.1335319 | R9: =E9/N9 -> 13.15641
B10: CPCL | D10: 14.92 | E10: 1102.2 | F10: =D10*E10 -> 16444.824 | G10: 1964.16 | H10: 300 | I10: =F10+G10-H10 -> 18108.984 | K10: 47500 | L10: 2600 | M10: 950 | N10: 63.67 | P10: =I10/K10 -> 0.38124177 | Q10: =I10/L10 -> 6.9649938 | R10: =E10/N10 -> 17.311136
B11: ONGC | D11: 630.36 | E11: 242.45 | F11: =D11*E11 -> 152830.78 | G11: 31500 | H11: 22000 | I11: =F11+G11-H11 -> 162330.78 | K11: 694500 | L11: 98000 | M11: 36800 | N11: 58.38 | P11: =I11/K11 -> 0.23373763 | Q11: =I11/L11 -> 1.6564366 | R11: =E11/N11 -> 4.1529633
N12: Average | P12: =AVERAGE(P6:P11) -> 0.33933287 | Q12: =AVERAGE(Q6:Q11) -> 5.2195895 | R12: =AVERAGE(R6:R11) -> 9.9413507
B13: M&M Industry Comparable Comps | F13: EV/Revenue | G13: EV/EBITDA | H13: P/E | N13: Median | P13: =MEDIAN(P6:P11) -> 0.33801995 | Q13: =MEDIAN(Q6:Q11) -> 6.131592 | R13: =MEDIAN(R6:R11) -> 10.14283
B14: Implied Enterprise Value | F14: =P13*K6 -> 265148.06 | G14: =Q13*L6 -> 498036.35 | H14: =R13*N6*D6 -> 433016.02
B15: Net Debt (₹ Cr.) | F15: ='Balance Sheet'!C16+'Balance Sheet'!C22-'Balance Sheet'!C44 -> 127407.73 | G15: ='Balance Sheet'!C16+'Balance Sheet'!C22-'Balance Sheet'!C44 -> 127407.73 | H15: ='Balance Sheet'!C16+'Balance Sheet'!C22-'Balance Sheet'!C44 -> 127407.73 | N15: Max | P15: =MAX(P6:P11) -> 0.46239486 | Q15: =MAX(Q6:Q11) -> 6.9649938 | R15: =MAX(R6:R11) -> 17.311136
B16: Implied Market Cap (₹ Cr.) | F16: =F14-F15 -> 137740.33 | G16: =G14-G15 -> 370628.62 | H16: =H14-H15 -> 305608.29 | N16: 75th %ile | P16: =PERCENTILE(P6:P11,0.75) -> 0.41068829 | Q16: =PERCENTILE(Q6:Q11,0.75) -> 6.3123581 | R16: =PERCENTILE(R6:R11,0.75) -> 12.533084
B17: Shares Outstanding (Cr.) | F17: ='Balance Sheet'!C9/WACC!C23 -> 1377.156 | G17: ='Balance Sheet'!C9/WACC!C23 -> 1377.156 | H17: ='Balance Sheet'!C9/WACC!C23 -> 1377.156
B18: Implied Value per Share (₹) | F18: =F16/F17 -> 100.01796 | G18: =G16/G17 -> 269.1261 | H18: =H16/H17 -> 221.91262 | N18: 25th %ile | P18: =PERCENTILE(P6:P11,0.25) -> 0.25619033 | Q18: =PERCENTILE(Q6:Q11,0.25) -> 4.5781298 | R18: =PERCENTILE(R6:R11,0.25) -> 5.96209
N19: Min | P19: =MIN(P6:P11) -> 0.23373763 | Q19: =MIN(Q6:Q11) -> 1.6564366 | R19: =MIN(R6:R11) -> 4.1529633

Sheet Growth Rate Analysis
B1: GROWTH RATE ANALYSIS
B3: Particulars | C3: 2022 | D3: 2023 | E3: 2024 | F3: 2025 | G3: 2026
B4: Revenue from Operations
B5: Year | C5: 2022 | D5: 2023 | E5: 2024 | F5: 2025 | G5: 2026
B6: 2022 | C6: =Assumption!C5 -> 585484.22 | E6: 1 | F6: =LN(C6) -> 13.280195
B7: 2023 | C7: =Assumption!D5 -> 837764.89 | D7: =C7/C6-1 -> 0.43089235 | E7: 2 | F7: =LN(C7) -> 13.638493 | G7: =C7/C6 -> 1.4308923
B8: 2024 | C8: =Assumption!E5 -> 772067.59 | D8: =C8/C7-1 -> -0.078419734 | E8: 3 | F8: =LN(C8) -> 13.556827 | G8: =C8/C7 -> 0.92158027
B9: 2025 | C9: =Assumption!F5 -> 753695.85 | D9: =C9/C8-1 -> -0.023795507 | E9: 4 | F9: =LN(C9) -> 13.532744 | G9: =C9/C8 -> 0.97620449
B10: 2026 | C10: =Assumption!G5 -> 784415.43 | D10: =C10/C9-1 -> 0.04075859 | E10: 5 | F10: =LN(C10) -> 13.572694 | G10: =C10/C9 -> 1.0407586
B12: Approaches to calculate 'g' (Revenue Growth Rate) | C12: Value | F12: Method | G12: Value
B13: Arithmetic Mean (Avg YoY Growth) | C13: =AVERAGE(D7:D10) -> 0.092358924 | F13: Arithmetic | G13: =C13 -> 0.092358924
B14: CAGR Method | C14: =(C10/C6)^(1/(E10-E6))-1 -> 0.075864886 | F14: CAGR | G14: =C14 -> 0.075864886
B15: Log Regression (SLOPE) | C15: =EXP(SLOPE(F6:F10,E6:E10))-1 -> 0.04909202 | F15: Log Regression | G15: =C15 -> 0.04909202
B16: Geometric Mean | C16: =GEOMEAN(G7:G10)-1 -> 0.075864886 | F16: Geomean | G16: =C16 -> 0.075864886
B18: Fundamental Growth Rate (g = Retention Ratio × Return on Equity)
B19: Component | C19: Formula / Source | D19: Value
B20: Basic EPS (₹) | C20: Latest year (FY26) | D20: ='Profit & Loss'!C40 -> 31
B21: Dividend Per Share (₹) | C21: Equity Dividend ÷ Shares Outstanding | D21: =IF('Profit & Loss'!C40=0,0,'Profit & Loss'!D43/('Profit & Loss'!D37/'Profit & Loss'!D40)) -> 7.0895672
B22: Dividend Payout Ratio (D/P Ratio) | C22: DPS ÷ EPS | D22: =D21/D20 -> 0.22869572
B23: Retention Ratio (Ploughback) | C23: 1 − D/P Ratio | D23: =1-D22 -> 0.77130428
B24: Return on Equity (5-Yr Avg RoE) | C24: Avg PAT / Shareholders Funds | D24: =AVERAGE('Ratio Analysis'!C39:G39) -> 0.15005246
B25: 'g' — Implied Growth Rate (Fundamental) | C25: Retention Ratio × RoE | D25: =D23*D24 -> 0.1157361

Sheet Growth Scenerio
B1: Growth Scenarios — Indian Oil Corporation
B3: Scenario 1: High Growth
B4: INR Cr. | C4: LTM | D4: Y1E | E4: Y2E | F4: Y3E | G4: Y4E | H4: Y5E | I4: Y6E | J4: Y7E | K4: Y8E | L4: Y9E | M4: Y10E | N4: Avg Revenue Growth | O4: ='Growth Rate Analysis'!C13 -> 0.092358924
B5: Sales | C5: ='Profit & Loss'!C10 -> 784415.43 | D5: =C5*(1+D6) -> 856863.2 | E5: =D5*(1+E6) -> 933730.62 | F5: =E5*(1+F6) -> 1015018.4 | G5: =F5*(1+G6) -> 1100691.9 | H5: =G5*(1+H6) -> 1190679 | I5: =H5*(1+I6) -> 1284866.4 | J5: =I5*(1+J6) -> 1383098.2 | K5: =J5*(1+K6) -> 1485173.6 | ... M5: =L5*(1+M6) -> 1699818.1 | N5: Risk Free Rate | O5: =WACC!C6 -> 0.0685
B6: Sales Growth % | D6: =O4 -> 0.092358924 | E6: =D6-$O$7 -> 0.089707932 | F6: =E6-$O$7 -> 0.087056941 | G6: =F6-$O$7 -> 0.084405949 | H6: =G6-$O$7 -> 0.081754958 | I6: =H6-$O$7 -> 0.079103966 | J6: =I6-$O$7 -> 0.076452975 | K6: =J6-$O$7 -> 0.073801983 | L6: =K6-$O$7 -> 0.071150992 | M6: =L6-$O$7 -> 0.0685 | O6: =O4-O5 -> 0.023858924
N7: Growth Per Year Decay | O7: =O6/9 -> 0.0026509916
B8: Scenario 2: Average Growth
B9: INR Cr. | C9: LTM | D9: Y1E | E9: Y2E | F9: Y3E | G9: Y4E | H9: Y5E | I9: Y6E | J9: Y7E | K9: Y8E | L9: Y9E | M9: Y10E | N9: Avg Revenue Growth | O9: ='Growth Rate Analysis'!C14 -> 0.075864886
B10: Sales | C10: =C5 -> 784415.43 | D10: =C10*(1+D11) -> 843925.02 | E10: =D10*(1+E11) -> 907258.69 | F10: =E10*(1+F11) -> 974602.91 | G10: =F10*(1+G11) -> 1046148.4 | H10: =G10*(1+H11) -> 1122090 | I10: =H10*(1+I11) -> 1202626.1 | J10: =I10*(1+J11) -> 1287958.4 | K10: =J10*(1+K11) -> 1378291.5 | ... M10: =L10*(1+M11) -> 1574789.8 | N10: Risk Free Rate | O10: =WACC!C6 -> 0.0685
B11: Sales Growth % | D11: =O9 -> 0.075864886 | E11: =D11-$O$12 -> 0.075046566 | F11: =E11-$O$12 -> 0.074228245 | G11: =F11-$O$12 -> 0.073409924 | H11: =G11-$O$12 -> 0.072591603 | I11: =H11-$O$12 -> 0.071773283 | J11: =I11-$O$12 -> 0.070954962 | K11: =J11-$O$12 -> 0.070136641 | L11: =K11-$O$12 -> 0.069318321 | M11: =L11-$O$12 -> 0.0685 | O11: =O9-O10 -> 0.0073648863
N12: Growth Per Year Decay | O12: =O11/9 -> 0.0008183207
B13: Scenario 3: g (Retention × RoE)
B14: INR Cr. | C14: LTM | D14: Y1E | E14: Y2E | F14: Y3E | G14: Y4E | H14: Y5E | I14: Y6E | J14: Y7E | K14: Y8E | L14: Y9E | M14: Y10E | N14: Avg Revenue Growth | O14: ='Growth Rate Analysis'!D25 -> 0.1157361
B15: Sales | C15: =C10 -> 784415.43 | D15: =C15*(1+D16) -> 875200.61 | E15: =D15*(1+E16) -> 981086.37 | F15: =E15*(1+F16) -> 1104931.9 | G15: =F15*(1+G16) -> 1250209.9 | H15: =G15*(1+H16) -> 1421151 | I15: =H15*(1+I16) -> 1622923.8 | J15: =I15*(1+J16) -> 1861861.7 | K15: =J15*(1+K16) -> 2145749.6 | ... M15: =L15*(1+M16) -> 2876000.3 | N15: Risk Free Rate | O15: =WACC!C6 -> 0.0685
B16: Sales Growth % | D16: =O14 -> 0.1157361 | E16: =D16-(-P17) -> 0.12098456 | F16: =E16-(-Q17) -> 0.12623301 | G16: =F16-(-R17) -> 0.13148147 | H16: =G16-(-S17) -> 0.13672993 | I16: =H16-(-T17) -> 0.14197838 | J16: =I16-(-U17) -> 0.14722684 | K16: =J16-(-V17) -> 0.15247529 | L16: =K16-(-W17) -> 0.15772375 | M16: =L16-(-X17) -> 0.15772375 | O16: =O14-O15 -> 0.047236102
N17: Growth Per Year Decay | O17: =O16/9 -> 0.0052484558 | P17: =O16/9 -> 0.0052484558 | Q17: =O16/9 -> 0.0052484558 | R17: =O16/9 -> 0.0052484558 | S17: =O16/9 -> 0.0052484558 | T17: =O16/9 -> 0.0052484558 | U17: =O16/9 -> 0.0052484558 | V17: =O16/9 -> 0.0052484558 | W17: =O16/9 -> 0.0052484558
B18: Live Scenario | C18: 2
B19: INR Cr. | C19: LTM | D19: Y1E | E19: Y2E | F19: Y3E | G19: Y4E | H19: Y5E | I19: Y6E | J19: Y7E | K19: Y8E | L19: Y9E | M19: Y10E
B20: Sales | C20: =C5 -> 784415.43 | D20: =C20*(1+D21) -> 843925.02 | E20: =D20*(1+E21) -> 907258.69 | F20: =E20*(1+F21) -> 974602.91 | G20: =F20*(1+G21) -> 1046148.4 | H20: =G20*(1+H21) -> 1122090 | I20: =H20*(1+I21) -> 1202626.1 | J20: =I20*(1+J21) -> 1287958.4 | K20: =J20*(1+K21) -> 1378291.5 | ... M20: =L20*(1+M21) -> 1574789.8
B21: Sales Growth % | D21: =CHOOSE($C$18,D6,D11,D16) -> 0.075864886 | E21: =CHOOSE($C$18,E6,E11,E16) -> 0.075046566 | F21: =CHOOSE($C$18,F6,F11,F16) -> 0.074228245 | G21: =CHOOSE($C$18,G6,G11,G16) -> 0.073409924 | H21: =CHOOSE($C$18,H6,H11,H16) -> 0.072591603 | I21: =CHOOSE($C$18,I6,I11,I16) -> 0.071773283 | J21: =CHOOSE($C$18,J6,J11,J16) -> 0.070954962 | K21: =CHOOSE($C$18,K6,K11,K16) -> 0.070136641 | ... M21: =CHOOSE($C$18,M6,M11,M16) -> 0.0685
N23: Scenario | O23: Starting g
N24: High Growth (Arithmetic) | O24: =O4 -> 0.092358924
N25: Avg Growth (CAGR) | O25: =O9 -> 0.075864886
N26: Fundamental g (Ret × RoE) | O26: =O14 -> 0.1157361

Sheet DCF Valuation 
B1: DCF Valuation — Indian Oil Corporation (₹ Cr.)
D3: 1 | E3: 2 | F3: 3 | G3: 4 | H3: 5 | I3: 6 | J3: 7 | K3: 8 | L3: 9 | M3: 10
B4: INR Cr. | C4: LTM | D4: Y1E | E4: Y2E | F4: Y3E | G4: Y4E | H4: Y5E | I4: Y6E | J4: Y7E | K4: Y8E | L4: Y9E | M4: Y10E | O4: Terminal Year | R4: Terminal growth rate % | S4: 0.01
B5: Sales | C5: ='Growth Scenerio'!C20 -> 784415.43 | D5: ='Growth Scenerio'!D20 -> 843925.02 | E5: ='Growth Scenerio'!E20 -> 907258.69 | F5: ='Growth Scenerio'!F20 -> 974602.91 | G5: ='Growth Scenerio'!G20 -> 1046148.4 | H5: ='Growth Scenerio'!H20 -> 1122090 | I5: ='Growth Scenerio'!I20 -> 1202626.1 | J5: ='Growth Scenerio'!J20 -> 1287958.4 | ... M5: ='Growth Scenerio'!M20 -> 1574789.8 | O5: Terminal Year Revenue | P5: =M5*(1+S4) -> 1590537.7 | R5: Cost of Capital (WACC) % | S5: =WACC!C34 -> 0.10595786
B6: Sales Growth % | D6: ='Growth Scenerio'!D21 -> 0.075864886 | E6: ='Growth Scenerio'!E21 -> 0.075046566 | F6: ='Growth Scenerio'!F21 -> 0.074228245 | G6: ='Growth Scenerio'!G21 -> 0.073409924 | H6: ='Growth Scenerio'!H21 -> 0.072591603 | I6: ='Growth Scenerio'!I21 -> 0.071773283 | J6: ='Growth Scenerio'!J21 -> 0.070954962 | K6: ='Growth Scenerio'!K21 -> 0.070136641 | ... M6: ='Growth Scenerio'!M21 -> 0.0685 | O6: projected sales/revenue | P6: =S4 -> 0.01 | R6: Terminal reinvestment rate % | S6: =S4*S5 -> 0.0010595786
B7: EBIT | D7: =D8*D5 -> 45073.513 | E7: =E8*E5 -> 48456.125 | F7: =F8*F5 -> 52052.939 | G7: =G8*G5 -> 55874.141 | H7: =H8*H5 -> 59930.134 | I7: =I8*I5 -> 64231.517 | J7: =J8*J5 -> 68789.062 | K7: =K8*K5 -> 73613.695 | ... M7: =M8*M5 -> 84108.552 | O7: EBIT | P7: =P8*P5 -> 84949.637
B8: EBIT Margin % | D8: =Assumption!$J$34 -> 0.053409381 | E8: =Assumption!$J$34 -> 0.053409381 | F8: =Assumption!$J$34 -> 0.053409381 | G8: =Assumption!$J$34 -> 0.053409381 | H8: =Assumption!$J$34 -> 0.053409381 | I8: =Assumption!$J$34 -> 0.053409381 | J8: =Assumption!$J$34 -> 0.053409381 | K8: =Assumption!$J$34 -> 0.053409381 | ... M8: =Assumption!$J$34 -> 0.053409381 | O8: EBIT Margin | P8: =M8 -> 0.053409381
B9: Less: Tax on EBIT | D9: =D7*Assumption!$C$40 -> 11268.378 | E9: =E7*Assumption!$C$40 -> 12114.031 | F9: =F7*Assumption!$C$40 -> 13013.235 | G9: =G7*Assumption!$C$40 -> 13968.535 | H9: =H7*Assumption!$C$40 -> 14982.534 | I9: =I7*Assumption!$C$40 -> 16057.879 | J9: =J7*Assumption!$C$40 -> 17197.265 | K9: =K7*Assumption!$C$40 -> 18403.424 | ... M9: =M7*Assumption!$C$40 -> 21027.138 | O9: Tax on EBIT | P9: =25%*P7 -> 21237.409
B10: EBIT(1-T) | D10: =D7-D9 -> 33805.135 | E10: =E7-E9 -> 36342.094 | F10: =F7-F9 -> 39039.704 | G10: =G7-G9 -> 41905.606 | H10: =H7-H9 -> 44947.601 | I10: =I7-I9 -> 48173.638 | J10: =J7-J9 -> 51591.796 | K10: =K7-K9 -> 55210.272 | ... M10: =M7-M9 -> 63081.414 | O10: EBIT(1-T) | P10: =P7-P9 -> 63712.228
B11: Less: Net Capital Expenditure | D11: =D5*'Fixed Assets Schedule'!$D$13 -> 23257.331 | E11: =E5*'Fixed Assets Schedule'!$D$13 -> 25002.714 | F11: =F5*'Fixed Assets Schedule'!$D$13 -> 26858.621 | G11: =G5*'Fixed Assets Schedule'!$D$13 -> 28830.311 | H11: =H5*'Fixed Assets Schedule'!$D$13 -> 30923.149 | I11: =I5*'Fixed Assets Schedule'!$D$13 -> 33142.605 | J11: =J5*'Fixed Assets Schedule'!$D$13 -> 35494.237 | K11: =K5*'Fixed Assets Schedule'!$D$13 -> 37983.684 | ... M11: =M5*'Fixed Assets Schedule'!$D$13 -> 43398.889
B12: Non Cash Working Capital | C12: ='Working Capital Changes'!G17 -> 2224.06 | D12: =C12+D5*'Working Capital Changes'!$D$21 -> 619.21551 | E12: =D12+E5*'Working Capital Changes'!$D$21 -> -1106.067 | F12: =E12+F5*'Working Capital Changes'!$D$21 -> -2959.4143 | G12: =F12+G5*'Working Capital Changes'!$D$21 -> -4948.8156 | H12: =G12+H5*'Working Capital Changes'!$D$21 -> -7082.6308 | I12: =H12+I5*'Working Capital Changes'!$D$21 -> -9369.5969 | J12: =I12+J5*'Working Capital Changes'!$D$21 -> -11818.835 | K12: =J12+K5*'Working Capital Changes'!$D$21 -> -14439.854 | ... M12: =L12+M5*'Working Capital Changes'!$D$21 -> -20237.246
B13: Less: Change in Working Capital | D13: =D12-C12 -> -1604.8445 | E13: =E12-D12 -> -1725.2826 | F13: =F12-E12 -> -1853.3473 | G13: =G12-F12 -> -1989.4013 | H13: =H12-G12 -> -2133.8152 | I13: =I12-H12 -> -2286.9661 | J13: =J12-I12 -> -2449.2377 | K13: =K12-J12 -> -2621.019 | ... M13: =M12-L12 -> -2994.6888
B14: Reinvestment | D14: =D11+D13 -> 21652.486 | E14: =E11+E13 -> 23277.431 | F14: =F11+F13 -> 25005.274 | G14: =G11+G13 -> 26840.909 | H14: =H11+H13 -> 28789.334 | I14: =I11+I13 -> 30855.639 | J14: =J11+J13 -> 33045 | K14: =K11+K13 -> 35362.665 | ... M14: =M11+M13 -> 40404.201 | P14: =P10*P16 -> 67.508112
B15: Free Cash Flow To Firm (FCFF) | D15: =D10-D14 -> 12152.648 | E15: =E10-E14 -> 13064.663 | F15: =F10-F14 -> 14034.43 | G15: =G10-G14 -> 15064.696 | H15: =H10-H14 -> 16158.267 | I15: =I10-I14 -> 17317.999 | J15: =J10-J14 -> 18546.797 | K15: =K10-K14 -> 19847.607 | ... M15: =M10-M14 -> 22677.213 | P15: =P10-P14 -> 63644.72
B16: Implied Reinvestment rate % | D16: =D14/D10 -> 0.6405088 | E16: =E14/E10 -> 0.6405088 | F16: =F14/F10 -> 0.6405088 | G16: =G14/G10 -> 0.6405088 | H16: =H14/H10 -> 0.6405088 | I16: =I14/I10 -> 0.6405088 | J16: =J14/J10 -> 0.6405088 | K16: =K14/K10 -> 0.6405088 | ... M16: =M14/M10 -> 0.6405088 | P16: =S6 -> 0.0010595786
B18: Terminal Value | M18: =P15/(S5-S4) -> 663256.99
B20: Present Value Interest Factor (PVIF) | D20: =1/(1+$S$5)^1 -> 0.90419359 | E20: =1/(1+$S$5)^2 -> 0.81756604 | F20: =1/(1+$S$5)^3 -> 0.73923797 | G20: =1/(1+$S$5)^4 -> 0.66841423 | H20: =1/(1+$S$5)^5 -> 0.60437586 | I20: =1/(1+$S$5)^6 -> 0.54647277 | J20: =1/(1+$S$5)^7 -> 0.49411718 | K20: =1/(1+$S$5)^8 -> 0.44677758 | L20: =1/(1+$S$5)^9 -> 0.40397342 | M20: =1/(1+$S$5)^10 -> 0.36527018
B22: Present value of FCFF | C22: =SUM(D22:M22) -> 96232.054 | D22: =D15*D20 -> 10988.347 | E22: =E15*E20 -> 10681.225 | F22: =F15*F20 -> 10374.784 | G22: =G15*G20 -> 10069.457 | H22: =H15*H20 -> 9765.6664 | I22: =I15*I20 -> 9463.8148 | J22: =J15*J20 -> 9164.2908 | K22: =K15*K20 -> 8867.4657 | ... M22: =M15*M20 -> 8283.3097
B23: Present value of Terminal value | M23: =M18*M20 -> 242268
I24: Sensitivity: Intrinsic Value per Share (₹)
B25: Value of operating assets | C25: =C22+M23 -> 338500.05 | I25: =C32 -> 148.90307 | J25: =S5-0.02 -> 0.085957857 | K25: =S5-0.01 -> 0.095957857 | L25: =S5 -> 0.10595786 | M25: =S5+0.01 -> 0.11595786
B26: Add: Cash & Cash Equivalents | C26: ='Balance Sheet'!C44 -> 4414.66 | I26: =S4-0.01 -> 0 | J26: =(D15*(1/(1+J25)^1)+E15*(1/(1+J25)^2)+F15*(1/(1+J25)^3)+G15*(1/(1+J25)^4)+H15*(1/(1+J25)^5)+I15*(1/(1+J25)^6)+J15*(1/(1+J25)^7)+K15*(1/(1+J25)^8)+L15*(1/(1+J25)^9)+M15*(1/(1+J25)^10)+(P15/(J25-I26))*(1/(1+J25)^10)+C26-C27-C28)/C31 -> 215.80638 | K26: =(D15*(1/(1+K25)^1)+E15*(1/(1+K25)^2)+F15*(1/(1+K25)^3)+G15*(1/(1+K25)^4)+H15*(1/(1+K25)^5)+I15*(1/(1+K25)^6)+J15*(1/(1+K25)^7)+K15*(1/(1+K25)^8)+L15*(1/(1+K25)^9)+M15*(1/(1+K25)^10)+(P15/(K25-I26))*(1/(1+K25)^10)+C26-C27-C28)/C31 -> 169.06245 | L26: =(D15*(1/(1+L25)^1)+E15*(1/(1+L25)^2)+F15*(1/(1+L25)^3)+G15*(1/(1+L25)^4)+H15*(1/(1+L25)^5)+I15*(1/(1+L25)^6)+J15*(1/(1+L25)^7)+K15*(1/(1+L25)^8)+L15*(1/(1+L25)^9)+M15*(1/(1+L25)^10)+(P15/(L25-I26))*(1/(1+L25)^10)+C26-C27-C28)/C31 -> 132.30033 | M26: =(D15*(1/(1+M25)^1)+E15*(1/(1+M25)^2)+F15*(1/(1+M25)^3)+G15*(1/(1+M25)^4)+H15*(1/(1+M25)^5)+I15*(1/(1+M25)^6)+J15*(1/(1+M25)^7)+K15*(1/(1+M25)^8)+L15*(1/(1+M25)^9)+M15*(1/(1+M25)^10)+(P15/(M25-I26))*(1/(1+M25)^10)+C26-C27-C28)/C31 -> 102.8313
B27: Less: Total Debt (LT + ST) | C27: ='Balance Sheet'!C16+'Balance Sheet'!C22 -> 131822.39 | I27: =S4 -> 0.01 | J27: =(D15*(1/(1+J25)^1)+E15*(1/(1+J25)^2)+F15*(1/(1+J25)^3)+G15*(1/(1+J25)^4)+H15*(1/(1+J25)^5)+I15*(1/(1+J25)^6)+J15*(1/(1+J25)^7)+K15*(1/(1+J25)^8)+L15*(1/(1+J25)^9)+M15*(1/(1+J25)^10)+(P15/(J25-I27))*(1/(1+J25)^10)+C26-C27-C28)/C31 -> 246.83706 | K27: =(D15*(1/(1+K25)^1)+E15*(1/(1+K25)^2)+F15*(1/(1+K25)^3)+G15*(1/(1+K25)^4)+H15*(1/(1+K25)^5)+I15*(1/(1+K25)^6)+J15*(1/(1+K25)^7)+K15*(1/(1+K25)^8)+L15*(1/(1+K25)^9)+M15*(1/(1+K25)^10)+(P15/(K25-I27))*(1/(1+K25)^10)+C26-C27-C28)/C31 -> 191.47414 | L27: =(D15*(1/(1+L25)^1)+E15*(1/(1+L25)^2)+F15*(1/(1+L25)^3)+G15*(1/(1+L25)^4)+H15*(1/(1+L25)^5)+I15*(1/(1+L25)^6)+J15*(1/(1+L25)^7)+K15*(1/(1+L25)^8)+L15*(1/(1+L25)^9)+M15*(1/(1+L25)^10)+(P15/(L25-I27))*(1/(1+L25)^10)+C26-C27-C28)/C31 -> 148.90307 | M27: =(D15*(1/(1+M25)^1)+E15*(1/(1+M25)^2)+F15*(1/(1+M25)^3)+G15*(1/(1+M25)^4)+H15*(1/(1+M25)^5)+I15*(1/(1+M25)^6)+J15*(1/(1+M25)^7)+K15*(1/(1+M25)^8)+L15*(1/(1+M25)^9)+M15*(1/(1+M25)^10)+(P15/(M25-I27))*(1/(1+M25)^10)+C26-C27-C28)/C31 -> 115.38778
B28: Less: Minority Interest | C28: ='Balance Sheet'!C14 -> 6029.56 | I28: =S4+0.01 -> 0.02 | J28: =(D15*(1/(1+J25)^1)+E15*(1/(1+J25)^2)+F15*(1/(1+J25)^3)+G15*(1/(1+J25)^4)+H15*(1/(1+J25)^5)+I15*(1/(1+J25)^6)+J15*(1/(1+J25)^7)+K15*(1/(1+J25)^8)+L15*(1/(1+J25)^9)+M15*(1/(1+J25)^10)+(P15/(J25-I28))*(1/(1+J25)^10)+C26-C27-C28)/C31 -> 287.27698 | K28: =(D15*(1/(1+K25)^1)+E15*(1/(1+K25)^2)+F15*(1/(1+K25)^3)+G15*(1/(1+K25)^4)+H15*(1/(1+K25)^5)+I15*(1/(1+K25)^6)+J15*(1/(1+K25)^7)+K15*(1/(1+K25)^8)+L15*(1/(1+K25)^9)+M15*(1/(1+K25)^10)+(P15/(K25-I28))*(1/(1+K25)^10)+C26-C27-C28)/C31 -> 219.78691 | L28: =(D15*(1/(1+L25)^1)+E15*(1/(1+L25)^2)+F15*(1/(1+L25)^3)+G15*(1/(1+L25)^4)+H15*(1/(1+L25)^5)+I15*(1/(1+L25)^6)+J15*(1/(1+L25)^7)+K15*(1/(1+L25)^8)+L15*(1/(1+L25)^9)+M15*(1/(1+L25)^10)+(P15/(L25-I28))*(1/(1+L25)^10)+C26-C27-C28)/C31 -> 169.36881 | M28: =(D15*(1/(1+M25)^1)+E15*(1/(1+M25)^2)+F15*(1/(1+M25)^3)+G15*(1/(1+M25)^4)+H15*(1/(1+M25)^5)+I15*(1/(1+M25)^6)+J15*(1/(1+M25)^7)+K15*(1/(1+M25)^8)+L15*(1/(1+M25)^9)+M15*(1/(1+M25)^10)+(P15/(M25-I28))*(1/(1+M25)^10)+C26-C27-C28)/C31 -> 130.56134
B29: Equity Value | C29: =C25+C26-C27-C28 -> 205062.76 | I29: =S4+0.02 -> 0.03 | J29: =(D15*(1/(1+J25)^1)+E15*(1/(1+J25)^2)+F15*(1/(1+J25)^3)+G15*(1/(1+J25)^4)+H15*(1/(1+J25)^5)+I15*(1/(1+J25)^6)+J15*(1/(1+J25)^7)+K15*(1/(1+J25)^8)+L15*(1/(1+J25)^9)+M15*(1/(1+J25)^10)+(P15/(J25-I29))*(1/(1+J25)^10)+C26-C27-C28)/C31 -> 342.1706 | K29: =(D15*(1/(1+K25)^1)+E15*(1/(1+K25)^2)+F15*(1/(1+K25)^3)+G15*(1/(1+K25)^4)+H15*(1/(1+K25)^5)+I15*(1/(1+K25)^6)+J15*(1/(1+K25)^7)+K15*(1/(1+K25)^8)+L15*(1/(1+K25)^9)+M15*(1/(1+K25)^10)+(P15/(K25-I29))*(1/(1+K25)^10)+C26-C27-C28)/C31 -> 256.6848 | L29: =(D15*(1/(1+L25)^1)+E15*(1/(1+L25)^2)+F15*(1/(1+L25)^3)+G15*(1/(1+L25)^4)+H15*(1/(1+L25)^5)+I15*(1/(1+L25)^6)+J15*(1/(1+L25)^7)+K15*(1/(1+L25)^8)+L15*(1/(1+L25)^9)+M15*(1/(1+L25)^10)+(P15/(L25-I29))*(1/(1+L25)^10)+C26-C27-C28)/C31 -> 195.22325 | M29: =(D15*(1/(1+M25)^1)+E15*(1/(1+M25)^2)+F15*(1/(1+M25)^3)+G15*(1/(1+M25)^4)+H15*(1/(1+M25)^5)+I15*(1/(1+M25)^6)+J15*(1/(1+M25)^7)+K15*(1/(1+M25)^8)+L15*(1/(1+M25)^9)+M15*(1/(1+M25)^10)+(P15/(M25-I29))*(1/(1+M25)^10)+C26-C27-C28)/C31 -> 149.26537
I30: =S4+0.03 -> 0.04 | J30: =(D15*(1/(1+J25)^1)+E15*(1/(1+J25)^2)+F15*(1/(1+J25)^3)+G15*(1/(1+J25)^4)+H15*(1/(1+J25)^5)+I15*(1/(1+J25)^6)+J15*(1/(1+J25)^7)+K15*(1/(1+J25)^8)+L15*(1/(1+J25)^9)+M15*(1/(1+J25)^10)+(P15/(J25-I30))*(1/(1+J25)^10)+C26-C27-C28)/C31 -> 420.9529 | K30: =(D15*(1/(1+K25)^1)+E15*(1/(1+K25)^2)+F15*(1/(1+K25)^3)+G15*(1/(1+K25)^4)+H15*(1/(1+K25)^5)+I15*(1/(1+K25)^6)+J15*(1/(1+K25)^7)+K15*(1/(1+K25)^8)+L15*(1/(1+K25)^9)+M15*(1/(1+K25)^10)+(P15/(K25-I30))*(1/(1+K25)^10)+C26-C27-C28)/C31 -> 306.77042 | L30: =(D15*(1/(1+L25)^1)+E15*(1/(1+L25)^2)+F15*(1/(1+L25)^3)+G15*(1/(1+L25)^4)+H15*(1/(1+L25)^5)+I15*(1/(1+L25)^6)+J15*(1/(1+L25)^7)+K15*(1/(1+L25)^8)+L15*(1/(1+L25)^9)+M15*(1/(1+L25)^10)+(P15/(L25-I30))*(1/(1+L25)^10)+C26-C27-C28)/C31 -> 228.91738 | M30: =(D15*(1/(1+M25)^1)+E15*(1/(1+M25)^2)+F15*(1/(1+M25)^3)+G15*(1/(1+M25)^4)+H15*(1/(1+M25)^5)+I15*(1/(1+M25)^6)+J15*(1/(1+M25)^7)+K15*(1/(1+M25)^8)+L15*(1/(1+M25)^9)+M15*(1/(1+M25)^10)+(P15/(M25-I30))*(1/(1+M25)^10)+C26-C27-C28)/C31 -> 172.89425
B31: No. of Shares outstanding (Cr.) | C31: =WACC!C24 -> 1377.156
B32: Intrinsic Value Per Share (₹) | C32: =C29/C31 -> 148.90307
C33: Current CMP ₹147 (June 2026)
