Workbook

Sheet About
A1: SOLAR INDUSTRIES INDIA LIMITED
B2: COMPANY OVERVIEW
B3: ABOUT THE COMPANY | L3: Source
B4: Solar Industries India Limited (NSE: SOLARINDS | BSE: 532725) is one of the world's leading manufacturers and suppliers of industrial explosives, initiating systems, and defence ammunition. Headquartered in Nagpur, Maharashtra, the company has a global presence spanning 90+ countries with 40+ manufacturing facilities across 9 countries. Founded in 1985, Solar has diversified from industrial explosives into a strategic defence and aerospace player, supplying Pinaka rockets and loitering munitions. With a near-zero net debt profile and a ₹15,000+ Crore defence order book, the company is well-positioned for high double-digit growth over the coming years.
B5: REGISTERED OFFICE
B6: Address | C6: "Solar" House, 14, Kachimet, Amravati Road, Nagpur, Maharashtra – 440023
B8: S.No | C8: Name of Entity | D8: Type | F8: Unit / Entity | G8: Full Address | H8: City / District & State
B9: 1 | C9: Solar Defence and Aerospace Limited (formerly Economic Explosives Ltd) | D9: Wholly Owned Subsidiary | F9: Solar Industries India Ltd - Chakdoh | G9: Khasra No. 37-39 & 78-83, Amravati Road, Village-Chakdoh (Bazargaon), Tehsil-Katol 441302 | H9: Nagpur, Maharashtra
B10: 2 | C10: Emul Tek Private Limited | D10: Wholly Owned Subsidiary | F10: Solar Industries India Ltd - Waidhan Unit 1 | G10: Plot No. 32-37, Udyog Deep Industrial Area, Tehsil Waidhan, District Singrauli, MP 486886 | H10: Waidhan, Madhya Pradesh
B11: 3 | C11: Solar Explochem Limited | D11: Wholly Owned Subsidiary | F11: Solar Industries India Ltd - Waidhan Unit 2 | G11: Khasra No 975/2, Post-Ganiyari, Tahsil-Waidhan, District Singrauli, MP 486886 | H11: Dist. Singrauli, Madhya Pradesh
B12: 4 | C12: Solar Defence Limited | D12: Wholly Owned Subsidiary | F12: Solar Industries India Ltd - Warur | G12: Survey No. 101, Warur Road, Tehsil Rajura, District Chandrapur, MH 442905 | H12: Chandrapur, Maharashtra
B13: 5 | C13: Solar Defence Systems Limited | D13: Wholly Owned Subsidiary | F13: Solar Industries India Ltd - Korba | G13: Khasra No. 5, Village-Mudapar (Hardi Bazar), Po-Korbi/Dhatura, Tahsil: Pali, District Korba, CG 495446 | H13: Korba, Chhattisgarh
B14: 6 | C14: Solar Avionics Limited | D14: Wholly Owned Subsidiary | F14: Solar Industries India Ltd - Ramgarh | G14: Plot No. 967 & 1156, Village-Manua (Binjhar), Post-Argada (Hesla), District Ramgarh, JH 829101 | H14: Hazaribagh, Jharkhand
B15: 7 | C15: Solar Aerospace Limited | D15: Wholly Owned Subsidiary | F15: Solar Industries India Ltd - Tadali | G15: Plot No. B-11, MIDC Growth Centre, Tadali, District Chandrapur, MH | H15: Tadali, Maharashtra
B16: 8 | C16: Solar Overseas Mauritius Limited | D16: Wholly Owned Subsidiary | F16: Solar Industries India Ltd - Dhanbad | G16: Plot No. C-32-33(P), Kandra Industrial Area, At-Bhetia, Post: Govindpur, District Dhanbad, JH 828109 | H16: Dhanbad, Jharkhand
B17: 9 | C17: Solar Overseas Singapore Pte Limited | D17: Step-Down Subsidiary | F17: Solar Industries India Ltd - Asansol | G17: Plot No. 2/848, 3&5, Mouza Barapukuria, Post: Kalla(C.H), District Paschim Bardhaman, WB 713340 | H17: Burdwan, West Bengal
B18: 10 | C18: Solar Overseas Netherlands Cooperative U.A. | D18: Step-Down Subsidiary | F18: Solar Industries India Ltd - Talcher | G18: IDCO Plot No. 27, Revenue Plot No. 48(P), Industrial Estate, Village Ghantapada, Post-South Balanda, District Angul, Odisha 759116 | H18: Angul, Odisha
B19: 11 | C19: Solar Industries Africa Limited | D19: Step-Down Subsidiary | F19: Solar Industries India Ltd - Manendragarh | G19: Khasara No. 323/2 Mouza-Chainpur, Tahsil & Post-Manendragarh, District Koria, CG 497442 | H19: Koria, Chhattisgarh
B20: 12 | C20: Solar Nitro Zimbabwe (Private) Limited | D20: Step-Down Subsidiary | F20: Solar Industries India Ltd - Karimnagar | G20: Survey No. 363, Village: Mustial, Post: Sundilla, Mandal-Ramagiri, District Peddapalli, Telangana 505209 | H20: Karimnagar, Telangana
... B25: 17 | C25: Solar Nitro SARL | D25: Step-Down Subsidiary | F25: Solar Industries India Ltd - Bailadila | G25: Forest Compartment No 626/1861 Deposit Kailash Nagar Bailadila Iron Ore Mines, Kirandul Complex, District Dantewada, CG 494556 | H25: BIOM Kirandul, Chhattisgarh
B26: 18 | C26: Solar Nitro Kazakhstan Limited | D26: Step-Down Subsidiary | F26: Solar Industries India Ltd - Pallewada | G26: Survey No 187/A/A & 188/A/B, Village-Pallewada, Dist. Khammam, Telangana | H26: Pallewada, Telangana | I26: Participates in Business
B27: 19 | C27: Solar Nitro (SL) Limited | D27: Step-Down Subsidiary | F27: Solar Industries India Ltd - Kotputli | G27: C/o Ultratech Cement Ltd, Unit: Kotputali, Kh. No. 221, 222, Village Kujota, District Kotputali, Rajasthan 303180 | H27: Kotputli, Rajasthan | I27: Yes
B28: 20 | C28: Solar Nitro Chemicals Limited | D28: Step-Down Subsidiary | F28: Solar Defence and Aerospace Ltd - Sawanga | G28: Village – Sawanga, Nagpur | H28: Nagpur, Maharashtra | I28: No
B29: 21 | C29: Solar Mining Services Burkina Faso SARL | D29: Step-Down Subsidiary | F29: Solar Defence and Aerospace Ltd - Nimjee | G29: Kh-40/1 & 40/2, Khapri, PO-MIDC, Gondkhari, Kamleshwar Road, Nagpur | H29: Nagpur, Maharashtra | I29: No
B30: 22 | C30: Solar Mining Services (Pty) Limited – South Africa | D30: Step-Down Subsidiary | F30: Emul Tek Private Ltd - Waidhan 1 | G30: Survey No. 61, Town/Village-Udyog Deep Industrial Estate, Waidhan, Singrauli, MP 486886 | H30: Dist. Singrauli, Madhya Pradesh | I30: No
B31: 23 | C31: Solar Nigachem Limited | D31: Step-Down Subsidiary | F31: Emul Tek Private Ltd - Raigarh | G31: Survey No(s). 280, 281, Town/Village-Darramuda, Post Office-Garhumariya, District Raigarh, CG 496001 | H31: Dist. Raigarh, Chhattisgarh | I31: No
B32: 24 | C32: Solar Overseas Netherlands B.V. | D32: Step-Down Subsidiary | F32: Emul Tek Private Ltd - Waidhan 3 | G32: Plot No 75, Udyogdeep Industrial Estate, Waidhan, Singrauli, MP 486886 | H32: Dist. Singrauli, Madhya Pradesh | I32: No
B33: 25 | C33: Solar Explochem Zambia Limited | D33: Step-Down Subsidiary | F33: Emul Tek Private Ltd - Korba | G33: Survey No. 624/3, Plot No. 14, Town/Village-Ratija, Korba, CG 495449 | H33: Dist. Korba, Chhattisgarh | I33: No
B34: 26 | C34: Solar Patlayici Maddeler Sanayi Ve Ticaret Anonim Sirketi | D34: Step-Down Subsidiary | I34: No
B35: 27 | C35: P.T. Solar Mining Services (Indonesia) | D35: Step-Down Subsidiary | I35: No
B36: 28 | C36: Solar Nitro Ghana Limited | D36: Step-Down Subsidiary | I36: No
B37: 29 | C37: Solar Madencilik Hizmetleri Anonim Sirketi | D37: Step-Down Subsidiary | I37: No
B38: 30 | C38: PATSAN Patlayici Maddeler Sanayi Ve Ticaret Anonim Sirketi | D38: Step-Down Subsidiary | I38: No
B39: 31 | C39: Power Blast LLP | D39: Step-Down Subsidiary | I39: No
B40: 32 | C40: Maxigear (Pty) Limited | D40: Step-Down Subsidiary | I40: No
B41: 33 | C41: Frag Shared Services (Pty) Limited | D41: Step-Down Subsidiary | I41: No
B42: 34 | C42: Procapture (Pty) Limited | D42: Step-Down Subsidiary | I42: No
B43: 35 | C43: Problast BS (Pty) Limited | D43: Step-Down Subsidiary | I43: No
B44: 36 | C44: Problast BBBEE Investment Co. (Pty) Limited | D44: Step-Down Subsidiary | I44: No
B45: 37 | C45: Ortiz Investments (Pty) Ltd | D45: Associate | I45: No
... B47: 39 | C47: Zmotion Autonomous Systems Private Limited | D47: Associate | I47: No
I48: No
I49: No
I50: No
I51: No
I52: No
I53: No
I54: No
I55: No
I56: No
I57: No
I58: No
I59: No
... I65: No

Sheet Promoter
C1: Public Shareholding Pattern
B2: Solar Industries India Limited | As at December 2025
B3: Category & Name of the Shareholders | C3: No. of shareholder | D3: No. of fully paid up equity shares held | E3: Total no. shares held | F3: Shareholding % calculated as per SCRR, 1957 As a % of (A+B+C2) | G3: No. of Voting Rights | H3: Total as a % of Total Voting right | I3: Total No. Of shares on fully diluted basis (including warrants, ESOP, Convertible Securities etc.) | J3: Shareholding , as a % assuming full conversion of convertible securities ( as a percentage of diluted share capital)As a % of (A+B+C2) | K3: No. of equity shares held in dematerialized form(Not Applicable) | L3: Sub-categorization of shares (XV)
L4: Shareholding (No. of shares) under
L5: SubCategory_I | M5: SubCategory_II | N5: SubCategory_III
B6: Institutions | C6: - | D6: - | E6: - | F6: 0 | G6: - | H6: 0 | I6: - | J6: 0 | K6: - | L6: - | M6: - | N6: -
B7: B1) Institutions (Domestic) | C7: - | D7: - | E7: - | F7: 0 | G7: - | H7: 0 | I7: - | J7: 0 | K7: - | L7: - | M7: - | N7: -
B8: Mutual Funds/ | C8: 41 | D8: 10798557 | E8: 10798557 | F8: 11.93 | G8: 10798557 | H8: 11.93 | I8: 10798557 | J8: 11.93 | K8: 10798557 | L8: - | M8: - | N8: -
B9: Axis Mutual Fund Trustee Limited A/C Axis Mutual Fund A/C Axis Midcap Fund | C9: 1 | D9: 1053013 | E9: 1053013 | F9: 1.16 | G9: 1053013 | H9: 1.16 | I9: 1053013 | J9: 1.16 | K9: 1053013 | L9: - | M9: - | N9: -
B10: Kotak Flexicap Fund | C10: 1 | D10: 2579213 | E10: 2579213 | F10: 2.85 | G10: 2579213 | H10: 2.85 | I10: 2579213 | J10: 2.85 | K10: 2579213 | L10: - | M10: - | N10: -
B11: Sbi Equity Hybrid Fund | C11: 1 | D11: 3251372 | E11: 3251372 | F11: 3.59 | G11: 3251372 | H11: 3.59 | I11: 3251372 | J11: 3.59 | K11: 3251372 | L11: - | M11: - | N11: -
B12: Venture Capital Funds | C12: - | D12: - | E12: - | F12: 0 | G12: - | H12: 0 | I12: - | J12: 0 | K12: - | L12: - | M12: - | N12: -
B13: Alternate Investment Funds | C13: 27 | D13: 218593 | E13: 218593 | F13: 0.24 | G13: 218593 | H13: 0.24 | I13: 218593 | J13: 0.24 | K13: 218593 | L13: - | M13: - | N13: -
B14: Banks | C14: 1 | D14: 25 | E14: 25 | F14: 0 | G14: 25 | H14: 0 | I14: 25 | J14: 0 | K14: 25 | L14: - | M14: - | N14: -
B15: Insurance Companies | C15: 17 | D15: 447243 | E15: 447243 | F15: 0.49 | G15: 447243 | H15: 0.49 | I15: 447243 | J15: 0.49 | K15: 447243 | L15: - | M15: - | N15: -
B16: Provident Funds/ Pension Funds | C16: 1 | D16: 207363 | E16: 207363 | F16: 0.23 | G16: 207363 | H16: 0.23 | I16: 207363 | J16: 0.23 | K16: 207363 | L16: - | M16: - | N16: -
B17: Asset reconstruction companies | C17: - | D17: - | E17: - | F17: 0 | G17: - | H17: 0 | I17: - | J17: 0 | K17: - | L17: - | M17: - | N17: -
B18: Sovereign Wealth Funds | C18: - | D18: - | E18: - | F18: 0 | G18: - | H18: 0 | I18: - | J18: 0 | K18: - | L18: - | M18: - | N18: -
B19: NBFCs registered with RBI | C19: 4 | D19: 3080 | E19: 3080 | F19: 0 | G19: 3080 | H19: 0 | I19: 3080 | J19: 0 | K19: 3080 | L19: - | M19: - | N19: -
B20: Other Financial Institutions | C20: 1 | D20: 2000 | E20: 2000 | F20: 0 | G20: 2000 | H20: 0 | I20: 2000 | J20: 0 | K20: 2000 | L20: - | M20: - | N20: -
B21: Any Other(Institutions (Domestic)) | C21: - | D21: - | E21: - | F21: 0 | G21: - | H21: 0 | I21: - | J21: 0 | K21: - | L21: - | M21: - | N21: -
B22: Sub Total B1 | C22: 92 | D22: 11676861 | E22: 11676861 | F22: 12.9 | G22: 11676861 | H22: 12.9 | I22: 11676861 | J22: 12.9 | K22: 11676861 | L22: - | M22: - | N22: -
B23: B17) Institutions (Foreign) | C23: - | D23: - | E23: - | F23: 0 | G23: - | H23: 0 | I23: - | J23: 0 | K23: - | L23: - | M23: - | N23: -
B24: Foreign Direct Investment | C24: - | D24: - | E24: - | F24: 0 | G24: - | H24: 0 | I24: - | J24: 0 | K24: - | L24: - | M24: - | N24: -
B25: Foreign Venture Capital Investors | C25: - | D25: - | E25: - | F25: 0 | G25: - | H25: 0 | I25: - | J25: 0 | K25: - | L25: - | M25: - | N25: -
B26: Sovereign Wealth Funds | C26: - | D26: - | E26: - | F26: 0 | G26: - | H26: 0 | I26: - | J26: 0 | K26: - | L26: - | M26: - | N26: -
B27: Foreign Portfolio Investors Category I | C27: 371 | D27: 5766958 | E27: 5766958 | F27: 6.37 | G27: 5766958 | H27: 6.37 | I27: 5766958 | J27: 6.37 | K27: 5766958 | L27: - | M27: - | N27: -
B28: Foreign Portfolio Investors Category II | C28: 20 | D28: 202861 | E28: 202861 | F28: 0.22 | G28: 202861 | H28: 0.22 | I28: 202861 | J28: 0.22 | K28: 202861 | L28: - | M28: - | N28: -
B29: Overseas Depositories (holding DRs) (balancing figure) | C29: - | D29: - | E29: - | F29: 0 | G29: - | H29: 0 | I29: - | J29: 0 | K29: - | L29: - | M29: - | N29: -
B30: Any Other(Institutions (Foreign)) | C30: - | D30: - | E30: - | F30: 0 | G30: - | H30: 0 | I30: - | J30: 0 | K30: - | L30: - | M30: - | N30: -
B31: Sub Total B2 | C31: 391 | D31: 5969819 | E31: 5969819 | F31: 6.6 | G31: 5969819 | H31: 6.6 | I31: 5969819 | J31: 6.6 | K31: 5969819 | L31: - | M31: - | N31: -
B32: B26) Central Government/ State Government(s)/ President of India | C32: - | D32: - | E32: - | F32: 0 | G32: - | H32: 0 | I32: - | J32: 0 | K32: - | L32: - | M32: - | N32: -
B33: Central Government / President of India | C33: 1 | D33: 946 | E33: 946 | F33: 0 | G33: 946 | H33: 0 | I33: 946 | J33: 0 | K33: 946 | L33: - | M33: - | N33: -
B34: State Government / Governor | C34: - | D34: - | E34: - | F34: 0 | G34: - | H34: 0 | I34: - | J34: 0 | K34: - | L34: - | M34: - | N34: -
B35: Shareholding by Companies or Bodies Corporate where Central / State Government is a promoter | C35: - | D35: - | E35: - | F35: 0 | G35: - | H35: 0 | I35: - | J35: 0 | K35: - | L35: - | M35: - | N35: -
B36: Sub Total B3 | C36: 1 | D36: 946 | E36: 946 | F36: 0 | G36: 946 | H36: 0 | I36: 946 | J36: 0 | K36: 946 | L36: - | M36: - | N36: -
B37: B31) Non-Institutions | C37: - | D37: - | E37: - | F37: 0 | G37: - | H37: 0 | I37: - | J37: 0 | K37: - | L37: - | M37: - | N37: -
B38: Associate companies / Subsidiaries | C38: - | D38: - | E38: - | F38: 0 | G38: - | H38: 0 | I38: - | J38: 0 | K38: - | L38: - | M38: - | N38: -
B39: Directors and their relatives (excluding independent directors and nominee directors) | C39: - | D39: - | E39: - | F39: 0 | G39: - | H39: 0 | I39: - | J39: 0 | K39: - | L39: - | M39: - | N39: -
B40: Key Managerial Personnel | C40: 2 | D40: 3978 | E40: 3978 | F40: 0 | G40: 3978 | H40: 0 | I40: 3978 | J40: 0 | K40: 3978 | L40: - | M40: - | N40: -
B41: Relatives of promoters (other than 'immediate relatives' of promoters disclosed under 'Promoter and Promoter Group' category) | C41: - | D41: - | E41: - | F41: 0 | G41: - | H41: 0 | I41: - | J41: 0 | K41: - | L41: - | M41: - | N41: -
B42: Trusts where any person belonging to 'Promoter and Promoter Group' category is 'trustee', 'beneficiary', or 'author of the trust' | C42: - | D42: - | E42: - | F42: 0 | G42: - | H42: 0 | I42: - | J42: 0 | K42: - | L42: - | M42: - | N42: -
B43: Investor Education and Protection Fund (IEPF) | C43: 1 | D43: 2352 | E43: 2352 | F43: 0 | G43: 2352 | H43: 0 | I43: 2352 | J43: 0 | K43: 2352 | L43: - | M43: - | N43: -
B44: Resident Individuals holding nominal share capital up to Rs. 2 lakhs | C44: 108874 | D44: 4294247 | E44: 4294247 | F44: 4.75 | G44: 4294247 | H44: 4.75 | I44: 4294247 | J44: 4.75 | K44: 4294247 | L44: - | M44: - | N44: -
B45: Resident Individuals holding nominal share capital in excess of Rs. 2 lakhs | C45: 4 | D45: 665483 | E45: 665483 | F45: 0.74 | G45: 665483 | H45: 0.74 | I45: 665483 | J45: 0.74 | K45: 665483 | L45: - | M45: - | N45: -
B46: Non Resident Indians (NRIs) | C46: 3335 | D46: 188955 | E46: 188955 | F46: 0.21 | G46: 188955 | H46: 0.21 | I46: 188955 | J46: 0.21 | K46: 188955 | L46: - | M46: - | N46: -
B47: Foreign Nationals | C47: - | D47: - | E47: - | F47: 0 | G47: - | H47: 0 | I47: - | J47: 0 | K47: - | L47: - | M47: - | N47: -
B48: Foreign Companies | C48: - | D48: - | E48: - | F48: 0 | G48: - | H48: 0 | I48: - | J48: 0 | K48: - | L48: - | M48: - | N48: -
B49: Bodies Corporate | C49: 766 | D49: 1177837 | E49: 1177837 | F49: 1.3 | G49: 1177837 | H49: 1.3 | I49: 1177837 | J49: 1.3 | K49: 1177837 | L49: - | M49: - | N49: -
B50: Any Other (specify) | C50: 2445 | D50: 318306 | E50: 318306 | F50: 0.35 | G50: 318306 | H50: 0.35 | I50: 318306 | J50: 0.35 | K50: 318306 | L50: - | M50: - | N50: -
B51: Trusts | C51: 20 | D51: 41244 | E51: 41244 | F51: 0.05 | G51: 41244 | H51: 0.05 | I51: 41244 | J51: 0.05 | K51: 41244 | L51: - | M51: - | N51: -
B52: Firm | C52: 103 | D52: 40439 | E52: 40439 | F52: 0.04 | G52: 40439 | H52: 0.04 | I52: 40439 | J52: 0.04 | K52: 40439 | L52: - | M52: - | N52: -
B53: HUF | C53: 2297 | D53: 222426 | E53: 222426 | F53: 0.25 | G53: 222426 | H53: 0.25 | I53: 222426 | J53: 0.25 | K53: 222426 | L53: - | M53: - | N53: -
B54: Clearing Members | C54: 25 | D54: 14197 | E54: 14197 | F54: 0.02 | G54: 14197 | H54: 0.02 | I54: 14197 | J54: 0.02 | K54: 14197 | L54: - | M54: - | N54: -
B55: Sub Total B4 | C55: 115427 | D55: 6651158 | E55: 6651158 | F55: 7.35 | G55: 6651158 | H55: 7.35 | I55: 6651158 | J55: 7.35 | K55: 6651158 | L55: - | M55: - | N55: -
B56: B=B1+B2+B3+B4 | C56: 115911 | D56: 24298784 | E56: 24298784 | F56: 26.85 | G56: 24298784 | H56: 26.85 | I56: 24298784 | J56: 26.85 | K56: 24298784 | L56: - | M56: - | N56: -

Sheet Public
B1: Promoters Shareholding Pattern
A2: Solar Industries India Limited | As at December 2025
A3: Category & Name of Shareholder | B3: Shareholding Calculated as per SCRR , 1957 As a % of (A+B+C2) | C3: Number of Voting Rights held in each class of securities
C4: No. of Voting Rights
C5: Class X
A6: Promoter and Promoter Group | B6: 0
A7: A1) Indian | B7: 0
A8: Individuals/Hindu undivided Family | B8: 73.15 | C8: 66191271
A9: HARSHWARDHAN MANISH NUWAL | B9: 0
A10: INDIRA KAILASHCHANDRA NUWAL | B10: 6.15 | C10: 5568230
A11: KAILASH CHANDRA NUWAL | B11: 23.08 | C11: 20882963
A12: Leeladevi Satyanarayan Nuwal | B12: 0 | C12: 1000
A13: MANISH SATYANARAYAN NUWAL | B13: 38.94 | C13: 35232069
A14: RAGHAV MANISH NUWAL | B14: 0
A15: RAHUL NUWAL | B15: 0.03 | C15: 25315
A16: SATYANARAYAN NANDLAL NUWAL | B16: 3.58 | C16: 3238254
A17: Seema Nuwal | B17: 1.37 | C17: 1243440
A18: Sub-Total(A)(1) | B18: 73.15 | C18: 66191271
A19: A2) Foreign | B19: 0
A20: Sub-Total(A)(2) | B20: 0
A21: Promoter and Promoter Group (A=A1+A2) | B21: 73.15 | C21: 66191271
A22: Public | B22: 0
A23: B1) Institutions (Domestic) | B23: 0
A24: Mutual Funds | B24: 11.96 | C24: 10825022
A25: AXIS MUTUAL FUND TRUSTEE LIMITED A/C AXIS MUTUAL FUND A/C AXIS NIFTY500 QUALITY 50 INDEX FUND | B25: 1.17 | C25: 1056591
A26: KOTAK MAHINDRA TRUSTEE CO LTD A/C KOTAK NIFTY CHEMICALS ETF | B26: 3.03 | C26: 2740695
A27: SBI NIFTY 500 INDEX FUND | B27: 3.4 | C27: 3072724
A28: Alternate Investment Funds | B28: 0.19 | C28: 174150
A29: Banks | B29: 0.03 | C29: 23783
A30: Insurance Companies | B30: 0.47 | C30: 422077
A31: Provident Funds/ Pension Funds | B31: 0.25 | C31: 228158
A32: NBFCs registered with RBI | B32: 0.01 | C32: 4624
A33: Bodies Corporate | B33: 0 | C33: 100
A34: Trust | B34: 0 | C34: 609
A35: Sub-Total(B)(1) | B35: 12.91 | C35: 11678523
A36: B2) Institutions (Foreign) | B36: 0
A37: Foreign Portfolio Investors Category I | B37: 6.47 | C37: 5854699
A38: Foreign Portfolio Investors Category II | B38: 0.27 | C38: 242768
A39: Sub-Total(B)(2) | B39: 6.74 | C39: 6097467
A40: B3) Central Government/ State Government(s)/ President of India | B40: 0
A41: Central Government / President of India | B41: 0 | C41: 882
A42: Sub-Total(B)(3) | B42: 0 | C42: 882
A43: B4) Non-Institutions | B43: 0
A44: Resident Individuals holding nominal share capital up to Rs. 2 lakhs | B44: 4.99 | C44: 4512819
A45: Resident Individuals holding nominal share capital in excess of Rs. 2 lakhs | B45: 0.35 | C45: 319188
A46: Non Resident Indians (NRIs) | B46: 0.19 | C46: 175915
A47: Bodies Corporate | B47: 1.33 | C47: 1200639
A48: Clearing Members | B48: 0.01 | C48: 8940
A49: HUF | B49: 0.25 | C49: 224494
A50: LLP | B50: 0.05 | C50: 41865
A51: Unclaimed or Suspense or Escrow Account | B51: 0.04 | C51: 38052
A52: Sub-Total(B)(4) | B52: 7.21 | C52: 6521912
A53: Public (B=B1+B2+B3+B4) | B53: 26.86 | C53: 24298784
A54: (C) Non Promoter-Non Public | B54: 0
A55: C1) Custodian/DR Holder | B55: 0
A56: Sub-Total(C)(1) | B56: 0
A57: C2) Employee Benefit Trust | B57: 0
A58: Sub-Total(C)(2) | B58: 0
A59: Non Promoter-Non Public (C= C1+C2) | B59: 0
A60: GRAND TOTAL | B60: 100.01 | C60: 90490055

Sheet Standalone Quarterly Result
C1: Standalone Quarterly Result
C2: Quarter ended | E2: Half Year ended | G2: Years | J2: %Change
B3: Particulars | C3: 45992 | D3: 45901 | E3: 45992 | F3: 45627 | G3: 45717 | H3: 45352 | J3: QTQ % | K3: HY YOY % | L3: YOY %
B4: I. REVENUE
B5: Revenue from Operations | C5: 2548 | D5: 2082 | E5: 4236 | F5: 3400 | G5: 7540 | H5: 6069 | J5: =C5/D5-1 -> 0.22382325 | K5: =E5/F5-1 -> 0.24588235 | L5: =G5/H5-1 -> 0.2423793
B6: Other Income | C6: 25 | D6: 29 | E6: 58 | F6: 54 | G6: 70 | H6: 44 | J6: =C6/D6-1 -> -0.13793103 | K6: =E6/F6-1 -> 0.074074074 | L6: =G6/H6-1 -> 0.59090909
B7: Total Income | C7: 2573 | D7: 2111 | E7: 4294 | F7: 3454 | G7: 7610 | H7: 6113 | J7: =C7/D7-1 -> 0.21885362 | K7: =E7/F7-1 -> 0.24319629 | L7: =G7/H7-1 -> 0.24488794
B8: II. EXPENSES
B9: Consumption of Raw Materials | C9: 1116 | D9: 908 | E9: 1902 | F9: 1454 | G9: 3375 | H9: 2709 | J9: =C9/D9-1 -> 0.22907489 | K9: =E9/F9-1 -> 0.30811554 | L9: =G9/H9-1 -> 0.24584718
B10: Purchase of Traded Goods | C10: 159 | D10: 122 | E10: 244 | F10: 349 | G10: 557 | H10: 402 | J10: =C10/D10-1 -> 0.30327869 | K10: =E10/F10-1 -> -0.3008596 | L10: =G10/H10-1 -> 0.38557214
B11: Employee Cost | C11: 213 | D11: 194 | E11: 378 | F11: 275 | G11: 600 | H11: 433 | J11: =C11/D11-1 -> 0.097938144 | K11: =E11/F11-1 -> 0.37454545 | L11: =G11/H11-1 -> 0.38568129
B12: Other Expenses | C12: 384 | D12: 346 | E12: 688 | F12: 517 | G12: 1072 | H12: 1070 | J12: =C12/D12-1 -> 0.10982659 | K12: =E12/F12-1 -> 0.33075435 | L12: =G12/H12-1 -> 0.0018691589
B13: Depreciation & Amortisation | C13: 62 | D13: 60 | E13: 116 | F13: 83 | G13: 181 | H13: 143 | J13: =C13/D13-1 -> 0.033333333 | K13: =E13/F13-1 -> 0.39759036 | L13: =G13/H13-1 -> 0.26573427
B14: Finance Costs | C14: 34 | D14: 30 | E14: 58 | F14: 57 | G14: 116 | H14: 109 | J14: =C14/D14-1 -> 0.13333333 | K14: =E14/F14-1 -> 0.01754386 | L14: =G14/H14-1 -> 0.064220183
B15: Total Expenses | C15: 1968 | D15: 1660 | E15: 3386 | F15: 2735 | G15: 5901 | H15: 4866 | J15: =C15/D15-1 -> 0.18554217 | K15: =E15/F15-1 -> 0.23802559 | L15: =G15/H15-1 -> 0.21270037
B16: III. PROFIT & LOSS
B17: EBITDA | C17: 645 | D17: 492 | E17: 971 | F17: 810 | G17: 1778 | H17: 1225 | J17: =C17/D17-1 -> 0.31097561 | K17: =E17/F17-1 -> 0.19876543 | L17: =G17/H17-1 -> 0.45142857
B18: EBITDA Margin (%) | C18: 0.253 | D18: 0.236 | E18: 0.229 | F18: 0.238 | G18: 0.236 | H18: 0.202 | J18: =C18/D18-1 -> 0.072033898 | K18: =E18/F18-1 -> -0.037815126 | L18: =G18/H18-1 -> 0.16831683
B19: EBIT | C19: 583 | D19: 432 | E19: 855 | F19: 727 | G19: 1597 | H19: 1082 | J19: =C19/D19-1 -> 0.34953704 | K19: =E19/F19-1 -> 0.17606602 | L19: =G19/H19-1 -> 0.47597043
B20: Profit Before Exceptional Items & Tax | C20: 636 | D20: 490 | E20: 971 | F20: 808 | G20: 1733 | H20: 1160 | J20: =C20/D20-1 -> 0.29795918 | K20: =E20/F20-1 -> 0.20173267 | L20: =G20/H20-1 -> 0.49396552
B21: Exceptional Items | C21: 0 | D21: 0 | E21: 0 | F21: 0 | G21: 0 | H21: 0 | J21: 0 | K21: 0 | L21: 0
B22: Profit Before Tax (PBT) | C22: 636 | D22: 490 | E22: 971 | F22: 808 | G22: 1733 | H22: 1160 | J22: =C22/D22-1 -> 0.29795918 | K22: =E22/F22-1 -> 0.20173267 | L22: =G22/H22-1 -> 0.49396552
B23: Tax Expense | C23: 169 | D23: 128 | E23: 256 | F23: 210 | G23: 450 | H23: 286 | J23: 0.32 | K23: 0.219 | L23: 0.573
B24: Profit After Tax (PAT) | C24: 466 | D24: 362 | E24: 714 | F24: 597 | G24: 1282 | H24: 874 | J24: =C24/D24-1 -> 0.28729282 | K24: =E24/F24-1 -> 0.1959799 | L24: =G24/H24-1 -> 0.46681922
B25: PAT Margin (%) | C25: 0.183 | D25: 0.174 | E25: 0.169 | F25: 0.176 | G25: 0.17 | H25: 0.144 | J25: =C25/D25-1 -> 0.051724138 | K25: =E25/F25-1 -> -0.039772727 | L25: =G25/H25-1 -> 0.18055556
B26: IV. EARNINGS PER SHARE (₹)
B27: Basic EPS | C27: 49.31 | D27: 38.12 | E27: 79 | F27: 63.25 | G27: 133.65 | H27: 92.38 | J27: =C27/D27-1 -> 0.29354669 | K27: =E27/F27-1 -> 0.24901186 | L27: =G27/H27-1 -> 0.44674172
B28: Diluted EPS | C28: 49.31 | D28: 38.12 | E28: 79 | F28: 63.25 | G28: 133.65 | H28: 92.38 | J28: =C28/D28-1 -> 0.29354669 | K28: =E28/F28-1 -> 0.24901186 | L28: =G28/H28-1 -> 0.44674172
B29: V. SUPPLEMENTARY
B30: Paid-up Equity Share Capital | C30: 18 | D30: 18 | E30: 18 | F30: 18 | G30: 18 | H30: 18 | J30: =C30/D30-1 -> 0 | K30: =E30/F30-1 -> 0 | L30: =G30/H30-1 -> 0
B31: Reserves excl. Revaluation | C31: 0 | D31: 0 | E31: 0 | F31: 0 | G31: 4368 | H31: 3287 | J31: 0 | K31: 0 | L31: =G31/H31-1 -> 0.32887131

Sheet Consolidated Quarterly Result
B1: Consolidated Quarterly Result
C3: Quarter ended | E3: Half Year ended | G3: Years | J3: %Change
B4: Particulars | C4: 45992 | D4: 45901 | E4: Dec-25 | F4: Dec-24 | G4: 45717 | H4: 45352 | J4: QTQ % | K4: HY YOY % | L4: YOY %
B5: I. REVENUE
B6: Revenue from Operations
B7: Other Income
B8: Total Income
B9: II. EXPENSES
B10: Consumption of Raw Materials
B11: Purchase of Traded Goods
B12: Increase / (Decrease) in Stocks
B13: Employee Cost
B14: Other Expenses
B15: Depreciation & Amortisation
B16: Finance Costs
... B33: Reserves excl. Revaluation

Sheet Standalone Balance Sheet
B1: Standalone Balance Sheet (₹ Cr.)
B3: Particulars | C3: 45717 | D3: 45352 | F3: % Change
B4: EQUITIES AND LIABILITIES
B5: SHAREHOLDER'S FUNDS
B6: Equity Share Capital
B7: Total Share Capital
B8: Reserves and Surplus
B9: Total Reserves and Surplus
B10: Employees Stock Options
B11: Total Shareholders Funds
B12: Equity Share Application Money
B13: NON-CURRENT LIABILITIES
B14: Other Long Term Liabilities
B15: Long Term Provisions
... B43: Total Assets

Sheet Standalone Profit & Loss
B1: Standalone Profit & Loss Account (₹ Cr.)
B2: Particulars | C2: 45717 | D2: 45352 | F2: % Change
B3: INCOME
B4: Revenue From Operations [Gross] | C4: 4456 | D4: 3717 | F4: =C4/D4-1 -> 0.19881625
B5: Revenue From Operations [Net] | C5: 4456 | D5: 3717 | F5: =C5/D5-1 -> 0.19881625
B6: Total Operating Revenues | C6: 4456 | D6: 3717 | F6: =C6/D6-1 -> 0.19881625
B7: Other Income | C7: 83 | D7: 58 | F7: =C7/D7-1 -> 0.43103448
B8: Total Revenue | C8: 4540 | D8: 3775 | F8: =C8/D8-1 -> 0.20264901
B9: EXPENSES
B10: Operating And Direct Expenses | C10: 2506 | D10: 2117 | F10: =C10/D10-1 -> 0.18375059
B11: Employee Benefit Expenses | C11: 402 | D11: 318 | F11: =C11/D11-1 -> 0.26415094
B12: Finance Costs | C12: 28 | D12: 29 | F12: =C12/D12-1 -> -0.034482759
B13: Depreciation And Amortisation Expenses | C13: 92 | D13: 76 | F13: =C13/D13-1 -> 0.21052632
B14: Other Expenses | C14: 406 | D14: 406 | F14: =C14/D14-1 -> 0
B15: Total Expenses | C15: 3434 | D15: 2946 | F15: =C15/D15-1 -> 0.16564834
C17: 45717 | D17: 45352 | F17: % Change
B18: Profit/Loss Before Exceptional, ExtraOrdinary Items And Tax | C18: 1106 | D18: 829 | F18: =C18/D18-1 -> 0.33413752
B19: Profit/Loss Before Tax | C19: 1106 | D19: 829 | F19: =C19/D19-1 -> 0.33413752
B20: Tax Expenses- Continued Operations
B21: Current Tax | C21: 274 | D21: 203 | F21: =C21/D21-1 -> 0.34975369
B22: Deferred Tax | C22: 29 | D22: 30 | F22: =C22/D22-1 -> -0.033333333
B23: Total Tax Expenses | C23: 303 | D23: 233 | F23: =C23/D23-1 -> 0.30042918
B24: Profit/Loss After Tax And Before ExtraOrdinary Items | C24: 803 | D24: 596 | F24: =C24/D24-1 -> 0.34731544
B25: Profit/Loss From Continuing Operations | C25: 803 | D25: 596 | F25: =C25/D25-1 -> 0.34731544
B26: Profit/Loss For The Period | C26: 803 | D26: 596 | F26: =C26/D26-1 -> 0.34731544
B29: Other Additional Information | C29: 45717 | D29: 45352 | E29: % Change
B30: EPS
B31: Basic EPS (₹) | C31: 89.2 | D31: 66.2 | E31: =C31/D31-1 -> 0.34743202
B32: Diluted EPS (₹) | C32: 89 | D32: 66 | E32: =C32/D32-1 -> 0.34848485
B33: Dividend and %
B34: Equity Share Dividend | C34: 90 | D34: 80 | E34: =C34/D34-1 -> 0.125
B35: Equity Dividend Rate (%) | C35: 5 | D35: 4.5 | E35: =C35/D35-1 -> 0.11111111
B37: Annual | C37: 45717 | D37: 45352 | E37: 44986 | F37: 44621 | G37: 44256
B38: Sales | C38: 4456 | D38: 3717 | E38: 4162 | F38: 2528 | G38: 1584
B39: Other Income | C39: 83 | D39: 58 | E39: 55 | F39: 36 | G39: 25
B40: Total Income | C40: 4540 | D40: 3775 | E40: 4218 | F40: 2564 | G40: 1610
B41: Total Expenditure | C41: 3434 | D41: 2946 | E41: 3590 | F41: 2202 | G41: 1350
B42: EBIT | C42: 1106 | D42: 829 | E42: 627 | F42: 361 | G42: 259
B43: Interest | C43: 28 | D43: 29 | E43: 27 | F43: 8 | G43: 6
B44: Tax | C44: 274 | D44: 203 | E44: 154 | F44: 91 | G44: 64
B45: Net Profit | C45: 803 | D45: 596 | E45: 445 | F45: 261 | G45: 189
B47: Growth Rates | C47: 3Y | D47: 5Y | E47: 10Y
B48: Revenues | C48: 0.208 | D48: 0.2414 | E48: 0.1595
B49: Operating Profit | C49: 0.4213 | D49: 0.3165 | E49: 0.2102
B50: Net Profit | C50: 0.4535 | D50: 0.3035 | E50: 0.2223

Sheet Peers Comparison
C1: Solar Industries - Peer Comparison
B3: Company | C3: Business Overview | M3: Trend-Chart of 5Yr
B4: Solar Industries India Ltd | C4: Solar Industries India Ltd is one of India’s leading manufacturers of industrial explosives, initiating systems, and defence products. The company operates across mining, infrastructure, and defence sectors, with growing presence in ammunition, rockets, propellants, and aerospace systems globally.
B5: Premier Explosives Ltd | C5: Premier Explosives Ltd manufactures industrial explosives, detonators, propellants, pyrogen igniters, and defence-related products. The company primarily serves defence, space, mining, and infrastructure sectors in India.
B6: GOCL Corporation Ltd | C6: GOCL Corporation Ltd operates in explosives and energetics businesses catering to mining and infrastructure industries. The company also has significant real estate and property development exposure.
B7: Keltech Energies Ltd | C7: Keltech Energies Ltd manufactures industrial explosives, bulk emulsion explosives, mono methylamine products, and perlite products. The company mainly serves mining, infrastructure, and industrial sectors.
B9: Attribute | C9: Solar Industries | D9: Premier Explosives | E9: GOCL Corp. | F9: Keltech Energies | H9: Metric | I9: Solar Industries | J9: Premier Explosives | K9: GOCL Corp.
B10: LTP (₹) | C10: 15830 | D10: 512 | E10: 300 | F10: 4698 | H10: Debtor Days (FY25) | I10: 42 | J10: 33 | K10: 26
B11: Sales (₹ Cr.) | C11: 8951.54 | D11: 373.22 | E11: 10.41 | F11: 528.85 | H11: Inventory Days (FY25) | I11: 49 | J11: 235 | K11: 27
B12: Net Profit 12M (₹ Cr.) | C12: 1526.72 | D12: 42.93 | E12: 1469.97 | F12: 27.1 | H12: Days Payable (FY25) | I12: 105 | J12: 178 | K12: 66
B13: Debt (₹ Cr.) | C13: 875.59 | D13: 32.1 | E13: 166.49 | F13: 45.05 | H13: Cash Conversion Cycle (FY25) | I13: -14 | J13: 90 | K13: -13
B14: Cash (₹ Cr.) | C14: 725.48 | D14: 101.25 | E14: 49.34 | F14: 25.74 | H14: Working Capital Days (FY25) | I14: -11 | J14: -31 | K14: 969
B15: OPM % | C15: 0.2605 | D15: 0.1305 | E15: -2.7195 | F15: 0.0761 | H15: ROCE % (FY25) | I15: 0.26 | J15: 0.17 | K15: 0.07
B16: P/E Ratio | C16: Premium Valuation | D16: 58.6 | E16: 6.02 | F16: 17.3
B17: ROCE % | C17: 0.26 | D17: 0.169 | E17: 0.0702 | F17: 0.258
B18: ROE % | C18: Strong | D18: 0.122 | E18: 0.0745 | F18: 0.222
B19: EV/EBITDA | C19: Premium | D19: 35.3 | E19: 4.38 | F19: 10.3
B20: EPS (₹) | C20: Strong | D20: 7.99 | E20: 297 | F20: 271

Sheet Stock Analysis
B18: Recommendation - Solar Industries India Ltd: | I18: Financial Year | J18: Revenue (₹ Cr) | K18: PAT (₹ Cr) | L18: Revenue Change (%) | M18: PAT Change (%)
B19: BUY-Solar Industries India Ltd continues to strengthen its position as one of India’s leading defence and industrial explosives manufacturers, supported by strong execution, rising exports, and increasing participation in high-value defence projects. The company reported FY 2024-25 revenue of nearly ₹4,456 crore and net profit of around ₹803 crore, compared to ₹3,717 crore revenue and ₹596 crore profit in FY 2023-24, reflecting healthy growth in both operational performance and profitability. Its expanding defence order pipeline, improving margins, efficient working capital management, and strong return ratios indicate sustained business momentum. The company’s long-term growth outlook remains favourable due to increasing government focus on indigenous defence manufacturing, ammunition production, and export opportunities. Solar Industries is steadily moving toward higher-margin defence products, which could further improve earnings visibility in coming years. Strong quarterly growth, healthy balance sheet strength, and consistent cash generation support investor confidence. However, elevated valuations after the recent stock rally and dependence on timely execution of defence contracts remain key monitorable risks. | I19: FY 2024-25 | J19: 4456 | K19: 803 | L19: =(J19-J20)/J20 -> 0.19881625 | M19: =(K19-K20)/K20 -> 0.34731544
I20: FY 2023-24 | J20: 3717 | K20: 596 | L20: =(J20-J21)/J21 -> -0.10691975 | M20: =(K20-K21)/K21 -> 0.33932584
I21: FY 2022-23 | J21: 4162 | K21: 445 | L21: =(J21-J22)/J22 -> 0.64636076 | M21: =(K21-K22)/K22 -> 0.70498084
I22: FY 2021-22 | J22: 2528 | K22: 261 | L22: =(J22-J23)/J23 -> 0.5959596 | M22: =(K22-K23)/K23 -> 0.38095238
I23: FY 2020-21 | J23: 1584 | K23: 189 | L23: =IFERROR(J23/J24,0) -> 0 | M23: =IFERROR(K23/K24,0) -> 0

Sheet Consolidated Profit & Loss
B1: Consolidated Profit & Loss Account (Rs. Cr.)
B2: Solar Industries India Limited
B3: Particulars | C3: 44256 | D3: 44621 | E3: 44986 | F3: 45352 | G3: 45717 | I3: YoY Mar22 | J3: YoY Mar23 | K3: YoY Mar24 | L3: YoY Mar25
B4: INCOME
B5: Revenue From Operations [Gross] | C5: 2441.92 | D5: 3828.51 | E5: 6804.35 | F5: 5909.02 | G5: 7360.06 | I5: =(D5/C5)-1 -> 0.56782777 | J5: =(E5/D5)-1 -> 0.77728411 | K5: =(F5/E5)-1 -> -0.131582 | L5: =(G5/F5)-1 -> 0.24556356
B6: Revenue From Operations [Net] | C6: 2441.92 | D6: 3828.51 | E6: 6804.35 | F6: 5909.02 | G6: 7360.06 | I6: =(D6/C6)-1 -> 0.56782777 | J6: =(E6/D6)-1 -> 0.77728411 | K6: =(F6/E6)-1 -> -0.131582 | L6: =(G6/F6)-1 -> 0.24556356
B7: Other Operating Revenues | C7: 73.71 | D7: 119.1 | E7: 118.18 | F7: 160.5 | G7: 180.2 | I7: =(D7/C7)-1 -> 0.61579162 | J7: =(E7/D7)-1 -> -0.0077246012 | K7: =(F7/E7)-1 -> 0.35809782 | L7: =(G7/F7)-1 -> 0.12274143
B8: Total Operating Revenues | C8: 2515.63 | D8: 3947.61 | E8: 6922.53 | F8: 6069.52 | G8: 7540.26 | I8: =(D8/C8)-1 -> 0.56923315 | J8: =(E8/D8)-1 -> 0.75360028 | K8: =(F8/E8)-1 -> -0.12322229 | L8: =(G8/F8)-1 -> 0.2423157
B9: Other Income | C9: 21.42 | D9: 19.66 | E9: 31.52 | F9: 44.47 | G9: 70.83 | I9: =(D9/C9)-1 -> -0.0821662 | J9: =(E9/D9)-1 -> 0.60325534 | K9: =(F9/E9)-1 -> 0.41085025 | L9: =(G9/F9)-1 -> 0.59275916
B10: Total Revenue | C10: 2537.05 | D10: 3967.27 | E10: 6954.05 | F10: 6113.99 | G10: 7611.09 | I10: =(D10/C10)-1 -> 0.56373347 | J10: =(E10/D10)-1 -> 0.75285524 | K10: =(F10/E10)-1 -> -0.12080155 | L10: =(G10/F10)-1 -> 0.24486465
B11: EXPENSES
B12: Cost Of Materials Consumed | C12: 1185.08 | D12: 2065.53 | E12: 3819.54 | F12: 2709.97 | G12: 3375.36 | I12: =(D12/C12)-1 -> 0.74294562 | J12: =(E12/D12)-1 -> 0.84918157 | K12: =(F12/E12)-1 -> -0.29049833 | L12: =(G12/F12)-1 -> 0.24553408
B13: Purchase Of Stock-In Trade | C13: 199.37 | D13: 301.85 | E13: 560.22 | F13: 402.58 | G13: 557.44 | I13: =(D13/C13)-1 -> 0.51401916 | J13: =(E13/D13)-1 -> 0.85595494 | K13: =(F13/E13)-1 -> -0.28138945 | L13: =(G13/F13)-1 -> 0.38466889
B14: Changes In Inventories Of FG, WIP And Stock-In Trade | C14: -37.68 | D14: -40.05 | E14: -37.39 | F14: 83.62 | G14: -25.51 | I14: =(D14/C14)-1 -> 0.062898089 | J14: =(E14/D14)-1 -> -0.066416979 | K14: =(F14/E14)-1 -> -3.2364269 | L14: =(G14/F14)-1 -> -1.3050706
B15: Employee Benefit Expenses | C15: 230.64 | D15: 289.63 | E15: 352.72 | F15: 433.46 | G15: 600.07 | I15: =(D15/C15)-1 -> 0.25576656 | J15: =(E15/D15)-1 -> 0.21782964 | K15: =(F15/E15)-1 -> 0.22890678 | L15: =(G15/F15)-1 -> 0.38437226
B16: Finance Costs | C16: 45.39 | D16: 109.25 | E16: 90.38 | F16: 109.37 | G16: 116.5 | I16: =(D16/C16)-1 -> 1.4069178 | J16: =(E16/D16)-1 -> -0.17272311 | K16: =(F16/E16)-1 -> 0.21011286 | L16: =(G16/F16)-1 -> 0.065191552
B17: Depreciation And Amortisation Expenses | C17: 93.53 | D17: 583.39 | E17: 128.21 | F17: 143.38 | G17: 181.5 | I17: =(D17/C17)-1 -> 5.2374639 | J17: =(E17/D17)-1 -> -0.78023278 | K17: =(F17/E17)-1 -> 0.1183215 | L17: =(G17/F17)-1 -> 0.26586693
B18: Other Expenses | C18: 423.62 | D18: 50.25 | E18: 938.52 | F18: 1070.68 | G18: 1072.54 | I18: =(D18/C18)-1 -> -0.88137954 | J18: =(E18/D18)-1 -> 17.677015 | K18: =(F18/E18)-1 -> 0.14081746 | L18: =(G18/F18)-1 -> 0.0017372137
B19: Total Expenses | C19: 2139.95 | D19: 3359.85 | E19: 5852.2 | F19: 4953.06 | G19: 5877.9 | I19: =(D19/C19)-1 -> 0.57006005 | J19: =(E19/D19)-1 -> 0.74180395 | K19: =(F19/E19)-1 -> -0.15364137 | L19: =(G19/F19)-1 -> 0.18672094
B20: PROFITABILITY
B21: Profit/Loss Before Exceptional Items And Tax | C21: 397.1 | D21: 607.42 | E21: 1101.85 | F21: 1160.93 | G21: 1733.19 | I21: =(D21/C21)-1 -> 0.52963989 | J21: =(E21/D21)-1 -> 0.81398373 | K21: =(F21/E21)-1 -> 0.053618914 | L21: =(G21/F21)-1 -> 0.49293239
B22: Profit/Loss Before Tax | C22: 397.1 | D22: 607.42 | E22: 1101.85 | F22: 1160.93 | G22: 1733.19 | I22: =(D22/C22)-1 -> 0.52963989 | J22: =(E22/D22)-1 -> 0.81398373 | K22: =(F22/E22)-1 -> 0.053618914 | L22: =(G22/F22)-1 -> 0.49293239
B23: TAX EXPENSES
B24: Current Tax | C24: 127.5 | D24: 163.3 | E24: 312.83 | F24: 307.24 | G24: 428.05 | I24: =(D24/C24)-1 -> 0.28078431 | J24: =(E24/D24)-1 -> 0.91567667 | K24: =(F24/E24)-1 -> -0.01786913 | L24: =(G24/F24)-1 -> 0.39321052
B25: Deferred Tax | C25: -17.29 | D25: -11.7 | E25: -23.62 | F25: -19.59 | G25: 24.05 | I25: =(D25/C25)-1 -> -0.32330827 | J25: =(E25/D25)-1 -> 1.0188034 | K25: =(F25/E25)-1 -> -0.17061812 | L25: =(G25/F25)-1 -> -2.2276672
B26: Tax For Earlier Years | C26: -1.18 | D26: 0.35 | E26: 1.2 | F26: -1.6 | G26: -1.29 | I26: =(D26/C26)-1 -> -1.2966102 | J26: =(E26/D26)-1 -> 2.4285714 | K26: =(F26/E26)-1 -> -2.3333333 | L26: =(G26/F26)-1 -> -0.19375
B27: Total Tax Expenses | C27: 109.03 | D27: 151.95 | E27: 290.41 | F27: 286.05 | G27: 450.81 | I27: =(D27/C27)-1 -> 0.39365312 | J27: =(E27/D27)-1 -> 0.9112208 | K27: =(F27/E27)-1 -> -0.015013257 | L27: =(G27/F27)-1 -> 0.57598322
B28: Profit/Loss After Tax And Before ExtraOrdinary Items | C28: 288.07 | D28: 455.47 | E28: 811.44 | F28: 874.88 | G28: 1282.38 | I28: =(D28/C28)-1 -> 0.58110876 | J28: =(E28/D28)-1 -> 0.78154434 | K28: =(F28/E28)-1 -> 0.078181997 | L28: =(G28/F28)-1 -> 0.46577816
B29: Profit/Loss From Continuing Operations | C29: 288.07 | D29: 455.47 | E29: 811.44 | F29: 874.88 | G29: 1282.38 | I29: =(D29/C29)-1 -> 0.58110876 | J29: =(E29/D29)-1 -> 0.78154434 | K29: =(F29/E29)-1 -> 0.078181997 | L29: =(G29/F29)-1 -> 0.46577816
B30: Profit/Loss For The Period | C30: 288.07 | D30: 455.47 | E30: 811.44 | F30: 874.88 | G30: 1282.38 | I30: =(D30/C30)-1 -> 0.58110876 | J30: =(E30/D30)-1 -> 0.78154434 | K30: =(F30/E30)-1 -> 0.078181997 | L30: =(G30/F30)-1 -> 0.46577816
B31: Minority Interest | C31: -11.72 | D31: -14.19 | E31: -53.98 | F31: -39.3 | G31: -78.49 | I31: =(D31/C31)-1 -> 0.21075085 | J31: =(E31/D31)-1 -> 2.8040874 | K31: =(F31/E31)-1 -> -0.27195258 | L31: =(G31/F31)-1 -> 0.99720102
B32: Share Of Profit/Loss Of Associates | C32: 0 | D32: 0 | E32: -0.27 | F32: 0.35 | G32: 5.55 | I32: N/M | J32: N/M | K32: =(F32/E32)-1 -> -2.2962963 | L32: =(G32/F32)-1 -> 14.857143
B33: Consolidated Profit/Loss After MI And Associates | C33: 276.35 | D33: 441.28 | E33: 757.19 | F33: 835.93 | G33: 1209.44 | I33: =(D33/C33)-1 -> 0.59681563 | J33: =(E33/D33)-1 -> 0.71589467 | K33: =(F33/E33)-1 -> 0.10398975 | L33: =(G33/F33)-1 -> 0.44681971
B35: EARNINGS PER SHARE & DIVIDEND
B36: Basic EPS (Rs.) | C36: 31 | D36: 49 | E36: 84 | F36: 92 | G36: 134 | I36: =(D36/C36)-1 -> 0.58064516 | J36: =(E36/D36)-1 -> 0.71428571 | K36: =(F36/E36)-1 -> 0.095238095 | L36: =(G36/F36)-1 -> 0.45652174
B37: Diluted EPS (Rs.) | C37: 31 | D37: 49 | E37: 84 | F37: 92 | G37: 134 | I37: =(D37/C37)-1 -> 0.58064516 | J37: =(E37/D37)-1 -> 0.71428571 | K37: =(F37/E37)-1 -> 0.095238095 | L37: =(G37/F37)-1 -> 0.45652174
B38: Equity Share Dividend (Rs. Cr.) | C38: 54.29 | D38: 54.29 | E38: 67.87 | F38: 72.39 | G38: 76.92 | I38: =(D38/C38)-1 -> 0 | J38: =(E38/D38)-1 -> 0.25013815 | K38: =(F38/E38)-1 -> 0.066597908 | L38: =(G38/F38)-1 -> 0.062577704
B39: No. of Equity Shares | C39: 9.05 | D39: 9.05 | E39: 9.05 | F39: 9.05 | G39: 9.05
B40: Dividend Per Share | C40: =C38/C39 -> 5.998895 | D40: =D38/D39 -> 5.998895 | E40: =E38/E39 -> 7.4994475 | F40: =F38/F39 -> 7.998895 | G40: =G38/G39 -> 8.4994475

Sheet Consolidated Balance Sheet
B1: Consolidated Balance Sheet (Rs. Cr.)
B2: Solar Industries India Limited
B3: Particulars | C3: 44256 | D3: 44621 | E3: 44986 | F3: 45352 | G3: 45717 | I3: YoY Mar25
B4: EQUITIES AND LIABILITIES
B5: SHAREHOLDER'S FUNDS
B6: Equity Share Capital | C6: 18.1 | D6: 18.1 | E6: 18.1 | F6: 18.1 | G6: 18.1 | I6: =(G6/F6)-1 -> 0
B7: Total Share Capital | C7: 18.1 | D7: 18.1 | E7: 18.1 | F7: 18.1 | G7: 18.1 | I7: =(G7/F7)-1 -> 0
B8: Reserves and Surplus | C8: 1561.31 | D8: 1896.18 | E8: 2592.24 | F8: 3287.5 | G8: 4368.24 | I8: =(G8/F8)-1 -> 0.32874221
B9: Total Reserves and Surplus | C9: 1561.31 | D9: 1896.18 | E9: 2592.24 | F9: 3287.5 | G9: 4368.24 | I9: =(G9/F9)-1 -> 0.32874221
B10: Total Shareholders Funds | C10: 1579.41 | D10: 1914.28 | E10: 2610.34 | F10: 3305.6 | G10: 4386.34 | I10: =(G10/F10)-1 -> 0.32694216
B11: Minority Interest | C11: 62.69 | D11: 100.63 | E11: 140.36 | F11: 121.65 | G11: 150.28 | I11: =(G11/F11)-1 -> 0.23534731
B12: NON-CURRENT LIABILITIES
B13: Long Term Borrowings | C13: 433.21 | D13: 435.86 | E13: 472.71 | F13: 583.55 | G13: 393.88 | I13: =(G13/F13)-1 -> -0.32502785
B14: Deferred Tax Liabilities [Net] | C14: 116.42 | D14: 137.14 | E14: 158.93 | F14: 197.78 | G14: 218.99 | I14: =(G14/F14)-1 -> 0.10724037
B15: Other Long Term Liabilities | C15: 17.64 | D15: 17.51 | E15: 18.95 | F15: 23.76 | G15: 992.63 | I15: =(G15/F15)-1 -> 40.777357
B16: Long Term Provisions | C16: 0.91 | D16: 1 | E16: 2.64 | F16: 3.44 | G16: 5.32 | I16: =(G16/F16)-1 -> 0.54651163
B17: Total Non-Current Liabilities | C17: 568.18 | D17: 591.51 | E17: 653.23 | F17: 808.53 | G17: 1610.82 | I17: =(G17/F17)-1 -> 0.99228229
B18: CURRENT LIABILITIES
B19: Short Term Borrowings | C19: 194.02 | D19: 430.25 | E19: 696.52 | F19: 521.42 | G19: 545.71 | I19: =(G19/F19)-1 -> 0.046584327
B20: Trade Payables | C20: 286.08 | D20: 464.94 | E20: 488.48 | F20: 552.65 | G20: 887.13 | I20: =(G20/F20)-1 -> 0.60522935
B21: Other Current Liabilities | C21: 328.52 | D21: 211.23 | E21: 433.16 | F21: 411.87 | G21: 657.18 | I21: =(G21/F21)-1 -> 0.59560055
B22: Short Term Provisions | C22: 10.81 | D22: 11.46 | E22: 14.16 | F22: 15.48 | G22: 23.86 | I22: =(G22/F22)-1 -> 0.54134367
B23: Total Current Liabilities | C23: 819.43 | D23: 1117.88 | E23: 1632.32 | F23: 1501.42 | G23: 2113.88 | I23: =(G23/F23)-1 -> 0.4079205
B24: Total Capital And Liabilities | C24: 3029.71 | D24: 3724.3 | E24: 5036.25 | F24: 5737.2 | G24: 8261.32 | I24: =(G24/F24)-1 -> 0.43995677
B26: ASSETS
B27: NON-CURRENT ASSETS
B28: Tangible Assets | C28: 1241.48 | D28: 1441.88 | E28: 1643.05 | F28: 1956.31 | G28: 2511.96 | I28: =(G28/F28)-1 -> 0.28402963
B29: Intangible Assets | C29: 36.49 | D29: 40.96 | E29: 48.12 | F29: 41.6 | G29: 69.49 | I29: =(G29/F29)-1 -> 0.67043269
B30: Capital Work-In-Progress | C30: 282.37 | D30: 221.13 | E30: 279.4 | F30: 487.36 | G30: 703.38 | I30: =(G30/F30)-1 -> 0.44324524
B31: Fixed Assets | C31: 1570.85 | D31: 1713.21 | E31: 1973.2 | F31: 2487.7 | G31: 3288.43 | I31: =(G31/F31)-1 -> 0.32187563
B32: Non-Current Investments | C32: 0.97 | D32: 18.22 | E32: 78.51 | F32: 156.47 | G32: 147.3 | I32: =(G32/F32)-1 -> -0.058605483
B33: Deferred Tax Assets [Net] | C33: 70.29 | D33: 94.88 | E33: 127.51 | F33: 160.16 | G33: 155.78 | I33: =(G33/F33)-1 -> -0.027347652
B34: Long Term Loans And Advances | C34: 20.7 | D34: 15.8 | E34: 17.14 | F34: 32.58 | G34: 32.55 | I34: =(G34/F34)-1 -> -0.00092081031
B35: Other Non-Current Assets | C35: 131.68 | D35: 208.44 | E35: 327.88 | F35: 222.1 | G35: 400.19 | I35: =(G35/F35)-1 -> 0.80184602
B36: Total Non-Current Assets | C36: 1804.05 | D36: 2060.44 | E36: 2534.9 | F36: 3088.82 | G36: 4134.81 | I36: =(G36/F36)-1 -> 0.33863741
B37: CURRENT ASSETS
B38: Current Investments | C38: 0 | D38: 0 | E38: 20 | F38: 213.44 | G38: 528.97 | I38: =(G38/F38)-1 -> 1.4783077
B39: Inventories | C39: 440.49 | D39: 718.87 | E39: 1097.99 | F39: 846.82 | G39: 1039.98 | I39: =(G39/F39)-1 -> 0.22810042
B40: Trade Receivables | C40: 455.48 | D40: 541.1 | E40: 825.28 | F40: 844.85 | G40: 1238.58 | I40: =(G40/F40)-1 -> 0.46603539
B41: Cash And Cash Equivalents | C41: 181.2 | D41: 98.75 | E41: 260.09 | F41: 287.26 | G41: 725.48 | I41: =(G41/F41)-1 -> 1.525517
B42: Short Term Loans And Advances | C42: 4.17 | D42: 8.23 | E42: 11.76 | F42: 3.22 | G42: 2.09 | I42: =(G42/F42)-1 -> -0.35093168
B43: Other Current Assets | C43: 144.32 | D43: 296.91 | E43: 286.23 | F43: 452.79 | G43: 591.41 | I43: =(G43/F43)-1 -> 0.30614634
B44: Total Current Assets | C44: 1225.66 | D44: 1663.86 | E44: 2501.35 | F44: 2648.38 | G44: 4126.51 | I44: =(G44/F44)-1 -> 0.5581261
B45: Total Assets | C45: 3029.71 | D45: 3724.3 | E45: 5036.25 | F45: 5737.2 | G45: 8261.32 | I45: =(G45/F45)-1 -> 0.43995677
B47: CONTINGENT LIABILITIES & COMMITMENTS
B48: Contingent Liabilities | C48: 55.36 | D48: 53.19 | E48: 218.85 | F48: 190.78 | G48: 449.5 | I48: =(G48/F48)-1 -> 1.356117

Sheet Consolidated Cash Flow
B1: Consolidated Cash Flow Statement (Rs. Cr.)
B2: Solar Industries India Limited
B3: Particulars | C3: 44256 | D3: 44621 | E3: 44986 | F3: 45352 | G3: 45717 | I3: YoY Mar25
B4: A. CASH FLOW FROM OPERATING ACTIVITIES
B5: Net Profit Before Tax | C5: 397.1 | D5: 607.42 | E5: 1101.85 | F5: 1160.93 | G5: 1733.19 | I5: =(G5/F5)-1 -> 0.49293239
B6: Depreciation & Amortisation | C6: 93.53 | D6: 583.39 | E6: 128.21 | F6: 143.38 | G6: 181.5 | I6: =(G6/F6)-1 -> 0.26586693
B7: Finance Costs | C7: 45.39 | D7: 109.25 | E7: 90.38 | F7: 109.37 | G7: 116.5 | I7: =(G7/F7)-1 -> 0.065191552
B8: Interest Income | C8: -21.42 | D8: -19.66 | E8: -31.52 | F8: -44.47 | G8: -70.83 | I8: =(G8/F8)-1 -> 0.59275916
B9: Changes in Working Capital (Net) | C9: -152.68 | D9: -289.28 | E9: -412.33 | F9: 298.12 | G9: -521.55 | I9: =(G9/F9)-1 -> -2.7494633
B10: Tax Paid | C10: -109.03 | D10: -151.95 | E10: -290.41 | F10: -286.05 | G10: -450.81 | I10: =(G10/F10)-1 -> 0.57598322
B11: Net Cash From Operating Activities (A) | C11: 252.89 | D11: 839.17 | E11: 586.18 | F11: 1381.28 | G11: 988 | I11: =(G11/F11)-1 -> -0.28472142
B13: B. CASH FLOW FROM INVESTING ACTIVITIES
B14: Purchase of Fixed Assets / CAPEX | C14: -300.52 | D14: -546.75 | E14: -388.17 | F14: -659.88 | G14: -975.31 | I14: =(G14/F14)-1 -> 0.47801115
B15: Proceeds from Sale of Assets | C15: 12.3 | D15: 8.45 | E15: 15.22 | F15: 18.6 | G15: 22.15 | I15: =(G15/F15)-1 -> 0.19086022
B16: Net Investments (Purchase/Sale) | C16: -0.97 | D16: -17.25 | E16: -60.29 | F16: -78.88 | G16: 66.64 | I16: =(G16/F16)-1 -> -1.8448276
B17: Interest / Dividend Received | C17: 21.42 | D17: 19.66 | E17: 31.52 | F17: 44.47 | G17: 70.83 | I17: =(G17/F17)-1 -> 0.59275916
B18: Other Investing Activities | C18: -15.4 | D18: -22.8 | E18: -35.6 | F18: -28.9 | G18: -45.2 | I18: =(G18/F18)-1 -> 0.56401384
B19: Net Cash From Investing Activities (B) | C19: -283.17 | D19: -558.69 | E19: -437.32 | F19: -704.59 | G19: -861.09 | I19: =(G19/F19)-1 -> 0.22211499
B21: C. CASH FLOW FROM FINANCING ACTIVITIES
B22: Proceeds from Borrowings | C22: 215.3 | D22: 450.5 | E22: 345.8 | F22: 236.7 | G22: 180.4 | I22: =(G22/F22)-1 -> -0.23785382
B23: Repayment of Borrowings | C23: -178.6 | D23: -212.8 | E23: -283.4 | F23: -350.6 | G23: -346.04 | I23: =(G23/F23)-1 -> -0.013006275
B24: Interest Paid | C24: -45.39 | D24: -109.25 | E24: -90.38 | F24: -109.37 | G24: -116.5 | I24: =(G24/F24)-1 -> 0.065191552
B25: Dividends Paid | C25: -54.29 | D25: -54.29 | E25: -67.87 | F25: -72.39 | G25: -76.92 | I25: =(G25/F25)-1 -> 0.062577704
B26: Net Cash From Financing Activities (C) | C26: -62.98 | D26: 74.16 | E26: -95.85 | F26: -295.66 | G26: -358.66 | I26: =(G26/F26)-1 -> 0.21308259
B28: Net Increase / (Decrease) in Cash & Equivalents (A+B+C) | C28: -93.26 | D28: 354.64 | E28: 53.01 | F28: 381.03 | G28: -231.75 | I28: =(G28/F28)-1 -> -1.6082198
B29: Opening Cash & Cash Equivalents | C29: 274.46 | D29: 181.2 | E29: 98.75 | F29: 260.09 | G29: 287.26 | I29: =(G29/F29)-1 -> 0.10446384
B30: Closing Cash & Cash Equivalents | C30: 181.2 | D30: 98.75 | E30: 260.09 | F30: 287.26 | G30: 725.48 | I30: =(G30/F30)-1 -> 1.525517

Sheet Historical FS
B1: Historical Financial Statement
B4: Years | C4: 2021 | D4: 2022 | E4: 2023 | F4: 2024 | G4: 2025
B5: Income statement
B6: Sales | C6: ='Consolidated Profit & Loss'!C6 -> 2441.92 | D6: ='Consolidated Profit & Loss'!D6 -> 3828.51 | E6: ='Consolidated Profit & Loss'!E6 -> 6804.35 | F6: ='Consolidated Profit & Loss'!F6 -> 5909.02 | G6: ='Consolidated Profit & Loss'!G6 -> 7360.06
B7: Sales Growth | D7: =D6/C6-1 -> 0.56782777 | E7: =E6/D6-1 -> 0.77728411 | F7: =F6/E6-1 -> -0.131582 | G7: =G6/F6-1 -> 0.24556356
B9: COGS | C9: ='Consolidated Profit & Loss'!C12 -> 1185.08 | D9: ='Consolidated Profit & Loss'!D12 -> 2065.53 | E9: ='Consolidated Profit & Loss'!E12 -> 3819.54 | F9: ='Consolidated Profit & Loss'!F12 -> 2709.97 | G9: ='Consolidated Profit & Loss'!G12 -> 3375.36
B10: COGS % Sales | C10: =C9/C6 -> 0.48530664 | D10: =D9/D6 -> 0.53951276 | E10: =E9/E6 -> 0.56133797 | F10: =F9/F6 -> 0.45861581 | G10: =G9/G6 -> 0.45860496
B12: Gross Profit | C12: =C6-C9 -> 1256.84 | D12: =D6-D9 -> 1762.98 | E12: =E6-E9 -> 2984.81 | F12: =F6-F9 -> 3199.05 | G12: =G6-G9 -> 3984.7
B13: Gross Margins | C13: =C12/C6 -> 0.51469336 | D13: =D12/D6 -> 0.46048724 | E13: =E12/E6 -> 0.43866203 | F13: =F12/F6 -> 0.54138419 | G13: =G12/G6 -> 0.54139504
B15: Selling & General Expense | C15: ='Consolidated Profit & Loss'!C18 -> 423.62 | D15: ='Consolidated Profit & Loss'!D18 -> 50.25 | E15: ='Consolidated Profit & Loss'!E18 -> 938.52 | F15: ='Consolidated Profit & Loss'!F18 -> 1070.68 | G15: ='Consolidated Profit & Loss'!G18 -> 1072.54
B16: S&G Exp % Sales | C16: =C15/C6 -> 0.17347825 | D16: =D15/D6 -> 0.013125211 | E16: =E15/E6 -> 0.13792941 | F16: =F15/F6 -> 0.18119417 | G16: =G15/G6 -> 0.14572436
B18: EBITDA | C18: =Assumption!C11 -> 440.89 | D18: =Assumption!D11 -> 1161.3 | E18: =Assumption!E11 -> 1170.74 | F18: =Assumption!F11 -> 1208.71 | G18: =Assumption!G11 -> 1780.16
B19: EBITDA Margins | C19: =C18/C6 -> 0.18055055 | D19: =D18/D6 -> 0.30332949 | E19: =E18/E6 -> 0.17205758 | F19: =F18/F6 -> 0.20455338 | G19: =G18/G6 -> 0.24186759
B21: Depriciation | C21: ='Consolidated Profit & Loss'!C17 -> 93.53 | D21: ='Consolidated Profit & Loss'!D17 -> 583.39 | E21: ='Consolidated Profit & Loss'!E17 -> 128.21 | F21: ='Consolidated Profit & Loss'!F17 -> 143.38 | G21: ='Consolidated Profit & Loss'!G17 -> 181.5
B22: Depriciation % of Sales | C22: =C21/C6 -> 0.038301828 | D22: =D21/D6 -> 0.15238043 | E22: =E21/E6 -> 0.018842358 | F22: =F21/F6 -> 0.024264599 | G22: =G21/G6 -> 0.024660125
B24: EBIT | C24: =Assumption!C13 -> 347.36 | D24: =Assumption!D13 -> 577.91 | E24: =Assumption!E13 -> 1042.53 | F24: =Assumption!F13 -> 1065.33 | G24: =Assumption!G13 -> 1598.66
B25: EBIT Margin | C25: =C24/C6 -> 0.14224872 | D25: =D24/D6 -> 0.15094906 | E25: =E24/E6 -> 0.15321522 | F25: =F24/F6 -> 0.18028878 | G25: =G24/G6 -> 0.21720747
B27: Interest | C27: ='Consolidated Profit & Loss'!C16 -> 45.39 | D27: ='Consolidated Profit & Loss'!D16 -> 109.25 | E27: ='Consolidated Profit & Loss'!E16 -> 90.38 | F27: ='Consolidated Profit & Loss'!F16 -> 109.37 | G27: ='Consolidated Profit & Loss'!G16 -> 116.5
B28: Interest % of Sales | C28: =C27/C6 -> 0.018587833 | D28: =D27/D6 -> 0.028535906 | E28: =E27/E6 -> 0.013282679 | F28: =F27/F6 -> 0.018508991 | G28: =G27/G6 -> 0.015828675
B30: Other Income | C30: ='Consolidated Profit & Loss'!C9 -> 21.42 | D30: ='Consolidated Profit & Loss'!D9 -> 19.66 | E30: ='Consolidated Profit & Loss'!E9 -> 31.52 | F30: ='Consolidated Profit & Loss'!F9 -> 44.47 | G30: ='Consolidated Profit & Loss'!G9 -> 70.83
B32: Earnings Before Tax | C32: =IFERROR(C24-C27+C30,0) -> 323.39 | D32: =IFERROR(D24-D27+D30,0) -> 488.32 | E32: =IFERROR(E24-E27+E30,0) -> 983.67 | F32: =IFERROR(F24-F27+F30,0) -> 1000.43 | G32: =IFERROR(G24-G27+G30,0) -> 1552.99
B33: EBT % Sales | C33: =C32/C6 -> 0.13243268 | D33: =D32/D6 -> 0.12754832 | E33: =E32/E6 -> 0.14456487 | F33: =F32/F6 -> 0.16930557 | G33: =G32/G6 -> 0.21100236
B35: Tax | C35: ='Consolidated Profit & Loss'!C27 -> 109.03 | D35: ='Consolidated Profit & Loss'!D27 -> 151.95 | E35: ='Consolidated Profit & Loss'!E27 -> 290.41 | F35: ='Consolidated Profit & Loss'!F27 -> 286.05 | G35: ='Consolidated Profit & Loss'!G27 -> 450.81
B36: Effective Tax Rate | C36: =C35/C32 -> 0.3371471 | D36: =D35/D32 -> 0.31116891 | E36: =E35/E32 -> 0.29523112 | F36: =F35/F32 -> 0.28592705 | G36: =G35/G32 -> 0.29028519
B38: Net Profit | C38: =Assumption!C20 -> 202.64 | D38: =Assumption!D20 -> 322.18 | E38: =Assumption!E20 -> 639.28 | F38: =Assumption!F20 -> 675.08 | G38: =Assumption!G20 -> 1023.69
B39: Net Margins | C39: =C38/C6 -> 0.082983882 | D39: =D38/D6 -> 0.084152843 | E39: =E38/E6 -> 0.093951663 | F39: =F38/F6 -> 0.11424568 | G39: =G38/G6 -> 0.13908718
B41: No. of Equity Shares | C41: ='Consolidated Profit & Loss'!C39 -> 9.05 | D41: ='Consolidated Profit & Loss'!D39 -> 9.05 | E41: ='Consolidated Profit & Loss'!E39 -> 9.05 | F41: ='Consolidated Profit & Loss'!F39 -> 9.05 | G41: ='Consolidated Profit & Loss'!G39 -> 9.05
B43: Earings Per Share | C43: ='Consolidated Profit & Loss'!C37 -> 31 | D43: ='Consolidated Profit & Loss'!D37 -> 49 | E43: ='Consolidated Profit & Loss'!E37 -> 84 | F43: ='Consolidated Profit & Loss'!F37 -> 92 | G43: ='Consolidated Profit & Loss'!G37 -> 134
B44: EPS Growth % | D44: =IFERROR(D43/C43-1,0) -> 0.58064516 | E44: =IFERROR(E43/D43-1,0) -> 0.71428571 | F44: =IFERROR(F43/E43-1,0) -> 0.095238095 | G44: =IFERROR(G43/F43-1,0) -> 0.45652174
B46: Divident per Share | C46: ='Consolidated Profit & Loss'!C40 -> 5.998895 | D46: ='Consolidated Profit & Loss'!D40 -> 5.998895 | E46: ='Consolidated Profit & Loss'!E40 -> 7.4994475 | F46: ='Consolidated Profit & Loss'!F40 -> 7.998895 | G46: ='Consolidated Profit & Loss'!G40 -> 8.4994475
B47: Divident Payout Ratio | C47: =IFERROR(C46/C43,0) -> 0.19351274 | D47: =IFERROR(D46/D43,0) -> 0.12242643 | E47: =IFERROR(E46/E43,0) -> 0.089279137 | F47: =IFERROR(F46/F43,0) -> 0.086944511 | G47: =IFERROR(G46/G43,0) -> 0.063428713
B49: Retained Earnings | C49: =IFERROR(IF(C43>C46,1-C47,0),0) -> 0.80648726 | D49: =IFERROR(IF(D43>D46,1-D47,0),0) -> 0.87757357 | E49: =IFERROR(IF(E43>E46,1-E47,0),0) -> 0.91072086 | F49: =IFERROR(IF(F43>F46,1-F47,0),0) -> 0.91305549 | G49: =IFERROR(IF(G43>G46,1-G47,0),0) -> 0.93657129
B51: Balance statement | C51: =C4 -> 2021 | D51: =D4 -> 2022 | E51: =E4 -> 2023 | F51: =F4 -> 2024 | G51: =G4 -> 2025
B52: Equity Share Capital | C52: ='Consolidated Balance Sheet'!C7 -> 18.1 | D52: ='Consolidated Balance Sheet'!D7 -> 18.1 | E52: ='Consolidated Balance Sheet'!E7 -> 18.1 | F52: ='Consolidated Balance Sheet'!F7 -> 18.1 | G52: ='Consolidated Balance Sheet'!G7 -> 18.1
B53: Reserves | C53: ='Consolidated Balance Sheet'!C9 -> 1561.31 | D53: ='Consolidated Balance Sheet'!D9 -> 1896.18 | E53: ='Consolidated Balance Sheet'!E9 -> 2592.24 | F53: ='Consolidated Balance Sheet'!F9 -> 3287.5 | G53: ='Consolidated Balance Sheet'!G9 -> 4368.24
B54: Borrowings | C54: ='Consolidated Balance Sheet'!C13+'Consolidated Balance Sheet'!C19 -> 627.23 | D54: ='Consolidated Balance Sheet'!D13+'Consolidated Balance Sheet'!D19 -> 866.11 | E54: ='Consolidated Balance Sheet'!E13+'Consolidated Balance Sheet'!E19 -> 1169.23 | F54: ='Consolidated Balance Sheet'!F13+'Consolidated Balance Sheet'!F19 -> 1104.97 | G54: ='Consolidated Balance Sheet'!G13+'Consolidated Balance Sheet'!G19 -> 939.59
B55: Other Liabilities | C55: ='Consolidated Balance Sheet'!C14+'Consolidated Balance Sheet'!C15+'Consolidated Balance Sheet'!C16+'Consolidated Balance Sheet'!C20+'Consolidated Balance Sheet'!C21+'Consolidated Balance Sheet'!C22 -> 760.38 | D55: ='Consolidated Balance Sheet'!D14+'Consolidated Balance Sheet'!D15+'Consolidated Balance Sheet'!D16+'Consolidated Balance Sheet'!D20+'Consolidated Balance Sheet'!D21+'Consolidated Balance Sheet'!D22 -> 843.28 | E55: ='Consolidated Balance Sheet'!E14+'Consolidated Balance Sheet'!E15+'Consolidated Balance Sheet'!E16+'Consolidated Balance Sheet'!E20+'Consolidated Balance Sheet'!E21+'Consolidated Balance Sheet'!E22 -> 1116.32 | F55: ='Consolidated Balance Sheet'!F14+'Consolidated Balance Sheet'!F15+'Consolidated Balance Sheet'!F16+'Consolidated Balance Sheet'!F20+'Consolidated Balance Sheet'!F21+'Consolidated Balance Sheet'!F22 -> 1204.98 | G55: ='Consolidated Balance Sheet'!G14+'Consolidated Balance Sheet'!G15+'Consolidated Balance Sheet'!G16+'Consolidated Balance Sheet'!G20+'Consolidated Balance Sheet'!G21+'Consolidated Balance Sheet'!G22 -> 2785.11
B56: Total Liabilities | C56: ='Consolidated Balance Sheet'!C17+'Consolidated Balance Sheet'!C23 -> 1387.61 | D56: ='Consolidated Balance Sheet'!D17+'Consolidated Balance Sheet'!D23 -> 1709.39 | E56: ='Consolidated Balance Sheet'!E17+'Consolidated Balance Sheet'!E23 -> 2285.55 | F56: ='Consolidated Balance Sheet'!F17+'Consolidated Balance Sheet'!F23 -> 2309.95 | G56: ='Consolidated Balance Sheet'!G17+'Consolidated Balance Sheet'!G23 -> 3724.7
B58: Fixed Assets Net Block | C58: 0 | D58: 0 | E58: 0 | F58: 0 | G58: 0
B59: Capital Work in Progress | C59: 0 | D59: 0 | E59: 0 | F59: 0 | G59: 0
B60: Investments | C60: 0 | D60: 0 | E60: 0 | F60: 0 | G60: 0
B61: Other Assets | C61: 0 | D61: 0 | E61: 0 | F61: 0 | G61: 0
B62: Total Non Current Assets | C62: =SUM(C58:C61) -> 0 | D62: =SUM(D58:D61) -> 0 | E62: =SUM(E58:E61) -> 0 | F62: =SUM(F58:F61) -> 0 | G62: =SUM(G58:G61) -> 0
B64: Receivables | C64: 0 | D64: 0 | E64: 0 | F64: 0 | G64: 0
B65: Inventory | C65: 0 | D65: 0 | E65: 0 | F65: 0 | G65: 0
B66: Cash & Bank | C66: 0 | D66: 0 | E66: 0 | F66: 0 | G66: 0
B67: Total Current Assets | C67: =IFERROR(SUM(C64:C66),0) -> 0 | D67: =IFERROR(SUM(D64:D66),0) -> 0 | E67: =IFERROR(SUM(E64:E66),0) -> 0 | F67: =IFERROR(SUM(F64:F66),0) -> 0 | G67: =IFERROR(SUM(G64:G66),0) -> 0
B69: Total Assets | C69: =IFERROR(SUM(C62+C67),0) -> 0 | D69: =IFERROR(SUM(D62+D67),0) -> 0 | E69: =IFERROR(SUM(E62+E67),0) -> 0 | F69: =IFERROR(SUM(F62+F67),0) -> 0 | G69: =IFERROR(SUM(G62+G67),0) -> 0

Sheet Fixed assets scheduled
B1: Fixed Assets Scheduled
B3: Particular | C3: 44256 | D3: 44621 | E3: 44986 | F3: 45352 | G3: 45717
B4: Beginning balance | D4: =C8 -> 1570.85 | E4: =D8 -> 1534.21 | F4: =E8 -> 1794.17 | G4: =F8 -> 2310.67
B5: Add: Net Purchases | C5: =-'Consolidated Cash Flow'!C14 -> 300.52 | D5: =-'Consolidated Cash Flow'!D14 -> 546.75 | E5: =-'Consolidated Cash Flow'!E14 -> 388.17 | F5: =-'Consolidated Cash Flow'!F14 -> 659.88 | G5: =-'Consolidated Cash Flow'!G14 -> 975.31
B6: Total Fixed Assets | C6: =C7+C8 -> 1664.38 | D6: =D4+D5 -> 2117.6 | E6: =E4+E5 -> 1922.38 | F6: =F4+F5 -> 2454.05 | G6: =G4+G5 -> 3285.98
B7: Less: Depreciation | C7: ='Consolidated Profit & Loss'!C17 -> 93.53 | D7: ='Consolidated Profit & Loss'!D17 -> 583.39 | E7: ='Consolidated Profit & Loss'!E17 -> 128.21 | F7: ='Consolidated Profit & Loss'!F17 -> 143.38 | G7: ='Consolidated Profit & Loss'!G17 -> 181.5
B8: Closing Balance(Fixed Asests ) | C8: ='Consolidated Balance Sheet'!C31 -> 1570.85 | D8: =D4+D5-D7 -> 1534.21 | E8: =E6-E7 -> 1794.17 | F8: =F6-F7 -> 2310.67 | G8: =G6-G7 -> 3104.48
B10: Net Capital expenditure | D10: =D5-D7 -> -36.64 | E10: =E5-E7 -> 259.96 | F10: =F5-F7 -> 516.5 | G10: =G5-G7 -> 793.81
B11: Net Capex / Sales % | D11: =D10/'Consolidated Profit & Loss'!D8 -> -0.0092815653 | E11: =E10/'Consolidated Profit & Loss'!E8 -> 0.037552744 | F11: =F10/'Consolidated Profit & Loss'!F8 -> 0.085097339 | G11: =G10/'Consolidated Profit & Loss'!G8 -> 0.10527621
B13: Median Capex / Sales % | D13: =MEDIAN(D11:G11) -> 0.061325042
B14: Average Capex / Sales % | D14: =AVERAGE(D11:G11) -> 0.054661182

Sheet FCFF
B1: FCFF
B3: Particulars | C3: 44256 | D3: 44621 | E3: 44986 | F3: 45352 | G3: 45717
B4: EBIT | C4: =Assumption!C13 -> 347.36 | D4: =Assumption!D13 -> 577.91 | E4: =Assumption!E13 -> 1042.53 | F4: =Assumption!F13 -> 1065.33 | G4: =Assumption!G13 -> 1598.66
B5: Less: Tax on EBIT | C5: =C4*25% -> 86.84 | D5: =D4*25% -> 144.4775 | E5: =E4*25% -> 260.6325 | F5: =F4*25% -> 266.3325 | G5: =G4*25% -> 399.665
B6: EBIT*(1-tax) | C6: =C4*(1-0.25) -> 260.52 | D6: =D4*(1-0.25) -> 433.4325 | E6: =E4*(1-0.25) -> 781.8975 | F6: =F4*(1-0.25) -> 798.9975 | G6: =G4*(1-0.25) -> 1198.995
B7: Less: Net capital expenditure | C7: ='Fixed assets scheduled'!C10 -> 0 | D7: ='Fixed assets scheduled'!D10 -> -36.64 | E7: ='Fixed assets scheduled'!E10 -> 259.96 | F7: ='Fixed assets scheduled'!F10 -> 516.5 | G7: ='Fixed assets scheduled'!G10 -> 793.81
B8: Less: Change in WC | C8: ='Change In Working Capital'!C8 -> 0 | D8: ='Change In Working Capital'!D8 -> 185.14 | E8: ='Change In Working Capital'!E8 -> 639.76 | F8: ='Change In Working Capital'!F8 -> -295.77 | G8: ='Change In Working Capital'!G8 -> 252.41
B9: Reinvestment | C9: =IFERROR(SUM(C7+C8),0) -> 0 | D9: =SUM(D7:D8) -> 148.5 | E9: =SUM(E7:E8) -> 899.72 | F9: =SUM(F7:F8) -> 220.73 | G9: =SUM(G7:G8) -> 1046.22
B10: Free Cah Flow to Firm (FCFF) | C10: =C6-C9 -> 260.52 | D10: =D6-D9 -> 284.9325 | E10: =E6-E9 -> -117.8225 | F10: =F6-F9 -> 578.2675 | G10: =G6-G9 -> 152.775
B12: Reinvestment Rate % | D12: =D9/D6 -> 0.3426139 | E12: =E9/E6 -> 1.1506879 | F12: =F9/F6 -> 0.27625869 | G12: =G9/G6 -> 0.87258079
B13: Medium Reinvestment Rate | C13: =IFERROR(MEDIAN(C12:G12),0) -> 0.60759734
B14: Average Reinvestment Rate | C14: =IFERROR(AVERAGE(C12:G12),0) -> 0.66053532

Sheet Change In Working Capital
B1: Change In Working Capital
B3: Particular | C3: 44256 | D3: 44621 | E3: 44986 | F3: 45352 | G3: 45717
B4: Inventory | C4: ='Consolidated Balance Sheet'!C39 -> 440.49 | D4: ='Consolidated Balance Sheet'!D39 -> 718.87 | E4: ='Consolidated Balance Sheet'!E39 -> 1097.99 | F4: ='Consolidated Balance Sheet'!F39 -> 846.82 | G4: ='Consolidated Balance Sheet'!G39 -> 1039.98
B5: Trade Receivables | C5: ='Consolidated Balance Sheet'!C40 -> 455.48 | D5: ='Consolidated Balance Sheet'!D40 -> 541.1 | E5: ='Consolidated Balance Sheet'!E40 -> 825.28 | F5: ='Consolidated Balance Sheet'!F40 -> 844.85 | G5: ='Consolidated Balance Sheet'!G40 -> 1238.58
B6: Trade Payable | C6: ='Consolidated Balance Sheet'!C20 -> 286.08 | D6: ='Consolidated Balance Sheet'!D20 -> 464.94 | E6: ='Consolidated Balance Sheet'!E20 -> 488.48 | F6: ='Consolidated Balance Sheet'!F20 -> 552.65 | G6: ='Consolidated Balance Sheet'!G20 -> 887.13
B7: Non Cash working Capital | C7: =C4+C5-C6 -> 609.89 | D7: =D4+D5-D6 -> 795.03 | E7: =E4+E5-E6 -> 1434.79 | F7: =F4+F5-F6 -> 1139.02 | G7: =G4+G5-G6 -> 1391.43
B8: Change in Working Capital | D8: =D7-C7 -> 185.14 | E8: =E7-D7 -> 639.76 | F8: =F7-E7 -> -295.77 | G8: =G7-F7 -> 252.41
B9: change in working Capital /percentage of sales | D9: =D8/'Consolidated Profit & Loss'!C6 -> 0.07581739 | E9: =E8/'Consolidated Profit & Loss'!D6 -> 0.16710417 | F9: =F8/'Consolidated Profit & Loss'!E6 -> -0.043467782 | G9: =G8/'Consolidated Profit & Loss'!F6 -> 0.042716051
B11: Median Non Cash working Capital /Sales percentage | D11: =MEDIAN(D9:G9) -> 0.05926672
B12: Average Non Cash working Capital /Sales percentage | D12: =AVERAGE(D9:G9) -> 0.060542458

Sheet Rm
B1: Total Market Return
B3: Year | C3: Market Return
B4: 2025 | C4: 0.1051 | E4: Average return | F4: =AVERAGE(C4:C29) -> 0.15149231 | G4: Market Return
B5: 2024 | C5: 0.0875 | E5: Dividend yield | F5: 0.013 | G5: Dividend Yield
B6: 2023 | C6: 0.1942 | E6: Total market return | F6: =SUM(F4:F5) -> 0.16449231
B7: 2022 | C7: 0.0432
B8: 2021 | C8: 0.2412
B9: 2020 | C9: 0.149
B10: 2019 | C10: 0.1202
B11: 2018 | C11: 0.0315
B12: 2017 | C12: 0.2865
B13: 2016 | C13: 0.0301
B14: 2015 | C14: -0.0406
B15: 2014 | C15: 0.3139
B16: 2013 | C16: 0.0676
B17: 2012 | C17: 0.277
B18: 2011 | C18: -0.2462
... B29: 2000 | C29: -0.1465

Sheet Wacc
B1: WACC Calculation
B3: Cost Of Capital
B4: As On Date: | C4: 46157
B6: Cost of equity using CAPM:
B7: Risk-free rate | C7: 0.0709 | D7: India 10-Year Government Bond Yield
B8: India default spread | C8: 0.0187 | D8: Country Default Spreads and Risk Premiums
B9: Beta | C9: =Beta!K9 -> 0.66451767
B10: Market Return | C10: =Rm!F6 -> 0.16449231
B11: Equity risk premium | C11: =C10-C7 -> 0.093592308
B12: Cost of equity | C12: =C7+(C9*C11)+C8 -> 0.15179374
B15: Cost of debt:
B16: Pre-Tax Cost of Debt | C16: =C17/C18 -> 0.12399025
B17: Finance Cost | C17: ='Consolidated Profit & Loss'!G16 -> 116.5
B18: Total Debt | C18: ='Consolidated Balance Sheet'!G13+'Consolidated Balance Sheet'!G19 -> 939.59
B20: Marginal tax rate % | C20: =Assumption!G34 -> 0.25
B21: Post-Tax Cost of Debt | C21: =C16*(1-C20) -> 0.092992688
B23: WACC Calculation :
B24: Equity Share Capital | C24: 18.2
B25: Face Value | C25: 2
B26: Shares Outstanding | C26: =C24/C25 -> 9.1
B29: Share Price (as on date) | C29: 17314
B30: Market Value of Equity | C30: =C29*C26 -> 157557.4
B32: Capital Structure Weights
B33: Total Capital | C33: =C18+C30 -> 158496.99
B35: Weight of Debt (Wd) | C35: =C18/C33 -> 0.0059281252
B36: Weight of Equity (We) | C36: =C30/C33 -> 0.99407187
B38: WACC | C38: =(C36*C12)+(C35*C21) -> 0.15144516

Sheet Beta
B1: Beta Calculation
B4: Date | D4: Nifty50_close | E4: Solarinds_close | G4: Return
D5: Close | E5: Close | G5: Nifty50 | H5: Solarinds
B6: 43922 | D6: 8253.8 | E6: 894.36
B7: 43924 | D7: 8083.8 | E7: 874.86 | G7: =(D7-D6)/D6 -> -0.020596574 | H7: =(E7-E6)/E6 -> -0.021803301 | J7: Beta 1 | K7: =SLOPE(H7:H1505,G7:G1505) -> 0.66451767 | M7: > The regression analysis shows a weak positive relationship between the stock and market returns. The R² value of 0.087 indicates that only 8.7% of stock movement is explained by market movement, while the majority of the movement is driven by company-specific factors.
B8: 43928 | D8: 8792.2 | E8: 906.32 | G8: =(D8-D7)/D7 -> 0.087632054 | H8: =(E8-E7)/E7 -> 0.035960039 | J8: Beta 2 | K8: =_xlfn.COVARIANCE.S(H6:H1505,G6:G1505)/_xlfn.VAR.S(G6:G1505) -> 0.66451767
B9: 43929 | D9: 8748.75 | E9: 886.04 | G9: =(D9-D8)/D8 -> -0.0049418803 | H9: =(E9-E8)/E8 -> -0.022376203 | J9: Beta 3 | K9: =K28 -> 0.66451767
B10: 43930 | D10: 9111.9 | E10: 901.1 | G10: =(D10-D9)/D9 -> 0.041508787 | H10: =(E10-E9)/E9 -> 0.016996975
B11: 43934 | D11: 8993.85 | E11: 894.11 | G11: =(D11-D10)/D10 -> -0.012955586 | H11: =(E11-E10)/E10 -> -0.0077571857 | J11: SUMMARY OUTPUT
B12: 43936 | D12: 8925.3 | E12: 885 | G12: =(D12-D11)/D11 -> -0.0076218749 | H12: =(E12-E11)/E11 -> -0.010188903
B13: 43937 | D13: 8992.8 | E13: 863.59 | G13: =(D13-D12)/D12 -> 0.007562771 | H13: =(E13-E12)/E12 -> -0.02419209 | J13: Regression Statistics
B14: 43938 | D14: 9266.75 | E14: 881.06 | G14: =(D14-D13)/D13 -> 0.030463259 | H14: =(E14-E13)/E13 -> 0.020229507 | J14: Multiple R | K14: 0.2951454
B15: 43941 | D15: 9261.85 | E15: 878.65 | G15: =(D15-D14)/D14 -> -0.00052877222 | H15: =(E15-E14)/E14 -> -0.0027353415 | J15: R Square | K15: 0.08711081
B16: 43942 | D16: 8981.45 | E16: 838.18 | G16: =(D16-D15)/D15 -> -0.030274729 | H16: =(E16-E15)/E15 -> -0.046059296 | J16: Adjusted R Square | K16: 0.086500997
B17: 43943 | D17: 9187.3 | E17: 872.89 | G17: =(D17-D16)/D16 -> 0.022919462 | H17: =(E17-E16)/E16 -> 0.041411153 | J17: Standard Error | K17: 0.021164339
B18: 43944 | D18: 9313.9 | E18: 855.51 | G18: =(D18-D17)/D17 -> 0.013779892 | H18: =(E18-E17)/E17 -> -0.019910871 | J18: Observations | K18: 1499
B19: 43945 | D19: 9154.4 | E19: 837.79 | G19: =(D19-D18)/D18 -> -0.017124942 | H19: =(E19-E18)/E18 -> -0.020712791
B20: 43948 | D20: 9282.3 | E20: 849.41 | G20: =(D20-D19)/D19 -> 0.013971424 | H20: =(E20-E19)/E19 -> 0.013869824 | J20: ANOVA
B21: 43949 | D21: 9380.9 | E21: 846.99 | G21: =(D21-D20)/D20 -> 0.010622367 | H21: =(E21-E20)/E20 -> -0.0028490364 | K21: df | L21: SS | M21: MS | N21: F | O21: Significance F
B22: 43950 | D22: 9553.35 | E22: 853.64 | G22: =(D22-D21)/D21 -> 0.018383098 | H22: =(E22-E21)/E21 -> 0.0078513324 | J22: Regression | K22: 1 | L22: 0.063986035 | M22: 0.063986035 | N22: 142.84853 | O22: 1.6374084e-31
B23: 43951 | D23: 9859.9 | E23: 871.96 | G23: =(D23-D22)/D22 -> 0.03208822 | H23: =(E23-E22)/E22 -> 0.021461037 | J23: Residual | K23: 1497 | L23: 0.67055008 | M23: 0.00044792924
B24: 43955 | D24: 9293.5 | E24: 862.26 | G24: =(D24-D23)/D23 -> -0.057444802 | H24: =(E24-E23)/E23 -> -0.011124364 | J24: Total | K24: 1498 | L24: 0.73453611
B25: 43956 | D25: 9205.6 | E25: 864.52 | G25: =(D25-D24)/D24 -> -0.0094582235 | H25: =(E25-E24)/E24 -> 0.0026210192
B26: 43957 | D26: 9270.9 | E26: 867.57 | G26: =(D26-D25)/D25 -> 0.0070935083 | H26: =(E26-E25)/E25 -> 0.0035279693 | K26: Coefficients | L26: Standard Error | M26: t Stat | N26: P-value | O26: Lower 95% | P26: Upper 95% | Q26: Lower 95.0% | R26: Upper 95.0%
B27: 43958 | D27: 9199.05 | E27: 848.77 | G27: =(D27-D26)/D26 -> -0.0077500566 | H27: =(E27-E26)/E26 -> -0.021669721 | J27: Intercept | K27: 0.0016335434 | L27: 0.00054829767 | M27: 2.9793003 | N27: 0.002935606 | O27: 0.00055803016 | P27: 0.0027090567 | Q27: 0.00055803016 | R27: 0.0027090567
B28: 43959 | D28: 9251.5 | E28: 846.6 | G28: =(D28-D27)/D27 -> 0.0057016757 | H28: =(E28-E27)/E27 -> -0.0025566408 | J28: X Variable 1 | K28: 0.66451767 | L28: 0.055599212 | M28: 11.951926 | N28: 1.6374084e-31 | O28: 0.55545704 | P28: 0.7735783 | Q28: 0.55545704 | R28: 0.7735783
B29: 43962 | D29: 9239.2 | E29: 862.01 | G29: =(D29-D28)/D28 -> -0.0013295141 | H29: =(E29-E28)/E28 -> 0.018202221
B30: 43963 | D30: 9196.55 | E30: 843.35 | G30: =(D30-D29)/D29 -> -0.0046162005 | H30: =(E30-E29)/E29 -> -0.021647081
B31: 43964 | D31: 9383.55 | E31: 874.37 | G31: =(D31-D30)/D30 -> 0.020333712 | H31: =(E31-E30)/E30 -> 0.036781882
B32: 43965 | D32: 9142.75 | E32: 870.68 | G32: =(D32-D31)/D31 -> -0.02566193 | H32: =(E32-E31)/E31 -> -0.0042201814
B33: 43966 | D33: 9136.85 | E33: 871.12 | G33: =(D33-D32)/D32 -> -0.00064532006 | H33: =(E33-E32)/E32 -> 0.00050535214
B34: 43969 | D34: 8823.25 | E34: 853.89 | G34: =(D34-D33)/D33 -> -0.034322551 | H34: =(E34-E33)/E33 -> -0.019779135
B35: 43970 | D35: 8879.1 | E35: 855.81 | G35: =(D35-D34)/D34 -> 0.0063298671 | H35: =(E35-E34)/E34 -> 0.0022485332
B36: 43971 | D36: 9066.55 | E36: 855.17 | G36: =(D36-D35)/D35 -> 0.021111374 | H36: =(E36-E35)/E35 -> -0.00074782954
B37: 43972 | D37: 9106.25 | E37: 877.27 | G37: =(D37-D36)/D36 -> 0.0043787328 | H37: =(E37-E36)/E36 -> 0.025842815
B38: 43973 | D38: 9039.25 | E38: 875.55 | G38: =(D38-D37)/D37 -> -0.0073575841 | H38: =(E38-E37)/E37 -> -0.0019606279
B39: 43977 | D39: 9029.05 | E39: 863.24 | G39: =(D39-D38)/D38 -> -0.0011284122 | H39: =(E39-E38)/E38 -> -0.014059734
B40: 43978 | D40: 9314.95 | E40: 861.62 | G40: =(D40-D39)/D39 -> 0.031664461 | H40: =(E40-E39)/E39 -> -0.0018766508
... B1505: 46141 | D1505: 24177.65 | E1505: 15377 | G1505: =(D1505-D1504)/D1504 -> 0.0075826086 | H1505: =(E1505-E1504)/E1504 -> 0.0047699948

Sheet Peer Comp.
B1: Peer comparison
B2: S.No. | C2: Name | D2: CMP Rs. | E2: No. Eq. Shares Cr. | F2: Debt Rs.Cr. | G2: EV Rs.Cr. | H2: NP 12M Rs.Cr. | I2: EPS 12M Rs. | J2: Sales Rs.Cr. | K2: EBIDT Ann Rs.Cr. | L2: Cash Rs.Cr.
B3: 1 | C3: Solar Industries | D3: 17314 | E3: 9.05 | F3: 1524.02 | G3: 157625.29 | H3: 1287.93 | I3: 133.65 | J3: 7611.09 | K3: =Assumption!G11 -> 1780.16 | L3: 931.52
B4: 2 | C4: Prem. Explosives | D4: 523.3 | E4: 5.38 | F4: 40.64 | G4: 2842.83 | H4: 28.73 | I4: 5.34 | J4: 419.57 | K4: 49.27 | L4: 93.15
B5: 3 | C5: GOCL Corpn. | D5: 300.5 | E5: 4.96 | F5: 1115.31 | G5: 2583.52 | H5: 157.21 | I5: 31.71 | J5: 554.65 | K5: 263.17 | L5: 22.27
B6: 4 | C6: Keltech Energies | D6: 4616.8 | E6: 0.1 | F6: 38.18 | G6: 488.2 | H6: 24.94 | I6: 249.41 | J6: 495.72 | K6: 44.26 | L6: 11.64
B7: 5 | C7: Beezaasan Exp. | D7: 228.05 | E7: 1.29 | F7: 244.18 | G7: 335.94 | H7: 13.12 | I7: 13.42 | J7: 214.99 | K7: 24.69 | L7: 204.9

Sheet Relative Valuation
B1: Relative Valuation
B3: Comparable Company Valuation
B4: Company Name | C4: Market Data | J4: Financials | O4: Valuation
C5: No. of shares | D5: Share Price | E5: Equity value | F5: Debt | G5: cash | H5: Enterprises value | J5: Revenue | K5: EBITDA | L5: Net Profit | M5: EPS | O5: EV/Revenue | P5: EV/EBITDA | Q5: P/E Ratio
B6: Solar Industries | C6: ='Peer Comp.'!E3 -> 9.05 | D6: ='Peer Comp.'!D3 -> 17314 | E6: =C6*D6 -> 156691.7 | F6: ='Peer Comp.'!F3 -> 1524.02 | G6: ='Peer Comp.'!L3 -> 931.52 | H6: =E6+F6-G6 -> 157284.2 | J6: ='Peer Comp.'!J3 -> 7611.09 | K6: ='Peer Comp.'!K3 -> 1780.16 | L6: ='Peer Comp.'!H3 -> 1287.93 | M6: ='Peer Comp.'!I3 -> 133.65 | O6: =H6/J6 -> 20.665135 | P6: =H6/K6 -> 88.353968 | Q6: =D6/M6 -> 129.54733
B7: Prem. Explosives | C7: ='Peer Comp.'!E4 -> 5.38 | D7: ='Peer Comp.'!D4 -> 523.3 | E7: =C7*D7 -> 2815.354 | F7: ='Peer Comp.'!F4 -> 40.64 | G7: ='Peer Comp.'!L4 -> 93.15 | H7: =E7+F7-G7 -> 2762.844 | J7: ='Peer Comp.'!J4 -> 419.57 | K7: ='Peer Comp.'!K4 -> 49.27 | L7: ='Peer Comp.'!H4 -> 28.73 | M7: ='Peer Comp.'!I4 -> 5.34 | O7: =H7/J7 -> 6.5849417 | P7: =H7/K7 -> 56.075584 | Q7: =D7/M7 -> 97.996255
B8: GOCL Corpn. | C8: ='Peer Comp.'!E5 -> 4.96 | D8: ='Peer Comp.'!D5 -> 300.5 | E8: =C8*D8 -> 1490.48 | F8: ='Peer Comp.'!F5 -> 1115.31 | G8: ='Peer Comp.'!L5 -> 22.27 | H8: =E8+F8-G8 -> 2583.52 | J8: ='Peer Comp.'!J5 -> 554.65 | K8: ='Peer Comp.'!K5 -> 263.17 | L8: ='Peer Comp.'!H5 -> 157.21 | M8: ='Peer Comp.'!I5 -> 31.71 | O8: =H8/J8 -> 4.6579284 | P8: =H8/K8 -> 9.8169244 | Q8: =D8/M8 -> 9.4765058
B9: Keltech Energies | C9: ='Peer Comp.'!E6 -> 0.1 | D9: ='Peer Comp.'!D6 -> 4616.8 | E9: =C9*D9 -> 461.68 | F9: ='Peer Comp.'!F6 -> 38.18 | G9: ='Peer Comp.'!L6 -> 11.64 | H9: =E9+F9-G9 -> 488.22 | J9: ='Peer Comp.'!J6 -> 495.72 | K9: ='Peer Comp.'!K6 -> 44.26 | L9: ='Peer Comp.'!H6 -> 24.94 | M9: ='Peer Comp.'!I6 -> 249.41 | O9: =H9/J9 -> 0.98487049 | P9: =H9/K9 -> 11.030728 | Q9: =D9/M9 -> 18.510886
B10: Beezaasan Exp. | C10: ='Peer Comp.'!E7 -> 1.29 | D10: ='Peer Comp.'!D7 -> 228.05 | E10: =C10*D10 -> 294.1845 | F10: ='Peer Comp.'!F7 -> 244.18 | G10: ='Peer Comp.'!L7 -> 204.9 | H10: =E10+F10-G10 -> 333.4645 | J10: ='Peer Comp.'!J7 -> 214.99 | K10: ='Peer Comp.'!K7 -> 24.69 | L10: ='Peer Comp.'!H7 -> 13.12 | M10: ='Peer Comp.'!I7 -> 13.42 | O10: =H10/J10 -> 1.5510698 | P10: =H10/K10 -> 13.506055 | Q10: =D10/M10 -> 16.993294
B12: M&M Industry Comparable comps | E12: EV/Revenue | F12: EV/EBITDA | G12: P/E Ratio | M12: Average | O12: =IFERROR(AVERAGE(O6:O10),0) -> 6.888789 | P12: =IFERROR(AVERAGE(P6:P10),0) -> 35.756652 | Q12: =IFERROR(AVERAGE(Q6:Q10),0) -> 54.504853
E13: Overvalued | F13: Overvalued | G13: Overvalued | M13: median | O13: =IFERROR(MEDIAN(O6:O10),0) -> 4.6579284 | P13: =IFERROR(MEDIAN(P6:P10),0) -> 13.506055 | Q13: =IFERROR(MEDIAN(Q6:Q10),0) -> 18.510886
B14: Implied Enterprise Value | E14: =$O$13*J6 -> 35451.912 | F14: =$P$13*K6 -> 24042.939 | G14: =Q13*L6 -> 23840.725
B15: Net Debt | E15: =F6-G6 -> 592.5 | F15: =E15 -> 592.5 | G15: =F15 -> 592.5 | M15: Max | O15: =IFERROR(MAX(O6:O10),0) -> 20.665135 | P15: =IFERROR(MAX(P6:P10),0) -> 88.353968 | Q15: =IFERROR(MAX(Q6:Q10),0) -> 129.54733
B16: Implied Market Value | E16: =E14-E15 -> 34859.412 | F16: =F14-F15 -> 23450.439 | G16: =G14-G15 -> 23248.225 | M16: 75th Percentile | O16: =IFERROR(QUARTILE(O6:O10,3),0) -> 6.5849417 | P16: =IFERROR(QUARTILE(P6:P10,3),0) -> 56.075584 | Q16: =IFERROR(QUARTILE(Q6:Q10,3),0) -> 97.996255
B17: Share Outstanding | E17: =C6 -> 9.05 | F17: =E17 -> 9.05 | G17: =F17 -> 9.05
B18: Implied Value per Share | E18: =E16/E17 -> 3851.8688 | F18: =F16/F17 -> 2591.2087 | G18: =G16/G17 -> 2568.8646 | M18: 25th Percentile | O18: =IFERROR(QUARTILE(O6:O10,1),0) -> 1.5510698 | P18: =IFERROR(QUARTILE(P6:P10,1),0) -> 11.030728 | Q18: =IFERROR(QUARTILE(Q6:Q10,1),0) -> 16.993294
M19: Min. | O19: =IFERROR(MIN(O6:O10),0) -> 0.98487049 | P19: =IFERROR(MIN(P6:P10),0) -> 9.8169244 | Q19: =IFERROR(MIN(Q6:Q10),0) -> 9.4765058
H22: =L6*Q13 -> 23840.725

Sheet COC
B3: Weighted average cost of capital
B5: All Figures are in INR unless stated otherwise
B7: Peer Comp
N8: S.No. | O8: Name | P8: CMP Rs. | Q8: Mar Cap Rs.Cr. | R8: Debt Rs.Cr. | S8: Debt / Eq
H9: Debt/ | I9: Debt/ | J9: Levered/ | K9: Unlevered/ | N9: 1 | O9: Solar Industries | P9: 18116 | Q9: 163892.22 | R9: 1524.02 | S9: 0.24
B10: Name of the company | D10: Country | E10: Total Equity | F10: Total Debt | G10: Tax Rate 1 | H10: Equity | I10: Capital | J10: beta 2 | K10: beta 3 | N10: 2 | O10: Prem. Explosives | P10: 524.75 | Q10: 2815.26 | R10: 32.1 | S10: 0.12
N11: 3 | O11: GOCL Corpn. | P11: 296 | Q11: 1474.23 | R11: 166.49 | S11: 0.06
B12: Solar Industries | D12: India | E12: =P9 -> 18116 | F12: =R9 -> 1524.02 | G12: 0.25 | H12: =S9 -> 0.24 | I12: =F12/(F12+E12) -> 0.077597681 | J12: =Beta!K9 -> 0.66451767 | K12: =J12/(1+(1-G12)*H12) -> 0.56315056 | N12: 4 | O12: Keltech Energies | P12: 4643.6 | Q12: 464.36 | R12: 45.05 | S12: 0.32
B13: Prem. Explosives | D13: India | E13: =P10 -> 524.75 | F13: =R10 -> 32.1 | G13: 0.25 | H13: =S10 -> 0.12 | I13: =F13/(F13+E13) -> 0.057645686 | J13: 0.23 | K13: =J13/(1+(1-G13)*H13) -> 0.21100917 | N13: 5 | O13: Beezaasan Exp. | P13: 232.65 | Q13: 352.51 | R13: 23.31 | S13: 0.22
B14: GOCL Corpn. | D14: India | E14: =P11 -> 296 | F14: =R11 -> 166.49 | G14: 0.25 | H14: =S11 -> 0.06 | I14: =F14/(F14+E14) -> 0.35998616 | J14: 1.47 | K14: =J14/(1+(1-G14)*H14) -> 1.4066986
B15: Keltech Energies | D15: India | E15: =P12 -> 4643.6 | F15: =R12 -> 45.05 | G15: 0.25 | H15: =S12 -> 0.32 | I15: =F15/(F15+E15) -> 0.0096083094 | J15: 0.13 | K15: =J15/(1+(1-G15)*H15) -> 0.10483871
B16: Beezaasan Exp. | D16: India | E16: =P13 -> 232.65 | F16: =R13 -> 23.31 | G16: 0.25 | H16: =S13 -> 0.22 | I16: =F16/(F16+E16) -> 0.091068917 | J16: 0.86 | K16: =J16/(1+(1-G16)*H16) -> 0.73819742
F18: Average | G18: =AVERAGE(G12:G16) -> 0.25 | H18: =AVERAGE(H12:H16) -> 0.192 | I18: =AVERAGE(I12:I16) -> 0.11918135 | J18: =AVERAGE(J12:J16) -> 0.67090353 | K18: =AVERAGE(K12:K16) -> 0.60477889
F19: Median | G19: =MEDIAN(G12:G16) -> 0.25 | H19: =MEDIAN(H12:H16) -> 0.22 | I19: =MEDIAN(I12:I16) -> 0.077597681 | J19: =MEDIAN(J12:J16) -> 0.66451767 | K19: =MEDIAN(K12:K16) -> 0.56315056
B22: Cost of Debt | G22: Cost of Equity
B24: Pre-tax Cost of Debt | E24: ='Consolidated Profit & Loss'!G16/COC!R9 -> 0.076442566 | G24: Risk Free Rate | K24: =Wacc!C7 -> 0.0709
B25: Tax Rate | E25: =G19 -> 0.25 | G25: Equity Risk Premium | K25: =Wacc!C11 -> 0.093592308
B26: After Tax Cost of Debt | E26: =E24*(1-E25) -> 0.057331925 | G26: Levered Beta 4 | K26: =K35 -> 0.62029943
G27: Cost of Equity | K27: =K24+(K25*K26) -> 0.12895525
B30: Capital Structure | G30: Levered Beta
D32: Current | E32: Target | G32: Comps Median Unlevered Beta | K32: =K19 -> 0.56315056
B33: Total Debt | C33: =F12 -> 1524.02 | D33: =C33/$C$35 -> 0.077597681 | E33: =I18 -> 0.11918135 | G33: Target Debt/ Equity | K33: =E37 -> 0.13530748
B34: Market Captailizatation | C34: =E12 -> 18116 | D34: =C34/$C$35 -> 0.92240232 | E34: =E35-E33 -> 0.88081865 | G34: Tax Rate | K34: 0.25
B35: Total Capital | C35: =SUM(C33:C34) -> 19640.02 | D35: =C35/$C$35 -> 1 | E35: =D35 -> 1 | G35: Levered Beta | K35: =K32*(1+(1-K34)*K33) -> 0.62029943
B37: Debt/equity | D37: =D33/D34 -> 0.084125635 | E37: =E33/E34 -> 0.13530748
G38: Weighted Average Cost of Capital
B40: 1. Tax Rate considered as Marginal Tax Rate for the country | G40: Cost of Equity | K40: =K27 -> 0.12895525
B41: 2. Levered Beta is based on 5 year monthly data | G41: Equity Weight | K41: =E34 -> 0.88081865
B42: 3. Unlevered Beta = Levered Beta/(1+(1-Tax Rate) x Debt/Equity)
B43: 4. Levered Beta = Unlevered Beta*(1+(1-Tax Rate) x Debt/Equity) | G43: Cost of Debt | K43: =E26 -> 0.057331925
G44: Debt Weight | K44: =E33 -> 0.11918135
G46: WACC | K46: =(K40*K41)+(K43*K44) -> 0.12041909

Sheet Assumption
B1: LTIM
B2: Particulars (in RS Cr.) | C2: 44256 | D2: 44621 | E2: 44986 | F2: 45352 | G2: 45717
B3: Revenue from operations | C3: ='Consolidated Profit & Loss'!C6 -> 2441.92 | D3: ='Consolidated Profit & Loss'!D6 -> 3828.51 | E3: ='Consolidated Profit & Loss'!E6 -> 6804.35 | F3: ='Consolidated Profit & Loss'!F6 -> 5909.02 | G3: ='Consolidated Profit & Loss'!G6 -> 7360.06 | I3: Median of Revenue Growth
B4: Revenue growth in % | D4: =(D3/C3)-1 -> 0.56782777 | E4: =(E3/D3)-1 -> 0.77728411 | F4: =(F3/E3)-1 -> -0.131582 | G4: =(G3/F3)-1 -> 0.24556356 | I4: =MEDIAN(D4:G4) -> 0.40669567
B5: Less: Material cost | C5: ='Consolidated Profit & Loss'!C12 -> 1185.08 | D5: ='Consolidated Profit & Loss'!D12 -> 2065.53 | E5: ='Consolidated Profit & Loss'!E12 -> 3819.54 | F5: ='Consolidated Profit & Loss'!F12 -> 2709.97 | G5: ='Consolidated Profit & Loss'!G12 -> 3375.36
B6: Less: Employee costs | C6: ='Consolidated Profit & Loss'!C15 -> 230.64 | D6: ='Consolidated Profit & Loss'!D15 -> 289.63 | E6: ='Consolidated Profit & Loss'!E15 -> 352.72 | F6: ='Consolidated Profit & Loss'!F15 -> 433.46 | G6: ='Consolidated Profit & Loss'!G15 -> 600.07
B7: Less: Purchase Of Stock-In Trade | C7: ='Consolidated Profit & Loss'!C13 -> 199.37 | D7: ='Consolidated Profit & Loss'!D13 -> 301.85 | E7: ='Consolidated Profit & Loss'!E13 -> 560.22 | F7: ='Consolidated Profit & Loss'!F13 -> 402.58 | G7: ='Consolidated Profit & Loss'!G13 -> 557.44
B8: Less: Other Expenses | C8: ='Consolidated Profit & Loss'!C18 -> 423.62 | D8: ='Consolidated Profit & Loss'!D18 -> 50.25 | E8: ='Consolidated Profit & Loss'!E18 -> 938.52 | F8: ='Consolidated Profit & Loss'!F18 -> 1070.68 | G8: ='Consolidated Profit & Loss'!G18 -> 1072.54
B9: Less: Change in Inventories | C9: ='Consolidated Profit & Loss'!C14 -> -37.68 | D9: ='Consolidated Profit & Loss'!D14 -> -40.05 | E9: ='Consolidated Profit & Loss'!E14 -> -37.39 | F9: ='Consolidated Profit & Loss'!F14 -> 83.62 | G9: ='Consolidated Profit & Loss'!G14 -> -25.51
B10: Total Expenses | C10: =C5+C6+C7+C8+C9 -> 2001.03 | D10: =D5+D6+D7+D8+D9 -> 2667.21 | E10: =E5+E6+E7+E8+E9 -> 5633.61 | F10: =F5+F6+F7+F8+F9 -> 4700.31 | G10: =G5+G6+G7+G8+G9 -> 5579.9
B11: EBITDA | C11: =C3-C10 -> 440.89 | D11: =D3-D10 -> 1161.3 | E11: =E3-E10 -> 1170.74 | F11: =F3-F10 -> 1208.71 | G11: =G3-G10 -> 1780.16
B12: Less: Depreciation And Amortization | C12: ='Consolidated Profit & Loss'!C17 -> 93.53 | D12: ='Consolidated Profit & Loss'!D17 -> 583.39 | E12: ='Consolidated Profit & Loss'!E17 -> 128.21 | F12: ='Consolidated Profit & Loss'!F17 -> 143.38 | G12: ='Consolidated Profit & Loss'!G17 -> 181.5
B13: EBIT | C13: =C11-C12 -> 347.36 | D13: =D11-D12 -> 577.91 | E13: =E11-E12 -> 1042.53 | F13: =F11-F12 -> 1065.33 | G13: =G11-G12 -> 1598.66
B14: ADD: Non operating income/ Other Income | C14: ='Consolidated Profit & Loss'!C9 -> 21.42 | D14: ='Consolidated Profit & Loss'!D9 -> 19.66 | E14: ='Consolidated Profit & Loss'!E9 -> 31.52 | F14: ='Consolidated Profit & Loss'!F9 -> 44.47 | G14: ='Consolidated Profit & Loss'!G9 -> 70.83
B15: Less: Interest Expenses | C15: ='Consolidated Profit & Loss'!C16 -> 45.39 | D15: ='Consolidated Profit & Loss'!D16 -> 109.25 | E15: ='Consolidated Profit & Loss'!E16 -> 90.38 | F15: ='Consolidated Profit & Loss'!F16 -> 109.37 | G15: ='Consolidated Profit & Loss'!G16 -> 116.5
B16: PBT | C16: =C13+C14-C15 -> 323.39 | D16: =D13+D14-D15 -> 488.32 | E16: =E13+E14-E15 -> 983.67 | F16: =F13+F14-F15 -> 1000.43 | G16: =G13+G14-G15 -> 1552.99
B17: Less: TAX | C17: ='Consolidated Profit & Loss'!C27 -> 109.03 | D17: ='Consolidated Profit & Loss'!D27 -> 151.95 | E17: ='Consolidated Profit & Loss'!E27 -> 290.41 | F17: ='Consolidated Profit & Loss'!F27 -> 286.05 | G17: ='Consolidated Profit & Loss'!G27 -> 450.81
B18: Tax Rate | C18: =C17/C16 -> 0.3371471 | D18: =D17/D16 -> 0.31116891 | E18: =E17/E16 -> 0.29523112 | F18: =F17/F16 -> 0.28592705 | G18: =G17/G16 -> 0.29028519
B19: Less:Non Controlling Interest/Minority Interest | C19: =-'Consolidated Profit & Loss'!C31 -> 11.72 | D19: =-'Consolidated Profit & Loss'!D31 -> 14.19 | E19: =-'Consolidated Profit & Loss'!E31 -> 53.98 | F19: =-'Consolidated Profit & Loss'!F31 -> 39.3 | G19: =-'Consolidated Profit & Loss'!G31 -> 78.49
B20: Net Profit- Pat | C20: =C16-C17-C19 -> 202.64 | D20: =D16-D17-D19 -> 322.18 | E20: =E16-E17-E19 -> 639.28 | F20: =F16-F17-F19 -> 675.08 | G20: =G16-G17-G19 -> 1023.69
B22: Historical Growth
B23: Average Growth | C23: =AVERAGE(D4:G4) -> 0.36477336
B24: CAGR | C24: =(G3/C3)^(1/4)-1 -> 0.31761182 | D24: =_xlfn.RRI(4,C3,G3) -> 0.31761182 | E24: RRI
B26: Margins
B27: EBITDA | C27: =C11/C3 -> 0.18055055 | D27: =D11/D3 -> 0.30332949 | E27: =E11/E3 -> 0.17205758 | F27: =F11/F3 -> 0.20455338 | G27: =G11/G3 -> 0.24186759
B28: EBIT | C28: =C13/C3 -> 0.14224872 | D28: =D13/D3 -> 0.15094906 | E28: =E13/E3 -> 0.15321522 | F28: =F13/F3 -> 0.18028878 | G28: =G13/G3 -> 0.21720747
B29: EBT | C29: =C16/C3 -> 0.13243268 | D29: =D16/D3 -> 0.12754832 | E29: =E16/E3 -> 0.14456487 | F29: =F16/F3 -> 0.16930557 | G29: =G16/G3 -> 0.21100236
B30: Net Proftt | C30: =C20/C3 -> 0.082983882 | D30: =D20/D3 -> 0.084152843 | E30: =E20/E3 -> 0.093951663 | F30: =F20/F3 -> 0.11424568 | G30: =G20/G3 -> 0.13908718
B32: Tax Rate
B33: Effective tax rate | C33: =C17/C16 -> 0.3371471 | D33: =D17/D16 -> 0.31116891 | E33: =E17/E16 -> 0.29523112 | F33: =F17/F16 -> 0.28592705 | G33: =G17/G16 -> 0.29028519
B34: Marginal Tax rate | C34: 0.25 | D34: 0.25 | E34: 0.25 | F34: 0.25 | G34: 0.25
B36: Return On Capital
B37: EBIT*(1-T) | C37: =C13*(1-C34) -> 260.52 | D37: =D13*(1-D34) -> 433.4325 | E37: =E13*(1-E34) -> 781.8975 | F37: =F13*(1-F34) -> 798.9975 | G37: =G13*(1-G34) -> 1198.995
B38: Book Equity | C38: ='Consolidated Balance Sheet'!C10 -> 1579.41 | D38: ='Consolidated Balance Sheet'!D10 -> 1914.28 | E38: ='Consolidated Balance Sheet'!E10 -> 2610.34 | F38: ='Consolidated Balance Sheet'!F10 -> 3305.6 | G38: ='Consolidated Balance Sheet'!G10 -> 4386.34
B39: Book Debt | C39: ='Consolidated Balance Sheet'!C13+'Consolidated Balance Sheet'!C19 -> 627.23 | D39: ='Consolidated Balance Sheet'!D13+'Consolidated Balance Sheet'!D19 -> 866.11 | E39: ='Consolidated Balance Sheet'!E13+'Consolidated Balance Sheet'!E19 -> 1169.23 | F39: ='Consolidated Balance Sheet'!F13+'Consolidated Balance Sheet'!F19 -> 1104.97 | G39: ='Consolidated Balance Sheet'!G13+'Consolidated Balance Sheet'!G19 -> 939.59
B40: Cash and Cash equivalents | C40: ='Consolidated Balance Sheet'!C41 -> 181.2 | D40: ='Consolidated Balance Sheet'!D41 -> 98.75 | E40: ='Consolidated Balance Sheet'!E41 -> 260.09 | F40: ='Consolidated Balance Sheet'!F41 -> 287.26 | G40: ='Consolidated Balance Sheet'!G41 -> 725.48
B41: Capital Employed | C41: =C38+C39+C40 -> 2387.84 | D41: =D38+D39+D40 -> 2879.14 | E41: =E38+E39+E40 -> 4039.66 | F41: =F38+F39+F40 -> 4697.83 | G41: =G38+G39+G40 -> 6051.41
B43: Pre-Tax Return on capital | C43: =C13/C41 -> 0.14547038 | D43: =D13/D41 -> 0.20072313 | E43: =E13/E41 -> 0.2580737 | F43: =F13/F41 -> 0.22677066 | G43: =G13/G41 -> 0.26417975
B44: Post Tax return On capital | C44: =C37/C41 -> 0.10910279 | D44: =D37/D41 -> 0.15054235 | E44: =E37/E41 -> 0.19355527 | F44: =F37/F41 -> 0.17007799 | G44: =G37/G41 -> 0.19813481
B46: Growth In EBIT | D46: ='Fixed assets scheduled'!D13*Assumption!G44 -> 0.012150626

Sheet Forecasting
B1: Forecasting
B3: Sales Forecasting | G3: EBITDA Forecasting | L3: EPS Forecasting
B4: Year Weight | C4: Year | D4: Sales | E4: Sales Growth | G4: Year Weight | H4: Year | I4: EBITDA | J4: EBITDA Growth | L4: Year Weight | M4: Year | N4: EPS | O4: EPS Growth
B5: 1 | C5: 2021 | D5: {=TRANSPOSE('Consolidated Profit & Loss'!C6:G6)} -> 2441.92 | G5: 1 | H5: =C5 -> 2021 | I5: =Assumption!C11 -> 440.89 | L5: 1 | M5: =H5 -> 2021 | N5: {=TRANSPOSE('Consolidated Profit & Loss'!C36:G36)} -> 31
B6: =B5+1 -> 2 | C6: =C5+1 -> 2022 | D6: 3828.51 | E6: =(D6-D5)/D5 -> 0.56782777 | G6: =G5+1 -> 2 | H6: =C6 -> 2022 | I6: =Assumption!D11 -> 1161.3 | J6: =(I6-I5)/I5 -> 1.6339903 | L6: 2 | M6: =H6 -> 2022 | N6: 49 | O6: =(N6-N5)/N5 -> 0.58064516
B7: =B6+1 -> 3 | C7: =C6+1 -> 2023 | D7: 6804.35 | E7: =(D7-D6)/D6 -> 0.77728411 | G7: =G6+1 -> 3 | H7: =C7 -> 2023 | I7: =Assumption!E11 -> 1170.74 | J7: =(I7-I6)/I6 -> 0.0081288211 | L7: 3 | M7: =H7 -> 2023 | N7: 84 | O7: =(N7-N6)/N6 -> 0.71428571
B8: =B7+1 -> 4 | C8: =C7+1 -> 2024 | D8: 5909.02 | E8: =(D8-D7)/D7 -> -0.131582 | G8: =G7+1 -> 4 | H8: =C8 -> 2024 | I8: =Assumption!F11 -> 1208.71 | J8: =(I8-I7)/I7 -> 0.032432479 | L8: 4 | M8: =H8 -> 2024 | N8: 92 | O8: =(N8-N7)/N7 -> 0.095238095
B9: =B8+1 -> 5 | C9: =C8+1 -> 2025 | D9: 7360.06 | E9: =(D9-D8)/D8 -> 0.24556356 | G9: =G8+1 -> 5 | H9: =C9 -> 2025 | I9: =Assumption!G11 -> 1780.16 | J9: =(I9-I8)/I8 -> 0.47277676 | L9: 5 | M9: =H9 -> 2025 | N9: 134 | O9: =(N9-N8)/N8 -> 0.45652174
B10: =B9+1 -> 6 | C10: 2026 | D10: =FORECAST(B10,$D$5:$D$9,$B$5:$B$9) -> 8843.809 | E10: =(D10-D9)/D9 -> 0.20159469 | G10: =G9+1 -> 6 | H10: 46221 | I10: =FORECAST(G10,$I$5:$I$9,$G$5:$G$9) -> 1970.145 | J10: =(I10-I9)/I9 -> 0.10672355 | L10: 6 | M10: =H10 -> 46221 | N10: =FORECAST(L10,$N$5:$N$9,$L$5:$L$9) -> 152.7 | O10: =(N10-N9)/N9 -> 0.13955224
B11: =B10+1 -> 7 | C11: =C10+1 -> 2027 | D11: =FORECAST(B11,$D$5:$D$9,$B$5:$B$9) -> 10035.488 | E11: =(D11-D10)/D10 -> 0.13474726 | G11: =G10+1 -> 7 | H11: 46587 | I11: =FORECAST(G11,$I$5:$I$9,$G$5:$G$9) -> 2242.74 | J11: =(I11-I10)/I10 -> 0.13836291 | L11: 7 | M11: =H11 -> 46587 | N11: =FORECAST(L11,$N$5:$N$9,$L$5:$L$9) -> 177.6 | O11: =(N11-N10)/N10 -> 0.16306483
B12: =B11+1 -> 8 | C12: =C11+1 -> 2028 | D12: =FORECAST(B12,$D$5:$D$9,$B$5:$B$9) -> 11227.167 | E12: =(D12-D11)/D11 -> 0.11874649 | G12: =G11+1 -> 8 | H12: 46953 | I12: =FORECAST(G12,$I$5:$I$9,$G$5:$G$9) -> 2515.335 | J12: =(I12-I11)/I11 -> 0.12154552 | L12: 8 | M12: =H12 -> 46953 | N12: =FORECAST(L12,$N$5:$N$9,$L$5:$L$9) -> 202.5 | O12: =(N12-N11)/N11 -> 0.1402027
B13: =B12+1 -> 9 | C13: =C12+1 -> 2029 | D13: =FORECAST(B13,$D$5:$D$9,$B$5:$B$9) -> 12418.846 | E13: =(D13-D12)/D12 -> 0.10614245 | G13: =G12+1 -> 9 | H13: 47319 | I13: =FORECAST(G13,$I$5:$I$9,$G$5:$G$9) -> 2787.93 | J13: =(I13-I12)/I12 -> 0.10837324 | L13: 9 | M13: =H13 -> 47319 | N13: =FORECAST(L13,$N$5:$N$9,$L$5:$L$9) -> 227.4 | O13: =(N13-N12)/N12 -> 0.12296296
B14: =B13+1 -> 10 | C14: =C13+1 -> 2030 | D14: =FORECAST(B14,$D$5:$D$9,$B$5:$B$9) -> 13610.525 | E14: =(D14-D13)/D13 -> 0.095957306 | G14: =G13+1 -> 10 | H14: 47685 | I14: =FORECAST(G14,$I$5:$I$9,$G$5:$G$9) -> 3060.525 | J14: =(I14-I13)/I13 -> 0.097776845 | L14: 10 | M14: =H14 -> 47685 | N14: =FORECAST(L14,$N$5:$N$9,$L$5:$L$9) -> 252.3 | O14: =(N14-N13)/N13 -> 0.10949868

Sheet Growth Scenerio
B1: Growth Scenarios
B4: Scenario 1: High Growth
B5: INR Cr. | C5: LTM | D5: Y1E | E5: Y2E | F5: Y3E | G5: Y4W | H5: Y5E | I5: Y6E | J5: Y7E | K5: Y8E | L5: Y9E | M5: Y10E | N5: Average Revenue Growth | O5: =Assumption!I4 -> 0.40669567
B6: Sales | C6: ='Consolidated Profit & Loss'!G6 -> 7360.06 | D6: =C6*(1+D7) -> 10353.365 | E6: =D6*(1+E7) -> 14177.742 | F6: =E6*(1+F7) -> 18885.808 | G6: =F6*(1+G7) -> 24452.66 | H6: =G6*(1+H7) -> 30748.074 | I6: =H6*(1+I7) -> 37517.033 | J6: =I6*(1+J7) -> 44376.343 | K6: =J6*(1+K7) -> 50834.044 | ... M6: =L6*(1+M7) -> 60328.968 | N6: Risk Free Rate | O6: =Wacc!C7 -> 0.0709
B7: Sales Growth % | D7: =O5 -> 0.40669567 | E7: =D7-$O$8 -> 0.36938504 | F7: =E7-$O$8 -> 0.33207441 | G7: =F7-$O$8 -> 0.29476378 | H7: =G7-$O$8 -> 0.25745315 | I7: =H7-$O$8 -> 0.22014252 | J7: =I7-$O$8 -> 0.18283189 | K7: =J7-$O$8 -> 0.14552126 | L7: =K7-$O$8 -> 0.10821063 | M7: =L7-$O$8 -> 0.0709 | O7: =O5-O6 -> 0.33579567
N8: Growth Per Year | O8: =O7/9 -> 0.03731063
B9: Scenario 2: Average Growth
B10: INR Cr. | C10: LTM | D10: Y1E | E10: Y2E | F10: Y3E | G10: Y4W | H10: Y5E | I10: Y6E | J10: Y7E | K10: Y8E | L10: Y9E | M10: Y10E | N10: Average Revenue Growth | O10: =Assumption!C23 -> 0.36477336
B11: Sales | C11: =C6 -> 7360.06 | D11: =C11*(1+D12) -> 10044.814 | E11: =D11*(1+E12) -> 13380.905 | F11: =E11*(1+F12) -> 17388.06 | G11: =F11*(1+G12) -> 22027.466 | H11: =G11*(1+H12) -> 27185.482 | I11: =H11*(1+I12) -> 32663.639 | J11: =I11*(1+J12) -> 38179.149 | K11: =J11*(1+K12) -> 43379.348 | ... M11: =L11*(1+M12) -> 51265.473 | N11: Risk Free Rate | O11: =Wacc!C7 -> 0.0709
B12: Sales Growth % | D12: =O10 -> 0.36477336 | E12: =D12-$O$13 -> 0.33212077 | F12: =E12-$O$13 -> 0.29946817 | G12: =F12-$O$13 -> 0.26681557 | H12: =G12-$O$13 -> 0.23416298 | I12: =H12-$O$13 -> 0.20151038 | J12: =I12-$O$13 -> 0.16885779 | K12: =J12-$O$13 -> 0.13620519 | L12: =K12-$O$13 -> 0.1035526 | M12: =L12-$O$13 -> 0.0709 | O12: =O10-O11 -> 0.29387336
N13: Growth Per Year | O13: =O12/9 -> 0.032652596
B14: Scenario 3: EBIT Growth
B15: INR Cr. | C15: LTM | D15: Y1E | E15: Y2E | F15: Y3E | G15: Y4W | H15: Y5E | I15: Y6E | J15: Y7E | K15: Y8E | L15: Y9E | M15: Y10E | N15: Average Revenue Growth | O15: =Assumption!D46 -> 0.012150626
B16: Sales | C16: =C11 -> 7360.06 | D16: =C16*(1+D17) -> 7449.4893 | E16: =D16*(1+E17) -> 7491.3772 | F16: =E16*(1+F17) -> 7533.5006 | G16: =F16*(1+G17) -> 7575.8608 | H16: =G16*(1+H17) -> 7618.4593 | I16: =H16*(1+I17) -> 7661.2973 | J16: =I16*(1+J17) -> 7704.3761 | K16: =J16*(1+K17) -> 7747.6972 | ... M16: =L16*(1+M17) -> 7835.0715 | N16: Risk Free Rate | O16: =Wacc!C7 -> 0.0709
B17: Sales Growth % | D17: =O15 -> 0.012150626 | E17: =D17-(-O18) -> 0.0056229175 | F17: =E17-(-P18) -> 0.0056229175 | G17: =F17-(-Q18) -> 0.0056229175 | H17: =G17-(-R18) -> 0.0056229175 | I17: =H17-(-S18) -> 0.0056229175 | J17: =I17-(-T18) -> 0.0056229175 | K17: =J17-(-U18) -> 0.0056229175 | L17: =K17-(-V18) -> 0.0056229175 | M17: =L17-(-W18) -> 0.0056229175 | O17: =O15-O16 -> -0.058749374
N18: Growth Per Year | O18: =O17/9 -> -0.0065277082
B19: Live Scenario | C19: 2
B20: INR Cr. | C20: LTM | D20: Y1E | E20: Y2E | F20: Y3E | G20: Y4W | H20: Y5E | I20: Y6E | J20: Y7E | K20: Y8E | L20: Y9E | M20: Y10E
B21: Sales | C21: =C6 -> 7360.06 | D21: =C21*(1+D22) -> 10044.814 | E21: =D21*(1+E22) -> 13380.905 | F21: =E21*(1+F22) -> 17388.06 | G21: =F21*(1+G22) -> 22027.466 | H21: =G21*(1+H22) -> 27185.482 | I21: =H21*(1+I22) -> 32663.639 | J21: =I21*(1+J22) -> 38179.149 | K21: =J21*(1+K22) -> 43379.348 | ... M21: =L21*(1+M22) -> 51265.473
B22: Sales Growth % | D22: =CHOOSE($C$19,D7,D12,D17) -> 0.36477336 | E22: =CHOOSE($C$19,E7,E12,E17) -> 0.33212077 | F22: =CHOOSE($C$19,F7,F12,F17) -> 0.29946817 | G22: =CHOOSE($C$19,G7,G12,G17) -> 0.26681557 | H22: =CHOOSE($C$19,H7,H12,H17) -> 0.23416298 | I22: =CHOOSE($C$19,I7,I12,I17) -> 0.20151038 | J22: =CHOOSE($C$19,J7,J12,J17) -> 0.16885779 | K22: =CHOOSE($C$19,K7,K12,K17) -> 0.13620519 | ... M22: =CHOOSE($C$19,M7,M12,M17) -> 0.0709
O23: >Median of Revenue Growth
O24: Less : Risk Free Rate
O25: >Risk/ Range of 9years
O26: : Per Year Risk

Sheet DCF Valuation
B1: Valuation
D3: 1 | E3: 2 | F3: 3 | G3: 4 | H3: 5 | I3: 6 | J3: 7 | K3: 8 | L3: 9 | M3: 10
B4: INR Cr | C4: LTM | D4: Y1E | E4: Y2E | F4: Y3E | G4: Y4W | H4: Y5E | I4: Y6E | J4: Y7E | K4: Y8E | L4: Y9E | M4: Y10E | O4: Terminal Year | Q4: Terminal growth rate % | R4: 0.076
B5: Sales | C5: ='Growth Scenerio'!C21 -> 7360.06 | D5: ='Growth Scenerio'!D21 -> 10044.814 | E5: ='Growth Scenerio'!E21 -> 13380.905 | F5: ='Growth Scenerio'!F21 -> 17388.06 | G5: ='Growth Scenerio'!G21 -> 22027.466 | H5: ='Growth Scenerio'!H21 -> 27185.482 | I5: ='Growth Scenerio'!I21 -> 32663.639 | J5: ='Growth Scenerio'!J21 -> 38179.149 | ... M5: ='Growth Scenerio'!M21 -> 51265.473 | N5: Terminal Year Revenue | O5: =M5*(1+R4) -> 55161.649 | Q5: Cost of Capital % | R5: =COC!K46 -> 0.12041909
B6: Sales Growth | D6: ='Growth Scenerio'!D22 -> 0.36477336 | E6: ='Growth Scenerio'!E22 -> 0.33212077 | F6: ='Growth Scenerio'!F22 -> 0.29946817 | G6: ='Growth Scenerio'!G22 -> 0.26681557 | H6: ='Growth Scenerio'!H22 -> 0.23416298 | I6: ='Growth Scenerio'!I22 -> 0.20151038 | J6: ='Growth Scenerio'!J22 -> 0.16885779 | K6: ='Growth Scenerio'!K22 -> 0.13620519 | ... M6: ='Growth Scenerio'!M22 -> 0.0709 | N6: projected sales/revenue | O6: =R4 -> 0.076 | Q6: Terminal reinvestment rate % | R6: =R4*R5 -> 0.0091518508
B7: EBIT | D7: =D8*D5 -> 1695.3823 | E7: =E8*E5 -> 2258.4539 | F7: =F8*F5 -> 2934.789 | G7: =G8*G5 -> 3717.8364 | H7: =H8*H5 -> 4588.4161 | I7: =I8*I5 -> 5513.0295 | J7: =J8*J5 -> 6443.9475 | K7: =K8*K5 -> 7321.6466 | ... M7: =M8*M5 -> 8652.6815 | N7: EBIT | O7: =O8*O5 -> 9310.2853
B8: EBIT Margin % | D8: =AVERAGE(Assumption!$C$28:$G$28) -> 0.16878185 | E8: =AVERAGE(Assumption!$C$28:$G$28) -> 0.16878185 | F8: =AVERAGE(Assumption!$C$28:$G$28) -> 0.16878185 | G8: =AVERAGE(Assumption!$C$28:$G$28) -> 0.16878185 | H8: =AVERAGE(Assumption!$C$28:$G$28) -> 0.16878185 | I8: =AVERAGE(Assumption!$C$28:$G$28) -> 0.16878185 | J8: =AVERAGE(Assumption!$C$28:$G$28) -> 0.16878185 | K8: =AVERAGE(Assumption!$C$28:$G$28) -> 0.16878185 | ... M8: =AVERAGE(Assumption!$C$28:$G$28) -> 0.16878185 | N8: EBIT Margin | O8: =M8 -> 0.16878185 | Q8: Enterprise value = Equity Value + Minority interest
B9: Less: Tax on EBIT | D9: =D7*Assumption!C34 -> 423.84557 | E9: =E7*Assumption!D34 -> 564.61348 | F9: =F7*Assumption!E34 -> 733.69725 | G9: =G7*Assumption!F34 -> 929.4591 | H9: =H7*Assumption!$G$34 -> 1147.104 | I9: =I7*Assumption!$G$34 -> 1378.2574 | J9: =J7*Assumption!$G$34 -> 1610.9869 | K9: =K7*Assumption!$G$34 -> 1830.4117 | L9: =L7*Assumption!$G$34 -> 2019.9555 | M9: =M7*Assumption!$G$34 -> 2163.1704 | N9: Tax on EBIT | O9: =25%*O7 -> 2327.5713
B10: EBIT(1-T) | D10: =D7-D9 -> 1271.5367 | E10: =E7-E9 -> 1693.8404 | F10: =F7-F9 -> 2201.0917 | G10: =G7-G9 -> 2788.3773 | H10: =H7-H9 -> 3441.312 | I10: =I7-I9 -> 4134.7722 | J10: =J7-J9 -> 4832.9606 | K10: =K7-K9 -> 5491.235 | ... M10: =M7-M9 -> 6489.5111 | N10: EBIT(1-T) | O10: =O7-O9 -> 6982.714
B11: Less: Net Capital Expenditure | D11: =D5*'Fixed assets scheduled'!$D$13 -> 615.99863 | E11: =E5*'Fixed assets scheduled'!$D$13 -> 820.58456 | F11: =F5*'Fixed assets scheduled'!$D$13 -> 1066.3235 | G11: =G5*'Fixed assets scheduled'!$D$13 -> 1350.8352 | H11: =H5*'Fixed assets scheduled'!$D$13 -> 1667.1508 | I11: =I5*'Fixed assets scheduled'!$D$13 -> 2003.0991 | J11: =J5*'Fixed assets scheduled'!$D$13 -> 2341.3379 | K11: =K5*'Fixed assets scheduled'!$D$13 -> 2660.2403 | ... M11: =M5*'Fixed assets scheduled'!$D$13 -> 3143.8573
B12: Non Cash Working Capital | C12: ='Change In Working Capital'!G7 -> 1391.43 | D12: =D5*'Change In Working Capital'!$D$11 -> 595.32317 | E12: =E5*'Change In Working Capital'!$D$11 -> 793.04236 | F12: =F5*'Change In Working Capital'!$D$11 -> 1030.5333 | G12: =G5*'Change In Working Capital'!$D$11 -> 1305.4956 | H12: =H5*'Change In Working Capital'!$D$11 -> 1611.1944 | I12: =I5*'Change In Working Capital'!$D$11 -> 1935.8668 | J12: =J5*'Change In Working Capital'!$D$11 -> 2262.753 | K12: =K5*'Change In Working Capital'!$D$11 -> 2570.9517 | ... M12: =M5*'Change In Working Capital'!$D$11 -> 3038.3365
B13: Less: Change in Working Capital | D13: =D12-C12 -> -796.10683 | E13: =E12-D12 -> 197.71919 | F13: =F12-E12 -> 237.49094 | G13: =G12-F12 -> 274.96234 | H13: =H12-G12 -> 305.69875 | I13: =I12-H12 -> 324.6724 | J13: =J12-I12 -> 326.88618 | K13: =K12-J12 -> 308.1987 | ... M13: =M12-L12 -> 201.15609
B14: Reinvestment | D14: =D11+D13 -> -180.1082 | E14: =E11+E13 -> 1018.3038 | F14: =F11+F13 -> 1303.8145 | G14: =G11+G13 -> 1625.7976 | H14: =H11+H13 -> 1972.8496 | I14: =I11+I13 -> 2327.7715 | J14: =J11+J13 -> 2668.2241 | K14: =K11+K13 -> 2968.439 | ... M14: =M11+M13 -> 3345.0134 | O14: =O10*O16 -> 63.904757
B15: Free Cash Flow To Firm (FCFF) | D15: =D10-D14 -> 1451.6449 | E15: =E10-E14 -> 675.5367 | F15: =F10-F14 -> 897.27729 | G15: =G10-G14 -> 1162.5797 | H15: =H10-H14 -> 1468.4625 | I15: =I10-I14 -> 1807.0007 | J15: =J10-J14 -> 2164.7365 | K15: =K10-K14 -> 2522.796 | ... M15: =M10-M14 -> 3144.4978 | O15: =O10-O14 -> 6918.8092
B16: Implied Reinvestment rate % | D16: =D14/D10 -> -0.14164609 | E16: =E14/E10 -> 0.60118044 | F16: =F14/F10 -> 0.59234899 | G16: =G14/G10 -> 0.58306226 | H16: =H14/H10 -> 0.57328413 | I16: =I14/I10 -> 0.56297454 | J16: =J14/J10 -> 0.55208894 | K16: =K14/K10 -> 0.54057767 | ... M16: =M14/M10 -> 0.51544921 | O16: =R6 -> 0.0091518508
B18: Terminal Value | M18: =O15/(R5-R4) -> 155762.07
B20: Present Value Interest Factor(PVIF) | D20: =1/(1+$R$5)^1 -> 0.89252317 | E20: =1/(1+$R$5)^2 -> 0.79659761 | F20: =1/(1+$R$5)^3 -> 0.71098183 | G20: =1/(1+$R$5)^4 -> 0.63456776 | H20: =1/(1+$R$5)^5 -> 0.56636643 | I20: =1/(1+$R$5)^6 -> 0.50549516 | J20: =1/(1+$R$5)^7 -> 0.45116614 | K20: =1/(1+$R$5)^8 -> 0.40267624 | L20: =1/(1+$R$5)^9 -> 0.35939787 | M20: =1/(1+$R$5)^10 -> 0.32077093
B22: Present value of FCFF | C22: =SUM(D22:M22) -> 8982.8797 | D22: =D15*D20 -> 1295.6267 | E22: =E15*E20 -> 538.13092 | F22: =F15*F20 -> 637.94784 | G22: =G15*G20 -> 737.73561 | H22: =H15*H20 -> 831.68783 | I22: =I15*I20 -> 913.43011 | J22: =J15*J20 -> 976.65583 | K22: =K15*K20 -> 1015.87 | ... M22: =M15*M20 -> 1008.6635
B23: Present value of Terminal value | M23: =M18*M20 -> 49963.943
I24: Sensitivity: Intrinsic Value per Share
B25: Value of operating assets | C25: =C22+M23 -> 58946.823 | J25: 0.1314 | K25: 0.1414 | L25: 0.1514 | M25: 0.1614
B26: Add: Cash | C26: 725.48 | I26: 0.03 | J26: 2638 | K26: 2347 | L26: 2112 | M26: 504
B27: Less: Debt | C27: 939.59 | I27: 0.04 | J27: 2839 | K27: 2502 | L27: 2233 | M27: 520
B28: Less: Minority Interest | C28: 150.28 | I28: 0.05 | J28: 3082 | K28: 2687 | L28: 2376 | M28: 539
B29: Equity Value | C29: =C25+C26-C27-C28 -> 58582.433 | I29: 0.06 | J29: 3386 | K29: 2912 | L29: 2548 | M29: 561
I30: 0.07 | J30: 3775 | K30: 3193 | L30: 2756 | M30: 589
B31: No. of Shares outstanding (Cr) | C31: 9.1
B32: intrinsic value per share | C32: =C29/C31 -> 6437.63 | F32: Current CMP - ₹17,314
B35: Note: Live Scenario changed to Scenario 2 (Avg Growth ~36.5% CAGR) - reflects Solar Industries' defence order book growth
